Workbook

Sheet Cover
A16: TIMES-Ireland Model
A19: Document type: | B19: Base Year Template
A20: Sector(s): | B20: Residential sector (RSD)
A21: Purpose: | B21: Specify base year (2018) data and define sector structure
A23: Original developer(s): | B23: Jason Mc Guire ( MaREI, jason.mcguire@ucc.ie)
B24: Alessandro Chiodi ( E4SMA, alessandro.chiodi@e4sma.com)
B25: Maurizio Gargiulo ( E4SMA, maurizio.gargiulo@e4sma.com)
A26: Current maintainer(s): | B26: Jason Mc Guire ( MaREI, jason.mcguire@ucc.ie)
B27: Olexandr Balyk ( MaREI, olexandr.balyk@ucc.ie)
A29: Part of TIM version: | B29: 1
A30: Model repository: | B30: https://github.com/MaREI-EPMG/TIMES-Ireland-model
A31: Licence: | B31: CC BY-NC-SA 4.0 (unless specified otherwise)
B32: https://creativecommons.org/licenses/by-nc-sa/4.0/

Sheet Intro
B2: Table of contents | G2: Colour code
B3: Sheet | C3: Description | D3: Updated | E3: By | H3: Referenced data (columns and rows headers)
B4: Regions | C4: County Level ( Mulit-Region ) or National Region Model Selection | D4: 44136 | E4: Olex | H4: Own calculations (columns and rows headers)
B5: RES | C5: Sector Reference Energy System | D5: 44169 | E5: JMcG | H5: Own assumptions (columns and rows headers)
B6: Setup | C6: Used for Automatic Naming Conenvtion | D6: 44166 | E6: JMcG | H6: Energy Balance Data
B7: EnergyBalance | C7: SEAI 2018 energy balance in ktoe | D7: 43862 | E7: JMcG | H7: Filtered Data
B8: RSD_Balance | C8: Description of the existing uses of energy in the residential sector, used for BY calibration | D8: 44166 | E8: JMcG
B9: Fuel-Age Adjustment | C9: Uses CSO data and BER data, to find probablilty of BER Rating for Age of dwelling | D9: 44044 | E9: JMcG
B10: COMM | C10: TIMES commodities list for the residential sector | D10: 44136 | E10: JMcG
B11: EMIS | C11: Emission coefficients for the residential sector | D11: 44013 | E11: JMcG | G11: Units
B12: Sector_Fuels | C12: Description of the fuel sectoral technologies for the residential sector | D12: 44136 | E12: Olex | G12: Capacity | H12: 000units or PJa
B13: Archetype Drivers | C13: The Share of Energy Service Drivers and projected demands assoicated with Archetypes | D13: 44136 | E13: JMcG | G13: Consumption | H13: PJ
B14: Non-Archetype Drivers | C14: projected demands NOT assoicated with Archetypes | D14: 44105 | E14: JMcG | G14: Currency (year) | H14: 2018M€
B15: DwellingStocks | C15: Description of the residential building stocks | D15: 44105 | E15: JMcG | G15: Base year | H15: 2018
B16: RHWLP-APT | C16: Description of space heat, water heat and lighting technologies in apartments | D16: 44166 | E16: JMcG
B17: RHWLP-Ter | C17: Description of space heat, water heat and lighting technologies in terrace dwellings | D17: 44166 | E17: JMcG
B18: RHWLP-Det | C18: Description of space heat, water heat and lighting technologies in detached dwellings | D18: 44166 | E18: JMcG | G18: Assumptions
G19: Value | H19: Comment
B27: Data Sources
B28: Sheet | C28: Description | D28: Updated | E28: By | F28: Open Source
B29: ArDEM | C29: ArDEM SQL | F29: ü
B30: LEAP | C30: Irish LEAP | F30: N/A
B31: JRC_EU_TIMES | C31: European TIMES | D31: Nov-19 | E31: JMcG | F31: ü | G31: Anybody can directly and anonymously access the data, without being required to register or authenticate + Attribution 4.0 International (CC BY 4.0)
B32: PET_IE | C32: Irish TIMES 1.0 | D32: 44044 | E32: JMcG | F32: N/A
B33: BER Database | C33: https://ndber.seai.ie/pass/ber/search.aspx | D33: 43952 | E33: JMcG | F33: ü
B34: Energy Balance 2018 | C34: https://www.seai.ie/data-and-insights/seai-statistics/key-publications/national-energy-balance/ | D34: 43952 | E34: JMcG | F34: ü | G34: Eurostat has a policy of encouraging free re-use of its data, both for non-commercial and commercial purposes
B35: CSO 2016 | C35: https://www.cso.ie/en/csolatestnews/presspages/2017/census2016profile1-housinginireland/ | D35: 43983 | E35: JMcG | F35: JMcG
B36: TopTen | C36: EU Appliances Data https://storage.topten.eu/source/files/WhiteGoods_in_Europe_June15.pdf | D36: 43983 | E36: JMcG | F36: JMcG
B37: SEAI Residential | C37: https://www.seai.ie/publications/Energy-in-the-Residential-Sector-2018-Final.pdf | D37: 43983 | E37: JMcG | F37: ü | G37: Reproduction of the contents is permissible provided the source is acknowledged.
B38: SEAI Emissions | C38: https://www.seai.ie/publications/Energy-Emissions-Report-2020.pdf | D38: 43983 | E38: JMcG | F38: ü | G38: Reproduction of the contents is permissible provided the source is acknowledged.
B39: EPA | C39: https://www.epa.ie/publications/monitoring--assessment/climate-change/air-emissions/Ireland-NIR-2018.pdf(Table 3.1.1)) | D39: 43983 | E39: JMcG | F39: ü | G39: Parts of this publication may be reproduced without further permission, provided the source is acknowledged.
B40: SEAI Data | C40: https://www.seai.ie/data-and-insights/seai-statistics/conversion-factors/ | D40: 43983 | E40: JMcG | F40: ü
B41: Central Bank | C41: vol-2019-no-14-population-change-and-housing-demand-in-ireland-(conefrey-and-staunton) | D41: 44044 | E41: JMcG | F41: ü
B42: HDD Projection | C42: http://www.epa.ie/pubs/reports/research/climate/researchreport339/Research_Report_339_Part3.pdf | D42: 44044 | E42: JMcG | F42: N/A
B43: HDD Projection | C43: http://www.epa.ie/pubs/reports/research/climate/researchreport339/Research_Report_339_Part3.pdf | D43: 44044 | E43: JMcG | F43: N/A
B44: TopTen | C44: https://storage.topten.eu/source/files/Market-Monitoring-2016-EN-Topten.eu.pdf | D44: 44044 | E44: JMcG | F44: ü | G44: Citation : Anette Michel, Sophie Attali, Eric Bush. Topten 2016. Energy efficiency of White Goods in Europe: monitoring the market with sales data – Final report. ADEME, 72 pages.
B46: Verision Control
B47: Verision | C47: Description | D47: Updated | E47: By
B48: 1 | C48: JMcG continue from Alessandro Chiodi BY template in 2018 - Initial Release | D48: 44166 | E48: JMcG | G48: E4SMA referenced

Sheet Regions
C3: {=INDEX(C5:C7,$A$4)} -> IE | D3: {=INDEX(D5:D7,$A$4)} -> National | E3: {=INDEX(E5:E7,$A$4)} -> IE-CW | F3: {=INDEX(F5:F7,$A$4)} -> IE-D | G3: {=INDEX(G5:G7,$A$4)} -> IE-KE | H3: {=INDEX(H5:H7,$A$4)} -> IE-KK | I3: {=INDEX(I5:I7,$A$4)} -> IE-LS | J3: {=INDEX(J5:J7,$A$4)} -> IE-LD | ... AD3: {=INDEX(AD5:AD7,$A$4)} -> IE-MN
A4: 1
A5: Development | C5: IE | D5: National | E5: =A11 -> IE-CW | F5: =A16 -> IE-D | G5: =A19 -> IE-KE | H5: =A20 -> IE-KK | I5: =A21 -> IE-LS | J5: =A24 -> IE-LD | K5: =A25 -> IE-LH | L5: =A27 -> IE-MH | M5: =A29 -> IE-OY | N5: =A34 -> IE-WH | O5: =A35 -> IE-WX | P5: =A36 -> IE-WW | Q5: =A13 -> IE-CE | R5: =A14 -> IE-CO | S5: =A18 -> IE-KY | T5: =A23 -> IE-LK | U5: =A32 -> IE-TA | V5: =A33 -> IE-WD | W5: =A17 -> IE-G | X5: =A22 -> IE-LM | Y5: =A26 -> IE-MO | Z5: =A30 -> IE-RN | AA5: =A31 -> IE-SO | AB5: =A12 -> IE-CN | AC5: =A15 -> IE-DL | AD5: =A28 -> IE-MN
A6: Single-region | C6: =C5 -> IE | D6: ="*"&D5 -> *National | E6: ="*"&E5 -> *IE-CW | F6: ="*"&F5 -> *IE-D | G6: ="*"&G5 -> *IE-KE | H6: ="*"&H5 -> *IE-KK | I6: ="*"&I5 -> *IE-LS | J6: ="*"&J5 -> *IE-LD | K6: ="*"&K5 -> *IE-LH | ... AD6: ="*"&AD5 -> *IE-MN
A7: Multi-region | C7: ="*"&C5 -> *IE | D7: =D5 -> National | E7: =E5 -> IE-CW | F7: =F5 -> IE-D | G7: =G5 -> IE-KE | H7: =H5 -> IE-KK | I7: =I5 -> IE-LS | J7: =J5 -> IE-LD | K7: =K5 -> IE-LH | ... AD7: =AD5 -> IE-MN
A10: Code | B10: County name
A11: IE-CW | B11: Carlow
A12: IE-CN | B12: Cavan
A13: IE-CE | B13: Clare
A14: IE-CO | B14: Cork
A15: IE-DL | B15: Donegal
A16: IE-D | B16: Dublin
A17: IE-G | B17: Galway
A18: IE-KY | B18: Kerry
A19: IE-KE | B19: Kildare
A20: IE-KK | B20: Kilkenny
A21: IE-LS | B21: Laois
... A36: IE-WW | B36: Wicklow
A37: Source: https://en.wikipedia.org/wiki/ISO_3166-2:IE

Sheet SETUP
A1: Automatic Naming Convention
A2: ( * = 0PJ, ie. unused commodity in BY ) | B2: TIMES | C2: Description
B3: RSD | C3: Residential
B4: FT | C4: Fuel Tech
B5: DISTN | C5: Distribution
B6: TIMES | C6: Description
A7: * Energy Carriers
B8: =B3&"COA" -> RSDCOA | C8: =TRIM("Coal"&" to "&C3) -> Coal to Residential
A9: =IF(RSD_Balance!C10>0," ",IF(ISBLANK('EB2018'!C13)," ","*")) | B9: =B3&RSD_Balance!A10 -> RSDPEA | C9: =TRIM(RSD_Balance!B10&" to "&C3) -> Peat to Residential
A10: =IF(RSD_Balance!C11>0," ",IF(ISBLANK('EB2018'!C14)," ","*")) | B10: =B3&RSD_Balance!A11 -> RSDLPG | C10: =TRIM(RSD_Balance!B11&" to "&C3) -> LPG to Residential
A11: =IF(RSD_Balance!C12>0," ",IF(ISBLANK('EB2018'!C15)," ","*")) -> * | B11: =B3&RSD_Balance!A12 -> RSDGSL | C11: =TRIM(RSD_Balance!B12&" to "&C3) -> Gasoline to Residential
A12: =IF(RSD_Balance!C13>0," ",IF(ISBLANK('EB2018'!C16)," ","*")) | B12: =B3&RSD_Balance!A13 -> RSDKER | C12: =TRIM(RSD_Balance!B13&" to "&C3) -> Kerosene to Residential
A13: =IF(RSD_Balance!C14>0," ",IF(ISBLANK('EB2018'!C17)," ","*")) | B13: =B3&RSD_Balance!A14 -> RSDDST | C13: =TRIM(RSD_Balance!B14&" to "&C3) -> Gasoil / Diesel /DERV to Residential
A14: =IF(RSD_Balance!C15>0," ",IF(ISBLANK('EB2018'!#REF!)," ","*")) -> * | B14: =B3&RSD_Balance!A15 -> RSDHFO | C14: =TRIM(RSD_Balance!B15&" to "&C3) -> Fueloil to Residential
A15: =IF(RSD_Balance!C16>0," ",IF(ISBLANK('EB2018'!C18)," ","*")) | B15: =B3&RSD_Balance!A16 -> RSDCOK | C15: =TRIM(RSD_Balance!B16&" to "&C3) -> Petroleum Coke to Residential
A16: =IF(RSD_Balance!C17>0," ",IF(ISBLANK('EB2018'!C19)," ","*")) | B16: =B3&RSD_Balance!A17 -> RSDGAS | C16: =TRIM(RSD_Balance!B17&" to "&C3) -> Natural Gas to Residential
A17: =IF(RSD_Balance!C18>0," ",IF(ISBLANK('EB2018'!C20)," ","*")) | B17: =B3&RSD_Balance!A18 -> RSDSOL | C17: =TRIM(RSD_Balance!B18&" to "&C3) -> Solar Thermal to Residential
A18: =IF(RSD_Balance!C19>0," ",IF(ISBLANK('EB2018'!C21)," ","*")) | B18: =B3&RSD_Balance!A19 -> RSDWOO | C18: =TRIM(RSD_Balance!B19&" to "&C3) -> Biomass to Residential
A19: =IF(RSD_Balance!C20>0," ",IF(ISBLANK('EB2018'!C22)," ","*")) | B19: =B3&RSD_Balance!A20 -> RSDBGS | C19: =TRIM(RSD_Balance!B20&" to "&C3) -> Biogas to Residential
A20: =IF(RSD_Balance!C21>0," ",IF(ISBLANK('EB2018'!C23)," ","*")) | B20: =B3&RSD_Balance!A21 -> RSDBIOMUN | C20: =TRIM(RSD_Balance!B21&" to "&C3) -> Landfill Gas to Residential
A21: =IF(RSD_Balance!C22>0," ",IF(ISBLANK('EB2018'!C24)," ","*")) | B21: =B3&RSD_Balance!A22 -> RSDAHT | C21: =TRIM(RSD_Balance!B22&" to "&C3) -> Ambient Heat to Residential
B22: =B3&RSD_Balance!A23 -> RSDETH | C22: =TRIM(RSD_Balance!B23&" to "&C3) -> Ethanol to Residential
B23: =B3&RSD_Balance!A24 -> RSDBDL | C23: =TRIM(RSD_Balance!B24&" to "&C3) -> Biodiesel to Residential
B24: =B3&RSD_Balance!A25 -> RSDBIOSLU | C24: =TRIM(RSD_Balance!B25&" to "&C3) -> Non-Renewable Waste to Residential
B25: RSDSMF | C25: Solid Multi-Fuel
A26: =IF(RSD_Balance!C26>0," ",IF(ISBLANK('EB2018'!C27)," ","*")) | B26: =B3&RSD_Balance!A26 -> RSDELC | C26: =TRIM(RSD_Balance!B26&" to "&C3) -> Electricity to Residential
B27: =B3&RSD_Balance!A27 -> RSDHET | C27: =TRIM(RSD_Balance!B27&" to "&C3) -> Heat to Residential
A28: * Emissions
B29: RSDCO2 | C29: Carbon Dioxide - Combustion (RSD)
B30: RSDCH4 | C30: Methane (RSD)
B31: RSDN2O | C31: Nitrogen Oxide (RSD)
B32: RSDSO2N | C32: Sulphur Oxides (RSD)
B33: RSDPM10 | C33: Particulate Matter <10 µm (RSD)
B34: RSDPM25 | C34: Particulate Matter <2.5 µm (RSD)
A35: * Building Types
B36: Apt | C36: Apartment
B37: Att | C37: Attached
B38: Det | C38: Detached
A39: * Building Energy Rating
B40: A | C40: -200 kWh/m2/yr to 75 kWh/m2/yr
B41: B1 | C41: 76 kWh/m2/yr to 100 kWh/m2/yr
B42: B2 | C42: 101 kWh/m2/yr to 125 kWh/m2/yr
B43: B3 | C43: 126 kWh/m2/yr to 150 kWh/m2/yr
B44: C | C44: 151 kWh/m2/yr to 225 kWh/m2/yr
B45: D | C45: 226 kWh/m2/yr to 300 kWh/m2/yr
B46: E | C46: 301 kWh/m2/yr to 380 kWh/m2/yr
B47: F | C47: 381 kWh/m2/yr to 450 kWh/m2/yr
B48: G | C48: 451 kWh/m2/yr to 1500 kWh/m2/yr
A49: * Energy Services
B50: SH | C50: Space Heating
A51: * | B51: SC | C51: Space Cooling
B52: WH | C52: Water Heating
B53: LT | C53: Lighting
B54: PF | C54: Pumps & Fans
B55: RF | C55: Refrigeration
B56: CK | C56: Cooking
B57: CW | C57: Cloth Washing
B58: CD | C58: Cloth Drying
B59: DW | C59: Dish Washing
B60: OE | C60: ELC Appliances
A61: * | B61: OA | C61: Other Applications
A62: * TECHNOLOGIES
A63: * Quality
B64: X0 | C64: Existing 00
B65: X1 | C65: Existing 01
B66: X2 | C66: Existing 02
B67: N1 | C67: New 01
B68: N2 | C68: New 02
B69: N3 | C69: New 03
A70: * Space Heating Control Type
B71: -NTC- | C71: No Temp Control-
B72: -FTC- | C72: Flow Temp Control-
B73: -RTC- | C73: Room Temp Control-
B74: -ZFTC- | C74: Zoned Flow Temp Control-
B75: -ZRTC- | C75: Zoned Room Temp Control-
A76: * Space Heating Device
B77: -GHP- | C77: Electrical Ground Sourced Heat Pump
B78: -AHP- | C78: Electrical Water Sourced Heat Pump
B79: -GHHP- | C79: Gas Hybrid Heat Pump
B80: -B- | C80: Boiler
B81: -S- | C81: Stove or Open Fire
B82: -DH- | C82: District Heating
B83: -R- | C83: Electrical Resistance
A84: * Demand process type
B85: BLD | C85: Building

Sheet EB2018
A1: 2018 Units = ktoe | B1: NACE (Rev 2) | C1: Coal | D1: Bituminous Coal | E1: Anthracite + Manufactured Ovoids | F1: Coke | G1: Lignite \ Brown Coal Briquettes | H1: Peat | I1: Milled Peat | J1: Sod Peat | K1: Briquettes | L1: Oil | M1: Crude | N1: Refinery Feedstocks | O1: Refinery Gas | P1: Gasoline | Q1: Kerosene | R1: Jet Kerosene | S1: Fueloil | T1: LPG | U1: Gasoil / Diesel /DERV | V1: Petroleum Coke | W1: Naphta | X1: Bitumen | Y1: White Spirit | Z1: Lubricants | AA1: Natural Gas | AB1: Renewables | AC1: Hydro | AD1: Wind | AE1: Biomass | AF1: Renewable Waste | AG1: Landfill Gas | AH1: Biogas | AI1: Biodiesel | AJ1: Bioethanol | AK1: Solar Photovoltaic | AL1: Solar Thermal | AM1: Ambient Heat | AN1: Non-Renewable Waste | AO1: Electricity | AP1: Heat | AQ1: TOTAL
A2: Indigenous Production | C2: =SUM(D2:G2) -> 0 | D2: 0 | H2: =SUM(I2:K2) -> 815.92435 | I2: 688.22035 | J2: 127.704 | L2: =SUM(M2:Z2) -> 0 | AA2: 2751.9192 | AB2: =SUM(AC2:AM2) -> 1334.6583 | AC2: 59.691709 | AD2: 743.01992 | AE2: 248.9086 | AF2: 139.99993 | AG2: 33.531819 | AH2: 16.813133 | AI2: 31.064468 | AJ2: 2.6691993 | AK2: 1.8899881 | AL2: 13.546086 | AM2: 43.523448 | AN2: 145.4371 | AQ2: =C2+H2+L2+AA2+AB2+AN2+AO2+AP2 -> 5047.9389
A3: Imports | C3: =SUM(D3:G3) -> 903.49466 | D3: 829.5746 | E3: 61.722868 | G3: 12.197194 | H3: =SUM(I3:K3) -> 0 | L3: =SUM(M3:Z3) -> 9138.5578 | M3: 3053.4743 | N3: 16.633377 | O3: 0 | P3: 564.23641 | Q3: 369.14639 | R3: 1542.2444 | S3: 82.827949 | T3: 157.54636 | U3: 2932.6956 | V3: 166.37648 | W3: 7.5616539 | X3: 200.83222 | Y3: 1.228147 | Z3: 43.754533 | AA3: 1728.3381 | AB3: =SUM(AC3:AM3) -> 151.93356 | AE3: 24.282116 | AI3: 104.81441 | AJ3: 22.83703 | AO3: 139.45062 | AQ3: =C3+H3+L3+AA3+AB3+AN3+AO3+AP3 -> 12061.775
A4: Exports | C4: =SUM(D4:G4) -> 15.186581 | D4: 0 | E4: 14.097722 | G4: 1.0888587 | H4: =SUM(I4:K4) -> 7.033068 | K4: 7.033068 | L4: =SUM(M4:Z4) -> 1717.0625 | M4: 0 | N4: 0 | P4: 364.52222 | Q4: 21.672508 | R4: 156.2938 | S4: 986.60612 | T4: 35.289733 | U4: 102.14625 | V4: 0.0029088438 | W4: 36.297317 | X4: 5.469469 | Y4: 0.018500298 | Z4: 8.7436483 | AA4: 0 | AB4: =SUM(AC4:AM4) -> 9.4476585 | AE4: 0.4126464 | AI4: 9.0350121 | AJ4: 0 | AO4: 141.83539 | AQ4: =C4+H4+L4+AA4+AB4+AN4+AO4+AP4 -> 1890.5652
A5: Mar. Bunkers | C5: =SUM(D5:G5) -> 0 | H5: =SUM(I5:K5) -> 0 | L5: =SUM(M5:Z5) -> 172.71259 | S5: 15.730078 | U5: 156.98251 | AB5: =SUM(AC5:AM5) -> 0 | AQ5: =C5+H5+L5+AA5+AB5+AN5+AO5+AP5 -> 172.71259
A6: Stock Change | C6: =SUM(D6:G6) -> -101.25635 | D6: -101.86989 | E6: -0.80797667 | G6: 1.421516 | H6: =SUM(I6:K6) -> -122.93905 | I6: -136.53827 | J6: 0 | K6: 13.599214 | L6: =SUM(M6:Z6) -> 151.33981 | M6: 38.730965 | N6: -8.875152 | P6: -9.6980083 | Q6: 12.883202 | R6: 82.120249 | S6: 23.6376 | T6: 1.4659197 | U6: 8.3874136 | V6: 3.2040911 | W6: -0.51646779 | X6: 0 | Y6: 0 | Z6: 0 | AA6: 0 | AB6: =SUM(AC6:AM6) -> 4.4601014 | AE6: 0.26707428 | AI6: 1.7828522 | AJ6: 2.410175 | AQ6: =C6+H6+L6+AA6+AB6+AN6+AO6+AP6 -> -68.395488
A7: Primary Energy Supply (incl non-energy) | C7: =C2+C3-C4-C5+C6 -> 787.05173 | D7: =D2+D3-D4-D5+D6 -> 727.70471 | E7: =E2+E3-E4-E5+E6 -> 46.817169 | F7: =F2+F3-F4-F5+F6 -> 0 | G7: =G2+G3-G4-G5+G6 -> 12.529851 | H7: =H2+H3-H4-H5+H6 -> 685.95223 | I7: =I2+I3-I4-I5+I6 -> 551.68208 | J7: =J2+J3-J4-J5+J6 -> 127.704 | ... AP7: =AP2+AP3-AP4-AP5+AP6 -> 0 | AQ7: =C7+H7+L7+AA7+AB7+AN7+AO7+AP7 -> 14978.04
A8: Primary Energy Requirement (excl. non-energy) | C8: =C7-C27 -> 787.05173 | D8: =D7-D27 -> 727.70471 | E8: =E7-E27 -> 46.817169 | F8: =F7-F27 -> 0 | G8: =G7-G27 -> 12.529851 | H8: =H7-H27 -> 685.95223 | I8: =I7-I27 -> 551.68208 | J8: =J7-J27 -> 127.704 | ... AP8: =AP7-AP27 -> 0 | AQ8: =C8+H8+L8+AA8+AB8+AN8+AO8+AP8 -> 14746.457
A9: Transformation Input | C9: =SUM(C10:C14) -> 489.1342 | D9: =SUM(D10:D14) -> 489.1342 | E9: =SUM(E10:E14) -> 0 | F9: =SUM(F10:F14) -> 0 | G9: =SUM(G10:G14) -> 0 | H9: =SUM(H10:H14) -> 541.02658 | I9: =SUM(I10:I14) -> 541.02658 | J9: =SUM(J10:J14) -> 0 | ... AP9: =SUM(AP10:AP14) -> 0 | AQ9: =C9+H9+L9+AA9+AB9+AN9+AO9+AP9 -> 7058.1841
A10: Public Thermal Power Plants | C10: =SUM(D10:G10) -> 489.1342 | D10: 489.1342 | H10: =SUM(I10:K10) -> 467.10846 | I10: 467.10846 | J10: 0 | L10: =SUM(M10:Z10) -> 34.094789 | S10: 25.868327 | U10: 8.2264622 | AA10: 2187.6034 | AB10: =SUM(AC10:AM10) -> 205.3059 | AE10: 72.46706 | AF10: 99.307023 | AG10: 33.531819 | AN10: 90.714163 | AQ10: =C10+H10+L10+AA10+AB10+AN10+AO10+AP10 -> 3473.9609
A11: Combined Heat and Power Plants | C11: =SUM(D11:G11) -> 0 | D11: 0 | H11: =SUM(I11:K11) -> 5.8425469 | I11: 5.8425469 | L11: =SUM(M11:Z11) -> 0.63499472 | O11: 0 | S11: 0 | T11: 0.63499472 | U11: 0 | AA11: 272.96145 | AB11: =SUM(AC11:AM11) -> 10.597627 | AE11: 3.561556 | AH11: 7.0360715 | AQ11: =C11+H11+L11+AA11+AB11+AN11+AO11+AP11 -> 290.03662
A12: Pumped Storage Consumption | AO12: 42.94206 | AQ12: =C12+H12+L12+AA12+AB12+AN12+AO12+AP12 -> 42.94206
A13: Briquetting Plants | C13: =SUM(D13:G13) -> 0 | H13: =SUM(I13:K13) -> 68.075577 | I13: 68.075577 | L13: =SUM(M13:Z13) -> 0 | AB13: =SUM(AC13:AM13) -> 0 | AQ13: =C13+H13+L13+AA13+AB13+AN13+AO13+AP13 -> 68.075577
A14: Oil Refineries & other energy sector | C14: =SUM(D14:G14) -> 0 | H14: =SUM(I14:K14) -> 0 | L14: =SUM(M14:Z14) -> 3130.9919 | M14: 3092.2053 | N14: 38.786602 | AA14: 40.734585 | AB14: =SUM(AC14:AM14) -> 0 | AO14: 11.442472 | AQ14: =C14+H14+L14+AA14+AB14+AN14+AO14+AP14 -> 3183.1689
A15: Transformation Output | C15: =SUM(C16:C20) -> 0 | D15: =SUM(D16:D20) -> 0 | E15: =SUM(E16:E20) -> 0 | F15: =SUM(F16:F20) -> 0 | G15: =SUM(G16:G20) -> 0 | H15: =SUM(H16:H20) -> 64.671798 | I15: =SUM(I16:I20) -> 0 | J15: =SUM(J16:J20) -> 0 | ... AP15: =SUM(AP16:AP20) -> 0 | AQ15: =C15+H15+L15+AA15+AB15+AN15+AO15+AP15 -> 5104.8192
A16: Public Thermal Power Plants | C16: =SUM(D16:G16) -> 0 | H16: =SUM(I16:K16) -> 0 | L16: =SUM(M16:Z16) -> 0 | AB16: =SUM(AC16:AL16) -> 0 | AO16: 1667.7866 | AQ16: =C16+H16+L16+AA16+AO16+AP16 -> 1667.7866
A17: Combined Heat and Power Plants | C17: =SUM(D17:G17) -> 0 | H17: =SUM(I17:K17) -> 0 | L17: =SUM(M17:Z17) -> 0 | AB17: =SUM(AC17:AL17) -> 0 | AO17: 185.14396 | AQ17: =C17+H17+L17+AA17+AO17+AP17 -> 185.14396
A18: Pumped Storage Generation | AO18: 20.430939 | AQ18: =C18+H18+L18+AA18+AB18+AN18+AO18+AP18 -> 20.430939
A19: Briquetting Plants | H19: =SUM(I19:K19) -> 64.671798 | K19: 64.671798 | L19: =SUM(M19:Z19) -> 0 | AB19: =SUM(AC19:AL19) -> 0 | AQ19: =C19+H19+L19+AA19+AB19+AN19+AO19+AP19 -> 64.671798
A20: Oil Refineries | H20: =SUM(I20:K20) -> 0 | L20: =SUM(M20:Z20) -> 3166.7859 | O20: 90.017984 | P20: 640.5368 | Q20: 226.77459 | R20: 0 | S20: 960.95018 | T20: 64.797463 | U20: 1146.9502 | W20: 36.758644 | AB20: =SUM(AC20:AL20) -> 0 | AQ20: =C20+H20+L20+AA20+AB20+AN20+AO20+AP20 -> 3166.7859
A21: Exchanges and transfers | C21: =SUM(C22:C24) -> 22.240062 | D21: =SUM(D22:D24) -> -17.141361 | E21: =SUM(E22:E24) -> 39.381423 | F21: =SUM(F22:F24) -> 0 | G21: =SUM(G22:G24) -> 0 | H21: =SUM(I21:K21) -> 0 | I21: =SUM(I22:I24) -> 0 | J21: =SUM(J22:J24) -> 0 | K21: =SUM(K22:K24) -> 0 | L21: =SUM(M21:Z21) -> -24.684016 | M21: =SUM(M22:M24) -> 0 | N21: =SUM(N22:N24) -> 30.880435 | O21: =SUM(O22:O24) -> 0 | P21: =SUM(P22:P24) -> -31.331711 | Q21: =SUM(Q22:Q24) -> 361.9108 | R21: =SUM(R22:R24) -> -361.12225 | S21: =SUM(S22:S24) -> -0.17168421 | T21: =SUM(T22:T24) -> 0 | ... AQ21: =SUM(AQ22:AQ24) -> -2.4439548
A22: Electricity | AB22: =SUM(AC22:AM22) -> -804.60162 | AC22: =-AC2 -> -59.691709 | AD22: =-AD2 -> -743.01992 | AK22: -1.8899881 | AO22: =-(C22+H22+L22+AA22+AB22) -> 804.60162 | AQ22: =C22+H22+L22+AA22+AB22+AN22+AO22+AP22 -> 0
A23: Heat | AQ23: =C23+H23+L23+AA23+AB23+AN23+AO23+AP23 -> 0
A24: Other | C24: =SUM(D24:G24) -> 22.240062 | D24: -17.141361 | E24: =-D24-V24 -> 39.381423 | L24: =SUM(N24:Z24) -> -24.684016 | N24: 30.880435 | P24: -31.331711 | Q24: 361.9108 | R24: -361.12225 | S24: -0.17168421 | U24: -2.6095464 | V24: -22.240062 | W24: 0 | AB24: =SUM(AC24:AM24) -> 0 | AQ24: =C24+H24+L24+AA24+AB24+AN24+AO24+AP24 -> -2.4439548
A25: Own Use and Distribution Losses | C25: =SUM(D25:G25) -> 0 | H25: =SUM(I25:K25) -> 10.283248 | I25: 10.283248 | L25: =SUM(O25:Z25) -> 98.284658 | O25: 95.274692 | S25: 0 | T25: 0.0041693256 | U25: 3.0057963 | AA25: 57.5286 | AB25: =SUM(AC25:AI25) -> 0 | AO25: 259.46681 | AQ25: =C25+H25+L25+AA25+AB25+AN25+AO25+AP25 -> 425.56332
A26: Available Final Energy Consumption | C26: =C7-C9+C15+C21-C25 -> 320.1576 | D26: =D7-D9+D15+D21-D25 -> 221.42916 | E26: =E7-E9+E15+E21-E25 -> 86.198592 | F26: =F7-F9+F15+F21-F25 -> 0 | G26: =G7-G9+G15+G21-G25 -> 12.529851 | H26: =H7-H9+H15+H21-H25 -> 199.3142 | I26: =I7-I9+I15+I21-I25 -> 0.37225107 | J26: =J7-J9+J15+J21-J25 -> 127.704 | ... AP26: =AP7-AP9+AP15+AP21-AP25 -> 0 | AQ26: =C26+H26+L26+AA26+AB26+AN26+AO26+AP26 -> 12596.668
A27: Non-Energy Consumption | C27: =C28 -> 0 | D27: =D28 -> 0 | E27: =E28 -> 0 | F27: =F28 -> 0 | G27: =G28 -> 0 | H27: =H28 -> 0 | I27: =I28 -> 0 | J27: =J28 -> 0 | ... V27: =V28 -> 0 | X27: =X28 -> 195.36275 | Y27: =Y28 -> 1.2096467 | Z27: =Z28 -> 35.010885 | AA27: =AA28 -> 0 | AB27: =AB28 -> 0 | AC27: =AC28 -> 0 | AD27: =AD28 -> 0 | AE27: =AE28 -> 0 | ... AQ27: =AQ28 -> 231.58328
A28: Final non-Energy Consumption (Feedstocks) | C28: =SUM(D28:G28) -> 0 | H28: =SUM(I28:K28) -> 0 | L28: =SUM(M28:Z28) -> 231.58328 | X28: =X26 -> 195.36275 | Y28: =Y26 -> 1.2096467 | Z28: =Z26 -> 35.010885 | AA28: 0 | AB28: =SUM(AC28:AI28) -> 0 | AQ28: =C28+H28+L28+AA28+AB28+AN28+AO28+AP28 -> 231.58328
A29: Total Final Energy Consumption | C29: =C30+C45+C56+C58+C65+C70+C71 -> 322.73713 | D29: =D30+D45+D56+D58+D65+D70+D71 -> 221.25199 | E29: =E30+E45+E56+E58+E65+E70+E71 -> 89.64728 | F29: =F30+F45+F56+F58+F65+F70+F71 -> 0 | G29: =G30+G45+G56+G58+G65+G70+G71 -> 11.837385 | H29: =H30+H45+H56+H58+H65+H70+H71 -> 197.36847 | I29: =I30+I45+I56+I58+I65+I70+I71 -> 0.82966372 | J29: =J30+J45+J56+J58+J65+J70+J71 -> 127.704 | ... AQ29: =AQ30+AQ45+AQ56+AQ58+AQ65+AQ70+AQ71 -> 12441.76
A30: Industry* | C30: =SUM(C31:C44) -> 105.42503 | D30: 105.42455 | E30: 0 | H30: =SUM(H31:H44) -> 0.82966372 | I30: =SUM(I31:I44) -> 0.82966372 | J30: =SUM(J31:J44) -> 0 | K30: =SUM(K31:K44) -> 0 | L30: =SUM(L31:L44) -> 333.21701 | M30: =SUM(M31:M44) -> 0 | N30: =SUM(N31:N44) -> 0 | O30: =SUM(O31:O44) -> 0 | P30: =SUM(P31:P44) -> 0 | Q30: 5.8273118 | R30: =SUM(R31:R44) -> 0 | S30: 30.396553 | T30: 55.10581 | U30: 100.77893 | V30: 141.1084 | W30: =SUM(W31:W44) -> 0 | X30: =SUM(X31:X44) -> 0 | Y30: =SUM(Y31:Y44) -> 0 | Z30: =SUM(Z31:Z44) -> 0 | AA30: 1006.4294 | AB30: =SUM(AB31:AB44) -> 198.81521 | AC30: =SUM(AC31:AC44) -> 0 | AD30: =SUM(AD31:AD44) -> 0 | AE30: =SUM(AE31:AE44) -> 153.96699 | AF30: =SUM(AF31:AF44) -> 40.692904 | AG30: =SUM(AG31:AG44) -> 0 | AH30: =SUM(AH31:AH44) -> 4.1553164 | AI30: =SUM(AI31:AI44) -> 0 | ... AN30: =SUM(AN31:AN44) -> 54.72294 | AO30: 562.37095 | AP30: =SUM(AP31:AP44) -> 0 | AQ30: =C30+H30+L30+AA30+AB30+AN30+AO30+AP30 -> 2261.8102
A31: Non-Energy Mining | B31: 05-09 | C31: =SUM(D31:G31) -> 0 | D31: 0 | H31: =SUM(I31:K31) -> 0 | L31: =SUM(M31:Z31) -> 15.076944 | Q31: 0.252 | S31: 0 | T31: 0.090944232 | U31: 14.734 | V31: 0 | AA31: 11.321518 | AB31: =SUM(AC31:AM31) -> 0 | AO31: 18.942945 | AQ31: =C31+H31+L31+AA31+AB31+AN31+AO31+AP31 -> 45.341408
A32: Food & beverages | B32: 10-11 | C32: =SUM(D32:G32) -> 18.505816 | D32: 18.505816 | H32: =SUM(I32:K32) -> 0.82966372 | I32: 0.82966372 | L32: =SUM(M32:Z32) -> 65.081235 | Q32: 1.514 | S32: 22.968462 | T32: 29.495772 | U32: 11.103 | V32: 0 | AA32: 272.71139 | AB32: =SUM(AC32:AM32) -> 27.983335 | AE32: 23.828019 | AH32: 4.1553164 | AO32: 95.275089 | AQ32: =C32+H32+L32+AA32+AB32+AN32+AO32+AP32 -> 480.38653
A33: Textiles and textile products | B33: 13-14 | C33: =SUM(D33:G33) -> 0 | D33: 0 | H33: =SUM(I33:K33) -> 0 | L33: =SUM(M33:Z33) -> 4.25876 | Q33: 0.077 | S33: 0 | T33: 3.90776 | U33: 0.274 | V33: 0 | AA33: 3.3044502 | AB33: =SUM(AC33:AM33) -> 0 | AO33: 2.6521774 | AQ33: =C33+H33+L33+AA33+AB33+AN33+AO33+AP33 -> 10.215388
A34: Wood and wood products | B34: 16 | C34: =SUM(D34:G34) -> 0 | D34: 0 | H34: =SUM(I34:K34) -> 0 | L34: =SUM(M34:Z34) -> 3.2131896 | Q34: 0.177 | S34: 0 | T34: 0.60818955 | U34: 2.428 | V34: 0 | AA34: 9.6605546 | AB34: =SUM(AC34:AM34) -> 127.9132 | AE34: 127.9132 | AO34: 24.722009 | AQ34: =C34+H34+L34+AA34+AB34+AN34+AO34+AP34 -> 165.50895
A35: Pulp, paper, publishing and printing | B35: 17-18 | C35: =SUM(D35:G35) -> 0 | D35: 0 | H35: =SUM(I35:K35) -> 0 | L35: =SUM(M35:Z35) -> 1.6055046 | Q35: 0.096 | S35: 0 | T35: 0.6295046 | U35: 0.88 | V35: 0 | AA35: 14.125994 | AB35: =SUM(AC35:AM35) -> 0 | AO35: 10.336268 | AQ35: =C35+H35+L35+AA35+AB35+AN35+AO35+AP35 -> 26.067767
A36: Chemicals & man-made fibres | B36: 20-21 | C36: =SUM(D36:G36) -> 0 | D36: 0 | H36: =SUM(I36:K36) -> 0 | L36: =SUM(M36:Z36) -> 21.418897 | Q36: 0.306 | S36: 2.7458234 | T36: 3.9702841 | U36: 4.579 | V36: 9.8177897 | AA36: 129.58451 | AB36: =SUM(AC36:AM36) -> 0 | AE36: 0 | AO36: 76.140196 | AQ36: =C36+H36+L36+AA36+AB36+AN36+AO36+AP36 -> 227.1436
A37: Rubber and plastic products | B37: 22 | C37: =SUM(D37:G37) -> 0 | D37: 0 | H37: =SUM(I37:K37) -> 0 | L37: =SUM(M37:Z37) -> 4.1927666 | Q37: 0.535 | S37: 0 | T37: 2.1897666 | U37: 1.468 | V37: 0 | AA37: 17.456036 | AB37: =SUM(AC37:AM37) -> 0 | AO37: 25.060497 | AQ37: =C37+H37+L37+AA37+AB37+AN37+AO37+AP37 -> 46.7093
A38: Other non-metallic mineral products | B38: 23 | C38: =SUM(D38:G38) -> 86.919212 | D38: 86.919212 | H38: =SUM(I38:K38) -> 0 | L38: =SUM(M38:Z38) -> 160.32357 | Q38: 1.144 | S38: 0 | T38: 2.6359617 | U38: 25.253 | V38: 131.29061 | AA38: 46.760405 | AB38: =SUM(AC38:AM38) -> 42.918678 | AE38: 2.2257741 | AF38: 40.692904 | AN38: 54.72294 | AO38: 73.686158 | AQ38: =C38+H38+L38+AA38+AB38+AN38+AO38+AP38 -> 465.33096
A39: Basic metals and fabricated metal products | B39: 24-25 | C39: =SUM(D39:G39) -> 0 | D39: 0 | H39: =SUM(I39:K39) -> 0 | L39: =SUM(M39:Z39) -> 5.6776554 | Q39: 0.338 | S39: 1.0397615 | T39: 1.5488939 | U39: 2.751 | V39: 0 | AA39: 411.95146 | AB39: =SUM(AC39:AM39) -> 0 | AO39: 67.595438 | AQ39: =C39+H39+L39+AA39+AB39+AN39+AO39+AP39 -> 485.22456
A40: Machinery and equipment n.e.c. | B40: 28 | C40: =SUM(D40:G40) -> 0 | D40: 0 | H40: =SUM(I40:K40) -> 0 | L40: =SUM(M40:Z40) -> 4.0583976 | Q40: 0.144 | S40: 0 | T40: 2.2053976 | U40: 1.709 | V40: 0 | AA40: 14.088543 | AB40: =SUM(AC40:AM40) -> 0 | AO40: 17.03379 | AQ40: =C40+H40+L40+AA40+AB40+AN40+AO40+AP40 -> 35.180731
A41: Electrical and optical equipment | B41: 26-27 | C41: =SUM(D41:G41) -> 0 | D41: 0 | H41: =SUM(I41:K41) -> 0 | L41: =SUM(M41:Z41) -> 2.3538977 | Q41: 0.184 | S41: 0 | T41: 1.4408977 | U41: 0.729 | V41: 0 | AA41: 20.514556 | AB41: =SUM(AC41:AM41) -> 0 | AO41: 88.215343 | AQ41: =C41+H41+L41+AA41+AB41+AN41+AO41+AP41 -> 111.0838
A42: Transport equipment manufacture | B42: 29-30 | C42: =SUM(D42:G42) -> 0 | D42: 0 | H42: =SUM(I42:K42) -> 0 | L42: =SUM(M42:Z42) -> 1.2106524 | Q42: 0.066 | S42: 0 | T42: 0.92365235 | U42: 0.221 | V42: 0 | AA42: 0.86574848 | AB42: =SUM(AC42:AM42) -> 0 | AO42: 2.5758112 | AQ42: =C42+H42+L42+AA42+AB42+AN42+AO42+AP42 -> 4.6522121
A43: Other manufacturing | B43: 31-33, 12 & 15 | C43: =SUM(D43:G43) -> 0 | D43: 0 | H43: =SUM(I43:K43) -> 0 | K43: 0 | L43: =SUM(M43:Z43) -> 12.040387 | Q43: 0.293 | S43: 3.6425061 | T43: 4.9848807 | U43: 3.12 | V43: 0 | AA43: 49.987456 | AB43: =SUM(AC43:AM43) -> 0 | AO43: 50.1922 | AQ43: =C43+H43+L43+AA43+AB43+AN43+AO43+AP43 -> 112.22004
A44: Construction | B44: 41-43 | C44: =SUM(D44:G44) -> 0 | D44: 0 | H44: =SUM(I44:K44) -> 0 | L44: =SUM(M44:Z44) -> 32.70515 | Q44: 0.70131178 | S44: 0 | T44: 0.4739052 | U44: 31.529933 | V44: 0 | AA44: 4.0968183 | AB44: =SUM(AC44:AM44) -> 0 | AO44: 9.9430291 | AQ44: =C44+H44+L44+AA44+AB44+AN44+AO44+AP44 -> 46.744997
A45: Transport | C45: =SUM(C46:C55) -> 0 | D45: =SUM(D46:D55) -> 0 | E45: =SUM(E46:E55) -> 0 | F45: =SUM(F46:F55) -> 0 | G45: =SUM(G46:G55) -> 0 | H45: =SUM(H46:H55) -> 0 | I45: =SUM(I46:I55) -> 0 | J45: =SUM(J46:J55) -> 0 | ... AP45: =SUM(AP46:AP55) -> 0 | AQ45: =C45+H45+L45+AA45+AB45+AN45+AO45+AP45 -> 5194.8404
A46: Road Freight | C46: =SUM(D46:G46) -> 0 | H46: =SUM(I46:K46) -> 0 | L46: =SUM(M46:Z46) -> 703.59089 | U46: 703.59089 | AA46: 0.029723186 | AB46: =SUM(AC46:AM46) -> 30.16231 | AI46: 30.16231 | AJ46: 0 | AQ46: =C46+H46+L46+AA46+AB46+AN46+AO46+AP46 -> 733.78292
A47: Road Light Goods Vehicle | C47: =SUM(D47:G47) -> 0 | H47: =SUM(I47:K47) -> 0 | L47: =SUM(M47:Z47) -> 329.18378 | U47: 329.18378 | AB47: =SUM(AC47:AM47) -> 14.111813 | AI47: 14.111813 | AJ47: 0 | AQ47: =C47+H47+L47+AA47+AB47+AN47+AO47+AP47 -> 343.29559
A48: Road Private Car | C48: =SUM(D48:G48) -> 0 | H48: =SUM(I48:K48) -> 0 | L48: =SUM(M48:Z48) -> 1988.8117 | P48: 674.58043 | T48: 1.8520724 | U48: 1312.3792 | AB48: =SUM(AC48:AM48) -> 78.598026 | AI48: 56.260518 | AJ48: 22.337507 | AO48: 1.0652907 | AQ48: =C48+H48+L48+AA48+AB48+AN48+AO48+AP48 -> 2068.475
A49: Public Passenger Services | C49: =SUM(D49:G49) -> 0 | H49: =SUM(I49:K49) -> 0 | L49: =SUM(M49:Z49) -> 132.19129 | P49: 6.5053364 | U49: 125.68595 | AB49: =SUM(AC49:AM49) -> 5.6034563 | AI49: 5.3880439 | AJ49: 0.21541241 | AQ49: =C49+H49+L49+AA49+AB49+AN49+AO49+AP49 -> 137.79474
A50: Rail | C50: =SUM(D50:G50) -> 0 | H50: =SUM(I50:K50) -> 0 | L50: =SUM(M50:Z50) -> 38.043222 | U50: 38.043222 | AB50: =SUM(AC50:AM50) -> 0 | AI50: 0 | AO50: 4.3080909 | AQ50: =C50+H50+L50+AA50+AB50+AN50+AO50+AP50 -> 42.351313
A51: Domestic Aviation | C51: =SUM(D51:G51) -> 0 | H51: =SUM(I51:K51) -> 0 | L51: =SUM(M51:Z51) -> 5.5768893 | P51: 0.66818889 | R51: 4.9087004 | AB51: =SUM(AC51:AM51) -> 0 | AQ51: =C51+H51+L51+AA51+AB51+AN51+AO51+AP51 -> 5.5768893
A52: International Aviation | C52: =SUM(D52:G52) -> 0 | H52: =SUM(I52:K52) -> 0 | L52: =SUM(M52:Z52) -> 1097.9355 | R52: 1097.9355 | AB52: =SUM(AC52:AM52) -> 0 | AQ52: =C52+H52+L52+AA52+AB52+AN52+AO52+AP52 -> 1097.9355
A53: Fuel Tourism | C53: =SUM(D53:G53) -> 0 | H53: =SUM(I53:K53) -> 0 | L53: =SUM(M53:Z53) -> 176.59351 | P53: 0 | U53: 176.59351 | AB53: =SUM(AC53:AM53) -> 7.5704053 | AI53: 7.5704053 | AJ53: 0 | AQ53: =C53+H53+L53+AA53+AB53+AN53+AO53+AP53 -> 184.16392
A54: Navigation | C54: =SUM(D54:G54) -> 0 | H54: =SUM(I54:K54) -> 0 | L54: =SUM(M54:Z54) -> 83.913724 | U54: 83.913724 | AB54: =SUM(AC54:AM54) -> 0 | AQ54: =C54+H54+L54+AA54+AB54+AN54+AO54+AP54 -> 83.913724
A55: Unspecified | C55: =SUM(D55:G55) -> 0 | H55: =SUM(I55:K55) -> 0 | L55: =SUM(M55:Z55) -> 456.82605 | P55: 142.49107 | S55: 0 | U55: 314.33498 | AA55: 22.531112 | AB55: =SUM(AC55:AM55) -> 18.193592 | AI55: 13.475259 | AJ55: 4.7183332 | AQ55: =C55+H55+L55+AA55+AB55+AN55+AO55+AP55 -> 497.55075
A56: Residential | C56: =SUM(D56:G56) -> 216.79218 | D56: 115.30752 | E56: 89.64728 | G56: 11.837385 | H56: =SUM(I56:K56) -> 196.53881 | J56: 127.704 | K56: 68.834806 | L56: =SUM(M56:Z56) -> 1254.8255 | P56: 0 | Q56: 865.6711 | S56: 0 | T56: 53.841523 | U56: 329.90901 | V56: 5.4038717 | AA56: 604.09376 | AB56: =SUM(AC56:AM56) -> 71.02667 | AE56: 29.776082 | AL56: 13.379591 | AM56: 27.870996 | AO56: 702.94474 | AQ56: =C56+H56+L56+AA56+AB56+AN56+AO56+AP56 -> 3046.2217
A57: Commercial/Public Services* | C57: =C58+C65 -> 0.5199218 | D57: =D58+D65 -> 0.5199218 | E57: =E58+E65 -> 0 | F57: =F58+F65 -> 0 | G57: =G58+G65 -> 0 | H57: =H58+H65 -> 0 | I57: =I58+I65 -> 0 | J57: =J58+J65 -> 0 | ... AP57: =AP58+AP65 -> 0 | AQ57: =C57+H57+L57+AA57+AB57+AN57+AO57+AP57 -> 1688.1847
A58: Commercial Services* | C58: =SUM(D58:G58) -> 0.51492256 | D58: 0.51492256 | E58: 0 | F58: =SUM(F59:F64) -> 0 | G58: 0 | H58: =SUM(I58:K58) -> 0 | I58: =SUM(I59:I64) -> 0 | J58: =SUM(J59:J64) -> 0 | K58: =SUM(K59:K64) -> 0 | L58: =SUM(M58:Z58) -> 109.16311 | M58: =SUM(M59:M64) -> 0 | N58: =SUM(N59:N64) -> 0 | O58: =SUM(O59:O64) -> 0 | P58: =SUM(P59:P64) -> 0 | Q58: 15.841 | R58: =SUM(R59:R64) -> 0 | S58: 0 | T58: 41.07411 | U58: 52.248 | V58: =SUM(V59:V64) -> 0 | W58: =SUM(W59:W64) -> 0 | X58: =SUM(X59:X64) -> 0 | Y58: =SUM(Y59:Y64) -> 0 | Z58: =SUM(Z59:Z64) -> 0 | AA58: 206.51565 | AB58: =SUM(AC58:AM58) -> 20.523796 | AC58: =SUM(AC59:AC64) -> 0 | AD58: =SUM(AD59:AD64) -> 0 | AE58: =SUM(AE59:AE64) -> 3.9004189 | AG58: =SUM(AG59:AG64) -> 0 | AH58: =SUM(AH59:AH64) -> 0.80443075 | AI58: =SUM(AI59:AI64) -> 0 | AJ58: =SUM(AJ59:AJ64) -> 0 | AL58: 0.16649466 | AM58: 15.652452 | AN58: =SUM(AN59:AN64) -> 0 | AO58: 828.90452 | AP58: =SUM(AP59:AP64) -> 0 | AQ58: =C58+H58+L58+AA58+AB58+AN58+AO58+AP58 -> 1165.622
A59: Wholesale, Retail, and Vehicle Repair | B59: 45-47 | C59: =SUM(D59:G59) -> 0.0039993985 | D59: 0.0039993985 | H59: =SUM(I59:K59) -> 0 | L59: =SUM(M59:Z59) -> 29.110393 | Q59: 6.548 | S59: 0 | T59: 11.487393 | U59: 11.075 | V59: 0 | AA59: 52.670839 | AB59: =SUM(AC59:AM59) -> 1.2953272 | AE59: 1.2953272 | AH59: 0 | AL59: 0 | AM59: 0 | AO59: 225.70856 | AQ59: =C59+H59+L59+AA59+AB59+AN59+AO59+AP59 -> 308.78912
A60: Transportation and Storage | B60: 49-53 | C60: =SUM(D60:G60) -> 0.0089986466 | D60: 0.0089986466 | H60: =SUM(I60:K60) -> 0 | L60: =SUM(M60:Z60) -> 24.503931 | Q60: 1.271 | S60: 0 | T60: 1.9979311 | U60: 21.235 | V60: 0 | AA60: 23.74348 | AB60: =SUM(AC60:AM60) -> 0.011385567 | AE60: 0.011385567 | AH60: 0 | AL60: 0 | AM60: 0 | AO60: 81.932676 | AQ60: =C60+H60+L60+AA60+AB60+AN60+AO60+AP60 -> 130.20047
A61: Accommodation and Food Services | B61: 55-56 | C61: =SUM(D61:G61) -> 0.42993534 | D61: 0.42993534 | H61: =SUM(I61:K61) -> 0 | L61: =SUM(M61:Z61) -> 27.815961 | Q61: 3.399 | S61: 0 | T61: 19.454961 | U61: 4.962 | V61: 0 | AA61: 30.235657 | AB61: =SUM(AC61:AM61) -> 0.86179983 | AE61: 0.86179983 | AH61: 0 | AL61: 0 | AM61: 0 | AO61: 126.36748 | AQ61: =C61+H61+L61+AA61+AB61+AN61+AO61+AP61 -> 185.71084
A62: Information and Communication | B62: 58-63 | C62: =SUM(D62:G62) -> 0.0069989474 | D62: 0.0069989474 | H62: =SUM(I62:K62) -> 0 | L62: =SUM(M62:Z62) -> 2.6967648 | Q62: 0.363 | S62: 0 | T62: 0.71476482 | U62: 1.619 | V62: 0 | AA62: 12.942534 | AB62: =SUM(AC62:AM62) -> 0.04641808 | AE62: 0.04641808 | AH62: 0 | AL62: 0 | AM62: 0 | AO62: 234.42875 | AQ62: =C62+H62+L62+AA62+AB62+AN62+AO62+AP62 -> 250.12147
A63: Financial, Insurance and Real Estate Activities | B63: 64-68 | C63: =SUM(D63:G63) -> 0.057991278 | D63: 0.057991278 | H63: =SUM(I63:K63) -> 0 | L63: =SUM(M63:Z63) -> 3.8680994 | Q63: 0.684 | S63: 0 | T63: 0.16909943 | U63: 3.015 | V63: 0 | AA63: 11.636733 | AB63: =SUM(AC63:AM63) -> 0.3476977 | AE63: 0.3476977 | AH63: 0 | AL63: 0 | AM63: 0 | AO63: 42.65981 | AQ63: =C63+H63+L63+AA63+AB63+AN63+AO63+AP63 -> 58.570331
A64: Other Services Sectors | C64: =SUM(D64:G64) -> 0.0069989474 | D64: 0.0069989474 | H64: =SUM(I64:K64) -> 0 | L64: =SUM(M64:Z64) -> 21.16796 | Q64: 3.576 | S64: 0 | T64: 7.2499605 | U64: 10.342 | V64: 0 | AA64: 75.286411 | AB64: =SUM(AC64:AM64) -> 17.961168 | AE64: 1.3377905 | AH64: 0.80443075 | AL64: 0.16649466 | AM64: 15.652452 | AO64: 117.80725 | AQ64: =C64+H64+L64+AA64+AB64+AN64+AO64+AP64 -> 232.22978
A65: Public Services* | C65: =SUM(D65:G65) -> 0.0049992481 | D65: =SUM(D66:D69) -> 0.0049992481 | H65: =SUM(I65:K65) -> 0 | J65: 0 | K65: 0 | L65: =SUM(M65:Z65) -> 131.70415 | Q65: 46.986 | S65: 0.64284747 | T65: 29.4503 | U65: 54.625 | V65: =SUM(V66:V69) -> 0 | AA65: 122.10424 | AB65: =SUM(AC65:AM65) -> 18.910018 | AE65: =SUM(AE66:AE69) -> 14.092704 | AH65: 4.817314 | AO65: 249.83924 | AQ65: =C65+H65+L65+AA65+AB65+AN65+AO65+AP65 -> 522.56265
A66: Water Supply, Sewerage, and Waste Management | B66: 36-39 | C66: =SUM(D66:G66) -> 0.0029995489 | D66: 0.0029995489 | H66: =SUM(I66:K66) -> 0 | L66: =SUM(M66:Z66) -> 4.8361472 | Q66: 0.13 | S66: 0.0031863567 | T66: 1.1339609 | U66: 3.569 | V66: 0 | AA66: 6.2855711 | AB66: =SUM(AC66:AM66) -> 4.8181898 | AE66: 0.00087581284 | AH66: 4.817314 | AO66: 62.066112 | AQ66: =C66+H66+L66+AA66+AB66+AN66+AO66+AP66 -> 78.00902
A67: Public Administration | B67: 84 | C67: =SUM(D67:G67) -> 0.0019996992 | D67: 0.0019996992 | H67: =SUM(I67:K67) -> 0 | L67: =SUM(M67:Z67) -> 37.495977 | Q67: 6.925 | S67: 0.36191702 | T67: 7.4190599 | U67: 22.79 | V67: 0 | AA67: 43.318633 | AB67: =SUM(AC67:AM67) -> 3.013672 | AE67: 3.013672 | AH67: 0 | AO67: 90.275167 | AQ67: =C67+H67+L67+AA67+AB67+AN67+AO67+AP67 -> 174.10545
A68: Education | B68: 85 | C68: =SUM(D68:G68) -> 0 | D68: 0 | H68: =SUM(I68:K68) -> 0 | L68: =SUM(M68:Z68) -> 63.764873 | Q68: 27.067 | S68: 0.054168064 | T68: 17.705705 | U68: 18.938 | V68: 0 | AA68: 27.252039 | AB68: =SUM(AC68:AM68) -> 9.8108554 | AE68: 9.8108554 | AH68: 0 | AO68: 58.093006 | AQ68: =C68+H68+L68+AA68+AB68+AN68+AO68+AP68 -> 158.92077
A69: Health, Residential Care and Social Work Activities | B69: 86-88 | C69: =SUM(D69:G69) -> 0 | D69: 0 | H69: =SUM(I69:K69) -> 0 | L69: =SUM(M69:Z69) -> 25.60715 | Q69: 12.864 | S69: 0.22357603 | T69: 3.1915741 | U69: 9.328 | V69: 0 | AA69: 45.247998 | AB69: =SUM(AC69:AM69) -> 1.2673012 | AE69: 1.2673012 | AH69: 0 | AO69: 39.404959 | AQ69: =C69+H69+L69+AA69+AB69+AN69+AO69+AP69 -> 111.52741
A70: Agricultural | C70: =SUM(D70:G70) -> 0 | D70: 0 | H70: =SUM(I70:K70) -> 0 | L70: =SUM(M70:Z70) -> 175.46549 | P70: 0 | Q70: 0 | T70: 0 | U70: 175.46549 | AA70: 0 | AB70: =SUM(AC70:AM70) -> 0 | AO70: 47.988 | AQ70: =C70+H70+L70+AA70+AB70+AN70+AO70+AP70 -> 223.45349
A71: Fisheries | C71: =SUM(D71:G71) -> 0 | H71: =SUM(I71:K71) -> 0 | L71: =SUM(M71:Z71) -> 27.249866 | U71: 27.249866 | AB71: =SUM(AC71:AM71) -> 0 | AQ71: =C71+H71+L71+AA71+AB71+AN71+AO71+AP71 -> 27.249866
A72: Statistical Difference | C72: =C26-C27-C29 -> -2.5795347 | D72: =D26-D27-D29 -> 0.17716668 | E72: =E26-E27-E29 -> -3.4486884 | F72: =F26-F27-F29 -> 0 | G72: =G26-G27-G29 -> 0.69246574 | H72: =H26-H27-H29 -> 1.945725 | I72: =I26-I27-I29 -> -0.45741265 | J72: =J26-J27-J29 -> 0 | ... AP72: =AP26-AP27-AP29 -> 0 | AQ72: =C72+H72+L72+AA72+AB72+AN72+AO72+AP72 -> -76.675386
A74: *Industry & Services sub-sectoral breakdown is based on the BEUS 2018.
A75: Last Updated : 1st September 2022
A76: 2018 provisional data
A77: 2018 provisional data based on 2017 breakdown
A78: 2017 data
A79: Sod peat is estimated due to new legislation and the methodology is under review
A80: Statistical differences may exist for crude oil between the calculated primary energy requirement and the observed refinery input
A81: Fuel Section
A82: Fuel Sub-Section

Sheet RSD_Balance
A1: ~Country | B1: IE | F1: SMF - Components | H1: SHARE
A2: Sector | B2: Residential | F2: COA | H2: 0.194
A3: ~Year | B3: 2018 | F3: PEA | H3: 0.744
A4: ~Unit conversion | B4: 0.041868 | F4: BIOWOO | H4: 0.062
F5: SMF | H5: =SUM(H2:H4) -> 1 | AN5: Light
AN6: APT | AO6: 0.33 | AQ6: ELC | AR6: 2.05
A7: Base-year energy consumption from SEAI (PJ) | F7: Space Heating | I7: Water Heating | L7: Lighting | O7: Pumps & Fans | R7: Cooking | S7: Appliances | Y7: TIMES-Ireland Total | Z7: SEAI Energy Balance 2018 | AA7: Excel Error | AD7: VEDA | AE7: VEDA Error | AI7: SH | AN7: ATT | AO7: 1.75 | AQ7: Gas | AR7: 0.67
A8: Fuel | B8: Description | C8: PJ | F8: Apartment | G8: Attached | H8: Detached | I8: Apartment | J8: Attached | K8: Detached | L8: Apartment | M8: Attached | N8: Detached | O8: Apartment | P8: Attached | Q8: Detached | S8: Refrigeration | T8: Cloth Washing | U8: Cloth Drying | V8: Dish Washing | W8: Other Electric | X8: Other Energy | AA8: Error | AE8: Error | AI8: RSDAHT | AJ8: 1.1516523 | AN8: DET | AO8: 2.73 | AQ8: LPG | AR8: 0.04
A9: COA | B9: Coal | C9: =SUM('EB2018'!C56)*RSD_Balance!B4 -> 9.0766551 | E9: COA | F9: ='SHWLP-Apt'!$AC$7+'SHWLP-Apt'!AC20 -> 0 | G9: ='SHWLP-Att'!$AC$7+'SHWLP-Att'!$AC$20 -> 5.0701051 | H9: ='SHWLP-Det'!$AC$7+'SHWLP-Det'!$AC$20 -> 4.428656 | I9: ='SHWLP-Apt'!$AC$33+'SHWLP-Apt'!$AC$46 -> 0 | J9: ='SHWLP-Att'!$AC$33+'SHWLP-Att'!$AC$46 -> 0.40856217 | K9: ='SHWLP-Det'!$AC$33+'SHWLP-Det'!$AC$46 -> 0.10058759 | Y9: =SUM(F9:X9) -> 10.007911 | Z9: =C9 -> 9.0766551 | AA9: =ABS(Z9-Y9)/Z9 -> 0.102599 | AD9: =AJ9+AJ20 -> 10.269076 | AE9: =ABS(AD9-Y9)/AD9 -> 0.025432157 | AI9: RSDCOA | AJ9: 9.659974 | AN9: P&F
A10: PEA | B10: ='EB2018'!H1 -> Peat | C10: ='EB2018'!H56*RSD_Balance!B4 -> 8.2286867 | E10: PEA | F10: ='SHWLP-Apt'!$AC$18+'SHWLP-Apt'!$AC$21 -> 0.0032061499 | G10: ='SHWLP-Att'!$AC$18+'SHWLP-Att'!$AC$21 -> 2.0071676 | H10: ='SHWLP-Det'!$AC$18+'SHWLP-Det'!$AC$21 -> 5.3563325 | I10: ='SHWLP-Apt'!$AC$44+'SHWLP-Apt'!$AC$47 -> 0 | J10: ='SHWLP-Att'!$AC$44+'SHWLP-Att'!$AC$47 -> 0.36088384 | K10: ='SHWLP-Det'!$AC$44+'SHWLP-Det'!$AC$47 -> 0.38575861 | Y10: =SUM(F10:X10) -> 8.1133487 | Z10: =C10 -> 8.2286867 | AA10: =ABS(Z10-Y10)/Z10 -> 0.014016576 | AD10: =AJ14+AJ27 -> 8.1954076 | AE10: =ABS(AD10-Y10)/AD10 -> 0.010012791 | AI10: RSDELC | AJ10: 4.4337734 | AN10: APT | AO10: 0.07
A11: LPG | B11: ='EB2018'!T1 -> LPG | C11: ='EB2018'!T56*RSD_Balance!B4 -> 2.2542369 | E11: OILLPG | F11: ='SHWLP-Apt'!$AC$10 -> 0 | G11: ='SHWLP-Att'!$AC$10 -> 0.33080594 | H11: ='SHWLP-Det'!$AC$10 -> 1.2958226 | I11: ='SHWLP-Apt'!$AC$36 -> 0 | J11: ='SHWLP-Att'!$AC$36 -> 0 | K11: ='SHWLP-Det'!$AC$36 -> 0 | R11: 0.039492406 | Y11: =SUM(F11:X11) -> 1.6661209 | Z11: =C11 -> 2.2542369 | AA11: =ABS(Z11-Y11)/Z11 -> 0.2608936 | AD11: =AJ13+AJ26+AR8 -> 2.1294859 | AE11: =ABS(AD11-Y11)/AD11 -> 0.21759477 | AI11: RSDGAS | AJ11: 16.539193 | AN11: ATT | AO11: 0.49
A12: GSL | B12: ='EB2018'!P1 -> Gasoline | C12: ='EB2018'!P56*B4 -> 0 | E12: OILGSL | Y12: =SUM(F12:X12) -> 0 | Z12: =C12 -> 0 | AI12: RSDKER | AJ12: 33.821001 | AN12: DET | AO12: 0.57
A13: KER | B13: ='EB2018'!Q1 -> Kerosene | C13: ='EB2018'!Q56*RSD_Balance!B4 -> 36.243918 | E13: OILKER | F13: ='SHWLP-Apt'!$AC$14 -> 0.23973747 | G13: ='SHWLP-Att'!$AC$14 -> 8.555665 | H13: ='SHWLP-Det'!$AC$14 -> 31.600518 | I13: ='SHWLP-Apt'!$AC$40 -> 0 | J13: ='SHWLP-Att'!$AC$40 -> 3.1609218 | K13: ='SHWLP-Det'!$AC$40 -> 8.4233865 | Y13: =SUM(F13:X13) -> 51.980229 | Z13: =C13 -> 36.243918 | AA13: =ABS(Z13+Z14+Z16-Y13)/(Z13+Z14+Z16) -> 0.033757693 | AD13: =AJ12+AJ25 -> 43.727301 | AE13: =ABS(AD13-Y13)/AD13 -> 0.18873628 | AI13: RSDLPG | AJ13: 1.6238402
A14: DST | B14: ='EB2018'!U1 -> Gasoil / Diesel /DERV | C14: ='EB2018'!U56*RSD_Balance!B4 -> 13.81263 | E14: OILDST | Y14: =SUM(F14:X14) -> 0 | Z14: =C14 -> 13.81263 | AA14: =ABS(Z13+Z14+Z16-Y13)/(Z13+Z14+Z16) -> 0.033757693 | AI14: RSDPEA | AJ14: 7.3969701
A15: HFO | B15: ='EB2018'!S1 -> Fueloil | C15: ='EB2018'!S56*RSD_Balance!B4 -> 0 | E15: OILHFO | Y15: =SUM(F15:X15) -> 0 | Z15: =C15 -> 0 | AA15: =ABS(Z13+Z14+Z16-Y13)/(Z13+Z14+Z16) -> 0.033757693 | AI15: RSDWOO | AJ15: 1.1222132 | AQ15: CD | AR15: 1.71
A16: COK | B16: ='EB2018'!V1 -> Petroleum Coke | C16: ='EB2018'!V56*RSD_Balance!B4 -> 0.2262493 | E16: OILCOK | Y16: =SUM(F16:X16) -> 0 | Z16: =C16 -> 0.2262493 | AA16: =ABS(Z13+Z14+Z16-Y13)/(Z13+Z14+Z16) -> 0.033757693 | AQ16: CW | AR16: 1.1
A17: GAS | B17: ='EB2018'!AA1 -> Natural Gas | C17: ='EB2018'!AA56*RSD_Balance!B4 -> 25.292197 | E17: GASNAT | F17: ='SHWLP-Apt'!$AC$16 -> 1.2906334 | G17: ='SHWLP-Att'!$AC$16 -> 11.879486 | H17: ='SHWLP-Det'!$AC$16 -> 5.2345577 | I17: ='SHWLP-Apt'!$AC$42 -> 0.60716402 | J17: ='SHWLP-Att'!$AC$42 -> 4.1120335 | K17: ='SHWLP-Det'!$AC$42 -> 1.4948266 | R17: 0.66992893 | Y17: =SUM(F17:X17) -> 25.28863 | Z17: =C17 -> 25.292197 | AA17: =ABS(Z17-Y17)/Z17 -> 0.00014104055 | AD17: =AJ11+AJ23+AR7 -> 23.522734 | AE17: =ABS(AD17-Y17)/AD17 -> 0.075071888 | AI17: WH | AQ17: DW | AR17: 1.19
A18: SOL | B18: ='EB2018'!AL1 -> Solar Thermal | C18: ='EB2018'!AL56*RSD_Balance!B4 -> 0.56017671 | E18: RENSOL | I18: =($C$18*0.05) -> 0.028008836 | J18: =($C$18*0.475) -> 0.26608394 | K18: =($C$18*0.475) -> 0.26608394 | Y18: =SUM(F18:X18) -> 0.56017671 | Z18: =C18 -> 0.56017671 | AA18: =ABS(Z18-Y18)/Z18 -> 1.9819157e-16 | AD18: =AJ28 -> 0.56017671 | AE18: =ABS(AD18-Y18)/AD18 -> 9.9095785e-16 | AI18: RSDAHT2 | AJ18: 1.05138 | AQ18: OE | AR18: 10.84
A19: WOO | B19: ='EB2018'!AE1 -> Biomass | C19: ='EB2018'!AE56*RSD_Balance!B4 -> 1.246665 | E19: BIOWOO | F19: ='SHWLP-Apt'!$AC$22+'SHWLP-Apt'!$AC$23 -> 0 | G19: ='SHWLP-Att'!$AC$22+'SHWLP-Att'!$AC$23 -> 0.15910158 | H19: ='SHWLP-Det'!$AC$22+'SHWLP-Det'!$AC$23 -> 0.86316679 | I19: ='SHWLP-Apt'!$AC$49+'SHWLP-Apt'!$AC$48 -> 0 | J19: ='SHWLP-Att'!$AC$49+'SHWLP-Att'!$AC$48 -> 0.030073653 | K19: ='SHWLP-Det'!$AC$49+'SHWLP-Det'!$AC$48 -> 0.032146551 | Y19: =SUM(F19:X19) -> 1.0844886 | Z19: =C19 -> 1.246665 | AA19: =ABS(Z19-Y19)/Z19 -> 0.13008822 | AD19: =AJ29+AJ15 -> 1.2689595 | AE19: =ABS(AD19-Y19)/AD19 -> 0.14537179 | AI19: RSDBDL | AJ19: 7.8153182e-05 | AQ19: RF | AR19: 1.41
A20: BGS | B20: ='EB2018'!AH1 -> Biogas | C20: ='EB2018'!AH56*RSD_Balance!B4 -> 0 | E20: BIOGAS | Y20: =SUM(F20:X20) -> 0 | Z20: =C20 -> 0 | AI20: RSDCOA | AJ20: 0.60910161
A21: BIOMUN | B21: ='EB2018'!AG1 -> Landfill Gas | C21: ='EB2018'!AG56*RSD_Balance!B4 -> 0 | E21: BIOMUN | Y21: =SUM(F21:X21) -> 0 | Z21: =C21 -> 0 | AI21: RSDELC | AJ21: 2.3626994
A22: AHT | B22: ='EB2018'!AM1 -> Ambient Heat | C22: ='EB2018'!AM56*RSD_Balance!B4 -> 1.1669029 | E22: RENAHT | F22: =('SHWLP-Apt'!$AC$12/('SHWLP-Apt'!$AC$12+'SHWLP-Att'!$AC$12+'SHWLP-Det'!$AC$12+'SHWLP-Apt'!$AC$38+'SHWLP-Att'!$AC$38+'SHWLP-Det'!$AC$38+'SHWLP-Apt'!AC24+'SHWLP-Apt'!AC50+'SHWLP-Att'!AC24+'SHWLP-Att'!AC50+'SHWLP-Det'!AC24+'SHWLP-Det'!AC50)) -> 0.21442628 | G22: =('SHWLP-Att'!$AC$12/('SHWLP-Apt'!$AC$12+'SHWLP-Att'!$AC$12+'SHWLP-Det'!$AC$12+'SHWLP-Apt'!$AC$38+'SHWLP-Att'!$AC$38+'SHWLP-Det'!$AC$38+'SHWLP-Apt'!AC24+'SHWLP-Apt'!AC50+'SHWLP-Att'!AC24+'SHWLP-Att'!AC50+'SHWLP-Det'!AC24+'SHWLP-Det'!AC50)) -> 0.13280396 | H22: =('SHWLP-Det'!$AC$12/('SHWLP-Apt'!$AC$12+'SHWLP-Att'!$AC$12+'SHWLP-Det'!$AC$12+'SHWLP-Apt'!$AC$38+'SHWLP-Att'!$AC$38+'SHWLP-Det'!$AC$38+'SHWLP-Apt'!AC24+'SHWLP-Apt'!AC50+'SHWLP-Att'!AC24+'SHWLP-Att'!AC50+'SHWLP-Det'!AC24+'SHWLP-Det'!AC50)) -> 0.1494104 | I22: =('SHWLP-Apt'!$AC$38/('SHWLP-Apt'!$AC$12+'SHWLP-Att'!$AC$12+'SHWLP-Det'!$AC$12+'SHWLP-Apt'!$AC$38+'SHWLP-Att'!$AC$38+'SHWLP-Det'!$AC$38+'SHWLP-Apt'!AC50)) -> 0.34644334 | J22: =('SHWLP-Att'!$AC$38/('SHWLP-Apt'!$AC$12+'SHWLP-Att'!$AC$12+'SHWLP-Det'!$AC$12+'SHWLP-Apt'!$AC$38+'SHWLP-Att'!$AC$38+'SHWLP-Det'!$AC$38+'SHWLP-Att'!AC50)) -> 0.15691601 | K22: =('SHWLP-Det'!$AC$38/('SHWLP-Apt'!$AC$12+'SHWLP-Att'!$AC$12+'SHWLP-Det'!$AC$12+'SHWLP-Apt'!$AC$38+'SHWLP-Att'!$AC$38+'SHWLP-Det'!$AC$38+'SHWLP-Det'!AC50)) -> 0 | Y22: =SUM(F22:X22) -> 1 | Z22: =C22 -> 1.1669029 | AA22: =ABS(Z22+Z27-Y22-Y27)/(Z22+Z27) -> 0.14303065 | AD22: =AJ8+AJ18+AJ24 -> 2.2054176 | AE22: =ABS(AD22-Y22)/SUM(AD22+AD27) -> 0.54657113 | AI22: RSDETH | AJ22: 2.1879413e-05
A23: ETH | B23: Ethanol | C23: ='EB2018'!AI56*RSD_Balance!B4*0.5 -> 0 | E23: BIOETH | F23: ='SHWLP-Apt'!$AC$9 -> 0 | G23: ='SHWLP-Att'!$AC$9 -> 0 | H23: ='SHWLP-Det'!$AC$9 -> 0 | I23: ='SHWLP-Apt'!$AC$35 -> 0 | J23: ='SHWLP-Att'!$AC$35 -> 0 | K23: ='SHWLP-Det'!$AC$35 -> 0 | Y23: =SUM(F23:X23) -> 0 | Z23: =C23 -> 0 | AI23: RSDGAS | AJ23: 6.313541
A24: BDL | B24: Biodiesel | C24: ='EB2018'!AI56*RSD_Balance!B4*0.5 -> 0 | E24: BIODST | F24: ='SHWLP-Apt'!$AC$8 -> 0 | G24: ='SHWLP-Att'!$AC$8 -> 0 | H24: ='SHWLP-Det'!$AC$8 -> 0 | I24: ='SHWLP-Apt'!$AC$34 -> 0 | J24: ='SHWLP-Att'!$AC$34 -> 0 | K24: ='SHWLP-Det'!$AC$34 -> 0 | Y24: =SUM(F24:X24) -> 0 | Z24: =C24 -> 0 | AI24: RSDHET | AJ24: 0.002385329
A25: BIOSLU | B25: ='EB2018'!AN1 -> Non-Renewable Waste | C25: ='EB2018'!AN56*RSD_Balance!B4 -> 0 | E25: BIOSLU | Y25: =SUM(F25:X25) -> 0 | Z25: =C25 -> 0 | AI25: RSDKER | AJ25: 9.9062996
A26: ELC | B26: ='EB2018'!AO1 -> Electricity | C26: ='EB2018'!AO56*RSD_Balance!B4 -> 29.43089 | E26: ELC | F26: ='SHWLP-Apt'!$AC$11+'SHWLP-Apt'!$AC$13 -> 0.66757192 | G26: ='SHWLP-Att'!$AC$11+'SHWLP-Att'!$AC$13 -> 1.0838903 | H26: ='SHWLP-Det'!$AC$11+'SHWLP-Det'!$AC$13 -> 1.589426 | I26: ='SHWLP-Apt'!$AC$37+'SHWLP-Apt'!$AC$39 -> 0.69372778 | J26: ='SHWLP-Att'!$AC$37+'SHWLP-Att'!$AC$39 -> 0.56457084 | K26: ='SHWLP-Det'!$AC$37+'SHWLP-Det'!$AC$39 -> 0 | L26: ='SHWLP-Apt'!$AC$59 -> 0.34353539 | M26: ='SHWLP-Att'!$AC$59 -> 1.8080719 | N26: ='SHWLP-Det'!$AC$59 -> 2.7736752 | O26: ='SHWLP-Apt'!$AC$60 -> 0.070788487 | P26: ='SHWLP-Att'!$AC$60 -> 0.5006851 | Q26: ='SHWLP-Det'!$AC$60 -> 0.57732325 | R26: 2.0517341 | S26: =(T38*0.0000000036)*(DwellingStocks!L28*RSD_Balance!U38) -> 1.4430683 | T26: =(T36*0.0000000036)*(DwellingStocks!L28*RSD_Balance!U36) -> 1.1268114 | U26: =(T37*0.0000000036)*(DwellingStocks!L28*RSD_Balance!U37) -> 1.7528219 | V26: =(T39*0.0000000036)*(DwellingStocks!L28*RSD_Balance!U39) -> 1.2125522 | W26: 10.843444 | X26: 0 | Y26: =SUM(F26:X26) -> 29.103698 | Z26: =C26 -> 29.43089 | AA26: =ABS(Z26-Y26)/Z26 -> 0.011117318 | AD26: =AJ10+AJ21+AO6+AO7+AO8+AO10+AO11+AO12+AR6+AR15+AR16+AR17+AR18+AR19 -> 31.036473 | AE26: =ABS(AD26-Y26)/AD26 -> 0.062274316 | AI26: RSDLPG | AJ26: 0.46564568
A27: HET | B27: ='EB2018'!AP1 -> Heat | C27: ='EB2018'!AP56*RSD_Balance!B4 -> 0 | E27: HET | F27: ='SHWLP-Apt'!$AC$24 -> 0 | G27: ='SHWLP-Att'!$AC$24 -> 0 | H27: ='SHWLP-Det'!$AC$24 -> 0 | I27: ='SHWLP-Apt'!$AC$50 -> 0 | J27: ='SHWLP-Att'!$AC$50 -> 0 | K27: ='SHWLP-Det'!$AC$50 -> 0 | Y27: =SUM(F27:X27) -> 0 | Z27: =C27 -> 0 | AA27: =ABS(Z22+Z27-Y22-Y27)/(Z22+Z27) -> 0.14303065 | AI27: RSDPEA | AJ27: 0.79843754
B28: Total | C28: =SUM(C9:C27) -> 127.53921 | E28: SMF | F28: =SUM('SHWLP-Apt'!AC20:AC22) -> 0 | G28: =SUM('SHWLP-Att'!AC20:AC22) -> 2.5661545 | H28: =SUM('SHWLP-Det'!AC20:AC22) -> 6.694108 | I28: =SUM('SHWLP-Apt'!AC46:AC48) -> 0 | J28: =SUM('SHWLP-Att'!AC46:AC48) -> 0.48505892 | K28: =SUM('SHWLP-Det'!AC46:AC48) -> 0.51849275 | Y28: =SUM(F28:K28) -> 10.263814 | AI28: RSDSOL | AJ28: 0.56017671
F29: =SUM(F9:F27) -> 2.4155752 | G29: =SUM(G9:G27) -> 29.219026 | H29: =SUM(H9:H27) -> 50.51789 | I29: =SUM(I9:I27) -> 1.675344 | J29: =SUM(J9:J27) -> 9.0600458 | K29: =SUM(K9:K27) -> 10.70279 | L29: =SUM(L9:L27) -> 0.34353539 | M29: =SUM(M9:M27) -> 1.8080719 | ... Z29: =SUM(Z9:Z27) -> 127.53921 | AA29: =ABS(Z29-Y29)/Z29 -> 0.0099216072 | AD29: =SUM(AD9:AD27) -> 122.91503 | AI29: RSDWOO | AJ29: 0.14674631
F30: =SUM(F29:H29) -> 82.152491 | G30: =F30/$Y$29 -> 0.63780711 | I30: =SUM(I29:K29) -> 21.43818 | J30: =I30/$Y$29 -> 0.16643955 | L30: =SUM(L29:N29) -> 4.9252825 | M30: =L30/$Y$29 -> 0.038238404 | O30: =SUM(O29:Q29) -> 1.1487968 | P30: =O30/$Y$29 -> 0.0089189114 | R30: =R29/$Y$29 -> 0.021436776 | S30: =SUM(S29:X29) -> 16.378697 | T30: =S30/$Y$29 -> 0.12715926 | Y30: =T30+R30+P30++M30+J30+G30 -> 1
Y33: =F7 -> Space Heating | Z33: =F30 -> 82.152491
Y34: =I7 -> Water Heating | Z34: =I30 -> 21.43818
S35: Item | T35: kWh/yr/unit | U35: Ownership | Y35: =O7 -> Pumps & Fans | Z35: =O30 -> 1.1487968
R36: Cloth Washing | T36: 185 | U36: 0.975 | Y36: =L7 -> Lighting | Z36: =L30 -> 4.9252825
R37: Cloth Drying | T37: 433 | U37: 0.648 | Y37: =R7 -> Cooking | Z37: =R29 -> 2.7611555
R38: Refrigeration | T38: 231 | U38: 1 | Y38: =S7 -> Appliances | Z38: =S30 -> 16.378697
R39: Dish Washing | T39: 300 | U39: 0.647

Sheet Fuel-Age_Adj
B3: Summary without Fuels | CA3: E1055: | CI3: E1008
B4: BER Database (Fuel-Age) | O4: CSO Database 2016 (Fuel-Age) | CA4: CSO Database 2016
B6: Year_of_Construction (group) | C6: Apartments | D6: Attached | E6: Detached | O6: Year_of_Construction (group) | P6: Apartments | Q6: Attached | R6: Detached | CA6: Private Households in Permanent Housing Units 2011 to 2016 (Number) by | CI6: Private Households in Permanent Housing Units 2011 to 2016 (Number) by | CQ6: Private Households in Permanent Housing Units 2011 to 2016 (Number) by
B7: Before_1919 | C7: 6094 | D7: 22883 | E7: 21159 | F7: =SUM(C7:E7) -> 50136 | O7: Before 1919 | P7: =CE76+CE64+CE88 -> 13706 | Q7: =CE39+CE52 -> 52434 | R7: =CE27 -> 74125 | S7: =SUM(P7:R7) -> 140265 | CA7: Persons per Household, Aggregate Town or Rural Area, Type of Private | CI7: Persons per Household, Aggregate Town or Rural Area, Type of Private | CQ7: Aggregate Town or Rural Area, Period in which Built, Type of Private
B8: 1919-1945 | C8: 2800 | D8: 26844 | E8: 16032 | F8: =SUM(C8:E8) -> 45676 | O8: 1919 to 1945 | P8: =CE77+CE65+CE89 -> 5393 | Q8: =CE40+CE53 -> 56743 | R8: =CE28 -> 46847 | S8: =SUM(P8:R8) -> 108983 | CA8: Accommodation, Period in which Built and Census Year | CI8: Accommodation, Type of Central Heating and Census Year | CQ8: Accommodation, Type of Central Heating and Census Year
B9: 1946-1960 | C9: 2187 | D9: 33473 | E9: 14682 | F9: =SUM(C9:E9) -> 50342 | O9: 1946 to 1960 | P9: =CE78+CE66+CE90 -> 5389 | Q9: =CE42+CE54 -> 77531 | R9: =CE29 -> 42427 | S9: =SUM(P9:R9) -> 125347
B10: 1961-1970 | C10: 2486 | D10: 24851 | E10: 14478 | F10: =SUM(C10:E10) -> 41815 | O10: 1961 to 1970 | P10: =CE79+CE67+CE91 -> 5420 | Q10: =CE43+CE55 -> 67734 | R10: =CE30 -> 42221 | S10: =SUM(P10:R10) -> 115375 | CE10: 2016 | CM10: 2016 | CU10: 2016
B11: 1971-1980 | C11: 3677 | D11: 51695 | E11: 35579 | F11: =SUM(C11:E11) -> 90951 | O11: 1971 to 1980 | P11: =CE80+CE68+CE92 -> 7201 | Q11: =CE44+CE56 -> 107453 | R11: =CE31 -> 97698 | S11: =SUM(P11:R11) -> 212352 | CA11: All private households | CI11: All private households | CQ11: State
B12: 1981-1990 | C12: 6342 | D12: 43624 | E12: 33190 | F12: =SUM(C12:E12) -> 83156 | O12: 1981 to 1990 | P12: =CE81+CE69+CE93 -> 10485 | Q12: =CE45+CE57 -> 73079 | R12: =CE32 -> 86491 | S12: =SUM(P12:R12) -> 170055 | CB12: State | CJ12: State | CR12: Before 1919
B13: 1991-2000 | C13: 25354 | D13: 64118 | E13: 50159 | F13: =SUM(C13:E13) -> 139631 | O13: 1991 to 2000 | P13: =CE82+CE70+CE94 -> 28780 | Q13: =CE46+CE58 -> 99598 | R13: =CE33 -> 111455 | S13: =SUM(P13:R13) -> 239833 | CC13: All households | CK13: All households | CR13: Before 1919 | CS13: All households
B14: 2001-2010 | C14: 78381 | D14: 115507 | E14: 69518 | F14: =SUM(C14:E14) -> 263406 | O14: 2001 to 2010 | P14: =CE83+CE71+CE95 -> 86920 | Q14: =CE47+CE59 -> 167551 | R14: =CE34 -> 175223 | S14: =SUM(P14:R14) -> 429694 | CD14: All years | CE14: 1697665 | CL14: All households | CM14: 1697665 | CR14: Before 1919 | CT14: All households | CU14: 141200
B15: Later_2010 | C15: 7476 | D15: 31963 | E15: 10694 | F15: =SUM(C15:E15) -> 50133 | O15: 2011 or later | P15: =CE84+CE72+CE96 -> 6124 | Q15: =CE48+CE60 -> 9027 | R15: =CE35 -> 18050 | S15: =SUM(P15:R15) -> 33201 | CD15: Before 1919 | CE15: 141200 | CL15: No central heating | CM15: 23174 | CR15: Before 1919 | CT15: No central heating | CU15: 6507
B16: Total | C16: =SUM(C7:C15) -> 134797 | D16: =SUM(D7:D15) -> 414958 | E16: =SUM(E7:E15) -> 265491 | F16: =SUM(C16:E16) -> 815246 | O16: Total | P16: =SUM(P7:P15) -> 169418 | Q16: =SUM(Q7:Q15) -> 711150 | R16: =SUM(R7:R15) -> 694537 | S16: =SUM(P16:R16) -> 1575105 | CD16: 1919 to 1945 | CE16: 109668 | CL16: Oil | CM16: 686004 | CR16: Before 1919 | CT16: Oil | CU16: 59339
CD17: 1946 to 1960 | CE17: 126107 | CL17: Natural Gas | CM17: 569166 | CR17: Before 1919 | CT17: Natural Gas | CU17: 32118
B18: Summary with Fuels | AB18: Data from Tableau | AY18: Data used in DwellingStocks Tab | BL18: Data only used to crosscheck in SHWLP-*** Tabs | CD18: 1961 to 1970 | CE18: 116041 | CL18: Electricity | CM18: 146302 | CR18: Before 1919 | CT18: Electricity | CU18: 13175
B19: BER Database (Fuel-Age) | O19: CSO Database 2016 (Fuel-Age) | AB19: BER Database (Rating to Age) | AN19: Correlation (Rating to Age) | AY19: Housing Stock based upon Age to BER correlation index | BL19: BER Rating/Fuel Type | CD19: 1971 to 1980 | CE19: 213473 | CL19: Coal (incl. Anthracite_Coal) | CM19: 86611 | CR19: Before 1919 | CT19: Coal (incl. Anthracite_Coal) | CU19: 10093
B20: Summary with Fuels | CD20: 1981 to 1990 | CE20: 171044 | CL20: Peat (incl. turf) | CM20: 90029 | CR20: Before 1919 | CT20: Peat (incl. turf) | CU20: 10892
B21: Apartments | C21: No central heating | D21: Oil | E21: Natural Gas | F21: Electricity | G21: Coal (incl. Anthracite_Coal) | H21: Peat (incl. turf) | I21: Liquid Petroleum Gas (LPG) | J21: Wood (incl. wood pellets) | K21: Other fuels | L21: Not stated | M21: Totals | O21: Apartments | P21: No central heating | Q21: Oil | R21: Natural Gas | S21: Electricity | T21: Coal (incl. Anthracite_Coal) | U21: Peat (incl. turf) | V21: Liquid Petroleum Gas (LPG) | W21: Wood (incl. wood pellets) | X21: Other fuels | Y21: Not stated | AC21: A | AD21: B1 | AE21: B2 | AF21: B3 | AG21: C | AH21: D | AI21: E | AJ21: F | AK21: G | AN21: Apartments | AO21: A | AP21: B1 | AQ21: B2 | AR21: B3 | AS21: C | AT21: D | AU21: E | AV21: F | AW21: G | AY21: Apartments | AZ21: A | BA21: B1 | BB21: B2 | BC21: B3 | BD21: C | BE21: D | BF21: E | BG21: F | BH21: G | BL21: Apartments | BM21: No central heating | BN21: Oil | BO21: Natural Gas | BP21: Electricity | BQ21: Coal (incl. Anthracite_Coal) | BR21: Peat (incl. turf) | BS21: Liquid Petroleum Gas (LPG) | BT21: Wood (incl. wood pellets) | BU21: Other fuels | BV21: Not stated | BW21: Solid Multi Fuel | CD21: 1991 to 2000 | CE21: 240811 | CL21: Liquid Petroleum Gas (LPG) | CM21: 9990 | CR21: Before 1919 | CT21: Liquid Petroleum Gas (LPG) | CU21: 830
B22: Before_1919 | D22: =SUMIFS(INDEX(Table5[],,MATCH(B21,Table5[#Headers],0)),Table5[MainSpaceHeatingFuel],"*Oil",Table5[Year_of_Construction (group)],B22) -> 469 | E22: =SUMIFS(INDEX(Table5[],,MATCH(B21,Table5[#Headers],0)),Table5[MainSpaceHeatingFuel],"Mains Gas",Table5[Year_of_Construction (group)],B22) -> 1700 | F22: =SUMIFS(INDEX(Table5[],,MATCH(B21,Table5[#Headers],0)),Table5[MainSpaceHeatingFuel],F21,Table5[Year_of_Construction (group)],B22) -> 3428 | G22: =SUMIFS(INDEX(Table5[],,MATCH(B21,Table5[#Headers],0)),Table5[MainSpaceHeatingFuel],"*Coal",Table5[Year_of_Construction (group)],B22) -> 41 | H22: =SUMIFS(INDEX(Table5[],,MATCH(B21,Table5[#Headers],0)),Table5[MainSpaceHeatingFuel],"*Peat*",Table5[Year_of_Construction (group)],B22) -> 6 | I22: =SUMIFS(INDEX(Table5[],,MATCH(B21,Table5[#Headers],0)),Table5[MainSpaceHeatingFuel],"*LPG*",Table5[Year_of_Construction (group)],B22) -> 31 | J22: =SUMIFS(INDEX(Table5[],,MATCH(B21,Table5[#Headers],0)),Table5[MainSpaceHeatingFuel],"*Wood*",Table5[Year_of_Construction (group)],B22) -> 4 | K22: =SUMIFS(INDEX(Table5[],,MATCH(B21,Table5[#Headers],0)),Table5[MainSpaceHeatingFuel],"*Multi-Fuel*",Table5[Year_of_Construction (group)],B22) -> 52 | L22: =SUMIFS(INDEX(Table5[],,MATCH(B21,Table5[#Headers],0)),Table5[MainSpaceHeatingFuel],"",Table5[Year_of_Construction (group)],B22) -> 363 | M22: =SUM(C22:L22) -> 6094 | O22: Before_1919 | P22: =SUMIFS( CU14:CU96,CT14:CT96, P21, CS14:CS96, O21) -> 941 | Q22: =SUMIFS( CU14:CU96,CT14:CT96, Q21, CS14:CS96, O21) -> 1622 | R22: =SUMIFS( CU14:CU96,CT14:CT96, R21, CS14:CS96, O21) -> 3653 | S22: =SUMIFS( CU14:CU96,CT14:CT96, S21, CS14:CS96, O21) -> 6835 | T22: =SUMIFS( CU14:CU96,CT14:CT96, T21, CS14:CS96, O21) -> 163 | U22: =SUMIFS( CU14:CU96,CT14:CT96, U21, CS14:CS96, O21) -> 75 | V22: =SUMIFS( CU14:CU96,CT14:CT96, V21, CS14:CS96, O21) -> 56 | W22: =SUMIFS( CU14:CU96,CT14:CT96, W21, CS14:CS96, O21) -> 88 | X22: =SUMIFS( CU14:CU96,CT14:CT96, X21, CS14:CS96, O21) -> 92 | Y22: =SUMIFS( CU14:CU96,CT14:CT96, Y21, CS14:CS96, O21) -> 181 | Z22: =SUM(P22:Y22) -> 13706 | AB22: Before_1919 | AC22: 3 | AD22: 13 | AE22: 40 | AF22: 85 | AG22: 527 | AH22: 986 | AI22: 1151 | AJ22: 882 | AK22: 2407 | AL22: =SUM(AC22:AK22) -> 6094 | AN22: Before_1919 | AO22: =AC22/AL22 -> 0.0004922875 | AP22: =AD22/AL22 -> 0.0021332458 | AQ22: =AE22/AL22 -> 0.0065638333 | AR22: =AF22/AL22 -> 0.013948146 | AS22: =AG22/AL22 -> 0.086478503 | AT22: =AH22/AL22 -> 0.16179849 | AU22: =AI22/AL22 -> 0.1888743 | AV22: =AJ22/AL22 -> 0.14473252 | AW22: =AK22/AL22 -> 0.39497867 | AZ22: =AO22*Z22 -> 6.7472924 | BA22: =AP22*$Z$22 -> 29.238267 | BB22: =AQ22*$Z$22 -> 89.963899 | BC22: =AR22*$Z$22 -> 191.17329 | BD22: =AS22*$Z$22 -> 1185.2744 | BE22: =AT22*$Z$22 -> 2217.6101 | BF22: =AU22*$Z$22 -> 2588.7112 | BG22: =AV22*$Z$22 -> 1983.704 | BH22: =AW22*$Z$22 -> 5413.5776 | BL22: A | BM22: =(P22*AO22+P23*AO23+P24*AO24+P25*AO25+P26*AO26+P27*AO27+P28*AO28+P29*AO29+P30*AO30+P31/9)*BX31 -> 183.89796 | BN22: =(Q22*AO22+Q23*AO23+Q24*AO24+Q25*AO25+Q26*AO26+Q27*AO27+Q28*AO28+Q29*AO29+Q30*AO30+Q31/9)*BX31 -> 369.35841 | BO22: =(R22*AO22+R23*AO23+R24*AO24+R25*AO25+R26*AO26+R27*AO27+R28*AO28+R29*AO29+R30*AO30+R31/9)*BX31 -> 3828.3051 | BP22: =(S22*AO22+S23*AO23+S24*AO24+S25*AO25+S26*AO26+S27*AO27+S28*AO28+S29*AO29+S30*AO30+S31/9)*BX31 -> 3682.2436 | BQ22: =(T22*AO22+T23*AO23+T24*AO24+T25*AO25+T26*AO26+T27*AO27+T28*AO28+T29*AO29+T30*AO30+T31/9)*BX31 -> 41.327709 | BR22: =(U22*AO22+U23*AO23+U24*AO24+U25*AO25+U26*AO26+U27*AO27+U28*AO28+U29*AO29+U30*AO30+U31/9)*BX31 -> 22.365812 | BS22: =(V22*AO22+V23*AO23+V24*AO24+V25*AO25+V26*AO26+V27*AO27+V28*AO28+V29*AO29+V30*AO30+V31/9)*BX31 -> 41.233455 | BT22: =(W22*AO22+W23*AO23+W24*AO24+W25*AO25+W26*AO26+W27*AO27+W28*AO28+W29*AO29+W30*AO30+W31/9)*BX31 -> 33.528461 | BU22: =(X22*AO22+X23*AO23+X24*AO24+X25*AO25+X26*AO26+X27*AO27+X28*AO28+X29*AO29+X30*AO30+X31/9)*BX31 -> 120.73024 | BV22: =(Y22*AO22+Y23*AO23+Y24*AO24+Y25*AO25+Y26*AO26+Y27*AO27+Y28*AO28+Y29*AO29+Y30*AO30+Y31/9)*BX31 -> 1335.6949 | BW22: =AVERAGE(BQ22,BR22,BT22)/3 -> 10.802442 | CD22: 2001 to 2010 | CE22: 431763 | CL22: Wood (incl. wood pellets) | CM22: 33976 | CR22: Before 1919 | CT22: Wood (incl. wood pellets) | CU22: 6539
B23: 1919-1945 | D23: =SUMIFS(INDEX(Table5[],,MATCH(B21,Table5[#Headers],0)),Table5[MainSpaceHeatingFuel],"*Oil",Table5[Year_of_Construction (group)],B23) -> 266 | E23: =SUMIFS(INDEX(Table5[],,MATCH(B21,Table5[#Headers],0)),Table5[MainSpaceHeatingFuel],"Mains Gas",Table5[Year_of_Construction (group)],B23) -> 1447 | F23: =SUMIFS(INDEX(Table5[],,MATCH(B21,Table5[#Headers],0)),Table5[MainSpaceHeatingFuel],F21,Table5[Year_of_Construction (group)],B23) -> 952 | G23: =SUMIFS(INDEX(Table5[],,MATCH(B21,Table5[#Headers],0)),Table5[MainSpaceHeatingFuel],"*Coal",Table5[Year_of_Construction (group)],B23) -> 18 | H23: =SUMIFS(INDEX(Table5[],,MATCH(B21,Table5[#Headers],0)),Table5[MainSpaceHeatingFuel],"*Peat*",Table5[Year_of_Construction (group)],B23) -> 1 | I23: =SUMIFS(INDEX(Table5[],,MATCH(B21,Table5[#Headers],0)),Table5[MainSpaceHeatingFuel],"*LPG*",Table5[Year_of_Construction (group)],B23) -> 21 | J23: =SUMIFS(INDEX(Table5[],,MATCH(B21,Table5[#Headers],0)),Table5[MainSpaceHeatingFuel],"*Wood*",Table5[Year_of_Construction (group)],B23) -> 0 | K23: =SUMIFS(INDEX(Table5[],,MATCH(B21,Table5[#Headers],0)),Table5[MainSpaceHeatingFuel],"*Multi-Fuel*",Table5[Year_of_Construction (group)],B23) -> 36 | L23: =SUMIFS(INDEX(Table5[],,MATCH(B21,Table5[#Headers],0)),Table5[MainSpaceHeatingFuel],"",Table5[Year_of_Construction (group)],B23) -> 59 | M23: =SUM(C23:L23) -> 2800 | O23: 1919-1945 | P23: =SUMIFS( CU110:CU181,CT110:CT181, P21, CS110:CS181, O21) -> 234 | Q23: =SUMIFS( CU110:CU181,CT110:CT181, Q21, CS110:CS181, O21) -> 575 | R23: =SUMIFS( CU110:CU181,CT110:CT181, R21, CS110:CS181, O21) -> 2069 | S23: =SUMIFS( CU110:CU181,CT110:CT181, S21, CS110:CS181, O21) -> 2235 | T23: =SUMIFS( CU110:CU181,CT110:CT181, T21, CS110:CS181, O21) -> 99 | U23: =SUMIFS( CU110:CU181,CT110:CT181, U21, CS110:CS181, O21) -> 43 | V23: =SUMIFS( CU110:CU181,CT110:CT181, V21, CS110:CS181, O21) -> 11 | W23: =SUMIFS( CU110:CU181,CT110:CT181, W21, CS110:CS181, O21) -> 29 | X23: =SUMIFS( CU110:CU181,CT110:CT181, X21, CS110:CS181, O21) -> 39 | Y23: =SUMIFS( CU110:CU181,CT110:CT181, Y21, CS110:CS181, O21) -> 59 | Z23: =SUM(P23:Y23) -> 5393 | AB23: 1919-1945 | AC23: 2 | AD23: 21 | AE23: 128 | AF23: 193 | AG23: 461 | AH23: 497 | AI23: 452 | AJ23: 308 | AK23: 738 | AL23: =SUM(AC23:AK23) -> 2800 | AN23: 1919-1945 | AO23: =AC23/AL23 -> 0.00071428571 | AP23: =AD23/AL23 -> 0.0075 | AQ23: =AE23/AL23 -> 0.045714286 | AR23: =AF23/AL23 -> 0.068928571 | AS23: =AG23/AL23 -> 0.16464286 | AT23: =AH23/AL23 -> 0.1775 | AU23: =AI23/AL23 -> 0.16142857 | AV23: =AJ23/AL23 -> 0.11 | AW23: =AK23/AL23 -> 0.26357143 | AZ23: =AO23*$Z23 -> 3.8521429 | BA23: =AP23*$Z$23 -> 40.4475 | BB23: =AQ23*$Z$23 -> 246.53714 | BC23: =AR23*$Z$23 -> 371.73179 | BD23: =AS23*$Z$23 -> 887.91893 | BE23: =AT23*$Z$23 -> 957.2575 | BF23: =AU23*$Z$23 -> 870.58429 | BG23: =AV23*$Z$23 -> 593.23 | BH23: =AW23*$Z$23 -> 1421.4407 | BL23: B1 | BM23: =(P22*AP22+P23*AP23+P24*AP24+P25*AP25+P26*AP26+P27*AP27+P28*AP28+P29*AP29+P30*AP30+P31/9)*BX31 -> 166.32489 | BN23: =(Q22*AP22+Q23*AP23+Q24*AP24+Q25*AP25+Q26*AP26+Q27*AP27+Q28*AP28+Q29*AP29+Q30*AP30+Q31/9)*BX31 -> 252.2461 | BO23: =(R22*AP22+R23*AP23+R24*AP24+R25*AP25+R26*AP26+R27*AP27+R28*AP28+R29*AP29+R30*AP30+R31/9)*BX31 -> 2661.9095 | BP23: =(S22*AP22+S23*AP23+S24*AP24+S25*AP25+S26*AP26+S27*AP27+S28*AP28+S29*AP29+S30*AP30+S31/9)*BX31 -> 3140.8766 | BQ23: =(T22*AP22+T23*AP23+T24*AP24+T25*AP25+T26*AP26+T27*AP27+T28*AP28+T29*AP29+T30*AP30+T31/9)*BX31 -> 37.24799 | BR23: =(U22*AP22+U23*AP23+U24*AP24+U25*AP25+U26*AP26+U27*AP27+U28*AP28+U29*AP29+U30*AP30+U31/9)*BX31 -> 13.343719 | BS23: =(V22*AP22+V23*AP23+V24*AP24+V25*AP25+V26*AP26+V27*AP27+V28*AP28+V29*AP29+V30*AP30+V31/9)*BX31 -> 25.546659 | BT23: =(W22*AP22+W23*AP23+W24*AP24+W25*AP25+W26*AP26+W27*AP27+W28*AP28+W29*AP29+W30*AP30+W31/9)*BX31 -> 14.5357 | BU23: =(X22*AP22+X23*AP23+X24*AP24+X25*AP25+X26*AP26+X27*AP27+X28*AP28+X29*AP29+X30*AP30+X31/9)*BX31 -> 51.13593 | BV23: =(Y22*AP22+Y23*AP23+Y24*AP24+Y25*AP25+Y26*AP26+Y27*AP27+Y28*AP28+Y29*AP29+Y30*AP30+Y31/9)*BX31 -> 1286.0232 | BW23: =AVERAGE(BQ23,BR23,BT23)/3 -> 7.2363787 | CD23: 2011 or later | CE23: 33436 | CL23: Other fuels | CM23: 11068 | CR23: Before 1919 | CT23: Other fuels | CU23: 744
B24: 1946-1960 | D24: =SUMIFS(INDEX(Table5[],,MATCH(B21,Table5[#Headers],0)),Table5[MainSpaceHeatingFuel],"*Oil",Table5[Year_of_Construction (group)],B24) -> 241 | E24: =SUMIFS(INDEX(Table5[],,MATCH(B21,Table5[#Headers],0)),Table5[MainSpaceHeatingFuel],"Mains Gas",Table5[Year_of_Construction (group)],B24) -> 1283 | F24: =SUMIFS(INDEX(Table5[],,MATCH(B21,Table5[#Headers],0)),Table5[MainSpaceHeatingFuel],F21,Table5[Year_of_Construction (group)],B24) -> 561 | G24: =SUMIFS(INDEX(Table5[],,MATCH(B21,Table5[#Headers],0)),Table5[MainSpaceHeatingFuel],"*Coal",Table5[Year_of_Construction (group)],B24) -> 16 | H24: =SUMIFS(INDEX(Table5[],,MATCH(B21,Table5[#Headers],0)),Table5[MainSpaceHeatingFuel],"*Peat*",Table5[Year_of_Construction (group)],B24) -> 1 | I24: =SUMIFS(INDEX(Table5[],,MATCH(B21,Table5[#Headers],0)),Table5[MainSpaceHeatingFuel],"*LPG*",Table5[Year_of_Construction (group)],B24) -> 15 | J24: =SUMIFS(INDEX(Table5[],,MATCH(B21,Table5[#Headers],0)),Table5[MainSpaceHeatingFuel],"*Wood*",Table5[Year_of_Construction (group)],B24) -> 3 | K24: =SUMIFS(INDEX(Table5[],,MATCH(B21,Table5[#Headers],0)),Table5[MainSpaceHeatingFuel],"*Multi-Fuel*",Table5[Year_of_Construction (group)],B24) -> 24 | L24: =SUMIFS(INDEX(Table5[],,MATCH(B21,Table5[#Headers],0)),Table5[MainSpaceHeatingFuel],"",Table5[Year_of_Construction (group)],B24) -> 43 | M24: =SUM(C24:L24) -> 2187 | O24: 1946-1960 | P24: =SUMIFS( CU195:CU266,CT195:CT266, P21, CS195:CS266, O21) -> 212 | Q24: =SUMIFS( CU195:CU266,CT195:CT266, Q21, CS195:CS266, O21) -> 505 | R24: =SUMIFS( CU195:CU266,CT195:CT266, R21, CS195:CS266, O21) -> 2730 | S24: =SUMIFS( CU195:CU266,CT195:CT266, S21, CS195:CS266, O21) -> 1710 | T24: =SUMIFS( CU195:CU266,CT195:CT266, T21, CS195:CS266, O21) -> 98 | U24: =SUMIFS( CU195:CU266,CT195:CT266, U21, CS195:CS266, O21) -> 37 | V24: =SUMIFS( CU195:CU266,CT195:CT266, V21, CS195:CS266, O21) -> 12 | W24: =SUMIFS( CU195:CU266,CT195:CT266, W21, CS195:CS266, O21) -> 19 | X24: =SUMIFS( CU195:CU266,CT195:CT266, X21, CS195:CS266, O21) -> 30 | Y24: =SUMIFS( CU195:CU266,CT195:CT266, Y21, CS195:CS266, O21) -> 36 | Z24: =SUM(P24:Y24) -> 5389 | AB24: 1946-1960 | AC24: 15 | AD24: 32 | AE24: 95 | AF24: 121 | AG24: 352 | AH24: 456 | AI24: 403 | AJ24: 249 | AK24: 464 | AL24: =SUM(AC24:AK24) -> 2187 | AN24: 1946-1960 | AO24: =AC24/AL24 -> 0.0068587106 | AP24: =AD24/AL24 -> 0.014631916 | AQ24: =AE24/AL24 -> 0.0434385 | AR24: =AF24/AL24 -> 0.055326932 | AS24: =AG24/AL24 -> 0.16095107 | AT24: =AH24/AL24 -> 0.2085048 | AU24: =AI24/AL24 -> 0.18427069 | AV24: =AJ24/AL24 -> 0.1138546 | AW24: =AK24/AL24 -> 0.21216278 | AZ24: =AO24*$Z$24 -> 36.961591 | BA24: =AP24*$Z$24 -> 78.851395 | BB24: =AQ24*$Z$24 -> 234.09008 | BC24: =AR24*$Z$24 -> 298.15684 | BD24: =AS24*$Z$24 -> 867.36534 | BE24: =AT24*$Z$24 -> 1123.6324 | BF24: =AU24*$Z$24 -> 993.03475 | BG24: =AV24*$Z$24 -> 613.56241 | BH24: =AW24*$Z$24 -> 1143.3452 | BL24: B2 | BM24: =(P22*AQ22+P23*AQ23+P24*AQ24+P25*AQ25+P26*AQ26+P27*AQ27+P28*AQ28+P29*AQ29+P30*AQ30+P31/9)*BX31 -> 278.21519 | BN24: =(Q22*AQ22+Q23*AQ23+Q24*AQ24+Q25*AQ25+Q26*AQ26+Q27*AQ27+Q28*AQ28+Q29*AQ29+Q30*AQ30+Q31/9)*BX31 -> 484.56021 | BO24: =(R22*AQ22+R23*AQ23+R24*AQ24+R25*AQ25+R26*AQ26+R27*AQ27+R28*AQ28+R29*AQ29+R30*AQ30+R31/9)*BX31 -> 6017.8273 | BP24: =(S22*AQ22+S23*AQ23+S24*AQ24+S25*AQ25+S26*AQ26+S27*AQ27+S28*AQ28+S29*AQ29+S30*AQ30+S31/9)*BX31 -> 5996.2801 | BQ24: =(T22*AQ22+T23*AQ23+T24*AQ24+T25*AQ25+T26*AQ26+T27*AQ27+T28*AQ28+T29*AQ29+T30*AQ30+T31/9)*BX31 -> 73.446016 | BR24: =(U22*AQ22+U23*AQ23+U24*AQ24+U25*AQ25+U26*AQ26+U27*AQ27+U28*AQ28+U29*AQ29+U30*AQ30+U31/9)*BX31 -> 25.961706 | BS24: =(V22*AQ22+V23*AQ23+V24*AQ24+V25*AQ25+V26*AQ26+V27*AQ27+V28*AQ28+V29*AQ29+V30*AQ30+V31/9)*BX31 -> 54.156589 | BT24: =(W22*AQ22+W23*AQ23+W24*AQ24+W25*AQ25+W26*AQ26+W27*AQ27+W28*AQ28+W29*AQ29+W30*AQ30+W31/9)*BX31 -> 30.357224 | BU24: =(X22*AQ22+X23*AQ23+X24*AQ24+X25*AQ25+X26*AQ26+X27*AQ27+X28*AQ28+X29*AQ29+X30*AQ30+X31/9)*BX31 -> 96.863308 | BV24: =(Y22*AQ22+Y23*AQ23+Y24*AQ24+Y25*AQ25+Y26*AQ26+Y27*AQ27+Y28*AQ28+Y29*AQ29+Y30*AQ30+Y31/9)*BX31 -> 1341.6578 | BW24: =AVERAGE(BQ24,BR24,BT24)/3 -> 14.418327 | CD24: Not stated | CE24: 114122 | CL24: Not stated | CM24: 41345 | CR24: Before 1919 | CT24: Not stated | CU24: 963
B25: 1961-1970 | D25: =SUMIFS(INDEX(Table5[],,MATCH(B21,Table5[#Headers],0)),Table5[MainSpaceHeatingFuel],"*Oil",Table5[Year_of_Construction (group)],B25) -> 219 | E25: =SUMIFS(INDEX(Table5[],,MATCH(B21,Table5[#Headers],0)),Table5[MainSpaceHeatingFuel],"Mains Gas",Table5[Year_of_Construction (group)],B25) -> 1112 | F25: =SUMIFS(INDEX(Table5[],,MATCH(B21,Table5[#Headers],0)),Table5[MainSpaceHeatingFuel],F21,Table5[Year_of_Construction (group)],B25) -> 735 | G25: =SUMIFS(INDEX(Table5[],,MATCH(B21,Table5[#Headers],0)),Table5[MainSpaceHeatingFuel],"*Coal",Table5[Year_of_Construction (group)],B25) -> 17 | H25: =SUMIFS(INDEX(Table5[],,MATCH(B21,Table5[#Headers],0)),Table5[MainSpaceHeatingFuel],"*Peat*",Table5[Year_of_Construction (group)],B25) -> 0 | I25: =SUMIFS(INDEX(Table5[],,MATCH(B21,Table5[#Headers],0)),Table5[MainSpaceHeatingFuel],"*LPG*",Table5[Year_of_Construction (group)],B25) -> 7 | J25: =SUMIFS(INDEX(Table5[],,MATCH(B21,Table5[#Headers],0)),Table5[MainSpaceHeatingFuel],"*Wood*",Table5[Year_of_Construction (group)],B25) -> 1 | K25: =SUMIFS(INDEX(Table5[],,MATCH(B21,Table5[#Headers],0)),Table5[MainSpaceHeatingFuel],"*Multi-Fuel*",Table5[Year_of_Construction (group)],B25) -> 18 | L25: =SUMIFS(INDEX(Table5[],,MATCH(B21,Table5[#Headers],0)),Table5[MainSpaceHeatingFuel],"",Table5[Year_of_Construction (group)],B25) -> 377 | M25: =SUM(C25:L25) -> 2486 | O25: 1961-1970 | P25: =SUMIFS( CU280:CU351,CT280:CT351, P21, CS280:CS351, O21) -> 197 | Q25: =SUMIFS( CU280:CU351,CT280:CT351, Q21, CS280:CS351, O21) -> 506 | R25: =SUMIFS( CU280:CU351,CT280:CT351, R21, CS280:CS351, O21) -> 2560 | S25: =SUMIFS( CU280:CU351,CT280:CT351, S21, CS280:CS351, O21) -> 1879 | T25: =SUMIFS( CU280:CU351,CT280:CT351, T21, CS280:CS351, O21) -> 100 | U25: =SUMIFS( CU280:CU351,CT280:CT351, U21, CS280:CS351, O21) -> 34 | V25: =SUMIFS( CU280:CU351,CT280:CT351, V21, CS280:CS351, O21) -> 15 | W25: =SUMIFS( CU280:CU351,CT280:CT351, W21, CS280:CS351, O21) -> 24 | X25: =SUMIFS( CU280:CU351,CT280:CT351, X21, CS280:CS351, O21) -> 49 | Y25: =SUMIFS( CU280:CU351,CT280:CT351, Y21, CS280:CS351, O21) -> 56 | Z25: =SUM(P25:Y25) -> 5420 | AB25: 1961-1970 | AC25: 24 | AD25: 43 | AE25: 172 | AF25: 183 | AG25: 512 | AH25: 549 | AI25: 369 | AJ25: 238 | AK25: 396 | AL25: =SUM(AC25:AK25) -> 2486 | AN25: 1961-1970 | AO25: =AC25/AL25 -> 0.0096540628 | AP25: =AD25/AL25 -> 0.017296862 | AQ25: =AE25/AL25 -> 0.06918745 | AR25: =AF25/AL25 -> 0.073612228 | AS25: =AG25/AL25 -> 0.20595334 | AT25: =AH25/AL25 -> 0.22083669 | AU25: =AI25/AL25 -> 0.14843121 | AV25: =AJ25/AL25 -> 0.095736122 | AW25: =AK25/AL25 -> 0.15929204 | AZ25: =AO25*$Z$25 -> 52.32502 | BA25: =AP25*$Z$25 -> 93.748994 | BB25: =AQ25*$Z$25 -> 374.99598 | BC25: =AR25*$Z$25 -> 398.97828 | BD25: =AS25*$Z$25 -> 1116.2671 | BE25: =AT25*$Z$25 -> 1196.9348 | BF25: =AU25*$Z$25 -> 804.49718 | BG25: =AV25*$Z$25 -> 518.88978 | BH25: =AW25*$Z$25 -> 863.36283 | BL25: B3 | BM25: =(P22*AR22+P23*AR23+P24*AR24+P25*AR25+P26*AR26+P27*AR27+P28*AR28+P29*AR29+P30*AR30+P31/9)*BX31 -> 379.72922 | BN25: =(Q22*AR22+Q23*AR23+Q24*AR24+Q25*AR25+Q26*AR26+Q27*AR27+Q28*AR28+Q29*AR29+Q30*AR30+Q31/9)*BX31 -> 674.89579 | BO25: =(R22*AR22+R23*AR23+R24*AR24+R25*AR25+R26*AR26+R27*AR27+R28*AR28+R29*AR29+R30*AR30+R31/9)*BX31 -> 8886.4227 | BP25: =(S22*AR22+S23*AR23+S24*AR24+S25*AR25+S26*AR26+S27*AR27+S28*AR28+S29*AR29+S30*AR30+S31/9)*BX31 -> 8702.3459 | BQ25: =(T22*AR22+T23*AR23+T24*AR24+T25*AR25+T26*AR26+T27*AR27+T28*AR28+T29*AR29+T30*AR30+T31/9)*BX31 -> 105.28476 | BR25: =(U22*AR22+U23*AR23+U24*AR24+U25*AR25+U26*AR26+U27*AR27+U28*AR28+U29*AR29+U30*AR30+U31/9)*BX31 -> 36.570564 | BS25: =(V22*AR22+V23*AR23+V24*AR24+V25*AR25+V26*AR26+V27*AR27+V28*AR28+V29*AR29+V30*AR30+V31/9)*BX31 -> 79.903217 | BT25: =(W22*AR22+W23*AR23+W24*AR24+W25*AR25+W26*AR26+W27*AR27+W28*AR28+W29*AR29+W30*AR30+W31/9)*BX31 -> 43.280916 | BU25: =(X22*AR22+X23*AR23+X24*AR24+X25*AR25+X26*AR26+X27*AR27+X28*AR28+X29*AR29+X30*AR30+X31/9)*BX31 -> 134.10174 | BV25: =(Y22*AR22+Y23*AR23+Y24*AR24+Y25*AR25+Y26*AR26+Y27*AR27+Y28*AR28+Y29*AR29+Y30*AR30+Y31/9)*BX31 -> 1389.1839 | BW25: =AVERAGE(BQ25,BR25,BT25)/3 -> 20.570693 | CC25: Detached house | CK25: Detached house | CR25: Before 1919 | CS25: Detached
B26: 1971-1980 | D26: =SUMIFS(INDEX(Table5[],,MATCH(B21,Table5[#Headers],0)),Table5[MainSpaceHeatingFuel],"*Oil",Table5[Year_of_Construction (group)],B26) -> 497 | E26: =SUMIFS(INDEX(Table5[],,MATCH(B21,Table5[#Headers],0)),Table5[MainSpaceHeatingFuel],"Mains Gas",Table5[Year_of_Construction (group)],B26) -> 1796 | F26: =SUMIFS(INDEX(Table5[],,MATCH(B21,Table5[#Headers],0)),Table5[MainSpaceHeatingFuel],F21,Table5[Year_of_Construction (group)],B26) -> 994 | G26: =SUMIFS(INDEX(Table5[],,MATCH(B21,Table5[#Headers],0)),Table5[MainSpaceHeatingFuel],"*Coal",Table5[Year_of_Construction (group)],B26) -> 25 | H26: =SUMIFS(INDEX(Table5[],,MATCH(B21,Table5[#Headers],0)),Table5[MainSpaceHeatingFuel],"*Peat*",Table5[Year_of_Construction (group)],B26) -> 1 | I26: =SUMIFS(INDEX(Table5[],,MATCH(B21,Table5[#Headers],0)),Table5[MainSpaceHeatingFuel],"*LPG*",Table5[Year_of_Construction (group)],B26) -> 34 | J26: =SUMIFS(INDEX(Table5[],,MATCH(B21,Table5[#Headers],0)),Table5[MainSpaceHeatingFuel],"*Wood*",Table5[Year_of_Construction (group)],B26) -> 3 | K26: =SUMIFS(INDEX(Table5[],,MATCH(B21,Table5[#Headers],0)),Table5[MainSpaceHeatingFuel],"*Multi-Fuel*",Table5[Year_of_Construction (group)],B26) -> 71 | L26: =SUMIFS(INDEX(Table5[],,MATCH(B21,Table5[#Headers],0)),Table5[MainSpaceHeatingFuel],"",Table5[Year_of_Construction (group)],B26) -> 256 | M26: =SUM(C26:L26) -> 3677 | O26: 1971-1980 | P26: =SUMIFS( CU365:CU436,CT365:CT436, P21, CS365:CS436, O21) -> 244 | Q26: =SUMIFS( CU365:CU436,CT365:CT436, Q21, CS365:CS436, O21) -> 679 | R26: =SUMIFS( CU365:CU436,CT365:CT436, R21, CS365:CS436, O21) -> 2911 | S26: =SUMIFS( CU365:CU436,CT365:CT436, S21, CS365:CS436, O21) -> 2951 | T26: =SUMIFS( CU365:CU436,CT365:CT436, T21, CS365:CS436, O21) -> 175 | U26: =SUMIFS( CU365:CU436,CT365:CT436, U21, CS365:CS436, O21) -> 48 | V26: =SUMIFS( CU365:CU436,CT365:CT436, V21, CS365:CS436, O21) -> 37 | W26: =SUMIFS( CU365:CU436,CT365:CT436, W21, CS365:CS436, O21) -> 37 | X26: =SUMIFS( CU365:CU436,CT365:CT436, X21, CS365:CS436, O21) -> 62 | Y26: =SUMIFS( CU365:CU436,CT365:CT436, Y21, CS365:CS436, O21) -> 57 | Z26: =SUM(P26:Y26) -> 7201 | AB26: 1971-1980 | AC26: 2 | AD26: 5 | AE26: 79 | AF26: 112 | AG26: 940 | AH26: 1033 | AI26: 747 | AJ26: 371 | AK26: 388 | AL26: =SUM(AC26:AK26) -> 3677 | AN26: 1971-1980 | AO26: =AC26/AL26 -> 0.00054392168 | AP26: =AD26/AL26 -> 0.0013598042 | AQ26: =AE26/AL26 -> 0.021484906 | AR26: =AF26/AL26 -> 0.030459614 | AS26: =AG26/AL26 -> 0.25564319 | AT26: =AH26/AL26 -> 0.28093555 | AU26: =AI26/AL26 -> 0.20315475 | AV26: =AJ26/AL26 -> 0.10089747 | AW26: =AK26/AL26 -> 0.10552081 | AZ26: =AO26*$Z$26 -> 3.91678 | BA26: =AP26*$Z$26 -> 9.79195 | BB26: =AQ26*$Z$26 -> 154.71281 | BC26: =AR26*$Z$26 -> 219.33968 | BD26: =AS26*$Z$26 -> 1840.8866 | BE26: =AT26*$Z$26 -> 2023.0169 | BF26: =AU26*$Z$26 -> 1462.9173 | BG26: =AV26*$Z$26 -> 726.56269 | BH26: =AW26*$Z$26 -> 759.85532 | BL26: C | BM26: =(P22*AS22+P23*AS23+P24*AS24+P25*AS25+P26*AS26+P27*AS27+P28*AS28+P29*AS29+P30*AS30+P31/9)*BX31 -> 1180.8689 | BN26: =(Q22*AS22+Q23*AS23+Q24*AS24+Q25*AS25+Q26*AS26+Q27*AS27+Q28*AS28+Q29*AS29+Q30*AS30+Q31/9)*BX31 -> 2201.4219 | BO26: =(R22*AS22+R23*AS23+R24*AS24+R25*AS25+R26*AS26+R27*AS27+R28*AS28+R29*AS29+R30*AS30+R31/9)*BX31 -> 26520.608 | BP26: =(S22*AS22+S23*AS23+S24*AS24+S25*AS25+S26*AS26+S27*AS27+S28*AS28+S29*AS29+S30*AS30+S31/9)*BX31 -> 27459.054 | BQ26: =(T22*AS22+T23*AS23+T24*AS24+T25*AS25+T26*AS26+T27*AS27+T28*AS28+T29*AS29+T30*AS30+T31/9)*BX31 -> 395.84031 | BR26: =(U22*AS22+U23*AS23+U24*AS24+U25*AS25+U26*AS26+U27*AS27+U28*AS28+U29*AS29+U30*AS30+U31/9)*BX31 -> 131.79057 | BS26: =(V22*AS22+V23*AS23+V24*AS24+V25*AS25+V26*AS26+V27*AS27+V28*AS28+V29*AS29+V30*AS30+V31/9)*BX31 -> 250.02644 | BT26: =(W22*AS22+W23*AS23+W24*AS24+W25*AS25+W26*AS26+W27*AS27+W28*AS28+W29*AS29+W30*AS30+W31/9)*BX31 -> 142.762 | BU26: =(X22*AS22+X23*AS23+X24*AS24+X25*AS25+X26*AS26+X27*AS27+X28*AS28+X29*AS29+X30*AS30+X31/9)*BX31 -> 403.32749 | BV26: =(Y22*AS22+Y23*AS23+Y24*AS24+Y25*AS25+Y26*AS26+Y27*AS27+Y28*AS28+Y29*AS29+Y30*AS30+Y31/9)*BX31 -> 1718.7055 | BW26: =AVERAGE(BQ26,BR26,BT26)/3 -> 74.488098 | CD26: All years | CE26: 715133 | CL26: All households | CM26: 715133 | CN26: =SUM(CM26,CM38,CM51,CM63,CM75,CM87) -> 1675795 | CR26: Before 1919 | CS26: Detached | CT26: All households | CU26: 74125
B27: 1981-1990 | D27: =SUMIFS(INDEX(Table5[],,MATCH(B21,Table5[#Headers],0)),Table5[MainSpaceHeatingFuel],"*Oil",Table5[Year_of_Construction (group)],B27) -> 399 | E27: =SUMIFS(INDEX(Table5[],,MATCH(B21,Table5[#Headers],0)),Table5[MainSpaceHeatingFuel],"Mains Gas",Table5[Year_of_Construction (group)],B27) -> 2009 | F27: =SUMIFS(INDEX(Table5[],,MATCH(B21,Table5[#Headers],0)),Table5[MainSpaceHeatingFuel],F21,Table5[Year_of_Construction (group)],B27) -> 3503 | G27: =SUMIFS(INDEX(Table5[],,MATCH(B21,Table5[#Headers],0)),Table5[MainSpaceHeatingFuel],"*Coal",Table5[Year_of_Construction (group)],B27) -> 85 | H27: =SUMIFS(INDEX(Table5[],,MATCH(B21,Table5[#Headers],0)),Table5[MainSpaceHeatingFuel],"*Peat*",Table5[Year_of_Construction (group)],B27) -> 3 | I27: =SUMIFS(INDEX(Table5[],,MATCH(B21,Table5[#Headers],0)),Table5[MainSpaceHeatingFuel],"*LPG*",Table5[Year_of_Construction (group)],B27) -> 79 | J27: =SUMIFS(INDEX(Table5[],,MATCH(B21,Table5[#Headers],0)),Table5[MainSpaceHeatingFuel],"*Wood*",Table5[Year_of_Construction (group)],B27) -> 4 | K27: =SUMIFS(INDEX(Table5[],,MATCH(B21,Table5[#Headers],0)),Table5[MainSpaceHeatingFuel],"*Multi-Fuel*",Table5[Year_of_Construction (group)],B27) -> 90 | L27: =SUMIFS(INDEX(Table5[],,MATCH(B21,Table5[#Headers],0)),Table5[MainSpaceHeatingFuel],"",Table5[Year_of_Construction (group)],B27) -> 170 | M27: =SUM(C27:L27) -> 6342 | O27: 1981-1990 | P27: =SUMIFS( CU450:CU521,CT450:CT521, P21, CS450:CS521, O21) -> 358 | Q27: =SUMIFS( CU450:CU521,CT450:CT521, Q21, CS450:CS521, O21) -> 672 | R27: =SUMIFS( CU450:CU521,CT450:CT521, R21, CS450:CS521, O21) -> 2926 | S27: =SUMIFS( CU450:CU521,CT450:CT521, S21, CS450:CS521, O21) -> 5984 | T27: =SUMIFS( CU450:CU521,CT450:CT521, T21, CS450:CS521, O21) -> 211 | U27: =SUMIFS( CU450:CU521,CT450:CT521, U21, CS450:CS521, O21) -> 82 | V27: =SUMIFS( CU450:CU521,CT450:CT521, V21, CS450:CS521, O21) -> 56 | W27: =SUMIFS( CU450:CU521,CT450:CT521, W21, CS450:CS521, O21) -> 43 | X27: =SUMIFS( CU450:CU521,CT450:CT521, X21, CS450:CS521, O21) -> 77 | Y27: =SUMIFS( CU450:CU521,CT450:CT521, Y21, CS450:CS521, O21) -> 76 | Z27: =SUM(P27:Y27) -> 10485 | AB27: 1981-1990 | AC27: 1 | AD27: 2 | AE27: 22 | AF27: 158 | AG27: 1445 | AH27: 2044 | AI27: 1642 | AJ27: 657 | AK27: 371 | AL27: =SUM(AC27:AK27) -> 6342 | AN27: 1981-1990 | AO27: =AC27/AL27 -> 0.00015767897 | AP27: =AD27/AL27 -> 0.00031535793 | AQ27: =AE27/AL27 -> 0.0034689372 | AR27: =AF27/AL27 -> 0.024913277 | AS27: =AG27/AL27 -> 0.22784611 | AT27: =AH27/AL27 -> 0.32229581 | AU27: =AI27/AL27 -> 0.25890886 | AV27: =AJ27/AL27 -> 0.10359508 | AW27: =AK27/AL27 -> 0.058498896 | AZ27: =AO27*$Z$27 -> 1.653264 | BA27: =AP27*$Z$27 -> 3.3065279 | BB27: =AQ27*$Z$27 -> 36.371807 | BC27: =AR27*$Z$27 -> 261.2157 | BD27: =AS27*$Z$27 -> 2388.9664 | BE27: =AT27*$Z$27 -> 3379.2715 | BF27: =AU27*$Z$27 -> 2714.6594 | BG27: =AV27*$Z$27 -> 1086.1944 | BH27: =AW27*$Z$27 -> 613.36093 | BL27: D | BM27: =(P22*AT22+P23*AT23+P24*AT24+P25*AT25+P26*AT26+P27*AT27+P28*AT28+P29*AT29+P30*AT30+P31/9)*BX31 -> 1116.84 | BN27: =(Q22*AT22+Q23*AT23+Q24*AT24+Q25*AT25+Q26*AT26+Q27*AT27+Q28*AT28+Q29*AT29+Q30*AT30+Q31/9)*BX31 -> 2038.6991 | BO27: =(R22*AT22+R23*AT23+R24*AT24+R25*AT25+R26*AT26+R27*AT27+R28*AT28+R29*AT29+R30*AT30+R31/9)*BX31 -> 17411.508 | BP27: =(S22*AT22+S23*AT23+S24*AT24+S25*AT25+S26*AT26+S27*AT27+S28*AT28+S29*AT29+S30*AT30+S31/9)*BX31 -> 21560.331 | BQ27: =(T22*AT22+T23*AT23+T24*AT24+T25*AT25+T26*AT26+T27*AT27+T28*AT28+T29*AT29+T30*AT30+T31/9)*BX31 -> 403.01706 | BR27: =(U22*AT22+U23*AT23+U24*AT24+U25*AT25+U26*AT26+U27*AT27+U28*AT28+U29*AT29+U30*AT30+U31/9)*BX31 -> 133.95312 | BS27: =(V22*AT22+V23*AT23+V24*AT24+V25*AT25+V26*AT26+V27*AT27+V28*AT28+V29*AT29+V30*AT30+V31/9)*BX31 -> 178.20458 | BT27: =(W22*AT22+W23*AT23+W24*AT24+W25*AT25+W26*AT26+W27*AT27+W28*AT28+W29*AT29+W30*AT30+W31/9)*BX31 -> 119.61963 | BU27: =(X22*AT22+X23*AT23+X24*AT24+X25*AT25+X26*AT26+X27*AT27+X28*AT28+X29*AT29+X30*AT30+X31/9)*BX31 -> 294.84815 | BV27: =(Y22*AT22+Y23*AT23+Y24*AT24+Y25*AT25+Y26*AT26+Y27*AT27+Y28*AT28+Y29*AT29+Y30*AT30+Y31/9)*BX31 -> 1595.8398 | BW27: =AVERAGE(BQ27,BR27,BT27)/3 -> 72.954422 | CD27: Before 1919 | CE27: 74125 | CL27: No central heating | CM27: 8850 | CR27: Before 1919 | CS27: Detached | CT27: No central heating | CU27: 3486
B28: 1991-2000 | D28: =SUMIFS(INDEX(Table5[],,MATCH(B21,Table5[#Headers],0)),Table5[MainSpaceHeatingFuel],"*Oil",Table5[Year_of_Construction (group)],B28) -> 685 | E28: =SUMIFS(INDEX(Table5[],,MATCH(B21,Table5[#Headers],0)),Table5[MainSpaceHeatingFuel],"Mains Gas",Table5[Year_of_Construction (group)],B28) -> 4626 | F28: =SUMIFS(INDEX(Table5[],,MATCH(B21,Table5[#Headers],0)),Table5[MainSpaceHeatingFuel],F21,Table5[Year_of_Construction (group)],B28) -> 19041 | G28: =SUMIFS(INDEX(Table5[],,MATCH(B21,Table5[#Headers],0)),Table5[MainSpaceHeatingFuel],"*Coal",Table5[Year_of_Construction (group)],B28) -> 62 | H28: =SUMIFS(INDEX(Table5[],,MATCH(B21,Table5[#Headers],0)),Table5[MainSpaceHeatingFuel],"*Peat*",Table5[Year_of_Construction (group)],B28) -> 1 | I28: =SUMIFS(INDEX(Table5[],,MATCH(B21,Table5[#Headers],0)),Table5[MainSpaceHeatingFuel],"*LPG*",Table5[Year_of_Construction (group)],B28) -> 222 | J28: =SUMIFS(INDEX(Table5[],,MATCH(B21,Table5[#Headers],0)),Table5[MainSpaceHeatingFuel],"*Wood*",Table5[Year_of_Construction (group)],B28) -> 1 | K28: =SUMIFS(INDEX(Table5[],,MATCH(B21,Table5[#Headers],0)),Table5[MainSpaceHeatingFuel],"*Multi-Fuel*",Table5[Year_of_Construction (group)],B28) -> 88 | L28: =SUMIFS(INDEX(Table5[],,MATCH(B21,Table5[#Headers],0)),Table5[MainSpaceHeatingFuel],"",Table5[Year_of_Construction (group)],B28) -> 626 | M28: =SUM(C28:L28) -> 25352 | O28: 1991-2000 | P28: =SUMIFS( CU535:CU606,CT535:CT606, P21, CS535:CS606, O21) -> 760 | Q28: =SUMIFS( CU535:CU606,CT535:CT606, Q21, CS535:CS606, O21) -> 1115 | R28: =SUMIFS( CU535:CU606,CT535:CT606, R21, CS535:CS606, O21) -> 7962 | S28: =SUMIFS( CU535:CU606,CT535:CT606, S21, CS535:CS606, O21) -> 18006 | T28: =SUMIFS( CU535:CU606,CT535:CT606, T21, CS535:CS606, O21) -> 298 | U28: =SUMIFS( CU535:CU606,CT535:CT606, U21, CS535:CS606, O21) -> 77 | V28: =SUMIFS( CU535:CU606,CT535:CT606, V21, CS535:CS606, O21) -> 103 | W28: =SUMIFS( CU535:CU606,CT535:CT606, W21, CS535:CS606, O21) -> 59 | X28: =SUMIFS( CU535:CU606,CT535:CT606, X21, CS535:CS606, O21) -> 168 | Y28: =SUMIFS( CU535:CU606,CT535:CT606, Y21, CS535:CS606, O21) -> 232 | Z28: =SUM(P28:Y28) -> 28780 | AB28: 1991-2000 | AC28: 7 | AD28: 41 | AE28: 240 | AF28: 742 | AG28: 7737 | AH28: 9452 | AI28: 5245 | AJ28: 1385 | AK28: 505 | AL28: =SUM(AC28:AK28) -> 25354 | AN28: 1991-2000 | AO28: =AC28/AL28 -> 0.00027609056 | AP28: =AD28/AL28 -> 0.0016171018 | AQ28: =AE28/AL28 -> 0.009465962 | AR28: =AF28/AL28 -> 0.029265599 | AS28: =AG28/AL28 -> 0.30515895 | AT28: =AH28/AL28 -> 0.37280114 | AU28: =AI28/AL28 -> 0.20687071 | AV28: =AJ28/AL28 -> 0.054626489 | AW28: =AK28/AL28 -> 0.019917962 | AZ28: =AO28*$Z$28 -> 7.9458863 | BA28: =AP28*$Z$28 -> 46.540191 | BB28: =AQ28*$Z$28 -> 272.43039 | BC28: =AR28*$Z$28 -> 842.26394 | BD28: =AS28*$Z$28 -> 8782.4746 | BE28: =AT28*$Z$28 -> 10729.217 | BF28: =AU28*$Z$28 -> 5953.7391 | BG28: =AV28*$Z$28 -> 1572.1504 | BH28: =AW28*$Z$28 -> 573.23894 | BL28: E | BM28: =(P22*AU22+P23*AU23+P24*AU24+P25*AU25+P26*AU26+P27*AU27+P28*AU28+P29*AU29+P30*AU30+P31/9)*BX31 -> 798.15519 | BN28: =(Q22*AU22+Q23*AU23+Q24*AU24+Q25*AU25+Q26*AU26+Q27*AU27+Q28*AU28+Q29*AU29+Q30*AU30+Q31/9)*BX31 -> 1443.2033 | BO28: =(R22*AU22+R23*AU23+R24*AU24+R25*AU25+R26*AU26+R27*AU27+R28*AU28+R29*AU29+R30*AU30+R31/9)*BX31 -> 9222.6348 | BP28: =(S22*AU22+S23*AU23+S24*AU24+S25*AU25+S26*AU26+S27*AU27+S28*AU28+S29*AU29+S30*AU30+S31/9)*BX31 -> 12782.81 | BQ28: =(T22*AU22+T23*AU23+T24*AU24+T25*AU25+T26*AU26+T27*AU27+T28*AU28+T29*AU29+T30*AU30+T31/9)*BX31 -> 281.50707 | BR28: =(U22*AU22+U23*AU23+U24*AU24+U25*AU25+U26*AU26+U27*AU27+U28*AU28+U29*AU29+U30*AU30+U31/9)*BX31 -> 96.774994 | BS28: =(V22*AU22+V23*AU23+V24*AU24+V25*AU25+V26*AU26+V27*AU27+V28*AU28+V29*AU29+V30*AU30+V31/9)*BX31 -> 100.24445 | BT28: =(W22*AU22+W23*AU23+W24*AU24+W25*AU25+W26*AU26+W27*AU27+W28*AU28+W29*AU29+W30*AU30+W31/9)*BX31 -> 79.237689 | BU28: =(X22*AU22+X23*AU23+X24*AU24+X25*AU25+X26*AU26+X27*AU27+X28*AU28+X29*AU29+X30*AU30+X31/9)*BX31 -> 171.49774 | BV28: =(Y22*AU22+Y23*AU23+Y24*AU24+Y25*AU25+Y26*AU26+Y27*AU27+Y28*AU28+Y29*AU29+Y30*AU30+Y31/9)*BX31 -> 1447.8115 | BW28: =AVERAGE(BQ28,BR28,BT28)/3 -> 50.835529 | CD28: 1919 to 1945 | CE28: 46847 | CL28: Oil | CM28: 445404 | CR28: Before 1919 | CS28: Detached | CT28: Oil | CU28: 42672
B29: 2001-2010 | D29: =SUMIFS(INDEX(Table5[],,MATCH(B21,Table5[#Headers],0)),Table5[MainSpaceHeatingFuel],"*Oil",Table5[Year_of_Construction (group)],B29) -> 1113 | E29: =SUMIFS(INDEX(Table5[],,MATCH(B21,Table5[#Headers],0)),Table5[MainSpaceHeatingFuel],"Mains Gas",Table5[Year_of_Construction (group)],B29) -> 38133 | F29: =SUMIFS(INDEX(Table5[],,MATCH(B21,Table5[#Headers],0)),Table5[MainSpaceHeatingFuel],F21,Table5[Year_of_Construction (group)],B29) -> 33830 | G29: =SUMIFS(INDEX(Table5[],,MATCH(B21,Table5[#Headers],0)),Table5[MainSpaceHeatingFuel],"*Coal",Table5[Year_of_Construction (group)],B29) -> 27 | H29: =SUMIFS(INDEX(Table5[],,MATCH(B21,Table5[#Headers],0)),Table5[MainSpaceHeatingFuel],"*Peat*",Table5[Year_of_Construction (group)],B29) -> 1 | I29: =SUMIFS(INDEX(Table5[],,MATCH(B21,Table5[#Headers],0)),Table5[MainSpaceHeatingFuel],"*LPG*",Table5[Year_of_Construction (group)],B29) -> 1494 | J29: =SUMIFS(INDEX(Table5[],,MATCH(B21,Table5[#Headers],0)),Table5[MainSpaceHeatingFuel],"*Wood*",Table5[Year_of_Construction (group)],B29) -> 171 | K29: =SUMIFS(INDEX(Table5[],,MATCH(B21,Table5[#Headers],0)),Table5[MainSpaceHeatingFuel],"*Multi-Fuel*",Table5[Year_of_Construction (group)],B29) -> 59 | L29: =SUMIFS(INDEX(Table5[],,MATCH(B21,Table5[#Headers],0)),Table5[MainSpaceHeatingFuel],"",Table5[Year_of_Construction (group)],B29) -> 3552 | M29: =SUM(C29:L29) -> 78380 | O29: 2001-2010 | P29: =SUMIFS( CU620:CU691,CT620:CT691, P21, CS620:CS691, O21) -> 1068 | Q29: =SUMIFS( CU620:CU691,CT620:CT691, Q21, CS620:CS691, O21) -> 2104 | R29: =SUMIFS( CU620:CU691,CT620:CT691, R21, CS620:CS691, O21) -> 45069 | S29: =SUMIFS( CU620:CU691,CT620:CT691, S21, CS620:CS691, O21) -> 36467 | T29: =SUMIFS( CU620:CU691,CT620:CT691, T21, CS620:CS691, O21) -> 255 | U29: =SUMIFS( CU620:CU691,CT620:CT691, U21, CS620:CS691, O21) -> 91 | V29: =SUMIFS( CU620:CU691,CT620:CT691, V21, CS620:CS691, O21) -> 389 | W29: =SUMIFS( CU620:CU691,CT620:CT691, W21, CS620:CS691, O21) -> 175 | X29: =SUMIFS( CU620:CU691,CT620:CT691, X21, CS620:CS691, O21) -> 594 | Y29: =SUMIFS( CU620:CU691,CT620:CT691, Y21, CS620:CS691, O21) -> 708 | Z29: =SUM(P29:Y29) -> 86920 | AB29: 2001-2010 | AC29: 387 | AD29: 2426 | AE29: 7356 | AF29: 11792 | AG29: 33487 | AH29: 15933 | AI29: 5572 | AJ29: 1098 | AK29: 330 | AL29: =SUM(AC29:AK29) -> 78381 | AN29: 2001-2010 | AO29: =AC29/AL29 -> 0.0049374211 | AP29: =AD29/AL29 -> 0.030951379 | AQ29: =AE29/AL29 -> 0.093849275 | AR29: =AF29/AL29 -> 0.15044462 | AS29: =AG29/AL29 -> 0.42723364 | AT29: =AH29/AL29 -> 0.2032763 | AU29: =AI29/AL29 -> 0.071088657 | AV29: =AJ29/AL29 -> 0.014008497 | AW29: =AK29/AL29 -> 0.004210204 | AZ29: =AO29*$Z$29 -> 429.16064 | BA29: =AP29*$Z$29 -> 2690.2938 | BB29: =AQ29*$Z$29 -> 8157.379 | BC29: =AR29*$Z$29 -> 13076.647 | BD29: =AS29*$Z$29 -> 37135.148 | BE29: =AT29*$Z$29 -> 17668.776 | BF29: =AU29*$Z$29 -> 6179.026 | BG29: =AV29*$Z$29 -> 1217.6186 | BH29: =AW29*$Z$29 -> 365.95093 | BL29: F | BM29: =(P22*AV22+P23*AV23+P24*AV24+P25*AV25+P26*AV26+P27*AV27+P28*AV28+P29*AV29+P30*AV30+P31/9)*BX31 -> 448.90541 | BN29: =(Q22*AV22+Q23*AV23+Q24*AV24+Q25*AV25+Q26*AV26+Q27*AV27+Q28*AV28+Q29*AV29+Q30*AV30+Q31/9)*BX31 -> 791.44228 | BO29: =(R22*AV22+R23*AV23+R24*AV24+R25*AV25+R26*AV26+R27*AV27+R28*AV28+R29*AV29+R30*AV30+R31/9)*BX31 -> 3886.9008 | BP29: =(S22*AV22+S23*AV23+S24*AV24+S25*AV25+S26*AV26+S27*AV27+S28*AV28+S29*AV29+S30*AV30+S31/9)*BX31 -> 5829.9075 | BQ29: =(T22*AV22+T23*AV23+T24*AV24+T25*AV25+T26*AV26+T27*AV27+T28*AV28+T29*AV29+T30*AV30+T31/9)*BX31 -> 141.19241 | BR29: =(U22*AV22+U23*AV23+U24*AV24+U25*AV25+U26*AV26+U27*AV27+U28*AV28+U29*AV29+U30*AV30+U31/9)*BX31 -> 50.543396 | BS29: =(V22*AV22+V23*AV23+V24*AV24+V25*AV25+V26*AV26+V27*AV27+V28*AV28+V29*AV29+V30*AV30+V31/9)*BX31 -> 43.015002 | BT29: =(W22*AV22+W23*AV23+W24*AV24+W25*AV25+W26*AV26+W27*AV27+W28*AV28+W29*AV29+W30*AV30+W31/9)*BX31 -> 40.324136 | BU29: =(X22*AV22+X23*AV23+X24*AV24+X25*AV25+X26*AV26+X27*AV27+X28*AV28+X29*AV29+X30*AV30+X31/9)*BX31 -> 79.341354 | BV29: =(Y22*AV22+Y23*AV23+Y24*AV24+Y25*AV25+Y26*AV26+Y27*AV27+Y28*AV28+Y29*AV29+Y30*AV30+Y31/9)*BX31 -> 1333.5285 | BW29: =AVERAGE(BQ29,BR29,BT29)/3 -> 25.784438 | CD29: 1946 to 1960 | CE29: 42427 | CL29: Natural Gas | CM29: 85670 | CR29: Before 1919 | CS29: Detached | CT29: Natural Gas | CU29: 3088
B30: Later_2010 | D30: =SUMIFS(INDEX(Table5[],,MATCH(B21,Table5[#Headers],0)),Table5[MainSpaceHeatingFuel],"*Oil",Table5[Year_of_Construction (group)],B30) -> 34 | E30: =SUMIFS(INDEX(Table5[],,MATCH(B21,Table5[#Headers],0)),Table5[MainSpaceHeatingFuel],"Mains Gas",Table5[Year_of_Construction (group)],B30) -> 2809 | F30: =SUMIFS(INDEX(Table5[],,MATCH(B21,Table5[#Headers],0)),Table5[MainSpaceHeatingFuel],F21,Table5[Year_of_Construction (group)],B30) -> 1307 | G30: =SUMIFS(INDEX(Table5[],,MATCH(B21,Table5[#Headers],0)),Table5[MainSpaceHeatingFuel],"*Coal",Table5[Year_of_Construction (group)],B30) -> 0 | H30: =SUMIFS(INDEX(Table5[],,MATCH(B21,Table5[#Headers],0)),Table5[MainSpaceHeatingFuel],"*Peat*",Table5[Year_of_Construction (group)],B30) -> 0 | I30: =SUMIFS(INDEX(Table5[],,MATCH(B21,Table5[#Headers],0)),Table5[MainSpaceHeatingFuel],"*LPG*",Table5[Year_of_Construction (group)],B30) -> 3 | J30: =SUMIFS(INDEX(Table5[],,MATCH(B21,Table5[#Headers],0)),Table5[MainSpaceHeatingFuel],"*Wood*",Table5[Year_of_Construction (group)],B30) -> 0 | K30: =SUMIFS(INDEX(Table5[],,MATCH(B21,Table5[#Headers],0)),Table5[MainSpaceHeatingFuel],"*Multi-Fuel*",Table5[Year_of_Construction (group)],B30) -> 0 | L30: =SUMIFS(INDEX(Table5[],,MATCH(B21,Table5[#Headers],0)),Table5[MainSpaceHeatingFuel],"",Table5[Year_of_Construction (group)],B30) -> 3321 | M30: =SUM(C30:L30) -> 7474 | O30: Later_2010 | P30: =SUMIFS( CU705:CU776,CT705:CT776, P21, CS705:CS776, O21) -> 73 | Q30: =SUMIFS( CU705:CU776,CT705:CT776, Q21, CS705:CS776, O21) -> 257 | R30: =SUMIFS( CU705:CU776,CT705:CT776, R21, CS705:CS776, O21) -> 3310 | S30: =SUMIFS( CU705:CU776,CT705:CT776, S21, CS705:CS776, O21) -> 2167 | T30: =SUMIFS( CU705:CU776,CT705:CT776, T21, CS705:CS776, O21) -> 19 | U30: =SUMIFS( CU705:CU776,CT705:CT776, U21, CS705:CS776, O21) -> 17 | V30: =SUMIFS( CU705:CU776,CT705:CT776, V21, CS705:CS776, O21) -> 36 | W30: =SUMIFS( CU705:CU776,CT705:CT776, W21, CS705:CS776, O21) -> 33 | X30: =SUMIFS( CU705:CU776,CT705:CT776, X21, CS705:CS776, O21) -> 117 | Y30: =SUMIFS( CU705:CU776,CT705:CT776, Y21, CS705:CS776, O21) -> 95 | Z30: =SUM(P30:Y30) -> 6124 | AB30: Later_2010 | AC30: 5978 | AD30: 626 | AE30: 533 | AF30: 184 | AG30: 105 | AH30: 29 | AI30: 14 | AJ30: 3 | AK30: 4 | AL30: =SUM(AC30:AK30) -> 7476 | AN30: Later_2010 | AO30: =AC30/AL30 -> 0.79962547 | AP30: =AD30/AL30 -> 0.083734617 | AQ30: =AE30/AL30 -> 0.07129481 | AR30: =AF30/AL30 -> 0.024612092 | AS30: =AG30/AL30 -> 0.014044944 | AT30: =AH30/AL30 -> 0.0038790797 | AU30: =AI30/AL30 -> 0.0018726592 | AV30: =AJ30/AL30 -> 0.00040128411 | AW30: =AK30/AL30 -> 0.00053504548 | AZ30: =AO30*$Z$30 -> 4896.9064 | BA30: =AP30*$Z$30 -> 512.7908 | BB30: =AQ30*$Z$30 -> 436.60942 | BC30: =AR30*$Z$30 -> 150.72445 | BD30: =AS30*$Z$30 -> 86.011236 | BE30: =AT30*$Z$30 -> 23.755484 | BF30: =AU30*$Z$30 -> 11.468165 | BG30: =AV30*$Z$30 -> 2.4574639 | BH30: =AW30*$Z$30 -> 3.2766185 | BL30: G | BM30: =(P22*AW22+P23*AW23+P24*AW24+P25*AW25+P26*AW26+P27*AW27+P28*AW28+P29*AW29+P30*AW30+P31/9)*BX31 -> 711.64585 | BN30: =(Q22*AW22+Q23*AW23+Q24*AW24+Q25*AW25+Q26*AW26+Q27*AW27+Q28*AW28+Q29*AW29+Q30*AW30+Q31/9)*BX31 -> 1299.993 | BO30: =(R22*AW22+R23*AW23+R24*AW24+R25*AW25+R26*AW26+R27*AW27+R28*AW28+R29*AW29+R30*AW30+R31/9)*BX31 -> 4745.9525 | BP30: =(S22*AW22+S23*AW23+S24*AW24+S25*AW25+S26*AW26+S27*AW27+S28*AW28+S29*AW29+S30*AW30+S31/9)*BX31 -> 6975.6863 | BQ30: =(T22*AW22+T23*AW23+T24*AW24+T25*AW25+T26*AW26+T27*AW27+T28*AW28+T29*AW29+T30*AW30+T31/9)*BX31 -> 193.58696 | BR30: =(U22*AW22+U23*AW23+U24*AW24+U25*AW25+U26*AW26+U27*AW27+U28*AW28+U29*AW29+U30*AW30+U31/9)*BX31 -> 75.611911 | BS30: =(V22*AW22+V23*AW23+V24*AW24+V25*AW25+V26*AW26+V27*AW27+V28*AW28+V29*AW29+V30*AW30+V31/9)*BX31 -> 51.429281 | BT30: =(W22*AW22+W23*AW23+W24*AW24+W25*AW25+W26*AW26+W27*AW27+W28*AW28+W29*AW29+W30*AW30+W31/9)*BX31 -> 65.610615 | BU30: =(X22*AW22+X23*AW23+X24*AW24+X25*AW25+X26*AW26+X27*AW27+X28*AW28+X29*AW29+X30*AW30+X31/9)*BX31 -> 100.38108 | BV30: =(Y22*AW22+Y23*AW23+Y24*AW24+Y25*AW25+Y26*AW26+Y27*AW27+Y28*AW28+Y29*AW29+Y30*AW30+Y31/9)*BX31 -> 1378.5214 | BW30: =AVERAGE(BQ30,BR30,BT30)/3 -> 37.201054 | CD30: 1961 to 1970 | CE30: 42221 | CL30: Electricity | CM30: 18348 | CR30: Before 1919 | CS30: Detached | CT30: Electricity | CU30: 2096
B31: Total | C31: =SUM(C22:C30) -> 0 | D31: =SUM(D22:D30) -> 3923 | E31: =SUM(E22:E30) -> 54915 | F31: =SUM(F22:F30) -> 64351 | G31: =SUM(G22:G30) -> 291 | H31: =SUM(H22:H30) -> 14 | I31: =SUM(I22:I30) -> 1906 | J31: =SUM(J22:J30) -> 187 | ... L31: =SUM(L22:L30) -> 8767 | M31: =SUM(C31:L31) -> 134792 | O31: Not Stated | P31: =SUMIFS( $CU$777:$CU$861,$CT$777:$CT$861, P21, $CS$777:$CS$861, $O$21) -> 981 | Q31: =SUMIFS( $CU$777:$CU$861,$CT$777:$CT$861, Q21, $CS$777:$CS$861, $O$21) -> 1164 | R31: =SUMIFS( $CU$777:$CU$861,$CT$777:$CT$861, R21, $CS$777:$CS$861, $O$21) -> 6886 | S31: =SUMIFS( $CU$777:$CU$861,$CT$777:$CT$861, S21, $CS$777:$CS$861, $O$21) -> 14306 | T31: =SUMIFS( $CU$777:$CU$861,$CT$777:$CT$861, T21, $CS$777:$CS$861, $O$21) -> 192 | U31: =SUMIFS( $CU$777:$CU$861,$CT$777:$CT$861, U21, $CS$777:$CS$861, $O$21) -> 61 | V31: =SUMIFS( $CU$777:$CU$861,$CT$777:$CT$861, V21, $CS$777:$CS$861, $O$21) -> 78 | W31: =SUMIFS( $CU$777:$CU$861,$CT$777:$CT$861, W21, $CS$777:$CS$861, $O$21) -> 41 | ... Y31: =SUMIFS( $CU$777:$CU$861,$CT$777:$CT$861, Y21, $CS$777:$CS$861, $O$21) -> 10848 | Z31: =SUM(P31:Y31) -> 34727 | AB31: Total | AC31: =SUM(AC22:AC30) -> 6419 | AD31: =SUM(AD22:AD30) -> 3209 | AE31: =SUM(AE22:AE30) -> 8665 | AF31: =SUM(AF22:AF30) -> 13570 | AG31: =SUM(AG22:AG30) -> 45566 | AH31: =SUM(AH22:AH30) -> 30979 | AI31: =SUM(AI22:AI30) -> 15595 | AJ31: =SUM(AJ22:AJ30) -> 5191 | ... AL31: =SUM(AL22:AL30) -> 134797 | AZ31: =$Z$31/9 -> 3858.5556 | BA31: =$Z$31/9 -> 3858.5556 | BB31: =$Z$31/9 -> 3858.5556 | BC31: =$Z$31/9 -> 3858.5556 | BD31: =$Z$31/9 -> 3858.5556 | BE31: =$Z$31/9 -> 3858.5556 | BF31: =$Z$31/9 -> 3858.5556 | BG31: =$Z$31/9 -> 3858.5556 | BH31: =$Z$31/9 -> 3858.5556 | BX31: 1.038789 | CD31: 1971 to 1980 | CE31: 97698 | CL31: Coal (incl. Anthracite_Coal) | CM31: 38120 | CR31: Before 1919 | CS31: Detached | CT31: Coal (incl. Anthracite_Coal) | CU31: 6482
O32: Total | P32: =SUM(P22:P31) -> 5068 | Q32: =SUM(Q22:Q31) -> 9199 | R32: =SUM(R22:R31) -> 80076 | S32: =SUM(S22:S31) -> 92540 | T32: =SUM(T22:T31) -> 1610 | U32: =SUM(U22:U31) -> 565 | V32: =SUM(V22:V31) -> 793 | W32: =SUM(W22:W31) -> 548 | ... Y32: =SUM(Y22:Y31) -> 12348 | Z32: =SUM(P32:Y32) -> 204145 | AY32: Total | AZ32: =SUM(AZ22:AZ31) -> 9298.0245 | BA32: =SUM(BA22:BA31) -> 7363.565 | BB32: =SUM(BB22:BB31) -> 13861.646 | BC32: =SUM(BC22:BC31) -> 19668.786 | BD32: =SUM(BD22:BD31) -> 58148.868 | BE32: =SUM(BE22:BE31) -> 43178.027 | BF32: =SUM(BF22:BF31) -> 25437.193 | BG32: =SUM(BG22:BG31) -> 12172.925 | BH32: =SUM(BH22:BH31) -> 15015.965 | BI32: =SUM(AZ32:BH32) -> 204145 | BJ32: 1.013 | CD32: 1981 to 1990 | CE32: 86491 | CL32: Peat (incl. turf) | CM32: 70819 | CR32: Before 1919 | CS32: Detached | CT32: Peat (incl. turf) | CU32: 9242
B33: Attached | C33: No central heating | D33: Oil | E33: Natural Gas | F33: Electricity | G33: Coal (incl. Anthracite_Coal) | H33: Peat (incl. turf) | I33: Liquid Petroleum Gas (LPG) | J33: Wood (incl. wood pellets) | K33: Other fuels | L33: Not stated | O33: Attached | P33: No central heating | Q33: Oil | R33: Natural Gas | S33: Electricity | T33: Coal (incl. Anthracite_Coal) | U33: Peat (incl. turf) | V33: Liquid Petroleum Gas (LPG) | W33: Wood (incl. wood pellets) | X33: Other fuels | Y33: Not stated | AB33: Attached | AC33: A | AD33: B1 | AE33: B2 | AF33: B3 | AG33: C | AH33: D | AI33: E | AJ33: F | AK33: G | AN33: Attached | AO33: A | AP33: B1 | AQ33: B2 | AR33: B3 | AS33: C | AT33: D | AU33: E | AV33: F | AW33: G | AY33: Adjusted Total | AZ33: =AZ32*$BJ$32 -> 9418.8989 | BA33: =BA32*$BJ$32 -> 7459.2913 | BB33: =BB32*$BJ$32 -> 14041.847 | BC33: =BC32*$BJ$32 -> 19924.48 | BD33: =BD32*$BJ$32 -> 58904.803 | BE33: =BE32*$BJ$32 -> 43739.342 | BF33: =BF32*$BJ$32 -> 25767.876 | BG33: =BG32*$BJ$32 -> 12331.173 | BH33: =BH32*$BJ$32 -> 15211.172 | BI33: =SUM(AZ33:BH33) -> 206798.88 | BL33: Attached | BM33: No central heating | BN33: Oil | BO33: Natural Gas | BP33: Electricity | BQ33: Coal (incl. Anthracite_Coal) | BR33: Peat (incl. turf) | BS33: Liquid Petroleum Gas (LPG) | BT33: Wood (incl. wood pellets) | BU33: Other fuels | BV33: Not stated | BW33: Solid Multi Fuel | CD33: 1991 to 2000 | CE33: 111455 | CL33: Liquid Petroleum Gas (LPG) | CM33: 6209 | CR33: Before 1919 | CS33: Detached | CT33: Liquid Petroleum Gas (LPG) | CU33: 574
B34: Before_1919 | D34: =SUMIFS(INDEX(Table5[],,MATCH(B33,Table5[#Headers],0)),Table5[MainSpaceHeatingFuel],"*Oil",Table5[Year_of_Construction (group)],B34) -> 6480 | E34: =SUMIFS(INDEX(Table5[],,MATCH(B33,Table5[#Headers],0)),Table5[MainSpaceHeatingFuel],"Mains Gas",Table5[Year_of_Construction (group)],B34) -> 11573 | F34: =SUMIFS(INDEX(Table5[],,MATCH(B33,Table5[#Headers],0)),Table5[MainSpaceHeatingFuel],F21,Table5[Year_of_Construction (group)],B34) -> 2965 | G34: =SUMIFS(INDEX(Table5[],,MATCH(B33,Table5[#Headers],0)),Table5[MainSpaceHeatingFuel],"*Coal",Table5[Year_of_Construction (group)],B34) -> 620 | H34: =SUMIFS(INDEX(Table5[],,MATCH(B33,Table5[#Headers],0)),Table5[MainSpaceHeatingFuel],"*Peat*",Table5[Year_of_Construction (group)],B34) -> 34 | I34: =SUMIFS(INDEX(Table5[],,MATCH(B33,Table5[#Headers],0)),Table5[MainSpaceHeatingFuel],"*LPG*",Table5[Year_of_Construction (group)],B34) -> 144 | J34: =SUMIFS(INDEX(Table5[],,MATCH(B33,Table5[#Headers],0)),Table5[MainSpaceHeatingFuel],"*Wood*",Table5[Year_of_Construction (group)],B34) -> 48 | K34: =SUMIFS(INDEX(Table5[],,MATCH(B33,Table5[#Headers],0)),Table5[MainSpaceHeatingFuel],"*Multi-Fuel*",Table5[Year_of_Construction (group)],B34) -> 964 | L34: =SUMIFS(INDEX(Table5[],,MATCH(B33,Table5[#Headers],0)),Table5[MainSpaceHeatingFuel],"",Table5[Year_of_Construction (group)],B34) -> 55 | M34: =SUM(C34:L34) -> 22883 | O34: Before_1919 | P34: =SUMIFS( CU14:CU96,CT14:CT96, P33, CS14:CS96, O33) -> 2042 | Q34: =SUMIFS( CU14:CU96,CT14:CT96, Q33, CS14:CS96, O33) -> 14677 | R34: =SUMIFS( CU14:CU96,CT14:CT96, R33, CS14:CS96, O33) -> 25267 | S34: =SUMIFS( CU14:CU96,CT14:CT96, S33, CS14:CS96, O33) -> 4140 | T34: =SUMIFS( CU14:CU96,CT14:CT96, T33, CS14:CS96, O33) -> 3344 | U34: =SUMIFS( CU14:CU96,CT14:CT96, U33, CS14:CS96, O33) -> 1463 | V34: =SUMIFS( CU14:CU96,CT14:CT96, V33, CS14:CS96, O33) -> 196 | W34: =SUMIFS( CU14:CU96,CT14:CT96, W33, CS14:CS96, O33) -> 811 | X34: =SUMIFS( CU14:CU96,CT14:CT96, X33, CS14:CS96, O33) -> 177 | Y34: =SUMIFS( CU14:CU96,CT14:CT96, Y33, CS14:CS96, O33) -> 317 | Z34: =SUM(P34:Y34) -> 52434 | AB34: Before_1919 | AC34: 48 | AD34: 62 | AE34: 209 | AF34: 560 | AG34: 2835 | AH34: 4516 | AI34: 4826 | AJ34: 3336 | AK34: 6491 | AL34: =SUM(AC34:AK34) -> 22883 | AN34: Before_1919 | AO34: =AC34/AL34 -> 0.0020976271 | AP34: =AD34/AL34 -> 0.002709435 | AQ34: =AE34/AL34 -> 0.0091334178 | AR34: =AF34/AL34 -> 0.024472316 | AS34: =AG34/AL34 -> 0.1238911 | AT34: =AH34/AL34 -> 0.19735175 | AU34: =AI34/AL34 -> 0.21089892 | AV34: =AJ34/AL34 -> 0.14578508 | AW34: =AK34/AL34 -> 0.28366036 | AY34: Attached | AZ34: A | BA34: B1 | BB34: B2 | BC34: B3 | BD34: C | BE34: D | BF34: E | BG34: F | BH34: G | BL34: A | BM34: =(P34*AO34+P35*AO35+P36*AO36+P37*AO37+P38*AO38+P39*AO39+P40*AO40+P41*AO41+P42*AO42+P43/9)*BX43 -> 110.44897 | BN34: =(Q34*AO34+Q35*AO35+Q36*AO36+Q37*AO37+Q38*AO38+Q39*AO39+Q40*AO40+Q41*AO41+Q42*AO42+Q43/9)*BX43 -> 3305.7206 | BO34: =(R34*AO34+R35*AO35+R36*AO36+R37*AO37+R38*AO38+R39*AO39+R40*AO40+R41*AO41+R42*AO42+R43/9)*BX43 -> 8596.9515 | BP34: =(S34*AO34+S35*AO35+S36*AO36+S37*AO37+S38*AO38+S39*AO39+S40*AO40+S41*AO41+S42*AO42+S43/9)*BX43 -> 1356.5313 | BQ34: =(T34*AO34+T35*AO35+T36*AO36+T37*AO37+T38*AO38+T39*AO39+T40*AO40+T41*AO41+T42*AO42+T43/9)*BX43 -> 546.50575 | BR34: =(U34*AO34+U35*AO35+U36*AO36+U37*AO37+U38*AO38+U39*AO39+U40*AO40+U41*AO41+U42*AO42+U43/9)*BX43 -> 184.25304 | BS34: =(V34*AO34+V35*AO35+V36*AO36+V37*AO37+V38*AO38+V39*AO39+V40*AO40+V41*AO41+V42*AO42+V43/9)*BX43 -> 77.700077 | BT34: =(W34*AO34+W35*AO35+W36*AO36+W37*AO37+W38*AO38+W39*AO39+W40*AO40+W41*AO41+W42*AO42+W43/9)*BX43 -> 122.56379 | BU34: =(X34*AO34+X35*AO35+X36*AO36+X37*AO37+X38*AO38+X39*AO39+X40*AO40+X41*AO41+X42*AO42+X43/9)*BX43 -> 198.25111 | BV34: =(Y34*AO34+Y35*AO35+Y36*AO36+Y37*AO37+Y38*AO38+Y39*AO39+Y40*AO40+Y41*AO41+Y42*AO42+Y43/9)*BX43 -> 1160.01 | BW34: =AVERAGE(BQ34,BR34,BT34)/3 -> 94.81362 | CD34: 2001 to 2010 | CE34: 175223 | CL34: Wood (incl. wood pellets) | CM34: 26591 | CR34: Before 1919 | CS34: Detached | CT34: Wood (incl. wood pellets) | CU34: 5593
B35: 1919-1945 | D35: =SUMIFS(INDEX(Table5[],,MATCH(B33,Table5[#Headers],0)),Table5[MainSpaceHeatingFuel],"*Oil",Table5[Year_of_Construction (group)],B35) -> 7569 | E35: =SUMIFS(INDEX(Table5[],,MATCH(B33,Table5[#Headers],0)),Table5[MainSpaceHeatingFuel],"Mains Gas",Table5[Year_of_Construction (group)],B35) -> 15245 | F35: =SUMIFS(INDEX(Table5[],,MATCH(B33,Table5[#Headers],0)),Table5[MainSpaceHeatingFuel],F21,Table5[Year_of_Construction (group)],B35) -> 1854 | G35: =SUMIFS(INDEX(Table5[],,MATCH(B33,Table5[#Headers],0)),Table5[MainSpaceHeatingFuel],"*Coal",Table5[Year_of_Construction (group)],B35) -> 757 | H35: =SUMIFS(INDEX(Table5[],,MATCH(B33,Table5[#Headers],0)),Table5[MainSpaceHeatingFuel],"*Peat*",Table5[Year_of_Construction (group)],B35) -> 50 | I35: =SUMIFS(INDEX(Table5[],,MATCH(B33,Table5[#Headers],0)),Table5[MainSpaceHeatingFuel],"*LPG*",Table5[Year_of_Construction (group)],B35) -> 95 | J35: =SUMIFS(INDEX(Table5[],,MATCH(B33,Table5[#Headers],0)),Table5[MainSpaceHeatingFuel],"*Wood*",Table5[Year_of_Construction (group)],B35) -> 38 | K35: =SUMIFS(INDEX(Table5[],,MATCH(B33,Table5[#Headers],0)),Table5[MainSpaceHeatingFuel],"*Multi-Fuel*",Table5[Year_of_Construction (group)],B35) -> 1204 | L35: =SUMIFS(INDEX(Table5[],,MATCH(B33,Table5[#Headers],0)),Table5[MainSpaceHeatingFuel],"",Table5[Year_of_Construction (group)],B35) -> 32 | M35: =SUM(C35:L35) -> 26844 | O35: 1919-1945 | P35: =SUMIFS( CU110:CU181,CT110:CT181, P33, CS110:CS181, O33) -> 1360 | Q35: =SUMIFS( CU110:CU181,CT110:CT181, Q33, CS110:CS181, O33) -> 15246 | R35: =SUMIFS( CU110:CU181,CT110:CT181, R33, CS110:CS181, O33) -> 29941 | S35: =SUMIFS( CU110:CU181,CT110:CT181, S33, CS110:CS181, O33) -> 2681 | T35: =SUMIFS( CU110:CU181,CT110:CT181, T33, CS110:CS181, O33) -> 4381 | U35: =SUMIFS( CU110:CU181,CT110:CT181, U33, CS110:CS181, O33) -> 1942 | V35: =SUMIFS( CU110:CU181,CT110:CT181, V33, CS110:CS181, O33) -> 122 | W35: =SUMIFS( CU110:CU181,CT110:CT181, W33, CS110:CS181, O33) -> 623 | X35: =SUMIFS( CU110:CU181,CT110:CT181, X33, CS110:CS181, O33) -> 161 | Y35: =SUMIFS( CU110:CU181,CT110:CT181, Y33, CS110:CS181, O33) -> 286 | Z35: =SUM(P35:Y35) -> 56743 | AB35: 1919-1945 | AC35: 51 | AD35: 75 | AE35: 274 | AF35: 833 | AG35: 4926 | AH35: 6303 | AI35: 5491 | AJ35: 3596 | AK35: 5295 | AL35: =SUM(AC35:AK35) -> 26844 | AN35: 1919-1945 | AO35: =AC35/AL35 -> 0.0018998659 | AP35: =AD35/AL35 -> 0.0027939204 | AQ35: =AE35/AL35 -> 0.010207123 | AR35: =AF35/AL35 -> 0.031031143 | AS35: =AG35/AL35 -> 0.18350469 | AT35: =AH35/AL35 -> 0.23480107 | AU35: =AI35/AL35 -> 0.20455223 | AV35: =AJ35/AL35 -> 0.13395917 | AW35: =AK35/AL35 -> 0.19725078 | AZ35: =AO34*$Z$34 -> 109.98698 | BA35: =AP34*$Z$34 -> 142.06651 | BB35: =AQ34*$Z$34 -> 478.90163 | BC35: =AR34*$Z$34 -> 1283.1814 | BD35: =AS34*$Z$34 -> 6496.1058 | BE35: =AT34*$Z$34 -> 10347.941 | BF35: =AU34*$Z$34 -> 11058.274 | BG35: =AV34*$Z$34 -> 7644.0949 | BH35: =AW34*$Z$34 -> 14873.447 | BL35: B1 | BM35: =(P34*AP34+P35*AP35+P36*AP36+P37*AP37+P38*AP38+P39*AP39+P40*AP40+P41*AP41+P42*AP42+P43/9)*BX43 -> 94.240578 | BN35: =(Q34*AP34+Q35*AP35+Q36*AP36+Q37*AP37+Q38*AP38+Q39*AP39+Q40*AP40+Q41*AP41+Q42*AP42+Q43/9)*BX43 -> 2546.6404 | BO35: =(R34*AP34+R35*AP35+R36*AP36+R37*AP37+R38*AP38+R39*AP39+R40*AP40+R41*AP41+R42*AP42+R43/9)*BX43 -> 4511.4356 | BP35: =(S34*AP34+S35*AP35+S36*AP36+S37*AP37+S38*AP38+S39*AP39+S40*AP40+S41*AP41+S42*AP42+S43/9)*BX43 -> 619.65855 | BQ35: =(T34*AP34+T35*AP35+T36*AP36+T37*AP37+T38*AP38+T39*AP39+T40*AP40+T41*AP41+T42*AP42+T43/9)*BX43 -> 472.9297 | BR35: =(U34*AP34+U35*AP35+U36*AP36+U37*AP37+U38*AP38+U39*AP39+U40*AP40+U41*AP41+U42*AP42+U43/9)*BX43 -> 156.66403 | BS35: =(V34*AP34+V35*AP35+V36*AP36+V37*AP37+V38*AP38+V39*AP39+V40*AP40+V41*AP41+V42*AP42+V43/9)*BX43 -> 45.466882 | BT35: =(W34*AP34+W35*AP35+W36*AP36+W37*AP37+W38*AP38+W39*AP39+W40*AP40+W41*AP41+W42*AP42+W43/9)*BX43 -> 65.862231 | BU35: =(X34*AP34+X35*AP35+X36*AP36+X37*AP37+X38*AP38+X39*AP39+X40*AP40+X41*AP41+X42*AP42+X43/9)*BX43 -> 34.022772 | BV35: =(Y34*AP34+Y35*AP35+Y36*AP36+Y37*AP37+Y38*AP38+Y39*AP39+Y40*AP40+Y41*AP41+Y42*AP42+Y43/9)*BX43 -> 1106.0492 | BW35: =AVERAGE(BQ35,BR35,BT35)/3 -> 77.272884 | CD35: 2011 or later | CE35: 18050 | CL35: Other fuels | CM35: 7587 | CR35: Before 1919 | CS35: Detached | CT35: Other fuels | CU35: 473
B36: 1946-1960 | D36: =SUMIFS(INDEX(Table5[],,MATCH(B33,Table5[#Headers],0)),Table5[MainSpaceHeatingFuel],"*Oil",Table5[Year_of_Construction (group)],B36) -> 9598 | E36: =SUMIFS(INDEX(Table5[],,MATCH(B33,Table5[#Headers],0)),Table5[MainSpaceHeatingFuel],"Mains Gas",Table5[Year_of_Construction (group)],B36) -> 20485 | F36: =SUMIFS(INDEX(Table5[],,MATCH(B33,Table5[#Headers],0)),Table5[MainSpaceHeatingFuel],F21,Table5[Year_of_Construction (group)],B36) -> 1666 | G36: =SUMIFS(INDEX(Table5[],,MATCH(B33,Table5[#Headers],0)),Table5[MainSpaceHeatingFuel],"*Coal",Table5[Year_of_Construction (group)],B36) -> 585 | H36: =SUMIFS(INDEX(Table5[],,MATCH(B33,Table5[#Headers],0)),Table5[MainSpaceHeatingFuel],"*Peat*",Table5[Year_of_Construction (group)],B36) -> 48 | I36: =SUMIFS(INDEX(Table5[],,MATCH(B33,Table5[#Headers],0)),Table5[MainSpaceHeatingFuel],"*LPG*",Table5[Year_of_Construction (group)],B36) -> 83 | J36: =SUMIFS(INDEX(Table5[],,MATCH(B33,Table5[#Headers],0)),Table5[MainSpaceHeatingFuel],"*Wood*",Table5[Year_of_Construction (group)],B36) -> 27 | K36: =SUMIFS(INDEX(Table5[],,MATCH(B33,Table5[#Headers],0)),Table5[MainSpaceHeatingFuel],"*Multi-Fuel*",Table5[Year_of_Construction (group)],B36) -> 952 | L36: =SUMIFS(INDEX(Table5[],,MATCH(B33,Table5[#Headers],0)),Table5[MainSpaceHeatingFuel],"",Table5[Year_of_Construction (group)],B36) -> 28 | M36: =SUM(C36:L36) -> 33472 | O36: 1946-1960 | P36: =SUMIFS( CU195:CU266,CT195:CT266, P33, CS195:CS266, O33) -> 1286 | Q36: =SUMIFS( CU195:CU266,CT195:CT266, Q33, CS195:CS266, O33) -> 20809 | R36: =SUMIFS( CU195:CU266,CT195:CT266, R33, CS195:CS266, O33) -> 44437 | S36: =SUMIFS( CU195:CU266,CT195:CT266, S33, CS195:CS266, O33) -> 2716 | T36: =SUMIFS( CU195:CU266,CT195:CT266, T33, CS195:CS266, O33) -> 4719 | U36: =SUMIFS( CU195:CU266,CT195:CT266, U33, CS195:CS266, O33) -> 2202 | V36: =SUMIFS( CU195:CU266,CT195:CT266, V33, CS195:CS266, O33) -> 112 | W36: =SUMIFS( CU195:CU266,CT195:CT266, W33, CS195:CS266, O33) -> 756 | X36: =SUMIFS( CU195:CU266,CT195:CT266, X33, CS195:CS266, O33) -> 163 | Y36: =SUMIFS( CU195:CU266,CT195:CT266, Y33, CS195:CS266, O33) -> 331 | Z36: =SUM(P36:Y36) -> 77531 | AB36: 1946-1960 | AC36: 76 | AD36: 168 | AE36: 434 | AF36: 1022 | AG36: 6663 | AH36: 8654 | AI36: 7730 | AJ36: 4391 | AK36: 4335 | AL36: =SUM(AC36:AK36) -> 33473 | AN36: 1946-1960 | AO36: =AC36/AL36 -> 0.0022704867 | AP36: =AD36/AL36 -> 0.0050189705 | AQ36: =AE36/AL36 -> 0.012965674 | AR36: =AF36/AL36 -> 0.030532071 | AS36: =AG36/AL36 -> 0.19905596 | AT36: =AH36/AL36 -> 0.25853673 | AU36: =AI36/AL36 -> 0.23093239 | AV36: =AJ36/AL36 -> 0.13118035 | AW36: =AK36/AL36 -> 0.12950736 | AZ36: =AO35*$Z$35 -> 107.80409 | BA36: =AP35*$Z$35 -> 158.53543 | BB36: =AQ35*$Z$35 -> 579.18276 | BC36: =AR35*$Z$35 -> 1760.8001 | BD36: =AS35*$Z$35 -> 10412.607 | BE36: =AT35*$Z$35 -> 13323.317 | BF36: =AU35*$Z$35 -> 11606.907 | BG36: =AV35*$Z$35 -> 7601.2453 | BH36: =AW35*$Z$35 -> 11192.601 | BL36: B2 | BM36: =(P34*AQ34+P35*AQ35+P36*AQ36+P37*AQ37+P38*AQ38+P39*AQ39+P40*AQ40+P41*AQ41+P42*AQ42+P43/9)*BX43 -> 164.97553 | BN36: =(Q34*AQ34+Q35*AQ35+Q36*AQ36+Q37*AQ37+Q38*AQ38+Q39*AQ39+Q40*AQ40+Q41*AQ41+Q42*AQ42+Q43/9)*BX43 -> 5047.0569 | BO36: =(R34*AQ34+R35*AQ35+R36*AQ36+R37*AQ37+R38*AQ38+R39*AQ39+R40*AQ40+R41*AQ41+R42*AQ42+R43/9)*BX43 -> 8965.1078 | BP36: =(S34*AQ34+S35*AQ35+S36*AQ36+S37*AQ37+S38*AQ38+S39*AQ39+S40*AQ40+S41*AQ41+S42*AQ42+S43/9)*BX43 -> 939.00892 | BQ36: =(T34*AQ34+T35*AQ35+T36*AQ36+T37*AQ37+T38*AQ38+T39*AQ39+T40*AQ40+T41*AQ41+T42*AQ42+T43/9)*BX43 -> 900.36368 | BR36: =(U34*AQ34+U35*AQ35+U36*AQ36+U37*AQ37+U38*AQ38+U39*AQ39+U40*AQ40+U41*AQ41+U42*AQ42+U43/9)*BX43 -> 323.44457 | BS36: =(V34*AQ34+V35*AQ35+V36*AQ36+V37*AQ37+V38*AQ38+V39*AQ39+V40*AQ40+V41*AQ41+V42*AQ42+V43/9)*BX43 -> 96.164722 | BT36: =(W34*AQ34+W35*AQ35+W36*AQ36+W37*AQ37+W38*AQ38+W39*AQ39+W40*AQ40+W41*AQ41+W42*AQ42+W43/9)*BX43 -> 130.7621 | BU36: =(X34*AQ34+X35*AQ35+X36*AQ36+X37*AQ37+X38*AQ38+X39*AQ39+X40*AQ40+X41*AQ41+X42*AQ42+X43/9)*BX43 -> 50.486966 | BV36: =(Y34*AQ34+Y35*AQ35+Y36*AQ36+Y37*AQ37+Y38*AQ38+Y39*AQ39+Y40*AQ40+Y41*AQ41+Y42*AQ42+Y43/9)*BX43 -> 1139.6208 | BW36: =AVERAGE(BQ36,BR36,BT36)/3 -> 150.50782 | CD36: Not stated | CE36: 20596 | CL36: Not stated | CM36: 7535 | CR36: Before 1919 | CS36: Detached | CT36: Not stated | CU36: 419
B37: 1961-1970 | D37: =SUMIFS(INDEX(Table5[],,MATCH(B33,Table5[#Headers],0)),Table5[MainSpaceHeatingFuel],"*Oil",Table5[Year_of_Construction (group)],B37) -> 8634 | E37: =SUMIFS(INDEX(Table5[],,MATCH(B33,Table5[#Headers],0)),Table5[MainSpaceHeatingFuel],"Mains Gas",Table5[Year_of_Construction (group)],B37) -> 14099 | F37: =SUMIFS(INDEX(Table5[],,MATCH(B33,Table5[#Headers],0)),Table5[MainSpaceHeatingFuel],F21,Table5[Year_of_Construction (group)],B37) -> 823 | G37: =SUMIFS(INDEX(Table5[],,MATCH(B33,Table5[#Headers],0)),Table5[MainSpaceHeatingFuel],"*Coal",Table5[Year_of_Construction (group)],B37) -> 373 | H37: =SUMIFS(INDEX(Table5[],,MATCH(B33,Table5[#Headers],0)),Table5[MainSpaceHeatingFuel],"*Peat*",Table5[Year_of_Construction (group)],B37) -> 47 | I37: =SUMIFS(INDEX(Table5[],,MATCH(B33,Table5[#Headers],0)),Table5[MainSpaceHeatingFuel],"*LPG*",Table5[Year_of_Construction (group)],B37) -> 61 | J37: =SUMIFS(INDEX(Table5[],,MATCH(B33,Table5[#Headers],0)),Table5[MainSpaceHeatingFuel],"*Wood*",Table5[Year_of_Construction (group)],B37) -> 27 | K37: =SUMIFS(INDEX(Table5[],,MATCH(B33,Table5[#Headers],0)),Table5[MainSpaceHeatingFuel],"*Multi-Fuel*",Table5[Year_of_Construction (group)],B37) -> 754 | L37: =SUMIFS(INDEX(Table5[],,MATCH(B33,Table5[#Headers],0)),Table5[MainSpaceHeatingFuel],"",Table5[Year_of_Construction (group)],B37) -> 33 | M37: =SUM(C37:L37) -> 24851 | O37: 1961-1970 | P37: =SUMIFS( CU280:CU351,CT280:CT351, P33, CS280:CS351, O33) -> 752 | Q37: =SUMIFS( CU280:CU351,CT280:CT351, Q33, CS280:CS351, O33) -> 22343 | R37: =SUMIFS( CU280:CU351,CT280:CT351, R33, CS280:CS351, O33) -> 36262 | S37: =SUMIFS( CU280:CU351,CT280:CT351, S33, CS280:CS351, O33) -> 1955 | T37: =SUMIFS( CU280:CU351,CT280:CT351, T33, CS280:CS351, O33) -> 3901 | U37: =SUMIFS( CU280:CU351,CT280:CT351, U33, CS280:CS351, O33) -> 1479 | V37: =SUMIFS( CU280:CU351,CT280:CT351, V33, CS280:CS351, O33) -> 129 | W37: =SUMIFS( CU280:CU351,CT280:CT351, W33, CS280:CS351, O33) -> 513 | X37: =SUMIFS( CU280:CU351,CT280:CT351, X33, CS280:CS351, O33) -> 119 | Y37: =SUMIFS( CU280:CU351,CT280:CT351, Y33, CS280:CS351, O33) -> 281 | Z37: =SUM(P37:Y37) -> 67734 | AB37: 1961-1970 | AC37: 79 | AD37: 57 | AE37: 248 | AF37: 903 | AG37: 6852 | AH37: 7789 | AI37: 5023 | AJ37: 2274 | AK37: 1626 | AL37: =SUM(AC37:AK37) -> 24851 | AN37: 1961-1970 | AO37: =AC37/AL37 -> 0.0031789465 | AP37: =AD37/AL37 -> 0.0022936703 | AQ37: =AE37/AL37 -> 0.0099794777 | AR37: =AF37/AL37 -> 0.036336566 | AS37: =AG37/AL37 -> 0.27572331 | AT37: =AH37/AL37 -> 0.31342803 | AU37: =AI37/AL37 -> 0.20212466 | AV37: =AJ37/AL37 -> 0.091505372 | AW37: =AK37/AL37 -> 0.065429963 | AZ37: =AO36*$Z$36 -> 176.0331 | BA37: =AP36*$Z$36 -> 389.1258 | BB37: =AQ36*$Z$36 -> 1005.2417 | BC37: =AR36*$Z$36 -> 2367.182 | BD37: =AS36*$Z$36 -> 15433.007 | BE37: =AT36*$Z$36 -> 20044.611 | BF37: =AU36*$Z$36 -> 17904.419 | BG37: =AV36*$Z$36 -> 10170.544 | BH37: =AW36*$Z$36 -> 10040.835 | BL37: B3 | BM37: =(P34*AR34+P35*AR35+P36*AR36+P37*AR37+P38*AR38+P39*AR39+P40*AR40+P41*AR41+P42*AR42+P43/9)*BX43 -> 421.8999 | BN37: =(Q34*AR34+Q35*AR35+Q36*AR36+Q37*AR37+Q38*AR38+Q39*AR39+Q40*AR40+Q41*AR41+Q42*AR42+Q43/9)*BX43 -> 15093.992 | BO37: =(R34*AR34+R35*AR35+R36*AR36+R37*AR37+R38*AR38+R39*AR39+R40*AR40+R41*AR41+R42*AR42+R43/9)*BX43 -> 26823.932 | BP37: =(S34*AR34+S35*AR35+S36*AR36+S37*AR37+S38*AR38+S39*AR39+S40*AR40+S41*AR41+S42*AR42+S43/9)*BX43 -> 2268.2507 | BQ37: =(T34*AR34+T35*AR35+T36*AR36+T37*AR37+T38*AR38+T39*AR39+T40*AR40+T41*AR41+T42*AR42+T43/9)*BX43 -> 2680.3414 | BR37: =(U34*AR34+U35*AR35+U36*AR36+U37*AR37+U38*AR38+U39*AR39+U40*AR40+U41*AR41+U42*AR42+U43/9)*BX43 -> 1002.6226 | BS37: =(V34*AR34+V35*AR35+V36*AR36+V37*AR37+V38*AR38+V39*AR39+V40*AR40+V41*AR41+V42*AR42+V43/9)*BX43 -> 285.00923 | BT37: =(W34*AR34+W35*AR35+W36*AR36+W37*AR37+W38*AR38+W39*AR39+W40*AR40+W41*AR41+W42*AR42+W43/9)*BX43 -> 389.07571 | BU37: =(X34*AR34+X35*AR35+X36*AR36+X37*AR37+X38*AR38+X39*AR39+X40*AR40+X41*AR41+X42*AR42+X43/9)*BX43 -> 129.7409 | BV37: =(Y34*AR34+Y35*AR35+Y36*AR36+Y37*AR37+Y38*AR38+Y39*AR39+Y40*AR40+Y41*AR41+Y42*AR42+Y43/9)*BX43 -> 1275.0638 | BW37: =AVERAGE(BQ37,BR37,BT37)/3 -> 452.44885 | CC37: Semi- detached house | CK37: Semi- detached house | CR37: Before 1919 | CS37: Attached
B38: 1971-1980 | D38: =SUMIFS(INDEX(Table5[],,MATCH(B33,Table5[#Headers],0)),Table5[MainSpaceHeatingFuel],"*Oil",Table5[Year_of_Construction (group)],B38) -> 19285 | E38: =SUMIFS(INDEX(Table5[],,MATCH(B33,Table5[#Headers],0)),Table5[MainSpaceHeatingFuel],"Mains Gas",Table5[Year_of_Construction (group)],B38) -> 26605 | F38: =SUMIFS(INDEX(Table5[],,MATCH(B33,Table5[#Headers],0)),Table5[MainSpaceHeatingFuel],F21,Table5[Year_of_Construction (group)],B38) -> 1444 | G38: =SUMIFS(INDEX(Table5[],,MATCH(B33,Table5[#Headers],0)),Table5[MainSpaceHeatingFuel],"*Coal",Table5[Year_of_Construction (group)],B38) -> 1164 | H38: =SUMIFS(INDEX(Table5[],,MATCH(B33,Table5[#Headers],0)),Table5[MainSpaceHeatingFuel],"*Peat*",Table5[Year_of_Construction (group)],B38) -> 208 | I38: =SUMIFS(INDEX(Table5[],,MATCH(B33,Table5[#Headers],0)),Table5[MainSpaceHeatingFuel],"*LPG*",Table5[Year_of_Construction (group)],B38) -> 119 | J38: =SUMIFS(INDEX(Table5[],,MATCH(B33,Table5[#Headers],0)),Table5[MainSpaceHeatingFuel],"*Wood*",Table5[Year_of_Construction (group)],B38) -> 61 | K38: =SUMIFS(INDEX(Table5[],,MATCH(B33,Table5[#Headers],0)),Table5[MainSpaceHeatingFuel],"*Multi-Fuel*",Table5[Year_of_Construction (group)],B38) -> 2773 | L38: =SUMIFS(INDEX(Table5[],,MATCH(B33,Table5[#Headers],0)),Table5[MainSpaceHeatingFuel],"",Table5[Year_of_Construction (group)],B38) -> 36 | M38: =SUM(C38:L38) -> 51695 | O38: 1971-1980 | P38: =SUMIFS( CU365:CU436,CT365:CT436, P33, CS365:CS436, O33) -> 1063 | Q38: =SUMIFS( CU365:CU436,CT365:CT436, Q33, CS365:CS436, O33) -> 40052 | R38: =SUMIFS( CU365:CU436,CT365:CT436, R33, CS365:CS436, O33) -> 51195 | S38: =SUMIFS( CU365:CU436,CT365:CT436, S33, CS365:CS436, O33) -> 2600 | T38: =SUMIFS( CU365:CU436,CT365:CT436, T33, CS365:CS436, O33) -> 7692 | U38: =SUMIFS( CU365:CU436,CT365:CT436, U33, CS365:CS436, O33) -> 2980 | V38: =SUMIFS( CU365:CU436,CT365:CT436, V33, CS365:CS436, O33) -> 208 | W38: =SUMIFS( CU365:CU436,CT365:CT436, W33, CS365:CS436, O33) -> 994 | X38: =SUMIFS( CU365:CU436,CT365:CT436, X33, CS365:CS436, O33) -> 220 | Y38: =SUMIFS( CU365:CU436,CT365:CT436, Y33, CS365:CS436, O33) -> 449 | Z38: =SUM(P38:Y38) -> 107453 | AB38: 1971-1980 | AC38: 114 | AD38: 126 | AE38: 355 | AF38: 1976 | AG38: 17845 | AH38: 17207 | AI38: 8983 | AJ38: 3200 | AK38: 1889 | AL38: =SUM(AC38:AK38) -> 51695 | AN38: 1971-1980 | AO38: =AC38/AL38 -> 0.0022052423 | AP38: =AD38/AL38 -> 0.0024373731 | AQ38: =AE38/AL38 -> 0.0068672019 | AR38: =AF38/AL38 -> 0.0382242 | AS38: =AG38/AL38 -> 0.34519779 | AT38: =AH38/AL38 -> 0.33285618 | AU38: =AI38/AL38 -> 0.17376922 | AV38: =AJ38/AL38 -> 0.061901538 | AW38: =AK38/AL38 -> 0.036541252 | AZ38: =AO37*$Z$37 -> 215.32276 | BA38: =AP37*$Z$37 -> 155.35946 | BB38: =AQ37*$Z$37 -> 675.94994 | BC38: =AR37*$Z$37 -> 2461.221 | BD38: =AS37*$Z$37 -> 18675.843 | BE38: =AT37*$Z$37 -> 21229.734 | BF38: =AU37*$Z$37 -> 13690.712 | BG38: =AV37*$Z$37 -> 6198.0249 | BH38: =AW37*$Z$37 -> 4431.8331 | BL38: C | BM38: =(P34*AS34+P35*AS35+P36*AS36+P37*AS37+P38*AS38+P39*AS39+P40*AS40+P41*AS41+P42*AS42+P43/9)*BX43 -> 2457.2252 | BN38: =(Q34*AS34+Q35*AS35+Q36*AS36+Q37*AS37+Q38*AS38+Q39*AS39+Q40*AS40+Q41*AS41+Q42*AS42+Q43/9)*BX43 -> 87503.975 | BO38: =(R34*AS34+R35*AS35+R36*AS36+R37*AS37+R38*AS38+R39*AS39+R40*AS40+R41*AS41+R42*AS42+R43/9)*BX43 -> 154216.98 | BP38: =(S34*AS34+S35*AS35+S36*AS36+S37*AS37+S38*AS38+S39*AS39+S40*AS40+S41*AS41+S42*AS42+S43/9)*BX43 -> 11909.649 | BQ38: =(T34*AS34+T35*AS35+T36*AS36+T37*AS37+T38*AS38+T39*AS39+T40*AS40+T41*AS41+T42*AS42+T43/9)*BX43 -> 16553.601 | BR38: =(U34*AS34+U35*AS35+U36*AS36+U37*AS37+U38*AS38+U39*AS39+U40*AS40+U41*AS41+U42*AS42+U43/9)*BX43 -> 6286.0022 | BS38: =(V34*AS34+V35*AS35+V36*AS36+V37*AS37+V38*AS38+V39*AS39+V40*AS40+V41*AS41+V42*AS42+V43/9)*BX43 -> 1394.6004 | BT38: =(W34*AS34+W35*AS35+W36*AS36+W37*AS37+W38*AS38+W39*AS39+W40*AS40+W41*AS41+W42*AS42+W43/9)*BX43 -> 2300.3428 | BU38: =(X34*AS34+X35*AS35+X36*AS36+X37*AS37+X38*AS38+X39*AS39+X40*AS40+X41*AS41+X42*AS42+X43/9)*BX43 -> 689.81397 | BV38: =(Y34*AS34+Y35*AS35+Y36*AS36+Y37*AS37+Y38*AS38+Y39*AS39+Y40*AS40+Y41*AS41+Y42*AS42+Y43/9)*BX43 -> 2246.9908 | BW38: =AVERAGE(BQ38,BR38,BT38)/3 -> 2793.3273 | CD38: All years | CE38: 471948 | CL38: All households | CM38: 471948 | CR38: Before 1919 | CS38: Attached | CT38: All households | CU38: 15478
B39: 1981-1990 | D39: =SUMIFS(INDEX(Table5[],,MATCH(B33,Table5[#Headers],0)),Table5[MainSpaceHeatingFuel],"*Oil",Table5[Year_of_Construction (group)],B39) -> 14405 | E39: =SUMIFS(INDEX(Table5[],,MATCH(B33,Table5[#Headers],0)),Table5[MainSpaceHeatingFuel],"Mains Gas",Table5[Year_of_Construction (group)],B39) -> 22617 | F39: =SUMIFS(INDEX(Table5[],,MATCH(B33,Table5[#Headers],0)),Table5[MainSpaceHeatingFuel],F21,Table5[Year_of_Construction (group)],B39) -> 2023 | G39: =SUMIFS(INDEX(Table5[],,MATCH(B33,Table5[#Headers],0)),Table5[MainSpaceHeatingFuel],"*Coal",Table5[Year_of_Construction (group)],B39) -> 1261 | H39: =SUMIFS(INDEX(Table5[],,MATCH(B33,Table5[#Headers],0)),Table5[MainSpaceHeatingFuel],"*Peat*",Table5[Year_of_Construction (group)],B39) -> 108 | I39: =SUMIFS(INDEX(Table5[],,MATCH(B33,Table5[#Headers],0)),Table5[MainSpaceHeatingFuel],"*LPG*",Table5[Year_of_Construction (group)],B39) -> 200 | J39: =SUMIFS(INDEX(Table5[],,MATCH(B33,Table5[#Headers],0)),Table5[MainSpaceHeatingFuel],"*Wood*",Table5[Year_of_Construction (group)],B39) -> 50 | K39: =SUMIFS(INDEX(Table5[],,MATCH(B33,Table5[#Headers],0)),Table5[MainSpaceHeatingFuel],"*Multi-Fuel*",Table5[Year_of_Construction (group)],B39) -> 2892 | L39: =SUMIFS(INDEX(Table5[],,MATCH(B33,Table5[#Headers],0)),Table5[MainSpaceHeatingFuel],"",Table5[Year_of_Construction (group)],B39) -> 68 | M39: =SUM(C39:L39) -> 43624 | O39: 1981-1990 | P39: =SUMIFS( CU450:CU521,CT450:CT521, P33, CS450:CS521, O33) -> 762 | Q39: =SUMIFS( CU450:CU521,CT450:CT521, Q33, CS450:CS521, O33) -> 23385 | R39: =SUMIFS( CU450:CU521,CT450:CT521, R33, CS450:CS521, O33) -> 35617 | S39: =SUMIFS( CU450:CU521,CT450:CT521, S33, CS450:CS521, O33) -> 3376 | T39: =SUMIFS( CU450:CU521,CT450:CT521, T33, CS450:CS521, O33) -> 6160 | U39: =SUMIFS( CU450:CU521,CT450:CT521, U33, CS450:CS521, O33) -> 2354 | V39: =SUMIFS( CU450:CU521,CT450:CT521, V33, CS450:CS521, O33) -> 196 | W39: =SUMIFS( CU450:CU521,CT450:CT521, W33, CS450:CS521, O33) -> 746 | X39: =SUMIFS( CU450:CU521,CT450:CT521, X33, CS450:CS521, O33) -> 193 | Y39: =SUMIFS( CU450:CU521,CT450:CT521, Y33, CS450:CS521, O33) -> 290 | Z39: =SUM(P39:Y39) -> 73079 | AB39: 1981-1990 | AC39: 45 | AD39: 43 | AE39: 300 | AF39: 1948 | AG39: 18599 | AH39: 15206 | AI39: 5228 | AJ39: 1424 | AK39: 831 | AL39: =SUM(AC39:AK39) -> 43624 | AN39: 1981-1990 | AO39: =AC39/AL39 -> 0.0010315423 | AP39: =AD39/AL39 -> 0.00098569595 | AQ39: =AE39/AL39 -> 0.0068769485 | AR39: =AF39/AL39 -> 0.044654319 | AS39: =AG39/AL39 -> 0.42634788 | AT39: =AH39/AL39 -> 0.34856959 | AU39: =AI39/AL39 -> 0.11984229 | AV39: =AJ39/AL39 -> 0.032642582 | AW39: =AK39/AL39 -> 0.019049147 | AZ39: =AO38*$Z$38 -> 236.9599 | BA39: =AP38*$Z$38 -> 261.90305 | BB39: =AQ38*$Z$38 -> 737.90144 | BC39: =AR38*$Z$38 -> 4107.3049 | BD39: =AS38*$Z$38 -> 37092.539 | BE39: =AT38*$Z$38 -> 35766.395 | BF39: =AU38*$Z$38 -> 18672.024 | BG39: =AV38*$Z$38 -> 6651.5059 | BH39: =AW38*$Z$38 -> 3926.4671 | BL39: D | BM39: =(P34*AT34+P35*AT35+P36*AT36+P37*AT37+P38*AT38+P39*AT39+P40*AT40+P41*AT41+P42*AT42+P43/9)*BX43 -> 2291.1705 | BN39: =(Q34*AT34+Q35*AT35+Q36*AT36+Q37*AT37+Q38*AT38+Q39*AT39+Q40*AT40+Q41*AT41+Q42*AT42+Q43/9)*BX43 -> 58227.471 | BO39: =(R34*AT34+R35*AT35+R36*AT36+R37*AT37+R38*AT38+R39*AT39+R40*AT40+R41*AT41+R42*AT42+R43/9)*BX43 -> 99700.378 | BP39: =(S34*AT34+S35*AT35+S36*AT36+S37*AT37+S38*AT38+S39*AT39+S40*AT40+S41*AT41+S42*AT42+S43/9)*BX43 -> 7986.4156 | BQ39: =(T34*AT34+T35*AT35+T36*AT36+T37*AT37+T38*AT38+T39*AT39+T40*AT40+T41*AT41+T42*AT42+T43/9)*BX43 -> 12311.358 | BR39: =(U34*AT34+U35*AT35+U36*AT36+U37*AT37+U38*AT38+U39*AT39+U40*AT40+U41*AT41+U42*AT42+U43/9)*BX43 -> 4792.3877 | BS39: =(V34*AT34+V35*AT35+V36*AT36+V37*AT37+V38*AT38+V39*AT39+V40*AT40+V41*AT41+V42*AT42+V43/9)*BX43 -> 587.86059 | BT39: =(W34*AT34+W35*AT35+W36*AT36+W37*AT37+W38*AT38+W39*AT39+W40*AT40+W41*AT41+W42*AT42+W43/9)*BX43 -> 1683.1767 | BU39: =(X34*AT34+X35*AT35+X36*AT36+X37*AT37+X38*AT38+X39*AT39+X40*AT40+X41*AT41+X42*AT42+X43/9)*BX43 -> 442.90799 | BV39: =(Y34*AT34+Y35*AT35+Y36*AT36+Y37*AT37+Y38*AT38+Y39*AT39+Y40*AT40+Y41*AT41+Y42*AT42+Y43/9)*BX43 -> 1869.9423 | BW39: =AVERAGE(BQ39,BR39,BT39)/3 -> 2087.4358 | CD39: Before 1919 | CE39: 15478 | CL39: No central heating | CM39: 3625 | CR39: Before 1919 | CS39: Attached | CT39: No central heating | CU39: 474
B40: 1991-2000 | D40: =SUMIFS(INDEX(Table5[],,MATCH(B33,Table5[#Headers],0)),Table5[MainSpaceHeatingFuel],"*Oil",Table5[Year_of_Construction (group)],B40) -> 19202 | E40: =SUMIFS(INDEX(Table5[],,MATCH(B33,Table5[#Headers],0)),Table5[MainSpaceHeatingFuel],"Mains Gas",Table5[Year_of_Construction (group)],B40) -> 33425 | F40: =SUMIFS(INDEX(Table5[],,MATCH(B33,Table5[#Headers],0)),Table5[MainSpaceHeatingFuel],F21,Table5[Year_of_Construction (group)],B40) -> 6012 | G40: =SUMIFS(INDEX(Table5[],,MATCH(B33,Table5[#Headers],0)),Table5[MainSpaceHeatingFuel],"*Coal",Table5[Year_of_Construction (group)],B40) -> 1528 | H40: =SUMIFS(INDEX(Table5[],,MATCH(B33,Table5[#Headers],0)),Table5[MainSpaceHeatingFuel],"*Peat*",Table5[Year_of_Construction (group)],B40) -> 68 | I40: =SUMIFS(INDEX(Table5[],,MATCH(B33,Table5[#Headers],0)),Table5[MainSpaceHeatingFuel],"*LPG*",Table5[Year_of_Construction (group)],B40) -> 388 | J40: =SUMIFS(INDEX(Table5[],,MATCH(B33,Table5[#Headers],0)),Table5[MainSpaceHeatingFuel],"*Wood*",Table5[Year_of_Construction (group)],B40) -> 41 | K40: =SUMIFS(INDEX(Table5[],,MATCH(B33,Table5[#Headers],0)),Table5[MainSpaceHeatingFuel],"*Multi-Fuel*",Table5[Year_of_Construction (group)],B40) -> 3271 | L40: =SUMIFS(INDEX(Table5[],,MATCH(B33,Table5[#Headers],0)),Table5[MainSpaceHeatingFuel],"",Table5[Year_of_Construction (group)],B40) -> 182 | M40: =SUM(C40:L40) -> 64117 | O40: 1991-2000 | P40: =SUMIFS( CU535:CU606,CT535:CT606, P33, CS535:CS606, O33) -> 555 | Q40: =SUMIFS( CU535:CU606,CT535:CT606, Q33, CS535:CS606, O33) -> 26660 | R40: =SUMIFS( CU535:CU606,CT535:CT606, R33, CS535:CS606, O33) -> 57434 | S40: =SUMIFS( CU535:CU606,CT535:CT606, S33, CS535:CS606, O33) -> 5219 | T40: =SUMIFS( CU535:CU606,CT535:CT606, T33, CS535:CS606, O33) -> 6133 | U40: =SUMIFS( CU535:CU606,CT535:CT606, U33, CS535:CS606, O33) -> 2066 | V40: =SUMIFS( CU535:CU606,CT535:CT606, V33, CS535:CS606, O33) -> 305 | W40: =SUMIFS( CU535:CU606,CT535:CT606, W33, CS535:CS606, O33) -> 645 | X40: =SUMIFS( CU535:CU606,CT535:CT606, X33, CS535:CS606, O33) -> 205 | Y40: =SUMIFS( CU535:CU606,CT535:CT606, Y33, CS535:CS606, O33) -> 376 | Z40: =SUM(P40:Y40) -> 99598 | AB40: 1991-2000 | AC40: 69 | AD40: 274 | AE40: 536 | AF40: 3008 | AG40: 30986 | AH40: 21728 | AI40: 5353 | AJ40: 1606 | AK40: 558 | AL40: =SUM(AC40:AK40) -> 64118 | AN40: 1991-2000 | AO40: =AC40/AL40 -> 0.0010761409 | AP40: =AD40/AL40 -> 0.004273371 | AQ40: =AE40/AL40 -> 0.008359587 | AR40: =AF40/AL40 -> 0.046913503 | AS40: =AG40/AL40 -> 0.48326523 | AT40: =AH40/AL40 -> 0.3388752 | AU40: =AI40/AL40 -> 0.083486696 | AV40: =AJ40/AL40 -> 0.025047569 | AW40: =AK40/AL40 -> 0.0087027044 | AZ40: =AO39*$Z$39 -> 75.384078 | BA40: =AP39*$Z$39 -> 72.033674 | BB40: =AQ39*$Z$39 -> 502.56052 | BC40: =AR39*$Z$39 -> 3263.293 | BD40: =AS39*$Z$39 -> 31157.077 | BE40: =AT39*$Z$39 -> 25473.117 | BF40: =AU39*$Z$39 -> 8757.9546 | BG40: =AV39*$Z$39 -> 2385.4873 | BH40: =AW39*$Z$39 -> 1392.0926 | BL40: E | BM40: =(P34*AU34+P35*AU35+P36*AU36+P37*AU37+P38*AU38+P39*AU39+P40*AU40+P41*AU41+P42*AU42+P43/9)*BX43 -> 1597.2423 | BN40: =(Q34*AU34+Q35*AU35+Q36*AU36+Q37*AU37+Q38*AU38+Q39*AU39+Q40*AU40+Q41*AU41+Q42*AU42+Q43/9)*BX43 -> 31052.311 | BO40: =(R34*AU34+R35*AU35+R36*AU36+R37*AU37+R38*AU38+R39*AU39+R40*AU40+R41*AU41+R42*AU42+R43/9)*BX43 -> 53130.666 | BP40: =(S34*AU34+S35*AU35+S36*AU36+S37*AU37+S38*AU38+S39*AU39+S40*AU40+S41*AU41+S42*AU42+S43/9)*BX43 -> 4452.5034 | BQ40: =(T34*AU34+T35*AU35+T36*AU36+T37*AU37+T38*AU38+T39*AU39+T40*AU40+T41*AU41+T42*AU42+T43/9)*BX43 -> 6690.3851 | BR40: =(U34*AU34+U35*AU35+U36*AU36+U37*AU37+U38*AU38+U39*AU39+U40*AU40+U41*AU41+U42*AU42+U43/9)*BX43 -> 2700.9801 | BS40: =(V34*AU34+V35*AU35+V36*AU36+V37*AU37+V38*AU38+V39*AU39+V40*AU40+V41*AU41+V42*AU42+V43/9)*BX43 -> 271.97706 | BT40: =(W34*AU34+W35*AU35+W36*AU36+W37*AU37+W38*AU38+W39*AU39+W40*AU40+W41*AU41+W42*AU42+W43/9)*BX43 -> 981.55177 | BU40: =(X34*AU34+X35*AU35+X36*AU36+X37*AU37+X38*AU38+X39*AU39+X40*AU40+X41*AU41+X42*AU42+X43/9)*BX43 -> 245.86984 | BV40: =(Y34*AU34+Y35*AU35+Y36*AU36+Y37*AU37+Y38*AU38+Y39*AU39+Y40*AU40+Y41*AU41+Y42*AU42+Y43/9)*BX43 -> 1520.2856 | BW40: =AVERAGE(BQ40,BR40,BT40)/3 -> 1152.5463 | CD40: 1919 to 1945 | CE40: 25149 | CL40: Oil | CM40: 165422 | CR40: Before 1919 | CS40: Attached | CT40: Oil | CU40: 6318
B41: 2001-2010 | D41: =SUMIFS(INDEX(Table5[],,MATCH(B33,Table5[#Headers],0)),Table5[MainSpaceHeatingFuel],"*Oil",Table5[Year_of_Construction (group)],B41) -> 38126 | E41: =SUMIFS(INDEX(Table5[],,MATCH(B33,Table5[#Headers],0)),Table5[MainSpaceHeatingFuel],"Mains Gas",Table5[Year_of_Construction (group)],B41) -> 61716 | F41: =SUMIFS(INDEX(Table5[],,MATCH(B33,Table5[#Headers],0)),Table5[MainSpaceHeatingFuel],F21,Table5[Year_of_Construction (group)],B41) -> 7057 | G41: =SUMIFS(INDEX(Table5[],,MATCH(B33,Table5[#Headers],0)),Table5[MainSpaceHeatingFuel],"*Coal",Table5[Year_of_Construction (group)],B41) -> 586 | H41: =SUMIFS(INDEX(Table5[],,MATCH(B33,Table5[#Headers],0)),Table5[MainSpaceHeatingFuel],"*Peat*",Table5[Year_of_Construction (group)],B41) -> 56 | I41: =SUMIFS(INDEX(Table5[],,MATCH(B33,Table5[#Headers],0)),Table5[MainSpaceHeatingFuel],"*LPG*",Table5[Year_of_Construction (group)],B41) -> 3355 | J41: =SUMIFS(INDEX(Table5[],,MATCH(B33,Table5[#Headers],0)),Table5[MainSpaceHeatingFuel],"*Wood*",Table5[Year_of_Construction (group)],B41) -> 181 | K41: =SUMIFS(INDEX(Table5[],,MATCH(B33,Table5[#Headers],0)),Table5[MainSpaceHeatingFuel],"*Multi-Fuel*",Table5[Year_of_Construction (group)],B41) -> 4072 | L41: =SUMIFS(INDEX(Table5[],,MATCH(B33,Table5[#Headers],0)),Table5[MainSpaceHeatingFuel],"",Table5[Year_of_Construction (group)],B41) -> 356 | M41: =SUM(C41:L41) -> 115505 | O41: 2001-2010 | P41: =SUMIFS( CU620:CU691,CT620:CT691, P33, CS620:CS691, O33) -> 652 | Q41: =SUMIFS( CU620:CU691,CT620:CT691, Q33, CS620:CS691, O33) -> 51402 | R41: =SUMIFS( CU620:CU691,CT620:CT691, R33, CS620:CS691, O33) -> 95400 | S41: =SUMIFS( CU620:CU691,CT620:CT691, S33, CS620:CS691, O33) -> 6741 | T41: =SUMIFS( CU620:CU691,CT620:CT691, T33, CS620:CS691, O33) -> 6981 | U41: =SUMIFS( CU620:CU691,CT620:CT691, U33, CS620:CS691, O33) -> 2601 | V41: =SUMIFS( CU620:CU691,CT620:CT691, V33, CS620:CS691, O33) -> 1478 | W41: =SUMIFS( CU620:CU691,CT620:CT691, W33, CS620:CS691, O33) -> 1160 | X41: =SUMIFS( CU620:CU691,CT620:CT691, X33, CS620:CS691, O33) -> 446 | Y41: =SUMIFS( CU620:CU691,CT620:CT691, Y33, CS620:CS691, O33) -> 690 | Z41: =SUM(P41:Y41) -> 167551 | AB41: 2001-2010 | AC41: 521 | AD41: 1666 | AE41: 5056 | AF41: 16625 | AG41: 73117 | AH41: 13951 | AI41: 3496 | AJ41: 892 | AK41: 183 | AL41: =SUM(AC41:AK41) -> 115507 | AN41: 2001-2010 | AO41: =AC41/AL41 -> 0.0045105491 | AP41: =AD41/AL41 -> 0.014423368 | AQ41: =AE41/AL41 -> 0.043772239 | AR41: =AF41/AL41 -> 0.14393067 | AS41: =AG41/AL41 -> 0.63300925 | AT41: =AH41/AL41 -> 0.12078056 | AU41: =AI41/AL41 -> 0.030266564 | AV41: =AJ41/AL41 -> 0.0077224757 | AW41: =AK41/AL41 -> 0.0015843196 | AZ41: =AO40*$Z$40 -> 107.18148 | BA41: =AP40*$Z$40 -> 425.6192 | BB41: =AQ40*$Z$40 -> 832.59815 | BC41: =AR40*$Z$40 -> 4672.4911 | BD41: =AS40*$Z$40 -> 48132.25 | BE41: =AT40*$Z$40 -> 33751.292 | BF41: =AU40*$Z$40 -> 8315.108 | BG41: =AV40*$Z$40 -> 2494.6877 | BH41: =AW40*$Z$40 -> 866.77195 | BL41: F | BM41: =(P34*AV34+P35*AV35+P36*AV36+P37*AV37+P38*AV38+P39*AV39+P40*AV40+P41*AV41+P42*AV42+P43/9)*BX43 -> 907.3325 | BN41: =(Q34*AV34+Q35*AV35+Q36*AV36+Q37*AV37+Q38*AV38+Q39*AV39+Q40*AV40+Q41*AV41+Q42*AV42+Q43/9)*BX43 -> 14837.528 | BO41: =(R34*AV34+R35*AV35+R36*AV36+R37*AV37+R38*AV38+R39*AV39+R40*AV40+R41*AV41+R42*AV42+R43/9)*BX43 -> 25918.29 | BP41: =(S34*AV34+S35*AV35+S36*AV36+S37*AV37+S38*AV38+S39*AV39+S40*AV40+S41*AV41+S42*AV42+S43/9)*BX43 -> 2414.1366 | BQ41: =(T34*AV34+T35*AV35+T36*AV36+T37*AV37+T38*AV38+T39*AV39+T40*AV40+T41*AV41+T42*AV42+T43/9)*BX43 -> 3263.3522 | BR41: =(U34*AV34+U35*AV35+U36*AV36+U37*AV37+U38*AV38+U39*AV39+U40*AV40+U41*AV41+U42*AV42+U43/9)*BX43 -> 1333.71 | BS41: =(V34*AV34+V35*AV35+V36*AV36+V37*AV37+V38*AV38+V39*AV39+V40*AV40+V41*AV41+V42*AV42+V43/9)*BX43 -> 130.16782 | BT41: =(W34*AV34+W35*AV35+W36*AV36+W37*AV37+W38*AV38+W39*AV39+W40*AV40+W41*AV41+W42*AV42+W43/9)*BX43 -> 500.67955 | BU41: =(X34*AV34+X35*AV35+X36*AV36+X37*AV37+X38*AV38+X39*AV39+X40*AV40+X41*AV41+X42*AV42+X43/9)*BX43 -> 127.16488 | BV41: =(Y34*AV34+Y35*AV35+Y36*AV36+Y37*AV37+Y38*AV38+Y39*AV39+Y40*AV40+Y41*AV41+Y42*AV42+Y43/9)*BX43 -> 1296.8096 | BW41: =AVERAGE(BQ41,BR41,BT41)/3 -> 566.41575 | CR41: Before 1919 | CS41: Attached | CT41: Natural Gas | CU41: 5273
B42: Later_2010 | D42: =SUMIFS(INDEX(Table5[],,MATCH(B33,Table5[#Headers],0)),Table5[MainSpaceHeatingFuel],"*Oil",Table5[Year_of_Construction (group)],B42) -> 1018 | E42: =SUMIFS(INDEX(Table5[],,MATCH(B33,Table5[#Headers],0)),Table5[MainSpaceHeatingFuel],"Mains Gas",Table5[Year_of_Construction (group)],B42) -> 19609 | F42: =SUMIFS(INDEX(Table5[],,MATCH(B33,Table5[#Headers],0)),Table5[MainSpaceHeatingFuel],F21,Table5[Year_of_Construction (group)],B42) -> 10902 | G42: =SUMIFS(INDEX(Table5[],,MATCH(B33,Table5[#Headers],0)),Table5[MainSpaceHeatingFuel],"*Coal",Table5[Year_of_Construction (group)],B42) -> 0 | H42: =SUMIFS(INDEX(Table5[],,MATCH(B33,Table5[#Headers],0)),Table5[MainSpaceHeatingFuel],"*Peat*",Table5[Year_of_Construction (group)],B42) -> 0 | I42: =SUMIFS(INDEX(Table5[],,MATCH(B33,Table5[#Headers],0)),Table5[MainSpaceHeatingFuel],"*LPG*",Table5[Year_of_Construction (group)],B42) -> 188 | J42: =SUMIFS(INDEX(Table5[],,MATCH(B33,Table5[#Headers],0)),Table5[MainSpaceHeatingFuel],"*Wood*",Table5[Year_of_Construction (group)],B42) -> 10 | K42: =SUMIFS(INDEX(Table5[],,MATCH(B33,Table5[#Headers],0)),Table5[MainSpaceHeatingFuel],"*Multi-Fuel*",Table5[Year_of_Construction (group)],B42) -> 9 | L42: =SUMIFS(INDEX(Table5[],,MATCH(B33,Table5[#Headers],0)),Table5[MainSpaceHeatingFuel],"",Table5[Year_of_Construction (group)],B42) -> 227 | M42: =SUM(C42:L42) -> 31963 | O42: Later_2010 | P42: =SUMIFS( CU705:CU776,CT705:CT776, P33, CS705:CS776, O33) -> 33 | Q42: =SUMIFS( CU705:CU776,CT705:CT776, Q33, CS705:CS776, O33) -> 1565 | R42: =SUMIFS( CU705:CU776,CT705:CT776, R33, CS705:CS776, O33) -> 5862 | S42: =SUMIFS( CU705:CU776,CT705:CT776, S33, CS705:CS776, O33) -> 907 | T42: =SUMIFS( CU705:CU776,CT705:CT776, T33, CS705:CS776, O33) -> 198 | U42: =SUMIFS( CU705:CU776,CT705:CT776, U33, CS705:CS776, O33) -> 75 | V42: =SUMIFS( CU705:CU776,CT705:CT776, V33, CS705:CS776, O33) -> 53 | W42: =SUMIFS( CU705:CU776,CT705:CT776, W33, CS705:CS776, O33) -> 80 | X42: =SUMIFS( CU705:CU776,CT705:CT776, X33, CS705:CS776, O33) -> 185 | Y42: =SUMIFS( CU705:CU776,CT705:CT776, Y33, CS705:CS776, O33) -> 69 | Z42: =SUM(P42:Y42) -> 9027 | AB42: Later_2010 | AC42: 29914 | AD42: 1251 | AE42: 470 | AF42: 206 | AG42: 103 | AH42: 18 | AJ42: 1 | AL42: =SUM(AC42:AK42) -> 31963 | AN42: Later_2010 | AO42: =AC42/AL42 -> 0.93589463 | AP42: =AD42/AL42 -> 0.039139004 | AQ42: =AE42/AL42 -> 0.014704502 | AR42: =AF42/AL42 -> 0.006444952 | AS42: =AG42/AL42 -> 0.003222476 | AT42: =AH42/AL42 -> 0.00056315114 | AU42: =AI42/AL42 -> 0 | AV42: =AJ42/AL42 -> 3.1286175e-05 | AW42: =AK42/AL42 -> 0 | AZ42: =AO41*$Z$41 -> 755.74702 | BA42: =AP41*$Z$41 -> 2416.6498 | BB42: =AQ41*$Z$41 -> 7334.0824 | BC42: =AR41*$Z$41 -> 24115.728 | BD42: =AS41*$Z$41 -> 106061.33 | BE42: =AT41*$Z$41 -> 20236.903 | BF42: =AU41*$Z$41 -> 5071.1931 | BG42: =AV41*$Z$41 -> 1293.9085 | BH42: =AW41*$Z$41 -> 265.45433 | BL42: G | BM42: =(P34*AW34+P35*AW35+P36*AW36+P37*AW37+P38*AW38+P39*AW39+P40*AW40+P41*AW41+P42*AW42+P43/9)*BX43 -> 1210.2555 | BN42: =(Q34*AW34+Q35*AW35+Q36*AW36+Q37*AW37+Q38*AW38+Q39*AW39+Q40*AW40+Q41*AW41+Q42*AW42+Q43/9)*BX43 -> 15130.944 | BO42: =(R34*AW34+R35*AW35+R36*AW36+R37*AW37+R38*AW38+R39*AW39+R40*AW40+R41*AW41+R42*AW42+R43/9)*BX43 -> 26996.66 | BP42: =(S34*AW34+S35*AW35+S36*AW36+S37*AW37+S38*AW38+S39*AW39+S40*AW40+S41*AW41+S42*AW42+S43/9)*BX43 -> 2871.8314 | BQ42: =(T34*AW34+T35*AW35+T36*AW36+T37*AW37+T38*AW38+T39*AW39+T40*AW40+T41*AW41+T42*AW42+T43/9)*BX43 -> 3475.3849 | BR42: =(U34*AW34+U35*AW35+U36*AW36+U37*AW37+U38*AW38+U39*AW39+U40*AW40+U41*AW41+U42*AW42+U43/9)*BX43 -> 1461.9315 | BS42: =(V34*AW34+V35*AW35+V36*AW36+V37*AW37+V38*AW38+V39*AW39+V40*AW40+V41*AW41+V42*AW42+V43/9)*BX43 -> 139.59561 | BT42: =(W34*AW34+W35*AW35+W36*AW36+W37*AW37+W38*AW38+W39*AW39+W40*AW40+W41*AW41+W42*AW42+W43/9)*BX43 -> 586.38098 | BU42: =(X34*AW34+X35*AW35+X36*AW36+X37*AW37+X38*AW38+X39*AW39+X40*AW40+X41*AW41+X42*AW42+X43/9)*BX43 -> 144.51318 | BV42: =(Y34*AW34+Y35*AW35+Y36*AW36+Y37*AW37+Y38*AW38+Y39*AW39+Y40*AW40+Y41*AW41+Y42*AW42+Y43/9)*BX43 -> 1325.7365 | BW42: =AVERAGE(BQ42,BR42,BT42)/3 -> 613.74416 | CD42: 1946 to 1960 | CE42: 39121 | CL42: Natural Gas | CM42: 235910 | CR42: Before 1919 | CS42: Attached | CT42: Electricity | CU42: 836
B43: Total | C43: =SUM(C34:C42) -> 0 | D43: =SUM(D34:D42) -> 124317 | E43: =SUM(E34:E42) -> 225374 | F43: =SUM(F34:F42) -> 34746 | G43: =SUM(G34:G42) -> 6874 | H43: =SUM(H34:H42) -> 619 | I43: =SUM(I34:I42) -> 4633 | J43: =SUM(J34:J42) -> 483 | ... L43: =SUM(L34:L42) -> 1017 | M43: =SUM(C43:L43) -> 414954 | O43: Not Stated | P43: =SUMIFS( $CU$777:$CU$861,$CT$777:$CT$861, P33, $CS$777:$CS$861, $O$33) -> 522 | Q43: =SUMIFS( $CU$777:$CU$861,$CT$777:$CT$861, Q33, $CS$777:$CS$861, $O$33) -> 10878 | R43: =SUMIFS( $CU$777:$CU$861,$CT$777:$CT$861, R33, $CS$777:$CS$861, $O$33) -> 17382 | S43: =SUMIFS( $CU$777:$CU$861,$CT$777:$CT$861, S33, $CS$777:$CS$861, $O$33) -> 3626 | T43: =SUMIFS( $CU$777:$CU$861,$CT$777:$CT$861, T33, $CS$777:$CS$861, $O$33) -> 2231 | U43: =SUMIFS( $CU$777:$CU$861,$CT$777:$CT$861, U33, $CS$777:$CS$861, $O$33) -> 631 | V43: =SUMIFS( $CU$777:$CU$861,$CT$777:$CT$861, V33, $CS$777:$CS$861, $O$33) -> 155 | W43: =SUMIFS( $CU$777:$CU$861,$CT$777:$CT$861, W33, $CS$777:$CS$861, $O$33) -> 266 | ... Y43: =SUMIFS( $CU$777:$CU$861,$CT$777:$CT$861, Y33, $CS$777:$CS$861, $O$33) -> 9533 | Z43: =SUM(P43:Y43) -> 45367 | AB43: Total | AC43: =SUM(AC34:AC42) -> 30917 | AD43: =SUM(AD34:AD42) -> 3722 | AE43: =SUM(AE34:AE42) -> 7882 | AF43: =SUM(AF34:AF42) -> 27081 | AG43: =SUM(AG34:AG42) -> 161926 | AH43: =SUM(AH34:AH42) -> 95372 | AI43: =SUM(AI34:AI42) -> 46130 | AJ43: =SUM(AJ34:AJ42) -> 20720 | ... AL43: =SUM(AL34:AL42) -> 414958 | AZ43: =AO42*$Z$42 -> 8448.3208 | BA43: =AP42*$Z$42 -> 353.30779 | BB43: =AQ42*$Z$42 -> 132.73754 | BC43: =AR42*$Z$42 -> 58.178581 | BD43: =AS42*$Z$42 -> 29.089291 | BE43: =AT42*$Z$42 -> 5.0835654 | BF43: =AU42*$Z$42 -> 0 | BG43: =AV42*$Z$42 -> 0.2824203 | BH43: =AW42*$Z$42 -> 0 | BX43: 1.0252344 | CD43: 1961 to 1970 | CE43: 43364 | CL43: Electricity | CM43: 15517 | CR43: Before 1919 | CS43: Attached | CT43: Coal (incl. Anthracite_Coal) | CU43: 1077
O44: Total | P44: =SUM(P34:P43) -> 9027 | Q44: =SUM(Q34:Q43) -> 227017 | R44: =SUM(R34:R43) -> 398797 | S44: =SUM(S34:S43) -> 33961 | T44: =SUM(T34:T43) -> 45740 | U44: =SUM(U34:U43) -> 17793 | V44: =SUM(V34:V43) -> 2954 | W44: =SUM(W34:W43) -> 6594 | ... Y44: =SUM(Y34:Y43) -> 12622 | Z44: =SUM(P44:Y44) -> 756517 | AZ44: =$Z$43/9 -> 5040.7778 | BA44: =$Z$43/9 -> 5040.7778 | BB44: =$Z$43/9 -> 5040.7778 | BC44: =$Z$43/9 -> 5040.7778 | BD44: =$Z$43/9 -> 5040.7778 | BE44: =$Z$43/9 -> 5040.7778 | BF44: =$Z$43/9 -> 5040.7778 | BG44: =$Z$43/9 -> 5040.7778 | BH44: =$Z$43/9 -> 5040.7778 | CD44: 1971 to 1980 | CE44: 71056 | CL44: Coal (incl. Anthracite_Coal) | CM44: 25563 | CR44: Before 1919 | CS44: Attached | CT44: Peat (incl. turf) | CU44: 831
B45: Detached | C45: No central heating | D45: Oil | E45: Natural Gas | F45: Electricity | G45: Coal (incl. Anthracite_Coal) | H45: Peat (incl. turf) | I45: Liquid Petroleum Gas (LPG) | J45: Wood (incl. wood pellets) | K45: Other fuels | L45: Not stated | O45: Detached | P45: No central heating | Q45: Oil | R45: Natural Gas | S45: Electricity | T45: Coal (incl. Anthracite_Coal) | U45: Peat (incl. turf) | V45: Liquid Petroleum Gas (LPG) | W45: Wood (incl. wood pellets) | X45: Other fuels | Y45: Not stated | AB45: Detached | AC45: A | AD45: B1 | AE45: B2 | AF45: B3 | AG45: C | AH45: D | AI45: E | AJ45: F | AK45: G | AN45: Detached | AO45: A | AP45: B1 | AQ45: B2 | AR45: B3 | AS45: C | AT45: D | AU45: E | AV45: F | AW45: G | AY45: Total | AZ45: =SUM(AZ35:AZ44) -> 15273.518 | BA45: =SUM(BA35:BA44) -> 9415.3785 | BB45: =SUM(BB35:BB44) -> 17319.934 | BC45: =SUM(BC35:BC44) -> 49130.158 | BD45: =SUM(BD35:BD44) -> 278530.63 | BE45: =SUM(BE35:BE44) -> 185219.17 | BF45: =SUM(BF35:BF44) -> 100117.37 | BG45: =SUM(BG35:BG44) -> 49480.559 | BH45: =SUM(BH35:BH44) -> 52030.281 | BI45: =SUM(AZ45:BH45) -> 756517 | BJ45: 1.013 | BL45: Detached | BM45: No central heating | BN45: Oil | BO45: Natural Gas | BP45: Electricity | BQ45: Coal (incl. Anthracite_Coal) | BR45: Peat (incl. turf) | BS45: Liquid Petroleum Gas (LPG) | BT45: Wood (incl. wood pellets) | BU45: Other fuels | BV45: Not stated | BW45: Solid Multi Fuel | CD45: 1981 to 1990 | CE45: 49522 | CL45: Peat (incl. turf) | CM45: 12102 | CR45: Before 1919 | CS45: Attached | CT45: Liquid Petroleum Gas (LPG) | CU45: 85
B46: Before_1919 | D46: =SUMIFS(INDEX(Table5[],,MATCH(B45,Table5[#Headers],0)),Table5[MainSpaceHeatingFuel],"*Oil",Table5[Year_of_Construction (group)],B46) -> 14309 | E46: =SUMIFS(INDEX(Table5[],,MATCH(B45,Table5[#Headers],0)),Table5[MainSpaceHeatingFuel],"Mains Gas",Table5[Year_of_Construction (group)],B46) -> 1169 | F46: =SUMIFS(INDEX(Table5[],,MATCH(B45,Table5[#Headers],0)),Table5[MainSpaceHeatingFuel],F21,Table5[Year_of_Construction (group)],B46) -> 2184 | G46: =SUMIFS(INDEX(Table5[],,MATCH(B45,Table5[#Headers],0)),Table5[MainSpaceHeatingFuel],"*Coal",Table5[Year_of_Construction (group)],B46) -> 307 | H46: =SUMIFS(INDEX(Table5[],,MATCH(B45,Table5[#Headers],0)),Table5[MainSpaceHeatingFuel],"*Peat*",Table5[Year_of_Construction (group)],B46) -> 143 | I46: =SUMIFS(INDEX(Table5[],,MATCH(B45,Table5[#Headers],0)),Table5[MainSpaceHeatingFuel],"*LPG*",Table5[Year_of_Construction (group)],B46) -> 416 | J46: =SUMIFS(INDEX(Table5[],,MATCH(B45,Table5[#Headers],0)),Table5[MainSpaceHeatingFuel],"*Wood*",Table5[Year_of_Construction (group)],B46) -> 153 | K46: =SUMIFS(INDEX(Table5[],,MATCH(B45,Table5[#Headers],0)),Table5[MainSpaceHeatingFuel],"*Multi-Fuel*",Table5[Year_of_Construction (group)],B46) -> 2455 | L46: =SUMIFS(INDEX(Table5[],,MATCH(B45,Table5[#Headers],0)),Table5[MainSpaceHeatingFuel],"",Table5[Year_of_Construction (group)],B46) -> 23 | M46: =SUM(C46:L46) -> 21159 | O46: Before_1919 | P46: =SUMIFS( CU14:CU96,CT14:CT96, P45, CS14:CS96, O45) -> 3486 | Q46: =SUMIFS( CU14:CU96,CT14:CT96, Q45, CS14:CS96, O45) -> 42672 | R46: =SUMIFS( CU14:CU96,CT14:CT96, R45, CS14:CS96, O45) -> 3088 | S46: =SUMIFS( CU14:CU96,CT14:CT96, S45, CS14:CS96, O45) -> 2096 | T46: =SUMIFS( CU14:CU96,CT14:CT96, T45, CS14:CS96, O45) -> 6482 | U46: =SUMIFS( CU14:CU96,CT14:CT96, U45, CS14:CS96, O45) -> 9242 | V46: =SUMIFS( CU14:CU96,CT14:CT96, V45, CS14:CS96, O45) -> 574 | W46: =SUMIFS( CU14:CU96,CT14:CT96, W45, CS14:CS96, O45) -> 5593 | X46: =SUMIFS( CU14:CU96,CT14:CT96, X45, CS14:CS96, O45) -> 473 | Y46: =SUMIFS( CU14:CU96,CT14:CT96, Y45, CS14:CS96, O45) -> 419 | Z46: =SUM(P46:Y46) -> 74125 | AB46: Before_1919 | AC46: 73 | AD46: 77 | AE46: 165 | AF46: 337 | AG46: 1930 | AH46: 3323 | AI46: 3790 | AJ46: 3009 | AK46: 8455 | AL46: =SUM(AC46:AK46) -> 21159 | AN46: Before_1919 | AO46: =AC46/AL46 -> 0.0034500685 | AP46: =AD46/AL46 -> 0.0036391134 | AQ46: =AE46/AL46 -> 0.0077981001 | AR46: =AF46/AL46 -> 0.015927029 | AS46: =AG46/AL46 -> 0.091214141 | AT46: =AH46/AL46 -> 0.15704901 | AU46: =AI46/AL46 -> 0.17912 | AV46: =AJ46/AL46 -> 0.14220899 | AW46: =AK46/AL46 -> 0.39959355 | AY46: Adjusted Total | AZ46: =AZ45*$BJ$32 -> 15472.074 | BA46: =BA45*$BJ$32 -> 9537.7784 | BB46: =BB45*$BJ$32 -> 17545.093 | BC46: =BC45*$BJ$32 -> 49768.85 | BD46: =BD45*$BJ$32 -> 282151.53 | BE46: =BE45*$BJ$32 -> 187627.02 | BF46: =BF45*$BJ$32 -> 101418.9 | BG46: =BG45*$BJ$32 -> 50123.806 | BH46: =BH45*$BJ$32 -> 52706.674 | BI46: =SUM(AZ46:BH46) -> 766351.72 | BL46: A | BM46: =(P46*AO46+P47*AO47+P48*AO48+P49*AO49+P50*AO50+P51*AO51+P52*AO52+P53*AO53+P54*AO54+P55/9)*BX55 -> 187.96821 | BN46: =(Q46*AO46+Q47*AO47+Q48*AO48+Q49*AO49+Q50*AO50+Q51*AO51+Q52*AO52+Q53*AO53+Q54*AO54+Q55/9)*BX55 -> 10715.079 | BO46: =(R46*AO46+R47*AO47+R48*AO48+R49*AO49+R50*AO50+R51*AO51+R52*AO52+R53*AO53+R54*AO54+R55/9)*BX55 -> 2492.9354 | BP46: =(S46*AO46+S47*AO47+S48*AO48+S49*AO49+S50*AO50+S51*AO51+S52*AO52+S53*AO53+S54*AO54+S55/9)*BX55 -> 2117.7742 | BQ46: =(T46*AO46+T47*AO47+T48*AO48+T49*AO49+T50*AO50+T51*AO51+T52*AO52+T53*AO53+T54*AO54+T55/9)*BX55 -> 636.87817 | BR46: =(U46*AO46+U47*AO47+U48*AO48+U49*AO49+U50*AO50+U51*AO51+U52*AO52+U53*AO53+U54*AO54+U55/9)*BX55 -> 1530.4366 | BS46: =(V46*AO46+V47*AO47+V48*AO48+V49*AO49+V50*AO50+V51*AO51+V52*AO52+V53*AO53+V54*AO54+V55/9)*BX55 -> 165.0403 | BT46: =(W46*AO46+W47*AO47+W48*AO48+W49*AO49+W50*AO50+W51*AO51+W52*AO52+W53*AO53+W54*AO54+W55/9)*BX55 -> 971.22047 | BU46: =(X46*AO46+X47*AO47+X48*AO48+X49*AO49+X50*AO50+X51*AO51+X52*AO52+X53*AO53+X54*AO54+X55/9)*BX55 -> 1187.916 | BV46: =(Y46*AO46+Y47*AO47+Y48*AO48+Y49*AO49+Y50*AO50+Y51*AO51+Y52*AO52+Y53*AO53+Y54*AO54+Y55/9)*BX55 -> 628.80572 | BW46: =AVERAGE(BQ46,BR46,BT46)/3 -> 348.72614 | CD46: 1991 to 2000 | CE46: 80437 | CL46: Liquid Petroleum Gas (LPG) | CM46: 1972 | CR46: Before 1919 | CS46: Attached | CT46: Wood (incl. wood pellets) | CU46: 420
B47: 1919-1945 | D47: =SUMIFS(INDEX(Table5[],,MATCH(B45,Table5[#Headers],0)),Table5[MainSpaceHeatingFuel],"*Oil",Table5[Year_of_Construction (group)],B47) -> 10518 | E47: =SUMIFS(INDEX(Table5[],,MATCH(B45,Table5[#Headers],0)),Table5[MainSpaceHeatingFuel],"Mains Gas",Table5[Year_of_Construction (group)],B47) -> 1646 | F47: =SUMIFS(INDEX(Table5[],,MATCH(B45,Table5[#Headers],0)),Table5[MainSpaceHeatingFuel],F21,Table5[Year_of_Construction (group)],B47) -> 1386 | G47: =SUMIFS(INDEX(Table5[],,MATCH(B45,Table5[#Headers],0)),Table5[MainSpaceHeatingFuel],"*Coal",Table5[Year_of_Construction (group)],B47) -> 256 | H47: =SUMIFS(INDEX(Table5[],,MATCH(B45,Table5[#Headers],0)),Table5[MainSpaceHeatingFuel],"*Peat*",Table5[Year_of_Construction (group)],B47) -> 121 | I47: =SUMIFS(INDEX(Table5[],,MATCH(B45,Table5[#Headers],0)),Table5[MainSpaceHeatingFuel],"*LPG*",Table5[Year_of_Construction (group)],B47) -> 241 | J47: =SUMIFS(INDEX(Table5[],,MATCH(B45,Table5[#Headers],0)),Table5[MainSpaceHeatingFuel],"*Wood*",Table5[Year_of_Construction (group)],B47) -> 90 | K47: =SUMIFS(INDEX(Table5[],,MATCH(B45,Table5[#Headers],0)),Table5[MainSpaceHeatingFuel],"*Multi-Fuel*",Table5[Year_of_Construction (group)],B47) -> 1763 | L47: =SUMIFS(INDEX(Table5[],,MATCH(B45,Table5[#Headers],0)),Table5[MainSpaceHeatingFuel],"",Table5[Year_of_Construction (group)],B47) -> 11 | M47: =SUM(C47:L47) -> 16032 | O47: 1919-1945 | P47: =SUMIFS( CU110:CU181,CT110:CT181, P45, CS110:CS181, O45) -> 1343 | Q47: =SUMIFS( CU110:CU181,CT110:CT181, Q45, CS110:CS181, O45) -> 25936 | R47: =SUMIFS( CU110:CU181,CT110:CT181, R45, CS110:CS181, O45) -> 3575 | S47: =SUMIFS( CU110:CU181,CT110:CT181, S45, CS110:CS181, O45) -> 1041 | T47: =SUMIFS( CU110:CU181,CT110:CT181, T45, CS110:CS181, O45) -> 4238 | U47: =SUMIFS( CU110:CU181,CT110:CT181, U45, CS110:CS181, O45) -> 7788 | V47: =SUMIFS( CU110:CU181,CT110:CT181, V45, CS110:CS181, O45) -> 266 | W47: =SUMIFS( CU110:CU181,CT110:CT181, W45, CS110:CS181, O45) -> 2251 | X47: =SUMIFS( CU110:CU181,CT110:CT181, X45, CS110:CS181, O45) -> 191 | Y47: =SUMIFS( CU110:CU181,CT110:CT181, Y45, CS110:CS181, O45) -> 218 | Z47: =SUM(P47:Y47) -> 46847 | AB47: 1919-1945 | AC47: 71 | AD47: 56 | AE47: 133 | AF47: 321 | AG47: 1698 | AH47: 2771 | AI47: 2825 | AJ47: 2170 | AK47: 5987 | AL47: =SUM(AC47:AK47) -> 16032 | AN47: 1919-1945 | AO47: =AC47/AL47 -> 0.0044286427 | AP47: =AD47/AL47 -> 0.003493014 | AQ47: =AE47/AL47 -> 0.0082959082 | AR47: =AF47/AL47 -> 0.020022455 | AS47: =AG47/AL47 -> 0.10591317 | AT47: =AH47/AL47 -> 0.17284182 | AU47: =AI47/AL47 -> 0.17621008 | AV47: =AJ47/AL47 -> 0.13535429 | AW47: =AK47/AL47 -> 0.37344062 | AY47: Detached | AZ47: A | BA47: B1 | BB47: B2 | BC47: B3 | BD47: C | BE47: D | BF47: E | BG47: F | BH47: G | BL47: B1 | BM47: =(P46*AP46+P47*AP47+P48*AP48+P49*AP49+P50*AP50+P51*AP51+P52*AP52+P53*AP53+P54*AP54+P55/9)*BX55 -> 84.287931 | BN47: =(Q46*AP46+Q47*AP47+Q48*AP48+Q49*AP49+Q50*AP50+Q51*AP51+Q52*AP52+Q53*AP53+Q54*AP54+Q55/9)*BX55 -> 5422.2427 | BO47: =(R46*AP46+R47*AP47+R48*AP48+R49*AP49+R50*AP50+R51*AP51+R52*AP52+R53*AP53+R54*AP54+R55/9)*BX55 -> 1318.6039 | BP47: =(S46*AP46+S47*AP47+S48*AP48+S49*AP49+S50*AP50+S51*AP51+S52*AP52+S53*AP53+S54*AP54+S55/9)*BX55 -> 490.82217 | BQ47: =(T46*AP46+T47*AP47+T48*AP48+T49*AP49+T50*AP50+T51*AP51+T52*AP52+T53*AP53+T54*AP54+T55/9)*BX55 -> 377.08548 | BR47: =(U46*AP46+U47*AP47+U48*AP48+U49*AP49+U50*AP50+U51*AP51+U52*AP52+U53*AP53+U54*AP54+U55/9)*BX55 -> 682.4236 | BS47: =(V46*AP46+V47*AP47+V48*AP48+V49*AP49+V50*AP50+V51*AP51+V52*AP52+V53*AP53+V54*AP54+V55/9)*BX55 -> 75.438607 | BT47: =(W46*AP46+W47*AP47+W48*AP48+W49*AP49+W50*AP50+W51*AP51+W52*AP52+W53*AP53+W54*AP54+W55/9)*BX55 -> 331.9527 | BU47: =(X46*AP46+X47*AP47+X48*AP48+X49*AP49+X50*AP50+X51*AP51+X52*AP52+X53*AP53+X54*AP54+X55/9)*BX55 -> 229.23177 | BV47: =(Y46*AP46+Y47*AP47+Y48*AP48+Y49*AP49+Y50*AP50+Y51*AP51+Y52*AP52+Y53*AP53+Y54*AP54+Y55/9)*BX55 -> 540.02012 | BW47: =AVERAGE(BQ47,BR47,BT47)/3 -> 154.60686 | CD47: 2001 to 2010 | CE47: 115869 | CL47: Wood (incl. wood pellets) | CM47: 4276 | CR47: Before 1919 | CS47: Attached | CT47: Other fuels | CU47: 76
B48: 1946-1960 | D48: =SUMIFS(INDEX(Table5[],,MATCH(B45,Table5[#Headers],0)),Table5[MainSpaceHeatingFuel],"*Oil",Table5[Year_of_Construction (group)],B48) -> 9928 | E48: =SUMIFS(INDEX(Table5[],,MATCH(B45,Table5[#Headers],0)),Table5[MainSpaceHeatingFuel],"Mains Gas",Table5[Year_of_Construction (group)],B48) -> 2121 | F48: =SUMIFS(INDEX(Table5[],,MATCH(B45,Table5[#Headers],0)),Table5[MainSpaceHeatingFuel],F21,Table5[Year_of_Construction (group)],B48) -> 923 | G48: =SUMIFS(INDEX(Table5[],,MATCH(B45,Table5[#Headers],0)),Table5[MainSpaceHeatingFuel],"*Coal",Table5[Year_of_Construction (group)],B48) -> 176 | H48: =SUMIFS(INDEX(Table5[],,MATCH(B45,Table5[#Headers],0)),Table5[MainSpaceHeatingFuel],"*Peat*",Table5[Year_of_Construction (group)],B48) -> 96 | I48: =SUMIFS(INDEX(Table5[],,MATCH(B45,Table5[#Headers],0)),Table5[MainSpaceHeatingFuel],"*LPG*",Table5[Year_of_Construction (group)],B48) -> 175 | J48: =SUMIFS(INDEX(Table5[],,MATCH(B45,Table5[#Headers],0)),Table5[MainSpaceHeatingFuel],"*Wood*",Table5[Year_of_Construction (group)],B48) -> 52 | K48: =SUMIFS(INDEX(Table5[],,MATCH(B45,Table5[#Headers],0)),Table5[MainSpaceHeatingFuel],"*Multi-Fuel*",Table5[Year_of_Construction (group)],B48) -> 1206 | L48: =SUMIFS(INDEX(Table5[],,MATCH(B45,Table5[#Headers],0)),Table5[MainSpaceHeatingFuel],"",Table5[Year_of_Construction (group)],B48) -> 5 | M48: =SUM(C48:L48) -> 14682 | O48: 1946-1960 | P48: =SUMIFS( CU195:CU266,CT195:CT266, P45, CS195:CS266, O45) -> 834 | Q48: =SUMIFS( CU195:CU266,CT195:CT266, Q45, CS195:CS266, O45) -> 23868 | R48: =SUMIFS( CU195:CU266,CT195:CT266, R45, CS195:CS266, O45) -> 4865 | S48: =SUMIFS( CU195:CU266,CT195:CT266, S45, CS195:CS266, O45) -> 864 | T48: =SUMIFS( CU195:CU266,CT195:CT266, T45, CS195:CS266, O45) -> 3293 | U48: =SUMIFS( CU195:CU266,CT195:CT266, U45, CS195:CS266, O45) -> 6483 | V48: =SUMIFS( CU195:CU266,CT195:CT266, V45, CS195:CS266, O45) -> 185 | W48: =SUMIFS( CU195:CU266,CT195:CT266, W45, CS195:CS266, O45) -> 1648 | X48: =SUMIFS( CU195:CU266,CT195:CT266, X45, CS195:CS266, O45) -> 192 | Y48: =SUMIFS( CU195:CU266,CT195:CT266, Y45, CS195:CS266, O45) -> 195 | Z48: =SUM(P48:Y48) -> 42427 | AB48: 1946-1960 | AC48: 81 | AD48: 78 | AE48: 186 | AF48: 316 | AG48: 1906 | AH48: 3214 | AI48: 2831 | AJ48: 1986 | AK48: 4084 | AL48: =SUM(AC48:AK48) -> 14682 | AN48: 1946-1960 | AO48: =AC48/AL48 -> 0.0055169595 | AP48: =AD48/AL48 -> 0.0053126277 | AQ48: =AE48/AL48 -> 0.012668574 | AR48: =AF48/AL48 -> 0.021522953 | AS48: =AG48/AL48 -> 0.12981883 | AT48: =AH48/AL48 -> 0.21890751 | AU48: =AI48/AL48 -> 0.19282114 | AV48: =AJ48/AL48 -> 0.13526767 | AW48: =AK48/AL48 -> 0.27816374 | AZ48: =AO46*$Z$46 -> 255.73633 | BA48: =AP46*$Z$46 -> 269.74928 | BB48: =AQ46*$Z$46 -> 578.03417 | BC48: =AR46*$Z$46 -> 1180.591 | BD48: =AS46*$Z$46 -> 6761.2482 | BE48: =AT46*$Z$46 -> 11641.258 | BF48: =AU46*$Z$46 -> 13277.27 | BG48: =AV46*$Z$46 -> 10541.241 | BH48: =AW46*$Z$46 -> 29619.872 | BL48: B2 | BM48: =(P46*AQ46+P47*AQ47+P48*AQ48+P49*AQ49+P50*AQ50+P51*AQ51+P52*AQ52+P53*AQ53+P54*AQ54+P55/9)*BX55 -> 151.90346 | BN48: =(Q46*AQ46+Q47*AQ47+Q48*AQ48+Q49*AQ49+Q50*AQ50+Q51*AQ51+Q52*AQ52+Q53*AQ53+Q54*AQ54+Q55/9)*BX55 -> 12442.404 | BO48: =(R46*AQ46+R47*AQ47+R48*AQ48+R49*AQ49+R50*AQ50+R51*AQ51+R52*AQ52+R53*AQ53+R54*AQ54+R55/9)*BX55 -> 2859.5617 | BP48: =(S46*AQ46+S47*AQ47+S48*AQ48+S49*AQ49+S50*AQ50+S51*AQ51+S52*AQ52+S53*AQ53+S54*AQ54+S55/9)*BX55 -> 741.34485 | BQ48: =(T46*AQ46+T47*AQ47+T48*AQ48+T49*AQ49+T50*AQ50+T51*AQ51+T52*AQ52+T53*AQ53+T54*AQ54+T55/9)*BX55 -> 806.99965 | BR48: =(U46*AQ46+U47*AQ47+U48*AQ48+U49*AQ49+U50*AQ50+U51*AQ51+U52*AQ52+U53*AQ53+U54*AQ54+U55/9)*BX55 -> 1528.2239 | BS48: =(V46*AQ46+V47*AQ47+V48*AQ48+V49*AQ49+V50*AQ50+V51*AQ51+V52*AQ52+V53*AQ53+V54*AQ54+V55/9)*BX55 -> 175.48984 | BT48: =(W46*AQ46+W47*AQ47+W48*AQ48+W49*AQ49+W50*AQ50+W51*AQ51+W52*AQ52+W53*AQ53+W54*AQ54+W55/9)*BX55 -> 682.8203 | BU48: =(X46*AQ46+X47*AQ47+X48*AQ48+X49*AQ49+X50*AQ50+X51*AQ51+X52*AQ52+X53*AQ53+X54*AQ54+X55/9)*BX55 -> 369.15024 | BV48: =(Y46*AQ46+Y47*AQ47+Y48*AQ48+Y49*AQ49+Y50*AQ50+Y51*AQ51+Y52*AQ52+Y53*AQ53+Y54*AQ54+Y55/9)*BX55 -> 584.79355 | BW48: =AVERAGE(BQ48,BR48,BT48)/3 -> 335.3382 | CD48: 2011 or later | CE48: 5900 | CL48: Other fuels | CM48: 1305 | CR48: Before 1919 | CS48: Attached | CT48: Not stated | CU48: 88
B49: 1961-1970 | D49: =SUMIFS(INDEX(Table5[],,MATCH(B45,Table5[#Headers],0)),Table5[MainSpaceHeatingFuel],"*Oil",Table5[Year_of_Construction (group)],B49) -> 10387 | E49: =SUMIFS(INDEX(Table5[],,MATCH(B45,Table5[#Headers],0)),Table5[MainSpaceHeatingFuel],"Mains Gas",Table5[Year_of_Construction (group)],B49) -> 2302 | F49: =SUMIFS(INDEX(Table5[],,MATCH(B45,Table5[#Headers],0)),Table5[MainSpaceHeatingFuel],F21,Table5[Year_of_Construction (group)],B49) -> 647 | G49: =SUMIFS(INDEX(Table5[],,MATCH(B45,Table5[#Headers],0)),Table5[MainSpaceHeatingFuel],"*Coal",Table5[Year_of_Construction (group)],B49) -> 109 | H49: =SUMIFS(INDEX(Table5[],,MATCH(B45,Table5[#Headers],0)),Table5[MainSpaceHeatingFuel],"*Peat*",Table5[Year_of_Construction (group)],B49) -> 61 | I49: =SUMIFS(INDEX(Table5[],,MATCH(B45,Table5[#Headers],0)),Table5[MainSpaceHeatingFuel],"*LPG*",Table5[Year_of_Construction (group)],B49) -> 195 | J49: =SUMIFS(INDEX(Table5[],,MATCH(B45,Table5[#Headers],0)),Table5[MainSpaceHeatingFuel],"*Wood*",Table5[Year_of_Construction (group)],B49) -> 53 | K49: =SUMIFS(INDEX(Table5[],,MATCH(B45,Table5[#Headers],0)),Table5[MainSpaceHeatingFuel],"*Multi-Fuel*",Table5[Year_of_Construction (group)],B49) -> 711 | L49: =SUMIFS(INDEX(Table5[],,MATCH(B45,Table5[#Headers],0)),Table5[MainSpaceHeatingFuel],"",Table5[Year_of_Construction (group)],B49) -> 13 | M49: =SUM(C49:L49) -> 14478 | O49: 1961-1970 | P49: =SUMIFS( CU280:CU351,CT280:CT351, P45, CS280:CS351, O45) -> 492 | Q49: =SUMIFS( CU280:CU351,CT280:CT351, Q45, CS280:CS351, O45) -> 26248 | R49: =SUMIFS( CU280:CU351,CT280:CT351, R45, CS280:CS351, O45) -> 6182 | S49: =SUMIFS( CU280:CU351,CT280:CT351, S45, CS280:CS351, O45) -> 856 | T49: =SUMIFS( CU280:CU351,CT280:CT351, T45, CS280:CS351, O45) -> 2338 | U49: =SUMIFS( CU280:CU351,CT280:CT351, U45, CS280:CS351, O45) -> 4315 | V49: =SUMIFS( CU280:CU351,CT280:CT351, V45, CS280:CS351, O45) -> 298 | W49: =SUMIFS( CU280:CU351,CT280:CT351, W45, CS280:CS351, O45) -> 1142 | X49: =SUMIFS( CU280:CU351,CT280:CT351, X45, CS280:CS351, O45) -> 160 | Y49: =SUMIFS( CU280:CU351,CT280:CT351, Y45, CS280:CS351, O45) -> 190 | Z49: =SUM(P49:Y49) -> 42221 | AB49: 1961-1970 | AC49: 88 | AD49: 67 | AE49: 171 | AF49: 331 | AG49: 2563 | AH49: 4213 | AI49: 3243 | AJ49: 1639 | AK49: 2163 | AL49: =SUM(AC49:AK49) -> 14478 | AN49: 1961-1970 | AO49: =AC49/AL49 -> 0.0060781876 | AP49: =AD49/AL49 -> 0.004627711 | AQ49: =AE49/AL49 -> 0.011811024 | AR49: =AF49/AL49 -> 0.022862274 | AS49: =AG49/AL49 -> 0.17702721 | AT49: =AH49/AL49 -> 0.29099323 | AU49: =AI49/AL49 -> 0.22399503 | AV49: =AJ49/AL49 -> 0.11320624 | AW49: =AK49/AL49 -> 0.14939909 | AZ49: =AO47*$Z$47 -> 207.46863 | BA49: =AP47*$Z$47 -> 163.63723 | BB49: =AQ47*$Z$47 -> 388.63841 | BC49: =AR47*$Z$47 -> 937.99195 | BD49: =AS47*$Z$47 -> 4961.7144 | BE49: =AT47*$Z$47 -> 8097.1206 | BF49: =AU47*$Z$47 -> 8254.9136 | BG49: =AV47*$Z$47 -> 6340.9425 | BH49: =AW47*$Z$47 -> 17494.573 | BL49: B3 | BM49: =(P46*AR46+P47*AR47+P48*AR48+P49*AR49+P50*AR50+P51*AR51+P52*AR52+P53*AR53+P54*AR54+P55/9)*BX55 -> 339.71019 | BN49: =(Q46*AR46+Q47*AR47+Q48*AR48+Q49*AR49+Q50*AR50+Q51*AR51+Q52*AR52+Q53*AR53+Q54*AR54+Q55/9)*BX55 -> 34329.607 | BO49: =(R46*AR46+R47*AR47+R48*AR48+R49*AR49+R50*AR50+R51*AR51+R52*AR52+R53*AR53+R54*AR54+R55/9)*BX55 -> 7656.668 | BP49: =(S46*AR46+S47*AR47+S48*AR48+S49*AR49+S50*AR50+S51*AR51+S52*AR52+S53*AR53+S54*AR54+S55/9)*BX55 -> 1630.4604 | BQ49: =(T46*AR46+T47*AR47+T48*AR48+T49*AR49+T50*AR50+T51*AR51+T52*AR52+T53*AR53+T54*AR54+T55/9)*BX55 -> 2133.3311 | BR49: =(U46*AR46+U47*AR47+U48*AR48+U49*AR49+U50*AR50+U51*AR51+U52*AR52+U53*AR53+U54*AR54+U55/9)*BX55 -> 4182.3695 | BS49: =(V46*AR46+V47*AR47+V48*AR48+V49*AR49+V50*AR50+V51*AR51+V52*AR52+V53*AR53+V54*AR54+V55/9)*BX55 -> 495.28416 | BT49: =(W46*AR46+W47*AR47+W48*AR48+W49*AR49+W50*AR50+W51*AR51+W52*AR52+W53*AR53+W54*AR54+W55/9)*BX55 -> 1780.4049 | BU49: =(X46*AR46+X47*AR47+X48*AR48+X49*AR49+X50*AR50+X51*AR51+X52*AR52+X53*AR53+X54*AR54+X55/9)*BX55 -> 860.52276 | BV49: =(Y46*AR46+Y47*AR47+Y48*AR48+Y49*AR49+Y50*AR50+Y51*AR51+Y52*AR52+Y53*AR53+Y54*AR54+Y55/9)*BX55 -> 727.78998 | BW49: =AVERAGE(BQ49,BR49,BT49)/3 -> 899.56727 | CD49: Not stated | CE49: 26052 | CL49: Not stated | CM49: 6256 | CR49: Before 1919 | CS49: Attached
B50: 1971-1980 | D50: =SUMIFS(INDEX(Table5[],,MATCH(B45,Table5[#Headers],0)),Table5[MainSpaceHeatingFuel],"*Oil",Table5[Year_of_Construction (group)],B50) -> 27683 | E50: =SUMIFS(INDEX(Table5[],,MATCH(B45,Table5[#Headers],0)),Table5[MainSpaceHeatingFuel],"Mains Gas",Table5[Year_of_Construction (group)],B50) -> 4302 | F50: =SUMIFS(INDEX(Table5[],,MATCH(B45,Table5[#Headers],0)),Table5[MainSpaceHeatingFuel],F21,Table5[Year_of_Construction (group)],B50) -> 902 | G50: =SUMIFS(INDEX(Table5[],,MATCH(B45,Table5[#Headers],0)),Table5[MainSpaceHeatingFuel],"*Coal",Table5[Year_of_Construction (group)],B50) -> 218 | H50: =SUMIFS(INDEX(Table5[],,MATCH(B45,Table5[#Headers],0)),Table5[MainSpaceHeatingFuel],"*Peat*",Table5[Year_of_Construction (group)],B50) -> 145 | I50: =SUMIFS(INDEX(Table5[],,MATCH(B45,Table5[#Headers],0)),Table5[MainSpaceHeatingFuel],"*LPG*",Table5[Year_of_Construction (group)],B50) -> 604 | J50: =SUMIFS(INDEX(Table5[],,MATCH(B45,Table5[#Headers],0)),Table5[MainSpaceHeatingFuel],"*Wood*",Table5[Year_of_Construction (group)],B50) -> 130 | K50: =SUMIFS(INDEX(Table5[],,MATCH(B45,Table5[#Headers],0)),Table5[MainSpaceHeatingFuel],"*Multi-Fuel*",Table5[Year_of_Construction (group)],B50) -> 1581 | L50: =SUMIFS(INDEX(Table5[],,MATCH(B45,Table5[#Headers],0)),Table5[MainSpaceHeatingFuel],"",Table5[Year_of_Construction (group)],B50) -> 14 | M50: =SUM(C50:L50) -> 35579 | O50: 1971-1980 | P50: =SUMIFS( CU365:CU436,CT365:CT436, P45, CS365:CS436, O45) -> 743 | Q50: =SUMIFS( CU365:CU436,CT365:CT436, Q45, CS365:CS436, O45) -> 66311 | R50: =SUMIFS( CU365:CU436,CT365:CT436, R45, CS365:CS436, O45) -> 10132 | S50: =SUMIFS( CU365:CU436,CT365:CT436, S45, CS365:CS436, O45) -> 1162 | T50: =SUMIFS( CU365:CU436,CT365:CT436, T45, CS365:CS436, O45) -> 5117 | U50: =SUMIFS( CU365:CU436,CT365:CT436, U45, CS365:CS436, O45) -> 9754 | V50: =SUMIFS( CU365:CU436,CT365:CT436, V45, CS365:CS436, O45) -> 841 | W50: =SUMIFS( CU365:CU436,CT365:CT436, W45, CS365:CS436, O45) -> 2881 | X50: =SUMIFS( CU365:CU436,CT365:CT436, X45, CS365:CS436, O45) -> 346 | Y50: =SUMIFS( CU365:CU436,CT365:CT436, Y45, CS365:CS436, O45) -> 411 | Z50: =SUM(P50:Y50) -> 97698 | AB50: 1971-1980 | AC50: 121 | AD50: 96 | AE50: 319 | AF50: 960 | AG50: 9473 | AH50: 12760 | AI50: 6909 | AJ50: 2593 | AK50: 2348 | AL50: =SUM(AC50:AK50) -> 35579 | AN50: 1971-1980 | AO50: =AC50/AL50 -> 0.0034008825 | AP50: =AD50/AL50 -> 0.0026982209 | AQ50: =AE50/AL50 -> 0.0089659631 | AR50: =AF50/AL50 -> 0.026982209 | AS50: =AG50/AL50 -> 0.26625256 | AT50: =AH50/AL50 -> 0.35863852 | AU50: =AI50/AL50 -> 0.19418758 | AV50: =AJ50/AL50 -> 0.07288007 | AW50: =AK50/AL50 -> 0.065993985 | AZ50: =AO48*$Z$48 -> 234.06804 | BA50: =AP48*$Z$48 -> 225.39886 | BB50: =AQ48*$Z$48 -> 537.48958 | BC50: =AR48*$Z$48 -> 913.15434 | BD50: =AS48*$Z$48 -> 5507.8233 | BE50: =AT48*$Z$48 -> 9287.5887 | BF50: =AU48*$Z$48 -> 8180.8226 | BG50: =AV48*$Z$48 -> 5739.0016 | BH50: =AW48*$Z$48 -> 11801.653 | BL50: C | BM50: =(P46*AS46+P47*AS47+P48*AS48+P49*AS49+P50*AS50+P51*AS51+P52*AS52+P53*AS53+P54*AS54+P55/9)*BX55 -> 1717.3043 | BN50: =(Q46*AS46+Q47*AS47+Q48*AS48+Q49*AS49+Q50*AS50+Q51*AS51+Q52*AS52+Q53*AS53+Q54*AS54+Q55/9)*BX55 -> 163849.26 | BO50: =(R46*AS46+R47*AS47+R48*AS48+R49*AS49+R50*AS50+R51*AS51+R52*AS52+R53*AS53+R54*AS54+R55/9)*BX55 -> 34460.956 | BP50: =(S46*AS46+S47*AS47+S48*AS48+S49*AS49+S50*AS50+S51*AS51+S52*AS52+S53*AS53+S54*AS54+S55/9)*BX55 -> 6165.604 | BQ50: =(T46*AS46+T47*AS47+T48*AS48+T49*AS49+T50*AS50+T51*AS51+T52*AS52+T53*AS53+T54*AS54+T55/9)*BX55 -> 11165.45 | BR50: =(U46*AS46+U47*AS47+U48*AS48+U49*AS49+U50*AS50+U51*AS51+U52*AS52+U53*AS53+U54*AS54+U55/9)*BX55 -> 21844.181 | BS50: =(V46*AS46+V47*AS47+V48*AS48+V49*AS49+V50*AS50+V51*AS51+V52*AS52+V53*AS53+V54*AS54+V55/9)*BX55 -> 2381.5891 | BT50: =(W46*AS46+W47*AS47+W48*AS48+W49*AS49+W50*AS50+W51*AS51+W52*AS52+W53*AS53+W54*AS54+W55/9)*BX55 -> 8282.3737 | BU50: =(X46*AS46+X47*AS47+X48*AS48+X49*AS49+X50*AS50+X51*AS51+X52*AS52+X53*AS53+X54*AS54+X55/9)*BX55 -> 3026.8541 | BV50: =(Y46*AS46+Y47*AS47+Y48*AS48+Y49*AS49+Y50*AS50+Y51*AS51+Y52*AS52+Y53*AS53+Y54*AS54+Y55/9)*BX55 -> 1574.4153 | BW50: =AVERAGE(BQ50,BR50,BT50)/3 -> 4588.0005 | CC50: Terraced house | CK50: Terraced house | CR50: Before 1919 | CS50: Attached | CT50: All households | CU50: 36956
B51: 1981-1990 | D51: =SUMIFS(INDEX(Table5[],,MATCH(B45,Table5[#Headers],0)),Table5[MainSpaceHeatingFuel],"*Oil",Table5[Year_of_Construction (group)],B51) -> 25187 | E51: =SUMIFS(INDEX(Table5[],,MATCH(B45,Table5[#Headers],0)),Table5[MainSpaceHeatingFuel],"Mains Gas",Table5[Year_of_Construction (group)],B51) -> 3952 | F51: =SUMIFS(INDEX(Table5[],,MATCH(B45,Table5[#Headers],0)),Table5[MainSpaceHeatingFuel],F21,Table5[Year_of_Construction (group)],B51) -> 744 | G51: =SUMIFS(INDEX(Table5[],,MATCH(B45,Table5[#Headers],0)),Table5[MainSpaceHeatingFuel],"*Coal",Table5[Year_of_Construction (group)],B51) -> 243 | H51: =SUMIFS(INDEX(Table5[],,MATCH(B45,Table5[#Headers],0)),Table5[MainSpaceHeatingFuel],"*Peat*",Table5[Year_of_Construction (group)],B51) -> 128 | I51: =SUMIFS(INDEX(Table5[],,MATCH(B45,Table5[#Headers],0)),Table5[MainSpaceHeatingFuel],"*LPG*",Table5[Year_of_Construction (group)],B51) -> 1048 | J51: =SUMIFS(INDEX(Table5[],,MATCH(B45,Table5[#Headers],0)),Table5[MainSpaceHeatingFuel],"*Wood*",Table5[Year_of_Construction (group)],B51) -> 134 | K51: =SUMIFS(INDEX(Table5[],,MATCH(B45,Table5[#Headers],0)),Table5[MainSpaceHeatingFuel],"*Multi-Fuel*",Table5[Year_of_Construction (group)],B51) -> 1737 | L51: =SUMIFS(INDEX(Table5[],,MATCH(B45,Table5[#Headers],0)),Table5[MainSpaceHeatingFuel],"",Table5[Year_of_Construction (group)],B51) -> 17 | M51: =SUM(C51:L51) -> 33190 | O51: 1981-1990 | P51: =SUMIFS( CU450:CU521,CT450:CT521, P45, CS450:CS521, O45) -> 474 | Q51: =SUMIFS( CU450:CU521,CT450:CT521, Q45, CS450:CS521, O45) -> 54892 | R51: =SUMIFS( CU450:CU521,CT450:CT521, R45, CS450:CS521, O45) -> 8821 | S51: =SUMIFS( CU450:CU521,CT450:CT521, S45, CS450:CS521, O45) -> 1049 | T51: =SUMIFS( CU450:CU521,CT450:CT521, T45, CS450:CS521, O45) -> 5425 | U51: =SUMIFS( CU450:CU521,CT450:CT521, U45, CS450:CS521, O45) -> 11032 | V51: =SUMIFS( CU450:CU521,CT450:CT521, V45, CS450:CS521, O45) -> 1160 | W51: =SUMIFS( CU450:CU521,CT450:CT521, W45, CS450:CS521, O45) -> 2941 | X51: =SUMIFS( CU450:CU521,CT450:CT521, X45, CS450:CS521, O45) -> 341 | Y51: =SUMIFS( CU450:CU521,CT450:CT521, Y45, CS450:CS521, O45) -> 356 | Z51: =SUM(P51:Y51) -> 86491 | AB51: 1981-1990 | AC51: 90 | AD51: 94 | AE51: 303 | AF51: 1399 | AG51: 12085 | AH51: 13010 | AI51: 4266 | AJ51: 1158 | AK51: 785 | AL51: =SUM(AC51:AK51) -> 33190 | AN51: 1981-1990 | AO51: =AC51/AL51 -> 0.0027116601 | AP51: =AD51/AL51 -> 0.0028321784 | AQ51: =AE51/AL51 -> 0.0091292558 | AR51: =AF51/AL51 -> 0.04215125 | AS51: =AG51/AL51 -> 0.3641157 | AT51: =AH51/AL51 -> 0.39198554 | AU51: =AI51/AL51 -> 0.12853269 | AV51: =AJ51/AL51 -> 0.034890027 | AW51: =AK51/AL51 -> 0.023651702 | AZ51: =AO49*$Z$49 -> 256.62716 | BA51: =AP49*$Z$49 -> 195.38659 | BB51: =AQ49*$Z$49 -> 498.67323 | BC51: =AR49*$Z$49 -> 965.26806 | BD51: =AS49*$Z$49 -> 7474.266 | BE51: =AT49*$Z$49 -> 12286.025 | BF51: =AU49*$Z$49 -> 9457.294 | BG51: =AV49*$Z$49 -> 4779.6808 | BH51: =AW49*$Z$49 -> 6307.7789 | BL51: D | BM51: =(P46*AT46+P47*AT47+P48*AT48+P49*AT49+P50*AT50+P51*AT51+P52*AT52+P53*AT53+P54*AT54+P55/9)*BX55 -> 1831.7627 | BN51: =(Q46*AT46+Q47*AT47+Q48*AT48+Q49*AT49+Q50*AT50+Q51*AT51+Q52*AT52+Q53*AT53+Q54*AT54+Q55/9)*BX55 -> 107228.37 | BO51: =(R46*AT46+R47*AT47+R48*AT48+R49*AT49+R50*AT50+R51*AT51+R52*AT52+R53*AT53+R54*AT54+R55/9)*BX55 -> 19875.02 | BP51: =(S46*AT46+S47*AT47+S48*AT48+S49*AT49+S50*AT50+S51*AT51+S52*AT52+S53*AT53+S54*AT54+S55/9)*BX55 -> 3174.5477 | BQ51: =(T46*AT46+T47*AT47+T48*AT48+T49*AT49+T50*AT50+T51*AT51+T52*AT52+T53*AT53+T54*AT54+T55/9)*BX55 -> 9373.7861 | BR51: =(U46*AT46+U47*AT47+U48*AT48+U49*AT49+U50*AT50+U51*AT51+U52*AT52+U53*AT53+U54*AT54+U55/9)*BX55 -> 17614.817 | BS51: =(V46*AT46+V47*AT47+V48*AT48+V49*AT49+V50*AT50+V51*AT51+V52*AT52+V53*AT53+V54*AT54+V55/9)*BX55 -> 1536.9749 | BT51: =(W46*AT46+W47*AT47+W48*AT48+W49*AT49+W50*AT50+W51*AT51+W52*AT52+W53*AT53+W54*AT54+W55/9)*BX55 -> 5836.3109 | BU51: =(X46*AT46+X47*AT47+X48*AT48+X49*AT49+X50*AT50+X51*AT51+X52*AT52+X53*AT53+X54*AT54+X55/9)*BX55 -> 1064.2403 | BV51: =(Y46*AT46+Y47*AT47+Y48*AT48+Y49*AT49+Y50*AT50+Y51*AT51+Y52*AT52+Y53*AT53+Y54*AT54+Y55/9)*BX55 -> 1220.3314 | BW51: =AVERAGE(BQ51,BR51,BT51)/3 -> 3647.2126 | CD51: All years | CE51: 284569 | CL51: All households | CM51: 284569 | CR51: Before 1919 | CS51: Attached | CT51: No central heating | CU51: 1568
B52: 1991-2000 | D52: =SUMIFS(INDEX(Table5[],,MATCH(B45,Table5[#Headers],0)),Table5[MainSpaceHeatingFuel],"*Oil",Table5[Year_of_Construction (group)],B52) -> 36438 | E52: =SUMIFS(INDEX(Table5[],,MATCH(B45,Table5[#Headers],0)),Table5[MainSpaceHeatingFuel],"Mains Gas",Table5[Year_of_Construction (group)],B52) -> 9175 | F52: =SUMIFS(INDEX(Table5[],,MATCH(B45,Table5[#Headers],0)),Table5[MainSpaceHeatingFuel],F21,Table5[Year_of_Construction (group)],B52) -> 1914 | G52: =SUMIFS(INDEX(Table5[],,MATCH(B45,Table5[#Headers],0)),Table5[MainSpaceHeatingFuel],"*Coal",Table5[Year_of_Construction (group)],B52) -> 149 | H52: =SUMIFS(INDEX(Table5[],,MATCH(B45,Table5[#Headers],0)),Table5[MainSpaceHeatingFuel],"*Peat*",Table5[Year_of_Construction (group)],B52) -> 58 | I52: =SUMIFS(INDEX(Table5[],,MATCH(B45,Table5[#Headers],0)),Table5[MainSpaceHeatingFuel],"*LPG*",Table5[Year_of_Construction (group)],B52) -> 1055 | J52: =SUMIFS(INDEX(Table5[],,MATCH(B45,Table5[#Headers],0)),Table5[MainSpaceHeatingFuel],"*Wood*",Table5[Year_of_Construction (group)],B52) -> 134 | K52: =SUMIFS(INDEX(Table5[],,MATCH(B45,Table5[#Headers],0)),Table5[MainSpaceHeatingFuel],"*Multi-Fuel*",Table5[Year_of_Construction (group)],B52) -> 1220 | L52: =SUMIFS(INDEX(Table5[],,MATCH(B45,Table5[#Headers],0)),Table5[MainSpaceHeatingFuel],"",Table5[Year_of_Construction (group)],B52) -> 16 | M52: =SUM(C52:L52) -> 50159 | O52: 1991-2000 | P52: =SUMIFS( CU535:CU606,CT535:CT606, P45, CS535:CS606, O45) -> 445 | Q52: =SUMIFS( CU535:CU606,CT535:CT606, Q45, CS535:CS606, O45) -> 74134 | R52: =SUMIFS( CU535:CU606,CT535:CT606, R45, CS535:CS606, O45) -> 17190 | S52: =SUMIFS( CU535:CU606,CT535:CT606, S45, CS535:CS606, O45) -> 1747 | T52: =SUMIFS( CU535:CU606,CT535:CT606, T45, CS535:CS606, O45) -> 4583 | U52: =SUMIFS( CU535:CU606,CT535:CT606, U45, CS535:CS606, O45) -> 8635 | V52: =SUMIFS( CU535:CU606,CT535:CT606, V45, CS535:CS606, O45) -> 969 | W52: =SUMIFS( CU535:CU606,CT535:CT606, W45, CS535:CS606, O45) -> 2895 | X52: =SUMIFS( CU535:CU606,CT535:CT606, X45, CS535:CS606, O45) -> 428 | Y52: =SUMIFS( CU535:CU606,CT535:CT606, Y45, CS535:CS606, O45) -> 429 | Z52: =SUM(P52:Y52) -> 111455 | AB52: 1991-2000 | AC52: 97 | AD52: 137 | AE52: 760 | AF52: 3782 | AG52: 26945 | AH52: 14603 | AI52: 2602 | AJ52: 820 | AK52: 413 | AL52: =SUM(AC52:AK52) -> 50159 | AN52: 1991-2000 | AO52: =AC52/AL52 -> 0.0019338504 | AP52: =AD52/AL52 -> 0.0027313144 | AQ52: =AE52/AL52 -> 0.015151817 | AR52: =AF52/AL52 -> 0.075400227 | AS52: =AG52/AL52 -> 0.53719173 | AT52: =AH52/AL52 -> 0.29113419 | AU52: =AI52/AL52 -> 0.051875037 | AV52: =AJ52/AL52 -> 0.016348013 | AW52: =AK52/AL52 -> 0.0082338165 | AZ52: =AO50*$Z$50 -> 332.25942 | BA52: =AP50*$Z$50 -> 263.61078 | BB52: =AQ50*$Z$50 -> 875.95666 | BC52: =AR50*$Z$50 -> 2636.1078 | BD52: =AS50*$Z$50 -> 26012.343 | BE52: =AT50*$Z$50 -> 35038.266 | BF52: =AU50*$Z$50 -> 18971.738 | BG52: =AV50*$Z$50 -> 7120.237 | BH52: =AW50*$Z$50 -> 6447.4804 | BL52: E | BM52: =(P46*AU46+P47*AU47+P48*AU48+P49*AU49+P50*AU50+P51*AU51+P52*AU52+P53*AU53+P54*AU54+P55/9)*BX55 -> 1434.0867 | BN52: =(Q46*AU46+Q47*AU47+Q48*AU48+Q49*AU49+Q50*AU50+Q51*AU51+Q52*AU52+Q53*AU53+Q54*AU54+Q55/9)*BX55 -> 50708.062 | BO52: =(R46*AU46+R47*AU47+R48*AU48+R49*AU49+R50*AU50+R51*AU51+R52*AU52+R53*AU53+R54*AU54+R55/9)*BX55 -> 8524.8396 | BP52: =(S46*AU46+S47*AU47+S48*AU48+S49*AU49+S50*AU50+S51*AU51+S52*AU52+S53*AU53+S54*AU54+S55/9)*BX55 -> 1630.6805 | BQ52: =(T46*AU46+T47*AU47+T48*AU48+T49*AU49+T50*AU50+T51*AU51+T52*AU52+T53*AU53+T54*AU54+T55/9)*BX55 -> 5326.9004 | BR52: =(U46*AU46+U47*AU47+U48*AU48+U49*AU49+U50*AU50+U51*AU51+U52*AU52+U53*AU53+U54*AU54+U55/9)*BX55 -> 9547.6158 | BS52: =(V46*AU46+V47*AU47+V48*AU48+V49*AU49+V50*AU50+V51*AU51+V52*AU52+V53*AU53+V54*AU54+V55/9)*BX55 -> 671.14821 | BT52: =(W46*AU46+W47*AU47+W48*AU48+W49*AU49+W50*AU50+W51*AU51+W52*AU52+W53*AU53+W54*AU54+W55/9)*BX55 -> 3290.2431 | BU52: =(X46*AU46+X47*AU47+X48*AU48+X49*AU49+X50*AU50+X51*AU51+X52*AU52+X53*AU53+X54*AU54+X55/9)*BX55 -> 415.74438 | BV52: =(Y46*AU46+Y47*AU47+Y48*AU48+Y49*AU49+Y50*AU50+Y51*AU51+Y52*AU52+Y53*AU53+Y54*AU54+Y55/9)*BX55 -> 867.28659 | BW52: =AVERAGE(BQ52,BR52,BT52)/3 -> 2018.3066 | CD52: Before 1919 | CE52: 36956 | CL52: No central heating | CM52: 5402 | CR52: Before 1919 | CS52: Attached | CT52: Oil | CU52: 8359
B53: 2001-2010 | D53: =SUMIFS(INDEX(Table5[],,MATCH(B45,Table5[#Headers],0)),Table5[MainSpaceHeatingFuel],"*Oil",Table5[Year_of_Construction (group)],B53) -> 47807 | E53: =SUMIFS(INDEX(Table5[],,MATCH(B45,Table5[#Headers],0)),Table5[MainSpaceHeatingFuel],"Mains Gas",Table5[Year_of_Construction (group)],B53) -> 14262 | F53: =SUMIFS(INDEX(Table5[],,MATCH(B45,Table5[#Headers],0)),Table5[MainSpaceHeatingFuel],F21,Table5[Year_of_Construction (group)],B53) -> 3795 | G53: =SUMIFS(INDEX(Table5[],,MATCH(B45,Table5[#Headers],0)),Table5[MainSpaceHeatingFuel],"*Coal",Table5[Year_of_Construction (group)],B53) -> 131 | H53: =SUMIFS(INDEX(Table5[],,MATCH(B45,Table5[#Headers],0)),Table5[MainSpaceHeatingFuel],"*Peat*",Table5[Year_of_Construction (group)],B53) -> 18 | I53: =SUMIFS(INDEX(Table5[],,MATCH(B45,Table5[#Headers],0)),Table5[MainSpaceHeatingFuel],"*LPG*",Table5[Year_of_Construction (group)],B53) -> 1997 | J53: =SUMIFS(INDEX(Table5[],,MATCH(B45,Table5[#Headers],0)),Table5[MainSpaceHeatingFuel],"*Wood*",Table5[Year_of_Construction (group)],B53) -> 520 | K53: =SUMIFS(INDEX(Table5[],,MATCH(B45,Table5[#Headers],0)),Table5[MainSpaceHeatingFuel],"*Multi-Fuel*",Table5[Year_of_Construction (group)],B53) -> 927 | L53: =SUMIFS(INDEX(Table5[],,MATCH(B45,Table5[#Headers],0)),Table5[MainSpaceHeatingFuel],"",Table5[Year_of_Construction (group)],B53) -> 48 | M53: =SUM(C53:L53) -> 69505 | O53: 2001-2010 | P53: =SUMIFS( CU620:CU691,CT620:CT691, P45, CS620:CS691, O45) -> 644 | Q53: =SUMIFS( CU620:CU691,CT620:CT691, Q45, CS620:CS691, O45) -> 113051 | R53: =SUMIFS( CU620:CU691,CT620:CT691, R45, CS620:CS691, O45) -> 26564 | S53: =SUMIFS( CU620:CU691,CT620:CT691, S45, CS620:CS691, O45) -> 6208 | T53: =SUMIFS( CU620:CU691,CT620:CT691, T45, CS620:CS691, O45) -> 5234 | U53: =SUMIFS( CU620:CU691,CT620:CT691, U45, CS620:CS691, O45) -> 11248 | V53: =SUMIFS( CU620:CU691,CT620:CT691, V45, CS620:CS691, O45) -> 1668 | W53: =SUMIFS( CU620:CU691,CT620:CT691, W45, CS620:CS691, O45) -> 5852 | X53: =SUMIFS( CU620:CU691,CT620:CT691, X45, CS620:CS691, O45) -> 3988 | Y53: =SUMIFS( CU620:CU691,CT620:CT691, Y45, CS620:CS691, O45) -> 766 | Z53: =SUM(P53:Y53) -> 175223 | AB53: 2001-2010 | AC53: 562 | AD53: 1504 | AE53: 4471 | AF53: 12409 | AG53: 41033 | AH53: 7731 | AI53: 1198 | AJ53: 410 | AK53: 200 | AL53: =SUM(AC53:AK53) -> 69518 | AN53: 2001-2010 | AO53: =AC53/AL53 -> 0.0080842372 | AP53: =AD53/AL53 -> 0.021634685 | AQ53: =AE53/AL53 -> 0.064314278 | AR53: =AF53/AL53 -> 0.17850053 | AS53: =AG53/AL53 -> 0.59025001 | AT53: =AH53/AL53 -> 0.11120861 | AU53: =AI53/AL53 -> 0.017232947 | AV53: =AJ53/AL53 -> 0.0058977531 | AW53: =AK53/AL53 -> 0.0028769527 | AZ53: =AO51*$Z$51 -> 234.5342 | BA53: =AP51*$Z$51 -> 244.95794 | BB53: =AQ51*$Z$51 -> 789.59846 | BC53: =AR51*$Z$51 -> 3645.7038 | BD53: =AS51*$Z$51 -> 31492.731 | BE53: =AT51*$Z$51 -> 33903.221 | BF53: =AU51*$Z$51 -> 11116.921 | BG53: =AV51*$Z$51 -> 3017.6733 | BH53: =AW51*$Z$51 -> 2045.6594 | BL53: F | BM53: =(P46*AV46+P47*AV47+P48*AV48+P49*AV49+P50*AV50+P51*AV51+P52*AV52+P53*AV53+P54*AV54+P55/9)*BX55 -> 979.01102 | BN53: =(Q46*AV46+Q47*AV47+Q48*AV48+Q49*AV49+Q50*AV50+Q51*AV51+Q52*AV52+Q53*AV53+Q54*AV54+Q55/9)*BX55 -> 26075.18 | BO53: =(R46*AV46+R47*AV47+R48*AV48+R49*AV49+R50*AV50+R51*AV51+R52*AV52+R53*AV53+R54*AV54+R55/9)*BX55 -> 4225.2763 | BP53: =(S46*AV46+S47*AV47+S48*AV48+S49*AV49+S50*AV50+S51*AV51+S52*AV52+S53*AV53+S54*AV54+S55/9)*BX55 -> 978.25477 | BQ53: =(T46*AV46+T47*AV47+T48*AV48+T49*AV49+T50*AV50+T51*AV51+T52*AV52+T53*AV53+T54*AV54+T55/9)*BX55 -> 3058.229 | BR53: =(U46*AV46+U47*AV47+U48*AV48+U49*AV49+U50*AV50+U51*AV51+U52*AV52+U53*AV53+U54*AV54+U55/9)*BX55 -> 5279.643 | BS53: =(V46*AV46+V47*AV47+V48*AV48+V49*AV49+V50*AV50+V51*AV51+V52*AV52+V53*AV53+V54*AV54+V55/9)*BX55 -> 322.72553 | BT53: =(W46*AV46+W47*AV47+W48*AV48+W49*AV49+W50*AV50+W51*AV51+W52*AV52+W53*AV53+W54*AV54+W55/9)*BX55 -> 1942.6335 | BU53: =(X46*AV46+X47*AV47+X48*AV48+X49*AV49+X50*AV50+X51*AV51+X52*AV52+X53*AV53+X54*AV54+X55/9)*BX55 -> 222.55131 | BV53: =(Y46*AV46+Y47*AV47+Y48*AV48+Y49*AV49+Y50*AV50+Y51*AV51+Y52*AV52+Y53*AV53+Y54*AV54+Y55/9)*BX55 -> 699.31593 | BW53: =AVERAGE(BQ53,BR53,BT53)/3 -> 1142.2784 | CD53: 1919 to 1945 | CE53: 31594 | CL53: Oil | CM53: 61595 | CR53: Before 1919 | CS53: Attached | CT53: Natural Gas | CU53: 19994
B54: Later_2010 | D54: =SUMIFS(INDEX(Table5[],,MATCH(B45,Table5[#Headers],0)),Table5[MainSpaceHeatingFuel],"*Oil",Table5[Year_of_Construction (group)],B54) -> 2311 | E54: =SUMIFS(INDEX(Table5[],,MATCH(B45,Table5[#Headers],0)),Table5[MainSpaceHeatingFuel],"Mains Gas",Table5[Year_of_Construction (group)],B54) -> 2722 | F54: =SUMIFS(INDEX(Table5[],,MATCH(B45,Table5[#Headers],0)),Table5[MainSpaceHeatingFuel],F21,Table5[Year_of_Construction (group)],B54) -> 5400 | G54: =SUMIFS(INDEX(Table5[],,MATCH(B45,Table5[#Headers],0)),Table5[MainSpaceHeatingFuel],"*Coal",Table5[Year_of_Construction (group)],B54) -> 6 | H54: =SUMIFS(INDEX(Table5[],,MATCH(B45,Table5[#Headers],0)),Table5[MainSpaceHeatingFuel],"*Peat*",Table5[Year_of_Construction (group)],B54) -> 1 | I54: =SUMIFS(INDEX(Table5[],,MATCH(B45,Table5[#Headers],0)),Table5[MainSpaceHeatingFuel],"*LPG*",Table5[Year_of_Construction (group)],B54) -> 125 | J54: =SUMIFS(INDEX(Table5[],,MATCH(B45,Table5[#Headers],0)),Table5[MainSpaceHeatingFuel],"*Wood*",Table5[Year_of_Construction (group)],B54) -> 51 | K54: =SUMIFS(INDEX(Table5[],,MATCH(B45,Table5[#Headers],0)),Table5[MainSpaceHeatingFuel],"*Multi-Fuel*",Table5[Year_of_Construction (group)],B54) -> 35 | L54: =SUMIFS(INDEX(Table5[],,MATCH(B45,Table5[#Headers],0)),Table5[MainSpaceHeatingFuel],"",Table5[Year_of_Construction (group)],B54) -> 43 | M54: =SUM(C54:L54) -> 10694 | O54: Later_2010 | P54: =SUMIFS( CU705:CU776,CT705:CT776, P45, CS705:CS776, O45) -> 149 | Q54: =SUMIFS( CU705:CU776,CT705:CT776, Q45, CS705:CS776, O45) -> 9159 | R54: =SUMIFS( CU705:CU776,CT705:CT776, R45, CS705:CS776, O45) -> 2065 | S54: =SUMIFS( CU705:CU776,CT705:CT776, S45, CS705:CS776, O45) -> 2298 | T54: =SUMIFS( CU705:CU776,CT705:CT776, T45, CS705:CS776, O45) -> 438 | U54: =SUMIFS( CU705:CU776,CT705:CT776, U45, CS705:CS776, O45) -> 1332 | V54: =SUMIFS( CU705:CU776,CT705:CT776, V45, CS705:CS776, O45) -> 151 | W54: =SUMIFS( CU705:CU776,CT705:CT776, W45, CS705:CS776, O45) -> 964 | X54: =SUMIFS( CU705:CU776,CT705:CT776, X45, CS705:CS776, O45) -> 1361 | Y54: =SUMIFS( CU705:CU776,CT705:CT776, Y45, CS705:CS776, O45) -> 133 | Z54: =SUM(P54:Y54) -> 18050 | AB54: Later_2010 | AC54: 8695 | AD54: 928 | AE54: 544 | AF54: 315 | AG54: 176 | AH54: 31 | AI54: 2 | AJ54: 2 | AK54: 1 | AL54: =SUM(AC54:AK54) -> 10694 | AN54: Later_2010 | AO54: =AC54/AL54 -> 0.81307275 | AP54: =AD54/AL54 -> 0.086777632 | AQ54: =AE54/AL54 -> 0.050869647 | AR54: =AF54/AL54 -> 0.02945577 | AS54: =AG54/AL54 -> 0.016457827 | AT54: =AH54/AL54 -> 0.0028988218 | AU54: =AI54/AL54 -> 0.00018702076 | AV54: =AJ54/AL54 -> 0.00018702076 | AW54: =AK54/AL54 -> 9.351038e-05 | AZ54: =AO52*$Z$52 -> 215.53729 | BA54: =AP52*$Z$52 -> 304.41865 | BB54: =AQ52*$Z$52 -> 1688.7458 | BC54: =AR52*$Z$52 -> 8403.7323 | BD54: =AS52*$Z$52 -> 59872.704 | BE54: =AT52*$Z$52 -> 32448.362 | BF54: =AU52*$Z$52 -> 5781.7323 | BG54: =AV52*$Z$52 -> 1822.0678 | BH54: =AW52*$Z$52 -> 917.70001 | BL54: G | BM54: =(P46*AW46+P47*AW47+P48*AW48+P49*AW49+P50*AW50+P51*AW51+P52*AW52+P53*AW53+P54*AW54+P55/9)*BX55 -> 2351.3485 | BN54: =(Q46*AW46+Q47*AW47+Q48*AW48+Q49*AW49+Q50*AW50+Q51*AW51+Q52*AW52+Q53*AW53+Q54*AW54+Q55/9)*BX55 -> 46077.566 | BO54: =(R46*AW46+R47*AW47+R48*AW48+R49*AW49+R50*AW50+R51*AW51+R52*AW52+R53*AW53+R54*AW54+R55/9)*BX55 -> 6457.2581 | BP54: =(S46*AW46+S47*AW47+S48*AW48+S49*AW49+S50*AW50+S51*AW51+S52*AW52+S53*AW53+S54*AW54+S55/9)*BX55 -> 1889.9266 | BQ54: =(T46*AW46+T47*AW47+T48*AW48+T49*AW49+T50*AW50+T51*AW51+T52*AW52+T53*AW53+T54*AW54+T55/9)*BX55 -> 6220.7575 | BR54: =(U46*AW46+U47*AW47+U48*AW48+U49*AW49+U50*AW50+U51*AW51+U52*AW52+U53*AW53+U54*AW54+U55/9)*BX55 -> 10428.842 | BS54: =(V46*AW46+V47*AW47+V48*AW48+V49*AW49+V50*AW50+V51*AW51+V52*AW52+V53*AW53+V54*AW54+V55/9)*BX55 -> 544.83711 | BT54: =(W46*AW46+W47*AW47+W48*AW48+W49*AW49+W50*AW50+W51*AW51+W52*AW52+W53*AW53+W54*AW54+W55/9)*BX55 -> 4156.243 | BU54: =(X46*AW46+X47*AW47+X48*AW48+X49*AW49+X50*AW50+X51*AW51+X52*AW52+X53*AW53+X54*AW54+X55/9)*BX55 -> 405.72196 | BV54: =(Y46*AW46+Y47*AW47+Y48*AW48+Y49*AW49+Y50*AW50+Y51*AW51+Y52*AW52+Y53*AW53+Y54*AW54+Y55/9)*BX55 -> 885.83814 | BW54: =AVERAGE(BQ54,BR54,BT54)/3 -> 2311.7603 | CD54: 1946 to 1960 | CE54: 38410 | CL54: Natural Gas | CM54: 162887 | CR54: Before 1919 | CS54: Attached | CT54: Electricity | CU54: 3304
B55: Total | C55: =SUM(C46:C54) -> 0 | D55: =SUM(D46:D54) -> 184568 | E55: =SUM(E46:E54) -> 41651 | F55: =SUM(F46:F54) -> 17895 | G55: =SUM(G46:G54) -> 1595 | H55: =SUM(H46:H54) -> 771 | I55: =SUM(I46:I54) -> 5856 | J55: =SUM(J46:J54) -> 1317 | ... L55: =SUM(L46:L54) -> 190 | M55: =SUM(C55:L55) -> 265478 | O55: Not Stated | P55: =SUMIFS( $CU$777:$CU$861,$CT$777:$CT$861, P45, $CS$777:$CS$861, $O$45) -> 240 | Q55: =SUMIFS( $CU$777:$CU$861,$CT$777:$CT$861, Q45, $CS$777:$CS$861, $O$45) -> 9133 | R55: =SUMIFS( $CU$777:$CU$861,$CT$777:$CT$861, R45, $CS$777:$CS$861, $O$45) -> 3188 | S55: =SUMIFS( $CU$777:$CU$861,$CT$777:$CT$861, S45, $CS$777:$CS$861, $O$45) -> 1027 | T55: =SUMIFS( $CU$777:$CU$861,$CT$777:$CT$861, T45, $CS$777:$CS$861, $O$45) -> 972 | U55: =SUMIFS( $CU$777:$CU$861,$CT$777:$CT$861, U45, $CS$777:$CS$861, $O$45) -> 990 | V55: =SUMIFS( $CU$777:$CU$861,$CT$777:$CT$861, V45, $CS$777:$CS$861, $O$45) -> 97 | W55: =SUMIFS( $CU$777:$CU$861,$CT$777:$CT$861, W45, $CS$777:$CS$861, $O$45) -> 424 | ... Y55: =SUMIFS( $CU$777:$CU$861,$CT$777:$CT$861, Y45, $CS$777:$CS$861, $O$45) -> 4418 | Z55: =SUM(P55:Y55) -> 20596 | AB55: Total | AC55: =SUM(AC46:AC54) -> 9878 | AD55: =SUM(AD46:AD54) -> 3037 | AE55: =SUM(AE46:AE54) -> 7052 | AF55: =SUM(AF46:AF54) -> 20170 | AG55: =SUM(AG46:AG54) -> 97809 | AH55: =SUM(AH46:AH54) -> 61656 | AI55: =SUM(AI46:AI54) -> 27666 | AJ55: =SUM(AJ46:AJ54) -> 13787 | ... AL55: =SUM(AL46:AL54) -> 265491 | AZ55: =AO53*$Z$53 -> 1416.5443 | BA55: =AP53*$Z$53 -> 3790.8943 | BB55: =AQ53*$Z$53 -> 11269.341 | BC55: =AR53*$Z$53 -> 31277.399 | BD55: =AS53*$Z$53 -> 103425.38 | BE55: =AT53*$Z$53 -> 19486.306 | BF55: =AU53*$Z$53 -> 3019.6086 | BG55: =AV53*$Z$53 -> 1033.422 | BH55: =AW53*$Z$53 -> 504.10829 | BX55: 1.025693 | CD55: 1961 to 1970 | CE55: 24370 | CL55: Electricity | CM55: 18444 | CR55: Before 1919 | CS55: Attached | CT55: Coal (incl. Anthracite_Coal) | CU55: 2267
B56: Year_of_Construction (group) | C56: MainSpaceHeatingFuel | D56: Apartments | E56: Attached | F56: Detached | O56: Total | P56: =SUM(P46:P55) -> 8850 | Q56: =SUM(Q46:Q55) -> 445404 | R56: =SUM(R46:R55) -> 85670 | S56: =SUM(S46:S55) -> 18348 | T56: =SUM(T46:T55) -> 38120 | U56: =SUM(U46:U55) -> 70819 | V56: =SUM(V46:V55) -> 6209 | W56: =SUM(W46:W55) -> 26591 | ... Y56: =SUM(Y46:Y55) -> 7535 | Z56: =SUM(P56:Y56) -> 715133 | AZ56: =AO54*$Z$54 -> 14675.963 | BA56: =AP54*$Z$54 -> 1566.3363 | BB56: =AQ54*$Z$54 -> 918.19712 | BC56: =AR54*$Z$54 -> 531.67664 | BD56: =AS54*$Z$54 -> 297.06377 | BE56: =AT54*$Z$54 -> 52.323733 | BF56: =AU54*$Z$54 -> 3.3757247 | BG56: =AV54*$Z$54 -> 3.3757247 | BH56: =AW54*$Z$54 -> 1.6878624 | CD56: 1971 to 1980 | CE56: 36397 | CL56: Coal (incl. Anthracite_Coal) | CM56: 20177 | CR56: Before 1919 | CS56: Attached | CT56: Peat (incl. turf) | CU56: 632
B57: Before_1919 | D57: 363 | E57: 55 | F57: 23 | AZ57: =$Z$55/9 -> 2288.4444 | BA57: =$Z$55/9 -> 2288.4444 | BB57: =$Z$55/9 -> 2288.4444 | BC57: =$Z$55/9 -> 2288.4444 | BD57: =$Z$55/9 -> 2288.4444 | BE57: =$Z$55/9 -> 2288.4444 | BF57: =$Z$55/9 -> 2288.4444 | BG57: =$Z$55/9 -> 2288.4444 | BH57: =$Z$55/9 -> 2288.4444 | CD57: 1981 to 1990 | CE57: 23557 | CL57: Peat (incl. turf) | CM57: 5691 | CR57: Before 1919 | CS57: Attached | CT57: Liquid Petroleum Gas (LPG) | CU57: 111
B58: Before_1919 | C58: Anthracite_Coal | D58: 2 | E58: 3 | F58: 8 | AY58: Total | AZ58: =SUM(AZ48:AZ57) -> 20117.183 | BA58: =SUM(BA48:BA57) -> 9312.8344 | BB58: =SUM(BB48:BB57) -> 19833.119 | BC58: =SUM(BC48:BC57) -> 52780.069 | BD58: =SUM(BD48:BD57) -> 248093.72 | BE58: =SUM(BE48:BE57) -> 164528.92 | BF58: =SUM(BF48:BF57) -> 80352.12 | BG58: =SUM(BG48:BG57) -> 42686.087 | BH58: =SUM(BH48:BH57) -> 77428.957 | BI58: =SUM(AZ58:BH58) -> 715133 | BJ58: 1.013 | CD58: 1991 to 2000 | CE58: 19161 | CL58: Liquid Petroleum Gas (LPG) | CM58: 982 | CR58: Before 1919 | CS58: Attached | CT58: Wood (incl. wood pellets) | CU58: 391
B59: Before_1919 | C59: Bottled LPG | D59: 7 | E59: 56 | F59: 62 | AY59: Adjusted Total | AZ59: =AZ58*$BJ$32 -> 20378.706 | BA59: =BA58*$BJ$32 -> 9433.9012 | BB59: =BB58*$BJ$32 -> 20090.949 | BC59: =BC58*$BJ$32 -> 53466.21 | BD59: =BD58*$BJ$32 -> 251318.93 | BE59: =BE58*$BJ$32 -> 166667.79 | BF59: =BF58*$BJ$32 -> 81396.698 | BG59: =BG58*$BJ$32 -> 43241.006 | BH59: =BH58*$BJ$32 -> 78435.533 | BI59: =SUM(AZ59:BH59) -> 724429.73 | CD59: 2001 to 2010 | CE59: 51682 | CL59: Wood (incl. wood pellets) | CM59: 2318 | CR59: Before 1919 | CS59: Attached | CT59: Other fuels | CU59: 101
B60: Before_1919 | C60: Bulk LPG (propane or butane) | D60: 24 | E60: 88 | F60: 354 | CD60: 2011 or later | CE60: 3127 | CL60: Other fuels | CM60: 707 | CR60: Before 1919 | CS60: Attached | CT60: Not stated | CU60: 229
B61: Before_1919 | C61: Electricity | D61: 3428 | E61: 2965 | F61: 2184 | CD61: Not stated | CE61: 19315 | CL61: Not stated | CM61: 6366 | CR61: Before 1919 | CS61: Apartments
B62: Before_1919 | C62: Heating Oil | D62: 469 | E62: 6480 | F62: 14309 | CC62: Flat or apartment in a purpose- built block | CK62: Flat or apartment in a purpose- built block | CR62: Before 1919 | CS62: Apartments | CT62: All households | CU62: 3159
B63: Before_1919 | C63: House Coal | D63: 13 | E63: 149 | F63: 189 | CD63: All years | CE63: 172096 | CL63: All households | CM63: 172096 | CR63: Before 1919 | CS63: Apartments | CT63: No central heating | CU63: 166
B64: Before_1919 | C64: Mains Gas | D64: 1700 | E64: 11573 | F64: 1169 | CD64: Before 1919 | CE64: 3159 | CL64: No central heating | CM64: 3289 | CR64: Before 1919 | CS64: Apartments | CT64: Oil | CU64: 223
B65: Before_1919 | C65: Manufactured Smokeless Fuel_Coal | D65: 26 | E65: 468 | F65: 110 | CD65: 1919 to 1945 | CE65: 2434 | CL65: Oil | CM65: 4596 | CR65: Before 1919 | CS65: Apartments | CT65: Natural Gas | CU65: 1077
B66: Before_1919 | C66: Peat Briquettes | D66: 5 | E66: 9 | F66: 19 | CD66: 1946 to 1960 | CE66: 3415 | CL66: Natural Gas | CM66: 73152 | CR66: Before 1919 | CS66: Apartments | CT66: Electricity | CU66: 1575
B67: Before_1919 | C67: Sod Peat | D67: 1 | E67: 25 | F67: 124 | CD67: 1961 to 1970 | CE67: 4039 | CL67: Electricity | CM67: 78339 | CR67: Before 1919 | CS67: Apartments | CT67: Coal (incl. Anthracite_Coal) | CU67: 40
B68: Before_1919 | C68: Solid Multi-Fuel | D68: 52 | E68: 964 | F68: 2455 | CD68: 1971 to 1980 | CE68: 5873 | CL68: Coal (incl. Anthracite_Coal) | CM68: 1107 | CR68: Before 1919 | CS68: Apartments | CT68: Peat (incl. turf) | CU68: 8
B69: Before_1919 | C69: Wood Chips | E69: 1 | F69: 4 | CD69: 1981 to 1990 | CE69: 9310 | CL69: Peat (incl. turf) | CM69: 317 | CR69: Before 1919 | CS69: Apartments | CT69: Liquid Petroleum Gas (LPG) | CU69: 13
B70: Before_1919 | C70: Wood Logs | D70: 2 | E70: 19 | F70: 78 | CD70: 1991 to 2000 | CE70: 27108 | CL70: Liquid Petroleum Gas (LPG) | CM70: 648 | CR70: Before 1919 | CS70: Apartments | CT70: Wood (incl. wood pellets) | CU70: 16
B71: Before_1919 | C71: Wood Pellets (bulk supply for | D71: 2 | E71: 24 | F71: 64 | CD71: 2001 to 2010 | CE71: 84521 | CL71: Wood (incl. wood pellets) | CM71: 350 | CR71: Before 1919 | CS71: Apartments | CT71: Other fuels | CU71: 17
B72: Before_1919 | C72: Wood Pellets (in bags for seco | E72: 4 | F72: 7 | CD72: 2011 or later | CE72: 5717 | CL72: Other fuels | CM72: 1146 | CR72: Before 1919 | CS72: Apartments | CT72: Not stated | CU72: 24
B73: 1919-1945 | D73: 59 | E73: 32 | F73: 11 | CD73: Not stated | CE73: 26520 | CL73: Not stated | CM73: 9152 | CR73: Before 1919 | CS73: Apartments
B74: 1919-1945 | C74: Anthracite_Coal | E74: 1 | F74: 1 | CC74: Flat or apartment in a converted house or commercial building | CK74: Flat or apartment in a converted house or commercial building | CR74: Before 1919 | CS74: Apartments | CT74: All households | CU74: 10547
B75: 1919-1945 | C75: Bottled LPG | D75: 6 | E75: 29 | F75: 36 | CD75: All years | CE75: 28783 | CL75: All households | CM75: 28783 | CR75: Before 1919 | CS75: Apartments | CT75: No central heating | CU75: 775
B76: 1919-1945 | C76: Bulk LPG (propane or butane) | D76: 15 | E76: 66 | F76: 205 | CD76: Before 1919 | CE76: 9575 | CL76: No central heating | CM76: 1513 | CR76: Before 1919 | CS76: Apartments | CT76: Oil | CU76: 1399
B77: 1919-1945 | C77: Electricity | D77: 952 | E77: 1854 | F77: 1386 | CD77: 1919 to 1945 | CE77: 2653 | CL77: Oil | CM77: 4191 | CR77: Before 1919 | CS77: Apartments | CT77: Natural Gas | CU77: 2576
B78: 1919-1945 | C78: Heating Oil | D78: 266 | E78: 7569 | F78: 10518 | CD78: 1946 to 1960 | CE78: 1745 | CL78: Natural Gas | CM78: 6389 | CR78: Before 1919 | CS78: Apartments | CT78: Electricity | CU78: 5260
B79: 1919-1945 | C79: House Coal | D79: 6 | E79: 189 | F79: 163 | CD79: 1961 to 1970 | CE79: 1186 | CL79: Electricity | CM79: 12593 | CR79: Before 1919 | CS79: Apartments | CT79: Coal (incl. Anthracite_Coal) | CU79: 123
B80: 1919-1945 | C80: Mains Gas | D80: 1447 | E80: 15245 | F80: 1646 | CD80: 1971 to 1980 | CE80: 1176 | CL80: Coal (incl. Anthracite_Coal) | CM80: 469 | CR80: Before 1919 | CS80: Apartments | CT80: Peat (incl. turf) | CU80: 67
B81: 1919-1945 | C81: Manufactured Smokeless Fuel_Coal | D81: 12 | E81: 567 | F81: 92 | CD81: 1981 to 1990 | CE81: 1039 | CL81: Peat (incl. turf) | CM81: 217 | CR81: Before 1919 | CS81: Apartments | CT81: Liquid Petroleum Gas (LPG) | CU81: 43
B82: 1919-1945 | C82: Peat Briquettes | E82: 19 | F82: 10 | CD82: 1991 to 2000 | CE82: 1530 | CL82: Liquid Petroleum Gas (LPG) | CM82: 126 | CR82: Before 1919 | CS82: Apartments | CT82: Wood (incl. wood pellets) | CU82: 72
B83: 1919-1945 | C83: Sod Peat | D83: 1 | E83: 31 | F83: 111 | CD83: 2001 to 2010 | CE83: 2247 | CL83: Wood (incl. wood pellets) | CM83: 182 | CR83: Before 1919 | CS83: Apartments | CT83: Other fuels | CU83: 75
B84: 1919-1945 | C84: Solid Multi-Fuel | D84: 36 | E84: 1204 | F84: 1763 | CD84: 2011 or later | CE84: 365 | CL84: Other fuels | CM84: 203 | CR84: Before 1919 | CS84: Apartments | CT84: Not stated | CU84: 157
B85: 1919-1945 | C85: Wood Chips | E85: 2 | F85: 5 | CD85: Not stated | CE85: 7267 | CL85: Not stated | CM85: 2900 | CR85: Before 1919 | CS85: Not stated
B86: 1919-1945 | C86: Wood Logs | E86: 18 | F86: 51 | CC86: Bed-sit | CK86: Bed-sit | CR86: Before 1919 | CS86: Not stated | CT86: All households | CU86: 935
B87: 1919-1945 | C87: Wood Pellets (bulk supply for | E87: 15 | F87: 30 | CD87: All years | CE87: 3266 | CL87: All households | CM87: 3266 | CR87: Before 1919 | CS87: Not stated | CT87: No central heating | CU87: 38
B88: 1919-1945 | C88: Wood Pellets (in bags for seco | E88: 3 | F88: 4 | CD88: Before 1919 | CE88: 972 | CL88: No central heating | CM88: 266 | CR88: Before 1919 | CS88: Not stated | CT88: Oil | CU88: 368
B89: 1946-1960 | D89: 43 | E89: 28 | F89: 5 | CD89: 1919 to 1945 | CE89: 306 | CL89: Oil | CM89: 412 | CR89: Before 1919 | CS89: Not stated | CT89: Natural Gas | CU89: 110
B90: 1946-1960 | C90: Anthracite_Coal | E90: 2 | F90: 4 | CD90: 1946 to 1960 | CE90: 229 | CL90: Natural Gas | CM90: 535 | CR90: Before 1919 | CS90: Not stated | CT90: Electricity | CU90: 104
B91: 1946-1960 | C91: Biodiesel from renewable sourc | E91: 1 | CD91: 1961 to 1970 | CE91: 195 | CL91: Electricity | CM91: 1608 | CR91: Before 1919 | CS91: Not stated | CT91: Coal (incl. Anthracite_Coal) | CU91: 104
B92: 1946-1960 | C92: Bottled LPG | D92: 4 | E92: 21 | F92: 29 | CD92: 1971 to 1980 | CE92: 152 | CL92: Coal (incl. Anthracite_Coal) | CM92: 34 | CR92: Before 1919 | CS92: Not stated | CT92: Peat (incl. turf) | CU92: 112
B93: 1946-1960 | C93: Bulk LPG (propane or butane) | D93: 11 | E93: 62 | F93: 146 | CD93: 1981 to 1990 | CE93: 136 | CL93: Peat (incl. turf) | CM93: 31 | CR93: Before 1919 | CS93: Not stated | CT93: Liquid Petroleum Gas (LPG) | CU93: 4
B94: 1946-1960 | C94: Electricity | D94: 561 | E94: 1666 | F94: 923 | CD94: 1991 to 2000 | CE94: 142 | CL94: Liquid Petroleum Gas (LPG) | CM94: 19 | CR94: Before 1919 | CS94: Not stated | CT94: Wood (incl. wood pellets) | CU94: 47
B95: 1946-1960 | C95: Heating Oil | D95: 241 | E95: 9598 | F95: 9928 | CD95: 2001 to 2010 | CE95: 152 | CL95: Wood (incl. wood pellets) | CM95: 16 | CR95: Before 1919 | CS95: Not stated | CT95: Other fuels | CU95: 2
B96: 1946-1960 | C96: House Coal | D96: 6 | E96: 136 | F96: 110 | CD96: 2011 or later | CE96: 42 | CL96: Other fuels | CM96: 49 | CR96: Before 1919 | CS96: Not stated | CT96: Not stated | CU96: 46
B97: 1946-1960 | C97: Mains Gas | D97: 1283 | E97: 20485 | F97: 2121 | CD97: Not stated | CE97: 940 | CL97: Not stated | CM97: 296 | CR97: 1919 to 1945
B98: 1946-1960 | C98: Manufactured Smokeless Fuel_Coal | D98: 10 | E98: 447 | F98: 62 | CC98: Not stated | CK98: Not stated | CR98: 1920 to 1945 | CS98: All households
B99: 1946-1960 | C99: Peat Briquettes | E99: 18 | F99: 15 | CD99: All years | CE99: 21870 | CL99: All households | CM99: 21870 | CR99: 1920 to 1945 | CT99: All households | CU99: 109668
B100: 1946-1960 | C100: Sod Peat | D100: 1 | E100: 30 | F100: 81 | CD100: Before 1919 | CE100: 935 | CL100: No central heating | CM100: 229 | CR100: 1920 to 1945 | CT100: No central heating | CU100: 2951
B101: 1946-1960 | C101: Solid Multi-Fuel | D101: 24 | E101: 952 | F101: 1206 | CD101: 1919 to 1945 | CE101: 685 | CL101: Oil | CM101: 4384 | CR101: 1920 to 1945 | CT101: Oil | CU101: 42020
B102: 1946-1960 | C102: Wood Logs | D102: 1 | E102: 13 | F102: 29 | CD102: 1946 to 1960 | CE102: 760 | CL102: Natural Gas | CM102: 4623 | CR102: 1920 to 1945 | CT102: Natural Gas | CU102: 35749
B103: 1946-1960 | C103: Wood Pellets (bulk supply for | D103: 2 | E103: 11 | F103: 19 | CD103: 1961 to 1970 | CE103: 666 | CL103: Electricity | CM103: 1453 | CR103: 1920 to 1945 | CT103: Electricity | CU103: 5995
...

Sheet COMM
C2: Commodities | M2: Commodities
C3: ~FI_COMM | M3: ~FI_COMM
C4: Csets | D4: Region | E4: CommName | F4: CommDesc | G4: Unit | H4: LimType | I4: CTSLvl | J4: PeakTS | K4: Ctype | M4: Csets | N4: Region | O4: CommName | P4: CommDesc | Q4: Unit | R4: LimType | S4: CTSLvl | T4: PeakTS | U4: Ctype
C5: * Set | D5: Region Name | E5: Commodity Name | F5: Commodity Description | G5: Unit | H5: Sense of the Balance EQ | I5: Timeslice Level | J5: Peak Monitoring | K5: Electricity Indicator | M5: * Set | N5: Region Name | O5: Commodity Name | P5: Commodity Description | Q5: Unit | R5: Sense of the Balance EQ | S5: Timeslice Level | T5: Peak Monitoring | U5: Electricity Indicator
A6: =TRIM(SETUP!A8) | C6: =A6&"NRG" -> NRG | D6: =_xlfn.TEXTJOIN(",",TRUE,IF(LEFT(Regions!$C$3,1)<>"*",Regions!$C$3,""),IF(LEFT(Regions!$D$3,1)<>"*",Regions!$D$3,"")) -> IE,National | E6: =SETUP!B8 -> RSDCOA | F6: =SETUP!C8 -> Coal to Residential | G6: PJ | H6: FX | M6: DEM | N6: =_xlfn.TEXTJOIN(",",TRUE,IF(LEFT(Regions!$C$3,1)<>"*",Regions!$C$3,""),IF(LEFT(Regions!$D$3,1)<>"*",Regions!$D$3,"")) -> IE,National | O6: =_xlfn.TEXTJOIN("",TRUE,SETUP!B$3,"_",SETUP!B36) -> RSD_Apt | P6: =_xlfn.TEXTJOIN(" ",TRUE,SETUP!C$3,SETUP!C36, "Demand") -> Residential Apartment Demand | Q6: 000dwellings | R6: FX
A7: =TRIM(SETUP!A9) | C7: =A7&"NRG" -> NRG | D7: =_xlfn.TEXTJOIN(",",TRUE,IF(LEFT(Regions!$C$3,1)<>"*",Regions!$C$3,""),IF(LEFT(Regions!$D$3,1)<>"*",Regions!$D$3,"")) -> IE,National | E7: =SETUP!B9 -> RSDPEA | F7: =SETUP!C9 -> Peat to Residential | G7: PJ | H7: FX | M7: DEM | N7: =_xlfn.TEXTJOIN(",",TRUE,IF(LEFT(Regions!$C$3,1)<>"*",Regions!$C$3,""),IF(LEFT(Regions!$D$3,1)<>"*",Regions!$D$3,"")) -> IE,National | O7: =_xlfn.TEXTJOIN("",TRUE,SETUP!B$3,"_",SETUP!B37) -> RSD_Att | P7: =_xlfn.TEXTJOIN(" ",TRUE,SETUP!C$3,SETUP!C37, "Demand") -> Residential Attached Demand | Q7: 000dwellings | R7: FX
A8: =TRIM(SETUP!A10) | C8: =A8&"NRG" -> NRG | D8: =_xlfn.TEXTJOIN(",",TRUE,IF(LEFT(Regions!$C$3,1)<>"*",Regions!$C$3,""),IF(LEFT(Regions!$D$3,1)<>"*",Regions!$D$3,"")) -> IE,National | E8: =SETUP!B10 -> RSDLPG | F8: =SETUP!C10 -> LPG to Residential | G8: PJ | H8: FX | M8: DEM | N8: =_xlfn.TEXTJOIN(",",TRUE,IF(LEFT(Regions!$C$3,1)<>"*",Regions!$C$3,""),IF(LEFT(Regions!$D$3,1)<>"*",Regions!$D$3,"")) -> IE,National | O8: =_xlfn.TEXTJOIN("",TRUE,SETUP!B$3,"_",SETUP!B38) -> RSD_Det | P8: =_xlfn.TEXTJOIN(" ",TRUE,SETUP!C$3,SETUP!C38, "Demand") -> Residential Detached Demand | Q8: 000dwellings | R8: FX
A9: =TRIM(SETUP!A11) -> * | C9: =A9&"NRG" -> *NRG | D9: =_xlfn.TEXTJOIN(",",TRUE,IF(LEFT(Regions!$C$3,1)<>"*",Regions!$C$3,""),IF(LEFT(Regions!$D$3,1)<>"*",Regions!$D$3,"")) -> IE,National | E9: =SETUP!B11 -> RSDGSL | F9: =SETUP!C11 -> Gasoline to Residential | G9: PJ | H9: FX | M9: NRG | N9: =_xlfn.TEXTJOIN(",",TRUE,IF(LEFT(Regions!$C$3,1)<>"*",Regions!$C$3,""),IF(LEFT(Regions!$D$3,1)<>"*",Regions!$D$3,"")) -> IE,National | O9: =_xlfn.TEXTJOIN("",TRUE,SETUP!B$3,SETUP!B$50,"_",SETUP!B$36,"-AB") -> RSDSH_Apt-AB | P9: =_xlfn.TEXTJOIN(" ",TRUE,SETUP!C$3,SETUP!C$50,SETUP!C$36) -> Residential Space Heating Apartment | Q9: PJ
A10: =TRIM(SETUP!A12) | C10: =A10&"NRG" -> NRG | D10: =_xlfn.TEXTJOIN(",",TRUE,IF(LEFT(Regions!$C$3,1)<>"*",Regions!$C$3,""),IF(LEFT(Regions!$D$3,1)<>"*",Regions!$D$3,"")) -> IE,National | E10: =SETUP!B12 -> RSDKER | F10: =SETUP!C12 -> Kerosene to Residential | G10: PJ | H10: FX | M10: NRG | N10: =_xlfn.TEXTJOIN(",",TRUE,IF(LEFT(Regions!$C$3,1)<>"*",Regions!$C$3,""),IF(LEFT(Regions!$D$3,1)<>"*",Regions!$D$3,"")) -> IE,National | O10: =_xlfn.TEXTJOIN("",TRUE,SETUP!B$3,SETUP!B$50,"_",SETUP!B$37,"-AB") -> RSDSH_Att-AB | P10: =_xlfn.TEXTJOIN(" ",TRUE,SETUP!C$3,SETUP!C$50,SETUP!C$37) -> Residential Space Heating Attached | Q10: PJ
A11: * | C11: =A11&"NRG" -> *NRG | D11: =_xlfn.TEXTJOIN(",",TRUE,IF(LEFT(Regions!$C$3,1)<>"*",Regions!$C$3,""),IF(LEFT(Regions!$D$3,1)<>"*",Regions!$D$3,"")) -> IE,National | E11: =SETUP!B13 -> RSDDST | F11: =SETUP!C13 -> Gasoil / Diesel /DERV to Residential | G11: PJ | H11: FX | M11: NRG | N11: =_xlfn.TEXTJOIN(",",TRUE,IF(LEFT(Regions!$C$3,1)<>"*",Regions!$C$3,""),IF(LEFT(Regions!$D$3,1)<>"*",Regions!$D$3,"")) -> IE,National | O11: =_xlfn.TEXTJOIN("",TRUE,SETUP!B$3,SETUP!B$50,"_",SETUP!B$38,"-AB") -> RSDSH_Det-AB | P11: =_xlfn.TEXTJOIN(" ",TRUE,SETUP!C$3,SETUP!C$50,SETUP!C$38) -> Residential Space Heating Detached | Q11: PJ
A12: * | C12: =A12&"NRG" -> *NRG | D12: =_xlfn.TEXTJOIN(",",TRUE,IF(LEFT(Regions!$C$3,1)<>"*",Regions!$C$3,""),IF(LEFT(Regions!$D$3,1)<>"*",Regions!$D$3,"")) -> IE,National | E12: =SETUP!B14 -> RSDHFO | F12: =SETUP!C14 -> Fueloil to Residential | G12: PJ | H12: FX | M12: NRG | N12: =_xlfn.TEXTJOIN(",",TRUE,IF(LEFT(Regions!$C$3,1)<>"*",Regions!$C$3,""),IF(LEFT(Regions!$D$3,1)<>"*",Regions!$D$3,"")) -> IE,National | O12: =_xlfn.TEXTJOIN("",TRUE,SETUP!B$3,SETUP!B$50,"_",SETUP!B$36,"-C") -> RSDSH_Apt-C | P12: =_xlfn.TEXTJOIN(" ",TRUE,SETUP!C$3,SETUP!C$50,SETUP!C$36) -> Residential Space Heating Apartment | Q12: PJ
