Workbook

Sheet Cover
A16: TIMES-Ireland Model
A19: Document type: | B19: Base Year Template
A20: Sector(s): | B20: Transport sector (TRA)
A21: Purpose: | B21: Transport structure in Ireland and the base year simulation
A23: Original developer(s): | B23: Vahid Aryanpur (UCC, vahid.aryanpur@ucc.ie)
B24: James Glynn (UCC, james.glynn@ucc.ie)
A26: Current maintainer(s): | B26: Vahid Aryanpur (UCC, vahid.aryanpur@ucc.ie)
A29: Part of TIM version: | B29: 1
A30: Model repository: | B30: https://github.com/MaREI-EPMG/TIMES-Ireland-model
A31: Licence: | B31: CC BY-NC-SA 4.0 (unless specified otherwise)
B32: https://creativecommons.org/licenses/by-nc-sa/4.0/

Sheet Intro
B2: Table of contents
B3: Sheet | C3: Description
B4: EB2018 | C4: SEAI 2018 energy balance in ktoe
B5: Commodities | C5: TIMES commodities list for the sector
B6: TRA_FuelTechs | C6: Fuel sectoral technologies/infrastructure
B7: TRA_FuelBlending | C7: Fuel blending
B8: Demands | C8: Energy service demands for the transport sector
B9: Emi | C9: Emission coefficients for the transport sector
B10: CAR | C10: TIMES inputs for Cars
B11: MOTO | C11: TIMES inputs for Moto
B12: FREH | C12: TIMES inputs for Freight
B13: PUB | C13: TIMES inputs for Public
B14: NAV | C14: TIMES inputs for Navigation
... B16: … | C16: Data elaboration sheets
B18: Tab colour legend
C19: General inputs
C20: Private cars
C21: Motorcycles
C22: Freight
C23: Public
C24: Navigation
C25: Aviation
B27: Units
B28: Capacity | C28: V or PJa
B29: Consumption | C29: PJ
B30: Currency (year) | C30: Milion Euro 2018
B31: Base year | C31: 2018

Sheet EB2018
A1: 2018 Units = ktoe | B1: NACE (Rev 2) | C1: Coal | D1: Bituminous Coal | E1: Anthracite + Manufactured Ovoids | F1: Coke | G1: Lignite \ Brown Coal Briquettes | H1: Peat | I1: Milled Peat | J1: Sod Peat | K1: Briquettes | L1: Oil | M1: Crude | N1: Refinery Feedstocks | O1: Refinery Gas | P1: Gasoline | Q1: Kerosene | R1: Jet Kerosene | S1: Fueloil | T1: LPG | U1: Gasoil / Diesel /DERV | V1: Petroleum Coke | W1: Naphta | X1: Bitumen | Y1: White Spirit | Z1: Lubricants | AA1: Natural Gas | AB1: Renewables | AC1: Hydro | AD1: Wind | AE1: Biomass | AF1: Renewable Waste | AG1: Landfill Gas | AH1: Biogas | AI1: Biodiesel | AJ1: Bioethanol | AK1: Solar Photovoltaic | AL1: Solar Thermal | AM1: Ambient Heat | AN1: Non-Renewable Waste | AO1: Electricity | AP1: Heat | AQ1: TOTAL
A2: Indigenous Production | C2: =SUM(D2:G2) -> 0 | D2: 0 | H2: =SUM(I2:K2) -> 815.92435 | I2: 688.22035 | J2: 127.704 | L2: =SUM(M2:Z2) -> 0 | AA2: 2751.9192 | AB2: =SUM(AC2:AM2) -> 1334.6583 | AC2: 59.691709 | AD2: 743.01992 | AE2: 248.9086 | AF2: 139.99993 | AG2: 33.531819 | AH2: 16.813133 | AI2: 31.064468 | AJ2: 2.6691993 | AK2: 1.8899881 | AL2: 13.546086 | AM2: 43.523448 | AN2: 145.4371 | AQ2: =C2+H2+L2+AA2+AB2+AN2+AO2+AP2 -> 5047.9389
A3: Imports | C3: =SUM(D3:G3) -> 903.49466 | D3: 829.5746 | E3: 61.722868 | G3: 12.197194 | H3: =SUM(I3:K3) -> 0 | L3: =SUM(M3:Z3) -> 9138.5578 | M3: 3053.4743 | N3: 16.633377 | O3: 0 | P3: 564.23641 | Q3: 369.14639 | R3: 1542.2444 | S3: 82.827949 | T3: 157.54636 | U3: 2932.6956 | V3: 166.37648 | W3: 7.5616539 | X3: 200.83222 | Y3: 1.228147 | Z3: 43.754533 | AA3: 1728.3381 | AB3: =SUM(AC3:AM3) -> 151.93356 | AE3: 24.282116 | AI3: 104.81441 | AJ3: 22.83703 | AO3: 139.45062 | AQ3: =C3+H3+L3+AA3+AB3+AN3+AO3+AP3 -> 12061.775
A4: Exports | C4: =SUM(D4:G4) -> 15.186581 | D4: 0 | E4: 14.097722 | G4: 1.0888587 | H4: =SUM(I4:K4) -> 7.033068 | K4: 7.033068 | L4: =SUM(M4:Z4) -> 1717.0625 | M4: 0 | N4: 0 | P4: 364.52222 | Q4: 21.672508 | R4: 156.2938 | S4: 986.60612 | T4: 35.289733 | U4: 102.14625 | V4: 0.0029088438 | W4: 36.297317 | X4: 5.469469 | Y4: 0.018500298 | Z4: 8.7436483 | AA4: 0 | AB4: =SUM(AC4:AM4) -> 9.4476585 | AE4: 0.4126464 | AI4: 9.0350121 | AJ4: 0 | AO4: 141.83539 | AQ4: =C4+H4+L4+AA4+AB4+AN4+AO4+AP4 -> 1890.5652
A5: Mar. Bunkers | C5: =SUM(D5:G5) -> 0 | H5: =SUM(I5:K5) -> 0 | L5: =SUM(M5:Z5) -> 172.71259 | S5: 15.730078 | U5: 156.98251 | AB5: =SUM(AC5:AM5) -> 0 | AQ5: =C5+H5+L5+AA5+AB5+AN5+AO5+AP5 -> 172.71259
A6: Stock Change | C6: =SUM(D6:G6) -> -101.25635 | D6: -101.86989 | E6: -0.80797667 | G6: 1.421516 | H6: =SUM(I6:K6) -> -122.93905 | I6: -136.53827 | J6: 0 | K6: 13.599214 | L6: =SUM(M6:Z6) -> 151.33981 | M6: 38.730965 | N6: -8.875152 | P6: -9.6980083 | Q6: 12.883202 | R6: 82.120249 | S6: 23.6376 | T6: 1.4659197 | U6: 8.3874136 | V6: 3.2040911 | W6: -0.51646779 | X6: 0 | Y6: 0 | Z6: 0 | AA6: 0 | AB6: =SUM(AC6:AM6) -> 4.4601014 | AE6: 0.26707428 | AI6: 1.7828522 | AJ6: 2.410175 | AQ6: =C6+H6+L6+AA6+AB6+AN6+AO6+AP6 -> -68.395488
A7: Primary Energy Supply (incl non-energy) | C7: =C2+C3-C4-C5+C6 -> 787.05173 | D7: =D2+D3-D4-D5+D6 -> 727.70471 | E7: =E2+E3-E4-E5+E6 -> 46.817169 | F7: =F2+F3-F4-F5+F6 -> 0 | G7: =G2+G3-G4-G5+G6 -> 12.529851 | H7: =H2+H3-H4-H5+H6 -> 685.95223 | I7: =I2+I3-I4-I5+I6 -> 551.68208 | J7: =J2+J3-J4-J5+J6 -> 127.704 | ... AP7: =AP2+AP3-AP4-AP5+AP6 -> 0 | AQ7: =C7+H7+L7+AA7+AB7+AN7+AO7+AP7 -> 14978.04
A8: Primary Energy Requirement (excl. non-energy) | C8: =C7-C27 -> 787.05173 | D8: =D7-D27 -> 727.70471 | E8: =E7-E27 -> 46.817169 | F8: =F7-F27 -> 0 | G8: =G7-G27 -> 12.529851 | H8: =H7-H27 -> 685.95223 | I8: =I7-I27 -> 551.68208 | J8: =J7-J27 -> 127.704 | ... AP8: =AP7-AP27 -> 0 | AQ8: =C8+H8+L8+AA8+AB8+AN8+AO8+AP8 -> 14746.457
A9: Transformation Input | C9: =SUM(C10:C14) -> 489.1342 | D9: =SUM(D10:D14) -> 489.1342 | E9: =SUM(E10:E14) -> 0 | F9: =SUM(F10:F14) -> 0 | G9: =SUM(G10:G14) -> 0 | H9: =SUM(H10:H14) -> 541.02658 | I9: =SUM(I10:I14) -> 541.02658 | J9: =SUM(J10:J14) -> 0 | ... AP9: =SUM(AP10:AP14) -> 0 | AQ9: =C9+H9+L9+AA9+AB9+AN9+AO9+AP9 -> 7058.1841
A10: Public Thermal Power Plants (Input) | C10: =SUM(D10:G10) -> 489.1342 | D10: 489.1342 | H10: =SUM(I10:K10) -> 467.10846 | I10: 467.10846 | J10: 0 | L10: =SUM(M10:Z10) -> 34.094789 | S10: 25.868327 | U10: 8.2264622 | AA10: 2187.6034 | AB10: =SUM(AC10:AM10) -> 205.3059 | AE10: 72.46706 | AF10: 99.307023 | AG10: 33.531819 | AN10: 90.714163 | AQ10: =C10+H10+L10+AA10+AB10+AN10+AO10+AP10 -> 3473.9609
A11: Combined Heat and Power Plants (Input) | C11: =SUM(D11:G11) -> 0 | D11: 0 | H11: =SUM(I11:K11) -> 5.8425469 | I11: 5.8425469 | L11: =SUM(M11:Z11) -> 0.63499472 | O11: 0 | S11: 0 | T11: 0.63499472 | U11: 0 | AA11: 272.96145 | AB11: =SUM(AC11:AM11) -> 10.597627 | AE11: 3.561556 | AH11: 7.0360715 | AQ11: =C11+H11+L11+AA11+AB11+AN11+AO11+AP11 -> 290.03662
A12: Pumped Storage Consumption (Input) | AO12: 42.94206 | AQ12: =C12+H12+L12+AA12+AB12+AN12+AO12+AP12 -> 42.94206
A13: Briquetting Plants (Input) | C13: =SUM(D13:G13) -> 0 | H13: =SUM(I13:K13) -> 68.075577 | I13: 68.075577 | L13: =SUM(M13:Z13) -> 0 | AB13: =SUM(AC13:AM13) -> 0 | AQ13: =C13+H13+L13+AA13+AB13+AN13+AO13+AP13 -> 68.075577
A14: Oil Refineries & other energy sector (Input) | C14: =SUM(D14:G14) -> 0 | H14: =SUM(I14:K14) -> 0 | L14: =SUM(M14:Z14) -> 3130.9919 | M14: 3092.2053 | N14: 38.786602 | AA14: 40.734585 | AB14: =SUM(AC14:AM14) -> 0 | AO14: 11.442472 | AQ14: =C14+H14+L14+AA14+AB14+AN14+AO14+AP14 -> 3183.1689
A15: Transformation Output | C15: =SUM(C16:C20) -> 0 | D15: =SUM(D16:D20) -> 0 | E15: =SUM(E16:E20) -> 0 | F15: =SUM(F16:F20) -> 0 | G15: =SUM(G16:G20) -> 0 | H15: =SUM(H16:H20) -> 64.671798 | I15: =SUM(I16:I20) -> 0 | J15: =SUM(J16:J20) -> 0 | ... AP15: =SUM(AP16:AP20) -> 0 | AQ15: =C15+H15+L15+AA15+AB15+AN15+AO15+AP15 -> 5104.8192
A16: Public Thermal Power Plants (Output) | C16: =SUM(D16:G16) -> 0 | H16: =SUM(I16:K16) -> 0 | L16: =SUM(M16:Z16) -> 0 | AB16: =SUM(AC16:AL16) -> 0 | AO16: 1667.7866 | AQ16: =C16+H16+L16+AA16+AO16+AP16 -> 1667.7866
A17: Combined Heat and Power Plants (Output) | C17: =SUM(D17:G17) -> 0 | H17: =SUM(I17:K17) -> 0 | L17: =SUM(M17:Z17) -> 0 | AB17: =SUM(AC17:AL17) -> 0 | AO17: 185.14396 | AQ17: =C17+H17+L17+AA17+AO17+AP17 -> 185.14396
A18: Pumped Storage Generation (Output) | AO18: 20.430939 | AQ18: =C18+H18+L18+AA18+AB18+AN18+AO18+AP18 -> 20.430939
A19: Briquetting Plants (Output) | H19: =SUM(I19:K19) -> 64.671798 | K19: 64.671798 | L19: =SUM(M19:Z19) -> 0 | AB19: =SUM(AC19:AL19) -> 0 | AQ19: =C19+H19+L19+AA19+AB19+AN19+AO19+AP19 -> 64.671798
A20: Oil Refineries & other energy sector (Output) | H20: =SUM(I20:K20) -> 0 | L20: =SUM(M20:Z20) -> 3166.7859 | O20: 90.017984 | P20: 640.5368 | Q20: 226.77459 | R20: 0 | S20: 960.95018 | T20: 64.797463 | U20: 1146.9502 | W20: 36.758644 | AB20: =SUM(AC20:AL20) -> 0 | AQ20: =C20+H20+L20+AA20+AB20+AN20+AO20+AP20 -> 3166.7859
A21: Exchanges and transfers | C21: =SUM(C22:C24) -> 22.240062 | D21: =SUM(D22:D24) -> -17.141361 | E21: =SUM(E22:E24) -> 39.381423 | F21: =SUM(F22:F24) -> 0 | G21: =SUM(G22:G24) -> 0 | H21: =SUM(I21:K21) -> 0 | I21: =SUM(I22:I24) -> 0 | J21: =SUM(J22:J24) -> 0 | K21: =SUM(K22:K24) -> 0 | L21: =SUM(M21:Z21) -> -24.684016 | M21: =SUM(M22:M24) -> 0 | N21: =SUM(N22:N24) -> 30.880435 | O21: =SUM(O22:O24) -> 0 | P21: =SUM(P22:P24) -> -31.331711 | Q21: =SUM(Q22:Q24) -> 361.9108 | R21: =SUM(R22:R24) -> -361.12225 | S21: =SUM(S22:S24) -> -0.17168421 | T21: =SUM(T22:T24) -> 0 | ... AQ21: =SUM(AQ22:AQ24) -> -2.4439548
A22: Electricity Exchange & Transfers | AB22: =SUM(AC22:AM22) -> -804.60162 | AC22: =-AC2 -> -59.691709 | AD22: =-AD2 -> -743.01992 | AK22: -1.8899881 | AO22: =-(C22+H22+L22+AA22+AB22) -> 804.60162 | AQ22: =C22+H22+L22+AA22+AB22+AN22+AO22+AP22 -> 0
A23: Heat Exchange & Transfers | AQ23: =C23+H23+L23+AA23+AB23+AN23+AO23+AP23 -> 0
A24: Other Exchange & Transfers | C24: =SUM(D24:G24) -> 22.240062 | D24: -17.141361 | E24: =-D24-V24 -> 39.381423 | L24: =SUM(N24:Z24) -> -24.684016 | N24: 30.880435 | P24: -31.331711 | Q24: 361.9108 | R24: -361.12225 | S24: -0.17168421 | U24: -2.6095464 | V24: -22.240062 | W24: 0 | AB24: =SUM(AC24:AM24) -> 0 | AQ24: =C24+H24+L24+AA24+AB24+AN24+AO24+AP24 -> -2.4439548
A25: Own Use and Distribution Losses | C25: =SUM(D25:G25) -> 0 | H25: =SUM(I25:K25) -> 10.283248 | I25: 10.283248 | L25: =SUM(O25:Z25) -> 98.284658 | O25: 95.274692 | S25: 0 | T25: 0.0041693256 | U25: 3.0057963 | AA25: 57.5286 | AB25: =SUM(AC25:AI25) -> 0 | AO25: 259.46681 | AQ25: =C25+H25+L25+AA25+AB25+AN25+AO25+AP25 -> 425.56332
A26: Available Final Energy Consumption | C26: =C7-C9+C15+C21-C25 -> 320.1576 | D26: =D7-D9+D15+D21-D25 -> 221.42916 | E26: =E7-E9+E15+E21-E25 -> 86.198592 | F26: =F7-F9+F15+F21-F25 -> 0 | G26: =G7-G9+G15+G21-G25 -> 12.529851 | H26: =H7-H9+H15+H21-H25 -> 199.3142 | I26: =I7-I9+I15+I21-I25 -> 0.37225107 | J26: =J7-J9+J15+J21-J25 -> 127.704 | ... AP26: =AP7-AP9+AP15+AP21-AP25 -> 0 | AQ26: =C26+H26+L26+AA26+AB26+AN26+AO26+AP26 -> 12596.668
A27: Non-Energy Consumption | C27: =C28 -> 0 | D27: =D28 -> 0 | E27: =E28 -> 0 | F27: =F28 -> 0 | G27: =G28 -> 0 | H27: =H28 -> 0 | I27: =I28 -> 0 | J27: =J28 -> 0 | ... V27: =V28 -> 0 | X27: =X28 -> 195.36275 | Y27: =Y28 -> 1.2096467 | Z27: =Z28 -> 35.010885 | AA27: =AA28 -> 0 | AB27: =AB28 -> 0 | AC27: =AC28 -> 0 | AD27: =AD28 -> 0 | AE27: =AE28 -> 0 | ... AQ27: =AQ28 -> 231.58328
A28: Final non-Energy Consumption (Feedstocks) | C28: =SUM(D28:G28) -> 0 | H28: =SUM(I28:K28) -> 0 | L28: =SUM(M28:Z28) -> 231.58328 | X28: =X26 -> 195.36275 | Y28: =Y26 -> 1.2096467 | Z28: =Z26 -> 35.010885 | AA28: 0 | AB28: =SUM(AC28:AI28) -> 0 | AQ28: =C28+H28+L28+AA28+AB28+AN28+AO28+AP28 -> 231.58328
A29: Total Final Energy Consumption | C29: =C30+C45+C56+C58+C65+C70+C71 -> 322.73713 | D29: =D30+D45+D56+D58+D65+D70+D71 -> 221.25199 | E29: =E30+E45+E56+E58+E65+E70+E71 -> 89.64728 | F29: =F30+F45+F56+F58+F65+F70+F71 -> 0 | G29: =G30+G45+G56+G58+G65+G70+G71 -> 11.837385 | H29: =H30+H45+H56+H58+H65+H70+H71 -> 197.36847 | I29: =I30+I45+I56+I58+I65+I70+I71 -> 0.82966372 | J29: =J30+J45+J56+J58+J65+J70+J71 -> 127.704 | ... AQ29: =AQ30+AQ45+AQ56+AQ58+AQ65+AQ70+AQ71 -> 12441.76
A30: Industry* | C30: =SUM(C31:C44) -> 105.42503 | D30: 105.42455 | E30: 0 | H30: =SUM(H31:H44) -> 0.82966372 | I30: =SUM(I31:I44) -> 0.82966372 | J30: =SUM(J31:J44) -> 0 | K30: =SUM(K31:K44) -> 0 | L30: =SUM(L31:L44) -> 333.21701 | M30: =SUM(M31:M44) -> 0 | N30: =SUM(N31:N44) -> 0 | O30: =SUM(O31:O44) -> 0 | P30: =SUM(P31:P44) -> 0 | Q30: 5.8273118 | R30: =SUM(R31:R44) -> 0 | S30: 30.396553 | T30: 55.10581 | U30: 100.77893 | V30: 141.1084 | W30: =SUM(W31:W44) -> 0 | X30: =SUM(X31:X44) -> 0 | Y30: =SUM(Y31:Y44) -> 0 | Z30: =SUM(Z31:Z44) -> 0 | AA30: 1006.4294 | AB30: =SUM(AB31:AB44) -> 198.81521 | AC30: =SUM(AC31:AC44) -> 0 | AD30: =SUM(AD31:AD44) -> 0 | AE30: =SUM(AE31:AE44) -> 153.96699 | AF30: =SUM(AF31:AF44) -> 40.692904 | AG30: =SUM(AG31:AG44) -> 0 | AH30: =SUM(AH31:AH44) -> 4.1553164 | AI30: =SUM(AI31:AI44) -> 0 | ... AN30: =SUM(AN31:AN44) -> 54.72294 | AO30: 562.37095 | AP30: =SUM(AP31:AP44) -> 0 | AQ30: =C30+H30+L30+AA30+AB30+AN30+AO30+AP30 -> 2261.8102
A31: Non-Energy Mining | B31: 05-09 | C31: =SUM(D31:G31) -> 0 | D31: 0 | H31: =SUM(I31:K31) -> 0 | L31: =SUM(M31:Z31) -> 15.076944 | Q31: 0.252 | S31: 0 | T31: 0.090944232 | U31: 14.734 | V31: 0 | AA31: 11.321518 | AB31: =SUM(AC31:AM31) -> 0 | AO31: 18.942945 | AQ31: =C31+H31+L31+AA31+AB31+AN31+AO31+AP31 -> 45.341408
A32: Food & beverages | B32: 10-11 | C32: =SUM(D32:G32) -> 18.505816 | D32: 18.505816 | H32: =SUM(I32:K32) -> 0.82966372 | I32: 0.82966372 | L32: =SUM(M32:Z32) -> 65.081235 | Q32: 1.514 | S32: 22.968462 | T32: 29.495772 | U32: 11.103 | V32: 0 | AA32: 272.71139 | AB32: =SUM(AC32:AM32) -> 27.983335 | AE32: 23.828019 | AH32: 4.1553164 | AO32: 95.275089 | AQ32: =C32+H32+L32+AA32+AB32+AN32+AO32+AP32 -> 480.38653
A33: Textiles and textile products | B33: 13-14 | C33: =SUM(D33:G33) -> 0 | D33: 0 | H33: =SUM(I33:K33) -> 0 | L33: =SUM(M33:Z33) -> 4.25876 | Q33: 0.077 | S33: 0 | T33: 3.90776 | U33: 0.274 | V33: 0 | AA33: 3.3044502 | AB33: =SUM(AC33:AM33) -> 0 | AO33: 2.6521774 | AQ33: =C33+H33+L33+AA33+AB33+AN33+AO33+AP33 -> 10.215388
A34: Wood and wood products | B34: 16 | C34: =SUM(D34:G34) -> 0 | D34: 0 | H34: =SUM(I34:K34) -> 0 | L34: =SUM(M34:Z34) -> 3.2131896 | Q34: 0.177 | S34: 0 | T34: 0.60818955 | U34: 2.428 | V34: 0 | AA34: 9.6605546 | AB34: =SUM(AC34:AM34) -> 127.9132 | AE34: 127.9132 | AO34: 24.722009 | AQ34: =C34+H34+L34+AA34+AB34+AN34+AO34+AP34 -> 165.50895
A35: Pulp, paper, publishing and printing | B35: 17-18 | C35: =SUM(D35:G35) -> 0 | D35: 0 | H35: =SUM(I35:K35) -> 0 | L35: =SUM(M35:Z35) -> 1.6055046 | Q35: 0.096 | S35: 0 | T35: 0.6295046 | U35: 0.88 | V35: 0 | AA35: 14.125994 | AB35: =SUM(AC35:AM35) -> 0 | AO35: 10.336268 | AQ35: =C35+H35+L35+AA35+AB35+AN35+AO35+AP35 -> 26.067767
A36: Chemicals & man-made fibres | B36: 20-21 | C36: =SUM(D36:G36) -> 0 | D36: 0 | H36: =SUM(I36:K36) -> 0 | L36: =SUM(M36:Z36) -> 21.418897 | Q36: 0.306 | S36: 2.7458234 | T36: 3.9702841 | U36: 4.579 | V36: 9.8177897 | AA36: 129.58451 | AB36: =SUM(AC36:AM36) -> 0 | AE36: 0 | AO36: 76.140196 | AQ36: =C36+H36+L36+AA36+AB36+AN36+AO36+AP36 -> 227.1436
A37: Rubber and plastic products | B37: 22 | C37: =SUM(D37:G37) -> 0 | D37: 0 | H37: =SUM(I37:K37) -> 0 | L37: =SUM(M37:Z37) -> 4.1927666 | Q37: 0.535 | S37: 0 | T37: 2.1897666 | U37: 1.468 | V37: 0 | AA37: 17.456036 | AB37: =SUM(AC37:AM37) -> 0 | AO37: 25.060497 | AQ37: =C37+H37+L37+AA37+AB37+AN37+AO37+AP37 -> 46.7093
A38: Other non-metallic mineral products | B38: 23 | C38: =SUM(D38:G38) -> 86.919212 | D38: 86.919212 | H38: =SUM(I38:K38) -> 0 | L38: =SUM(M38:Z38) -> 160.32357 | Q38: 1.144 | S38: 0 | T38: 2.6359617 | U38: 25.253 | V38: 131.29061 | AA38: 46.760405 | AB38: =SUM(AC38:AM38) -> 42.918678 | AE38: 2.2257741 | AF38: 40.692904 | AN38: 54.72294 | AO38: 73.686158 | AQ38: =C38+H38+L38+AA38+AB38+AN38+AO38+AP38 -> 465.33096
A39: Basic metals and fabricated metal products | B39: 24-25 | C39: =SUM(D39:G39) -> 0 | D39: 0 | H39: =SUM(I39:K39) -> 0 | L39: =SUM(M39:Z39) -> 5.6776554 | Q39: 0.338 | S39: 1.0397615 | T39: 1.5488939 | U39: 2.751 | V39: 0 | AA39: 411.95146 | AB39: =SUM(AC39:AM39) -> 0 | AO39: 67.595438 | AQ39: =C39+H39+L39+AA39+AB39+AN39+AO39+AP39 -> 485.22456
A40: Machinery and equipment n.e.c. | B40: 28 | C40: =SUM(D40:G40) -> 0 | D40: 0 | H40: =SUM(I40:K40) -> 0 | L40: =SUM(M40:Z40) -> 4.0583976 | Q40: 0.144 | S40: 0 | T40: 2.2053976 | U40: 1.709 | V40: 0 | AA40: 14.088543 | AB40: =SUM(AC40:AM40) -> 0 | AO40: 17.03379 | AQ40: =C40+H40+L40+AA40+AB40+AN40+AO40+AP40 -> 35.180731
A41: Electrical and optical equipment | B41: 26-27 | C41: =SUM(D41:G41) -> 0 | D41: 0 | H41: =SUM(I41:K41) -> 0 | L41: =SUM(M41:Z41) -> 2.3538977 | Q41: 0.184 | S41: 0 | T41: 1.4408977 | U41: 0.729 | V41: 0 | AA41: 20.514556 | AB41: =SUM(AC41:AM41) -> 0 | AO41: 88.215343 | AQ41: =C41+H41+L41+AA41+AB41+AN41+AO41+AP41 -> 111.0838
A42: Transport equipment manufacture | B42: 29-30 | C42: =SUM(D42:G42) -> 0 | D42: 0 | H42: =SUM(I42:K42) -> 0 | L42: =SUM(M42:Z42) -> 1.2106524 | Q42: 0.066 | S42: 0 | T42: 0.92365235 | U42: 0.221 | V42: 0 | AA42: 0.86574848 | AB42: =SUM(AC42:AM42) -> 0 | AO42: 2.5758112 | AQ42: =C42+H42+L42+AA42+AB42+AN42+AO42+AP42 -> 4.6522121
A43: Other manufacturing | B43: 31-33, 12 & 15 | C43: =SUM(D43:G43) -> 0 | D43: 0 | H43: =SUM(I43:K43) -> 0 | K43: 0 | L43: =SUM(M43:Z43) -> 12.040387 | Q43: 0.293 | S43: 3.6425061 | T43: 4.9848807 | U43: 3.12 | V43: 0 | AA43: 49.987456 | AB43: =SUM(AC43:AM43) -> 0 | AO43: 50.1922 | AQ43: =C43+H43+L43+AA43+AB43+AN43+AO43+AP43 -> 112.22004
A44: Construction | B44: 41-43 | C44: =SUM(D44:G44) -> 0 | D44: 0 | H44: =SUM(I44:K44) -> 0 | L44: =SUM(M44:Z44) -> 32.70515 | Q44: 0.70131178 | S44: 0 | T44: 0.4739052 | U44: 31.529933 | V44: 0 | AA44: 4.0968183 | AB44: =SUM(AC44:AM44) -> 0 | AO44: 9.9430291 | AQ44: =C44+H44+L44+AA44+AB44+AN44+AO44+AP44 -> 46.744997
A45: Transport | C45: =SUM(C46:C55) -> 0 | D45: =SUM(D46:D55) -> 0 | E45: =SUM(E46:E55) -> 0 | F45: =SUM(F46:F55) -> 0 | G45: =SUM(G46:G55) -> 0 | H45: =SUM(H46:H55) -> 0 | I45: =SUM(I46:I55) -> 0 | J45: =SUM(J46:J55) -> 0 | ... AP45: =SUM(AP46:AP55) -> 0 | AQ45: =C45+H45+L45+AA45+AB45+AN45+AO45+AP45 -> 5194.8404
A46: Road Freight | C46: =SUM(D46:G46) -> 0 | H46: =SUM(I46:K46) -> 0 | L46: =SUM(M46:Z46) -> 703.59089 | U46: 703.59089 | AA46: 0.029723186 | AB46: =SUM(AC46:AM46) -> 30.16231 | AI46: 30.16231 | AJ46: 0 | AQ46: =C46+H46+L46+AA46+AB46+AN46+AO46+AP46 -> 733.78292
A47: Road Light Goods Vehicle | C47: =SUM(D47:G47) -> 0 | H47: =SUM(I47:K47) -> 0 | L47: =SUM(M47:Z47) -> 329.18378 | U47: 329.18378 | AB47: =SUM(AC47:AM47) -> 14.111813 | AI47: 14.111813 | AJ47: 0 | AQ47: =C47+H47+L47+AA47+AB47+AN47+AO47+AP47 -> 343.29559
A48: Road Private Car | C48: =SUM(D48:G48) -> 0 | H48: =SUM(I48:K48) -> 0 | L48: =SUM(M48:Z48) -> 1988.8117 | P48: 674.58043 | T48: 1.8520724 | U48: 1312.3792 | AB48: =SUM(AC48:AM48) -> 78.598026 | AI48: 56.260518 | AJ48: 22.337507 | AO48: 1.0652907 | AQ48: =C48+H48+L48+AA48+AB48+AN48+AO48+AP48 -> 2068.475
A49: Public Passenger Services | C49: =SUM(D49:G49) -> 0 | H49: =SUM(I49:K49) -> 0 | L49: =SUM(M49:Z49) -> 132.19129 | P49: 6.5053364 | U49: 125.68595 | AB49: =SUM(AC49:AM49) -> 5.6034563 | AI49: 5.3880439 | AJ49: 0.21541241 | AQ49: =C49+H49+L49+AA49+AB49+AN49+AO49+AP49 -> 137.79474
A50: Rail | C50: =SUM(D50:G50) -> 0 | H50: =SUM(I50:K50) -> 0 | L50: =SUM(M50:Z50) -> 38.043222 | U50: 38.043222 | AB50: =SUM(AC50:AM50) -> 0 | AI50: 0 | AO50: 4.3080909 | AQ50: =C50+H50+L50+AA50+AB50+AN50+AO50+AP50 -> 42.351313
A51: Domestic Aviation | C51: =SUM(D51:G51) -> 0 | H51: =SUM(I51:K51) -> 0 | L51: =SUM(M51:Z51) -> 5.5768893 | P51: 0.66818889 | R51: 4.9087004 | AB51: =SUM(AC51:AM51) -> 0 | AQ51: =C51+H51+L51+AA51+AB51+AN51+AO51+AP51 -> 5.5768893
A52: International Aviation | C52: =SUM(D52:G52) -> 0 | H52: =SUM(I52:K52) -> 0 | L52: =SUM(M52:Z52) -> 1097.9355 | R52: 1097.9355 | AB52: =SUM(AC52:AM52) -> 0 | AQ52: =C52+H52+L52+AA52+AB52+AN52+AO52+AP52 -> 1097.9355
A53: Fuel Tourism | C53: =SUM(D53:G53) -> 0 | H53: =SUM(I53:K53) -> 0 | L53: =SUM(M53:Z53) -> 176.59351 | P53: 0 | U53: 176.59351 | AB53: =SUM(AC53:AM53) -> 7.5704053 | AI53: 7.5704053 | AJ53: 0 | AQ53: =C53+H53+L53+AA53+AB53+AN53+AO53+AP53 -> 184.16392
A54: Navigation | C54: =SUM(D54:G54) -> 0 | H54: =SUM(I54:K54) -> 0 | L54: =SUM(M54:Z54) -> 83.913724 | U54: 83.913724 | AB54: =SUM(AC54:AM54) -> 0 | AQ54: =C54+H54+L54+AA54+AB54+AN54+AO54+AP54 -> 83.913724
A55: Unspecified | C55: =SUM(D55:G55) -> 0 | H55: =SUM(I55:K55) -> 0 | L55: =SUM(M55:Z55) -> 456.82605 | P55: 142.49107 | S55: 0 | U55: 314.33498 | AA55: 22.531112 | AB55: =SUM(AC55:AM55) -> 18.193592 | AI55: 13.475259 | AJ55: 4.7183332 | AQ55: =C55+H55+L55+AA55+AB55+AN55+AO55+AP55 -> 497.55075
A56: Residential | C56: =SUM(D56:G56) -> 216.79218 | D56: 115.30752 | E56: 89.64728 | G56: 11.837385 | H56: =SUM(I56:K56) -> 196.53881 | J56: 127.704 | K56: 68.834806 | L56: =SUM(M56:Z56) -> 1254.8255 | P56: 0 | Q56: 865.6711 | S56: 0 | T56: 53.841523 | U56: 329.90901 | V56: 5.4038717 | AA56: 604.09376 | AB56: =SUM(AC56:AM56) -> 71.02667 | AE56: 29.776082 | AL56: 13.379591 | AM56: 27.870996 | AO56: 702.94474 | AQ56: =C56+H56+L56+AA56+AB56+AN56+AO56+AP56 -> 3046.2217
A57: Commercial/Public Services* | C57: =C58+C65 -> 0.5199218 | D57: =D58+D65 -> 0.5199218 | E57: =E58+E65 -> 0 | F57: =F58+F65 -> 0 | G57: =G58+G65 -> 0 | H57: =H58+H65 -> 0 | I57: =I58+I65 -> 0 | J57: =J58+J65 -> 0 | ... AP57: =AP58+AP65 -> 0 | AQ57: =C57+H57+L57+AA57+AB57+AN57+AO57+AP57 -> 1688.1847
A58: Commercial Services* | C58: =SUM(D58:G58) -> 0.51492256 | D58: 0.51492256 | E58: 0 | F58: =SUM(F59:F64) -> 0 | G58: 0 | H58: =SUM(I58:K58) -> 0 | I58: =SUM(I59:I64) -> 0 | J58: =SUM(J59:J64) -> 0 | K58: =SUM(K59:K64) -> 0 | L58: =SUM(M58:Z58) -> 109.16311 | M58: =SUM(M59:M64) -> 0 | N58: =SUM(N59:N64) -> 0 | O58: =SUM(O59:O64) -> 0 | P58: =SUM(P59:P64) -> 0 | Q58: 15.841 | R58: =SUM(R59:R64) -> 0 | S58: 0 | T58: 41.07411 | U58: 52.248 | V58: =SUM(V59:V64) -> 0 | W58: =SUM(W59:W64) -> 0 | X58: =SUM(X59:X64) -> 0 | Y58: =SUM(Y59:Y64) -> 0 | Z58: =SUM(Z59:Z64) -> 0 | AA58: 206.51565 | AB58: =SUM(AC58:AM58) -> 20.523796 | AC58: =SUM(AC59:AC64) -> 0 | AD58: =SUM(AD59:AD64) -> 0 | AE58: =SUM(AE59:AE64) -> 3.9004189 | AG58: =SUM(AG59:AG64) -> 0 | AH58: =SUM(AH59:AH64) -> 0.80443075 | AI58: =SUM(AI59:AI64) -> 0 | AJ58: =SUM(AJ59:AJ64) -> 0 | AL58: 0.16649466 | AM58: 15.652452 | AN58: =SUM(AN59:AN64) -> 0 | AO58: 828.90452 | AP58: =SUM(AP59:AP64) -> 0 | AQ58: =C58+H58+L58+AA58+AB58+AN58+AO58+AP58 -> 1165.622
A59: Wholesale, Retail, and Vehicle Repair | B59: 45-47 | C59: =SUM(D59:G59) -> 0.0039993985 | D59: 0.0039993985 | H59: =SUM(I59:K59) -> 0 | L59: =SUM(M59:Z59) -> 29.110393 | Q59: 6.548 | S59: 0 | T59: 11.487393 | U59: 11.075 | V59: 0 | AA59: 52.670839 | AB59: =SUM(AC59:AM59) -> 1.2953272 | AE59: 1.2953272 | AH59: 0 | AL59: 0 | AM59: 0 | AO59: 225.70856 | AQ59: =C59+H59+L59+AA59+AB59+AN59+AO59+AP59 -> 308.78912
A60: Transportation and Storage | B60: 49-53 | C60: =SUM(D60:G60) -> 0.0089986466 | D60: 0.0089986466 | H60: =SUM(I60:K60) -> 0 | L60: =SUM(M60:Z60) -> 24.503931 | Q60: 1.271 | S60: 0 | T60: 1.9979311 | U60: 21.235 | V60: 0 | AA60: 23.74348 | AB60: =SUM(AC60:AM60) -> 0.011385567 | AE60: 0.011385567 | AH60: 0 | AL60: 0 | AM60: 0 | AO60: 81.932676 | AQ60: =C60+H60+L60+AA60+AB60+AN60+AO60+AP60 -> 130.20047
A61: Accommodation and Food Services | B61: 55-56 | C61: =SUM(D61:G61) -> 0.42993534 | D61: 0.42993534 | H61: =SUM(I61:K61) -> 0 | L61: =SUM(M61:Z61) -> 27.815961 | Q61: 3.399 | S61: 0 | T61: 19.454961 | U61: 4.962 | V61: 0 | AA61: 30.235657 | AB61: =SUM(AC61:AM61) -> 0.86179983 | AE61: 0.86179983 | AH61: 0 | AL61: 0 | AM61: 0 | AO61: 126.36748 | AQ61: =C61+H61+L61+AA61+AB61+AN61+AO61+AP61 -> 185.71084
A62: Information and Communication | B62: 58-63 | C62: =SUM(D62:G62) -> 0.0069989474 | D62: 0.0069989474 | H62: =SUM(I62:K62) -> 0 | L62: =SUM(M62:Z62) -> 2.6967648 | Q62: 0.363 | S62: 0 | T62: 0.71476482 | U62: 1.619 | V62: 0 | AA62: 12.942534 | AB62: =SUM(AC62:AM62) -> 0.04641808 | AE62: 0.04641808 | AH62: 0 | AL62: 0 | AM62: 0 | AO62: 234.42875 | AQ62: =C62+H62+L62+AA62+AB62+AN62+AO62+AP62 -> 250.12147
A63: Financial, Insurance and Real Estate Activities | B63: 64-68 | C63: =SUM(D63:G63) -> 0.057991278 | D63: 0.057991278 | H63: =SUM(I63:K63) -> 0 | L63: =SUM(M63:Z63) -> 3.8680994 | Q63: 0.684 | S63: 0 | T63: 0.16909943 | U63: 3.015 | V63: 0 | AA63: 11.636733 | AB63: =SUM(AC63:AM63) -> 0.3476977 | AE63: 0.3476977 | AH63: 0 | AL63: 0 | AM63: 0 | AO63: 42.65981 | AQ63: =C63+H63+L63+AA63+AB63+AN63+AO63+AP63 -> 58.570331
A64: Other Services Sectors | C64: =SUM(D64:G64) -> 0.0069989474 | D64: 0.0069989474 | H64: =SUM(I64:K64) -> 0 | L64: =SUM(M64:Z64) -> 21.16796 | Q64: 3.576 | S64: 0 | T64: 7.2499605 | U64: 10.342 | V64: 0 | AA64: 75.286411 | AB64: =SUM(AC64:AM64) -> 17.961168 | AE64: 1.3377905 | AH64: 0.80443075 | AL64: 0.16649466 | AM64: 15.652452 | AO64: 117.80725 | AQ64: =C64+H64+L64+AA64+AB64+AN64+AO64+AP64 -> 232.22978
A65: Public Services* | C65: =SUM(D65:G65) -> 0.0049992481 | D65: =SUM(D66:D69) -> 0.0049992481 | H65: =SUM(I65:K65) -> 0 | J65: 0 | K65: 0 | L65: =SUM(M65:Z65) -> 131.70415 | Q65: 46.986 | S65: 0.64284747 | T65: 29.4503 | U65: 54.625 | V65: =SUM(V66:V69) -> 0 | AA65: 122.10424 | AB65: =SUM(AC65:AM65) -> 18.910018 | AE65: =SUM(AE66:AE69) -> 14.092704 | AH65: 4.817314 | AO65: 249.83924 | AQ65: =C65+H65+L65+AA65+AB65+AN65+AO65+AP65 -> 522.56265
A66: Water Supply, Sewerage, and Waste Management | B66: 36-39 | C66: =SUM(D66:G66) -> 0.0029995489 | D66: 0.0029995489 | H66: =SUM(I66:K66) -> 0 | L66: =SUM(M66:Z66) -> 4.8361472 | Q66: 0.13 | S66: 0.0031863567 | T66: 1.1339609 | U66: 3.569 | V66: 0 | AA66: 6.2855711 | AB66: =SUM(AC66:AM66) -> 4.8181898 | AE66: 0.00087581284 | AH66: 4.817314 | AO66: 62.066112 | AQ66: =C66+H66+L66+AA66+AB66+AN66+AO66+AP66 -> 78.00902
A67: Public Administration | B67: 84 | C67: =SUM(D67:G67) -> 0.0019996992 | D67: 0.0019996992 | H67: =SUM(I67:K67) -> 0 | L67: =SUM(M67:Z67) -> 37.495977 | Q67: 6.925 | S67: 0.36191702 | T67: 7.4190599 | U67: 22.79 | V67: 0 | AA67: 43.318633 | AB67: =SUM(AC67:AM67) -> 3.013672 | AE67: 3.013672 | AH67: 0 | AO67: 90.275167 | AQ67: =C67+H67+L67+AA67+AB67+AN67+AO67+AP67 -> 174.10545
A68: Education | B68: 85 | C68: =SUM(D68:G68) -> 0 | D68: 0 | H68: =SUM(I68:K68) -> 0 | L68: =SUM(M68:Z68) -> 63.764873 | Q68: 27.067 | S68: 0.054168064 | T68: 17.705705 | U68: 18.938 | V68: 0 | AA68: 27.252039 | AB68: =SUM(AC68:AM68) -> 9.8108554 | AE68: 9.8108554 | AH68: 0 | AO68: 58.093006 | AQ68: =C68+H68+L68+AA68+AB68+AN68+AO68+AP68 -> 158.92077
A69: Health, Residential Care and Social Work Activities | B69: 86-88 | C69: =SUM(D69:G69) -> 0 | D69: 0 | H69: =SUM(I69:K69) -> 0 | L69: =SUM(M69:Z69) -> 25.60715 | Q69: 12.864 | S69: 0.22357603 | T69: 3.1915741 | U69: 9.328 | V69: 0 | AA69: 45.247998 | AB69: =SUM(AC69:AM69) -> 1.2673012 | AE69: 1.2673012 | AH69: 0 | AO69: 39.404959 | AQ69: =C69+H69+L69+AA69+AB69+AN69+AO69+AP69 -> 111.52741
A70: Agricultural | C70: =SUM(D70:G70) -> 0 | D70: 0 | H70: =SUM(I70:K70) -> 0 | L70: =SUM(M70:Z70) -> 175.46549 | P70: 0 | Q70: 0 | T70: 0 | U70: 175.46549 | AA70: 0 | AB70: =SUM(AC70:AM70) -> 0 | AO70: 47.988 | AQ70: =C70+H70+L70+AA70+AB70+AN70+AO70+AP70 -> 223.45349
A71: Fisheries | C71: =SUM(D71:G71) -> 0 | H71: =SUM(I71:K71) -> 0 | L71: =SUM(M71:Z71) -> 27.249866 | U71: 27.249866 | AB71: =SUM(AC71:AM71) -> 0 | AQ71: =C71+H71+L71+AA71+AB71+AN71+AO71+AP71 -> 27.249866
A72: Statistical Difference | C72: =C26-C27-C29 -> -2.5795347 | D72: =D26-D27-D29 -> 0.17716668 | E72: =E26-E27-E29 -> -3.4486884 | F72: =F26-F27-F29 -> 0 | G72: =G26-G27-G29 -> 0.69246574 | H72: =H26-H27-H29 -> 1.945725 | I72: =I26-I27-I29 -> -0.45741265 | J72: =J26-J27-J29 -> 0 | ... AP72: =AP26-AP27-AP29 -> 0 | AQ72: =C72+H72+L72+AA72+AB72+AN72+AO72+AP72 -> -76.675386
A74: *Industry & Services sub-sectoral breakdown is based on the BEUS 2018.
A75: Last Updated : 1st September 2022
A76: 2018 provisional data
A77: 2018 provisional data based on 2017 breakdown
A78: 2017 data
A79: Sod peat is estimated due to new legislation and the methodology is under review
A80: Statistical differences may exist for crude oil between the calculated primary energy requirement and the observed refinery input

Sheet Regions
C3: {=IF(LEFT(INDEX(C5:C7,$A$4),1)<>"*",INDEX(C5:C7,$A$4),"")} -> IE | D3: {=IF(LEFT(INDEX(D5:D7,$A$4),1)<>"*",INDEX(D5:D7,$A$4),"")} | E3: {=IF(LEFT(INDEX(E5:E7,$A$4),1)<>"*",INDEX(E5:E7,$A$4),"")} -> IE-CW | F3: {=IF(LEFT(INDEX(F5:F7,$A$4),1)<>"*",INDEX(F5:F7,$A$4),"")} -> IE-D | G3: {=IF(LEFT(INDEX(G5:G7,$A$4),1)<>"*",INDEX(G5:G7,$A$4),"")} -> IE-KE | H3: {=IF(LEFT(INDEX(H5:H7,$A$4),1)<>"*",INDEX(H5:H7,$A$4),"")} -> IE-KK | I3: {=IF(LEFT(INDEX(I5:I7,$A$4),1)<>"*",INDEX(I5:I7,$A$4),"")} -> IE-LS | J3: {=IF(LEFT(INDEX(J5:J7,$A$4),1)<>"*",INDEX(J5:J7,$A$4),"")} -> IE-LD | ... AD3: {=IF(LEFT(INDEX(AD5:AD7,$A$4),1)<>"*",INDEX(AD5:AD7,$A$4),"")} -> IE-MN
A4: 1
A5: Development | C5: IE | D5: *National | E5: =Regions!A11 -> IE-CW | F5: =Regions!A16 -> IE-D | G5: =Regions!A19 -> IE-KE | H5: =Regions!A20 -> IE-KK | I5: =Regions!A21 -> IE-LS | J5: =Regions!A24 -> IE-LD | K5: =Regions!A25 -> IE-LH | L5: =Regions!A27 -> IE-MH | M5: =Regions!A29 -> IE-OY | N5: =Regions!A34 -> IE-WH | O5: =Regions!A35 -> IE-WX | P5: =Regions!A36 -> IE-WW | Q5: =Regions!A13 -> IE-CE | R5: =Regions!A14 -> IE-CO | S5: =Regions!A18 -> IE-KY | T5: =Regions!A23 -> IE-LK | U5: =Regions!A32 -> IE-TA | V5: =Regions!A33 -> IE-WD | W5: =Regions!A17 -> IE-G | X5: =Regions!A22 -> IE-LM | Y5: =Regions!A26 -> IE-MO | Z5: =Regions!A30 -> IE-RN | AA5: =Regions!A31 -> IE-SO | AB5: =Regions!A12 -> IE-CN | AC5: =Regions!A15 -> IE-DL | AD5: =Regions!A28 -> IE-MN
A6: Single-region | C6: =C5 -> IE | D6: =IF(LEFT(D5,1)<>"*","*"&D5,D5) -> *National | E6: =IF(LEFT(E5,1)<>"*","*"&E5,E5) -> *IE-CW | F6: =IF(LEFT(F5,1)<>"*","*"&F5,F5) -> *IE-D | G6: =IF(LEFT(G5,1)<>"*","*"&G5,G5) -> *IE-KE | H6: =IF(LEFT(H5,1)<>"*","*"&H5,H5) -> *IE-KK | I6: =IF(LEFT(I5,1)<>"*","*"&I5,I5) -> *IE-LS | J6: =IF(LEFT(J5,1)<>"*","*"&J5,J5) -> *IE-LD | K6: =IF(LEFT(K5,1)<>"*","*"&K5,K5) -> *IE-LH | ... AD6: =IF(LEFT(AD5,1)<>"*","*"&AD5,AD5) -> *IE-MN
A7: Multi-region | C7: ="*"&C5 -> *IE | D7: =D5 -> *National | E7: =E5 -> IE-CW | F7: =F5 -> IE-D | G7: =G5 -> IE-KE | H7: =H5 -> IE-KK | I7: =I5 -> IE-LS | J7: =J5 -> IE-LD | K7: =K5 -> IE-LH | ... AD7: =AD5 -> IE-MN
A10: Code | B10: County name
A11: IE-CW | B11: Carlow
A12: IE-CN | B12: Cavan
A13: IE-CE | B13: Clare
A14: IE-CO | B14: Cork
A15: IE-DL | B15: Donegal
A16: IE-D | B16: Dublin
A17: IE-G | B17: Galway
A18: IE-KY | B18: Kerry
A19: IE-KE | B19: Kildare
A20: IE-KK | B20: Kilkenny
A21: IE-LS | B21: Laois
... A36: IE-WW | B36: Wicklow
A37: Source: https://en.wikipedia.org/wiki/ISO_3166-2:IE

Sheet Commodities
A1: Commodities
A3: ~FI_Comm
A4: Csets | B4: Region | C4: CommName | D4: CommDesc | E4: Unit | F4: LimType | G4: CTSLvl | H4: PeakTS | I4: Ctype
A5: *Commodity Set Membership | B5: Region | C5: Commodity Name | D5: Commodity Description | E5: Unit | F5: Balance equation | G5: Timeslice Level | H5: Peak Monitoring | I5: Electricity Indicator
A6: NRG | B6: =_xlfn.TEXTJOIN(",",TRUE,Regions!$C$3:'Regions'!$AD$3) -> IE,IE-CW,IE-D,IE-KE,IE-KK,IE-LS,IE-LD,IE-LH,IE-MH,IE-OY,IE-WH,IE-WX,IE-WW,IE-CE,IE-CO,IE-KY,IE-LK,IE-TA,IE-WD,IE-G,IE-LM,IE-MO,IE-RN,IE-SO,IE-CN,IE-DL,IE-MN | C6: TRAWLK | D6: Walking (TRA) | E6: PJ
B7: =_xlfn.TEXTJOIN(",",TRUE,Regions!$C$3:'Regions'!$AD$3) -> IE,IE-CW,IE-D,IE-KE,IE-KK,IE-LS,IE-LD,IE-LH,IE-MH,IE-OY,IE-WH,IE-WX,IE-WW,IE-CE,IE-CO,IE-KY,IE-LK,IE-TA,IE-WD,IE-G,IE-LM,IE-MO,IE-RN,IE-SO,IE-CN,IE-DL,IE-MN | C7: TRACYC | D7: Cycling (TRA) | E7: PJ
B8: =_xlfn.TEXTJOIN(",",TRUE,Regions!$C$3:'Regions'!$AD$3) -> IE,IE-CW,IE-D,IE-KE,IE-KK,IE-LS,IE-LD,IE-LH,IE-MH,IE-OY,IE-WH,IE-WX,IE-WW,IE-CE,IE-CO,IE-KY,IE-LK,IE-TA,IE-WD,IE-G,IE-LM,IE-MO,IE-RN,IE-SO,IE-CN,IE-DL,IE-MN | C8: TRAGSL | D8: Gasoline (TRA) | E8: PJ | F8: FX
B9: =_xlfn.TEXTJOIN(",",TRUE,Regions!$C$3:'Regions'!$AD$3) -> IE,IE-CW,IE-D,IE-KE,IE-KK,IE-LS,IE-LD,IE-LH,IE-MH,IE-OY,IE-WH,IE-WX,IE-WW,IE-CE,IE-CO,IE-KY,IE-LK,IE-TA,IE-WD,IE-G,IE-LM,IE-MO,IE-RN,IE-SO,IE-CN,IE-DL,IE-MN | C9: TRADST | D9: Diesel (TRA) | E9: PJ | F9: FX
B10: =_xlfn.TEXTJOIN(",",TRUE,Regions!$C$3:'Regions'!$AD$3) -> IE,IE-CW,IE-D,IE-KE,IE-KK,IE-LS,IE-LD,IE-LH,IE-MH,IE-OY,IE-WH,IE-WX,IE-WW,IE-CE,IE-CO,IE-KY,IE-LK,IE-TA,IE-WD,IE-G,IE-LM,IE-MO,IE-RN,IE-SO,IE-CN,IE-DL,IE-MN | C10: TRAETH | D10: BioEthanol (TRA) | E10: PJ | F10: FX
B11: =_xlfn.TEXTJOIN(",",TRUE,Regions!$C$3:'Regions'!$AD$3) -> IE,IE-CW,IE-D,IE-KE,IE-KK,IE-LS,IE-LD,IE-LH,IE-MH,IE-OY,IE-WH,IE-WX,IE-WW,IE-CE,IE-CO,IE-KY,IE-LK,IE-TA,IE-WD,IE-G,IE-LM,IE-MO,IE-RN,IE-SO,IE-CN,IE-DL,IE-MN | C11: TRABDL | D11: BioDiesel (TRA) | E11: PJ | F11: FX
B12: =_xlfn.TEXTJOIN(",",TRUE,Regions!$C$3:'Regions'!$AD$3) -> IE,IE-CW,IE-D,IE-KE,IE-KK,IE-LS,IE-LD,IE-LH,IE-MH,IE-OY,IE-WH,IE-WX,IE-WW,IE-CE,IE-CO,IE-KY,IE-LK,IE-TA,IE-WD,IE-G,IE-LM,IE-MO,IE-RN,IE-SO,IE-CN,IE-DL,IE-MN | C12: TRABJK | D12: Bio Jet Kerosene (TRA) | E12: PJ | F12: FX
B13: =_xlfn.TEXTJOIN(",",TRUE,Regions!$C$3:'Regions'!$AD$3) -> IE,IE-CW,IE-D,IE-KE,IE-KK,IE-LS,IE-LD,IE-LH,IE-MH,IE-OY,IE-WH,IE-WX,IE-WW,IE-CE,IE-CO,IE-KY,IE-LK,IE-TA,IE-WD,IE-G,IE-LM,IE-MO,IE-RN,IE-SO,IE-CN,IE-DL,IE-MN | C13: TRACNG | D13: CNG (TRA) | E13: PJ | F13: FX
B14: =_xlfn.TEXTJOIN(",",TRUE,Regions!$C$3:'Regions'!$AD$3) -> IE,IE-CW,IE-D,IE-KE,IE-KK,IE-LS,IE-LD,IE-LH,IE-MH,IE-OY,IE-WH,IE-WX,IE-WW,IE-CE,IE-CO,IE-KY,IE-LK,IE-TA,IE-WD,IE-G,IE-LM,IE-MO,IE-RN,IE-SO,IE-CN,IE-DL,IE-MN | C14: TRABNG | D14: BioCNG (TRA) | E14: PJ | F14: FX
B15: =_xlfn.TEXTJOIN(",",TRUE,Regions!$C$3:'Regions'!$AD$3) -> IE,IE-CW,IE-D,IE-KE,IE-KK,IE-LS,IE-LD,IE-LH,IE-MH,IE-OY,IE-WH,IE-WX,IE-WW,IE-CE,IE-CO,IE-KY,IE-LK,IE-TA,IE-WD,IE-G,IE-LM,IE-MO,IE-RN,IE-SO,IE-CN,IE-DL,IE-MN | C15: TRAELC | D15: Electricity (TRA) | E15: PJ | F15: FX | G15: DAYNITE | I15: ELC
B16: =_xlfn.TEXTJOIN(",",TRUE,Regions!$C$3:'Regions'!$AD$3) -> IE,IE-CW,IE-D,IE-KE,IE-KK,IE-LS,IE-LD,IE-LH,IE-MH,IE-OY,IE-WH,IE-WX,IE-WW,IE-CE,IE-CO,IE-KY,IE-LK,IE-TA,IE-WD,IE-G,IE-LM,IE-MO,IE-RN,IE-SO,IE-CN,IE-DL,IE-MN | C16: TRALNG | D16: LNG (TRA) | E16: PJ | F16: FX
B17: =_xlfn.TEXTJOIN(",",TRUE,Regions!$C$3:'Regions'!$AD$3) -> IE,IE-CW,IE-D,IE-KE,IE-KK,IE-LS,IE-LD,IE-LH,IE-MH,IE-OY,IE-WH,IE-WX,IE-WW,IE-CE,IE-CO,IE-KY,IE-LK,IE-TA,IE-WD,IE-G,IE-LM,IE-MO,IE-RN,IE-SO,IE-CN,IE-DL,IE-MN | C17: TRAH2 | D17: Hydrogen (TRA) | E17: PJ | F17: FX
B18: =_xlfn.TEXTJOIN(",",TRUE,Regions!$C$3:'Regions'!$AD$3) -> IE,IE-CW,IE-D,IE-KE,IE-KK,IE-LS,IE-LD,IE-LH,IE-MH,IE-OY,IE-WH,IE-WX,IE-WW,IE-CE,IE-CO,IE-KY,IE-LK,IE-TA,IE-WD,IE-G,IE-LM,IE-MO,IE-RN,IE-SO,IE-CN,IE-DL,IE-MN | C18: TRAKER | D18: Kerosene (TRA) | E18: PJ | F18: FX
B19: =B18 -> IE,IE-CW,IE-D,IE-KE,IE-KK,IE-LS,IE-LD,IE-LH,IE-MH,IE-OY,IE-WH,IE-WX,IE-WW,IE-CE,IE-CO,IE-KY,IE-LK,IE-TA,IE-WD,IE-G,IE-LM,IE-MO,IE-RN,IE-SO,IE-CN,IE-DL,IE-MN | C19: TRAPtLKER | D19: Power to Liquid, pure synthetic kerosene (TRA) | E19: PJ | F19: FX
B20: =B19 -> IE,IE-CW,IE-D,IE-KE,IE-KK,IE-LS,IE-LD,IE-LH,IE-MH,IE-OY,IE-WH,IE-WX,IE-WW,IE-CE,IE-CO,IE-KY,IE-LK,IE-TA,IE-WD,IE-G,IE-LM,IE-MO,IE-RN,IE-SO,IE-CN,IE-DL,IE-MN | C20: AVIKER | D20: Kerosene for Aviation | E20: PJ | F20: FX
B21: =B20 -> IE,IE-CW,IE-D,IE-KE,IE-KK,IE-LS,IE-LD,IE-LH,IE-MH,IE-OY,IE-WH,IE-WX,IE-WW,IE-CE,IE-CO,IE-KY,IE-LK,IE-TA,IE-WD,IE-G,IE-LM,IE-MO,IE-RN,IE-SO,IE-CN,IE-DL,IE-MN | C21: AVIBJK | D21: Biojet kerosene or SAF for Aviation | E21: PJ | F21: FX
B22: =B21 -> IE,IE-CW,IE-D,IE-KE,IE-KK,IE-LS,IE-LD,IE-LH,IE-MH,IE-OY,IE-WH,IE-WX,IE-WW,IE-CE,IE-CO,IE-KY,IE-LK,IE-TA,IE-WD,IE-G,IE-LM,IE-MO,IE-RN,IE-SO,IE-CN,IE-DL,IE-MN | C22: AVIELC | D22: Electricity for Aviation | E22: PJ | F22: FX
B23: =B22 -> IE,IE-CW,IE-D,IE-KE,IE-KK,IE-LS,IE-LD,IE-LH,IE-MH,IE-OY,IE-WH,IE-WX,IE-WW,IE-CE,IE-CO,IE-KY,IE-LK,IE-TA,IE-WD,IE-G,IE-LM,IE-MO,IE-RN,IE-SO,IE-CN,IE-DL,IE-MN | C23: AVIH2 | D23: Hydrogen for Aviation | E23: PJ | F23: FX
B24: =B23 -> IE,IE-CW,IE-D,IE-KE,IE-KK,IE-LS,IE-LD,IE-LH,IE-MH,IE-OY,IE-WH,IE-WX,IE-WW,IE-CE,IE-CO,IE-KY,IE-LK,IE-TA,IE-WD,IE-G,IE-LM,IE-MO,IE-RN,IE-SO,IE-CN,IE-DL,IE-MN | C24: AVIPtL | D24: Syntethic fuel for Aviation | E24: PJ | F24: FX
A25: DEM | B25: =_xlfn.TEXTJOIN(",",TRUE,Regions!$C$3:'Regions'!$AD$3) -> IE,IE-CW,IE-D,IE-KE,IE-KK,IE-LS,IE-LD,IE-LH,IE-MH,IE-OY,IE-WH,IE-WX,IE-WW,IE-CE,IE-CO,IE-KY,IE-LK,IE-TA,IE-WD,IE-G,IE-LM,IE-MO,IE-RN,IE-SO,IE-CN,IE-DL,IE-MN | C25: TRAPS | D25: Transport Demand: Short-range passenger travels | E25: Bpkm
B26: =_xlfn.TEXTJOIN(",",TRUE,Regions!$C$3:'Regions'!$AD$3) -> IE,IE-CW,IE-D,IE-KE,IE-KK,IE-LS,IE-LD,IE-LH,IE-MH,IE-OY,IE-WH,IE-WX,IE-WW,IE-CE,IE-CO,IE-KY,IE-LK,IE-TA,IE-WD,IE-G,IE-LM,IE-MO,IE-RN,IE-SO,IE-CN,IE-DL,IE-MN | C26: TRAPM | D26: Transport Demand: Medium-range passenger travels | E26: Bpkm
B27: =_xlfn.TEXTJOIN(",",TRUE,Regions!$C$3:'Regions'!$AD$3) -> IE,IE-CW,IE-D,IE-KE,IE-KK,IE-LS,IE-LD,IE-LH,IE-MH,IE-OY,IE-WH,IE-WX,IE-WW,IE-CE,IE-CO,IE-KY,IE-LK,IE-TA,IE-WD,IE-G,IE-LM,IE-MO,IE-RN,IE-SO,IE-CN,IE-DL,IE-MN | C27: TRAPL | D27: Transport Demand: Long-range passenger travels | E27: Bpkm
B28: =_xlfn.TEXTJOIN(",",TRUE,Regions!$C$3:'Regions'!$AD$3) -> IE,IE-CW,IE-D,IE-KE,IE-KK,IE-LS,IE-LD,IE-LH,IE-MH,IE-OY,IE-WH,IE-WX,IE-WW,IE-CE,IE-CO,IE-KY,IE-LK,IE-TA,IE-WD,IE-G,IE-LM,IE-MO,IE-RN,IE-SO,IE-CN,IE-DL,IE-MN | C28: TRAF | D28: Transport Demand: Goods vehicle for freight | E28: Btkm
B29: =_xlfn.TEXTJOIN(",",TRUE,Regions!$C$3:'Regions'!$AD$3) -> IE,IE-CW,IE-D,IE-KE,IE-KK,IE-LS,IE-LD,IE-LH,IE-MH,IE-OY,IE-WH,IE-WX,IE-WW,IE-CE,IE-CO,IE-KY,IE-LK,IE-TA,IE-WD,IE-G,IE-LM,IE-MO,IE-RN,IE-SO,IE-CN,IE-DL,IE-MN | C29: TTURS | D29: Transport Demand: Turism fuel | E29: PJ
B30: =_xlfn.TEXTJOIN(",",TRUE,Regions!$C$3:'Regions'!$AD$3) -> IE,IE-CW,IE-D,IE-KE,IE-KK,IE-LS,IE-LD,IE-LH,IE-MH,IE-OY,IE-WH,IE-WX,IE-WW,IE-CE,IE-CO,IE-KY,IE-LK,IE-TA,IE-WD,IE-G,IE-LM,IE-MO,IE-RN,IE-SO,IE-CN,IE-DL,IE-MN | C30: TNAV | D30: Transport Demand: Navigation fuel | E30: PJ
B31: =_xlfn.TEXTJOIN(",",TRUE,Regions!$C$3:'Regions'!$AD$3) -> IE,IE-CW,IE-D,IE-KE,IE-KK,IE-LS,IE-LD,IE-LH,IE-MH,IE-OY,IE-WH,IE-WX,IE-WW,IE-CE,IE-CO,IE-KY,IE-LK,IE-TA,IE-WD,IE-G,IE-LM,IE-MO,IE-RN,IE-SO,IE-CN,IE-DL,IE-MN | C31: TOTH | D31: Transport Demand: Unspecified fuel | E31: PJ
B32: =_xlfn.TEXTJOIN(",",TRUE,Regions!$C$3:'Regions'!$AD$3) -> IE,IE-CW,IE-D,IE-KE,IE-KK,IE-LS,IE-LD,IE-LH,IE-MH,IE-OY,IE-WH,IE-WX,IE-WW,IE-CE,IE-CO,IE-KY,IE-LK,IE-TA,IE-WD,IE-G,IE-LM,IE-MO,IE-RN,IE-SO,IE-CN,IE-DL,IE-MN | C32: TAVIDOM | D32: Transport Demand: Aviation domestic | E32: PJ
B33: =_xlfn.TEXTJOIN(",",TRUE,Regions!$C$3:'Regions'!$AD$3) -> IE,IE-CW,IE-D,IE-KE,IE-KK,IE-LS,IE-LD,IE-LH,IE-MH,IE-OY,IE-WH,IE-WX,IE-WW,IE-CE,IE-CO,IE-KY,IE-LK,IE-TA,IE-WD,IE-G,IE-LM,IE-MO,IE-RN,IE-SO,IE-CN,IE-DL,IE-MN | C33: TAVIINT | D33: Transport Demand: Aviation international | E33: PJ
B34: =_xlfn.TEXTJOIN(",",TRUE,Regions!$C$3:'Regions'!$AD$3) -> IE,IE-CW,IE-D,IE-KE,IE-KK,IE-LS,IE-LD,IE-LH,IE-MH,IE-OY,IE-WH,IE-WX,IE-WW,IE-CE,IE-CO,IE-KY,IE-LK,IE-TA,IE-WD,IE-G,IE-LM,IE-MO,IE-RN,IE-SO,IE-CN,IE-DL,IE-MN | C34: TAVIINTS | D34: Transport Demand: Aviation international_Short | E34: Bpkm
B35: =_xlfn.TEXTJOIN(",",TRUE,Regions!$C$3:'Regions'!$AD$3) -> IE,IE-CW,IE-D,IE-KE,IE-KK,IE-LS,IE-LD,IE-LH,IE-MH,IE-OY,IE-WH,IE-WX,IE-WW,IE-CE,IE-CO,IE-KY,IE-LK,IE-TA,IE-WD,IE-G,IE-LM,IE-MO,IE-RN,IE-SO,IE-CN,IE-DL,IE-MN | C35: TAVIINTM | D35: Transport Demand: Aviation international_Medium | E35: Bpkm
B36: =_xlfn.TEXTJOIN(",",TRUE,Regions!$C$3:'Regions'!$AD$3) -> IE,IE-CW,IE-D,IE-KE,IE-KK,IE-LS,IE-LD,IE-LH,IE-MH,IE-OY,IE-WH,IE-WX,IE-WW,IE-CE,IE-CO,IE-KY,IE-LK,IE-TA,IE-WD,IE-G,IE-LM,IE-MO,IE-RN,IE-SO,IE-CN,IE-DL,IE-MN | C36: TAVIINTL | D36: Transport Demand: Aviation international_Long | E36: Bpkm
A37: ENV | B37: =_xlfn.TEXTJOIN(",",TRUE,Regions!$C$3:'Regions'!$AD$3) -> IE,IE-CW,IE-D,IE-KE,IE-KK,IE-LS,IE-LD,IE-LH,IE-MH,IE-OY,IE-WH,IE-WX,IE-WW,IE-CE,IE-CO,IE-KY,IE-LK,IE-TA,IE-WD,IE-G,IE-LM,IE-MO,IE-RN,IE-SO,IE-CN,IE-DL,IE-MN | C37: TRACO2N | D37: Carbon Dioxide - Combustion (TRA) | E37: kt
B38: =_xlfn.TEXTJOIN(",",TRUE,Regions!$C$3:'Regions'!$AD$3) -> IE,IE-CW,IE-D,IE-KE,IE-KK,IE-LS,IE-LD,IE-LH,IE-MH,IE-OY,IE-WH,IE-WX,IE-WW,IE-CE,IE-CO,IE-KY,IE-LK,IE-TA,IE-WD,IE-G,IE-LM,IE-MO,IE-RN,IE-SO,IE-CN,IE-DL,IE-MN | C38: TRACH4N | D38: Methane (TRA) | E38: kt
B39: =_xlfn.TEXTJOIN(",",TRUE,Regions!$C$3:'Regions'!$AD$3) -> IE,IE-CW,IE-D,IE-KE,IE-KK,IE-LS,IE-LD,IE-LH,IE-MH,IE-OY,IE-WH,IE-WX,IE-WW,IE-CE,IE-CO,IE-KY,IE-LK,IE-TA,IE-WD,IE-G,IE-LM,IE-MO,IE-RN,IE-SO,IE-CN,IE-DL,IE-MN | C39: TRASO2N | D39: Sulphur Oxides (TRA) | E39: kt
B40: =_xlfn.TEXTJOIN(",",TRUE,Regions!$C$3:'Regions'!$AD$3) -> IE,IE-CW,IE-D,IE-KE,IE-KK,IE-LS,IE-LD,IE-LH,IE-MH,IE-OY,IE-WH,IE-WX,IE-WW,IE-CE,IE-CO,IE-KY,IE-LK,IE-TA,IE-WD,IE-G,IE-LM,IE-MO,IE-RN,IE-SO,IE-CN,IE-DL,IE-MN | C40: TRANOXN | D40: Nitrogen Oxide (TRA) | E40: kt
B41: =_xlfn.TEXTJOIN(",",TRUE,Regions!$C$3:'Regions'!$AD$3) -> IE,IE-CW,IE-D,IE-KE,IE-KK,IE-LS,IE-LD,IE-LH,IE-MH,IE-OY,IE-WH,IE-WX,IE-WW,IE-CE,IE-CO,IE-KY,IE-LK,IE-TA,IE-WD,IE-G,IE-LM,IE-MO,IE-RN,IE-SO,IE-CN,IE-DL,IE-MN | C41: TRAPM10 | D41: Particulate Matter <10 µm (TRA) | E41: kt
B42: =_xlfn.TEXTJOIN(",",TRUE,Regions!$C$3:'Regions'!$AD$3) -> IE,IE-CW,IE-D,IE-KE,IE-KK,IE-LS,IE-LD,IE-LH,IE-MH,IE-OY,IE-WH,IE-WX,IE-WW,IE-CE,IE-CO,IE-KY,IE-LK,IE-TA,IE-WD,IE-G,IE-LM,IE-MO,IE-RN,IE-SO,IE-CN,IE-DL,IE-MN | C42: TRAPM25 | D42: Particulate Matter <2.5 µm (TRA) | E42: kt
A43: ENV | B43: =_xlfn.TEXTJOIN(",",TRUE,Regions!$C$3:'Regions'!$AD$3) -> IE,IE-CW,IE-D,IE-KE,IE-KK,IE-LS,IE-LD,IE-LH,IE-MH,IE-OY,IE-WH,IE-WX,IE-WW,IE-CE,IE-CO,IE-KY,IE-LK,IE-TA,IE-WD,IE-G,IE-LM,IE-MO,IE-RN,IE-SO,IE-CN,IE-DL,IE-MN | C43: TRACO2INT | D43: Carbon Dioxide - Combustion (TRA) International | E43: kt
A45: 1. Fuel tourism is defined as fuel that is bought within the State by private motorists and hauliers but consumed outside the State (SEAI).
A46: 2. Navigation, which accounts for fuel used by watercraft or sea going vessels operating in coastal or inland waters, excluding that used for international sea transport of passengers or freight or by fishing vessels
A47: International sea passenger and freight transport energy use is counted under international marine bunkers and is not considered under the national energy balance; energy use in fishing vessels is accounted for under agriculture and fisheries.
A48: 3. Unspecified, which accounts for the difference between the sum of the energy demand estimates for each individual mode listed above and data from the national energy balance on the overall fuel consumption of the transport sector.

Sheet Processes
B2: ~FI_Process
B3: Sets | C3: Region | D3: TechName | E3: TechDesc | F3: Tact | G3: Tcap | H3: Tslvl | I3: PrimaryCG | J3: Vintage
B4: *Passengers
B5: *Active modes
B6: DMD | C6: =_xlfn.TEXTJOIN(",",TRUE,Regions!$C$3:'Regions'!$AD$3) -> IE,IE-CW,IE-D,IE-KE,IE-KK,IE-LS,IE-LD,IE-LH,IE-MH,IE-OY,IE-WH,IE-WX,IE-WW,IE-CE,IE-CO,IE-KY,IE-LK,IE-TA,IE-WD,IE-G,IE-LM,IE-MO,IE-RN,IE-SO,IE-CN,IE-DL,IE-MN | D6: T-WLK_WLK | E6: TRA Walking | F6: Bpkm | G6: kUnits
B7: DMD | C7: =_xlfn.TEXTJOIN(",",TRUE,Regions!$C$3:'Regions'!$AD$3) -> IE,IE-CW,IE-D,IE-KE,IE-KK,IE-LS,IE-LD,IE-LH,IE-MH,IE-OY,IE-WH,IE-WX,IE-WW,IE-CE,IE-CO,IE-KY,IE-LK,IE-TA,IE-WD,IE-G,IE-LM,IE-MO,IE-RN,IE-SO,IE-CN,IE-DL,IE-MN | D7: T-CYC_CYC | E7: TRA Cycling | F7: Bpkm | G7: kUnits
B8: *Two-wheelers
B9: DMD | C9: =_xlfn.TEXTJOIN(",",TRUE,Regions!$C$3:'Regions'!$AD$3) -> IE,IE-CW,IE-D,IE-KE,IE-KK,IE-LS,IE-LD,IE-LH,IE-MH,IE-OY,IE-WH,IE-WX,IE-WW,IE-CE,IE-CO,IE-KY,IE-LK,IE-TA,IE-WD,IE-G,IE-LM,IE-MO,IE-RN,IE-SO,IE-CN,IE-DL,IE-MN | D9: T-MOT-ICE_GSL00 | E9: TRA Motorcycles: Gasoline ICEs - Existing | F9: Bpkm | G9: kUnits
B10: *Private cars
B11: DMD | C11: =_xlfn.TEXTJOIN(",",TRUE,Regions!$C$3:'Regions'!$AD$3) -> IE,IE-CW,IE-D,IE-KE,IE-KK,IE-LS,IE-LD,IE-LH,IE-MH,IE-OY,IE-WH,IE-WX,IE-WW,IE-CE,IE-CO,IE-KY,IE-LK,IE-TA,IE-WD,IE-G,IE-LM,IE-MO,IE-RN,IE-SO,IE-CN,IE-DL,IE-MN | D11: T-CAR-ICE_GSL00 | E11: TRA Cars: Gasoline ICEs - Existing | F11: Bpkm | G11: kUnits
B12: DMD | C12: =_xlfn.TEXTJOIN(",",TRUE,Regions!$C$3:'Regions'!$AD$3) -> IE,IE-CW,IE-D,IE-KE,IE-KK,IE-LS,IE-LD,IE-LH,IE-MH,IE-OY,IE-WH,IE-WX,IE-WW,IE-CE,IE-CO,IE-KY,IE-LK,IE-TA,IE-WD,IE-G,IE-LM,IE-MO,IE-RN,IE-SO,IE-CN,IE-DL,IE-MN | D12: T-CAR-ICE_DST00 | E12: TRA Cars: Diesel ICEs - Existing | F12: Bpkm | G12: kUnits
B13: DMD | C13: =_xlfn.TEXTJOIN(",",TRUE,Regions!$C$3:'Regions'!$AD$3) -> IE,IE-CW,IE-D,IE-KE,IE-KK,IE-LS,IE-LD,IE-LH,IE-MH,IE-OY,IE-WH,IE-WX,IE-WW,IE-CE,IE-CO,IE-KY,IE-LK,IE-TA,IE-WD,IE-G,IE-LM,IE-MO,IE-RN,IE-SO,IE-CN,IE-DL,IE-MN | D13: T-CAR-ICE_DF00 | E13: TRA Cars: Dual fuel ICEs - Existing | F13: Bpkm | G13: kUnits
B14: DMD | C14: =_xlfn.TEXTJOIN(",",TRUE,Regions!$C$3:'Regions'!$AD$3) -> IE,IE-CW,IE-D,IE-KE,IE-KK,IE-LS,IE-LD,IE-LH,IE-MH,IE-OY,IE-WH,IE-WX,IE-WW,IE-CE,IE-CO,IE-KY,IE-LK,IE-TA,IE-WD,IE-G,IE-LM,IE-MO,IE-RN,IE-SO,IE-CN,IE-DL,IE-MN | D14: T-CAR-ICE_E8500 | E14: TRA Cars: Flex fuel ICEs - Existing | F14: Bpkm | G14: kUnits
B15: DMD | C15: =_xlfn.TEXTJOIN(",",TRUE,Regions!$C$3:'Regions'!$AD$3) -> IE,IE-CW,IE-D,IE-KE,IE-KK,IE-LS,IE-LD,IE-LH,IE-MH,IE-OY,IE-WH,IE-WX,IE-WW,IE-CE,IE-CO,IE-KY,IE-LK,IE-TA,IE-WD,IE-G,IE-LM,IE-MO,IE-RN,IE-SO,IE-CN,IE-DL,IE-MN | D15: T-CAR-HEV_GSL00 | E15: TRA Cars: Gasoline HEV - Existing | F15: Bpkm | G15: kUnits
B16: DMD | C16: =_xlfn.TEXTJOIN(",",TRUE,Regions!$C$3:'Regions'!$AD$3) -> IE,IE-CW,IE-D,IE-KE,IE-KK,IE-LS,IE-LD,IE-LH,IE-MH,IE-OY,IE-WH,IE-WX,IE-WW,IE-CE,IE-CO,IE-KY,IE-LK,IE-TA,IE-WD,IE-G,IE-LM,IE-MO,IE-RN,IE-SO,IE-CN,IE-DL,IE-MN | D16: T-CAR-HEV_DST00 | E16: TRA Cars: Diesel HEV - Existing | F16: Bpkm | G16: kUnits
B17: DMD | C17: =_xlfn.TEXTJOIN(",",TRUE,Regions!$C$3:'Regions'!$AD$3) -> IE,IE-CW,IE-D,IE-KE,IE-KK,IE-LS,IE-LD,IE-LH,IE-MH,IE-OY,IE-WH,IE-WX,IE-WW,IE-CE,IE-CO,IE-KY,IE-LK,IE-TA,IE-WD,IE-G,IE-LM,IE-MO,IE-RN,IE-SO,IE-CN,IE-DL,IE-MN | D17: T-CAR-PHEV_GSL00 | E17: TRA Cars: Gasoline PHEV - Existing | F17: Bpkm | G17: kUnits
B18: DMD | C18: =_xlfn.TEXTJOIN(",",TRUE,Regions!$C$3:'Regions'!$AD$3) -> IE,IE-CW,IE-D,IE-KE,IE-KK,IE-LS,IE-LD,IE-LH,IE-MH,IE-OY,IE-WH,IE-WX,IE-WW,IE-CE,IE-CO,IE-KY,IE-LK,IE-TA,IE-WD,IE-G,IE-LM,IE-MO,IE-RN,IE-SO,IE-CN,IE-DL,IE-MN | D18: T-CAR-PHEV_DST00 | E18: TRA Cars: Diesel PHEV - Existing | F18: Bpkm | G18: kUnits
B19: DMD | C19: =_xlfn.TEXTJOIN(",",TRUE,Regions!$C$3:'Regions'!$AD$3) -> IE,IE-CW,IE-D,IE-KE,IE-KK,IE-LS,IE-LD,IE-LH,IE-MH,IE-OY,IE-WH,IE-WX,IE-WW,IE-CE,IE-CO,IE-KY,IE-LK,IE-TA,IE-WD,IE-G,IE-LM,IE-MO,IE-RN,IE-SO,IE-CN,IE-DL,IE-MN | D19: T-CAR-BEV_ELC00 | E19: TRA Cars: Battery Electric Vehicle - Existing | F19: Bpkm | G19: kUnits
B20: *Small sevice vehicle
B21: DMD | C21: =_xlfn.TEXTJOIN(",",TRUE,Regions!$C$3:'Regions'!$AD$3) -> IE,IE-CW,IE-D,IE-KE,IE-KK,IE-LS,IE-LD,IE-LH,IE-MH,IE-OY,IE-WH,IE-WX,IE-WW,IE-CE,IE-CO,IE-KY,IE-LK,IE-TA,IE-WD,IE-G,IE-LM,IE-MO,IE-RN,IE-SO,IE-CN,IE-DL,IE-MN | D21: T-TAX-ICE_GSL00 | E21: TRA Taxis: Gasoline ICEs - Existing | F21: Bpkm | G21: kUnits
B22: DMD | C22: =_xlfn.TEXTJOIN(",",TRUE,Regions!$C$3:'Regions'!$AD$3) -> IE,IE-CW,IE-D,IE-KE,IE-KK,IE-LS,IE-LD,IE-LH,IE-MH,IE-OY,IE-WH,IE-WX,IE-WW,IE-CE,IE-CO,IE-KY,IE-LK,IE-TA,IE-WD,IE-G,IE-LM,IE-MO,IE-RN,IE-SO,IE-CN,IE-DL,IE-MN | D22: T-TAX-ICE_DST00 | E22: TRA Taxis: Diesel ICEs - Existing | F22: Bpkm | G22: kUnits
B23: DMD | C23: =_xlfn.TEXTJOIN(",",TRUE,Regions!$C$3:'Regions'!$AD$3) -> IE,IE-CW,IE-D,IE-KE,IE-KK,IE-LS,IE-LD,IE-LH,IE-MH,IE-OY,IE-WH,IE-WX,IE-WW,IE-CE,IE-CO,IE-KY,IE-LK,IE-TA,IE-WD,IE-G,IE-LM,IE-MO,IE-RN,IE-SO,IE-CN,IE-DL,IE-MN | D23: T-TAX-HEV_GSL00 | E23: TRA Taxis: Gasoline HEVs - Existing | F23: Bpkm | G23: kUnits
B24: *Large sevice vehicle
B25: DMD | C25: =_xlfn.TEXTJOIN(",",TRUE,Regions!$C$3:'Regions'!$AD$3) -> IE,IE-CW,IE-D,IE-KE,IE-KK,IE-LS,IE-LD,IE-LH,IE-MH,IE-OY,IE-WH,IE-WX,IE-WW,IE-CE,IE-CO,IE-KY,IE-LK,IE-TA,IE-WD,IE-G,IE-LM,IE-MO,IE-RN,IE-SO,IE-CN,IE-DL,IE-MN | D25: T-BUS-ICE_DST00 | E25: TRA BUS: Diesel ICEs - Existing | F25: Bpkm | G25: kUnits
B26: *Rail
B27: DMD | C27: =_xlfn.TEXTJOIN(",",TRUE,Regions!$C$3:'Regions'!$AD$3) -> IE,IE-CW,IE-D,IE-KE,IE-KK,IE-LS,IE-LD,IE-LH,IE-MH,IE-OY,IE-WH,IE-WX,IE-WW,IE-CE,IE-CO,IE-KY,IE-LK,IE-TA,IE-WD,IE-G,IE-LM,IE-MO,IE-RN,IE-SO,IE-CN,IE-DL,IE-MN | D27: T-LPT-BEV_ELC00 | E27: TRA Light Passenger Train: Electric - Existing | F27: Bpkm | G27: kUnits
B28: DMD | C28: =_xlfn.TEXTJOIN(",",TRUE,Regions!$C$3:'Regions'!$AD$3) -> IE,IE-CW,IE-D,IE-KE,IE-KK,IE-LS,IE-LD,IE-LH,IE-MH,IE-OY,IE-WH,IE-WX,IE-WW,IE-CE,IE-CO,IE-KY,IE-LK,IE-TA,IE-WD,IE-G,IE-LM,IE-MO,IE-RN,IE-SO,IE-CN,IE-DL,IE-MN | D28: T-HPT-BEV_ELC00 | E28: TRA Heavy Passenger Train: Electric - Existing | F28: Bpkm | G28: kUnits
B29: DMD | C29: =_xlfn.TEXTJOIN(",",TRUE,Regions!$C$3:'Regions'!$AD$3) -> IE,IE-CW,IE-D,IE-KE,IE-KK,IE-LS,IE-LD,IE-LH,IE-MH,IE-OY,IE-WH,IE-WX,IE-WW,IE-CE,IE-CO,IE-KY,IE-LK,IE-TA,IE-WD,IE-G,IE-LM,IE-MO,IE-RN,IE-SO,IE-CN,IE-DL,IE-MN | D29: T-HPT-ICE_DST00 | E29: TRA Heavy Passenger Train: Diesel - Existing | F29: Bpkm | G29: kUnits
B30: *Freight
B31: *Trucks and Rail
B32: DMD | C32: =_xlfn.TEXTJOIN(",",TRUE,Regions!$C$3:'Regions'!$AD$3) -> IE,IE-CW,IE-D,IE-KE,IE-KK,IE-LS,IE-LD,IE-LH,IE-MH,IE-OY,IE-WH,IE-WX,IE-WW,IE-CE,IE-CO,IE-KY,IE-LK,IE-TA,IE-WD,IE-G,IE-LM,IE-MO,IE-RN,IE-SO,IE-CN,IE-DL,IE-MN | D32: T-LGT-ICE_GSL00 | E32: TRA Light Goods Truck: Gasoline ICEs - Existing | F32: Btkm | G32: kUnits
B33: DMD | C33: =_xlfn.TEXTJOIN(",",TRUE,Regions!$C$3:'Regions'!$AD$3) -> IE,IE-CW,IE-D,IE-KE,IE-KK,IE-LS,IE-LD,IE-LH,IE-MH,IE-OY,IE-WH,IE-WX,IE-WW,IE-CE,IE-CO,IE-KY,IE-LK,IE-TA,IE-WD,IE-G,IE-LM,IE-MO,IE-RN,IE-SO,IE-CN,IE-DL,IE-MN | D33: T-LGT-ICE_DST00 | E33: TRA Light Goods Truck: Diesel ICEs - Existing | F33: Btkm | G33: kUnits
B34: DMD | C34: =_xlfn.TEXTJOIN(",",TRUE,Regions!$C$3:'Regions'!$AD$3) -> IE,IE-CW,IE-D,IE-KE,IE-KK,IE-LS,IE-LD,IE-LH,IE-MH,IE-OY,IE-WH,IE-WX,IE-WW,IE-CE,IE-CO,IE-KY,IE-LK,IE-TA,IE-WD,IE-G,IE-LM,IE-MO,IE-RN,IE-SO,IE-CN,IE-DL,IE-MN | D34: T-MGT-ICE_DST00 | E34: TRA Medium Goods Truck: Diesel ICEs - Existing | F34: Btkm | G34: kUnits
B35: DMD | C35: =_xlfn.TEXTJOIN(",",TRUE,Regions!$C$3:'Regions'!$AD$3) -> IE,IE-CW,IE-D,IE-KE,IE-KK,IE-LS,IE-LD,IE-LH,IE-MH,IE-OY,IE-WH,IE-WX,IE-WW,IE-CE,IE-CO,IE-KY,IE-LK,IE-TA,IE-WD,IE-G,IE-LM,IE-MO,IE-RN,IE-SO,IE-CN,IE-DL,IE-MN | D35: T-HGT-ICE_DST00 | E35: TRA Heavy Goods Truck: Diesel ICEs - Existing | F35: Btkm | G35: kUnits
B36: DMD | C36: =_xlfn.TEXTJOIN(",",TRUE,Regions!$C$3:'Regions'!$AD$3) -> IE,IE-CW,IE-D,IE-KE,IE-KK,IE-LS,IE-LD,IE-LH,IE-MH,IE-OY,IE-WH,IE-WX,IE-WW,IE-CE,IE-CO,IE-KY,IE-LK,IE-TA,IE-WD,IE-G,IE-LM,IE-MO,IE-RN,IE-SO,IE-CN,IE-DL,IE-MN | D36: T-GTR-ICE_DST00 | E36: TRA Goods Train: ICE Diesel Train - Existing | F36: Btkm | G36: kUnits
B37: *Turism, Navigation & Others
B38: DMD | C38: =_xlfn.TEXTJOIN(",",TRUE,Regions!$C$3:'Regions'!$AD$3) -> IE,IE-CW,IE-D,IE-KE,IE-KK,IE-LS,IE-LD,IE-LH,IE-MH,IE-OY,IE-WH,IE-WX,IE-WW,IE-CE,IE-CO,IE-KY,IE-LK,IE-TA,IE-WD,IE-G,IE-LM,IE-MO,IE-RN,IE-SO,IE-CN,IE-DL,IE-MN | D38: T-TUR_CON00 | E38: TRA Tourism: Conventional Tourism Vehicles - Existing | F38: PJ | G38: PJa
B39: DMD | C39: =_xlfn.TEXTJOIN(",",TRUE,Regions!$C$3:'Regions'!$AD$3) -> IE,IE-CW,IE-D,IE-KE,IE-KK,IE-LS,IE-LD,IE-LH,IE-MH,IE-OY,IE-WH,IE-WX,IE-WW,IE-CE,IE-CO,IE-KY,IE-LK,IE-TA,IE-WD,IE-G,IE-LM,IE-MO,IE-RN,IE-SO,IE-CN,IE-DL,IE-MN | D39: T-NAV_CON00 | E39: TRA Navigation: Conventional Navigation Vehicles - Existing | F39: PJ | G39: PJa
B40: DMD | C40: =_xlfn.TEXTJOIN(",",TRUE,Regions!$C$3:'Regions'!$AD$3) -> IE,IE-CW,IE-D,IE-KE,IE-KK,IE-LS,IE-LD,IE-LH,IE-MH,IE-OY,IE-WH,IE-WX,IE-WW,IE-CE,IE-CO,IE-KY,IE-LK,IE-TA,IE-WD,IE-G,IE-LM,IE-MO,IE-RN,IE-SO,IE-CN,IE-DL,IE-MN | D40: T-OTH_CON00 | E40: TRA Unspecified: Conventional Unspecified Vehicles - Existing | F40: PJ | G40: PJa
B41: *Aviation
B42: DMD | C42: =_xlfn.TEXTJOIN(",",TRUE,Regions!$C$3:'Regions'!$AD$3) -> IE,IE-CW,IE-D,IE-KE,IE-KK,IE-LS,IE-LD,IE-LH,IE-MH,IE-OY,IE-WH,IE-WX,IE-WW,IE-CE,IE-CO,IE-KY,IE-LK,IE-TA,IE-WD,IE-G,IE-LM,IE-MO,IE-RN,IE-SO,IE-CN,IE-DL,IE-MN | D42: T-AVI_DOM00 | E42: TRA Domestic Aviation: Aviation for Domestic Flights | F42: PJ | G42: PJa
B43: DMD | C43: =_xlfn.TEXTJOIN(",",TRUE,Regions!$C$3:'Regions'!$AD$3) -> IE,IE-CW,IE-D,IE-KE,IE-KK,IE-LS,IE-LD,IE-LH,IE-MH,IE-OY,IE-WH,IE-WX,IE-WW,IE-CE,IE-CO,IE-KY,IE-LK,IE-TA,IE-WD,IE-G,IE-LM,IE-MO,IE-RN,IE-SO,IE-CN,IE-DL,IE-MN | D43: T-AVI_INT00 | E43: TRA International Aviation: Aviation for International Flights | F43: PJ | G43: PJa
B44: *Fuel Technology
B45: PRE | C45: =_xlfn.TEXTJOIN(",",TRUE,Regions!$C$3:'Regions'!$AD$3) -> IE,IE-CW,IE-D,IE-KE,IE-KK,IE-LS,IE-LD,IE-LH,IE-MH,IE-OY,IE-WH,IE-WX,IE-WW,IE-CE,IE-CO,IE-KY,IE-LK,IE-TA,IE-WD,IE-G,IE-LM,IE-MO,IE-RN,IE-SO,IE-CN,IE-DL,IE-MN | D45: =_xlfn.TEXTJOIN("-",TRUE,"FT",Commodities!C6) -> FT-TRAWLK | E45: ="TRA "&Commodities!D6 -> TRA Walking (TRA) | F45: PJ | G45: PJa
B46: PRE | C46: =_xlfn.TEXTJOIN(",",TRUE,Regions!$C$3:'Regions'!$AD$3) -> IE,IE-CW,IE-D,IE-KE,IE-KK,IE-LS,IE-LD,IE-LH,IE-MH,IE-OY,IE-WH,IE-WX,IE-WW,IE-CE,IE-CO,IE-KY,IE-LK,IE-TA,IE-WD,IE-G,IE-LM,IE-MO,IE-RN,IE-SO,IE-CN,IE-DL,IE-MN | D46: =_xlfn.TEXTJOIN("-",TRUE,"FT",Commodities!C7) -> FT-TRACYC | E46: ="TRA "&Commodities!D7 -> TRA Cycling (TRA) | F46: PJ | G46: PJa
B47: PRE | C47: =_xlfn.TEXTJOIN(",",TRUE,Regions!$C$3:'Regions'!$AD$3) -> IE,IE-CW,IE-D,IE-KE,IE-KK,IE-LS,IE-LD,IE-LH,IE-MH,IE-OY,IE-WH,IE-WX,IE-WW,IE-CE,IE-CO,IE-KY,IE-LK,IE-TA,IE-WD,IE-G,IE-LM,IE-MO,IE-RN,IE-SO,IE-CN,IE-DL,IE-MN | D47: =_xlfn.TEXTJOIN("-",TRUE,"FT",Commodities!C8) -> FT-TRAGSL | E47: ="TRA "&Commodities!D8 -> TRA Gasoline (TRA) | F47: PJ | G47: PJa
B48: PRE | C48: =_xlfn.TEXTJOIN(",",TRUE,Regions!$C$3:'Regions'!$AD$3) -> IE,IE-CW,IE-D,IE-KE,IE-KK,IE-LS,IE-LD,IE-LH,IE-MH,IE-OY,IE-WH,IE-WX,IE-WW,IE-CE,IE-CO,IE-KY,IE-LK,IE-TA,IE-WD,IE-G,IE-LM,IE-MO,IE-RN,IE-SO,IE-CN,IE-DL,IE-MN | D48: =_xlfn.TEXTJOIN("-",TRUE,"FT",Commodities!C9) -> FT-TRADST | E48: ="TRA "&Commodities!D9 -> TRA Diesel (TRA) | F48: PJ | G48: PJa
B49: PRE | C49: =_xlfn.TEXTJOIN(",",TRUE,Regions!$C$3:'Regions'!$AD$3) -> IE,IE-CW,IE-D,IE-KE,IE-KK,IE-LS,IE-LD,IE-LH,IE-MH,IE-OY,IE-WH,IE-WX,IE-WW,IE-CE,IE-CO,IE-KY,IE-LK,IE-TA,IE-WD,IE-G,IE-LM,IE-MO,IE-RN,IE-SO,IE-CN,IE-DL,IE-MN | D49: =_xlfn.TEXTJOIN("-",TRUE,"FT",Commodities!C10) -> FT-TRAETH | E49: ="TRA "&Commodities!D10 -> TRA BioEthanol (TRA) | F49: PJ | G49: PJa
B50: PRE | C50: =_xlfn.TEXTJOIN(",",TRUE,Regions!$C$3:'Regions'!$AD$3) -> IE,IE-CW,IE-D,IE-KE,IE-KK,IE-LS,IE-LD,IE-LH,IE-MH,IE-OY,IE-WH,IE-WX,IE-WW,IE-CE,IE-CO,IE-KY,IE-LK,IE-TA,IE-WD,IE-G,IE-LM,IE-MO,IE-RN,IE-SO,IE-CN,IE-DL,IE-MN | D50: =_xlfn.TEXTJOIN("-",TRUE,"FT",Commodities!C11) -> FT-TRABDL | E50: ="TRA "&Commodities!D11 -> TRA BioDiesel (TRA) | F50: PJ | G50: PJa
B51: PRE | C51: =_xlfn.TEXTJOIN(",",TRUE,Regions!$C$3:'Regions'!$AD$3) -> IE,IE-CW,IE-D,IE-KE,IE-KK,IE-LS,IE-LD,IE-LH,IE-MH,IE-OY,IE-WH,IE-WX,IE-WW,IE-CE,IE-CO,IE-KY,IE-LK,IE-TA,IE-WD,IE-G,IE-LM,IE-MO,IE-RN,IE-SO,IE-CN,IE-DL,IE-MN | D51: =_xlfn.TEXTJOIN("-",TRUE,"FT",Commodities!C12) -> FT-TRABJK | E51: ="TRA "&Commodities!D12 -> TRA Bio Jet Kerosene (TRA) | F51: PJ | G51: PJa
B52: PRE | C52: =_xlfn.TEXTJOIN(",",TRUE,Regions!$C$3:'Regions'!$AD$3) -> IE,IE-CW,IE-D,IE-KE,IE-KK,IE-LS,IE-LD,IE-LH,IE-MH,IE-OY,IE-WH,IE-WX,IE-WW,IE-CE,IE-CO,IE-KY,IE-LK,IE-TA,IE-WD,IE-G,IE-LM,IE-MO,IE-RN,IE-SO,IE-CN,IE-DL,IE-MN | D52: =_xlfn.TEXTJOIN("-",TRUE,"FT",Commodities!C13) -> FT-TRACNG | E52: ="TRA "&Commodities!D13 -> TRA CNG (TRA) | F52: PJ | G52: PJa
B53: PRE | C53: =_xlfn.TEXTJOIN(",",TRUE,Regions!$C$3:'Regions'!$AD$3) -> IE,IE-CW,IE-D,IE-KE,IE-KK,IE-LS,IE-LD,IE-LH,IE-MH,IE-OY,IE-WH,IE-WX,IE-WW,IE-CE,IE-CO,IE-KY,IE-LK,IE-TA,IE-WD,IE-G,IE-LM,IE-MO,IE-RN,IE-SO,IE-CN,IE-DL,IE-MN | D53: =_xlfn.TEXTJOIN("-",TRUE,"FT",Commodities!C14) -> FT-TRABNG | E53: ="TRA "&Commodities!D14 -> TRA BioCNG (TRA) | F53: PJ | G53: PJa
B54: PRE | C54: =_xlfn.TEXTJOIN(",",TRUE,Regions!$C$3:'Regions'!$AD$3) -> IE,IE-CW,IE-D,IE-KE,IE-KK,IE-LS,IE-LD,IE-LH,IE-MH,IE-OY,IE-WH,IE-WX,IE-WW,IE-CE,IE-CO,IE-KY,IE-LK,IE-TA,IE-WD,IE-G,IE-LM,IE-MO,IE-RN,IE-SO,IE-CN,IE-DL,IE-MN | D54: =_xlfn.TEXTJOIN("-",TRUE,"FT",Commodities!C15) -> FT-TRAELC | E54: ="TRA "&Commodities!D15 -> TRA Electricity (TRA) | F54: PJ | G54: PJa | H54: DAYNITE
B55: PRE | C55: =_xlfn.TEXTJOIN(",",TRUE,Regions!$C$3:'Regions'!$AD$3) -> IE,IE-CW,IE-D,IE-KE,IE-KK,IE-LS,IE-LD,IE-LH,IE-MH,IE-OY,IE-WH,IE-WX,IE-WW,IE-CE,IE-CO,IE-KY,IE-LK,IE-TA,IE-WD,IE-G,IE-LM,IE-MO,IE-RN,IE-SO,IE-CN,IE-DL,IE-MN | D55: =_xlfn.TEXTJOIN("-",TRUE,"FT",Commodities!C16) -> FT-TRALNG | E55: ="TRA "&Commodities!D16 -> TRA LNG (TRA) | F55: PJ | G55: PJa
B56: PRE | C56: =_xlfn.TEXTJOIN(",",TRUE,Regions!$C$3:'Regions'!$AD$3) -> IE,IE-CW,IE-D,IE-KE,IE-KK,IE-LS,IE-LD,IE-LH,IE-MH,IE-OY,IE-WH,IE-WX,IE-WW,IE-CE,IE-CO,IE-KY,IE-LK,IE-TA,IE-WD,IE-G,IE-LM,IE-MO,IE-RN,IE-SO,IE-CN,IE-DL,IE-MN | D56: =_xlfn.TEXTJOIN("-",TRUE,"FT",Commodities!C17) -> FT-TRAH2 | E56: ="TRA "&Commodities!D17 -> TRA Hydrogen (TRA) | F56: PJ | G56: PJa
B57: PRE | C57: =_xlfn.TEXTJOIN(",",TRUE,Regions!$C$3:'Regions'!$AD$3) -> IE,IE-CW,IE-D,IE-KE,IE-KK,IE-LS,IE-LD,IE-LH,IE-MH,IE-OY,IE-WH,IE-WX,IE-WW,IE-CE,IE-CO,IE-KY,IE-LK,IE-TA,IE-WD,IE-G,IE-LM,IE-MO,IE-RN,IE-SO,IE-CN,IE-DL,IE-MN | D57: =_xlfn.TEXTJOIN("-",TRUE,"FT",Commodities!C18) -> FT-TRAKER | E57: ="TRA "&Commodities!D18 -> TRA Kerosene (TRA) | F57: PJ | G57: PJa
B58: PRE | C58: =_xlfn.TEXTJOIN(",",TRUE,Regions!$C$3:'Regions'!$AD$3) -> IE,IE-CW,IE-D,IE-KE,IE-KK,IE-LS,IE-LD,IE-LH,IE-MH,IE-OY,IE-WH,IE-WX,IE-WW,IE-CE,IE-CO,IE-KY,IE-LK,IE-TA,IE-WD,IE-G,IE-LM,IE-MO,IE-RN,IE-SO,IE-CN,IE-DL,IE-MN | D58: FT-TRAPtLKER | E58: TRA PtL Synthetic Kerosene (TRA) | F58: PJ | G58: PJa
B59: PRE | C59: =_xlfn.TEXTJOIN(",",TRUE,Regions!$C$3:'Regions'!$AD$3) -> IE,IE-CW,IE-D,IE-KE,IE-KK,IE-LS,IE-LD,IE-LH,IE-MH,IE-OY,IE-WH,IE-WX,IE-WW,IE-CE,IE-CO,IE-KY,IE-LK,IE-TA,IE-WD,IE-G,IE-LM,IE-MO,IE-RN,IE-SO,IE-CN,IE-DL,IE-MN | D59: FT-AVIKER | E59: Kerosene for aviation | F59: PJ | G59: PJa
B60: PRE | C60: =_xlfn.TEXTJOIN(",",TRUE,Regions!$C$3:'Regions'!$AD$3) -> IE,IE-CW,IE-D,IE-KE,IE-KK,IE-LS,IE-LD,IE-LH,IE-MH,IE-OY,IE-WH,IE-WX,IE-WW,IE-CE,IE-CO,IE-KY,IE-LK,IE-TA,IE-WD,IE-G,IE-LM,IE-MO,IE-RN,IE-SO,IE-CN,IE-DL,IE-MN | D60: FT-AVIBJK | E60: SAF for aviation | F60: PJ | G60: PJa
B61: PRE | C61: =_xlfn.TEXTJOIN(",",TRUE,Regions!$C$3:'Regions'!$AD$3) -> IE,IE-CW,IE-D,IE-KE,IE-KK,IE-LS,IE-LD,IE-LH,IE-MH,IE-OY,IE-WH,IE-WX,IE-WW,IE-CE,IE-CO,IE-KY,IE-LK,IE-TA,IE-WD,IE-G,IE-LM,IE-MO,IE-RN,IE-SO,IE-CN,IE-DL,IE-MN | D61: FT-AVIELC | E61: Electricity for aviation | F61: PJ | G61: PJa
B62: PRE | C62: =_xlfn.TEXTJOIN(",",TRUE,Regions!$C$3:'Regions'!$AD$3) -> IE,IE-CW,IE-D,IE-KE,IE-KK,IE-LS,IE-LD,IE-LH,IE-MH,IE-OY,IE-WH,IE-WX,IE-WW,IE-CE,IE-CO,IE-KY,IE-LK,IE-TA,IE-WD,IE-G,IE-LM,IE-MO,IE-RN,IE-SO,IE-CN,IE-DL,IE-MN | D62: FT-AVIH2 | E62: Hydrogen for aviation | F62: PJ | G62: PJa
B63: PRE | C63: =_xlfn.TEXTJOIN(",",TRUE,Regions!$C$3:'Regions'!$AD$3) -> IE,IE-CW,IE-D,IE-KE,IE-KK,IE-LS,IE-LD,IE-LH,IE-MH,IE-OY,IE-WH,IE-WX,IE-WW,IE-CE,IE-CO,IE-KY,IE-LK,IE-TA,IE-WD,IE-G,IE-LM,IE-MO,IE-RN,IE-SO,IE-CN,IE-DL,IE-MN | D63: FT-AVIPtL | E63: Synthetic fuel for aviation | F63: PJ | G63: PJa
B64: *Fuel Blending
B65: PRE | C65: =_xlfn.TEXTJOIN(",",TRUE,Regions!$C$3:'Regions'!$AD$3) -> IE,IE-CW,IE-D,IE-KE,IE-KK,IE-LS,IE-LD,IE-LH,IE-MH,IE-OY,IE-WH,IE-WX,IE-WW,IE-CE,IE-CO,IE-KY,IE-LK,IE-TA,IE-WD,IE-G,IE-LM,IE-MO,IE-RN,IE-SO,IE-CN,IE-DL,IE-MN | D65: TRAGSL_BLD | E65: Fuel Blending - Gasoline with Ethanol | F65: PJ | G65: PJa
B66: PRE | C66: =_xlfn.TEXTJOIN(",",TRUE,Regions!$C$3:'Regions'!$AD$3) -> IE,IE-CW,IE-D,IE-KE,IE-KK,IE-LS,IE-LD,IE-LH,IE-MH,IE-OY,IE-WH,IE-WX,IE-WW,IE-CE,IE-CO,IE-KY,IE-LK,IE-TA,IE-WD,IE-G,IE-LM,IE-MO,IE-RN,IE-SO,IE-CN,IE-DL,IE-MN | D66: TRADST_BLD | E66: Fuel Blending - Diesel with Biodiesel | F66: PJ | G66: PJa
B67: PRE | C67: =_xlfn.TEXTJOIN(",",TRUE,Regions!$C$3:'Regions'!$AD$3) -> IE,IE-CW,IE-D,IE-KE,IE-KK,IE-LS,IE-LD,IE-LH,IE-MH,IE-OY,IE-WH,IE-WX,IE-WW,IE-CE,IE-CO,IE-KY,IE-LK,IE-TA,IE-WD,IE-G,IE-LM,IE-MO,IE-RN,IE-SO,IE-CN,IE-DL,IE-MN | D67: TRAE85_BLD | E67: Fuel Blending - E85 | F67: PJ | G67: PJa
B68: PRE | C68: =_xlfn.TEXTJOIN(",",TRUE,Regions!$C$3:'Regions'!$AD$3) -> IE,IE-CW,IE-D,IE-KE,IE-KK,IE-LS,IE-LD,IE-LH,IE-MH,IE-OY,IE-WH,IE-WX,IE-WW,IE-CE,IE-CO,IE-KY,IE-LK,IE-TA,IE-WD,IE-G,IE-LM,IE-MO,IE-RN,IE-SO,IE-CN,IE-DL,IE-MN | D68: TRABCNG_BLD | E68: Fuel Blending - CNG + BioCNG | F68: PJ | G68: PJa
B69: PRE | C69: =_xlfn.TEXTJOIN(",",TRUE,Regions!$C$3:'Regions'!$AD$3) -> IE,IE-CW,IE-D,IE-KE,IE-KK,IE-LS,IE-LD,IE-LH,IE-MH,IE-OY,IE-WH,IE-WX,IE-WW,IE-CE,IE-CO,IE-KY,IE-LK,IE-TA,IE-WD,IE-G,IE-LM,IE-MO,IE-RN,IE-SO,IE-CN,IE-DL,IE-MN | D69: TRABJK_BLD | E69: Fuel Blending - Fossil jet kerosene + Bio Jet Kerosene | F69: PJ | G69: PJa

Sheet FT
E2: ~FI_T
B3: Region | C3: TechName | D3: Comm-IN | E3: Comm-OUT | F3: EFF | G3: LIFE | H3: DELIV~2018 | I3: DELIV~2025 | J3: DELIV~2050 | K3: DELIV~0 | L3: ACT_BND~2030 | M3: ACT_BND~2045 | N3: ACT_BND~2050 | O3: ACT_BND~2070 | P3: ACT_BND~0
B4: Region | C4: *Technology Name | D4: Input Commodity | E4: Output Commodity | F4: Efficiency | G4: Lifetime
B5: *Units | G5: Years | H5: MEuro2018/PJ | I5: MEuro2018/PJ | J5: MEuro2018/PJ | K5: MEuro2018/PJ | L5: Maximum | M5: Maximum | N5: Maximum | O5: Maximum
B6: =Processes!C45 -> IE,IE-CW,IE-D,IE-KE,IE-KK,IE-LS,IE-LD,IE-LH,IE-MH,IE-OY,IE-WH,IE-WX,IE-WW,IE-CE,IE-CO,IE-KY,IE-LK,IE-TA,IE-WD,IE-G,IE-LM,IE-MO,IE-RN,IE-SO,IE-CN,IE-DL,IE-MN | C6: =Processes!D45 -> FT-TRAWLK | D6: WLK | E6: =Commodities!C6 -> TRAWLK | F6: 1 | G6: 50 | H6: 0.01 | I6: 0.01 | J6: 0.01 | K6: 5
B7: =Processes!C46 -> IE,IE-CW,IE-D,IE-KE,IE-KK,IE-LS,IE-LD,IE-LH,IE-MH,IE-OY,IE-WH,IE-WX,IE-WW,IE-CE,IE-CO,IE-KY,IE-LK,IE-TA,IE-WD,IE-G,IE-LM,IE-MO,IE-RN,IE-SO,IE-CN,IE-DL,IE-MN | C7: =Processes!D46 -> FT-TRACYC | D7: CYC | E7: =Commodities!C7 -> TRACYC | F7: 1 | G7: 50 | H7: 0.01 | I7: 0.01 | J7: 0.01 | K7: 5
B8: =Processes!C47 -> IE,IE-CW,IE-D,IE-KE,IE-KK,IE-LS,IE-LD,IE-LH,IE-MH,IE-OY,IE-WH,IE-WX,IE-WW,IE-CE,IE-CO,IE-KY,IE-LK,IE-TA,IE-WD,IE-G,IE-LM,IE-MO,IE-RN,IE-SO,IE-CN,IE-DL,IE-MN | C8: =Processes!D47 -> FT-TRAGSL | D8: OILGSL | E8: =Commodities!C8 -> TRAGSL | F8: 1 | G8: 50 | H8: 0.01 | I8: 0.01 | J8: 0.01 | K8: 5
B9: =Processes!C48 -> IE,IE-CW,IE-D,IE-KE,IE-KK,IE-LS,IE-LD,IE-LH,IE-MH,IE-OY,IE-WH,IE-WX,IE-WW,IE-CE,IE-CO,IE-KY,IE-LK,IE-TA,IE-WD,IE-G,IE-LM,IE-MO,IE-RN,IE-SO,IE-CN,IE-DL,IE-MN | C9: =Processes!D48 -> FT-TRADST | D9: OILDST | E9: =Commodities!C9 -> TRADST | F9: 1 | G9: 50 | H9: 0.01 | I9: 0.01 | J9: 0.01 | K9: 5
B10: =Processes!C49 -> IE,IE-CW,IE-D,IE-KE,IE-KK,IE-LS,IE-LD,IE-LH,IE-MH,IE-OY,IE-WH,IE-WX,IE-WW,IE-CE,IE-CO,IE-KY,IE-LK,IE-TA,IE-WD,IE-G,IE-LM,IE-MO,IE-RN,IE-SO,IE-CN,IE-DL,IE-MN | C10: =Processes!D49 -> FT-TRAETH | D10: BIOETH1G,BIOETH2G | E10: =Commodities!C10 -> TRAETH | F10: 1 | G10: 50 | H10: 0.01 | I10: 0.01 | J10: 0.01 | K10: 5
B11: =Processes!C50 -> IE,IE-CW,IE-D,IE-KE,IE-KK,IE-LS,IE-LD,IE-LH,IE-MH,IE-OY,IE-WH,IE-WX,IE-WW,IE-CE,IE-CO,IE-KY,IE-LK,IE-TA,IE-WD,IE-G,IE-LM,IE-MO,IE-RN,IE-SO,IE-CN,IE-DL,IE-MN | C11: =Processes!D50 -> FT-TRABDL | D11: BIODST1G,BIODST2G | E11: =Commodities!C11 -> TRABDL | F11: 1 | G11: 50 | H11: 0.01 | I11: 0.01 | J11: 0.01 | K11: 5
B12: =Processes!C51 -> IE,IE-CW,IE-D,IE-KE,IE-KK,IE-LS,IE-LD,IE-LH,IE-MH,IE-OY,IE-WH,IE-WX,IE-WW,IE-CE,IE-CO,IE-KY,IE-LK,IE-TA,IE-WD,IE-G,IE-LM,IE-MO,IE-RN,IE-SO,IE-CN,IE-DL,IE-MN | C12: =Processes!D51 -> FT-TRABJK | D12: BIOJKR | E12: =Commodities!C12 -> TRABJK | F12: 1 | G12: 50 | H12: 0.01 | I12: 0.01 | J12: 0.01 | K12: 5
B13: =Processes!C52 -> IE,IE-CW,IE-D,IE-KE,IE-KK,IE-LS,IE-LD,IE-LH,IE-MH,IE-OY,IE-WH,IE-WX,IE-WW,IE-CE,IE-CO,IE-KY,IE-LK,IE-TA,IE-WD,IE-G,IE-LM,IE-MO,IE-RN,IE-SO,IE-CN,IE-DL,IE-MN | C13: =Processes!D52 -> FT-TRACNG | D13: GASNAT | E13: =Commodities!C13 -> TRACNG | F13: 1 | G13: 50 | H13: 4 | I13: 80 | J13: =I13 -> 80 | K13: 5
B14: =Processes!C53 -> IE,IE-CW,IE-D,IE-KE,IE-KK,IE-LS,IE-LD,IE-LH,IE-MH,IE-OY,IE-WH,IE-WX,IE-WW,IE-CE,IE-CO,IE-KY,IE-LK,IE-TA,IE-WD,IE-G,IE-LM,IE-MO,IE-RN,IE-SO,IE-CN,IE-DL,IE-MN | C14: =Processes!D53 -> FT-TRABNG | D14: BIOGAS1G,BIOGAS2G | E14: =Commodities!C14 -> TRABNG | F14: 1 | G14: 50 | H14: 4 | I14: 80 | J14: =I14 -> 80 | K14: 5
B15: =Processes!C54 -> IE,IE-CW,IE-D,IE-KE,IE-KK,IE-LS,IE-LD,IE-LH,IE-MH,IE-OY,IE-WH,IE-WX,IE-WW,IE-CE,IE-CO,IE-KY,IE-LK,IE-TA,IE-WD,IE-G,IE-LM,IE-MO,IE-RN,IE-SO,IE-CN,IE-DL,IE-MN | C15: =Processes!D54 -> FT-TRAELC | D15: ELCD | E15: =Commodities!C15 -> TRAELC | F15: 1 | G15: 50 | H15: 0.01 | I15: 0.01 | J15: 0.01 | K15: 5
B16: =Processes!C55 -> IE,IE-CW,IE-D,IE-KE,IE-KK,IE-LS,IE-LD,IE-LH,IE-MH,IE-OY,IE-WH,IE-WX,IE-WW,IE-CE,IE-CO,IE-KY,IE-LK,IE-TA,IE-WD,IE-G,IE-LM,IE-MO,IE-RN,IE-SO,IE-CN,IE-DL,IE-MN | C16: =Processes!D55 -> FT-TRALNG | D16: GASLNG | E16: =Commodities!C16 -> TRALNG | F16: 1 | G16: 50 | H16: 80 | I16: 80 | J16: 80 | K16: 5
B17: =Processes!C56 -> IE,IE-CW,IE-D,IE-KE,IE-KK,IE-LS,IE-LD,IE-LH,IE-MH,IE-OY,IE-WH,IE-WX,IE-WW,IE-CE,IE-CO,IE-KY,IE-LK,IE-TA,IE-WD,IE-G,IE-LM,IE-MO,IE-RN,IE-SO,IE-CN,IE-DL,IE-MN | C17: =Processes!D56 -> FT-TRAH2 | D17: SUPH2GD | E17: =Commodities!C17 -> TRAH2 | F17: 1 | G17: 50 | H17: 4 | I17: 4 | J17: 4 | K17: 5
B18: =Processes!C57 -> IE,IE-CW,IE-D,IE-KE,IE-KK,IE-LS,IE-LD,IE-LH,IE-MH,IE-OY,IE-WH,IE-WX,IE-WW,IE-CE,IE-CO,IE-KY,IE-LK,IE-TA,IE-WD,IE-G,IE-LM,IE-MO,IE-RN,IE-SO,IE-CN,IE-DL,IE-MN | C18: =Processes!D57 -> FT-TRAKER | D18: OILKER | E18: =Commodities!C18 -> TRAKER | F18: 1 | G18: 50 | H18: 0.01 | I18: 0.01 | J18: 0.01 | K18: 5
B19: =B18 -> IE,IE-CW,IE-D,IE-KE,IE-KK,IE-LS,IE-LD,IE-LH,IE-MH,IE-OY,IE-WH,IE-WX,IE-WW,IE-CE,IE-CO,IE-KY,IE-LK,IE-TA,IE-WD,IE-G,IE-LM,IE-MO,IE-RN,IE-SO,IE-CN,IE-DL,IE-MN | C19: =Processes!D58 -> FT-TRAPtLKER | D19: PtLKER | E19: =Commodities!C19 -> TRAPtLKER | F19: 1 | G19: 50 | H19: 0.01 | K19: 5
B20: =B19 -> IE,IE-CW,IE-D,IE-KE,IE-KK,IE-LS,IE-LD,IE-LH,IE-MH,IE-OY,IE-WH,IE-WX,IE-WW,IE-CE,IE-CO,IE-KY,IE-LK,IE-TA,IE-WD,IE-G,IE-LM,IE-MO,IE-RN,IE-SO,IE-CN,IE-DL,IE-MN | C20: =Processes!D59 -> FT-AVIKER | D20: =Commodities!C18 -> TRAKER | E20: =Commodities!C20 -> AVIKER | F20: 1 | G20: 100 | H20: 0.01 | K20: 5
B21: =B20 -> IE,IE-CW,IE-D,IE-KE,IE-KK,IE-LS,IE-LD,IE-LH,IE-MH,IE-OY,IE-WH,IE-WX,IE-WW,IE-CE,IE-CO,IE-KY,IE-LK,IE-TA,IE-WD,IE-G,IE-LM,IE-MO,IE-RN,IE-SO,IE-CN,IE-DL,IE-MN | C21: =Processes!D60 -> FT-AVIBJK | D21: =Commodities!C12 -> TRABJK | E21: =Commodities!C21 -> AVIBJK | F21: 1 | G21: 100 | H21: 0.01 | K21: 5
B22: =B21 -> IE,IE-CW,IE-D,IE-KE,IE-KK,IE-LS,IE-LD,IE-LH,IE-MH,IE-OY,IE-WH,IE-WX,IE-WW,IE-CE,IE-CO,IE-KY,IE-LK,IE-TA,IE-WD,IE-G,IE-LM,IE-MO,IE-RN,IE-SO,IE-CN,IE-DL,IE-MN | C22: =Processes!D61 -> FT-AVIELC | D22: =Commodities!C15 -> TRAELC | E22: =Commodities!C22 -> AVIELC | F22: 1 | G22: 100 | H22: 0.01 | K22: 5 | L22: =0.05*Q35/L61/H61 -> 0.32054829 | N22: =AK35/L61/I61 -> 7.173431 | O22: =N22+(0.5*BE36/I62/L62) -> 20.289794 | P22: 5 | R22: *from 5% of existing fleet to 100% by 2050 for short-range flights and 50% of medium-range flights by 2070
B23: =B22 -> IE,IE-CW,IE-D,IE-KE,IE-KK,IE-LS,IE-LD,IE-LH,IE-MH,IE-OY,IE-WH,IE-WX,IE-WW,IE-CE,IE-CO,IE-KY,IE-LK,IE-TA,IE-WD,IE-G,IE-LM,IE-MO,IE-RN,IE-SO,IE-CN,IE-DL,IE-MN | C23: =Processes!D62 -> FT-AVIH2 | D23: =Commodities!C17 -> TRAH2 | E23: =Commodities!C23 -> AVIH2 | F23: 1 | G23: 100 | H23: 0.01 | K23: 5 | L23: 0 | M23: =0.01*SUM(AF35:AF37)/I64/L64 -> 0.44416387 | O23: =0.25*SUM(BE35:BE37)/L64/I64 -> 11.499396 | P23: 5 | R23: *from 1% of existing fleet in 2045 to 25% by 2070 for all ranges
B24: =B23 -> IE,IE-CW,IE-D,IE-KE,IE-KK,IE-LS,IE-LD,IE-LH,IE-MH,IE-OY,IE-WH,IE-WX,IE-WW,IE-CE,IE-CO,IE-KY,IE-LK,IE-TA,IE-WD,IE-G,IE-LM,IE-MO,IE-RN,IE-SO,IE-CN,IE-DL,IE-MN | C24: =Processes!D63 -> FT-AVIPtL | D24: =Commodities!C19 -> TRAPtLKER | E24: =Commodities!C24 -> AVIPtL | F24: 1 | G24: 100 | H24: 0.01 | K24: 5
C32: Cset_CN | D32: *Description | E32: 2018 | F32: 2019 | G32: 2020 | H32: 2021 | I32: 2022 | J32: 2023 | K32: 2024 | L32: 2025 | M32: 2026 | N32: 2027 | O32: 2028 | P32: 2029 | Q32: 2030 | R32: 2031 | S32: 2032 | T32: 2033 | U32: 2034 | V32: 2035 | W32: 2036 | X32: 2037 | Y32: 2038 | Z32: 2039 | AA32: 2040 | AB32: 2041 | AC32: 2042 | AD32: 2043 | AE32: 2044 | AF32: 2045 | AG32: 2046 | AH32: 2047 | AI32: 2048 | AJ32: 2049 | AK32: 2050 | AL32: 2051 | AM32: 2052 | AN32: 2053 | AO32: 2054 | AP32: 2055 | AQ32: 2056 | AR32: 2057 | AS32: 2058 | AT32: 2059 | AU32: 2060 | AV32: 2061 | AW32: 2062 | AX32: 2063 | AY32: 2064 | AZ32: 2065 | BA32: 2066 | BB32: 2067 | BC32: 2068 | BD32: 2069 | BE32: 2070 | BF32: 2071 | BG32: 2072 | BH32: 2073 | BI32: 2074 | BJ32: 2075 | BK32: 2076 | BL32: 2077 | BM32: 2078 | BN32: 2079 | BO32: 2080 | BP32: 2081 | BQ32: 2082 | BR32: 2083 | BS32: 2084 | BT32: 2085 | BU32: 2086 | BV32: 2087 | BW32: 2088 | BX32: 2089 | BY32: 2090 | BZ32: 2091 | CA32: 2092 | CB32: 2093 | CC32: 2094 | CD32: 2095 | CE32: 2096 | CF32: 2097 | CG32: 2098 | CH32: 2099 | CI32: 2100
C33: TAVIDOM | D33: Transport Demand: Aviation domestic | E33: 0.2334932 | F33: 0.2509092 | G33: 0.11004689 | H33: 0.12006442 | I33: 0.23 | J33: 0.23 | K33: 0.23 | L33: 0.23 | M33: 0.23 | N33: 0.23 | O33: 0.23 | P33: 0.23 | Q33: 0.23 | R33: 0.23 | S33: 0.23 | T33: 0.23 | U33: 0.23 | V33: 0.23 | W33: 0.23 | X33: 0.23 | Y33: 0.23 | Z33: 0.23 | AA33: 0.23 | AB33: 0.23 | AC33: 0.23 | AD33: 0.23 | AE33: 0.23 | AF33: 0.23 | AG33: 0.23 | AH33: 0.23 | AI33: 0.23 | AJ33: 0.23 | AK33: 0.23 | AL33: 0.23 | AM33: 0.23 | AN33: 0.23 | AO33: 0.23 | AP33: 0.23 | AQ33: 0.23 | AR33: 0.23 | AS33: 0.23 | AT33: 0.23 | AU33: 0.23 | AV33: 0.23 | AW33: 0.23 | AX33: 0.23 | AY33: 0.23 | AZ33: 0.23 | BA33: 0.23 | BB33: 0.23 | BC33: 0.23 | BD33: 0.23 | BE33: 0.23 | BF33: 0.23 | BG33: 0.23 | BH33: 0.23 | BI33: 0.23 | BJ33: 0.23 | BK33: 0.23 | BL33: 0.23 | BM33: 0.23 | BN33: 0.23 | BO33: 0.23 | BP33: 0.23 | BQ33: 0.23 | BR33: 0.23 | BS33: 0.23 | BT33: 0.23 | BU33: 0.23 | BV33: 0.23 | BW33: 0.23 | BX33: 0.23 | BY33: 0.23 | BZ33: 0.23 | CA33: 0.23 | CB33: 0.23 | CC33: 0.23 | CD33: 0.23 | CE33: 0.23 | CF33: 0.23 | CG33: 0.23 | CH33: 0.23 | CI33: 0.23
C34: TAVIINT | D34: Transport Demand: Aviation international | E34: 45.968364 | F34: 46.490628 | G34: 16.580491 | H34: 18.57572 | I34: 48.192397 | J34: 48.860779 | K34: 49.515792 | L34: 0 | M34: 0 | N34: 0 | O34: 0 | P34: 0 | Q34: 0 | R34: 0 | S34: 0 | T34: 0 | U34: 0 | V34: 0 | W34: 0 | X34: 0 | Y34: 0 | Z34: 0 | AA34: 0 | AB34: 0 | AC34: 0 | AD34: 0 | AE34: 0 | AF34: 0 | AG34: 0 | AH34: 0 | AI34: 0 | AJ34: 0 | AK34: 0 | AL34: 0 | AM34: 0 | AN34: 0 | AO34: 0 | AP34: 0 | AQ34: 0 | AR34: 0 | AS34: 0 | AT34: 0 | AU34: 0 | AV34: 0 | AW34: 0 | AX34: 0 | AY34: 0 | AZ34: 0 | BA34: 0 | BB34: 0 | BC34: 0 | BD34: 0 | BE34: 0 | BF34: 0 | BG34: 0 | BH34: 0 | BI34: 0 | BJ34: 0 | BK34: 0 | BL34: 0 | BM34: 0 | BN34: 0 | BO34: 0 | BP34: 0 | BQ34: 0 | BR34: 0 | BS34: 0 | BT34: 0 | BU34: 0 | BV34: 0 | BW34: 0 | BX34: 0 | BY34: 0 | BZ34: 0 | CA34: 0 | CB34: 0 | CC34: 0 | CD34: 0 | CE34: 0 | CF34: 0 | CG34: 0 | CH34: 0 | CI34: 0
C35: TAVIINTS | D35: Transport Demand: Aviation international_Short | E35: 0 | F35: 0 | G35: 0 | H35: 0 | I35: 0 | J35: 0 | K35: 0 | L35: 2.9392746 | M35: 2.9833143 | N35: 3.027354 | O35: 3.0713937 | P35: 3.1154334 | Q35: 3.1594731 | R35: 3.2035128 | S35: 3.2475525 | T35: 3.2915922 | U35: 3.3356319 | V35: 3.3796716 | W35: 3.4237113 | X35: 3.467751 | Y35: 3.5117907 | Z35: 3.5558304 | AA35: 3.5998701 | AB35: 3.6439098 | AC35: 3.6879495 | AD35: 3.7319892 | AE35: 3.7760289 | AF35: 3.8200686 | AG35: 3.8641083 | AH35: 3.908148 | AI35: 3.9521876 | AJ35: 3.9962273 | AK35: 4.040267 | AL35: 4.040267 | AM35: 4.040267 | AN35: 4.040267 | AO35: 4.040267 | AP35: 4.040267 | AQ35: 4.040267 | AR35: 4.040267 | AS35: 4.040267 | AT35: 4.040267 | AU35: 4.040267 | AV35: 4.040267 | AW35: 4.040267 | AX35: 4.040267 | AY35: 4.040267 | AZ35: 4.040267 | BA35: 4.040267 | BB35: 4.040267 | BC35: 4.040267 | BD35: 4.040267 | BE35: 4.040267 | BF35: 4.040267 | BG35: 4.040267 | BH35: 4.040267 | BI35: 4.040267 | BJ35: 4.040267 | BK35: 4.040267 | BL35: 4.040267 | BM35: 4.040267 | BN35: 4.040267 | BO35: 4.040267 | BP35: 4.040267 | BQ35: 4.040267 | BR35: 4.040267 | BS35: 4.040267 | BT35: 4.040267 | BU35: 4.040267 | BV35: 4.040267 | BW35: 4.040267 | BX35: 4.040267 | BY35: 4.040267 | BZ35: 4.040267 | CA35: 4.040267 | CB35: 4.040267 | CC35: 4.040267 | CD35: 4.040267 | CE35: 4.040267 | CF35: 4.040267 | CG35: 4.040267 | CH35: 4.040267 | CI35: 4.040267
C36: TAVIINTM | D36: Transport Demand: Aviation international_Medium | E36: 0 | F36: 0 | G36: 0 | H36: 0 | I36: 0 | J36: 0 | K36: 0 | L36: 15.777791 | M36: 15.900361 | N36: 16.022932 | O36: 16.145502 | P36: 16.268073 | Q36: 16.390643 | R36: 16.513213 | S36: 16.635784 | T36: 16.758354 | U36: 16.880925 | V36: 17.003495 | W36: 17.126065 | X36: 17.248636 | Y36: 17.371206 | Z36: 17.493777 | AA36: 17.616347 | AB36: 17.738917 | AC36: 17.861488 | AD36: 17.984058 | AE36: 18.106629 | AF36: 18.229199 | AG36: 18.351769 | AH36: 18.47434 | AI36: 18.59691 | AJ36: 18.719481 | AK36: 18.842051 | AL36: 18.842051 | AM36: 18.842051 | AN36: 18.842051 | AO36: 18.842051 | AP36: 18.842051 | AQ36: 18.842051 | AR36: 18.842051 | AS36: 18.842051 | AT36: 18.842051 | AU36: 18.842051 | AV36: 18.842051 | AW36: 18.842051 | AX36: 18.842051 | AY36: 18.842051 | AZ36: 18.842051 | BA36: 18.842051 | BB36: 18.842051 | BC36: 18.842051 | BD36: 18.842051 | BE36: 18.842051 | BF36: 18.842051 | BG36: 18.842051 | BH36: 18.842051 | BI36: 18.842051 | BJ36: 18.842051 | BK36: 18.842051 | BL36: 18.842051 | BM36: 18.842051 | BN36: 18.842051 | BO36: 18.842051 | BP36: 18.842051 | BQ36: 18.842051 | BR36: 18.842051 | BS36: 18.842051 | BT36: 18.842051 | BU36: 18.842051 | BV36: 18.842051 | BW36: 18.842051 | BX36: 18.842051 | BY36: 18.842051 | BZ36: 18.842051 | CA36: 18.842051 | CB36: 18.842051 | CC36: 18.842051 | CD36: 18.842051 | CE36: 18.842051 | CF36: 18.842051 | CG36: 18.842051 | CH36: 18.842051 | CI36: 18.842051
C37: TAVIINTL | D37: Transport Demand: Aviation international_Long | E37: 0 | F37: 0 | G37: 0 | H37: 0 | I37: 0 | J37: 0 | K37: 0 | L37: 13.766068 | M37: 13.869136 | N37: 13.972203 | O37: 14.07527 | P37: 14.178337 | Q37: 14.281405 | R37: 14.384472 | S37: 14.487539 | T37: 14.590607 | U37: 14.693674 | V37: 14.796741 | W37: 14.899808 | X37: 15.002876 | Y37: 15.105943 | Z37: 15.20901 | AA37: 15.312078 | AB37: 15.415145 | AC37: 15.518212 | AD37: 15.621279 | AE37: 15.724347 | AF37: 15.827414 | AG37: 15.930481 | AH37: 16.033549 | AI37: 16.136616 | AJ37: 16.239683 | AK37: 16.34275 | AL37: 16.34275 | AM37: 16.34275 | AN37: 16.34275 | AO37: 16.34275 | AP37: 16.34275 | AQ37: 16.34275 | AR37: 16.34275 | AS37: 16.34275 | AT37: 16.34275 | AU37: 16.34275 | AV37: 16.34275 | AW37: 16.34275 | AX37: 16.34275 | AY37: 16.34275 | AZ37: 16.34275 | BA37: 16.34275 | BB37: 16.34275 | BC37: 16.34275 | BD37: 16.34275 | BE37: 16.34275 | BF37: 16.34275 | BG37: 16.34275 | BH37: 16.34275 | BI37: 16.34275 | BJ37: 16.34275 | BK37: 16.34275 | BL37: 16.34275 | BM37: 16.34275 | BN37: 16.34275 | BO37: 16.34275 | BP37: 16.34275 | BQ37: 16.34275 | BR37: 16.34275 | BS37: 16.34275 | BT37: 16.34275 | BU37: 16.34275 | BV37: 16.34275 | BW37: 16.34275 | BX37: 16.34275 | BY37: 16.34275 | BZ37: 16.34275 | CA37: 16.34275 | CB37: 16.34275 | CC37: 16.34275 | CD37: 16.34275 | CE37: 16.34275 | CF37: 16.34275 | CG37: 16.34275 | CH37: 16.34275 | CI37: 16.34275
C46: TechName | D46: Comm-IN | E46: Comm-OUT | F46: START | G46: EFF~2018 | H46: EFF~2030 | I46: EFF~2050 | J46: INVCOST~2018 | K46: AFA~2018 | L46: ACTFLO~DEMO | M46: LIFE | N46: CAP2ACT
C47: *Technology Name | D47: Input Commodity | E47: Output Commodity | G47: Efficiency | H47: Efficiency | I47: Efficiency | J47: Purchase price | K47: Utilisation Factor | L47: Activity to Flo | M47: Lifetime | N47: Capacity to Activity Factor
C48: *Units | G48: BV*km/PJ | H48: BV*km/PJ | I48: BV*km/PJ | J48: M€2018/000_units | K48: '000 km | L48: Passenger or tonnage/Vehicle | M48: Years | N48: bvkm/mvkm
C49: *Aviation
C50: T-AVI_DOM_NEW | D50: AVIKER,AVIBJK | E50: TAVIDOM | F50: 2019 | G50: 1 | H50: 1.05 | I50: 1.2 | N50: 1
C51: T-AVI_INT_NEW | D51: AVIKER,AVIBJK | E51: TAVIINT | F51: 2019 | G51: 1 | H51: 1.05 | I51: 1.2 | N51: 1
C52: T-SAVI_INT_JETK_NEW | D52: AVIKER | E52: TAVIINTS | F52: 2024 | G52: 0.0027498626 | H52: 0.0028873557 | I52: 0.0032998351 | J52: 63300 | K52: 2800 | L52: 117.34854 | M52: 30 | N52: 0.001
C53: T-MAVI_INT_JETK_NEW | D53: AVIKER | E53: TAVIINTM | F53: 2024 | G53: 0.004748628 | H53: 0.0049860594 | I53: 0.0056983536 | J53: 81410 | K53: 2800 | L53: 149.65089 | M53: 30 | N53: 0.001
C54: T-LAVI_INT_JETK_NEW | D54: AVIKER | E54: TAVIINTL | F54: 2024 | G54: 0.002924603 | H54: 0.0030708332 | I54: 0.0035095236 | J54: 224140 | K54: 2800 | L54: 220.27434 | M54: 30 | N54: 0.001
C55: T-SAVI_INT_SAF_NEW | D55: AVIKER,AVIBJK,AVIPtL | E55: TAVIINTS | F55: 2024 | G55: 0.0027498626 | H55: 0.0028873557 | I55: 0.0032998351 | J55: 69630 | K55: 2800 | L55: 117.34854 | M55: 30 | N55: 0.001
C56: T-MAVI_INT_SAF_NEW | D56: AVIKER,AVIBJK,AVIPtL | E56: TAVIINTM | F56: 2024 | G56: 0.004748628 | H56: 0.0049860594 | I56: 0.0056983536 | J56: 89551 | K56: 2800 | L56: 149.65089 | M56: 30 | N56: 0.001
C57: T-LAVI_INT_SAF_NEW | D57: AVIKER,AVIBJK,AVIPtL | E57: TAVIINTL | F57: 2024 | G57: 0.002924603 | H57: 0.0030708332 | I57: 0.0035095236 | J57: 246554 | K57: 2800 | L57: 220.27434 | M57: 30 | N57: 0.001
C58: T-SAVI_INT_SYN-FUEL_NEW | D58: AVIKER,AVIPtL | E58: TAVIINTS | F58: 2024 | G58: 0.0027498626 | H58: 0.0028873557 | I58: 0.0032998351 | J58: 69630 | K58: 2800 | L58: 117.34854 | M58: 30 | N58: 0.001
C59: T-MAVI_INT_SYN-FUEL_NEW | D59: AVIKER,AVIPtL | E59: TAVIINTM | F59: 2024 | G59: 0.004748628 | H59: 0.0049860594 | I59: 0.0056983536 | J59: 89551 | K59: 2800 | L59: 149.65089 | M59: 30 | N59: 0.001
C60: T-LAVI_INT_SYN-FUEL_NEW | D60: AVIKER,AVIPtL | E60: TAVIINTL | F60: 2024 | G60: 0.002924603 | H60: 0.0030708332 | I60: 0.0035095236 | J60: 246554 | K60: 2800 | L60: 220.27434 | M60: 30 | N60: 0.001
C61: T-SAVI_INT_ELC_NEW | D61: AVIELC | E61: TAVIINTS | F61: 2030 | G61: 0.0039996705 | H61: 0.004199654 | I61: 0.0047996046 | J61: 126600 | K61: 2800 | L61: 117.34854 | M61: 30 | N61: 0.001
C62: T-MAVI_INT_ELC_NEW | D62: AVIELC | E62: TAVIINTM | F62: 2045 | G62: 0.0039996705 | H62: 0.004199654 | I62: 0.0047996046 | J62: 162820 | K62: 2800 | L62: 149.65089 | M62: 30 | N62: 0.001
C63: T-SAVI_INT_H2_NEW | D63: AVIH2 | E63: TAVIINTS | F63: 2045 | G63: 0.0027498626 | H63: 0.0028873557 | I63: 0.0032998351 | J63: 189900 | K63: 2800 | L63: 117.34854 | M63: 30 | N63: 0.001
... C65: T-LAVI_INT_H2_NEW | D65: AVIH2 | E65: TAVIINTL | F65: 2045 | G65: 0.002924603 | H65: 0.0030708332 | I65: 0.0035095236 | J65: 672420 | K65: 2800 | L65: 220.27434 | M65: 30 | N65: 0.001

Sheet Stock
AI2: Passenger | BM2: Freight
F3: ~FI_T: Stock~2018 | AI3: Total available supply (Bpkm) | BM3: Total available supply (Btkm)
C4: TechName | D4: *Unit | E4: Comm-IN | F4: Comm-OUT | G4: =Regions!C3 -> IE | H4: =Regions!E3 -> IE-CW | I4: =Regions!F3 -> IE-D | J4: =Regions!G3 -> IE-KE | K4: =Regions!H3 -> IE-KK | L4: =Regions!I3 -> IE-LS | M4: =Regions!J3 -> IE-LD | N4: =Regions!K3 -> IE-LH | O4: =Regions!L3 -> IE-MH | ... AG4: =Regions!AD3 -> IE-MN | AJ4: =G4 -> IE | AK4: =H4 -> IE-CW | AL4: =I4 -> IE-D | AM4: =J4 -> IE-KE | AN4: =K4 -> IE-KK | AO4: =L4 -> IE-LS | AP4: =M4 -> IE-LD | AQ4: =N4 -> IE-LH | ... BJ4: =AG4 -> IE-MN | BM4: Technology | BN4: =AJ4 -> IE | BO4: =AK4 -> IE-CW | BP4: =AL4 -> IE-D | BQ4: =AM4 -> IE-KE | BR4: =AN4 -> IE-KK | BS4: =AO4 -> IE-LS | BT4: =AP4 -> IE-LD | BU4: =AQ4 -> IE-LH | ... CN4: =BJ4 -> IE-MN
C5: *Two-wheelers | AI5: =C5 -> *Two-wheelers | BM5: Goods Vehicles
C6: =Processes!D9 -> T-MOT-ICE_GSL00 | D6: kUnits | E6: =Commodities!C8&","&Commodities!C10 -> TRAGSL,TRAETH | F6: =Commodities!C25&","&Commodities!C26 -> TRAPS,TRAPM | G6: =SUM(H6:AG6) -> 39.852 | H6: =F185/1000 -> 0.563 | I6: =G185/1000 -> 12.616 | J6: =H185/1000 -> 2.168 | K6: =I185/1000 -> 0.872 | L6: =J185/1000 -> 0.513 | M6: =K185/1000 -> 0.213 | N6: =L185/1000 -> 0.855 | O6: =M185/1000 -> 1.684 | ... AG6: =AE185/1000 -> 0.301 | AI6: =C6 -> T-MOT-ICE_GSL00 | AJ6: =G6*AF!D6*ACT2FLO!E52/1000 -> 0.11971939 | AK6: =H6*AF!E6*ACT2FLO!F52/1000 -> 0.0016330941 | AL6: =I6*AF!F6*ACT2FLO!G52/1000 -> 0.038829525 | AM6: =J6*AF!G6*ACT2FLO!H52/1000 -> 0.0065057344 | AN6: =K6*AF!H6*ACT2FLO!I52/1000 -> 0.0025437984 | AO6: =L6*AF!I6*ACT2FLO!J52/1000 -> 0.001529253 | AP6: =M6*AF!J6*ACT2FLO!K52/1000 -> 0.0006253467 | AQ6: =N6*AF!K6*ACT2FLO!L52/1000 -> 0.002593899 | ... BJ6: =AG6*AF!AD6*ACT2FLO!AE52/1000 -> 0.000920458 | BM6: =C28 -> T-LGT-ICE_GSL00 | BN6: =G28*AF!D23*ACT2FLO!E70/1000 -> 0.00079580552 | BO6: =H28*AF!E23*ACT2FLO!F70/1000 -> 8.879285e-06 | BP6: =I28*AF!F23*ACT2FLO!G70/1000 -> 0.00026747075 | BQ6: =J28*AF!G23*ACT2FLO!H70/1000 -> 4.5203578e-05 | BR6: =K28*AF!H23*ACT2FLO!I70/1000 -> 1.2900645e-05 | BS6: =L28*AF!I23*ACT2FLO!J70/1000 -> 1.8639274e-05 | BT6: =M28*AF!J23*ACT2FLO!K70/1000 -> 7.00212e-06 | BU6: =N28*AF!K23*ACT2FLO!L70/1000 -> 1.3527585e-05 | ... CN6: =AG28*AF!AD23*ACT2FLO!AE70/1000 -> 1.0767888e-05
C7: *Private cars | AI7: =C7 -> *Private cars | BM7: =C31 -> T-HGT-ICE_DST00 | BN7: =G31*AF!D26*ACT2FLO!E73/1000 -> 10.105241 | BO7: =H31*AF!E26*ACT2FLO!F73/1000 -> 0.17478036 | BP7: =I31*AF!F26*ACT2FLO!G73/1000 -> 1.7660123 | BQ7: =J31*AF!G26*ACT2FLO!H73/1000 -> 0.55782975 | BR7: =K31*AF!H26*ACT2FLO!I73/1000 -> 0.38957272 | BS7: =L31*AF!I26*ACT2FLO!J73/1000 -> 0.21890466 | BT7: =M31*AF!J26*ACT2FLO!K73/1000 -> 0.12980282 | BU7: =N31*AF!K26*ACT2FLO!L73/1000 -> 0.2927574 | ... CN7: =AG31*AF!AD26*ACT2FLO!AE73/1000 -> 0.5420726
C8: =Processes!D11 -> T-CAR-ICE_GSL00 | D8: kUnits | E8: =Commodities!C8&","&Commodities!C10 -> TRAGSL,TRAETH | F8: =Commodities!C25&","&Commodities!C26&","&Commodities!C27 -> TRAPS,TRAPM,TRAPL | G8: =SUM(H8:AG8) -> 946.86 | H8: =F186/1000 -> 10.796 | I8: =G186/1000 -> 299.408 | J8: =H186/1000 -> 44.521 | K8: =I186/1000 -> 17.346 | L8: =J186/1000 -> 12.391 | M8: =K186/1000 -> 5.804 | N8: =L186/1000 -> 20.722 | O8: =M186/1000 -> 34.216 | ... AG8: =AE186/1000 -> 7.85 | AI8: =C8 -> T-CAR-ICE_GSL00 | AJ8: =G8*AF!D7*ACT2FLO!E53/1000 -> 18.10691 | AK8: =H8*AF!E7*ACT2FLO!F53/1000 -> 0.21806681 | AL8: =I8*AF!F7*ACT2FLO!G53/1000 -> 4.9233032 | AM8: =J8*AF!G7*ACT2FLO!H53/1000 -> 0.89867526 | AN8: =K8*AF!H7*ACT2FLO!I53/1000 -> 0.35621826 | AO8: =L8*AF!I7*ACT2FLO!J53/1000 -> 0.26035967 | AP8: =M8*AF!J7*ACT2FLO!K53/1000 -> 0.1214254 | AQ8: =N8*AF!K7*ACT2FLO!L53/1000 -> 0.40758491 | ... BJ8: =AG8*AF!AD7*ACT2FLO!AE53/1000 -> 0.16140707 | BM8: =C32 -> T-GTR-ICE_DST00 | BN8: =G32*AF!D27*ACT2FLO!E74/1000 -> 0.090839 | BO8: =H32*AF!E27*ACT2FLO!F74/1000 -> 0 | BP8: =I32*AF!F27*ACT2FLO!G74/1000 -> 0.090839 | BQ8: =J32*AF!G27*ACT2FLO!H74/1000 -> 0 | BR8: =K32*AF!H27*ACT2FLO!I74/1000 -> 0 | BS8: =L32*AF!I27*ACT2FLO!J74/1000 -> 0 | BT8: =M32*AF!J27*ACT2FLO!K74/1000 -> 0 | BU8: =N32*AF!K27*ACT2FLO!L74/1000 -> 0 | ... CN8: =AG32*AF!AD27*ACT2FLO!AE74/1000 -> 0
C9: =Processes!D12 -> T-CAR-ICE_DST00 | D9: kUnits | E9: =Commodities!C9&","&Commodities!C11 -> TRADST,TRABDL | F9: =Commodities!C25&","&Commodities!C26&","&Commodities!C27 -> TRAPS,TRAPM,TRAPL | G9: =SUM(H9:AG9) -> 1129.404 | H9: =F187/1000 -> 17.385 | I9: =G187/1000 -> 225.706 | J9: =H187/1000 -> 56.834 | K9: =I187/1000 -> 26.674 | L9: =J187/1000 -> 22.058 | M9: =K187/1000 -> 11.27 | N9: =L187/1000 -> 29.947 | O9: =M187/1000 -> 52.424 | ... AG9: =AE187/1000 -> 17.634 | AI9: =C9 -> T-CAR-ICE_DST00 | AJ9: =G9*AF!D8*ACT2FLO!E54/1000 -> 34.741372 | AK9: =H9*AF!E8*ACT2FLO!F54/1000 -> 0.56367216 | AL9: =I9*AF!F8*ACT2FLO!G54/1000 -> 6.0973033 | AM9: =J9*AF!G8*ACT2FLO!H54/1000 -> 1.7730201 | AN9: =K9*AF!H8*ACT2FLO!I54/1000 -> 0.86560466 | AO9: =L9*AF!I8*ACT2FLO!J54/1000 -> 0.73387771 | AP9: =M9*AF!J8*ACT2FLO!K54/1000 -> 0.38208656 | AQ9: =N9*AF!K8*ACT2FLO!L54/1000 -> 0.921015 | ... BJ9: =AG9*AF!AD8*ACT2FLO!AE54/1000 -> 0.56787787
C10: =Processes!D13 -> T-CAR-ICE_DF00 | D10: kUnits | E10: =Commodities!C8&","&Commodities!C13 -> TRAGSL,TRACNG | F10: =Commodities!C25&","&Commodities!C26&","&Commodities!C27 -> TRAPS,TRAPM,TRAPL | G10: =SUM(H10:AG10) -> 0.067 | H10: =F188/1000 -> 0 | I10: =G188/1000 -> 0.028 | J10: =H188/1000 -> 0.001 | K10: =I188/1000 -> 0.001 | L10: =J188/1000 -> 0 | M10: =K188/1000 -> 0.002 | N10: =L188/1000 -> 0.001 | O10: =M188/1000 -> 0.002 | ... AG10: =AE188/1000 -> 0 | AI10: =C10 -> T-CAR-ICE_DF00 | AJ10: =G10*AF!D9*ACT2FLO!E55/1000 -> 0.0013439264 | AK10: =H10*AF!E9*ACT2FLO!F55/1000 -> 0 | AL10: =I10*AF!F9*ACT2FLO!G55/1000 -> 0.00053670042 | AM10: =J10*AF!G9*ACT2FLO!H55/1000 -> 2.0758356e-05 | AN10: =K10*AF!H9*ACT2FLO!I55/1000 -> 2.1422301e-05 | AO10: =L10*AF!I9*ACT2FLO!J55/1000 -> 0 | AP10: =M10*AF!J9*ACT2FLO!K55/1000 -> 4.1788259e-05 | AQ10: =N10*AF!K9*ACT2FLO!L55/1000 -> 2.0013843e-05 | ... BJ10: =AG10*AF!AD9*ACT2FLO!AE55/1000 -> 0
C11: =Processes!D14 -> T-CAR-ICE_E8500 | D11: kUnits | E11: =Commodities!C8&","&Commodities!C10 -> TRAGSL,TRAETH | F11: =Commodities!C25&","&Commodities!C26&","&Commodities!C27 -> TRAPS,TRAPM,TRAPL | G11: =SUM(H11:AG11) -> 8.529 | H11: =F189/1000 -> 0.098 | I11: =G189/1000 -> 0.265 | J11: =H189/1000 -> 0.281 | K11: =I189/1000 -> 0.574 | L11: =J189/1000 -> 0.124 | M11: =K189/1000 -> 0.316 | N11: =L189/1000 -> 0.041 | O11: =M189/1000 -> 0.083 | ... AG11: =AE189/1000 -> 0.472 | AI11: =C11 -> T-CAR-ICE_E8500 | AJ11: =G11*AF!D10*ACT2FLO!E56/1000 -> 0.17107982 | AK11: =H11*AF!E10*ACT2FLO!F56/1000 -> 0.0020603456 | AL11: =I11*AF!F10*ACT2FLO!G56/1000 -> 0.0050794861 | AM11: =J11*AF!G10*ACT2FLO!H56/1000 -> 0.0058330981 | AN11: =K11*AF!H10*ACT2FLO!I56/1000 -> 0.012296401 | AO11: =L11*AF!I10*ACT2FLO!J56/1000 -> 0.0026985475 | AP11: =M11*AF!J10*ACT2FLO!K56/1000 -> 0.0066025449 | AQ11: =N11*AF!K10*ACT2FLO!L56/1000 -> 0.00082056755 | ... BJ11: =AG11*AF!AD10*ACT2FLO!AE56/1000 -> 0.0097120282 | BM11: Total available supply: New (Btkm)
C12: =Processes!D15 -> T-CAR-HEV_GSL00 | D12: kUnits | E12: =Commodities!C8&","&Commodities!C10 -> TRAGSL,TRAETH | F12: =Commodities!C25&","&Commodities!C26&","&Commodities!C27 -> TRAPS,TRAPM,TRAPL | G12: =SUM(H12:AG12) -> 29.8 | H12: =F190/1000 -> 0.205 | I12: =G190/1000 -> 1.109 | J12: =H190/1000 -> 0.572 | K12: =I190/1000 -> 1.428 | L12: =J190/1000 -> 0.365 | M12: =K190/1000 -> 0.805 | N12: =L190/1000 -> 0.159 | O12: =M190/1000 -> 0.457 | ... AG12: =AE190/1000 -> 1.105 | AI12: =C12 -> T-CAR-HEV_GSL00 | AJ12: =G12*AF!D11*ACT2FLO!E57/1000 -> 0.56986873 | AK12: =H12*AF!E11*ACT2FLO!F57/1000 -> 0.0041407647 | AL12: =I12*AF!F11*ACT2FLO!G57/1000 -> 0.018235796 | AM12: =J12*AF!G11*ACT2FLO!H57/1000 -> 0.011546062 | AN12: =K12*AF!H11*ACT2FLO!I57/1000 -> 0.029325475 | AO12: =L12*AF!I11*ACT2FLO!J57/1000 -> 0.0076693794 | AP12: =M12*AF!J11*ACT2FLO!K57/1000 -> 0.016841393 | AQ12: =N12*AF!K11*ACT2FLO!L57/1000 -> 0.0031274009 | ... BJ12: =AG12*AF!AD11*ACT2FLO!AE57/1000 -> 0.022720359 | BM12: =BM4 -> Technology | BN12: =BN4 -> IE | BO12: =BO4 -> IE-CW | BP12: =BP4 -> IE-D | BQ12: =BQ4 -> IE-KE | BR12: =BR4 -> IE-KK | BS12: =BS4 -> IE-LS | BT12: =BT4 -> IE-LD | ... CN12: =CN4 -> IE-MN
C13: =Processes!D16 -> T-CAR-HEV_DST00 | D13: kUnits | E13: =Commodities!C9&","&Commodities!C11 -> TRADST,TRABDL | F13: =Commodities!C25&","&Commodities!C26&","&Commodities!C27 -> TRAPS,TRAPM,TRAPL | G13: =SUM(H13:AG13) -> 0.773 | H13: =F191/1000 -> 0.014 | I13: =G191/1000 -> 0.033 | J13: =H191/1000 -> 0.019 | K13: =I191/1000 -> 0.043 | L13: =J191/1000 -> 0.016 | M13: =K191/1000 -> 0.024 | N13: =L191/1000 -> 0.008 | O13: =M191/1000 -> 0.013 | ... AG13: =AE191/1000 -> 0.038 | AI13: =C13 -> T-CAR-HEV_DST00 | AJ13: =G13*AF!D12*ACT2FLO!E58/1000 -> 0.0237781 | AK13: =H13*AF!E12*ACT2FLO!F58/1000 -> 0.00045392063 | AL13: =I13*AF!F12*ACT2FLO!G58/1000 -> 0.0008914739 | AM13: =J13*AF!G12*ACT2FLO!H58/1000 -> 0.00059273291 | AN13: =K13*AF!H12*ACT2FLO!I58/1000 -> 0.0013954038 | AO13: =L13*AF!I12*ACT2FLO!J58/1000 -> 0.00053232584 | AP13: =M13*AF!J12*ACT2FLO!K58/1000 -> 0.00081367147 | AQ13: =N13*AF!K12*ACT2FLO!L58/1000 -> 0.00024603867 | ... BJ13: =AG13*AF!AD12*ACT2FLO!AE58/1000 -> 0.0012237359 | BM13: =BM6 -> T-LGT-ICE_GSL00
C14: =Processes!D17 -> T-CAR-PHEV_GSL00 | D14: kUnits | E14: =Commodities!C8&","&Commodities!C15 -> TRAGSL,TRAELC | F14: =Commodities!C25&","&Commodities!C26&","&Commodities!C27 -> TRAPS,TRAPM,TRAPL | G14: =SUM(H14:AG14) -> 2.759 | H14: =F192/1000 -> 0.015 | I14: =G192/1000 -> 0.109 | J14: =H192/1000 -> 0.033 | K14: =I192/1000 -> 0.15 | L14: =J192/1000 -> 0.024 | M14: =K192/1000 -> 0.054 | N14: =L192/1000 -> 0.018 | O14: =M192/1000 -> 0.023 | ... AG14: =AE192/1000 -> 0.108 | AI14: =C14 -> T-CAR-PHEV_GSL00 | AJ14: =G14*AF!D13*ACT2FLO!E59/1000 -> 0.052760665 | AK14: =H14*AF!E13*ACT2FLO!F59/1000 -> 0.00030298278 | AL14: =I14*AF!F13*ACT2FLO!G59/1000 -> 0.001792337 | AM14: =J14*AF!G13*ACT2FLO!H59/1000 -> 0.00066611899 | AN14: =K14*AF!H13*ACT2FLO!I59/1000 -> 0.003080407 | AO14: =L14*AF!I13*ACT2FLO!J59/1000 -> 0.00050428796 | AP14: =M14*AF!J13*ACT2FLO!K59/1000 -> 0.0011297332 | AQ14: =N14*AF!K13*ACT2FLO!L59/1000 -> 0.00035404538 | ... BJ14: =AG14*AF!AD13*ACT2FLO!AE59/1000 -> 0.0022206324 | BM14: =BM7 -> T-HGT-ICE_DST00
C15: =Processes!D18 -> T-CAR-PHEV_DST00 | D15: kUnits | E15: =Commodities!C9&","&Commodities!C15 -> TRADST,TRAELC | F15: =Commodities!C25&","&Commodities!C26&","&Commodities!C27 -> TRAPS,TRAPM,TRAPL | G15: 0 | H15: =F193/1000 -> 0 | I15: =G193/1000 -> 0.011 | J15: =H193/1000 -> 0.002 | K15: =I193/1000 -> 0 | L15: =J193/1000 -> 0 | M15: =K193/1000 -> 0.001 | N15: =L193/1000 -> 0 | O15: =M193/1000 -> 0.001 | ... AG15: =AE193/1000 -> 0.001 | AI15: =C15 -> T-CAR-PHEV_DST00 | AJ15: =G15*AF!D14*ACT2FLO!E60/1000 -> 0 | AK15: =H15*AF!E14*ACT2FLO!F60/1000 -> 0 | AL15: =I15*AF!F14*ACT2FLO!G60/1000 -> 0.00029715797 | AM15: =J15*AF!G14*ACT2FLO!H60/1000 -> 6.2392938e-05 | AN15: =K15*AF!H14*ACT2FLO!I60/1000 -> 0 | AO15: =L15*AF!I14*ACT2FLO!J60/1000 -> 0 | AP15: =M15*AF!J14*ACT2FLO!K60/1000 -> 3.3902978e-05 | AQ15: =N15*AF!K14*ACT2FLO!L60/1000 -> 0 | ... BJ15: =AG15*AF!AD14*ACT2FLO!AE60/1000 -> 3.2203577e-05 | BM15: =BM8 -> T-GTR-ICE_DST00
C16: =Processes!D19 -> T-CAR-BEV_ELC00 | D16: kUnits | E16: =Commodities!C15 -> TRAELC | F16: =Commodities!C25&","&Commodities!C26&","&Commodities!C27 -> TRAPS,TRAPM,TRAPL | G16: =SUM(H16:AG16) -> 4.53 | H16: =F194/1000 -> 0.046 | I16: =G194/1000 -> 1.676 | J16: =H194/1000 -> 0.292 | K16: =I194/1000 -> 0.054 | L16: =J194/1000 -> 0.056 | M16: =K194/1000 -> 0.024 | N16: =L194/1000 -> 0.103 | O16: =M194/1000 -> 0.239 | ... AG16: =AE194/1000 -> 0.031 | AI16: =C16 -> T-CAR-BEV_ELC00 | AJ16: =G16*AF!D15*ACT2FLO!E61/1000 -> 0.090865471 | AK16: =H16*AF!E15*ACT2FLO!F61/1000 -> 0.00096710098 | AL16: =I16*AF!F15*ACT2FLO!G61/1000 -> 0.032125354 | AM16: =J16*AF!G15*ACT2FLO!H61/1000 -> 0.00606144 | AN16: =K16*AF!H15*ACT2FLO!I61/1000 -> 0.0011568043 | AO16: =L16*AF!I15*ACT2FLO!J61/1000 -> 0.0012186989 | AP16: =M16*AF!J15*ACT2FLO!K61/1000 -> 0.0005014591 | AQ16: =N16*AF!K15*ACT2FLO!L61/1000 -> 0.0020614258 | ... BJ16: =AG16*AF!AD15*ACT2FLO!AE61/1000 -> 0.00063786626 | BM16: Total
C17: *Small sevice vehicle | AI17: =C17 -> *Small sevice vehicle
C18: =Processes!D21 -> T-TAX-ICE_GSL00 | D18: kUnits | E18: =Commodities!C8&","&Commodities!C10 -> TRAGSL,TRAETH | F18: =Commodities!C25&","&Commodities!C26&","&Commodities!C27 -> TRAPS,TRAPM,TRAPL | G18: =SUM(H18:AG18) -> 2.5 | H18: =F195/1000 -> 0.01 | I18: =G195/1000 -> 1.579 | J18: =H195/1000 -> 0.071 | K18: =I195/1000 -> 0.01 | L18: =J195/1000 -> 0.012 | M18: =K195/1000 -> 0.004 | N18: =L195/1000 -> 0.048 | O18: =M195/1000 -> 0.095 | ... AG18: =AE195/1000 -> 0.004 | AI18: =C18 -> T-TAX-ICE_GSL00 | AJ18: =G18*AF!D16*ACT2FLO!E62/1000 -> 0.13281514 | AK18: =H18*AF!E16*ACT2FLO!F62/1000 -> 0.00033237541 | AL18: =I18*AF!F16*ACT2FLO!G62/1000 -> 0.083617469 | AM18: =J18*AF!G16*ACT2FLO!H62/1000 -> 0.0043649618 | AN18: =K18*AF!H16*ACT2FLO!I62/1000 -> 0.00061736453 | AO18: =L18*AF!I16*ACT2FLO!J62/1000 -> 0.00057978971 | AP18: =M18*AF!J16*ACT2FLO!K62/1000 -> 0.00024642659 | AQ18: =N18*AF!K16*ACT2FLO!L62/1000 -> 0.0025945961 | ... BJ18: =AG18*AF!AD16*ACT2FLO!AE62/1000 -> 8.3105042e-05
C19: =Processes!D22 -> T-TAX-ICE_DST00 | D19: kUnits | E19: =Commodities!C9&","&Commodities!C11 -> TRADST,TRABDL | F19: =Commodities!C25&","&Commodities!C26&","&Commodities!C27 -> TRAPS,TRAPM,TRAPL | G19: =SUM(H19:AG19) -> 17.463 | H19: =F196/1000 -> 0.147 | I19: =G196/1000 -> 8.514 | J19: =H196/1000 -> 0.715 | K19: =I196/1000 -> 0.204 | L19: =J196/1000 -> 0.2 | M19: =K196/1000 -> 0.083 | N19: =L196/1000 -> 0.508 | O19: =M196/1000 -> 0.832 | ... AG19: =AE196/1000 -> 0.075 | AI19: =C19 -> T-TAX-ICE_DST00 | AJ19: =G19*AF!D17*ACT2FLO!E63/1000 -> 1.0402458 | AK19: =H19*AF!E17*ACT2FLO!F63/1000 -> 0.0080437698 | AL19: =I19*AF!F17*ACT2FLO!G63/1000 -> 0.49445103 | AM19: =J19*AF!G17*ACT2FLO!H63/1000 -> 0.04510274 | AN19: =K19*AF!H17*ACT2FLO!I63/1000 -> 0.012695592 | AO19: =L19*AF!I17*ACT2FLO!J63/1000 -> 0.012450836 | AP19: =M19*AF!J17*ACT2FLO!K63/1000 -> 0.0056404019 | AQ19: =N19*AF!K17*ACT2FLO!L63/1000 -> 0.03237397 | ... BJ19: =AG19*AF!AD17*ACT2FLO!AE63/1000 -> 0.0047557867 | BM19: Difference between supply and demand
C20: =Processes!D23 -> T-TAX-HEV_GSL00 | D20: kUnits | E20: =Commodities!C8&","&Commodities!C10 -> TRAGSL,TRAETH | F20: =Commodities!C25&","&Commodities!C26&","&Commodities!C27 -> TRAPS,TRAPM,TRAPL | G20: =SUM(H20:AG20) -> 1.35 | H20: =F197/1000 -> 0.004 | I20: =G197/1000 -> 1.055 | J20: =H197/1000 -> 0.037 | K20: =I197/1000 -> 0.001 | L20: =J197/1000 -> 0.016 | M20: =K197/1000 -> 0 | N20: =L197/1000 -> 0.025 | O20: =M197/1000 -> 0.051 | ... AG20: =AE197/1000 -> 0 | AI20: =C20 -> T-TAX-HEV_GSL00 | AJ20: =G20*AF!D18*ACT2FLO!E64/1000 -> 0.083007837 | AK20: =H20*AF!E18*ACT2FLO!F64/1000 -> 0.00027577147 | AL20: =I20*AF!F18*ACT2FLO!G64/1000 -> 0.063488626 | AM20: =J20*AF!G18*ACT2FLO!H64/1000 -> 0.0025930071 | AN20: =K20*AF!H18*ACT2FLO!I64/1000 -> 6.3337381e-05 | AO20: =L20*AF!I18*ACT2FLO!J64/1000 -> 0.00096935392 | AP20: =M20*AF!J18*ACT2FLO!K64/1000 -> 0 | AQ20: =N20*AF!K18*ACT2FLO!L64/1000 -> 0.0015758253 | ... BJ20: =AG20*AF!AD18*ACT2FLO!AE64/1000 -> 0 | BM20: =BM12 -> Technology | BN20: =BN12 -> IE | BO20: =BO12 -> IE-CW | BP20: =BP12 -> IE-D | BQ20: =BQ12 -> IE-KE | BR20: =BR12 -> IE-KK | BS20: =BS12 -> IE-LS | BT20: =BT12 -> IE-LD | ... CN20: =CN12 -> IE-MN
C21: *Large sevice vehicle | AI21: =C21 -> *Large sevice vehicle | BM21: Trucks | BN21: =BN6+BN7-BN29 -> -0.59655452 | BO21: =BO6+BO7-BO29 -> -0.0031517603 | BP21: =BP6+BP7-BP29 -> -0.89141107 | BQ21: =BQ6+BQ7-BQ29 -> 0.075590908 | BR21: =BR6+BR7-BR29 -> 0.079435948 | BS21: =BS6+BS7-BS29 -> -0.001981384 | BT21: =BT6+BT7-BT29 -> 0.023205843 | BU21: =BU6+BU7-BU29 -> 0.013411025 | ... CN21: =CN6+CN7-CN29 -> 0.38750062
C22: =Processes!D25 -> T-BUS-ICE_DST00 | D22: kUnits | E22: =Commodities!C9&","&Commodities!C11 -> TRADST,TRABDL | F22: =Commodities!C25&","&Commodities!C26&","&Commodities!C27 -> TRAPS,TRAPM,TRAPL | G22: =SUM(H22:AG22) -> 10.695 | H22: =F198/1000 -> 0.149 | I22: =G198/1000 -> 3.066 | J22: =H198/1000 -> 0.501 | K22: =I198/1000 -> 0.295 | L22: =J198/1000 -> 0.198 | M22: =K198/1000 -> 0.105 | N22: =L198/1000 -> 0.23 | O22: =M198/1000 -> 0.376 | ... AG22: =AE198/1000 -> 0.221 | AI22: =C22 -> T-BUS-ICE_DST00 | AJ22: =G22*AF!D19*ACT2FLO!E65/1000 -> 10.519482 | AK22: =H22*AF!E19*ACT2FLO!F65/1000 -> 0.11808831 | AL22: =I22*AF!F19*ACT2FLO!G65/1000 -> 3.5358561 | AM22: =J22*AF!G19*ACT2FLO!H65/1000 -> 0.45269496 | AN22: =K22*AF!H19*ACT2FLO!I65/1000 -> 0.29241757 | AO22: =L22*AF!I19*ACT2FLO!J65/1000 -> 0.14937442 | AP22: =M22*AF!J19*ACT2FLO!K65/1000 -> 0.084421181 | AQ22: =N22*AF!K19*ACT2FLO!L65/1000 -> 0.22892671 | ... BJ22: =AG22*AF!AD19*ACT2FLO!AE65/1000 -> 0.27255499 | BM22: Train | BN22: =BN8-BN30 -> #REF! | BO22: =BO8-BO30 -> #REF! | BP22: =BP8-BP30 -> #REF! | BQ22: =BQ8-BQ30 -> #REF! | BR22: =BR8-BR30 -> #REF! | BS22: =BS8-BS30 -> #REF! | BT22: =BT8-BT30 -> #REF! | BU22: =BU8-BU30 -> #REF! | ... CN22: =CN8-CN30 -> #REF!
C23: *Rail | AI23: =C23 -> *Rail | BM23: Total | BN23: =SUM(BN21:BN22) -> #REF! | BO23: =SUM(BO21:BO22) -> #REF! | BP23: =SUM(BP21:BP22) -> #REF! | BQ23: =SUM(BQ21:BQ22) -> #REF! | BR23: =SUM(BR21:BR22) -> #REF! | BS23: =SUM(BS21:BS22) -> #REF! | BT23: =SUM(BT21:BT22) -> #REF! | BU23: =SUM(BU21:BU22) -> #REF! | ... CN23: =SUM(CN21:CN22) -> #REF!
C24: =Processes!D27 -> T-LPT-BEV_ELC00 | D24: kUnits | E24: =Commodities!C15 -> TRAELC | F24: =Commodities!C25&","&Commodities!C26 -> TRAPS,TRAPM | G24: =SUM(H24:AG24) -> 0.073 | H24: =F199/1000 -> 0 | I24: =G199/1000 -> 0.073 | J24: =H199/1000 -> 0 | K24: =I199/1000 -> 0 | L24: =J199/1000 -> 0 | M24: =K199/1000 -> 0 | N24: =L199/1000 -> 0 | O24: =M199/1000 -> 0 | ... AG24: =AE199/1000 -> 0 | AI24: =C24 -> T-LPT-BEV_ELC00 | AJ24: =G24*AF!D20*ACT2FLO!E66/1000 -> 0.31718343 | AK24: =H24*AF!E20*ACT2FLO!F66/1000 -> 0 | AL24: =I24*AF!F20*ACT2FLO!G66/1000 -> 0.31718343 | AM24: =J24*AF!G20*ACT2FLO!H66/1000 -> 0 | AN24: =K24*AF!H20*ACT2FLO!I66/1000 -> 0 | AO24: =L24*AF!I20*ACT2FLO!J66/1000 -> 0 | AP24: =M24*AF!J20*ACT2FLO!K66/1000 -> 0 | AQ24: =N24*AF!K20*ACT2FLO!L66/1000 -> 0 | ... BJ24: =AG24*AF!AD20*ACT2FLO!AE66/1000 -> 0
C25: =Processes!D28 -> T-HPT-BEV_ELC00 | D25: kUnits | E25: =Commodities!C15 -> TRAELC | F25: =Commodities!C27 -> TRAPL | G25: =SUM(H25:AG25) -> 0.052 | H25: =F200/1000 -> 0 | I25: =G200/1000 -> 0.052 | J25: =H200/1000 -> 0 | K25: =I200/1000 -> 0 | L25: =J200/1000 -> 0 | M25: =K200/1000 -> 0 | N25: =L200/1000 -> 0 | O25: =M200/1000 -> 0 | ... AG25: =AE200/1000 -> 0 | AI25: =C25 -> T-HPT-BEV_ELC00 | AJ25: =G25*AF!D21*ACT2FLO!E67/1000 -> 0.64293854 | AK25: =H25*AF!E21*ACT2FLO!F67/1000 -> 0 | AL25: =I25*AF!F21*ACT2FLO!G67/1000 -> 0.64293854 | AM25: =J25*AF!G21*ACT2FLO!H67/1000 -> 0 | AN25: =K25*AF!H21*ACT2FLO!I67/1000 -> 0 | AO25: =L25*AF!I21*ACT2FLO!J67/1000 -> 0 | AP25: =M25*AF!J21*ACT2FLO!K67/1000 -> 0 | AQ25: =N25*AF!K21*ACT2FLO!L67/1000 -> 0 | ... BJ25: =AG25*AF!AD21*ACT2FLO!AE67/1000 -> 0
C26: =Processes!D29 -> T-HPT-ICE_DST00 | D26: kUnits | E26: =Commodities!C9&","&Commodities!C11 -> TRADST,TRABDL | F26: =Commodities!C27 -> TRAPL | G26: =SUM(H26:AG26) -> 0.144 | H26: =F201/1000 -> 0.0017216381 | I26: =G201/1000 -> 0.040744476 | J26: =H201/1000 -> 0.0067285771 | K26: =I201/1000 -> 0.0030008007 | L26: =J201/1000 -> 0.0025612587 | M26: =K201/1000 -> 0.0012360098 | N26: =L201/1000 -> 0.0038974847 | O26: =M201/1000 -> 0.0058981798 | ... AG26: =AE201/1000 -> 0.0018563281 | AI26: =C26 -> T-HPT-ICE_DST00 | AJ26: =G26*AF!D22*ACT2FLO!E68/1000 -> 1.2767155 | AK26: =H26*AF!E22*ACT2FLO!F68/1000 -> 0.015264181 | AL26: =I26*AF!F22*ACT2FLO!G68/1000 -> 0.36124379 | AM26: =J26*AF!G22*ACT2FLO!H68/1000 -> 0.059656103 | AN26: =K26*AF!H22*ACT2FLO!I68/1000 -> 0.026605339 | AO26: =L26*AF!I22*ACT2FLO!J68/1000 -> 0.022708324 | AP26: =M26*AF!J22*ACT2FLO!K68/1000 -> 0.010958562 | AQ26: =N26*AF!K22*ACT2FLO!L68/1000 -> 0.034555411 | ... BJ26: =AG26*AF!AD22*ACT2FLO!AE68/1000 -> 0.016458354
C27: *Goods vehicle | AI27: *Active modes | BM27: Total demand (Btkm)
C28: =Processes!D32 -> T-LGT-ICE_GSL00 | D28: kUnits | E28: =Commodities!C8&","&Commodities!C10 -> TRAGSL,TRAETH | F28: =Commodities!C28 -> TRAF | G28: =SUM(H28:AG28) -> 0.89 | H28: =F202/1000 -> 0.01 | I28: =G202/1000 -> 0.278 | J28: =H202/1000 -> 0.049 | K28: =I202/1000 -> 0.015 | L28: =J202/1000 -> 0.021 | M28: =K202/1000 -> 0.008 | N28: =L202/1000 -> 0.015 | O28: =M202/1000 -> 0.021 | ... AG28: =AE202/1000 -> 0.012 | AI28: =C49 -> T-WLK_WLK | AJ28: =G49*AF!D4*ACT2FLO!E50/1000 -> 37.6 | AK28: =H49*AF!E4*ACT2FLO!F50/1000 -> 0.44953883 | AL28: =I49*AF!F4*ACT2FLO!G50/1000 -> 10.638835 | AM28: =J49*AF!G4*ACT2FLO!H50/1000 -> 1.7569063 | AN28: =K49*AF!H4*ACT2FLO!I50/1000 -> 0.78354241 | AO28: =L49*AF!I4*ACT2FLO!J50/1000 -> 0.6687731 | AP28: =M49*AF!J4*ACT2FLO!K50/1000 -> 0.3227359 | AQ28: =N49*AF!K4*ACT2FLO!L50/1000 -> 1.0176766 | ... BJ28: =AG49*AF!AD4*ACT2FLO!AE50/1000 -> 0.4847079 | BM28: =BM20 -> Technology | BN28: =BN20 -> IE | BO28: =BO20 -> IE-CW | BP28: =BP20 -> IE-D | BQ28: =BQ20 -> IE-KE | BR28: =BR20 -> IE-KK | BS28: =BS20 -> IE-LS | BT28: =BT20 -> IE-LD | ... CN28: =CN20 -> IE-MN
C29: =Processes!D33 -> T-LGT-ICE_DST00 | D29: kUnits | E29: =Commodities!C9&","&Commodities!C11 -> TRADST,TRABDL | F29: =Commodities!C28 -> TRAF | G29: =SUM(H29:AG29) -> 320.883 | H29: =F203/1000 -> 5.262 | I29: =G203/1000 -> 67.396 | J29: =H203/1000 -> 14.377 | K29: =I203/1000 -> 7.244 | L29: =J203/1000 -> 5.341 | M29: =K203/1000 -> 3.521 | N29: =L203/1000 -> 7.139 | O29: =M203/1000 -> 12.86 | ... AG29: =AE203/1000 -> 6.664 | AI29: =C50 -> T-CYC_CYC | AJ29: =G50*AF!D5*ACT2FLO!E51/1000 -> 16 | AK29: =H50*AF!E5*ACT2FLO!F51/1000 -> 0.19129312 | AL29: =I50*AF!F5*ACT2FLO!G51/1000 -> 4.527164 | AM29: =J50*AF!G5*ACT2FLO!H51/1000 -> 0.74761968 | AN29: =K50*AF!H5*ACT2FLO!I51/1000 -> 0.3334223 | AO29: =L50*AF!I5*ACT2FLO!J51/1000 -> 0.2845843 | AP29: =M50*AF!J5*ACT2FLO!K51/1000 -> 0.13733443 | AQ29: =N50*AF!K5*ACT2FLO!L51/1000 -> 0.43305386 | ... BJ29: =AG50*AF!AD5*ACT2FLO!AE51/1000 -> 0.20625868 | BM29: Trucks | BN29: =Demands!C7 -> 10.702591 | BO29: =Demands!D7 -> 0.177941 | BP29: =Demands!E7 -> 2.6576908 | BQ29: =Demands!F7 -> 0.48228404 | BR29: =Demands!G7 -> 0.31014967 | BS29: =Demands!H7 -> 0.22090468 | BT29: =Demands!I7 -> 0.10660398 | BU29: =Demands!J7 -> 0.27935991 | ... CN29: =Demands!AC7 -> 0.15458274
C30: =Processes!D34 -> T-MGT-ICE_DST00 | D30: kUnits | E30: =Commodities!C9&","&Commodities!C11 -> TRADST,TRABDL | F30: =Commodities!C28 -> TRAF | G30: =SUM(H30:AG30) -> 11.035 | H30: =F204/1000 -> 0.147 | I30: =G204/1000 -> 2.966 | J30: =H204/1000 -> 0.553 | K30: =I204/1000 -> 0.249 | L30: =J204/1000 -> 0.217 | M30: =K204/1000 -> 0.134 | N30: =L204/1000 -> 0.372 | O30: =M204/1000 -> 0.479 | ... AG30: =AE204/1000 -> 0.256 | BM30: Train | BN30: =Demands!#REF! -> #REF! | BO30: =Demands!#REF! -> #REF! | BP30: =Demands!#REF! -> #REF! | BQ30: =Demands!#REF! -> #REF! | BR30: =Demands!#REF! -> #REF! | BS30: =Demands!#REF! -> #REF! | BT30: =Demands!#REF! -> #REF! | BU30: =Demands!#REF! -> #REF! | ... CN30: =Demands!#REF! -> #REF!
C31: =Processes!D35 -> T-HGT-ICE_DST00 | D31: kUnits | E31: =Commodities!C9&","&Commodities!C11 -> TRADST,TRABDL | F31: =Commodities!C28 -> TRAF | G31: =SUM(H31:AG31) -> 21.648 | H31: =F205/1000 -> 0.39 | I31: =G205/1000 -> 3.883 | J31: =H205/1000 -> 1.112 | K31: =I205/1000 -> 0.713 | L31: =J205/1000 -> 0.455 | M31: =K205/1000 -> 0.276 | N31: =L205/1000 -> 0.617 | O31: =M205/1000 -> 1.424 | ... AG31: =AE205/1000 -> 1.036 | BM31: Total | BN31: =SUM(BN29:BN30) -> #REF! | BO31: =SUM(BO29:BO30) -> #REF! | BP31: =SUM(BP29:BP30) -> #REF! | BQ31: =SUM(BQ29:BQ30) -> #REF! | BR31: =SUM(BR29:BR30) -> #REF! | BS31: =SUM(BS29:BS30) -> #REF! | BT31: =SUM(BT29:BT30) -> #REF! | BU31: =SUM(BU29:BU30) -> #REF! | ... CN31: =SUM(CN29:CN30) -> #REF!
C32: =Processes!D36 -> T-GTR-ICE_DST00 | D32: kUnits | E32: =Commodities!C9&","&Commodities!C11 -> TRADST,TRABDL | F32: =Commodities!C28 -> TRAF | G32: =E206/1000 -> 0.014 | H32: =F206/1000 -> 0 | I32: =G206/1000 -> 0.014 | J32: =H206/1000 -> 0 | K32: =I206/1000 -> 0 | L32: =J206/1000 -> 0 | M32: =K206/1000 -> 0 | N32: =L206/1000 -> 0 | ... AG32: =AE206/1000 -> 0 | AI32: Total available supply: Original (Bpkm)
C33: *Turism, Navigation & Others | AI33: Transport type | AJ33: =AJ4 -> IE | AK33: =AK4 -> IE-CW | AL33: =AL4 -> IE-D | AM33: =AM4 -> IE-KE | AN33: =AN4 -> IE-KK | AO33: =AO4 -> IE-LS | AP33: =AP4 -> IE-LD | AQ33: =AQ4 -> IE-LH | ... BJ33: =BJ4 -> IE-MN
C34: =Processes!D38 -> T-TUR_CON00 | D34: PJa | E34: =Commodities!C9&","&Commodities!C11 -> TRADST,TRABDL | F34: =Commodities!C29 -> TTURS | AI34: 2-wheelers | AJ34: =AJ6 -> 0.11971939 | AK34: =AK6 -> 0.0016330941 | AL34: =AL6 -> 0.038829525 | AM34: =AM6 -> 0.0065057344 | AN34: =AN6 -> 0.0025437984 | AO34: =AO6 -> 0.001529253 | AP34: =AP6 -> 0.0006253467 | AQ34: =AQ6 -> 0.002593899 | ... BJ34: =BJ6 -> 0.000920458
C35: =Processes!D39 -> T-NAV_CON00 | D35: PJa | E35: =Commodities!C9&","&Commodities!C11 -> TRADST,TRABDL | F35: =Commodities!C30 -> TNAV | AI35: LDV | AJ35: =SUM(AJ8:AJ16) -> 53.757979 | AK35: =SUM(AK8:AK16) -> 0.78966408 | AL35: =SUM(AL8:AL16) -> 11.079565 | AM35: =SUM(AM8:AM16) -> 2.696478 | AN35: =SUM(AN8:AN16) -> 1.2690988 | AO35: =SUM(AO8:AO16) -> 1.0068606 | AP35: =SUM(AP8:AP16) -> 0.52947645 | AQ35: =SUM(AQ8:AQ16) -> 1.3352294 | ... BJ35: =SUM(BJ8:BJ16) -> 0.76583177 | BM35: New tonnage rate (ton/vehicle)
C36: =Processes!D40 -> T-OTH_CON00 | D36: PJa | E36: =Commodities!C8&","&Commodities!C10&","&Commodities!C9&","&Commodities!C11&","&Commodities!C13 -> TRAGSL,TRAETH,TRADST,TRABDL,TRACNG | F36: =Commodities!C31 -> TOTH | AI36: Taxis | AJ36: =SUM(AJ18:AJ20) -> 1.2560687 | AK36: =SUM(AK18:AK20) -> 0.0086519167 | AL36: =SUM(AL18:AL20) -> 0.64155713 | AM36: =SUM(AM18:AM20) -> 0.052060709 | AN36: =SUM(AN18:AN20) -> 0.013376294 | AO36: =SUM(AO18:AO20) -> 0.01399998 | AP36: =SUM(AP18:AP20) -> 0.0058868284 | AQ36: =SUM(AQ18:AQ20) -> 0.036544392 | ... BJ36: =SUM(BJ18:BJ20) -> 0.0048388918 | BM36: =BM28 -> Technology | BN36: =BN28 -> IE | BO36: =BO28 -> IE-CW | BP36: =BP28 -> IE-D | BQ36: =BQ28 -> IE-KE | BR36: =BR28 -> IE-KK | BS36: =BS28 -> IE-LS | BT36: =BT28 -> IE-LD | ... CN36: =CN28 -> IE-MN
C37: *Aviation | AI37: BUS | AJ37: =AJ22 -> 10.519482 | AK37: =AK22 -> 0.11808831 | AL37: =AL22 -> 3.5358561 | AM37: =AM22 -> 0.45269496 | AN37: =AN22 -> 0.29241757 | AO37: =AO22 -> 0.14937442 | AP37: =AP22 -> 0.084421181 | AQ37: =AQ22 -> 0.22892671 | ... BJ37: =BJ22 -> 0.27255499 | BM37: Trucks | BN37: =1000*BN29/SUMPRODUCT(G28:G31,AF!D23:'AF'!D26) -> 1.3184201 | BO37: =1000*BO29/SUMPRODUCT(H28:H31,AF!E23:'AF'!E26) -> 1.3428425 | BP37: =1000*BP29/SUMPRODUCT(I28:I31,AF!F23:'AF'!F26) -> 1.4718999 | BQ37: =1000*BQ29/SUMPRODUCT(J28:J31,AF!G23:'AF'!G26) -> 1.2553304 | BR37: =1000*BR29/SUMPRODUCT(K28:K31,AF!H23:'AF'!H26) -> 1.5999301 | BS37: =1000*BS29/SUMPRODUCT(L28:L31,AF!I23:'AF'!I26) -> 1.5754342 | BT37: =1000*BT29/SUMPRODUCT(M28:M31,AF!J23:'AF'!J26) -> 1.1939298 | BU37: =1000*BU29/SUMPRODUCT(N28:N31,AF!K23:'AF'!K26) -> 1.4478862 | ... CN37: =1000*CN29/SUMPRODUCT(AG28:AG31,AF!AD23:'AF'!AD26) -> 0.74828745
C38: =Processes!D42 -> T-AVI_DOM00 | D38: PJa | E38: =Commodities!C20 -> AVIKER | F38: =Commodities!C32 -> TAVIDOM | AI38: Light rail (LUAS) | AJ38: =AJ24 -> 0.31718343 | AK38: =AK24 -> 0 | AL38: =AL24 -> 0.31718343 | AM38: =AM24 -> 0 | AN38: =AN24 -> 0 | AO38: =AO24 -> 0 | AP38: =AP24 -> 0 | AQ38: =AQ24 -> 0 | ... BJ38: =BJ24 -> 0
C39: =Processes!D43 -> T-AVI_INT00 | D39: PJa | E39: =Commodities!C20 -> AVIKER | F39: =Commodities!C33 -> TAVIINT | AI39: Train | AJ39: =SUM(AJ25:AJ26) -> 1.9196541 | AK39: =SUM(AK25:AK26) -> 0.015264181 | AL39: =SUM(AL25:AL26) -> 1.0041823 | AM39: =SUM(AM25:AM26) -> 0.059656103 | AN39: =SUM(AN25:AN26) -> 0.026605339 | AO39: =SUM(AO25:AO26) -> 0.022708324 | AP39: =SUM(AP25:AP26) -> 0.010958562 | AQ39: =SUM(AQ25:AQ26) -> 0.034555411 | ... BJ39: =SUM(BJ25:BJ26) -> 0.016458354 | BM39: New supply light truck | BN39: =G28*AF!D23*Stock!BN37/1000 -> 0.024400139 | BO39: =H28*AF!E23*Stock!BO37/1000 -> 0.00027729026 | BP39: =I28*AF!F23*Stock!BP37/1000 -> 0.0091555856 | BQ39: =J28*AF!G23*Stock!BQ37/1000 -> 0.001319661 | BR39: =K28*AF!H23*Stock!BR37/1000 -> 0.00048000304 | BS39: =L28*AF!I23*Stock!BS37/1000 -> 0.00068290581 | BT39: =M28*AF!J23*Stock!BT37/1000 -> 0.00019441952 | BU39: =N28*AF!K23*Stock!BU37/1000 -> 0.00045549776 | ... CN39: =AG28*AF!AD23*Stock!CN37/1000 -> 0.00018738315
AI40: TOTAL | AJ40: =SUM(AJ34:AJ39) -> 67.890086 | AK40: =SUM(AK34:AK39) -> 0.93330158 | AL40: =SUM(AL34:AL39) -> 16.617173 | AM40: =SUM(AM34:AM39) -> 3.2673955 | AN40: =SUM(AN34:AN39) -> 1.6040418 | AO40: =SUM(AO34:AO39) -> 1.1944726 | AP40: =SUM(AP34:AP39) -> 0.63136837 | AQ40: =SUM(AQ34:AQ39) -> 1.6378498 | ... BJ40: =SUM(BJ34:BJ39) -> 1.0606045 | BM40: New supply heavy truck | BN40: =G31*AF!D26*Stock!BN37/1000 -> 1.4532016 | BO40: =H31*AF!E26*Stock!BO37/1000 -> 0.025600185 | BP40: =I31*AF!F26*Stock!BP37/1000 -> 0.28352894 | BQ40: =J31*AF!G26*Stock!BQ37/1000 -> 0.076380959 | BR40: =K31*AF!H26*Stock!BR37/1000 -> 0.067985289 | BS40: =L31*AF!I26*Stock!BS37/1000 -> 0.037616696 | BT40: =M31*AF!J26*Stock!BT37/1000 -> 0.016903954 | BU40: =N31*AF!K26*Stock!BU37/1000 -> 0.046234664 | ... CN40: =AG31*AF!AD26*Stock!CN37/1000 -> 0.044243687
BM41: Total new supply | BN41: =SUM(BN39:BN40) -> 1.4776017 | BO41: =SUM(BO39:BO40) -> 0.025877475 | BP41: =SUM(BP39:BP40) -> 0.29268453 | BQ41: =SUM(BQ39:BQ40) -> 0.07770062 | BR41: =SUM(BR39:BR40) -> 0.068465292 | BS41: =SUM(BS39:BS40) -> 0.038299602 | BT41: =SUM(BT39:BT40) -> 0.017098373 | BU41: =SUM(BU39:BU40) -> 0.046690162 | ... CN41: =SUM(CN39:CN40) -> 0.04443107
AI42: Total available supply: NEW (Bpkm) | BM42: Difference sup and dem | BN42: =BN41-Demands!C7 -> -9.2249893 | BO42: =BO41-Demands!D7 -> -0.15206352 | BP42: =BP41-Demands!E7 -> -2.3650063 | BQ42: =BQ41-Demands!F7 -> -0.40458342 | BR42: =BR41-Demands!G7 -> -0.24168438 | BS42: =BS41-Demands!H7 -> -0.18260508 | BT42: =BT41-Demands!I7 -> -0.089505603 | BU42: =BU41-Demands!J7 -> -0.23266974 | ... CN42: =CN41-Demands!AC7 -> -0.11015167
AI43: Transport type | AJ43: =AJ33 -> IE | AK43: =AK33 -> IE-CW | AL43: =AL33 -> IE-D | AM43: =AM33 -> IE-KE | AN43: =AN33 -> IE-KK | AO43: =AO33 -> IE-LS | AP43: =AP33 -> IE-LD | AQ43: =AQ33 -> IE-LH | ... BJ43: =BJ33 -> IE-MN
AI44: 2-wheelers | AJ44: =G6*AF!D6*ACT2FLO!E10/1000 -> 0.12080775 | AK44: =H6*AF!E6*ACT2FLO!F10/1000 -> 0.001484631 | AL44: =I6*AF!F6*ACT2FLO!G10/1000 -> 0.037417542 | AM44: =J6*AF!G6*ACT2FLO!H10/1000 -> 0.0072745939 | AN44: =K6*AF!H6*ACT2FLO!I10/1000 -> 0.002312544 | AO44: =L6*AF!I6*ACT2FLO!J10/1000 -> 0.00139023 | AP44: =M6*AF!J6*ACT2FLO!K10/1000 -> 0.0011028842 | AQ44: =N6*AF!K6*ACT2FLO!L10/1000 -> 0.00235809 | ... BJ44: =AG6*AF!AD6*ACT2FLO!AE10/1000 -> 0.0011045496
AI45: LDV | AJ45: =SUMPRODUCT(G8:G16,AF!D7:'AF'!D15,ACT2FLO!E11:'ACT2FLO'!E19)/1000 -> 53.685502 | AK45: =SUMPRODUCT(H8:H16,AF!E7:'AF'!E15,ACT2FLO!F11:'ACT2FLO'!F19)/1000 -> 0.79389207 | AL45: =SUMPRODUCT(I8:I16,AF!F7:'AF'!F15,ACT2FLO!G11:'ACT2FLO'!G19)/1000 -> 11.361664 | AM45: =SUMPRODUCT(J8:J16,AF!G7:'AF'!G15,ACT2FLO!H11:'ACT2FLO'!H19)/1000 -> 2.7289881 | AN45: =SUMPRODUCT(K8:K16,AF!H7:'AF'!H15,ACT2FLO!I11:'ACT2FLO'!I19)/1000 -> 1.24187 | AO45: =SUMPRODUCT(L8:L16,AF!I7:'AF'!I15,ACT2FLO!J11:'ACT2FLO'!J19)/1000 -> 1.0055032 | AP45: =SUMPRODUCT(M8:M16,AF!J7:'AF'!J15,ACT2FLO!K11:'ACT2FLO'!K19)/1000 -> 0.50747016 | AQ45: =SUMPRODUCT(N8:N16,AF!K7:'AF'!K15,ACT2FLO!L11:'ACT2FLO'!L19)/1000 -> 1.3513276 | ... BJ45: =SUMPRODUCT(AG8:AG16,AF!AD7:'AF'!AD15,ACT2FLO!AE11:'ACT2FLO'!AE19)/1000 -> 0.73913488
F46: ~FI_T: NCAP_BND~2018 | AI46: Taxis | AJ46: =SUMPRODUCT(G18:G20,AF!D16:'AF'!D18,ACT2FLO!E20:'ACT2FLO'!E22)/1000 -> 1.2543753 | AK46: =SUMPRODUCT(H18:H20,AF!E16:'AF'!E18,ACT2FLO!F20:'ACT2FLO'!F22)/1000 -> 0.0074804868 | AL46: =SUMPRODUCT(I18:I20,AF!F16:'AF'!F18,ACT2FLO!G20:'ACT2FLO'!G22)/1000 -> 0.64499213 | AM46: =SUMPRODUCT(J18:J20,AF!G16:'AF'!G18,ACT2FLO!H20:'ACT2FLO'!H22)/1000 -> 0.05233945 | AN46: =SUMPRODUCT(K18:K20,AF!H16:'AF'!H18,ACT2FLO!I20:'ACT2FLO'!I22)/1000 -> 0.013447912 | AO46: =SUMPRODUCT(L18:L20,AF!I16:'AF'!I18,ACT2FLO!J20:'ACT2FLO'!J22)/1000 -> 0.01351194 | AP46: =SUMPRODUCT(M18:M20,AF!J16:'AF'!J18,ACT2FLO!K20:'ACT2FLO'!K22)/1000 -> 0.0059972588 | AQ46: =SUMPRODUCT(N18:N20,AF!K16:'AF'!K18,ACT2FLO!L20:'ACT2FLO'!L22)/1000 -> 0.037474858 | ... BJ46: =SUMPRODUCT(AG18:AG20,AF!AD16:'AF'!AD18,ACT2FLO!AE20:'ACT2FLO'!AE22)/1000 -> 0.004508048 | BM46: *Goods vehicle | BN46: =BN36 -> IE | BO46: =BO36 -> IE-CW | BP46: =BP36 -> IE-D | BQ46: =BQ36 -> IE-KE | BR46: =BR36 -> IE-KK | BS46: =BS36 -> IE-LS | BT46: =BT36 -> IE-LD | BU46: =BU36 -> IE-LH | ... CN46: =CN36 -> IE-MN
C47: =C4 -> TechName | D47: =D4 -> *Unit | E47: =E4 -> Comm-IN | F47: =F4 -> Comm-OUT | G47: =Regions!C3 -> IE | H47: =Regions!E3 -> IE-CW | I47: =Regions!F3 -> IE-D | J47: =Regions!G3 -> IE-KE | K47: =Regions!H3 -> IE-KK | L47: =Regions!I3 -> IE-LS | M47: =Regions!J3 -> IE-LD | N47: =Regions!K3 -> IE-LH | O47: =Regions!L3 -> IE-MH | ... AG47: =Regions!AD3 -> IE-MN | AI47: BUS | AJ47: =G22*AF!D19*ACT2FLO!E23/1000 -> 9.8168961 | AK47: =H22*AF!E19*ACT2FLO!F23/1000 -> 0.10903126 | AL47: =I22*AF!F19*ACT2FLO!G23/1000 -> 3.5436414 | AM47: =J22*AF!G19*ACT2FLO!H23/1000 -> 0.46332706 | AN47: =K22*AF!H19*ACT2FLO!I23/1000 -> 0.2998219 | AO47: =L22*AF!I19*ACT2FLO!J23/1000 -> 0.13627332 | AP47: =M22*AF!J19*ACT2FLO!K23/1000 -> 0.08175688 | AQ47: =N22*AF!K19*ACT2FLO!L23/1000 -> 0.21800543 | ... BJ47: =AG22*AF!AD19*ACT2FLO!AE23/1000 -> 0.27255499 | BM47: =C28 -> T-LGT-ICE_GSL00 | BN47: =G28*1000*AF!D23*1000*ACT2FLO!E28/1000000 -> 0.85132683
C48: *Active modes | AI48: Light rail (LUAS) | AJ48: =G24*AF!D20*ACT2FLO!E24/1000 -> 0.31722652 | AK48: =H24*AF!E20*ACT2FLO!F24/1000 -> 0 | AL48: =I24*AF!F20*ACT2FLO!G24/1000 -> 0.31722652 | AM48: =J24*AF!G20*ACT2FLO!H24/1000 -> 0 | AN48: =K24*AF!H20*ACT2FLO!I24/1000 -> 0 | AO48: =L24*AF!I20*ACT2FLO!J24/1000 -> 0 | AP48: =M24*AF!J20*ACT2FLO!K24/1000 -> 0 | AQ48: =N24*AF!K20*ACT2FLO!L24/1000 -> 0 | ... BJ48: =AG24*AF!AD20*ACT2FLO!AE24/1000 -> 0 | BM48: =C29 -> T-LGT-ICE_DST00 | BN48: =G29*1000*AF!D24*1000*ACT2FLO!E29/1000000 -> 306.93967
C49: =Processes!D6 -> T-WLK_WLK | D49: kUnits | E49: =Commodities!C6 -> TRAWLK | F49: =Commodities!C25 -> TRAPS | G49: 4700 | H49: =$G$49*Demands!C139 -> 56.192353 | I49: =$G$49*Demands!D139 -> 1329.8544 | J49: =$G$49*Demands!E139 -> 219.61328 | K49: =$G$49*Demands!F139 -> 97.942802 | L49: =$G$49*Demands!G139 -> 83.596637 | M49: =$G$49*Demands!H139 -> 40.341988 | N49: =$G$49*Demands!I139 -> 127.20957 | O49: =$G$49*Demands!J139 -> 192.51004 | ... AG49: =$G$49*Demands!AB139 -> 60.588488 | AI49: Train | AJ49: =SUMPRODUCT(G25:G26,AF!D21:'AF'!D22,ACT2FLO!E25:'ACT2FLO'!E26)/1000 -> 2.2810874 | AK49: =SUMPRODUCT(H25:H26,AF!E21:'AF'!E22,ACT2FLO!F25:'ACT2FLO'!F26)/1000 -> 0.027273275 | AL49: =SUMPRODUCT(I25:I26,AF!F21:'AF'!F22,ACT2FLO!G25:'ACT2FLO'!G26)/1000 -> 0.64547658 | AM49: =SUMPRODUCT(J25:J26,AF!G21:'AF'!G22,ACT2FLO!H25:'ACT2FLO'!H26)/1000 -> 0.10659054 | AN49: =SUMPRODUCT(K25:K26,AF!H21:'AF'!H22,ACT2FLO!I25:'ACT2FLO'!I26)/1000 -> 0.04753709 | AO49: =SUMPRODUCT(L25:L26,AF!I21:'AF'!I22,ACT2FLO!J25:'ACT2FLO'!J26)/1000 -> 0.040574098 | AP49: =SUMPRODUCT(M25:M26,AF!J21:'AF'!J22,ACT2FLO!K25:'ACT2FLO'!K26)/1000 -> 0.019580211 | AQ49: =SUMPRODUCT(N25:N26,AF!K21:'AF'!K22,ACT2FLO!L25:'ACT2FLO'!L26)/1000 -> 0.061741881 | ... BJ49: =SUMPRODUCT(AG25:AG26,AF!AD21:'AF'!AD22,ACT2FLO!AE25:'ACT2FLO'!AE26)/1000 -> 0.029406964 | BM49: =C30 -> T-MGT-ICE_DST00 | BN49: =G30*1000*AF!D25*1000*ACT2FLO!E30/1000000 -> 1054.5966
C50: =Processes!D7 -> T-CYC_CYC | D50: kUnits | E50: =Commodities!C7 -> TRACYC | F50: =Commodities!C25 -> TRAPS | G50: 2000 | H50: =$G$50*Demands!C139 -> 23.91164 | I50: =$G$50*Demands!D139 -> 565.89551 | J50: =$G$50*Demands!E139 -> 93.45246 | K50: =$G$50*Demands!F139 -> 41.677788 | L50: =$G$50*Demands!G139 -> 35.573037 | M50: =$G$50*Demands!H139 -> 17.166803 | N50: =$G$50*Demands!I139 -> 54.131732 | O50: =$G$50*Demands!J139 -> 81.919164 | ... AG50: =$G$50*Demands!AB139 -> 25.782335 | AI50: TOTAL | AJ50: =SUM(AJ44:AJ49) -> 67.475895 | AK50: =SUM(AK44:AK49) -> 0.93916173 | AL50: =SUM(AL44:AL49) -> 16.550419 | AM50: =SUM(AM44:AM49) -> 3.3585198 | AN50: =SUM(AN44:AN49) -> 1.6049894 | AO50: =SUM(AO44:AO49) -> 1.1972528 | AP50: =SUM(AP44:AP49) -> 0.6159074 | AQ50: =SUM(AQ44:AQ49) -> 1.6709079 | ... BJ50: =SUM(BJ44:BJ49) -> 1.0467094 | BM50: =C31 -> T-HGT-ICE_DST00 | BN50: =G31*1000*AF!D26*1000*ACT2FLO!E31/1000000 -> 9384.6471
BM51: =C32 -> T-GTR-ICE_DST00 | BN51: =G32*1000*AF!D27*1000*ACT2FLO!E32/1000000 -> 90.842665
C53: ~FI_T | AI53: Difference between supply and demand (New)
B54: Region | C54: TechName | D54: Life | E54: FIXOM | AI54: Transport type | AJ54: =AJ43 -> IE | AK54: =AK43 -> IE-CW | AL54: =AL43 -> IE-D | AM54: =AM43 -> IE-KE | AN54: =AN43 -> IE-KK | AO54: =AO43 -> IE-LS | AP54: =AP43 -> IE-LD | AQ54: =AQ43 -> IE-LH | ... BJ54: =BJ43 -> IE-MN
B55: *Active modes | E55: M€2018/000_units/a | AI55: 2-wheelers | AJ55: =AJ44-AJ70-AJ83-AJ96 -> 0.00090775132 | AK55: =AK44-AK70-AK83-AK96 -> 0.000384631 | AL55: =AL44-AL70-AL83-AL96 -> 1.754208e-05 | AM55: =AM44-AM70-AM83-AM96 -> 0.00067459392 | AN55: =AN44-AN70-AN83-AN96 -> 0.000112544 | AO55: =AO44-AO70-AO83-AO96 -> 0.00029023 | AP55: =AP44-AP70-AP83-AP96 -> 2.88418e-06 | AQ55: =AQ44-AQ70-AQ83-AQ96 -> 0.00015809 | ... BJ55: =BJ44-BJ70-BJ83-BJ96 -> 4.5496e-06
B56: =_xlfn.TEXTJOIN(",",TRUE,Regions!$C$3:'Regions'!$AD$3) -> IE,IE-CW,IE-D,IE-KE,IE-KK,IE-LS,IE-LD,IE-LH,IE-MH,IE-OY,IE-WH,IE-WX,IE-WW,IE-CE,IE-CO,IE-KY,IE-LK,IE-TA,IE-WD,IE-G,IE-LM,IE-MO,IE-RN,IE-SO,IE-CN,IE-DL,IE-MN | C56: =C49 -> T-WLK_WLK | D56: 100 | E56: 0 | AI56: LDV | AJ56: =AJ45-AJ71-AJ84-AJ97 -> 0.0074037723 | AK56: =AK45-AK71-AK84-AK97 -> 0.0046179759 | AL56: =AL45-AL71-AL84-AL97 -> 0.0059646149 | AM56: =AM45-AM71-AM84-AM97 -> 0.013527164 | AN56: =AN45-AN71-AN84-AN97 -> 0.0079764379 | AO56: =AO45-AO71-AO84-AO97 -> 0.0013794207 | AP56: =AP45-AP71-AP84-AP97 -> 0.00018624401 | AQ56: =AQ45-AQ71-AQ84-AQ97 -> 0.005533239 | ... BJ56: =BJ45-BJ71-BJ84-BJ97 -> 0.0050652063
B57: =_xlfn.TEXTJOIN(",",TRUE,Regions!$C$3:'Regions'!$AD$3) -> IE,IE-CW,IE-D,IE-KE,IE-KK,IE-LS,IE-LD,IE-LH,IE-MH,IE-OY,IE-WH,IE-WX,IE-WW,IE-CE,IE-CO,IE-KY,IE-LK,IE-TA,IE-WD,IE-G,IE-LM,IE-MO,IE-RN,IE-SO,IE-CN,IE-DL,IE-MN | C57: =C50 -> T-CYC_CYC | D57: 100 | E57: 0 | AI57: Taxis | AJ57: =AJ46-AJ72-AJ85-AJ98 -> 0.0010856321 | AK57: =AK46-AK72-AK85-AK98 -> 2.0429216e-05 | AL57: =AL46-AL72-AL85-AL98 -> 0.0034271747 | AM57: =AM46-AM72-AM85-AM98 -> 0.0001190472 | AN57: =AN46-AN72-AN85-AN98 -> 1.9808795e-05 | AO57: =AO46-AO72-AO85-AO98 -> 8.3836775e-05 | AP57: =AP46-AP72-AP85-AP98 -> 2.9212709e-05 | AQ57: =AQ46-AQ72-AQ85-AQ98 -> 0.00017456956 | ... BJ57: =BJ46-BJ72-BJ85-BJ98 -> 3.2013432e-05
B58: =C5 -> *Two-wheelers | AI58: BUS | AJ58: =AJ47-AJ73-AJ86-AJ99 -> 0.00083756832 | AK58: =AK47-AK73-AK86-AK99 -> 3.126256e-05 | AL58: =AL47-AL73-AL86-AL99 -> 0.0011414397 | AM58: =AM47-AM73-AM86-AM99 -> 7.705951e-05 | AN58: =AN47-AN73-AN86-AN99 -> 7.19048e-05 | AO58: =AO47-AO73-AO86-AO99 -> 2.33218e-05 | AP58: =AP47-AP73-AP86-AP99 -> 6.87975e-06 | AQ58: =AQ47-AQ73-AQ86-AQ99 -> 5.431e-06 | ... BJ58: =BJ47-BJ73-BJ86-BJ99 -> 5.49905e-05
B59: =_xlfn.TEXTJOIN(",",TRUE,Regions!$C$3:'Regions'!$AD$3) -> IE,IE-CW,IE-D,IE-KE,IE-KK,IE-LS,IE-LD,IE-LH,IE-MH,IE-OY,IE-WH,IE-WX,IE-WW,IE-CE,IE-CO,IE-KY,IE-LK,IE-TA,IE-WD,IE-G,IE-LM,IE-MO,IE-RN,IE-SO,IE-CN,IE-DL,IE-MN | C59: =C6 -> T-MOT-ICE_GSL00 | D59: 10 | E59: 0.34222939 | AI59: Light rail (LUAS) | AJ59: =AJ48-AJ74-AJ87-AJ100 -> 4.028029e-05 | AK59: =AK48-AK74-AK87-AK100 -> 0 | AL59: =AL48-AL74-AL87-AL100 -> 4.028029e-05 | AM59: =AM48-AM74-AM87-AM100 -> 0 | AN59: =AN48-AN74-AN87-AN100 -> 0 | AO59: =AO48-AO74-AO87-AO100 -> 0 | AP59: =AP48-AP74-AP87-AP100 -> 0 | AQ59: =AQ48-AQ74-AQ87-AQ100 -> 0 | ... BJ59: =BJ48-BJ74-BJ87-BJ100 -> 0
B60: =C7 -> *Private cars | AI60: Train | AJ60: =AJ49-AJ75-AJ88-AJ101 -> 4.39936e-06 | AK60: =AK49-AK75-AK88-AK101 -> 1.0575563e-06 | AL60: =AL49-AL75-AL88-AL101 -> 4.9267753e-05 | AM60: =AM49-AM75-AM88-AM101 -> 4.1331855e-06 | AN60: =AN49-AN75-AN88-AN101 -> 1.8433119e-06 | AO60: =AO49-AO75-AO88-AO101 -> 1.5733129e-06 | AP60: =AP49-AP75-AP88-AP101 -> 7.5924788e-07 | AQ60: =AQ49-AQ75-AQ88-AQ101 -> 2.3941209e-06 | ... BJ60: =BJ49-BJ75-BJ88-BJ101 -> 1.1402929e-06
B61: =_xlfn.TEXTJOIN(",",TRUE,Regions!$C$3:'Regions'!$AD$3) -> IE,IE-CW,IE-D,IE-KE,IE-KK,IE-LS,IE-LD,IE-LH,IE-MH,IE-OY,IE-WH,IE-WX,IE-WW,IE-CE,IE-CO,IE-KY,IE-LK,IE-TA,IE-WD,IE-G,IE-LM,IE-MO,IE-RN,IE-SO,IE-CN,IE-DL,IE-MN | C61: =C8 -> T-CAR-ICE_GSL00 | D61: 15 | E61: 1.0145072
B62: =_xlfn.TEXTJOIN(",",TRUE,Regions!$C$3:'Regions'!$AD$3) -> IE,IE-CW,IE-D,IE-KE,IE-KK,IE-LS,IE-LD,IE-LH,IE-MH,IE-OY,IE-WH,IE-WX,IE-WW,IE-CE,IE-CO,IE-KY,IE-LK,IE-TA,IE-WD,IE-G,IE-LM,IE-MO,IE-RN,IE-SO,IE-CN,IE-DL,IE-MN | C62: =C9 -> T-CAR-ICE_DST00 | D62: 15 | E62: 1.0145072
B63: =_xlfn.TEXTJOIN(",",TRUE,Regions!$C$3:'Regions'!$AD$3) -> IE,IE-CW,IE-D,IE-KE,IE-KK,IE-LS,IE-LD,IE-LH,IE-MH,IE-OY,IE-WH,IE-WX,IE-WW,IE-CE,IE-CO,IE-KY,IE-LK,IE-TA,IE-WD,IE-G,IE-LM,IE-MO,IE-RN,IE-SO,IE-CN,IE-DL,IE-MN | C63: =C10 -> T-CAR-ICE_DF00 | D63: 15 | E63: 1.0145072
B64: =_xlfn.TEXTJOIN(",",TRUE,Regions!$C$3:'Regions'!$AD$3) -> IE,IE-CW,IE-D,IE-KE,IE-KK,IE-LS,IE-LD,IE-LH,IE-MH,IE-OY,IE-WH,IE-WX,IE-WW,IE-CE,IE-CO,IE-KY,IE-LK,IE-TA,IE-WD,IE-G,IE-LM,IE-MO,IE-RN,IE-SO,IE-CN,IE-DL,IE-MN | C64: =C11 -> T-CAR-ICE_E8500 | D64: 15 | E64: 1.0145072
B65: =_xlfn.TEXTJOIN(",",TRUE,Regions!$C$3:'Regions'!$AD$3) -> IE,IE-CW,IE-D,IE-KE,IE-KK,IE-LS,IE-LD,IE-LH,IE-MH,IE-OY,IE-WH,IE-WX,IE-WW,IE-CE,IE-CO,IE-KY,IE-LK,IE-TA,IE-WD,IE-G,IE-LM,IE-MO,IE-RN,IE-SO,IE-CN,IE-DL,IE-MN | C65: =C12 -> T-CAR-HEV_GSL00 | D65: 15 | E65: 1.0145072
B66: =_xlfn.TEXTJOIN(",",TRUE,Regions!$C$3:'Regions'!$AD$3) -> IE,IE-CW,IE-D,IE-KE,IE-KK,IE-LS,IE-LD,IE-LH,IE-MH,IE-OY,IE-WH,IE-WX,IE-WW,IE-CE,IE-CO,IE-KY,IE-LK,IE-TA,IE-WD,IE-G,IE-LM,IE-MO,IE-RN,IE-SO,IE-CN,IE-DL,IE-MN | C66: =C13 -> T-CAR-HEV_DST00 | D66: 15 | E66: 1.0145072
B67: =_xlfn.TEXTJOIN(",",TRUE,Regions!$C$3:'Regions'!$AD$3) -> IE,IE-CW,IE-D,IE-KE,IE-KK,IE-LS,IE-LD,IE-LH,IE-MH,IE-OY,IE-WH,IE-WX,IE-WW,IE-CE,IE-CO,IE-KY,IE-LK,IE-TA,IE-WD,IE-G,IE-LM,IE-MO,IE-RN,IE-SO,IE-CN,IE-DL,IE-MN | C67: =C14 -> T-CAR-PHEV_GSL00 | D67: 15 | E67: 1.0145072
B68: =_xlfn.TEXTJOIN(",",TRUE,Regions!$C$3:'Regions'!$AD$3) -> IE,IE-CW,IE-D,IE-KE,IE-KK,IE-LS,IE-LD,IE-LH,IE-MH,IE-OY,IE-WH,IE-WX,IE-WW,IE-CE,IE-CO,IE-KY,IE-LK,IE-TA,IE-WD,IE-G,IE-LM,IE-MO,IE-RN,IE-SO,IE-CN,IE-DL,IE-MN | C68: =C15 -> T-CAR-PHEV_DST00 | D68: 15 | E68: 1.0145072 | AI68: Total Short-range demand (Bpkm)
B69: =_xlfn.TEXTJOIN(",",TRUE,Regions!$C$3:'Regions'!$AD$3) -> IE,IE-CW,IE-D,IE-KE,IE-KK,IE-LS,IE-LD,IE-LH,IE-MH,IE-OY,IE-WH,IE-WX,IE-WW,IE-CE,IE-CO,IE-KY,IE-LK,IE-TA,IE-WD,IE-G,IE-LM,IE-MO,IE-RN,IE-SO,IE-CN,IE-DL,IE-MN | C69: =C16 -> T-CAR-BEV_ELC00 | D69: 15 | E69: 1.0145072 | AI69: Transport type | AJ69: =AJ33 -> IE | AK69: =AK33 -> IE-CW | AL69: =AL33 -> IE-D | AM69: =AM33 -> IE-KE | AN69: =AN33 -> IE-KK | AO69: =AO33 -> IE-LS | AP69: =AP33 -> IE-LD | AQ69: =AQ33 -> IE-LH | ... BJ69: =BJ33 -> IE-MN
B70: =C17 -> *Small sevice vehicle | AI70: 2-wheelers | AJ70: =Demands!C$4*Demands!C35 -> 0.01750365 | AK70: =Demands!D$4*Demands!D35 -> 0.00016058394 | AL70: =Demands!E$4*Demands!E35 -> 0.005459854 | AM70: =Demands!F$4*Demands!F35 -> 0.00096350365 | AN70: =Demands!G$4*Demands!G35 -> 0.00032116788 | AO70: =Demands!H$4*Demands!H35 -> 0.00016058394 | AP70: =Demands!I$4*Demands!I35 -> 0.00016058394 | AQ70: =Demands!J$4*Demands!J35 -> 0.00032116788 | ... BJ70: =Demands!AC$4*Demands!AC35 -> 0.00016058394
B71: =_xlfn.TEXTJOIN(",",TRUE,Regions!$C$3:'Regions'!$AD$3) -> IE,IE-CW,IE-D,IE-KE,IE-KK,IE-LS,IE-LD,IE-LH,IE-MH,IE-OY,IE-WH,IE-WX,IE-WW,IE-CE,IE-CO,IE-KY,IE-LK,IE-TA,IE-WD,IE-G,IE-LM,IE-MO,IE-RN,IE-SO,IE-CN,IE-DL,IE-MN | C71: =C18 -> T-TAX-ICE_GSL00 | D71: 10 | E71: 1.0145072 | AI71: LDV | AJ71: =Demands!C$4*Demands!C36 -> 7.4852298 | AK71: =Demands!D$4*Demands!D36 -> 0.11006161 | AL71: =Demands!E$4*Demands!E36 -> 1.583514 | AM71: =Demands!F$4*Demands!F36 -> 0.37866187 | AN71: =Demands!G$4*Demands!G36 -> 0.17206229 | AO71: =Demands!H$4*Demands!H36 -> 0.14002167 | AP71: =Demands!I$4*Demands!I36 -> 0.070739031 | AQ71: =Demands!J$4*Demands!J36 -> 0.18766649 | ... BJ71: =Demands!AC$4*Demands!AC36 -> 0.10236354
B72: =_xlfn.TEXTJOIN(",",TRUE,Regions!$C$3:'Regions'!$AD$3) -> IE,IE-CW,IE-D,IE-KE,IE-KK,IE-LS,IE-LD,IE-LH,IE-MH,IE-OY,IE-WH,IE-WX,IE-WW,IE-CE,IE-CO,IE-KY,IE-LK,IE-TA,IE-WD,IE-G,IE-LM,IE-MO,IE-RN,IE-SO,IE-CN,IE-DL,IE-MN | C72: =C19 -> T-TAX-ICE_DST00 | D72: 10 | E72: 1.0145072 | AI72: Taxis | AJ72: =Demands!C$4*Demands!C37 -> 0.23872184 | AK72: =Demands!D$4*Demands!D37 -> 0.0014209634 | AL72: =Demands!E$4*Demands!E37 -> 0.12220285 | AM72: =Demands!F$4*Demands!F37 -> 0.0099467435 | AN72: =Demands!G$4*Demands!G37 -> 0.002557734 | AO72: =Demands!H$4*Demands!H37 -> 0.002557734 | AP72: =Demands!I$4*Demands!I37 -> 0.0011367707 | AQ72: =Demands!J$4*Demands!J37 -> 0.0071048168 | ... BJ72: =Demands!AC$4*Demands!AC37 -> 0.00085257801
B73: =_xlfn.TEXTJOIN(",",TRUE,Regions!$C$3:'Regions'!$AD$3) -> IE,IE-CW,IE-D,IE-KE,IE-KK,IE-LS,IE-LD,IE-LH,IE-MH,IE-OY,IE-WH,IE-WX,IE-WW,IE-CE,IE-CO,IE-KY,IE-LK,IE-TA,IE-WD,IE-G,IE-LM,IE-MO,IE-RN,IE-SO,IE-CN,IE-DL,IE-MN | C73: =C20 -> T-TAX-HEV_GSL00 | D73: 10 | E73: 1.0145072 | AI73: BUS | AJ73: =Demands!C$4*Demands!C38 -> 1.2044244 | AK73: =Demands!D$4*Demands!D38 -> 0.013374233 | AL73: =Demands!E$4*Demands!E38 -> 0.43466258 | AM73: =Demands!F$4*Demands!F38 -> 0.056840491 | AN73: =Demands!G$4*Demands!G38 -> 0.036779141 | AO73: =Demands!H$4*Demands!H38 -> 0.016717791 | AP73: =Demands!I$4*Demands!I38 -> 0.010030675 | AQ73: =Demands!J$4*Demands!J38 -> 0.026748466 | ... BJ73: =Demands!AC$4*Demands!AC38 -> 0.033435583
B74: =C21 -> *Large sevice vehicle | AI74: Light rail (LUAS) | AJ74: =Demands!C$4*Demands!C39 -> 0.11204033 | AK74: =Demands!D$4*Demands!D39 -> 0 | AL74: =Demands!E$4*Demands!E39 -> 0.11204033 | AM74: =Demands!F$4*Demands!F39 -> 0 | AN74: =Demands!G$4*Demands!G39 -> 0 | AO74: =Demands!H$4*Demands!H39 -> 0 | AP74: =Demands!I$4*Demands!I39 -> 0 | AQ74: =Demands!J$4*Demands!J39 -> 0 | ... BJ74: =Demands!AC$4*Demands!AC39 -> 0
B75: =_xlfn.TEXTJOIN(",",TRUE,Regions!$C$3:'Regions'!$AD$3) -> IE,IE-CW,IE-D,IE-KE,IE-KK,IE-LS,IE-LD,IE-LH,IE-MH,IE-OY,IE-WH,IE-WX,IE-WW,IE-CE,IE-CO,IE-KY,IE-LK,IE-TA,IE-WD,IE-G,IE-LM,IE-MO,IE-RN,IE-SO,IE-CN,IE-DL,IE-MN | C75: =C22 -> T-BUS-ICE_DST00 | D75: 15 | E75: 5.49795 | AI75: Train | AJ75: =Demands!C$4*Demands!C40 -> 0 | AK75: =Demands!D$4*Demands!D40 -> 0 | AL75: =Demands!E$4*Demands!E40 -> 0 | AM75: =Demands!F$4*Demands!F40 -> 0 | AN75: =Demands!G$4*Demands!G40 -> 0 | AO75: =Demands!H$4*Demands!H40 -> 0 | AP75: =Demands!I$4*Demands!I40 -> 0 | AQ75: =Demands!J$4*Demands!J40 -> 0 | ... BJ75: =Demands!AC$4*Demands!AC40 -> 0
B76: =C23 -> *Rail | AI76: TOTAL | AJ76: =SUM(AJ70:AJ75) -> 9.0579199 | AK76: =SUM(AK70:AK75) -> 0.12501739 | AL76: =SUM(AL70:AL75) -> 2.2578796 | AM76: =SUM(AM70:AM75) -> 0.44641261 | AN76: =SUM(AN70:AN75) -> 0.21172033 | AO76: =SUM(AO70:AO75) -> 0.15945778 | AP76: =SUM(AP70:AP75) -> 0.08206706 | AQ76: =SUM(AQ70:AQ75) -> 0.22184094 | ... BJ76: =SUM(BJ70:BJ75) -> 0.13681228
B77: =_xlfn.TEXTJOIN(",",TRUE,Regions!$C$3:'Regions'!$AD$3) -> IE,IE-CW,IE-D,IE-KE,IE-KK,IE-LS,IE-LD,IE-LH,IE-MH,IE-OY,IE-WH,IE-WX,IE-WW,IE-CE,IE-CO,IE-KY,IE-LK,IE-TA,IE-WD,IE-G,IE-LM,IE-MO,IE-RN,IE-SO,IE-CN,IE-DL,IE-MN | C77: =C24 -> T-LPT-BEV_ELC00 | D77: 30 | E77: 11.579168
B78: =_xlfn.TEXTJOIN(",",TRUE,Regions!$C$3:'Regions'!$AD$3) -> IE,IE-CW,IE-D,IE-KE,IE-KK,IE-LS,IE-LD,IE-LH,IE-MH,IE-OY,IE-WH,IE-WX,IE-WW,IE-CE,IE-CO,IE-KY,IE-LK,IE-TA,IE-WD,IE-G,IE-LM,IE-MO,IE-RN,IE-SO,IE-CN,IE-DL,IE-MN | C78: =C25 -> T-HPT-BEV_ELC00 | D78: 30 | E78: 46.776119
B79: =_xlfn.TEXTJOIN(",",TRUE,Regions!$C$3:'Regions'!$AD$3) -> IE,IE-CW,IE-D,IE-KE,IE-KK,IE-LS,IE-LD,IE-LH,IE-MH,IE-OY,IE-WH,IE-WX,IE-WW,IE-CE,IE-CO,IE-KY,IE-LK,IE-TA,IE-WD,IE-G,IE-LM,IE-MO,IE-RN,IE-SO,IE-CN,IE-DL,IE-MN | C79: =C26 -> T-HPT-ICE_DST00 | D79: 30 | E79: 49.463575
B80: =C27 -> *Goods vehicle
B81: =_xlfn.TEXTJOIN(",",TRUE,Regions!$C$3:'Regions'!$AD$3) -> IE,IE-CW,IE-D,IE-KE,IE-KK,IE-LS,IE-LD,IE-LH,IE-MH,IE-OY,IE-WH,IE-WX,IE-WW,IE-CE,IE-CO,IE-KY,IE-LK,IE-TA,IE-WD,IE-G,IE-LM,IE-MO,IE-RN,IE-SO,IE-CN,IE-DL,IE-MN | C81: =C28 -> T-LGT-ICE_GSL00 | D81: 20 | E81: 0.50484614 | AI81: Total Medium-range demand (Bpkm)
B82: =_xlfn.TEXTJOIN(",",TRUE,Regions!$C$3:'Regions'!$AD$3) -> IE,IE-CW,IE-D,IE-KE,IE-KK,IE-LS,IE-LD,IE-LH,IE-MH,IE-OY,IE-WH,IE-WX,IE-WW,IE-CE,IE-CO,IE-KY,IE-LK,IE-TA,IE-WD,IE-G,IE-LM,IE-MO,IE-RN,IE-SO,IE-CN,IE-DL,IE-MN | C82: =C29 -> T-LGT-ICE_DST00 | D82: 20 | E82: 0.50484614 | AI82: Transport type | AJ82: =AJ69 -> IE | AK82: =AK69 -> IE-CW | AL82: =AL69 -> IE-D | AM82: =AM69 -> IE-KE | AN82: =AN69 -> IE-KK | AO82: =AO69 -> IE-LS | AP82: =AP69 -> IE-LD | AQ82: =AQ69 -> IE-LH | ... BJ82: =BJ69 -> IE-MN
B83: =_xlfn.TEXTJOIN(",",TRUE,Regions!$C$3:'Regions'!$AD$3) -> IE,IE-CW,IE-D,IE-KE,IE-KK,IE-LS,IE-LD,IE-LH,IE-MH,IE-OY,IE-WH,IE-WX,IE-WW,IE-CE,IE-CO,IE-KY,IE-LK,IE-TA,IE-WD,IE-G,IE-LM,IE-MO,IE-RN,IE-SO,IE-CN,IE-DL,IE-MN | C83: =C30 -> T-MGT-ICE_DST00 | D83: 20 | E83: 0.50484614 | AI83: 2-wheelers | AJ83: =Demands!C$5*Demands!C49 -> 0.10239635 | AK83: =Demands!D$5*Demands!D49 -> 0.00093941606 | AL83: =Demands!E$5*Demands!E49 -> 0.031940146 | AM83: =Demands!F$5*Demands!F49 -> 0.0056364964 | AN83: =Demands!G$5*Demands!G49 -> 0.0018788321 | AO83: =Demands!H$5*Demands!H49 -> 0.00093941606 | AP83: =Demands!I$5*Demands!I49 -> 0.00093941606 | AQ83: =Demands!J$5*Demands!J49 -> 0.0018788321 | ... BJ83: =Demands!AC$5*Demands!AC49 -> 0.00093941606
B84: =_xlfn.TEXTJOIN(",",TRUE,Regions!$C$3:'Regions'!$AD$3) -> IE,IE-CW,IE-D,IE-KE,IE-KK,IE-LS,IE-LD,IE-LH,IE-MH,IE-OY,IE-WH,IE-WX,IE-WW,IE-CE,IE-CO,IE-KY,IE-LK,IE-TA,IE-WD,IE-G,IE-LM,IE-MO,IE-RN,IE-SO,IE-CN,IE-DL,IE-MN | C84: =C31 -> T-HGT-ICE_DST00 | D84: 20 | E84: 0.50484614 | AI84: LDV | AJ84: =Demands!C$5*Demands!C50 -> 26.086026 | AK84: =Demands!D$5*Demands!D50 -> 0.38356471 | AL84: =Demands!E$5*Demands!E50 -> 5.5185463 | AM84: =Demands!F$5*Demands!F50 -> 1.3196366 | AN84: =Demands!G$5*Demands!G50 -> 0.59963708 | AO84: =Demands!H$5*Demands!H50 -> 0.48797552 | AP84: =Demands!I$5*Demands!I50 -> 0.24652552 | AQ84: =Demands!J$5*Demands!J50 -> 0.65401771 | ... BJ84: =Demands!AC$5*Demands!AC50 -> 0.35673693
B85: =_xlfn.TEXTJOIN(",",TRUE,Regions!$C$3:'Regions'!$AD$3) -> IE,IE-CW,IE-D,IE-KE,IE-KK,IE-LS,IE-LD,IE-LH,IE-MH,IE-OY,IE-WH,IE-WX,IE-WW,IE-CE,IE-CO,IE-KY,IE-LK,IE-TA,IE-WD,IE-G,IE-LM,IE-MO,IE-RN,IE-SO,IE-CN,IE-DL,IE-MN | C85: =C32 -> T-GTR-ICE_DST00 | D85: 30 | E85: 0.50484614 | AI85: Taxis | AJ85: =Demands!C$5*Demands!C51 -> 0.68513169 | AK85: =Demands!D$5*Demands!D51 -> 0.0040781648 | AL85: =Demands!E$5*Demands!E51 -> 0.35072218 | AM85: =Demands!F$5*Demands!F51 -> 0.028547154 | AN85: =Demands!G$5*Demands!G51 -> 0.0073406967 | AO85: =Demands!H$5*Demands!H51 -> 0.0073406967 | AP85: =Demands!I$5*Demands!I51 -> 0.0032625319 | AQ85: =Demands!J$5*Demands!J51 -> 0.020390824 | ... BJ85: =Demands!AC$5*Demands!AC51 -> 0.0024468989
AI86: BUS | AJ86: =Demands!C$5*Demands!C52 -> 4.1974189 | AK86: =Demands!D$5*Demands!D52 -> 0.046609202 | AL86: =Demands!E$5*Demands!E52 -> 1.5147991 | AM86: =Demands!F$5*Demands!F52 -> 0.19808911 | AN86: =Demands!G$5*Demands!G52 -> 0.12817531 | AO86: =Demands!H$5*Demands!H52 -> 0.058261503 | AP86: =Demands!I$5*Demands!I52 -> 0.034956902 | AQ86: =Demands!J$5*Demands!J52 -> 0.093218405 | ... BJ86: =Demands!AC$5*Demands!AC52 -> 0.11652301
AI87: Light rail (LUAS) | AJ87: =Demands!C$5*Demands!C53 -> 0.20514591 | AK87: =Demands!D$5*Demands!D53 -> 0 | AL87: =Demands!E$5*Demands!E53 -> 0.20514591 | AM87: =Demands!F$5*Demands!F53 -> 0 | AN87: =Demands!G$5*Demands!G53 -> 0 | AO87: =Demands!H$5*Demands!H53 -> 0 | AP87: =Demands!I$5*Demands!I53 -> 0 | AQ87: =Demands!J$5*Demands!J53 -> 0 | ... BJ87: =Demands!AC$5*Demands!AC53 -> 0
AI88: Train | AJ88: =Demands!C$5*Demands!C54 -> 0 | AK88: =Demands!D$5*Demands!D54 -> 0 | AL88: =Demands!E$5*Demands!E54 -> 0 | AM88: =Demands!F$5*Demands!F54 -> 0 | AN88: =Demands!G$5*Demands!G54 -> 0 | AO88: =Demands!H$5*Demands!H54 -> 0 | AP88: =Demands!I$5*Demands!I54 -> 0 | AQ88: =Demands!J$5*Demands!J54 -> 0 | ... BJ88: =Demands!AC$5*Demands!AC54 -> 0
AI89: TOTAL | AJ89: =SUM(AJ83:AJ88) -> 31.276119 | AK89: =SUM(AK83:AK88) -> 0.43519149 | AL89: =SUM(AL83:AL88) -> 7.6211536 | AM89: =SUM(AM83:AM88) -> 1.5519094 | AN89: =SUM(AN83:AN88) -> 0.73703192 | AO89: =SUM(AO83:AO88) -> 0.55451714 | AP89: =SUM(AP83:AP88) -> 0.28568437 | AQ89: =SUM(AQ83:AQ88) -> 0.76950577 | ... BJ89: =SUM(BJ83:BJ88) -> 0.47664625
C93: Fuel Blending
AI94: Total Long-range demand (Bpkm)
E95: ~FI_T | AI95: Transport type | AJ95: =AJ82 -> IE | AK95: =AK82 -> IE-CW | AL95: =AL82 -> IE-D | AM95: =AM82 -> IE-KE | AN95: =AN82 -> IE-KK | AO95: =AO82 -> IE-LS | AP95: =AP82 -> IE-LD | AQ95: =AQ82 -> IE-LH | ... BJ95: =BJ82 -> IE-MN
B96: Region | C96: TechName | D96: Comm-IN | E96: LimType | F96: Share-I~2018 | G96: Share-I~2020 | H96: Share-I~2030 | I96: Share-I~0 | AI96: 2-wheelers | AJ96: =Demands!C$6*Demands!C63 -> 0 | AK96: =Demands!D$6*Demands!D63 -> 0 | AL96: =Demands!E$6*Demands!E63 -> 0 | AM96: =Demands!F$6*Demands!F63 -> 0 | AN96: =Demands!G$6*Demands!G63 -> 0 | AO96: =Demands!H$6*Demands!H63 -> 0 | AP96: =Demands!I$6*Demands!I63 -> 0 | AQ96: =Demands!J$6*Demands!J63 -> 0 | ... BJ96: =Demands!AC$6*Demands!AC63 -> 0
B97: =_xlfn.TEXTJOIN(",",TRUE,Regions!$C$3:'Regions'!$AD$3) -> IE,IE-CW,IE-D,IE-KE,IE-KK,IE-LS,IE-LD,IE-LH,IE-MH,IE-OY,IE-WH,IE-WX,IE-WW,IE-CE,IE-CO,IE-KY,IE-LK,IE-TA,IE-WD,IE-G,IE-LM,IE-MO,IE-RN,IE-SO,IE-CN,IE-DL,IE-MN | C97: =C6 -> T-MOT-ICE_GSL00 | D97: =Commodities!C8 -> TRAGSL | E97: UP | F97: ='EB2018'!P48/('EB2018'!P48+'EB2018'!AJ48) -> 0.96794815 | G97: 1 | H97: 1 | I97: 5 | AI97: LDV | AJ97: =Demands!C$6*Demands!C64 -> 20.106843 | AK97: =Demands!D$6*Demands!D64 -> 0.29564778 | AL97: =Demands!E$6*Demands!E64 -> 4.2536394 | AM97: =Demands!F$6*Demands!F64 -> 1.0171625 | AN97: =Demands!G$6*Demands!G64 -> 0.46219416 | AO97: =Demands!H$6*Demands!H64 -> 0.37612656 | AP97: =Demands!I$6*Demands!I64 -> 0.19001936 | AQ97: =Demands!J$6*Demands!J64 -> 0.5041102 | ... BJ97: =Demands!AC$6*Demands!AC64 -> 0.2749692
B98: =_xlfn.TEXTJOIN(",",TRUE,Regions!$C$3:'Regions'!$AD$3) -> IE,IE-CW,IE-D,IE-KE,IE-KK,IE-LS,IE-LD,IE-LH,IE-MH,IE-OY,IE-WH,IE-WX,IE-WW,IE-CE,IE-CO,IE-KY,IE-LK,IE-TA,IE-WD,IE-G,IE-LM,IE-MO,IE-RN,IE-SO,IE-CN,IE-DL,IE-MN | C98: =C97 -> T-MOT-ICE_GSL00 | D98: =Commodities!C8 -> TRAGSL | E98: LO | F98: =F97 -> 0.96794815 | G98: 0.95 | H98: 0.9 | I98: 5 | AI98: Taxis | AJ98: =Demands!C$6*Demands!C65 -> 0.32943614 | AK98: =Demands!D$6*Demands!D65 -> 0.0019609294 | AL98: =Demands!E$6*Demands!E65 -> 0.16863993 | AM98: =Demands!F$6*Demands!F65 -> 0.013726506 | AN98: =Demands!G$6*Demands!G65 -> 0.003529673 | AO98: =Demands!H$6*Demands!H65 -> 0.003529673 | AP98: =Demands!I$6*Demands!I65 -> 0.0015687435 | AQ98: =Demands!J$6*Demands!J65 -> 0.0098046472 | ... BJ98: =Demands!AC$6*Demands!AC65 -> 0.0011765577
B99: =_xlfn.TEXTJOIN(",",TRUE,Regions!$C$3:'Regions'!$AD$3) -> IE,IE-CW,IE-D,IE-KE,IE-KK,IE-LS,IE-LD,IE-LH,IE-MH,IE-OY,IE-WH,IE-WX,IE-WW,IE-CE,IE-CO,IE-KY,IE-LK,IE-TA,IE-WD,IE-G,IE-LM,IE-MO,IE-RN,IE-SO,IE-CN,IE-DL,IE-MN | C99: =C8 -> T-CAR-ICE_GSL00 | D99: =Commodities!C8 -> TRAGSL | E99: UP | F99: ='EB2018'!P48/('EB2018'!P48+'EB2018'!AJ48) -> 0.96794815 | G99: 1 | H99: 1 | I99: 5 | AI99: BUS | AJ99: =Demands!C$6*Demands!C66 -> 4.4142153 | AK99: =Demands!D$6*Demands!D66 -> 0.049016564 | AL99: =Demands!E$6*Demands!E66 -> 1.5930383 | AM99: =Demands!F$6*Demands!F66 -> 0.2083204 | AN99: =Demands!G$6*Demands!G66 -> 0.13479555 | AO99: =Demands!H$6*Demands!H66 -> 0.061270706 | AP99: =Demands!I$6*Demands!I66 -> 0.036762423 | AQ99: =Demands!J$6*Demands!J66 -> 0.098033129 | ... BJ99: =Demands!AC$6*Demands!AC66 -> 0.12254141
B100: =_xlfn.TEXTJOIN(",",TRUE,Regions!$C$3:'Regions'!$AD$3) -> IE,IE-CW,IE-D,IE-KE,IE-KK,IE-LS,IE-LD,IE-LH,IE-MH,IE-OY,IE-WH,IE-WX,IE-WW,IE-CE,IE-CO,IE-KY,IE-LK,IE-TA,IE-WD,IE-G,IE-LM,IE-MO,IE-RN,IE-SO,IE-CN,IE-DL,IE-MN | C100: =C8 -> T-CAR-ICE_GSL00 | D100: =Commodities!C8 -> TRAGSL | E100: LO | F100: =F99 -> 0.96794815 | G100: 0.95 | H100: 0.9 | I100: 5 | AI100: Light rail (LUAS) | AJ100: =Demands!C$6*Demands!C67 -> 0 | AK100: =Demands!D$6*Demands!D67 -> 0 | AL100: =Demands!E$6*Demands!E67 -> 0 | AM100: =Demands!F$6*Demands!F67 -> 0 | AN100: =Demands!G$6*Demands!G67 -> 0 | AO100: =Demands!H$6*Demands!H67 -> 0 | AP100: =Demands!I$6*Demands!I67 -> 0 | AQ100: =Demands!J$6*Demands!J67 -> 0 | ... BJ100: =Demands!AC$6*Demands!AC67 -> 0
B101: =_xlfn.TEXTJOIN(",",TRUE,Regions!$C$3:'Regions'!$AD$3) -> IE,IE-CW,IE-D,IE-KE,IE-KK,IE-LS,IE-LD,IE-LH,IE-MH,IE-OY,IE-WH,IE-WX,IE-WW,IE-CE,IE-CO,IE-KY,IE-LK,IE-TA,IE-WD,IE-G,IE-LM,IE-MO,IE-RN,IE-SO,IE-CN,IE-DL,IE-MN | C101: =C9 -> T-CAR-ICE_DST00 | D101: =Commodities!C9 -> TRADST | E101: UP | F101: 1 | G101: 1 | H101: 1 | I101: 5 | L101: EB2018'!U48/('EB2018'!U48+'EB2018'!AI48) | AI101: Train | AJ101: =Demands!C$6*Demands!C68 -> 2.281083 | AK101: =Demands!D$6*Demands!D68 -> 0.027272217 | AL101: =Demands!E$6*Demands!E68 -> 0.64542731 | AM101: =Demands!F$6*Demands!F68 -> 0.10658641 | AN101: =Demands!G$6*Demands!G68 -> 0.047535247 | AO101: =Demands!H$6*Demands!H68 -> 0.040572525 | AP101: =Demands!I$6*Demands!I68 -> 0.019579452 | AQ101: =Demands!J$6*Demands!J68 -> 0.061739487 | ... BJ101: =Demands!AC$6*Demands!AC68 -> 0.029405823
B102: =_xlfn.TEXTJOIN(",",TRUE,Regions!$C$3:'Regions'!$AD$3) -> IE,IE-CW,IE-D,IE-KE,IE-KK,IE-LS,IE-LD,IE-LH,IE-MH,IE-OY,IE-WH,IE-WX,IE-WW,IE-CE,IE-CO,IE-KY,IE-LK,IE-TA,IE-WD,IE-G,IE-LM,IE-MO,IE-RN,IE-SO,IE-CN,IE-DL,IE-MN | C102: =C9 -> T-CAR-ICE_DST00 | D102: =Commodities!C9 -> TRADST | E102: LO | F102: 0.959 | G102: 0.95 | H102: 0.8 | I102: 5 | AI102: TOTAL | AJ102: =SUM(AJ96:AJ101) -> 27.131578 | AK102: =SUM(AK96:AK101) -> 0.37389749 | AL102: =SUM(AL96:AL101) -> 6.6607449 | AM102: =SUM(AM96:AM101) -> 1.3457958 | AN102: =SUM(AN96:AN101) -> 0.64805463 | AO102: =SUM(AO96:AO101) -> 0.48149947 | AP102: =SUM(AP96:AP101) -> 0.24792998 | AQ102: =SUM(AQ96:AQ101) -> 0.67368746 | ... BJ102: =SUM(BJ96:BJ101) -> 0.42809299
B103: =_xlfn.TEXTJOIN(",",TRUE,Regions!$C$3:'Regions'!$AD$3) -> IE,IE-CW,IE-D,IE-KE,IE-KK,IE-LS,IE-LD,IE-LH,IE-MH,IE-OY,IE-WH,IE-WX,IE-WW,IE-CE,IE-CO,IE-KY,IE-LK,IE-TA,IE-WD,IE-G,IE-LM,IE-MO,IE-RN,IE-SO,IE-CN,IE-DL,IE-MN | C103: =C10 -> T-CAR-ICE_DF00 | D103: =Commodities!C13 -> TRACNG | E103: UP | F103: 0.5 | G103: 0.5 | H103: 0.8 | I103: 5
B104: =_xlfn.TEXTJOIN(",",TRUE,Regions!$C$3:'Regions'!$AD$3) -> IE,IE-CW,IE-D,IE-KE,IE-KK,IE-LS,IE-LD,IE-LH,IE-MH,IE-OY,IE-WH,IE-WX,IE-WW,IE-CE,IE-CO,IE-KY,IE-LK,IE-TA,IE-WD,IE-G,IE-LM,IE-MO,IE-RN,IE-SO,IE-CN,IE-DL,IE-MN | C104: =C103 -> T-CAR-ICE_DF00 | D104: =Commodities!C13 -> TRACNG | E104: LO | F104: 0.4 | G104: 0.4 | H104: 0.4 | I104: 5
B105: =_xlfn.TEXTJOIN(",",TRUE,Regions!$C$3:'Regions'!$AD$3) -> IE,IE-CW,IE-D,IE-KE,IE-KK,IE-LS,IE-LD,IE-LH,IE-MH,IE-OY,IE-WH,IE-WX,IE-WW,IE-CE,IE-CO,IE-KY,IE-LK,IE-TA,IE-WD,IE-G,IE-LM,IE-MO,IE-RN,IE-SO,IE-CN,IE-DL,IE-MN | C105: =C11 -> T-CAR-ICE_E8500 | D105: =Commodities!C10 -> TRAETH | E105: UP | F105: 0.85 | G105: 0.85 | H105: 0.85 | I105: 5
...

Sheet ACT2FLO
B3: Vehicle occupancy (passenger/tonnage per vehicle)
E5: ~FI_T: ACTFLO~2018
B6: =B48 -> TechName | C6: =C48 -> CommGrp | D6: =D48 -> *unit | E6: =E48 -> IE | F6: =F48 -> IE-CW | G6: =G48 -> IE-D | H6: =H48 -> IE-KE | I6: =I48 -> IE-KK | ... AE6: =AE48 -> IE-MN
B7: *Passenger transport
B8: =B50 -> T-WLK_WLK | C8: =C50 -> DEMO | D8: =D50 -> pass/vehicle | E8: =ROUNDUP(E50,2) -> 1 | F8: =ROUNDUP(F50,2) -> 1 | G8: =ROUNDUP(G50,2) -> 1 | H8: =ROUNDUP(H50,2) -> 1 | I8: =ROUNDUP(I50,2) -> 1 | J8: =ROUNDUP(J50,2) -> 1 | K8: =ROUNDUP(K50,2) -> 1 | L8: =ROUNDUP(L50,2) -> 1 | ... AE8: =ROUNDUP(AE50,2) -> 1
B9: =B51 -> T-CYC_CYC | C9: =C51 -> DEMO | D9: =D51 -> pass/vehicle | E9: =ROUNDUP(E51,2) -> 1 | F9: =ROUNDUP(F51,2) -> 1 | G9: =ROUNDUP(G51,2) -> 1 | H9: =ROUNDUP(H51,2) -> 1 | I9: =ROUNDUP(I51,2) -> 1 | J9: =ROUNDUP(J51,2) -> 1 | K9: =ROUNDUP(K51,2) -> 1 | L9: =ROUNDUP(L51,2) -> 1 | ... AE9: =ROUNDUP(AE51,2) -> 1
B10: =B52 -> T-MOT-ICE_GSL00 | C10: =C52 -> DEMO | D10: =D52 -> pass/vehicle | E10: =ROUNDUP(IF(Stock!AJ119>1,Stock!AJ119,1),2) -> 1.11 | F10: =ROUNDUP(IF(Stock!AK119>1,Stock!AK119,1),2) -> 1 | G10: =ROUNDUP(IF(Stock!AL119>1,Stock!AL119,1),2) -> 1.06 | H10: =ROUNDUP(IF(Stock!AM119>1,Stock!AM119,1),2) -> 1.23 | I10: =ROUNDUP(IF(Stock!AN119>1,Stock!AN119,1),2) -> 1 | J10: =ROUNDUP(IF(Stock!AO119>1,Stock!AO119,1),2) -> 1 | K10: =ROUNDUP(IF(Stock!AP119>1,Stock!AP119,1),2) -> 1.94 | L10: =ROUNDUP(IF(Stock!AQ119>1,Stock!AQ119,1),2) -> 1 | ... AE10: =ROUNDUP(IF(Stock!BJ119>1,Stock!BJ119,1),2) -> 1.32
B11: =B53 -> T-CAR-ICE_GSL00 | C11: =C53 -> DEMO | D11: =D53 -> pass/vehicle | E11: =ROUNDUP(Stock!AJ120,2) -> 1.49 | F11: =ROUNDUP(Stock!AK120,2) -> 1.5 | G11: =ROUNDUP(Stock!AL120,2) -> 1.53 | H11: =ROUNDUP(Stock!AM120,2) -> 1.51 | I11: =ROUNDUP(Stock!AN120,2) -> 1.46 | J11: =ROUNDUP(Stock!AO120,2) -> 1.49 | K11: =ROUNDUP(Stock!AP120,2) -> 1.43 | L11: =ROUNDUP(Stock!AQ120,2) -> 1.51 | ... AE11: =ROUNDUP(Stock!BJ120,2) -> 1.44
B12: =B54 -> T-CAR-ICE_DST00 | C12: =C54 -> DEMO | D12: =D54 -> pass/vehicle | E12: =ROUNDUP(E11,2) -> 1.49 | F12: =ROUNDUP(F11,2) -> 1.5 | G12: =ROUNDUP(G11,2) -> 1.53 | H12: =ROUNDUP(H11,2) -> 1.51 | I12: =ROUNDUP(I11,2) -> 1.46 | J12: =ROUNDUP(J11,2) -> 1.49 | K12: =ROUNDUP(K11,2) -> 1.43 | L12: =ROUNDUP(L11,2) -> 1.51 | ... AE12: =ROUNDUP(AE11,2) -> 1.44
B13: =B55 -> T-CAR-ICE_DF00 | C13: =C55 -> DEMO | D13: =D55 -> pass/vehicle | E13: =ROUNDUP(E12,2) -> 1.49 | F13: =ROUNDUP(F12,2) -> 1.5 | G13: =ROUNDUP(G12,2) -> 1.53 | H13: =ROUNDUP(H12,2) -> 1.51 | I13: =ROUNDUP(I12,2) -> 1.46 | J13: =ROUNDUP(J12,2) -> 1.49 | K13: =ROUNDUP(K12,2) -> 1.43 | L13: =ROUNDUP(L12,2) -> 1.51 | ... AE13: =ROUNDUP(AE12,2) -> 1.44
B14: =B56 -> T-CAR-ICE_E8500 | C14: =C56 -> DEMO | D14: =D56 -> pass/vehicle | E14: =ROUNDUP(E13,2) -> 1.49 | F14: =ROUNDUP(F13,2) -> 1.5 | G14: =ROUNDUP(G13,2) -> 1.53 | H14: =ROUNDUP(H13,2) -> 1.51 | I14: =ROUNDUP(I13,2) -> 1.46 | J14: =ROUNDUP(J13,2) -> 1.49 | K14: =ROUNDUP(K13,2) -> 1.43 | L14: =ROUNDUP(L13,2) -> 1.51 | ... AE14: =ROUNDUP(AE13,2) -> 1.44
B15: =B57 -> T-CAR-HEV_GSL00 | C15: =C57 -> DEMO | D15: =D57 -> pass/vehicle | E15: =ROUNDUP(E14,2) -> 1.49 | F15: =ROUNDUP(F14,2) -> 1.5 | G15: =ROUNDUP(G14,2) -> 1.53 | H15: =ROUNDUP(H14,2) -> 1.51 | I15: =ROUNDUP(I14,2) -> 1.46 | J15: =ROUNDUP(J14,2) -> 1.49 | K15: =ROUNDUP(K14,2) -> 1.43 | L15: =ROUNDUP(L14,2) -> 1.51 | ... AE15: =ROUNDUP(AE14,2) -> 1.44
B16: =B58 -> T-CAR-HEV_DST00 | C16: =C58 -> DEMO | D16: =D58 -> pass/vehicle | E16: =ROUNDUP(E15,2) -> 1.49 | F16: =ROUNDUP(F15,2) -> 1.5 | G16: =ROUNDUP(G15,2) -> 1.53 | H16: =ROUNDUP(H15,2) -> 1.51 | I16: =ROUNDUP(I15,2) -> 1.46 | J16: =ROUNDUP(J15,2) -> 1.49 | K16: =ROUNDUP(K15,2) -> 1.43 | L16: =ROUNDUP(L15,2) -> 1.51 | ... AE16: =ROUNDUP(AE15,2) -> 1.44
B17: =B59 -> T-CAR-PHEV_GSL00 | C17: =C59 -> DEMO | D17: =D59 -> pass/vehicle | E17: =ROUNDUP(E16,2) -> 1.49 | F17: =ROUNDUP(F16,2) -> 1.5 | G17: =ROUNDUP(G16,2) -> 1.53 | H17: =ROUNDUP(H16,2) -> 1.51 | I17: =ROUNDUP(I16,2) -> 1.46 | J17: =ROUNDUP(J16,2) -> 1.49 | K17: =ROUNDUP(K16,2) -> 1.43 | L17: =ROUNDUP(L16,2) -> 1.51 | ... AE17: =ROUNDUP(AE16,2) -> 1.44
B18: =B60 -> T-CAR-PHEV_DST00 | C18: =C60 -> DEMO | D18: =D60 -> pass/vehicle | E18: =ROUNDUP(E17,2) -> 1.49 | F18: =ROUNDUP(F17,2) -> 1.5 | G18: =ROUNDUP(G17,2) -> 1.53 | H18: =ROUNDUP(H17,2) -> 1.51 | I18: =ROUNDUP(I17,2) -> 1.46 | J18: =ROUNDUP(J17,2) -> 1.49 | K18: =ROUNDUP(K17,2) -> 1.43 | L18: =ROUNDUP(L17,2) -> 1.51 | ... AE18: =ROUNDUP(AE17,2) -> 1.44
B19: =B61 -> T-CAR-BEV_ELC00 | C19: =C61 -> DEMO | D19: =D61 -> pass/vehicle | E19: =ROUNDUP(E18,2) -> 1.49 | F19: =ROUNDUP(F18,2) -> 1.5 | G19: =ROUNDUP(G18,2) -> 1.53 | H19: =ROUNDUP(H18,2) -> 1.51 | I19: =ROUNDUP(I18,2) -> 1.46 | J19: =ROUNDUP(J18,2) -> 1.49 | K19: =ROUNDUP(K18,2) -> 1.43 | L19: =ROUNDUP(L18,2) -> 1.51 | ... AE19: =ROUNDUP(AE18,2) -> 1.44
B20: =B62 -> T-TAX-ICE_GSL00 | C20: =C62 -> DEMO | D20: =D62 -> pass/vehicle | E20: =ROUNDUP(Stock!AJ121,2) -> 1.49 | F20: =ROUNDUP(Stock!AK121,2) -> 1.29 | G20: =ROUNDUP(Stock!AL121,2) -> 1.5 | H20: =ROUNDUP(Stock!AM121,2) -> 1.5 | I20: =ROUNDUP(Stock!AN121,2) -> 1.5 | J20: =ROUNDUP(Stock!AO121,2) -> 1.44 | K20: =ROUNDUP(Stock!AP121,2) -> 1.52 | L20: =ROUNDUP(Stock!AQ121,2) -> 1.53 | ... AE20: =ROUNDUP(Stock!BJ121,2) -> 1.39
B21: =B63 -> T-TAX-ICE_DST00 | C21: =C63 -> DEMO | D21: =D63 -> pass/vehicle | E21: =ROUND(E20,2) -> 1.49 | F21: =ROUND(F20,2) -> 1.29 | G21: =ROUND(G20,2) -> 1.5 | H21: =ROUND(H20,2) -> 1.5 | I21: =ROUND(I20,2) -> 1.5 | J21: =ROUND(J20,2) -> 1.44 | K21: =ROUND(K20,2) -> 1.52 | L21: =ROUND(L20,2) -> 1.53 | ... AE21: =ROUND(AE20,2) -> 1.39
B22: =B64 -> T-TAX-HEV_GSL00 | C22: =C64 -> DEMO | D22: =D64 -> pass/vehicle | E22: =ROUND(E21,2) -> 1.49 | F22: =ROUND(F21,2) -> 1.29 | G22: =ROUND(G21,2) -> 1.5 | H22: =ROUND(H21,2) -> 1.5 | I22: =ROUND(I21,2) -> 1.5 | J22: =ROUND(J21,2) -> 1.44 | K22: =ROUND(K21,2) -> 1.52 | L22: =ROUND(L21,2) -> 1.53 | ... AE22: =ROUND(AE21,2) -> 1.39
B23: =B65 -> T-BUS-ICE_DST00 | C23: =C65 -> DEMO | D23: =D65 -> pass/vehicle | E23: =ROUNDUP(Stock!AJ122,2) -> 25.43 | F23: =ROUNDUP(Stock!AK122,2) -> 25.16 | G23: =ROUNDUP(Stock!AL122,2) -> 27.31 | H23: =ROUNDUP(Stock!AM122,2) -> 27.89 | I23: =ROUNDUP(Stock!AN122,2) -> 27.94 | J23: =ROUNDUP(Stock!AO122,2) -> 24.86 | K23: =ROUNDUP(Stock!AP122,2) -> 26.39 | L23: =ROUNDUP(Stock!AQ122,2) -> 25.95 | ... AB23: =ROUNDUP(Stock!BG122,2) -> 26.24 | AC23: =E23 -> 25.43 | AD23: =E23 -> 25.43 | AE23: =ROUNDUP(Stock!BJ122,2) -> 27.25
B24: =B66 -> T-LPT-BEV_ELC00 | C24: =C66 -> DEMO | D24: =D66 -> pass/vehicle | E24: =ROUNDUP(Stock!AJ123,2) -> 78.03 | F24: =ROUNDUP(Stock!AK123,2) -> 78.03 | G24: =ROUNDUP(Stock!AL123,2) -> 78.03 | H24: =ROUNDUP(Stock!AM123,2) -> 78.03 | I24: =ROUNDUP(Stock!AN123,2) -> 78.03 | J24: =ROUNDUP(Stock!AO123,2) -> 78.03 | K24: =ROUNDUP(Stock!AP123,2) -> 78.03 | L24: =ROUNDUP(Stock!AQ123,2) -> 78.03 | ... AE24: =ROUNDUP(Stock!BJ123,2) -> 78.03
B25: =B67 -> T-HPT-BEV_ELC00 | C25: =C67 -> DEMO | D25: =D67 -> pass/vehicle | E25: =ROUNDUP(Stock!AJ124,2) -> 120.82 | F25: =ROUNDUP(Stock!AK124,2) -> 214.41 | G25: =ROUNDUP(Stock!AL124,2) -> 57.37 | H25: =ROUNDUP(Stock!AM124,2) -> 214.41 | I25: =ROUNDUP(Stock!AN124,2) -> 214.41 | J25: =ROUNDUP(Stock!AO124,2) -> 214.41 | K25: =ROUNDUP(Stock!AP124,2) -> 214.41 | L25: =ROUNDUP(Stock!AQ124,2) -> 214.41 | ... AE25: =ROUNDUP(Stock!BJ124,2) -> 214.41
B26: =B68 -> T-HPT-ICE_DST00 | C26: =C68 -> DEMO | D26: =D68 -> pass/vehicle | E26: =ROUNDUP(E25,2) -> 120.82 | F26: =ROUNDUP(F25,2) -> 214.41 | G26: =ROUNDUP(G25,2) -> 57.37 | H26: =ROUNDUP(H25,2) -> 214.41 | I26: =ROUNDUP(I25,2) -> 214.41 | J26: =ROUNDUP(J25,2) -> 214.41 | K26: =ROUNDUP(K25,2) -> 214.41 | L26: =ROUNDUP(L25,2) -> 214.41 | ... AE26: =ROUNDUP(AE25,2) -> 214.41
B27: *Goods transport
B28: =B70 -> T-LGT-ICE_GSL00 | C28: =C70 -> DEMO | D28: =D70 -> tonne/vehicle | E28: =ROUNDUP(Demands!C403,3) -> 0.046 | F28: =ROUNDUP(Demands!D403,3) -> 0.044 | G28: =ROUNDUP(Demands!E403,3) -> 0.046 | H28: =ROUNDUP(Demands!F403,3) -> 0.041 | I28: =ROUNDUP(Demands!G403,3) -> 0.057 | J28: =ROUNDUP(Demands!H403,3) -> 0.052 | K28: =ROUNDUP(Demands!I403,3) -> 0.042 | L28: =ROUNDUP(Demands!J403,3) -> 0.049 | ... AE28: =ROUNDUP(Demands!AC403,3) -> 0.03
B29: =B71 -> T-LGT-ICE_DST00 | C29: =C71 -> DEMO | D29: =D71 -> tonne/vehicle | E29: =ROUNDUP(Demands!C403,3) -> 0.046 | F29: =ROUNDUP(Demands!D403,3) -> 0.044 | G29: =ROUNDUP(Demands!E403,3) -> 0.046 | H29: =ROUNDUP(Demands!F403,3) -> 0.041 | I29: =ROUNDUP(Demands!G403,3) -> 0.057 | J29: =ROUNDUP(Demands!H403,3) -> 0.052 | K29: =ROUNDUP(Demands!I403,3) -> 0.042 | L29: =ROUNDUP(Demands!J403,3) -> 0.049 | ... AE29: =ROUNDUP(Demands!AC403,3) -> 0.03
B30: =B72 -> T-MGT-ICE_DST00 | C30: =C72 -> DEMO | D30: =D72 -> tonne/vehicle | E30: =ROUNDUP(Demands!C404,3)*Demands!G694 -> 3.2509 | F30: =ROUNDUP(Demands!D404,3) -> 5.604 | G30: =ROUNDUP(Demands!E404,3) -> 3.834 | H30: =ROUNDUP(Demands!F404,3) -> 4.905 | I30: =ROUNDUP(Demands!G404,3) -> 7.161 | J30: =ROUNDUP(Demands!H404,3) -> 5.617 | K30: =ROUNDUP(Demands!I404,3) -> 4.611 | L30: =ROUNDUP(Demands!J404,3) -> 3.638 | M30: =ROUNDUP(Demands!K404,3) -> 4.439 | ... AE30: =ROUNDUP(Demands!AC404,3) -> 2.796
B31: =B73 -> T-HGT-ICE_DST00 | C31: =C73 -> DEMO | D31: =D73 -> tonne/vehicle | E31: =ROUNDUP(Demands!C405,3)*Demands!G695 -> 8.51424 | F31: =ROUNDUP(Demands!D405,3) -> 11.208 | G31: =ROUNDUP(Demands!E405,3) -> 17.58 | H31: =ROUNDUP(Demands!F405,3) -> 10.245 | I31: =ROUNDUP(Demands!G405,3) -> 9.308 | J31: =ROUNDUP(Demands!H405,3) -> 11.438 | K31: =ROUNDUP(Demands!I405,3) -> 9.005 | L31: =ROUNDUP(Demands!J405,3) -> 11.565 | M31: =ROUNDUP(Demands!K405,3) -> 7.747 | ... AE31: =ROUNDUP(Demands!AC405,3) -> 3.337
B32: =B74 -> T-GTR-ICE_DST00 | C32: =C74 -> DEMO | D32: =D74 -> tonne/vehicle | E32: =ROUNDUP(E74,2) -> 164.84 | F32: =ROUNDUP(F74,2) -> 164.84 | G32: =ROUNDUP(G74,2) -> 164.84 | H32: =ROUNDUP(H74,2) -> 164.84 | I32: =ROUNDUP(I74,2) -> 164.84 | J32: =ROUNDUP(J74,2) -> 164.84 | K32: =ROUNDUP(K74,2) -> 164.84 | L32: =ROUNDUP(L74,2) -> 164.84 | ... AE32: =ROUNDUP(AE74,2) -> 164.84
B48: TechName | C48: CommGrp | D48: *unit | E48: =Stock!G4 -> IE | F48: =Stock!H4 -> IE-CW | G48: =Stock!I4 -> IE-D | H48: =Stock!J4 -> IE-KE | I48: =Stock!K4 -> IE-KK | J48: =Stock!L4 -> IE-LS | K48: =Stock!M4 -> IE-LD | L48: =Stock!N4 -> IE-LH | ... AE48: =Stock!AG4 -> IE-MN
B49: *Passenger transport
B50: =Processes!D6 -> T-WLK_WLK | C50: DEMO | D50: pass/vehicle | E50: 1 | F50: 1 | G50: 1 | H50: 1 | I50: 1 | J50: 1 | K50: 1 | L50: 1 | M50: 1 | N50: 1 | O50: 1 | P50: 1 | Q50: 1 | R50: 1 | S50: 1 | T50: 1 | U50: 1 | V50: 1 | W50: 1 | X50: 1 | Y50: 1 | Z50: 1 | AA50: 1 | AB50: 1 | AC50: 1 | AD50: 1 | AE50: 1
B51: =Processes!D7 -> T-CYC_CYC | C51: DEMO | D51: pass/vehicle | E51: 1 | F51: 1 | G51: 1 | H51: 1 | I51: 1 | J51: 1 | K51: 1 | L51: 1 | M51: 1 | N51: 1 | O51: 1 | P51: 1 | Q51: 1 | R51: 1 | S51: 1 | T51: 1 | U51: 1 | V51: 1 | W51: 1 | X51: 1 | Y51: 1 | Z51: 1 | AA51: 1 | AB51: 1 | AC51: 1 | AD51: 1 | AE51: 1
B52: =Processes!D9 -> T-MOT-ICE_GSL00 | C52: DEMO | D52: pass/vehicle | E52: 1.1 | F52: =E52 -> 1.1 | G52: =F52 -> 1.1 | H52: =G52 -> 1.1 | I52: =H52 -> 1.1 | J52: =I52 -> 1.1 | K52: =J52 -> 1.1 | L52: =K52 -> 1.1 | M52: =L52 -> 1.1 | ... AE52: =AD52 -> 1.1
B53: =Processes!D11 -> T-CAR-ICE_GSL00 | C53: DEMO | D53: pass/vehicle | E53: =N95 -> 1.4920115 | F53: =E53 -> 1.4920115 | G53: =F53 -> 1.4920115 | H53: =G53 -> 1.4920115 | I53: =H53 -> 1.4920115 | J53: =I53 -> 1.4920115 | K53: =J53 -> 1.4920115 | L53: =K53 -> 1.4920115 | M53: =L53 -> 1.4920115 | ... AE53: =AD53 -> 1.4920115
B54: =Processes!D12 -> T-CAR-ICE_DST00 | C54: DEMO | D54: pass/vehicle | E54: =N95 -> 1.4920115 | F54: =E54 -> 1.4920115 | G54: =F54 -> 1.4920115 | H54: =G54 -> 1.4920115 | I54: =H54 -> 1.4920115 | J54: =I54 -> 1.4920115 | K54: =J54 -> 1.4920115 | L54: =K54 -> 1.4920115 | M54: =L54 -> 1.4920115 | ... AE54: =AD54 -> 1.4920115
B55: =Processes!D13 -> T-CAR-ICE_DF00 | C55: DEMO | D55: pass/vehicle | E55: =N95 -> 1.4920115 | F55: =E55 -> 1.4920115 | G55: =F55 -> 1.4920115 | H55: =G55 -> 1.4920115 | I55: =H55 -> 1.4920115 | J55: =I55 -> 1.4920115 | K55: =J55 -> 1.4920115 | L55: =K55 -> 1.4920115 | M55: =L55 -> 1.4920115 | ... AE55: =AD55 -> 1.4920115
B56: =Processes!D14 -> T-CAR-ICE_E8500 | C56: DEMO | D56: pass/vehicle | E56: =N95 -> 1.4920115 | F56: =E56 -> 1.4920115 | G56: =F56 -> 1.4920115 | H56: =G56 -> 1.4920115 | I56: =H56 -> 1.4920115 | J56: =I56 -> 1.4920115 | K56: =J56 -> 1.4920115 | L56: =K56 -> 1.4920115 | M56: =L56 -> 1.4920115 | ... AE56: =AD56 -> 1.4920115
B57: =Processes!D15 -> T-CAR-HEV_GSL00 | C57: DEMO | D57: pass/vehicle | E57: =N95 -> 1.4920115 | F57: =E57 -> 1.4920115 | G57: =F57 -> 1.4920115 | H57: =G57 -> 1.4920115 | I57: =H57 -> 1.4920115 | J57: =I57 -> 1.4920115 | K57: =J57 -> 1.4920115 | L57: =K57 -> 1.4920115 | M57: =L57 -> 1.4920115 | ... AE57: =AD57 -> 1.4920115
B58: =Processes!D16 -> T-CAR-HEV_DST00 | C58: DEMO | D58: pass/vehicle | E58: =N95 -> 1.4920115 | F58: =E58 -> 1.4920115 | G58: =F58 -> 1.4920115 | H58: =G58 -> 1.4920115 | I58: =H58 -> 1.4920115 | J58: =I58 -> 1.4920115 | K58: =J58 -> 1.4920115 | L58: =K58 -> 1.4920115 | M58: =L58 -> 1.4920115 | ... AE58: =AD58 -> 1.4920115
B59: =Processes!D17 -> T-CAR-PHEV_GSL00 | C59: DEMO | D59: pass/vehicle | E59: =N95 -> 1.4920115 | F59: =E59 -> 1.4920115 | G59: =F59 -> 1.4920115 | H59: =G59 -> 1.4920115 | I59: =H59 -> 1.4920115 | J59: =I59 -> 1.4920115 | K59: =J59 -> 1.4920115 | L59: =K59 -> 1.4920115 | M59: =L59 -> 1.4920115 | ... AE59: =AD59 -> 1.4920115
B60: =Processes!D18 -> T-CAR-PHEV_DST00 | C60: DEMO | D60: pass/vehicle | E60: =N95 -> 1.4920115 | F60: =E60 -> 1.4920115 | G60: =F60 -> 1.4920115 | H60: =G60 -> 1.4920115 | I60: =H60 -> 1.4920115 | J60: =I60 -> 1.4920115 | K60: =J60 -> 1.4920115 | L60: =K60 -> 1.4920115 | M60: =L60 -> 1.4920115 | ... AE60: =AD60 -> 1.4920115
B61: =Processes!D19 -> T-CAR-BEV_ELC00 | C61: DEMO | D61: pass/vehicle | E61: =N95 -> 1.4920115 | F61: =E61 -> 1.4920115 | G61: =F61 -> 1.4920115 | H61: =G61 -> 1.4920115 | I61: =H61 -> 1.4920115 | J61: =I61 -> 1.4920115 | K61: =J61 -> 1.4920115 | L61: =K61 -> 1.4920115 | M61: =L61 -> 1.4920115 | ... AE61: =AD61 -> 1.4920115
B62: =Processes!D21 -> T-TAX-ICE_GSL00 | C62: DEMO | D62: pass/vehicle | E62: =N95 -> 1.4920115 | F62: =E62 -> 1.4920115 | G62: =F62 -> 1.4920115 | H62: =G62 -> 1.4920115 | I62: =H62 -> 1.4920115 | J62: =I62 -> 1.4920115 | K62: =J62 -> 1.4920115 | L62: =K62 -> 1.4920115 | M62: =L62 -> 1.4920115 | ... AE62: =AD62 -> 1.4920115
B63: =Processes!D22 -> T-TAX-ICE_DST00 | C63: DEMO | D63: pass/vehicle | E63: =N95 -> 1.4920115 | F63: =E63 -> 1.4920115 | G63: =F63 -> 1.4920115 | H63: =G63 -> 1.4920115 | I63: =H63 -> 1.4920115 | J63: =I63 -> 1.4920115 | K63: =J63 -> 1.4920115 | L63: =K63 -> 1.4920115 | M63: =L63 -> 1.4920115 | ... AE63: =AD63 -> 1.4920115
B64: =Processes!D23 -> T-TAX-HEV_GSL00 | C64: DEMO | D64: pass/vehicle | E64: =N95 -> 1.4920115 | F64: =E64 -> 1.4920115 | G64: =F64 -> 1.4920115 | H64: =G64 -> 1.4920115 | I64: =H64 -> 1.4920115 | J64: =I64 -> 1.4920115 | K64: =J64 -> 1.4920115 | L64: =K64 -> 1.4920115 | M64: =L64 -> 1.4920115 | ... AE64: =AD64 -> 1.4920115
B65: =Processes!D25 -> T-BUS-ICE_DST00 | C65: DEMO | D65: pass/vehicle | E65: 27.25 | F65: =E65 -> 27.25 | G65: =F65 -> 27.25 | H65: =G65 -> 27.25 | I65: =H65 -> 27.25 | J65: =I65 -> 27.25 | K65: =J65 -> 27.25 | L65: =K65 -> 27.25 | M65: =L65 -> 27.25 | ... AE65: =AD65 -> 27.25
B66: =Processes!D27 -> T-LPT-BEV_ELC00 | C66: DEMO | D66: pass/vehicle | E66: =C113 -> 78.019401 | F66: 0 | G66: =E66 -> 78.019401 | H66: =F66 -> 0 | I66: =H66 -> 0 | J66: =I66 -> 0 | K66: =J66 -> 0 | L66: =K66 -> 0 | M66: =L66 -> 0 | N66: =M66 -> 0 | O66: =N66 -> 0 | P66: =O66 -> 0 | ... AE66: =AD66 -> 0
B67: =Processes!D28 -> T-HPT-BEV_ELC00 | C67: DEMO | D67: pass/vehicle | E67: =E66 -> 78.019401 | F67: =E67 -> 78.019401 | G67: =F67 -> 78.019401 | H67: =G67 -> 78.019401 | I67: =H67 -> 78.019401 | J67: =I67 -> 78.019401 | K67: =J67 -> 78.019401 | L67: =K67 -> 78.019401 | M67: =L67 -> 78.019401 | ... AE67: =AD67 -> 78.019401
B68: =Processes!D29 -> T-HPT-ICE_DST00 | C68: DEMO | D68: pass/vehicle | E68: 120 | F68: =E68 -> 120 | G68: =F68 -> 120 | H68: =G68 -> 120 | I68: =H68 -> 120 | J68: =I68 -> 120 | K68: =J68 -> 120 | L68: =K68 -> 120 | M68: =L68 -> 120 | ... AE68: =AD68 -> 120
B69: *Goods transport
B70: =Processes!D32 -> T-LGT-ICE_GSL00 | C70: DEMO | D70: tonne/vehicle | E70: 0.043 | F70: =E70 -> 0.043 | G70: =F70 -> 0.043 | H70: =G70 -> 0.043 | I70: =H70 -> 0.043 | J70: =I70 -> 0.043 | K70: =J70 -> 0.043 | L70: =K70 -> 0.043 | M70: =L70 -> 0.043 | ... AE70: =AD70 -> 0.043
B71: =Processes!D33 -> T-LGT-ICE_DST00 | C71: DEMO | D71: tonne/vehicle | E71: 0.043 | F71: =E71 -> 0.043 | G71: =F71 -> 0.043 | H71: =G71 -> 0.043 | I71: =H71 -> 0.043 | J71: =I71 -> 0.043 | K71: =J71 -> 0.043 | L71: =K71 -> 0.043 | M71: =L71 -> 0.043 | ... AE71: =AD71 -> 0.043
B72: =Processes!D34 -> T-MGT-ICE_DST00 | C72: DEMO | D72: tonne/vehicle | E72: 3.513 | F72: =E72 -> 3.513 | G72: =F72 -> 3.513 | H72: =G72 -> 3.513 | I72: =H72 -> 3.513 | J72: =I72 -> 3.513 | K72: =J72 -> 3.513 | L72: =K72 -> 3.513 | M72: =L72 -> 3.513 | ... AE72: =AD72 -> 3.513
B73: =Processes!D35 -> T-HGT-ICE_DST00 | C73: DEMO | D73: tonne/vehicle | E73: 9.168 | F73: =E73 -> 9.168 | G73: =F73 -> 9.168 | H73: =G73 -> 9.168 | I73: =H73 -> 9.168 | J73: =I73 -> 9.168 | K73: =J73 -> 9.168 | L73: =K73 -> 9.168 | M73: =L73 -> 9.168 | ... AE73: =AD73 -> 9.168
B74: =Processes!D36 -> T-GTR-ICE_DST00 | C74: DEMO | D74: tonne/vehicle | E74: 164.83335 | F74: =E74 -> 164.83335 | G74: =F74 -> 164.83335 | H74: =G74 -> 164.83335 | I74: =H74 -> 164.83335 | J74: =I74 -> 164.83335 | K74: =J74 -> 164.83335 | L74: =K74 -> 164.83335 | M74: =L74 -> 164.83335 | ... AE74: =AD74 -> 164.83335
B76: Source:
B77: 1. Vehicle ocupancy rate for private cars and small public services estimated based on table below.
B78: 2. Vehicle ocupancy rate for other passenger cars adopted from JRC_EU_TIMES model
B79: 3. Vehicle tannage for road vehicles is dopted from CSO and for Rail is adopted from Irish TIMES 2.0
B80: 4. For LUAS passenger kilometer is divided by vehicle kilometer.
B91: Vehicle Occupancy Rates, by Flow Group and Time Modes
D92: Weekday | H92: Weekend
D93: 1 | E93: 2 | F93: 3 | G93: 4 | H93: 6 | I93: 7 | J93: 8 | K93: 9 | M93: Average Occupancy Rate for cars
C94: No. of Hours | D94: 2540 | E94: 2680 | F94: 522 | G94: 522 | H94: 1300 | I94: 780 | J94: 208 | K94: 208 | M94: Total Hours | N94: =SUM(D94:K94) -> 8760
C95: Time of Day | D95: Overnight Off-Peak | E95: Daytime Off-Peak | F95: Adjacent to Peak | G95: Peak | H95: Overnight Off-Peak | I95: Daytime Off-Peak | J95: Adjacent to Peak | K95: Peak | M95: Average | N95: =((D94/N94)*D102)+((E94/N94)*E102)+((F94/N94)*F102)+((G94/N94)*G102)+((H94/N94)*H102)+((I94/N94)*I102)+((J94/N94)*J102)+((K94/N94)*K102) -> 1.4920115
B96: Work | C96: Occupancy Rate | D96: 1.24 | E96: 1.25 | F96: 1.26 | G96: 1.26 | H96: 1.33 | I96: 1.34 | J96: 1.38 | K96: 1.38
C97: Proportions | D97: 0.103 | E97: 0.169 | F97: 0.133 | G97: 0.12 | H97: 0.045 | I97: 0.018 | J97: 0.027 | K97: 0.027
B98: Commuting | C98: Occupancy Rate | D98: 1.21 | E98: 1.22 | F98: 1.23 | G98: 1.23 | H98: 1.2 | I98: 1.23 | J98: 1.22 | K98: 1.22
C99: Proportions | D99: 0.422 | E99: 0.367 | F99: 0.442 | G99: 0.429 | H99: 0.242 | I99: 0.079 | J99: 0.065 | K99: 0.065
B100: Other-non Work | C100: Occupancy Rate | D100: 1.64 | E100: 1.65 | F100: 1.66 | G100: 1.68 | H100: 1.7 | I100: 1.83 | J100: 1.85 | K100: 1.85
C101: Proportions | D101: 0.475 | E101: 0.464 | F101: 0.425 | G101: 0.451 | H101: 0.713 | I101: 0.903 | J101: 0.909 | K101: 0.909
B102: All | C102: Occupancy Rate | D102: =(D96*D97)+(D98*D99)+(D100*D101) -> 1.41734 | E102: =(E96*E97)+(E98*E99)+(E100*E101) -> 1.42459 | F102: =(F96*F97)+(F98*F99)+(F100*F101) -> 1.41674 | G102: =(G96*G97)+(G98*G99)+(G100*G101) -> 1.43655 | H102: =(H96*H97)+(H98*H99)+(H100*H101) -> 1.56235 | I102: =(I96*I97)+(I98*I99)+(I100*I101) -> 1.77378 | J102: =(J96*J97)+(J98*J99)+(J100*J101) -> 1.79821 | K102: =(K96*K97)+(K98*K99)+(K100*K101) -> 1.79821
B103: Source: Project Appraisal Guidelines for National Roads Unit 6.11 -National Parameters Values Sheet, TII publication, Oct. 2016.
B109: Luas infrastructure, 2018
C110: LUAS lines
B111: Vehicle kilometres | C111: =Demands!B126+Demands!C126 -> 4065479
B112: Passenger kilometres | C112: =Demands!B127+Demands!C127 -> 317186237
B113: Passenger/vehicle | C113: =C112/C111 -> 78.019401
B114: Source: Transport Infrastructure Ireland, https://www.cso.ie/en/releasesandpublications/ep/p-tranom/transportomnibus2018/publictransport/

Sheet Demands
A2: ~FI_T: Demand
A3: CommName | B3: *Unit | C3: =Regions!C3 -> IE | D3: =Regions!E3 -> IE-CW | E3: =Regions!F3 -> IE-D | F3: =Regions!G3 -> IE-KE | G3: =Regions!H3 -> IE-KK | H3: =Regions!I3 -> IE-LS | I3: =Regions!J3 -> IE-LD | J3: =Regions!K3 -> IE-LH | K3: =Regions!L3 -> IE-MH | ... AC3: =Regions!AD3 -> IE-MN
A4: =Commodities!C25 -> TRAPS | B4: =Commodities!E25 -> Bpkm | C4: =C323/1000 -> 14.556561 | D4: =D323/1000 -> 0.19075815 | E4: =E323/1000 -> 3.8137078 | F4: =F323/1000 -> 0.70334338 | G4: =G323/1000 -> 0.32630593 | H4: =H323/1000 -> 0.25725946 | I4: =I323/1000 -> 0.12926411 | J4: =J323/1000 -> 0.37066642 | ... AC4: =AC323/1000 -> 0.20769619
A5: =Commodities!C26 -> TRAPM | B5: =Commodities!E26 -> Bpkm | C5: =C337/1000 -> 31.276119 | D5: =D337/1000 -> 0.43519149 | E5: =E337/1000 -> 7.6211536 | F5: =F337/1000 -> 1.5519094 | G5: =G337/1000 -> 0.73703192 | H5: =H337/1000 -> 0.55451714 | I5: =I337/1000 -> 0.28568437 | J5: =J337/1000 -> 0.76950577 | ... AC5: =AC337/1000 -> 0.47664625
A6: =Commodities!C27 -> TRAPL | B6: =Commodities!E27 -> Bpkm | C6: =C351/1000 -> 27.131578 | D6: =D351/1000 -> 0.37389749 | E6: =E351/1000 -> 6.6607449 | F6: =F351/1000 -> 1.3457958 | G6: =G351/1000 -> 0.64805463 | H6: =H351/1000 -> 0.48149947 | I6: =I351/1000 -> 0.24792998 | J6: =J351/1000 -> 0.67368746 | ... AC6: =AC351/1000 -> 0.42809299
A7: =Commodities!C28 -> TRAF | B7: =Commodities!E28 -> Btkm | C7: =0.92*(C479/1000)+C18 -> 10.702591 | D7: =(D479/1000)+D18 -> 0.177941 | E7: =(E479/1000)+E18 -> 2.6576908 | F7: =(F479/1000)+F18 -> 0.48228404 | G7: =(G479/1000)+G18 -> 0.31014967 | H7: =(H479/1000)+H18 -> 0.22090468 | I7: =(I479/1000)+I18 -> 0.10660398 | J7: =(J479/1000)+J18 -> 0.27935991 | K7: =(K479/1000)+K18 -> 0.43225128 | ... AC7: =(AC479/1000)+AC18 -> 0.15458274
A8: =Commodities!C29 -> TTURS | B8: =Commodities!E29 -> PJ | C8: =C619 -> 7.7105748 | D8: =D619 -> 0.092186243 | E8: =E619 -> 2.1816898 | F8: =F619 -> 0.36028609 | G8: =G619 -> 0.16067985 | H8: =H619 -> 0.13714428 | I8: =I619 -> 0.066182961 | J8: =J619 -> 0.20869339 | ... AC8: =AC619 -> 0.099398313
A9: =Commodities!C30 -> TNAV | B9: =Commodities!E30 -> PJ | C9: =C620 -> 3.5132998 | D9: =D620 -> 0.04200438 | E9: =E620 -> 0.99408029 | F9: =F620 -> 0.16416326 | G9: =G620 -> 0.073213282 | H9: =H620 -> 0.062489372 | I9: =I620 -> 0.030156063 | J9: =J620 -> 0.095090502 | ... AC9: =AC620 -> 0.045290537
A10: =Commodities!C31 -> TOTH | B10: =Commodities!E31 -> PJ | C10: =C621 -> 20.831455 | D10: =D621 -> 0.24905712 | E10: =E621 -> 5.8942134 | F10: =F621 -> 0.97337536 | G10: =G621 -> 0.43410448 | H10: =H621 -> 0.37051906 | I10: =I621 -> 0.17880474 | J10: =J621 -> 0.56382137 | ... AC10: =AC621 -> 0.26854178
A11: =Commodities!C32 -> TAVIDOM | B11: =Commodities!E32 -> PJ | C11: =C632 -> 0.2334932 | D11: =D632 -> 0 | E11: =E632 -> 0.13599128 | F11: =F632 -> 0 | G11: =G632 -> 0 | H11: =H632 -> 0 | I11: =I632 -> 0 | J11: =J632 -> 0 | ... AC11: =AC632 -> 0
A12: =Commodities!C33 -> TAVIINT | B12: =Commodities!E33 -> PJ | C12: =C633 -> 45.968364 | D12: =D633 -> 0 | E12: =E633 -> 40.440163 | F12: =F633 -> 0 | G12: =G633 -> 0 | H12: =H633 -> 0 | I12: =I633 -> 0 | J12: =J633 -> 0 | ... AC12: =AC633 -> 0
A16: Freight by rail
A17: CommName | B17: *Unit | C17: =C3 -> IE | D17: =D3 -> IE-CW | E17: =E3 -> IE-D | F17: =F3 -> IE-KE | G17: =G3 -> IE-KK | H17: =H3 -> IE-LS | I17: =I3 -> IE-LD | J17: =J3 -> IE-LH | ... AC17: =AC3 -> IE-MN
B18: Btkm | C18: =G535/1000000 -> 0.088551 | D18: 0 | E18: =C18*Stock!D317 -> 0.028462821 | F18: 0 | G18: 0 | H18: 0 | I18: 0 | J18: 0 | K18: =C18*Stock!F317 -> 0.0094876071 | L18: 0 | M18: 0 | N18: 0 | O18: 0 | P18: 0 | Q18: 0 | R18: 0 | S18: 0 | T18: 0 | U18: =C18*Stock!E317 -> 0.015812679 | V18: 0 | W18: 0 | X18: =C18*Stock!C317 -> 0.034787893 | Y18: 0 | Z18: 0 | AA18: 0 | AB18: 0 | AC18: 0
A22: Share of distance range class in passenger transport
A23: Range class | B23: Distance | C23: =Regions!C3 -> IE | D23: =Regions!E3 -> IE-CW | E23: =Regions!F3 -> IE-D | F23: =Regions!G3 -> IE-KE | G23: =Regions!H3 -> IE-KK | H23: =Regions!I3 -> IE-LS | I23: =Regions!J3 -> IE-LD | J23: =Regions!K3 -> IE-LH | K23: =Regions!L3 -> IE-MH | ... AC23: =Regions!AD3 -> IE-MN
A24: Short-range | B24: <5km | C24: =C4/SUM(C4:C6) -> 0.19950263 | D24: =D4/SUM(D4:D6) -> 0.19078732 | E24: =E4/SUM(E4:E6) -> 0.21075325 | F24: =F4/SUM(F4:F6) -> 0.19531627 | G24: =G4/SUM(G4:G6) -> 0.19066692 | H24: =H4/SUM(H4:H6) -> 0.19892076 | I24: =I4/SUM(I4:I6) -> 0.19500423 | J24: =J4/SUM(J4:J6) -> 0.20435232 | ... AC24: =AC4/SUM(AC4:AC6) -> 0.18670404
A25: Medium-range | B25: 5-30 km | C25: =C5/SUM(C4:C6) -> 0.42864986 | D25: =D5/SUM(D4:D6) -> 0.43525803 | E25: =E5/SUM(E4:E6) -> 0.42116045 | F25: =F5/SUM(F4:F6) -> 0.43096042 | G25: =G5/SUM(G4:G6) -> 0.43066212 | H25: =H5/SUM(H4:H6) -> 0.42876935 | I25: =I5/SUM(I4:I6) -> 0.43097549 | J25: =J5/SUM(J4:J6) -> 0.42423667 | ... AC25: =AC5/SUM(AC4:AC6) -> 0.42847094
A26: Long-range | B26: >30 km | C26: =C6/SUM(C4:C6) -> 0.37184751 | D26: =D6/SUM(D4:D6) -> 0.37395465 | E26: =E6/SUM(E4:E6) -> 0.36808631 | F26: =F6/SUM(F4:F6) -> 0.37372331 | G26: =G6/SUM(G4:G6) -> 0.37867096 | H26: =H6/SUM(H4:H6) -> 0.37230989 | I26: =I6/SUM(I4:I6) -> 0.37402027 | J26: =J6/SUM(J4:J6) -> 0.37141102 | ... AC26: =AC6/SUM(AC4:AC6) -> 0.38482502
A27: Total | B27: - | C27: =SUM(C24:C26) -> 1 | D27: =SUM(D24:D26) -> 1 | E27: =SUM(E24:E26) -> 1 | F27: =SUM(F24:F26) -> 1 | G27: =SUM(G24:G26) -> 1 | H27: =SUM(H24:H26) -> 1 | I27: =SUM(I24:I26) -> 1 | J27: =SUM(J24:J26) -> 1 | ... AC27: =SUM(AC24:AC26) -> 1
A31: Share of transport modes in short-range passenger demand in 2018
A32: Modes | B32: Transport type | C32: =Regions!C3 -> IE | D32: =Regions!E3 -> IE-CW | E32: =Regions!F3 -> IE-D | F32: =Regions!G3 -> IE-KE | G32: =Regions!H3 -> IE-KK | H32: =Regions!I3 -> IE-LS | I32: =Regions!J3 -> IE-LD | J32: =Regions!K3 -> IE-LH | K32: =Regions!L3 -> IE-MH | ... AC32: =Regions!AD3 -> IE-MN
A33: Non-motorized | B33: Walk | C33: =C315/C$323 -> 0.32377984 | D33: =D315/D$323 -> 0.29539616 | E33: =E315/E$323 -> 0.34967729 | F33: =F315/F$323 -> 0.3131136 | G33: =G315/G$323 -> 0.30099431 | H33: =H315/H$323 -> 0.32585784 | I33: =I315/I$323 -> 0.3129609 | J33: =J315/J$323 -> 0.3441496 | ... AC33: =AC315/AC$323 -> 0.29253128
B34: Bike | C34: =C316/C$323 -> 0.053963306 | D34: =D316/D$323 -> 0.049232693 | E34: =E316/E$323 -> 0.058279548 | F34: =F316/F$323 -> 0.0521856 | G34: =G316/G$323 -> 0.050165718 | H34: =H316/H$323 -> 0.054309641 | I34: =I316/I$323 -> 0.052160149 | J34: =J316/J$323 -> 0.057358267 | ... AC34: =AC316/AC$323 -> 0.048755214
A35: Private | B35: 2-wheelers | C35: =C317/C$323 -> 0.0012024577 | D35: =D317/D$323 -> 0.00084181954 | E35: =E317/E$323 -> 0.0014316393 | F35: =F317/F$323 -> 0.0013698908 | G35: =G317/G$323 -> 0.00098425389 | H35: =H317/H$323 -> 0.00062421005 | I35: =I317/I$323 -> 0.0012422934 | J35: =J317/J$323 -> 0.00086646068 | ... AC35: =AC317/AC$323 -> 0.00077316749
B36: LDV | C36: =C318/C$323 -> 0.5142169 | D36: =D318/D$323 -> 0.57696936 | E36: =E318/E$323 -> 0.4152164 | F36: =F318/F$323 -> 0.53837412 | G36: =G318/G$323 -> 0.52730359 | H36: =H318/H$323 -> 0.5442819 | I36: =I318/I$323 -> 0.54724419 | J36: =J318/J$323 -> 0.50629481 | ... AC36: =AC318/AC$323 -> 0.49285227
A37: Public | B37: Taxis | C37: =C319/C$323 -> 0.016399604 | D37: =D319/D$323 -> 0.0074490308 | E37: =E319/E$323 -> 0.032043055 | F37: =F319/F$323 -> 0.014142087 | G37: =G319/G$323 -> 0.007838454 | H37: =H319/H$323 -> 0.009942235 | I37: =I319/I$323 -> 0.0087941712 | J37: =J319/J$323 -> 0.019167684 | ... AC37: =AC319/AC$323 -> 0.0041049285
B38: BUS | C38: =C320/C$323 -> 0.082740996 | D38: =D320/D$323 -> 0.070110938 | E38: =E320/E$323 -> 0.11397375 | F38: =F320/F$323 -> 0.080814709 | G38: =G320/G$323 -> 0.11271368 | H38: =H320/H$323 -> 0.064984165 | I38: =I320/I$323 -> 0.0775983 | J38: =J320/J$323 -> 0.072163176 | ... AC38: =AC320/AC$323 -> 0.16098313
B39: Light rail (LUAS) | C39: =C321/C$323 -> 0.0076968955 | D39: =D321/D$323 -> 0 | E39: =E321/E$323 -> 0.02937832 | F39: =F321/F$323 -> 0 | G39: =G321/G$323 -> 0 | H39: =H321/H$323 -> 0 | I39: =I321/I$323 -> 0 | J39: =J321/J$323 -> 0 | ... AC39: =AC321/AC$323 -> 0
B40: Train | C40: 0 | D40: 0 | E40: 0 | F40: 0 | G40: 0 | H40: 0 | I40: 0 | J40: 0 | K40: 0 | L40: 0 | M40: 0 | N40: 0 | O40: 0 | P40: 0 | Q40: 0 | R40: 0 | S40: 0 | T40: 0 | U40: 0 | V40: 0 | W40: 0 | X40: 0 | Y40: 0 | Z40: 0 | AA40: 0 | AB40: 0 | AC40: 0
B41: TOTAL | C41: =SUM(C33:C40) -> 1 | D41: =SUM(D33:D40) -> 1 | E41: =SUM(E33:E40) -> 1 | F41: =SUM(F33:F40) -> 1 | G41: =SUM(G33:G40) -> 1 | H41: =SUM(H33:H40) -> 1 | I41: =SUM(I33:I40) -> 1 | J41: =SUM(J33:J40) -> 1 | ... AC41: =SUM(AC33:AC40) -> 1
A45: Share of transport modes in medium-range passenger demand in 2018
A46: Modes | B46: Transport type | C46: =Regions!C3 -> IE | D46: =Regions!E3 -> IE-CW | E46: =Regions!F3 -> IE-D | F46: =Regions!G3 -> IE-KE | G46: =Regions!H3 -> IE-KK | H46: =Regions!I3 -> IE-LS | I46: =Regions!J3 -> IE-LD | J46: =Regions!K3 -> IE-LH | K46: =Regions!L3 -> IE-MH | ... AC46: =Regions!AD3 -> IE-MN
A47: Non-motorized | B47: Walk | C47: =C329/C$337 -> 0 | D47: =D329/D$337 -> 0 | E47: =E329/E$337 -> 0 | F47: =F329/F$337 -> 0 | G47: =G329/G$337 -> 0 | H47: =H329/H$337 -> 0 | I47: =I329/I$337 -> 0 | J47: =J329/J$337 -> 0 | ... AC47: =AC329/AC$337 -> 0
B48: Bike | C48: =C330/C$337 -> 0 | D48: =D330/D$337 -> 0 | E48: =E330/E$337 -> 0 | F48: =F330/F$337 -> 0 | G48: =G330/G$337 -> 0 | H48: =H330/H$337 -> 0 | I48: =I330/I$337 -> 0 | J48: =J330/J$337 -> 0 | ... AC48: =AC330/AC$337 -> 0
A49: Private | B49: 2-wheelers | C49: =C331/C$337 -> 0.0032739469 | D49: =D331/D$337 -> 0.0021586269 | E49: =E331/E$337 -> 0.0041909857 | F49: =F331/F$337 -> 0.0036319752 | G49: =G331/G$337 -> 0.0025491869 | H49: =H331/H$337 -> 0.0016941155 | I49: =I331/I$337 -> 0.0032883005 | J49: =J331/J$337 -> 0.0024416089 | ... AC49: =AC331/AC$337 -> 0.0019708873
B50: LDV | C50: =C332/C$337 -> 0.83405572 | D50: =D332/D$337 -> 0.88136996 | E50: =E332/E$337 -> 0.72410905 | F50: =F332/F$337 -> 0.85033098 | G50: =G332/G$337 -> 0.8135836 | H50: =H332/H$337 -> 0.88000079 | I50: =I332/I$337 -> 0.86292968 | J50: =J332/J$337 -> 0.84991917 | ... AC50: =AC332/AC$337 -> 0.74843121
A51: Public | B51: Taxis | C51: =C333/C$337 -> 0.021905905 | D51: =D333/D$337 -> 0.0093709663 | E51: =E333/E$337 -> 0.046019565 | F51: =F333/F$337 -> 0.018394859 | G51: =G333/G$337 -> 0.0099598084 | H51: =H333/H$337 -> 0.013237998 | I51: =I333/I$337 -> 0.011420057 | J51: =J333/J$337 -> 0.026498598 | ... AC51: =AC333/AC$337 -> 0.0051335742
B52: BUS | C52: =C334/C$337 -> 0.13420524 | D52: =D334/D$337 -> 0.10710044 | E52: =E334/E$337 -> 0.19876244 | F52: =F334/F$337 -> 0.12764219 | G52: =G334/G$337 -> 0.1739074 | H52: =H334/H$337 -> 0.10506709 | I52: =I334/I$337 -> 0.12236197 | J52: =J334/J$337 -> 0.12114062 | ... AC52: =AC334/AC$337 -> 0.24446433
B53: Light rail (LUAS) | C53: =C335/C$337 -> 0.0065591869 | D53: =D335/D$337 -> 0 | E53: =E335/E$337 -> 0.02691796 | F53: =F335/F$337 -> 0 | G53: =G335/G$337 -> 0 | H53: =H335/H$337 -> 0 | I53: =I335/I$337 -> 0 | J53: =J335/J$337 -> 0 | ... AC53: =AC335/AC$337 -> 0
B54: Train | C54: =C336/C$337 -> 0 | D54: =D336/D$337 -> 0 | E54: =E336/E$337 -> 0 | F54: =F336/F$337 -> 0 | G54: =G336/G$337 -> 0 | H54: =H336/H$337 -> 0 | I54: =I336/I$337 -> 0 | J54: =J336/J$337 -> 0 | ... AC54: =AC336/AC$337 -> 0
B55: TOTAL | C55: =SUM(C47:C54) -> 1 | D55: =SUM(D47:D54) -> 1 | E55: =SUM(E47:E54) -> 1 | F55: =SUM(F47:F54) -> 1 | G55: =SUM(G47:G54) -> 1 | H55: =SUM(H47:H54) -> 1 | I55: =SUM(I47:I54) -> 1 | J55: =SUM(J47:J54) -> 1 | ... AC55: =SUM(AC47:AC54) -> 1
A59: Share of transport modes in long-range passenger demand in 2018
A60: Modes | B60: Transport type | C60: =Regions!C3 -> IE | D60: =Regions!E3 -> IE-CW | E60: =Regions!F3 -> IE-D | F60: =Regions!G3 -> IE-KE | G60: =Regions!H3 -> IE-KK | H60: =Regions!I3 -> IE-LS | I60: =Regions!J3 -> IE-LD | J60: =Regions!K3 -> IE-LH | K60: =Regions!L3 -> IE-MH | ... AC60: =Regions!AD3 -> IE-MN
A61: Non-motorized | B61: Walk | C61: =C343/C$351 -> 0 | D61: =D343/D$351 -> 0 | E61: =E343/E$351 -> 0 | F61: =F343/F$351 -> 0 | G61: =G343/G$351 -> 0 | H61: =H343/H$351 -> 0 | I61: =I343/I$351 -> 0 | J61: =J343/J$351 -> 0 | ... AC61: =AC343/AC$351 -> 0
B62: Bike | C62: =C344/C$351 -> 0 | D62: =D344/D$351 -> 0 | E62: =E344/E$351 -> 0 | F62: =F344/F$351 -> 0 | G62: =G344/G$351 -> 0 | H62: =H344/H$351 -> 0 | I62: =I344/I$351 -> 0 | J62: =J344/J$351 -> 0 | ... AC62: =AC344/AC$351 -> 0
A63: Private | B63: 2-wheelers | C63: =C345/C$351 -> 0 | D63: =D345/D$351 -> 0 | E63: =E345/E$351 -> 0 | F63: =F345/F$351 -> 0 | G63: =G345/G$351 -> 0 | H63: =H345/H$351 -> 0 | I63: =I345/I$351 -> 0 | J63: =J345/J$351 -> 0 | ... AC63: =AC345/AC$351 -> 0
B64: LDV | C64: =C346/C$351 -> 0.7410864 | D64: =D346/D$351 -> 0.79071881 | E64: =E346/E$351 -> 0.63861316 | F64: =F346/F$351 -> 0.75580744 | G64: =G346/G$351 -> 0.71320246 | H64: =H346/H$351 -> 0.78115676 | I64: =I346/I$351 -> 0.7664235 | J64: =J346/J$351 -> 0.74828496 | ... AC64: =AC346/AC$351 -> 0.64231184
A65: Public | B65: Taxis | C65: =C347/C$351 -> 0.012142167 | D65: =D347/D$351 -> 0.0052445644 | E65: =E347/E$351 -> 0.025318479 | F65: =F347/F$351 -> 0.010199546 | G65: =G347/G$351 -> 0.005446567 | H65: =H347/H$351 -> 0.0073305854 | I65: =I347/I$351 -> 0.0063273652 | J65: =J347/J$351 -> 0.014553703 | ... AC65: =AC347/AC$351 -> 0.0027483694
B66: BUS | C66: =C348/C$351 -> 0.1626966 | D66: =D348/D$351 -> 0.13109627 | E66: =E348/E$351 -> 0.2391682 | F66: =F348/F$351 -> 0.15479347 | G66: =G348/G$351 -> 0.20800029 | H66: =H348/H$351 -> 0.12724979 | I66: =I348/I$351 -> 0.14827744 | J66: =J348/J$351 -> 0.14551722 | ... AC66: =AC348/AC$351 -> 0.28624952
B67: Light rail (LUAS) | C67: =C349/C$351 -> 0 | D67: =D349/D$351 -> 0 | E67: =E349/E$351 -> 0 | F67: =F349/F$351 -> 0 | G67: =G349/G$351 -> 0 | H67: =H349/H$351 -> 0 | I67: =I349/I$351 -> 0 | J67: =J349/J$351 -> 0 | ... AC67: =AC349/AC$351 -> 0
B68: Train | C68: =C350/C$351 -> 0.084074838 | D68: =D350/D$351 -> 0.07294036 | E68: =E350/E$351 -> 0.096900169 | F68: =F350/F$351 -> 0.079199541 | G68: =G350/G$351 -> 0.073350678 | H68: =H350/H$351 -> 0.084262866 | I68: =I350/I$351 -> 0.078971698 | J68: =J350/J$351 -> 0.091644109 | ... AC68: =AC350/AC$351 -> 0.068690271
B69: TOTAL | C69: =SUM(C61:C68) -> 1 | D69: =SUM(D61:D68) -> 1 | E69: =SUM(E61:E68) -> 1 | F69: =SUM(F61:F68) -> 1 | G69: =SUM(G61:G68) -> 1 | H69: =SUM(H61:H68) -> 1 | I69: =SUM(I61:I68) -> 1 | J69: =SUM(J61:J68) -> 1 | ... AC69: =SUM(AC61:AC68) -> 1
A75: Passengers
A78: Vehicle travelled by counties in 2018 (Mvkm)
A79: Vehicle | B79: Fuel | C79: =Regions!C3 -> IE | D79: =Regions!E3 -> IE-CW | E79: =Regions!F3 -> IE-D | F79: =Regions!G3 -> IE-KE | G79: =Regions!H3 -> IE-KK | H79: =Regions!I3 -> IE-LS | I79: =Regions!J3 -> IE-LD | J79: =Regions!K3 -> IE-LH | K79: =Regions!L3 -> IE-MH | ... AC79: =Regions!AD3 -> IE-MN
A80: Two-wheelers | B80: Gasoline | C80: =SUM(D80:AC80) -> 109 | D80: 1 | E80: 34 | F80: 6 | G80: 2 | H80: 1 | I80: 1 | J80: 2 | K80: 5 | L80: 2 | M80: 2 | N80: 4 | O80: 4 | P80: 3 | Q80: 15 | R80: 3 | S80: 4 | T80: 4 | U80: 3 | V80: 4 | W80: 1 | X80: 2 | Y80: 1 | Z80: 1 | AA80: 1 | AB80: 2 | AC80: 1
A81: Private Cars | B81: Gasoline | C81: =SUM(D81:AC81) -> 12136 | D81: 146 | E81: 3300 | F81: 602 | G81: 239 | H81: 175 | I81: 81 | J81: 273 | K81: 477 | L81: 173 | M81: 200 | N81: 408 | O81: 441 | P81: 342 | Q81: 1584 | R81: 441 | S81: 541 | T81: 439 | U81: 357 | V81: 621 | W81: 72 | X81: 313 | Y81: 184 | Z81: 158 | AA81: 150 | AB81: 311 | AC81: 108
B82: Diesel | C82: =SUM(D82:AC82) -> 23286 | D82: 378 | E82: 4087 | F82: 1188 | G82: 580 | H82: 492 | I82: 256 | J82: 617 | K82: 1111 | L82: 480 | M82: 575 | N82: 963 | O82: 698 | P82: 718 | Q82: 2655 | R82: 824 | S82: 1023 | T82: 1063 | U82: 616 | V82: 1419 | W82: 211 | X82: 815 | Y82: 472 | Z82: 362 | AA82: 457 | AB82: 845 | AC82: 381
B83: Other fuels | C83: =SUM(D83:AC83) -> 555 | D83: 5 | E83: 224 | F83: 30 | G83: 8 | H83: 6 | I83: 3 | J83: 12 | K83: 24 | L83: 6 | M83: 10 | N83: 14 | O83: 22 | P83: 11 | Q83: 59 | R83: 13 | S83: 16 | T83: 11 | U83: 11 | V83: 30 | W83: 2 | X83: 8 | Y83: 5 | Z83: 5 | AA83: 6 | AB83: 11 | AC83: 3
A84: Small PSVs | B84: Gasoline | C84: =SUM(D84:AC84) -> 89 | D84: 0 | E84: 56 | F84: 3 | G84: 0 | H84: 0 | I84: 0 | J84: 2 | K84: 4 | L84: 0 | M84: 1 | N84: 1 | O84: 1 | P84: 2 | Q84: 6 | R84: 1 | S84: 5 | T84: 0 | U84: 1 | V84: 4 | W84: 0 | X84: 1 | Y84: 0 | Z84: 0 | AA84: 0 | AB84: 1 | AC84: 0
B85: Diesel | C85: =SUM(D85:AC85) -> 696 | D85: 5 | E85: 331 | F85: 30 | G85: 9 | H85: 8 | I85: 4 | J85: 22 | K85: 36 | L85: 6 | M85: 11 | N85: 10 | O85: 12 | P85: 12 | Q85: 62 | R85: 17 | S85: 20 | T85: 10 | U85: 10 | V85: 33 | W85: 3 | X85: 10 | Y85: 5 | Z85: 6 | AA85: 7 | AB85: 14 | AC85: 3
B86: Other fuels | C86: =SUM(D86:AC86) -> 55 | D86: 0 | E86: 43 | F86: 2 | G86: 0 | H86: 1 | I86: 0 | J86: 1 | K86: 2 | L86: 0 | M86: 0 | N86: 0 | O86: 1 | P86: 0 | Q86: 2 | R86: 0 | S86: 2 | T86: 0 | U86: 0 | V86: 1 | W86: 0 | X86: 0 | Y86: 0 | Z86: 0 | AA86: 0 | AB86: 0 | AC86: 0
A87: Large PSVs | B87: Diesel | C87: =SUM(D87:AC87) -> 360.22233 | D87: 4 | E87: 130 | F87: 17 | G87: 11 | H87: 5 | I87: 3 | J87: 8 | K87: 11 | L87: 7 | M87: 5 | N87: 10 | O87: 9 | P87: 7 | Q87: 29 | R87: 18 | S87: 11 | T87: 13 | U87: 6 | V87: 21 | W87: 2 | X87: 13 | Y87: 4 | Z87: 4 | AA87: 1.6719368 | AB87: 0.55039526 | AC87: 10
A88: Light Rail (LUAS) | B88: Electricity | C88: =(B126+C126)/1000000 -> 4.065479 | D88: 0 | E88: =C88 -> 4.065479 | F88: 0 | G88: 0 | H88: 0 | I88: 0 | J88: 0 | K88: 0 | L88: 0 | M88: 0 | N88: 0 | O88: 0 | P88: 0 | Q88: 0 | R88: 0 | S88: 0 | T88: 0 | U88: 0 | V88: 0 | W88: 0 | X88: 0 | Y88: 0 | Z88: 0 | AA88: 0 | AB88: 0 | AC88: 0
A89: TOTAL | C89: =SUM(C81:C88) -> 37181.288 | D89: =SUM(D81:D88) -> 538 | E89: =SUM(E81:E88) -> 8175.0655 | F89: =SUM(F81:F88) -> 1872 | G89: =SUM(G81:G88) -> 847 | H89: =SUM(H81:H88) -> 687 | I89: =SUM(I81:I88) -> 347 | J89: =SUM(J81:J88) -> 935 | ... AC89: =SUM(AC81:AC88) -> 505
A90: Source: CSO, Tables: THA 17, THA18, THA20
A94: Vehicle travelled by counties in 2018 (Mpkm)
A95: Mode | B95: Tech. & Fuel | C95: =Regions!C3 -> IE | D95: =Regions!E3 -> IE-CW | E95: =Regions!F3 -> IE-D | F95: =Regions!G3 -> IE-KE | G95: =Regions!H3 -> IE-KK | H95: =Regions!I3 -> IE-LS | I95: =Regions!J3 -> IE-LD | J95: =Regions!K3 -> IE-LH | K95: =Regions!L3 -> IE-MH | ... AC95: =Regions!AD3 -> IE-MN
A96: Non-motorized 1 | B96: Walk | C96: =C89*B194*I194/H194 -> 4713.121 | D96: =$C$96*C139 -> 56.349225 | E96: =$C$96*D139 -> 1333.567 | F96: =$C$96*E139 -> 220.22638 | G96: =$C$96*F139 -> 98.216229 | H96: =$C$96*G139 -> 83.830014 | I96: =$C$96*H139 -> 40.454611 | J96: =$C$96*I139 -> 127.5647 | K96: =$C$96*J139 -> 193.04747 | ... AC96: =$C$96*AB139 -> 60.757633
B97: Bike | C97: =C89*B194*K194/H194 -> 785.52017 | D97: =$C$97*C139 -> 9.3915376 | E97: =$C$97*D139 -> 222.26117 | F97: =$C$97*E139 -> 36.704396 | G97: =$C$97*F139 -> 16.369371 | H97: =$C$97*G139 -> 13.971669 | I97: =$C$97*H139 -> 6.7424351 | J97: =$C$97*I139 -> 21.260784 | K97: =$C$97*J139 -> 32.174578 | ... AC97: =$C$97*AB139 -> 10.126272
A98: Two-wheelers 2 | B98: Motor_Gasoline | C98: =C80*ACT2FLO!E52 -> 119.9 | D98: =D80*ACT2FLO!F52 -> 1.1 | E98: =E80*ACT2FLO!G52 -> 37.4 | F98: =F80*ACT2FLO!H52 -> 6.6 | G98: =G80*ACT2FLO!I52 -> 2.2 | H98: =H80*ACT2FLO!J52 -> 1.1 | I98: =I80*ACT2FLO!K52 -> 1.1 | J98: =J80*ACT2FLO!L52 -> 2.2 | ... AC98: =AC80*ACT2FLO!AE52 -> 1.1
A99: Private Cars 2 | B99: Car_Gasoline | C99: =C81*ACT2FLO!E53 -> 18107.052 | D99: =D81*ACT2FLO!F53 -> 217.83368 | E99: =E81*ACT2FLO!G53 -> 4923.638 | F99: =F81*ACT2FLO!H53 -> 898.19094 | G99: =G81*ACT2FLO!I53 -> 356.59075 | H99: =H81*ACT2FLO!J53 -> 261.10202 | I99: =I81*ACT2FLO!K53 -> 120.85293 | J99: =J81*ACT2FLO!L53 -> 407.31915 | ... AC99: =AC81*ACT2FLO!AE53 -> 161.13724
B100: Car_Diesel | C100: =C82*ACT2FLO!E54 -> 34742.98 | D100: =D82*ACT2FLO!F54 -> 563.98036 | E100: =E82*ACT2FLO!G54 -> 6097.8511 | F100: =F82*ACT2FLO!H54 -> 1772.5097 | G100: =G82*ACT2FLO!I54 -> 865.36668 | H100: =H82*ACT2FLO!J54 -> 734.06967 | I100: =I82*ACT2FLO!K54 -> 381.95495 | J100: =J82*ACT2FLO!L54 -> 920.57111 | ... AC100: =AC82*ACT2FLO!AE54 -> 568.45639
B101: Car_Other fuels | C101: =C83*ACT2FLO!E55 -> 828.0664 | D101: =D83*ACT2FLO!F55 -> 7.4600576 | E101: =E83*ACT2FLO!G55 -> 334.21058 | F101: =F83*ACT2FLO!H55 -> 44.760346 | G101: =G83*ACT2FLO!I55 -> 11.936092 | H101: =H83*ACT2FLO!J55 -> 8.9520691 | I101: =I83*ACT2FLO!K55 -> 4.4760346 | J101: =J83*ACT2FLO!L55 -> 17.904138 | ... AC101: =AC83*ACT2FLO!AE55 -> 4.4760346
B102: Total Car | C102: =SUM(C99:C101) -> 53678.099 | D102: =SUM(D99:D101) -> 789.2741 | E102: =SUM(E99:E101) -> 11355.7 | F102: =SUM(F99:F101) -> 2715.461 | G102: =SUM(G99:G101) -> 1233.8935 | H102: =SUM(H99:H101) -> 1004.1238 | I102: =SUM(I99:I101) -> 507.28392 | J102: =SUM(J99:J101) -> 1345.7944 | ... AC102: =SUM(AC99:AC101) -> 734.06967
A103: Small PSVs 2 | B103: Taxi_Gasoline | C103: =C84*ACT2FLO!E62 -> 132.78903 | D103: =D84*ACT2FLO!F62 -> 0 | E103: =E84*ACT2FLO!G62 -> 83.552645 | F103: =F84*ACT2FLO!H62 -> 4.4760346 | G103: =G84*ACT2FLO!I62 -> 0 | H103: =H84*ACT2FLO!J62 -> 0 | I103: =I84*ACT2FLO!K62 -> 0 | J103: =J84*ACT2FLO!L62 -> 2.984023 | ... AC103: =AC84*ACT2FLO!AE62 -> 0
B104: Taxi_Diesel | C104: =C85*ACT2FLO!E63 -> 1038.44 | D104: =D85*ACT2FLO!F63 -> 7.4600576 | E104: =E85*ACT2FLO!G63 -> 493.85581 | F104: =F85*ACT2FLO!H63 -> 44.760346 | G104: =G85*ACT2FLO!I63 -> 13.428104 | H104: =H85*ACT2FLO!J63 -> 11.936092 | I104: =I85*ACT2FLO!K63 -> 5.9680461 | J104: =J85*ACT2FLO!L63 -> 32.824254 | ... AC104: =AC85*ACT2FLO!AE63 -> 4.4760346
B105: Taxi_Other fuels | C105: =C86*ACT2FLO!E64 -> 82.060634 | D105: =D86*ACT2FLO!F64 -> 0 | E105: =E86*ACT2FLO!G64 -> 64.156495 | F105: =F86*ACT2FLO!H64 -> 2.984023 | G105: =G86*ACT2FLO!I64 -> 0 | H105: =H86*ACT2FLO!J64 -> 1.4920115 | I105: =I86*ACT2FLO!K64 -> 0 | J105: =J86*ACT2FLO!L64 -> 1.4920115 | ... AC105: =AC86*ACT2FLO!AE64 -> 0
B106: Total Taxi | C106: =SUM(C103:C105) -> 1253.2897 | D106: =SUM(D103:D105) -> 7.4600576 | E106: =SUM(E103:E105) -> 641.56495 | F106: =SUM(F103:F105) -> 52.220403 | G106: =SUM(G103:G105) -> 13.428104 | H106: =SUM(H103:H105) -> 13.428104 | I106: =SUM(I103:I105) -> 5.9680461 | J106: =SUM(J103:J105) -> 37.300288 | ... AC106: =SUM(AC103:AC105) -> 4.4760346
A107: Large PSVs | B107: Bus_Diesel 2 | C107: =C87*ACT2FLO!E65 -> 9816.0585 | D107: =D87*ACT2FLO!F65 -> 109 | E107: =E87*ACT2FLO!G65 -> 3542.5 | F107: =F87*ACT2FLO!H65 -> 463.25 | G107: =G87*ACT2FLO!I65 -> 299.75 | H107: =H87*ACT2FLO!J65 -> 136.25 | I107: =I87*ACT2FLO!K65 -> 81.75 | J107: =J87*ACT2FLO!L65 -> 218 | ... AC107: =AC87*ACT2FLO!AE65 -> 272.5
B108: Light rail (LUAS) 3 | C108: =SUM(B127:C127)/1000000 -> 317.18624 | D108: =C643*0 -> 0 | E108: =$C$108*1 -> 317.18624 | F108: =E643*0 -> 0 | G108: =F643*0 -> 0 | H108: =G643*0 -> 0 | I108: =H643*0 -> 0 | J108: =I643*0 -> 0 | K108: =J643*0 -> 0 | L108: =K643*0 -> 0 | M108: =L643*0 -> 0 | ... AC108: =AB643*0 -> 0
B109: Train 4 | C109: =K126/1000 -> 2281.083 | D109: =$C$109*C139 -> 27.272217 | E109: =$C$109*D139 -> 645.42731 | F109: =$C$109*E139 -> 106.58641 | G109: =$C$109*F139 -> 47.535247 | H109: =$C$109*G139 -> 40.572525 | I109: =$C$109*H139 -> 19.579452 | J109: =$C$109*I139 -> 61.739487 | K109: =$C$109*J139 -> 93.432206 | ... AC109: =$C$109*AB139 -> 29.405823
A110: TOTAL | C110: =SUM(C96:C109)-C102-C106 -> 72964.257 | D110: =SUM(D96:D109)-D102-D106 -> 999.84713 | E110: =SUM(E96:E109)-E102-E106 -> 18095.606 | F110: =SUM(F96:F109)-F102-F106 -> 3601.0486 | G110: =SUM(G96:G109)-G102-G106 -> 1711.3925 | H110: =SUM(H96:H109)-H102-H106 -> 1293.2761 | I110: =SUM(I96:I109)-I102-I106 -> 662.87846 | J110: =SUM(J96:J109)-J102-J106 -> 1813.8597 | ... AC110: =SUM(AC96:AC109)-AC102-AC106 -> 1112.4354
A111: 1. Estimated based on the relative share of active mode and car mode in short trips for national travels. For regional estimation they are calculated based on the population shares.
A112: 2. Actual data (regional million vehicle kilometers) multiplied by the occupancy rates.
A113: 3.Adopted from table below (LUAS infrastructure).
A114: 4. National data adopted from table below (rail) and regional data estimated based on population shares.
A118: Luas infrastructure, 2018 | G118: Summary of passenger and freight traffic by rail | K118: Thousands
B119: Red line | C119: Green line | H119: 2015 | I119: 2016 | J119: 2017 | K119: 2018
A120: Length of line | B120: 20.5km | C120: 22.0km | G120: Passengers
A121: Journey time | B121: 51 minutes | C121: 40 minutes | G121: Mainline and other services | H121: 10490 | I121: 10771.652 | J121: 11557.034 | K121: 12438
A122: Number of trams | B122: 40 | C122: 33 | G122: Dublin suburban services | H122: 10962 | I122: 11953.521 | J122: 12695.599 | K122: 13299
A123: Length of tram | B123: 40.8 metres | C123: 43.6/54.7 metres | G123: DART | H123: 17150 | I123: 18986.618 | J123: 20077.245 | K123: 20934
A124: Capacity of tram | B124: 262 | C124: 287/367 | G124: International journeys | H124: 1058 | I124: 1102.8053 | J124: 1175.0164 | K124: 1290
A125: Passengers carried | B125: 21837268 | C125: 19999700 | G125: Total | H125: 39660 | I125: 42815 | J125: 45505 | K125: 47960
A126: Vehicle kilometres | B126: 2119703 | C126: 1945776 | G126: Passenger kilometres | H126: 1916722 | I126: 1989798 | J126: 2120987 | K126: 2281083
A127: Passenger kilometres | B127: 112040329 | C127: 205145908 | G127: Freight traffic tonnes | H127: 540 | I127: 581 | J127: 546 | K127: 516
A128: Share of short and medium travels | B128: =B127/(B127+C127) -> 0.353232 | C128: =C127/(B127+C127) -> 0.646768 | G128: Freight traffic tonnes kilometres | H128: 96406 | I128: 101480 | J128: 100399 | K128: 88551
A129: Average length of journey (km) | B129: 4.45 | C129: 8.1 | G129: Source: Iarnród Éireann and CSO, https://www.cso.ie/en/releasesandpublications/ep/p-tranom/transportomnibus2018/publictransport/
...

Sheet Aviation
B3: FI_Process
B4: Sets | C4: Region | D4: TechName | E4: TechDesc | F4: Tact | G4: Tcap | H4: Tslvl | I4: PrimaryCG | J4: Vintage
B5: *Passengers
B6: *Aviation
B7: DMD | C7: IE,National | D7: T-SAVI_INT_JETK00 | E7: TRA Aviation: Small Aircraft - Existing | F7: Bpkm | G7: kUnits
B8: DMD | C8: IE,National | D8: T-MAVI_INT_JETK00 | E8: TRA Aviation: Medium Aircraft - Existing | F8: Bpkm | G8: kUnits
B9: DMD | C9: IE,National | D9: T-LAVI_INT_JETK00 | E9: TRA Aviation: Large Aircraft - Existing | F9: Bpkm | G9: kUnits
E14: FI_T
B15: TechName | C15: *Unit | D15: Comm-IN | E15: Comm-OUT | F15: YEAR | G15: NCAP_Pasti | H15: Life | I15: NCAP_Pasty | J15: ACTFLO | K15: AF | L15: EFFICIENCY | M15: CAP2ACT
B16: *Aircraftes | G16: KUnits | H16: year | R16: EU | S16: Ireland | U16: Ireland
B17: =D7 -> T-SAVI_INT_JETK00 | C17: kUnits | D17: =Commodities!C18&","&Commodities!C12&","&Commodities!C19 -> TRAKER,TRABJK,TRAPtLKER | E17: =Commodities!C34&","&Commodities!C33 -> TAVIINTS,TAVIINT | F17: 2010 | G17: =S17/3/1000 -> 0.18966667 | H17: 30 | I17: 10 | J17: 117 | K17: 2800 | L17: 0.0027 | M17: 0.001 | Q17: Aircrafts | R17: 6711 | S17: 569 | U17: number | V17: age
B18: =D8 -> T-MAVI_INT_JETK00 | C18: kUnits | D18: =Commodities!C18&","&Commodities!C12&","&Commodities!C19 -> TRAKER,TRABJK,TRAPtLKER | E18: =Commodities!C35&","&Commodities!C33 -> TAVIINTM,TAVIINT | F18: 2010 | G18: =G17 -> 0.18966667 | H18: 30 | I18: 10 | J18: 150 | K18: 2800 | L18: 0.0027 | M18: 0.001 | Q18: <5 years | R18: 0.21 | S18: 0.27 | U18: =S17*S18 -> 153.63 | V18: 3
B19: =D9 -> T-LAVI_INT_JETK00 | C19: kUnits | D19: =Commodities!C18&","&Commodities!C12&","&Commodities!C19 -> TRAKER,TRABJK,TRAPtLKER | E19: =Commodities!C36&","&Commodities!C33 -> TAVIINTL,TAVIINT | F19: 2010 | G19: =G18 -> 0.18966667 | H19: 30 | I19: 10 | J19: 220 | K19: 2800 | L19: 0.0027 | M19: 0.001 | Q19: 5-9 years | R19: 0.27 | U19: =S17*R19 -> 153.63 | V19: 8
Q20: 10-14 years | R20: 0.19 | U20: =S17*R20 -> 108.11 | V20: 13
Q21: 15-19 years | R21: 0.17 | U21: =S17-SUM(U18:U20,U22) -> 113.8 | V21: 17
Q22: >20 years | R22: 0.17 | S22: 0.07 | U22: =S17*S22 -> 39.83 | V22: 25
Q23: Source: https://ec.europa.eu/eurostat/web/products-eurostat-news/-/edn-20191206-1
B28: FI_T: Demand
B29: CommName | C29: *Unit | D29: IE
B30: =Commodities!C34 -> TAVIINTS | C30: Bpkm | D30: 2.9
B31: =Commodities!C35 -> TAVIINTM | C31: Bpkm | D31: 15.8
B32: =Commodities!C36 -> TAVIINTL | C32: Bpkm | D32: 13.8
E38: FI_T
B39: Region | C39: TechName | D39: Comm-IN | E39: LimType | F39: Share-I~2018 | G39: Share-I~2030 | H39: Share-I~2050 | I39: Share-I~0
B40: IE | C40: =B17 -> T-SAVI_INT_JETK00 | D40: TRAKER | E40: LO | F40: 1 | G40: 0.95 | H40: 0.5 | I40: 5
B41: IE | C41: =B18 -> T-MAVI_INT_JETK00 | D41: TRAKER | E41: LO | F41: =F40 -> 1 | G41: =G40 -> 0.95 | H41: =H40 -> 0.5 | I41: 5
B42: IE | C42: =B19 -> T-LAVI_INT_JETK00 | D42: TRAKER | E42: LO | F42: =F41 -> 1 | G42: =G41 -> 0.95 | H42: =H41 -> 0.5 | I42: 5

Sheet Efficiency
B4: TechName | C4: *Unit | D4: Attribute | E4: =Demands!C3 -> IE | F4: =Demands!D3 -> IE-CW | G4: =Demands!E3 -> IE-D | H4: =Demands!F3 -> IE-KE | I4: =Demands!G3 -> IE-KK | J4: =Demands!H3 -> IE-LS | K4: =Demands!I3 -> IE-LD | L4: =Demands!J3 -> IE-LH | ... AE4: =Demands!AC3 -> IE-MN
B5: =Processes!D6 -> T-WLK_WLK | C5: mVkm/PJ | D5: EFFICIENCY | E5: 1500 | F5: 1500 | G5: 1500 | H5: 1500 | I5: 1500 | J5: 1500 | K5: 1500 | L5: 1500 | M5: 1500 | N5: 1500 | O5: 1500 | P5: 1500 | Q5: 1500 | R5: 1500 | S5: 1500 | T5: 1500 | U5: 1500 | V5: 1500 | W5: 1500 | X5: 1500 | Y5: 1500 | Z5: 1500 | AA5: 1500 | AB5: 1500 | AC5: 1500 | AD5: 1500 | AE5: 1500
B6: =Processes!D7 -> T-CYC_CYC | C6: mVkm/PJ | D6: EFFICIENCY | E6: 1500 | F6: 1500 | G6: 1500 | H6: 1500 | I6: 1500 | J6: 1500 | K6: 1500 | L6: 1500 | M6: 1500 | N6: 1500 | O6: 1500 | P6: 1500 | Q6: 1500 | R6: 1500 | S6: 1500 | T6: 1500 | U6: 1500 | V6: 1500 | W6: 1500 | X6: 1500 | Y6: 1500 | Z6: 1500 | AA6: 1500 | AB6: 1500 | AC6: 1500 | AD6: 1500 | AE6: 1500
B7: =Processes!D9 -> T-MOT-ICE_GSL00 | C7: mVkm/PJ | D7: EFFICIENCY | E7: 587.97955 | F7: 587.97955 | G7: 587.97955 | H7: 587.97955 | I7: 587.97955 | J7: 587.97955 | K7: 587.97955 | L7: 587.97955 | M7: 587.97955 | N7: 587.97955 | O7: 587.97955 | P7: 587.97955 | Q7: 587.97955 | R7: 587.97955 | S7: 587.97955 | T7: 587.97955 | U7: 587.97955 | V7: 587.97955 | W7: 587.97955 | X7: 587.97955 | Y7: 587.97955 | Z7: 587.97955 | AA7: 587.97955 | AB7: 587.97955 | AC7: 587.97955 | AD7: 587.97955 | AE7: 587.97955
B8: =Processes!D11 -> T-CAR-ICE_GSL00 | C8: mVkm/PJ | D8: EFFICIENCY | E8: =D117/(1+'On-Road Fac.'!$D$5) -> 433.50426 | F8: =E117/(1+'On-Road Fac.'!$D$5) -> 434.10338 | G8: =F117/(1+'On-Road Fac.'!$D$5) -> 432.27719 | H8: =G117/(1+'On-Road Fac.'!$D$5) -> 434.11834 | I8: =H117/(1+'On-Road Fac.'!$D$5) -> 435.1727 | J8: =I117/(1+'On-Road Fac.'!$D$5) -> 434.45389 | K8: =J117/(1+'On-Road Fac.'!$D$5) -> 434.67645 | L8: =K117/(1+'On-Road Fac.'!$D$5) -> 437.49004 | ... AE8: =AD117/(1+'On-Road Fac.'!$D$5) -> 434.29321
B9: =Processes!D12 -> T-CAR-ICE_DST00 | C9: mVkm/PJ | D9: EFFICIENCY | E9: =D163/(1+'On-Road Fac.'!$D$5) -> 401.1808 | F9: =E163/(1+'On-Road Fac.'!$D$5) -> 401.54966 | G9: =F163/(1+'On-Road Fac.'!$D$5) -> 397.35475 | H9: =G163/(1+'On-Road Fac.'!$D$5) -> 400.80412 | I9: =H163/(1+'On-Road Fac.'!$D$5) -> 403.19076 | J9: =I163/(1+'On-Road Fac.'!$D$5) -> 402.604 | K9: =J163/(1+'On-Road Fac.'!$D$5) -> 399.42461 | L9: =K163/(1+'On-Road Fac.'!$D$5) -> 404.22747 | ... AE9: =AD163/(1+'On-Road Fac.'!$D$5) -> 400.63388
B10: =Processes!D13 -> T-CAR-ICE_DF00 | C10: mVkm/PJ | D10: EFFICIENCY | E10: =D211/(1+'On-Road Fac.'!$D$5) -> 346.42547 | F10: =E211/(1+'On-Road Fac.'!$D$5) -> 346.42547 | G10: =F211/(1+'On-Road Fac.'!$D$5) -> 356.92116 | H10: =G211/(1+'On-Road Fac.'!$D$5) -> 346.42547 | I10: =H211/(1+'On-Road Fac.'!$D$5) -> 346.42547 | J10: =I211/(1+'On-Road Fac.'!$D$5) -> 346.42547 | K10: =J211/(1+'On-Road Fac.'!$D$5) -> 313.62301 | L10: =K211/(1+'On-Road Fac.'!$D$5) -> 346.42547 | ... AE10: =AD211/(1+'On-Road Fac.'!$D$5) -> 346.42547
B11: =Processes!D14 -> T-CAR-ICE_E8500 | C11: mVkm/PJ | D11: EFFICIENCY | E11: =D260/(1+'On-Road Fac.'!$D$5) -> 414.96671 | F11: =E260/(1+'On-Road Fac.'!$D$5) -> 420.11337 | G11: =F260/(1+'On-Road Fac.'!$D$5) -> 409.91964 | H11: =G260/(1+'On-Road Fac.'!$D$5) -> 420.96104 | I11: =H260/(1+'On-Road Fac.'!$D$5) -> 419.47774 | J11: =I260/(1+'On-Road Fac.'!$D$5) -> 417.59928 | K11: =J260/(1+'On-Road Fac.'!$D$5) -> 416.06108 | L11: =K260/(1+'On-Road Fac.'!$D$5) -> 423.30919 | ... AE11: =AD260/(1+'On-Road Fac.'!$D$5) -> 422.3099
B12: =Processes!D15 -> T-CAR-HEV_GSL00 | C12: mVkm/PJ | D12: EFFICIENCY | E12: =D308/(1+'On-Road Fac.'!$D$5) -> 487.30496 | F12: =E308/(1+'On-Road Fac.'!$D$5) -> 487.99562 | G12: =F308/(1+'On-Road Fac.'!$D$5) -> 488.36951 | H12: =G308/(1+'On-Road Fac.'!$D$5) -> 489.06911 | I12: =H308/(1+'On-Road Fac.'!$D$5) -> 489.69693 | J12: =I308/(1+'On-Road Fac.'!$D$5) -> 493.027 | K12: =J308/(1+'On-Road Fac.'!$D$5) -> 491.13558 | L12: =K308/(1+'On-Road Fac.'!$D$5) -> 487.62642 | ... AE12: =AD308/(1+'On-Road Fac.'!$D$5) -> 486.8549
B13: =Processes!D16 -> T-CAR-HEV_DST00 | C13: mVkm/PJ | D13: EFFICIENCY | E13: =D356/(1+'On-Road Fac.'!$D$5) -> 492.55495 | F13: =E356/(1+'On-Road Fac.'!$D$5) -> 491.8071 | G13: =F356/(1+'On-Road Fac.'!$D$5) -> 492.4263 | H13: =G356/(1+'On-Road Fac.'!$D$5) -> 499.37029 | I13: =H356/(1+'On-Road Fac.'!$D$5) -> 494.91148 | J13: =I356/(1+'On-Road Fac.'!$D$5) -> 490.53491 | K13: =J356/(1+'On-Road Fac.'!$D$5) -> 484.684 | L13: =K356/(1+'On-Road Fac.'!$D$5) -> 490.53491 | ... AE13: =AD356/(1+'On-Road Fac.'!$D$5) -> 492.88355
B14: =Processes!D17 -> T-CAR-PHEV_GSL00 | C14: mVkm/PJ | D14: EFFICIENCY | E14: =D404/(1+'On-Road Fac.'!$D$5) -> 640.60354 | F14: =E404/(1+'On-Road Fac.'!$D$5) -> 654.05503 | G14: =F404/(1+'On-Road Fac.'!$D$5) -> 640.31103 | H14: =G404/(1+'On-Road Fac.'!$D$5) -> 648.65711 | I14: =H404/(1+'On-Road Fac.'!$D$5) -> 639.99953 | J14: =I404/(1+'On-Road Fac.'!$D$5) -> 637.65878 | K14: =J404/(1+'On-Road Fac.'!$D$5) -> 646.37011 | L14: =K404/(1+'On-Road Fac.'!$D$5) -> 639.98747 | ... AE14: =AD404/(1+'On-Road Fac.'!$D$5) -> 641.21298
B15: =Processes!D18 -> T-CAR-PHEV_DST00 | C15: mVkm/PJ | D15: EFFICIENCY | E15: =D452/(1+'On-Road Fac.'!$D$5) -> 632.48824 | F15: =E452/(1+'On-Road Fac.'!$D$5) -> 346.42547 | G15: =F452/(1+'On-Road Fac.'!$D$5) -> 637.34452 | H15: =G452/(1+'On-Road Fac.'!$D$5) -> 628.72419 | I15: =H452/(1+'On-Road Fac.'!$D$5) -> 346.42547 | J15: =I452/(1+'On-Road Fac.'!$D$5) -> 346.42547 | K15: =J452/(1+'On-Road Fac.'!$D$5) -> 346.42547 | L15: =K452/(1+'On-Road Fac.'!$D$5) -> 346.42547 | ... AE15: =AD452/(1+'On-Road Fac.'!$D$5) -> 346.42547
B16: =Processes!D19 -> T-CAR-BEV_ELC00 | C16: mVkm/PJ | D16: EFFICIENCY | E16: =D500/(1+'On-Road Fac.'!$D$5) -> 1173.2288 | F16: =E500/(1+'On-Road Fac.'!$D$5) -> 1231.9897 | G16: =F500/(1+'On-Road Fac.'!$D$5) -> 1172.1268 | H16: =G500/(1+'On-Road Fac.'!$D$5) -> 1167.3429 | I16: =H500/(1+'On-Road Fac.'!$D$5) -> 1152.6359 | J16: =I500/(1+'On-Road Fac.'!$D$5) -> 1140.9697 | K16: =J500/(1+'On-Road Fac.'!$D$5) -> 1204.8629 | L16: =K500/(1+'On-Road Fac.'!$D$5) -> 1167.7576 | ... AE16: =AD500/(1+'On-Road Fac.'!$D$5) -> 1239.1527
B17: =Processes!D21 -> T-TAX-ICE_GSL00 | C17: mVkm/PJ | D17: EFFICIENCY | E17: =D548/(1+'On-Road Fac.'!$D$5) -> 380.16954 | F17: =E548/(1+'On-Road Fac.'!$D$5) -> 354.39129 | G17: =F548/(1+'On-Road Fac.'!$D$5) -> 382.34697 | H17: =G548/(1+'On-Road Fac.'!$D$5) -> 381.32983 | I17: =H548/(1+'On-Road Fac.'!$D$5) -> 376.9454 | J17: =I548/(1+'On-Road Fac.'!$D$5) -> 372.82795 | K17: =J548/(1+'On-Road Fac.'!$D$5) -> 341.7233 | L17: =K548/(1+'On-Road Fac.'!$D$5) -> 373.85977 | ... AE17: =AD548/(1+'On-Road Fac.'!$D$5) -> 345.30231
B18: =Processes!D22 -> T-TAX-ICE_DST00 | C18: mVkm/PJ | D18: EFFICIENCY | E18: =D596/(1+'On-Road Fac.'!$D$5) -> 418.24524 | F18: =E596/(1+'On-Road Fac.'!$D$5) -> 417.35103 | G18: =F596/(1+'On-Road Fac.'!$D$5) -> 423.84507 | H18: =G596/(1+'On-Road Fac.'!$D$5) -> 417.68253 | I18: =H596/(1+'On-Road Fac.'!$D$5) -> 420.89355 | J18: =I596/(1+'On-Road Fac.'!$D$5) -> 424.70573 | K18: =J596/(1+'On-Road Fac.'!$D$5) -> 411.13832 | L18: =K596/(1+'On-Road Fac.'!$D$5) -> 413.09357 | ... AE18: =AD596/(1+'On-Road Fac.'!$D$5) -> 407.83459
B19: =Processes!D23 -> T-TAX-HEV_GSL00 | C19: mVkm/PJ | D19: EFFICIENCY | E19: =D644/(1+'On-Road Fac.'!$D$5) -> 493.21318 | F19: =E644/(1+'On-Road Fac.'!$D$5) -> 482.49903 | G19: =F644/(1+'On-Road Fac.'!$D$5) -> 493.55513 | H19: =G644/(1+'On-Road Fac.'!$D$5) -> 493.40332 | I19: =H644/(1+'On-Road Fac.'!$D$5) -> 437.01804 | J19: =I644/(1+'On-Road Fac.'!$D$5) -> 502.0676 | K19: =J644/(1+'On-Road Fac.'!$D$5) -> 493.21318 | L19: =K644/(1+'On-Road Fac.'!$D$5) -> 478.3235 | ... AE19: =AD644/(1+'On-Road Fac.'!$D$5) -> 493.21318
B20: =Processes!D25 -> T-BUS-ICE_DST00 | C20: mVkm/PJ | D20: EFFICIENCY | E20: 98.42 | F20: =E20 -> 98.42 | G20: =F20 -> 98.42 | H20: =G20 -> 98.42 | I20: =H20 -> 98.42 | J20: =I20 -> 98.42 | K20: =J20 -> 98.42 | L20: =K20 -> 98.42 | M20: =L20 -> 98.42 | ... AE20: =AD20 -> 98.42
B21: =Processes!D27 -> T-LPT-BEV_ELC00 | C21: mVkm/PJ | D21: EFFICIENCY | E21: 40.3 | F21: =E21 -> 40.3 | G21: =F21 -> 40.3 | H21: =G21 -> 40.3 | I21: =H21 -> 40.3 | J21: =I21 -> 40.3 | K21: =J21 -> 40.3 | L21: =K21 -> 40.3 | M21: =L21 -> 40.3 | ... AE21: =AD21 -> 40.3
B22: =Processes!D28 -> T-HPT-BEV_ELC00 | C22: mVkm/PJ | D22: EFFICIENCY | E22: 40.3 | F22: =E22 -> 40.3 | G22: =F22 -> 40.3 | H22: =G22 -> 40.3 | I22: =H22 -> 40.3 | J22: =I22 -> 40.3 | K22: =J22 -> 40.3 | L22: =K22 -> 40.3 | M22: =L22 -> 40.3 | ... AE22: =AD22 -> 40.3
B23: =Processes!D29 -> T-HPT-ICE_DST00 | C23: mVkm/PJ | D23: EFFICIENCY | E23: 13 | F23: =E23 -> 13 | G23: =F23 -> 13 | H23: =G23 -> 13 | I23: =H23 -> 13 | J23: =I23 -> 13 | K23: =J23 -> 13 | L23: =K23 -> 13 | M23: =L23 -> 13 | ... AE23: =AD23 -> 13
B24: =Processes!D32 -> T-LGT-ICE_GSL00 | C24: mVkm/PJ | D24: EFFICIENCY | E24: 459.7935 | F24: =E24 -> 459.7935 | G24: =F24 -> 459.7935 | H24: =G24 -> 459.7935 | I24: =H24 -> 459.7935 | J24: =I24 -> 459.7935 | K24: =J24 -> 459.7935 | L24: =K24 -> 459.7935 | M24: =L24 -> 459.7935 | ... AE24: =AD24 -> 459.7935
B25: =Processes!D33 -> T-LGT-ICE_DST00 | C25: mVkm/PJ | D25: EFFICIENCY | E25: 453.28818 | F25: =E25 -> 453.28818 | G25: =F25 -> 453.28818 | H25: =G25 -> 453.28818 | I25: =H25 -> 453.28818 | J25: =I25 -> 453.28818 | K25: =J25 -> 453.28818 | L25: =K25 -> 453.28818 | M25: =L25 -> 453.28818 | ... AE25: =AD25 -> 453.28818
B26: =Processes!D34 -> T-MGT-ICE_DST00 | C26: mVkm/PJ | D26: EFFICIENCY | E26: 34.167945 | F26: =E26 -> 34.167945 | G26: =F26 -> 34.167945 | H26: =G26 -> 34.167945 | I26: =H26 -> 34.167945 | J26: =I26 -> 34.167945 | K26: =J26 -> 34.167945 | L26: =K26 -> 34.167945 | M26: =L26 -> 34.167945 | ... AE26: =AD26 -> 34.167945
B27: =Processes!D35 -> T-HGT-ICE_DST00 | C27: mVkm/PJ | D27: EFFICIENCY | E27: 31.388598 | F27: =E27 -> 31.388598 | G27: =F27 -> 31.388598 | H27: =G27 -> 31.388598 | I27: =H27 -> 31.388598 | J27: =I27 -> 31.388598 | K27: =J27 -> 31.388598 | L27: =K27 -> 31.388598 | M27: =L27 -> 31.388598 | ... AE27: =AD27 -> 31.388598
B28: =Processes!D36 -> T-GTR-ICE_DST00 | C28: mVkm/PJ | D28: EFFICIENCY | E28: 4.711241 | F28: =E28 -> 4.711241 | G28: =F28 -> 4.711241 | H28: =G28 -> 4.711241 | I28: =H28 -> 4.711241 | J28: =I28 -> 4.711241 | K28: =J28 -> 4.711241 | L28: =K28 -> 4.711241 | M28: =L28 -> 4.711241 | ... AE28: =AD28 -> 4.711241
B29: =Processes!D38 -> T-TUR_CON00 | C29: - | D29: EFFICIENCY | E29: 1 | F29: 1 | G29: 1 | H29: 1 | I29: 1 | J29: 1 | K29: 1 | L29: 1 | M29: 1 | N29: 1 | O29: 1 | P29: 1 | Q29: 1 | R29: 1 | S29: 1 | T29: 1 | U29: 1 | V29: 1 | W29: 1 | X29: 1 | Y29: 1 | Z29: 1 | AA29: 1 | AB29: 1 | AC29: 1 | AD29: 1 | AE29: 1
B30: =Processes!D39 -> T-NAV_CON00 | C30: - | D30: EFFICIENCY | E30: 1 | F30: 1 | G30: 1 | H30: 1 | I30: 1 | J30: 1 | K30: 1 | L30: 1 | M30: 1 | N30: 1 | O30: 1 | P30: 1 | Q30: 1 | R30: 1 | S30: 1 | T30: 1 | U30: 1 | V30: 1 | W30: 1 | X30: 1 | Y30: 1 | Z30: 1 | AA30: 1 | AB30: 1 | AC30: 1 | AD30: 1 | AE30: 1
B31: =Processes!D40 -> T-OTH_CON00 | C31: - | D31: EFFICIENCY | E31: 1 | F31: 1 | G31: 1 | H31: 1 | I31: 1 | J31: 1 | K31: 1 | L31: 1 | M31: 1 | N31: 1 | O31: 1 | P31: 1 | Q31: 1 | R31: 1 | S31: 1 | T31: 1 | U31: 1 | V31: 1 | W31: 1 | X31: 1 | Y31: 1 | Z31: 1 | AA31: 1 | AB31: 1 | AC31: 1 | AD31: 1 | AE31: 1
B32: =Processes!D42 -> T-AVI_DOM00 | C32: - | D32: EFFICIENCY | E32: 1 | F32: 1 | G32: 1 | H32: 1 | I32: 1 | J32: 1 | K32: 1 | L32: 1 | M32: 1 | N32: 1 | O32: 1 | P32: 1 | Q32: 1 | R32: 1 | S32: 1 | T32: 1 | U32: 1 | V32: 1 | W32: 1 | X32: 1 | Y32: 1 | Z32: 1 | AA32: 1 | AB32: 1 | AC32: 1 | AD32: 1 | AE32: 1
B33: =Processes!D43 -> T-AVI_INT00 | C33: - | D33: EFFICIENCY | E33: 1 | F33: 1 | G33: 1 | H33: 1 | I33: 1 | J33: 1 | K33: 1 | L33: 1 | M33: 1 | N33: 1 | O33: 1 | P33: 1 | Q33: 1 | R33: 1 | S33: 1 | T33: 1 | U33: 1 | V33: 1 | W33: 1 | X33: 1 | Y33: 1 | Z33: 1 | AA33: 1 | AB33: 1 | AC33: 1 | AD33: 1 | AE33: 1
B34: * On a national basis for motorcycle and buses, buses are the average of fuel consumption from IRISH_TIMES 2.0, for trains and freights are taken fron IRISH_TIMES 2.0, for cars and taxis calculated from regional vehicle stock.
D38: ~FI_T
B39: TechName | C39: *Unit | D39: Attribute | E39: =E4 -> IE | F39: =F4 -> IE-CW | G39: =G4 -> IE-D | H39: =H4 -> IE-KE | I39: =I4 -> IE-KK | J39: =J4 -> IE-LS | K39: =K4 -> IE-LD | L39: =L4 -> IE-LH | ... AE39: =AE4 -> IE-MN
