Workbook

Sheet Cover
A16: TIMES-Ireland Model
A19: Document type: | B19: Base Year Template
A20: Sector(s): | B20: Supply sector (SUP)
A21: Purpose: | B21: Specify base year data and define sector structure
A23: Original developer(s): | B23: James Glynn (UCC, james.glynn@ucc.ie)
B24: Xiufeng Yue (UCC, xiufeng.yue@ucc.ie)
B25: Olexandr Balyk (UCC, olexandr.balyk@ucc.ie)
A26: Current maintainer(s): | B26: Vahid Aryanpur (UCC,vahid.aryanpur@ucc.ie)
B27: Bakytzhan Suleimenov (UCC, bsuleimenov@ucc.ie)
A29: Part of TIM version: | B29: 1
A30: Model repository: | B30: https://github.com/MaREI-EPMG/TIMES-Ireland-model
A31: Licence: | B31: CC BY-NC-SA 4.0 (unless specified otherwise)
B32: https://creativecommons.org/licenses/by-nc-sa/4.0/

Sheet Regions
C3: {=INDEX(C5:C7,$A$4)} -> IE | D3: {=INDEX(D5:D7,$A$4)} -> National | E3: {=INDEX(E5:E7,$A$4)} -> IE-CW | F3: {=INDEX(F5:F7,$A$4)} -> IE-D | G3: {=INDEX(G5:G7,$A$4)} -> IE-KE | H3: {=INDEX(H5:H7,$A$4)} -> IE-KK | I3: {=INDEX(I5:I7,$A$4)} -> IE-LS | J3: {=INDEX(J5:J7,$A$4)} -> IE-LD | ... AD3: {=INDEX(AD5:AD7,$A$4)} -> IE-MN
A4: 1
A5: Development | C5: IE | D5: National | E5: =A11 -> IE-CW | F5: =A16 -> IE-D | G5: =A19 -> IE-KE | H5: =A20 -> IE-KK | I5: =A21 -> IE-LS | J5: =A24 -> IE-LD | K5: =A25 -> IE-LH | L5: =A27 -> IE-MH | M5: =A29 -> IE-OY | N5: =A34 -> IE-WH | O5: =A35 -> IE-WX | P5: =A36 -> IE-WW | Q5: =A13 -> IE-CE | R5: =A14 -> IE-CO | S5: =A18 -> IE-KY | T5: =A23 -> IE-LK | U5: =A32 -> IE-TA | V5: =A33 -> IE-WD | W5: =A17 -> IE-G | X5: =A22 -> IE-LM | Y5: =A26 -> IE-MO | Z5: =A30 -> IE-RN | AA5: =A31 -> IE-SO | AB5: =A12 -> IE-CN | AC5: =A15 -> IE-DL | AD5: =A28 -> IE-MN
A6: Single-region | C6: =C5 -> IE | D6: ="*"&D5 -> *National | E6: ="*"&E5 -> *IE-CW | F6: ="*"&F5 -> *IE-D | G6: ="*"&G5 -> *IE-KE | H6: ="*"&H5 -> *IE-KK | I6: ="*"&I5 -> *IE-LS | J6: ="*"&J5 -> *IE-LD | K6: ="*"&K5 -> *IE-LH | ... AD6: ="*"&AD5 -> *IE-MN
A7: Multi-region | C7: ="*"&C5 -> *IE | D7: =D5 -> National | E7: =E5 -> IE-CW | F7: =F5 -> IE-D | G7: =G5 -> IE-KE | H7: =H5 -> IE-KK | I7: =I5 -> IE-LS | J7: =J5 -> IE-LD | K7: =K5 -> IE-LH | ... AD7: =AD5 -> IE-MN
A10: Code | B10: County name
A11: IE-CW | B11: Carlow
A12: IE-CN | B12: Cavan
A13: IE-CE | B13: Clare
A14: IE-CO | B14: Cork
A15: IE-DL | B15: Donegal
A16: IE-D | B16: Dublin
A17: IE-G | B17: Galway
A18: IE-KY | B18: Kerry
A19: IE-KE | B19: Kildare
A20: IE-KK | B20: Kilkenny
A21: IE-LS | B21: Laois
... A36: IE-WW | B36: Wicklow
A37: Source: https://en.wikipedia.org/wiki/ISO_3166-2:IE

Sheet EB2018
A1: 2018 Units = ktoe | B1: NACE (Rev 2) | C1: Coal | D1: Bituminous Coal | E1: Anthracite + Manufactured Ovoids | F1: Coke | G1: Lignite \ Brown Coal Briquettes | H1: Peat | I1: Milled Peat | J1: Sod Peat | K1: Briquettes | L1: Oil | M1: Crude | N1: Refinery Feedstocks | O1: Refinery Gas | P1: Gasoline | Q1: Kerosene | R1: Jet Kerosene | S1: Fueloil | T1: LPG | U1: Gasoil / Diesel /DERV | V1: Petroleum Coke | W1: Naphta | X1: Bitumen | Y1: White Spirit | Z1: Lubricants | AA1: Natural Gas | AB1: Renewables | AC1: Hydro | AD1: Wind | AE1: Biomass | AF1: Renewable Waste | AG1: Landfill Gas | AH1: Biogas | AI1: Biodiesel | AJ1: Bioethanol | AK1: Solar Photovoltaic | AL1: Solar Thermal | AM1: Ambient Heat | AN1: Non-Renewable Waste | AO1: Electricity | AP1: Heat | AQ1: TOTAL
A2: Indigenous Production | C2: =SUM(D2:G2) -> 0 | D2: 0 | H2: =SUM(I2:K2) -> 815.92435 | I2: 688.22035 | J2: 127.704 | L2: =SUM(M2:Z2) -> 0 | AA2: 2751.9192 | AB2: =SUM(AC2:AM2) -> 1334.6583 | AC2: 59.691709 | AD2: 743.01992 | AE2: 248.9086 | AF2: 139.99993 | AG2: 33.531819 | AH2: 16.813133 | AI2: 31.064468 | AJ2: 2.6691993 | AK2: 1.8899881 | AL2: 13.546086 | AM2: 43.523448 | AN2: 145.4371 | AQ2: =C2+H2+L2+AA2+AB2+AN2+AO2+AP2 -> 5047.9389
A3: Imports | C3: =SUM(D3:G3) -> 903.49466 | D3: 829.5746 | E3: 61.722868 | G3: 12.197194 | H3: =SUM(I3:K3) -> 0 | L3: =SUM(M3:Z3) -> 9138.5578 | M3: 3053.4743 | N3: 16.633377 | O3: 0 | P3: 564.23641 | Q3: 369.14639 | R3: 1542.2444 | S3: 82.827949 | T3: 157.54636 | U3: 2932.6956 | V3: 166.37648 | W3: 7.5616539 | X3: 200.83222 | Y3: 1.228147 | Z3: 43.754533 | AA3: 1728.3381 | AB3: =SUM(AC3:AM3) -> 151.93356 | AE3: 24.282116 | AI3: 104.81441 | AJ3: 22.83703 | AO3: 139.45062 | AQ3: =C3+H3+L3+AA3+AB3+AN3+AO3+AP3 -> 12061.775
A4: Exports | C4: =SUM(D4:G4) -> 15.186581 | D4: 0 | E4: 14.097722 | G4: 1.0888587 | H4: =SUM(I4:K4) -> 7.033068 | K4: 7.033068 | L4: =SUM(M4:Z4) -> 1717.0625 | M4: 0 | N4: 0 | P4: 364.52222 | Q4: 21.672508 | R4: 156.2938 | S4: 986.60612 | T4: 35.289733 | U4: 102.14625 | V4: 0.0029088438 | W4: 36.297317 | X4: 5.469469 | Y4: 0.018500298 | Z4: 8.7436483 | AA4: 0 | AB4: =SUM(AC4:AM4) -> 9.4476585 | AE4: 0.4126464 | AI4: 9.0350121 | AJ4: 0 | AO4: 141.83539 | AQ4: =C4+H4+L4+AA4+AB4+AN4+AO4+AP4 -> 1890.5652
A5: Mar. Bunkers | C5: =SUM(D5:G5) -> 0 | H5: =SUM(I5:K5) -> 0 | L5: =SUM(M5:Z5) -> 172.71259 | S5: 15.730078 | U5: 156.98251 | AB5: =SUM(AC5:AM5) -> 0 | AQ5: =C5+H5+L5+AA5+AB5+AN5+AO5+AP5 -> 172.71259
A6: Stock Change | C6: =SUM(D6:G6) -> -101.25635 | D6: -101.86989 | E6: -0.80797667 | G6: 1.421516 | H6: =SUM(I6:K6) -> -122.93905 | I6: -136.53827 | J6: 0 | K6: 13.599214 | L6: =SUM(M6:Z6) -> 151.33981 | M6: 38.730965 | N6: -8.875152 | P6: -9.6980083 | Q6: 12.883202 | R6: 82.120249 | S6: 23.6376 | T6: 1.4659197 | U6: 8.3874136 | V6: 3.2040911 | W6: -0.51646779 | X6: 0 | Y6: 0 | Z6: 0 | AA6: 0 | AB6: =SUM(AC6:AM6) -> 4.4601014 | AE6: 0.26707428 | AI6: 1.7828522 | AJ6: 2.410175 | AQ6: =C6+H6+L6+AA6+AB6+AN6+AO6+AP6 -> -68.395488
A7: Primary Energy Supply (incl non-energy) | C7: =C2+C3-C4-C5+C6 -> 787.05173 | D7: =D2+D3-D4-D5+D6 -> 727.70471 | E7: =E2+E3-E4-E5+E6 -> 46.817169 | F7: =F2+F3-F4-F5+F6 -> 0 | G7: =G2+G3-G4-G5+G6 -> 12.529851 | H7: =H2+H3-H4-H5+H6 -> 685.95223 | I7: =I2+I3-I4-I5+I6 -> 551.68208 | J7: =J2+J3-J4-J5+J6 -> 127.704 | ... AP7: =AP2+AP3-AP4-AP5+AP6 -> 0 | AQ7: =C7+H7+L7+AA7+AB7+AN7+AO7+AP7 -> 14978.04
A8: Primary Energy Requirement (excl. non-energy) | C8: =C7-C27 -> 787.05173 | D8: =D7-D27 -> 727.70471 | E8: =E7-E27 -> 46.817169 | F8: =F7-F27 -> 0 | G8: =G7-G27 -> 12.529851 | H8: =H7-H27 -> 685.95223 | I8: =I7-I27 -> 551.68208 | J8: =J7-J27 -> 127.704 | ... AP8: =AP7-AP27 -> 0 | AQ8: =C8+H8+L8+AA8+AB8+AN8+AO8+AP8 -> 14978.04
A9: Transformation Input | C9: =SUM(C10:C14) -> 489.1342 | D9: =SUM(D10:D14) -> 489.1342 | E9: =SUM(E10:E14) -> 0 | F9: =SUM(F10:F14) -> 0 | G9: =SUM(G10:G14) -> 0 | H9: =SUM(H10:H14) -> 541.02658 | I9: =SUM(I10:I14) -> 541.02658 | J9: =SUM(J10:J14) -> 0 | ... AP9: =SUM(AP10:AP14) -> 0 | AQ9: =C9+H9+L9+AA9+AB9+AN9+AO9+AP9 -> 7058.1841
A10: Public Thermal Power Plants (Input) | C10: =SUM(D10:G10) -> 489.1342 | D10: 489.1342 | H10: =SUM(I10:K10) -> 467.10846 | I10: 467.10846 | J10: 0 | L10: =SUM(M10:Z10) -> 34.094789 | S10: 25.868327 | U10: 8.2264622 | AA10: 2187.6034 | AB10: =SUM(AC10:AM10) -> 205.3059 | AE10: 72.46706 | AF10: 99.307023 | AG10: 33.531819 | AN10: 90.714163 | AQ10: =C10+H10+L10+AA10+AB10+AN10+AO10+AP10 -> 3473.9609
A11: Combined Heat and Power Plants (Input) | C11: =SUM(D11:G11) -> 0 | D11: 0 | H11: =SUM(I11:K11) -> 5.8425469 | I11: 5.8425469 | L11: =SUM(M11:Z11) -> 0.63499472 | O11: 0 | S11: 0 | T11: 0.63499472 | U11: 0 | AA11: 272.96145 | AB11: =SUM(AC11:AM11) -> 10.597627 | AE11: 3.561556 | AH11: 7.0360715 | AQ11: =C11+H11+L11+AA11+AB11+AN11+AO11+AP11 -> 290.03662
A12: Pumped Storage Consumption (Input) | AO12: 42.94206 | AQ12: =C12+H12+L12+AA12+AB12+AN12+AO12+AP12 -> 42.94206
A13: Briquetting Plants (Input) | C13: =SUM(D13:G13) -> 0 | H13: =SUM(I13:K13) -> 68.075577 | I13: 68.075577 | L13: =SUM(M13:Z13) -> 0 | AB13: =SUM(AC13:AM13) -> 0 | AQ13: =C13+H13+L13+AA13+AB13+AN13+AO13+AP13 -> 68.075577
A14: Oil Refineries & other energy sector (Input) | C14: =SUM(D14:G14) -> 0 | H14: =SUM(I14:K14) -> 0 | L14: =SUM(M14:Z14) -> 3130.9919 | M14: 3092.2053 | N14: 38.786602 | AA14: 40.734585 | AB14: =SUM(AC14:AM14) -> 0 | AO14: 11.442472 | AQ14: =C14+H14+L14+AA14+AB14+AN14+AO14+AP14 -> 3183.1689
A15: Transformation Output | C15: =SUM(C16:C20) -> 0 | D15: =SUM(D16:D20) -> 0 | E15: =SUM(E16:E20) -> 0 | F15: =SUM(F16:F20) -> 0 | G15: =SUM(G16:G20) -> 0 | H15: =SUM(H16:H20) -> 64.671798 | I15: =SUM(I16:I20) -> 0 | J15: =SUM(J16:J20) -> 0 | ... AP15: =SUM(AP16:AP20) -> 0 | AQ15: =C15+H15+L15+AA15+AB15+AN15+AO15+AP15 -> 5104.8192
A16: Public Thermal Power Plants (Output) | C16: =SUM(D16:G16) -> 0 | H16: =SUM(I16:K16) -> 0 | L16: =SUM(M16:Z16) -> 0 | AB16: =SUM(AC16:AL16) -> 0 | AO16: 1667.7866 | AQ16: =C16+H16+L16+AA16+AO16+AP16 -> 1667.7866
A17: Combined Heat and Power Plants (Output) | C17: =SUM(D17:G17) -> 0 | H17: =SUM(I17:K17) -> 0 | L17: =SUM(M17:Z17) -> 0 | AB17: =SUM(AC17:AL17) -> 0 | AO17: 185.14396 | AQ17: =C17+H17+L17+AA17+AO17+AP17 -> 185.14396
A18: Pumped Storage Generation (Output) | AO18: 20.430939 | AQ18: =C18+H18+L18+AA18+AB18+AN18+AO18+AP18 -> 20.430939
A19: Briquetting Plants (Output) | H19: =SUM(I19:K19) -> 64.671798 | K19: 64.671798 | L19: =SUM(M19:Z19) -> 0 | AB19: =SUM(AC19:AL19) -> 0 | AQ19: =C19+H19+L19+AA19+AB19+AN19+AO19+AP19 -> 64.671798
A20: Oil Refineries & other energy sector (Output) | H20: =SUM(I20:K20) -> 0 | L20: =SUM(M20:Z20) -> 3166.7859 | O20: 90.017984 | P20: 640.5368 | Q20: 226.77459 | R20: 0 | S20: 960.95018 | T20: 64.797463 | U20: 1146.9502 | W20: 36.758644 | AB20: =SUM(AC20:AL20) -> 0 | AQ20: =C20+H20+L20+AA20+AB20+AN20+AO20+AP20 -> 3166.7859
A21: Exchanges and transfers | C21: =SUM(C22:C24) -> 22.240062 | D21: =SUM(D22:D24) -> -17.141361 | E21: =SUM(E22:E24) -> 39.381423 | F21: =SUM(F22:F24) -> 0 | G21: =SUM(G22:G24) -> 0 | H21: =SUM(I21:K21) -> 0 | I21: =SUM(I22:I24) -> 0 | J21: =SUM(J22:J24) -> 0 | K21: =SUM(K22:K24) -> 0 | L21: =SUM(M21:Z21) -> -24.684016 | M21: =SUM(M22:M24) -> 0 | N21: =SUM(N22:N24) -> 30.880435 | O21: =SUM(O22:O24) -> 0 | P21: =SUM(P22:P24) -> -31.331711 | Q21: =SUM(Q22:Q24) -> 361.9108 | R21: =SUM(R22:R24) -> -361.12225 | S21: =SUM(S22:S24) -> -0.17168421 | T21: =SUM(T22:T24) -> 0 | ... AQ21: =SUM(AQ22:AQ24) -> -2.4439548
A22: Electricity Exchange & Transfers | AB22: =SUM(AC22:AM22) -> -804.60162 | AC22: =-AC2 -> -59.691709 | AD22: =-AD2 -> -743.01992 | AK22: -1.8899881 | AO22: =-(C22+H22+L22+AA22+AB22) -> 804.60162 | AQ22: =C22+H22+L22+AA22+AB22+AN22+AO22+AP22 -> 0
A23: Heat Exchange & Transfers | AQ23: =C23+H23+L23+AA23+AB23+AN23+AO23+AP23 -> 0
A24: Other Exchange & Transfers | C24: =SUM(D24:G24) -> 22.240062 | D24: -17.141361 | E24: =-D24-V24 -> 39.381423 | L24: =SUM(N24:Z24) -> -24.684016 | N24: 30.880435 | P24: -31.331711 | Q24: 361.9108 | R24: -361.12225 | S24: -0.17168421 | U24: -2.6095464 | V24: -22.240062 | W24: 0 | AB24: =SUM(AC24:AM24) -> 0 | AQ24: =C24+H24+L24+AA24+AB24+AN24+AO24+AP24 -> -2.4439548
A25: Own Use and Distribution Losses | C25: =SUM(D25:G25) -> 0 | H25: =SUM(I25:K25) -> 10.283248 | I25: 10.283248 | L25: =SUM(O25:Z25) -> 98.284658 | O25: 95.274692 | S25: 0 | T25: 0.0041693256 | U25: 3.0057963 | AA25: 57.5286 | AB25: =SUM(AC25:AI25) -> 0 | AO25: 259.46681 | AQ25: =C25+H25+L25+AA25+AB25+AN25+AO25+AP25 -> 425.56332
A26: Available Final Energy Consumption | C26: =C7-C9+C15+C21-C25 -> 320.1576 | D26: =D7-D9+D15+D21-D25 -> 221.42916 | E26: =E7-E9+E15+E21-E25 -> 86.198592 | F26: =F7-F9+F15+F21-F25 -> 0 | G26: =G7-G9+G15+G21-G25 -> 12.529851 | H26: =H7-H9+H15+H21-H25 -> 199.3142 | I26: =I7-I9+I15+I21-I25 -> 0.37225107 | J26: =J7-J9+J15+J21-J25 -> 127.704 | ... AP26: =AP7-AP9+AP15+AP21-AP25 -> 0 | AQ26: =C26+H26+L26+AA26+AB26+AN26+AO26+AP26 -> 12596.668

Sheet CONVENTIONS
B3: Energy Commodities | E3: Technologies - Convention for Naming | L3: . | M3: Emission Commodities | P3: Sectors | S3: Transformations | V3: Suffixes | Y3: Commodity State | AB3: Commodity Type
B4: Code | C4: Description | E4: Code | F4: Description | G4: Technology type | H4: Fuel | I4: Technology Type | J4: Suffix (Technology Generation or regions) | K4: TIMES Set | M4: Code | N4: Description | P4: Code | Q4: Description | S4: Code | T4: Description | V4: Code | W4: Description | Y4: Code | Z4: Description | AB4: Code | AC4: Description
B5: COA | C5: Coal | E5: =I5&H5&J5 -> IMPCOABIT | F5: =G5 & " of " & VLOOKUP(H5,$B$5:$C$84,2,FALSE) & IF(J5<>0,IF(VLOOKUP(J5,$V$5:$W$12,2,FALSE)<>""," - " & VLOOKUP(J5,$V$5:$W$12,2,FALSE),""),"") -> Import of Bituminous Coal | G5: =VLOOKUP(I5,$S$5:$T$10,2,FALSE) -> Import | H5: =B38 -> COABIT | I5: =$S$6 -> IMP | K5: IMP | M5: CH4N | N5: Methane - eNergy Emissions | P5: SUP | Q5: Supply and Upstream | S5: MIN | T5: Domestic Potential | V5: _UK | W5: UK | Y5: G | Z5: gaseous | AB5: C | AC5: centralised
B6: DST | C6: Diesel | E6: =I6&H6&J6 -> IMPCOAHAR | F6: =G6 & " of " & VLOOKUP(H6,$B$5:$C$84,2,FALSE) & IF(J6<>0,IF(VLOOKUP(J6,$V$5:$W$12,2,FALSE)<>""," - " & VLOOKUP(J6,$V$5:$W$12,2,FALSE),""),"") -> Import of Hard Coal / Antracite | G6: =VLOOKUP(I6,$S$5:$T$10,2,FALSE) -> Import | H6: =B39 -> COAHAR | I6: =$S$6 -> IMP | K6: IMP | M6: CH4P | N6: Methane Emissions - Process Emissions | P6: ELC | Q6: Electricity | S6: IMP | T6: Import | V6: _UK-EWIC | W6: UK East-West Interconnector | Y6: L | Z6: liquid | AB6: D | AC6: decentralised
B7: GSL | C7: Gasoline | E7: =I7&H7&J7 -> IMPCOACOK | F7: =G7 & " of " & VLOOKUP(H7,$B$5:$C$84,2,FALSE) & IF(J7<>0,IF(VLOOKUP(J7,$V$5:$W$12,2,FALSE)<>""," - " & VLOOKUP(J7,$V$5:$W$12,2,FALSE),""),"") -> Import of Coke Coal | G7: =VLOOKUP(I7,$S$5:$T$10,2,FALSE) -> Import | H7: =B40 -> COACOK | I7: =$S$6 -> IMP | K7: IMP | M7: N2ON | N7: N2O Emissions - eNergy Emissions | S7: EXP | T7: Export | V7: _GLOBAL
B8: HFO | C8: Heavy Fuel Oil | E8: =I8&H8&J8 -> IMPCOALIG | F8: =G8 & " of " & VLOOKUP(H8,$B$5:$C$84,2,FALSE) & IF(J8<>0,IF(VLOOKUP(J8,$V$5:$W$12,2,FALSE)<>""," - " & VLOOKUP(J8,$V$5:$W$12,2,FALSE),""),"") -> Import of Lignite / Brown Coal | G8: =VLOOKUP(I8,$S$5:$T$10,2,FALSE) -> Import | H8: =B41 -> COALIG | I8: =$S$6 -> IMP | K8: IMP | M8: SO2N | N8: Sulfur dioxide - eNergy Emissions | S8: REF | T8: Refinery | V8: _Whitegate | W8: Whitegate
B9: KER | C9: Kerosene | E9: =I9&H9&J9 -> IMPOILCRD | F9: =G9 & " of " & VLOOKUP(H9,$B$5:$C$84,2,FALSE) & IF(J9<>0,IF(VLOOKUP(J9,$V$5:$W$12,2,FALSE)<>""," - " & VLOOKUP(J9,$V$5:$W$12,2,FALSE),""),"") -> Import of Crude Oil | G9: =VLOOKUP(I9,$S$5:$T$10,2,FALSE) -> Import | H9: =B43 -> OILCRD | I9: =$S$6 -> IMP | K9: IMP | M9: CO2N | N9: Carbon Dioxide - eNergy Emissions | S9: FT- | T9: Fuel Tech | V9: _S1 | W9: Step 1
B10: LPG | C10: Liquified Petroleum Gases | E10: =I10&H10&J10 -> IMPOILKER | F10: =G10 & " of " & VLOOKUP(H10,$B$5:$C$84,2,FALSE) & IF(J10<>0,IF(VLOOKUP(J10,$V$5:$W$12,2,FALSE)<>""," - " & VLOOKUP(J10,$V$5:$W$12,2,FALSE),""),"") -> Import of Kerosene | G10: =VLOOKUP(I10,$S$5:$T$10,2,FALSE) -> Import | H10: =B45 -> OILKER | I10: =$S$6 -> IMP | K10: IMP | M10: CO2P | N10: Carbon Dioxide - Process Emissions | V10: _S2 | W10: Step 2
B11: OIL | C11: Oil | E11: =I11&H11&J11 -> IMPOILHFO | F11: =G11 & " of " & VLOOKUP(H11,$B$5:$C$84,2,FALSE) & IF(J11<>0,IF(VLOOKUP(J11,$V$5:$W$12,2,FALSE)<>""," - " & VLOOKUP(J11,$V$5:$W$12,2,FALSE),""),"") -> Import of Heavy Fuel Oil | G11: =VLOOKUP(I11,$S$5:$T$10,2,FALSE) -> Import | H11: =B46 -> OILHFO | I11: =$S$6 -> IMP | K11: IMP | M11: CO2S | N11: Carbon Dioxide - Sequestered | V11: _S3 | W11: Step 3
B12: NGA | C12: Natural Gas | E12: =I12&H12&J12 -> IMPOILDST | F12: =G12 & " of " & VLOOKUP(H12,$B$5:$C$84,2,FALSE) & IF(J12<>0,IF(VLOOKUP(J12,$V$5:$W$12,2,FALSE)<>""," - " & VLOOKUP(J12,$V$5:$W$12,2,FALSE),""),"") -> Import of Diesel Oil | G12: =VLOOKUP(I12,$S$5:$T$10,2,FALSE) -> Import | H12: =B47 -> OILDST | I12: =$S$6 -> IMP | K12: IMP | M12: NOXN | N12: Nitrogen Oxide - eNergy Emissions | V12: _S4 | W12: Step 4
B13: BIO | C13: Biomass | E13: =I13&H13&J13 -> IMPOILLPG | F13: =G13 & " of " & VLOOKUP(H13,$B$5:$C$84,2,FALSE) & IF(J13<>0,IF(VLOOKUP(J13,$V$5:$W$12,2,FALSE)<>""," - " & VLOOKUP(J13,$V$5:$W$12,2,FALSE),""),"") -> Import of Liquified Petroleum Gas | G13: =VLOOKUP(I13,$S$5:$T$10,2,FALSE) -> Import | H13: =B48 -> OILLPG | I13: =$S$6 -> IMP | K13: IMP | M13: PM10 | N13: Particulate Matter <10 µm
B14: BLQ | C14: Bioliquid | E14: =I14&H14&J14 -> IMPOILGSL | F14: =G14 & " of " & VLOOKUP(H14,$B$5:$C$84,2,FALSE) & IF(J14<>0,IF(VLOOKUP(J14,$V$5:$W$12,2,FALSE)<>""," - " & VLOOKUP(J14,$V$5:$W$12,2,FALSE),""),"") -> Import of Gasoline | G14: =VLOOKUP(I14,$S$5:$T$10,2,FALSE) -> Import | H14: =B49 -> OILGSL | I14: =$S$6 -> IMP | K14: IMP | M14: PM25 | N14: Particulate Matter <2.5 µm
B15: BSL | C15: Biomass solid | E15: =I15&H15&J15 -> IMPOILCOK | F15: =G15 & " of " & VLOOKUP(H15,$B$5:$C$84,2,FALSE) & IF(J15<>0,IF(VLOOKUP(J15,$V$5:$W$12,2,FALSE)<>""," - " & VLOOKUP(J15,$V$5:$W$12,2,FALSE),""),"") -> Import of Petroleum Coke | G15: =VLOOKUP(I15,$S$5:$T$10,2,FALSE) -> Import | H15: =B50 -> OILCOK | I15: =$S$6 -> IMP | K15: IMP
B16: BGA | C16: Biogas | E16: =I16&H16&J16 -> IMPOILNEU | F16: =G16 & " of " & VLOOKUP(H16,$B$5:$C$84,2,FALSE) & IF(J16<>0,IF(VLOOKUP(J16,$V$5:$W$12,2,FALSE)<>""," - " & VLOOKUP(J16,$V$5:$W$12,2,FALSE),""),"") -> Import of Oil for Non-Energy uses | G16: =VLOOKUP(I16,$S$5:$T$10,2,FALSE) -> Import | H16: =B52 -> OILNEU | I16: =$S$6 -> IMP | K16: IMP
B17: BWA | C17: Bio Wastes | E17: =I17&H17&J17 -> IMPGASNAT_UK | F17: =G17 & " of " & VLOOKUP(H17,$B$5:$C$84,2,FALSE) & IF(J17<>0,IF(VLOOKUP(J17,$V$5:$W$12,2,FALSE)<>""," - " & VLOOKUP(J17,$V$5:$W$12,2,FALSE),""),"") -> Import of Natural Gas - UK | G17: =VLOOKUP(I17,$S$5:$T$10,2,FALSE) -> Import | H17: =B53 -> GASNAT | I17: =$S$6 -> IMP | J17: =V5 -> _UK | K17: IMP
B18: AVG | C18: Aviation Gasoline | E18: =I18&H18&J18 -> IMPGASLNG_GLOBAL | F18: =G18 & " of " & VLOOKUP(H18,$B$5:$C$84,2,FALSE) & IF(J18<>0,IF(VLOOKUP(J18,$V$5:$W$12,2,FALSE)<>""," - " & VLOOKUP(J18,$V$5:$W$12,2,FALSE),""),"") -> Import of Liquified Natural Gas | G18: =VLOOKUP(I18,$S$5:$T$10,2,FALSE) -> Import | H18: =B54 -> GASLNG | I18: =$S$6 -> IMP | J18: =V7 -> _GLOBAL | K18: IMP
B19: JTK | C19: Jet Kerosene | E19: =I19&H19&J19 -> IMPNUCURM | F19: =G19 & " of " & VLOOKUP(H19,$B$5:$C$84,2,FALSE) & IF(J19<>0,IF(VLOOKUP(J19,$V$5:$W$12,2,FALSE)<>""," - " & VLOOKUP(J19,$V$5:$W$12,2,FALSE),""),"") -> Import of Uranium | G19: =VLOOKUP(I19,$S$5:$T$10,2,FALSE) -> Import | H19: =B55 -> NUCURM | I19: =$S$6 -> IMP | K19: IMP
B20: BDL | C20: Bio Diesel | E20: =I20&H20&J20 -> IMPBIOETH1G_S1 | F20: =G20 & " of " & VLOOKUP(H20,$B$5:$C$84,2,FALSE) & IF(J20<>0,IF(VLOOKUP(J20,$V$5:$W$12,2,FALSE)<>""," - " & VLOOKUP(J20,$V$5:$W$12,2,FALSE),""),"") -> Import of Ethanol 1st generation - Step 1 | G20: =VLOOKUP(I20,$S$5:$T$10,2,FALSE) -> Import | H20: =B62 -> BIOETH1G | I20: =$S$6 -> IMP | J20: =$V$9 -> _S1 | K20: IMP
B21: BGL | C21: Bio Gasoline | E21: =I21&H21&J21 -> IMPBIOETH1G_S2 | F21: =G21 & " of " & VLOOKUP(H21,$B$5:$C$84,2,FALSE) & IF(J21<>0,IF(VLOOKUP(J21,$V$5:$W$12,2,FALSE)<>""," - " & VLOOKUP(J21,$V$5:$W$12,2,FALSE),""),"") -> Import of Ethanol 1st generation - Step 2 | G21: =VLOOKUP(I21,$S$5:$T$10,2,FALSE) -> Import | H21: =B62 -> BIOETH1G | I21: =$S$6 -> IMP | J21: =$V$10 -> _S2 | K21: IMP
B22: BGA | C22: Bio Gas | E22: =I22&H22&J22 -> IMPBIOETH1G_S3 | F22: =G22 & " of " & VLOOKUP(H22,$B$5:$C$84,2,FALSE) & IF(J22<>0,IF(VLOOKUP(J22,$V$5:$W$12,2,FALSE)<>""," - " & VLOOKUP(J22,$V$5:$W$12,2,FALSE),""),"") -> Import of Ethanol 1st generation - Step 3 | G22: =VLOOKUP(I22,$S$5:$T$10,2,FALSE) -> Import | H22: =B62 -> BIOETH1G | I22: =$S$6 -> IMP | J22: =$V$11 -> _S3 | K22: IMP
B23: BJK | C23: Jet Bio Kerosene | E23: =I23&H23&J23 -> IMPBIOETH1G_S4 | F23: =G23 & " of " & VLOOKUP(H23,$B$5:$C$84,2,FALSE) & IF(J23<>0,IF(VLOOKUP(J23,$V$5:$W$12,2,FALSE)<>""," - " & VLOOKUP(J23,$V$5:$W$12,2,FALSE),""),"") -> Import of Ethanol 1st generation - Step 4 | G23: =VLOOKUP(I23,$S$5:$T$10,2,FALSE) -> Import | H23: =B62 -> BIOETH1G | I23: =$S$6 -> IMP | J23: =$V$12 -> _S4 | K23: IMP
B24: SOL | C24: Solar | E24: =I24&H24&J24 -> IMPBIODST1G_S1 | F24: =G24 & " of " & VLOOKUP(H24,$B$5:$C$84,2,FALSE) & IF(J24<>0,IF(VLOOKUP(J24,$V$5:$W$12,2,FALSE)<>""," - " & VLOOKUP(J24,$V$5:$W$12,2,FALSE),""),"") -> Import of Biodiesel 1st generation - Step 1 | G24: =VLOOKUP(I24,$S$5:$T$10,2,FALSE) -> Import | H24: =B64 -> BIODST1G | I24: =$S$6 -> IMP | J24: =$V$9 -> _S1 | K24: IMP
B25: SPV | C25: Solar Photovoltaic | E25: =I25&H25&J25 -> IMPBIODST1G_S2 | F25: =G25 & " of " & VLOOKUP(H25,$B$5:$C$84,2,FALSE) & IF(J25<>0,IF(VLOOKUP(J25,$V$5:$W$12,2,FALSE)<>""," - " & VLOOKUP(J25,$V$5:$W$12,2,FALSE),""),"") -> Import of Biodiesel 1st generation - Step 2 | G25: =VLOOKUP(I25,$S$5:$T$10,2,FALSE) -> Import | H25: =B64 -> BIODST1G | I25: =$S$6 -> IMP | J25: =$V$10 -> _S2 | K25: IMP
B26: STH | C26: Solar Thermal | E26: =I26&H26&J26 -> IMPBIODST1G_S3 | F26: =G26 & " of " & VLOOKUP(H26,$B$5:$C$84,2,FALSE) & IF(J26<>0,IF(VLOOKUP(J26,$V$5:$W$12,2,FALSE)<>""," - " & VLOOKUP(J26,$V$5:$W$12,2,FALSE),""),"") -> Import of Biodiesel 1st generation - Step 3 | G26: =VLOOKUP(I26,$S$5:$T$10,2,FALSE) -> Import | H26: =B64 -> BIODST1G | I26: =$S$6 -> IMP | J26: =$V$11 -> _S3 | K26: IMP
B27: GEO | C27: Geothermal | E27: =I27&H27&J27 -> IMPBIODST1G_S4 | F27: =G27 & " of " & VLOOKUP(H27,$B$5:$C$84,2,FALSE) & IF(J27<>0,IF(VLOOKUP(J27,$V$5:$W$12,2,FALSE)<>""," - " & VLOOKUP(J27,$V$5:$W$12,2,FALSE),""),"") -> Import of Biodiesel 1st generation - Step 4 | G27: =VLOOKUP(I27,$S$5:$T$10,2,FALSE) -> Import | H27: =B64 -> BIODST1G | I27: =$S$6 -> IMP | J27: =$V$12 -> _S4 | K27: IMP
B28: WIN | C28: Wind | E28: =I28&H28&J28 -> IMPBIOJKR_S1 | F28: =G28 & " of " & VLOOKUP(H28,$B$5:$C$84,2,FALSE) & IF(J28<>0,IF(VLOOKUP(J28,$V$5:$W$12,2,FALSE)<>""," - " & VLOOKUP(J28,$V$5:$W$12,2,FALSE),""),"") -> Import of Bio Jet Kerosene - Step 1 | G28: =VLOOKUP(I28,$S$5:$T$10,2,FALSE) -> Import | H28: =B68 -> BIOJKR | I28: =$S$6 -> IMP | J28: =$V$9 -> _S1 | K28: IMP
B29: WON | C29: Wind On-Shore | E29: =I29&H29&J29 -> IMPBIOWPE_S1 | F29: =G29 & " of " & VLOOKUP(H29,$B$5:$C$84,2,FALSE) & IF(J29<>0,IF(VLOOKUP(J29,$V$5:$W$12,2,FALSE)<>""," - " & VLOOKUP(J29,$V$5:$W$12,2,FALSE),""),"") -> Import of Wood Pellets - Step 1 | G29: =VLOOKUP(I29,$S$5:$T$10,2,FALSE) -> Import | H29: =B73 -> BIOWPE | I29: =$S$6 -> IMP | J29: =$V$9 -> _S1 | K29: IMP
B30: WOF | C30: Wind Off-Shore | E30: =I30&H30&J30 -> IMPBIOWPE_S2 | F30: =G30 & " of " & VLOOKUP(H30,$B$5:$C$84,2,FALSE) & IF(J30<>0,IF(VLOOKUP(J30,$V$5:$W$12,2,FALSE)<>""," - " & VLOOKUP(J30,$V$5:$W$12,2,FALSE),""),"") -> Import of Wood Pellets - Step 2 | G30: =VLOOKUP(I30,$S$5:$T$10,2,FALSE) -> Import | H30: =B73 -> BIOWPE | I30: =$S$6 -> IMP | J30: =$V$10 -> _S2 | K30: IMP
B31: HYD | C31: Hydro | E31: =I31&H31&J31 -> IMPBIOWPE_S3 | F31: =G31 & " of " & VLOOKUP(H31,$B$5:$C$84,2,FALSE) & IF(J31<>0,IF(VLOOKUP(J31,$V$5:$W$12,2,FALSE)<>""," - " & VLOOKUP(J31,$V$5:$W$12,2,FALSE),""),"") -> Import of Wood Pellets - Step 3 | G31: =VLOOKUP(I31,$S$5:$T$10,2,FALSE) -> Import | H31: =B73 -> BIOWPE | I31: =$S$6 -> IMP | J31: =$V$11 -> _S3 | K31: IMP
B32: TDL | C32: Tide | E32: =I32&H32&J32 -> IMPBIOWPE_S4 | F32: =G32 & " of " & VLOOKUP(H32,$B$5:$C$84,2,FALSE) & IF(J32<>0,IF(VLOOKUP(J32,$V$5:$W$12,2,FALSE)<>""," - " & VLOOKUP(J32,$V$5:$W$12,2,FALSE),""),"") -> Import of Wood Pellets - Step 4 | G32: =VLOOKUP(I32,$S$5:$T$10,2,FALSE) -> Import | H32: =B73 -> BIOWPE | I32: =$S$6 -> IMP | J32: =$V$12 -> _S4 | K32: IMP
B33: WAV | C33: Wave | E33: =I33&H33&J33 -> IMPBIOWCH_S1 | F33: =G33 & " of " & VLOOKUP(H33,$B$5:$C$84,2,FALSE) & IF(J33<>0,IF(VLOOKUP(J33,$V$5:$W$12,2,FALSE)<>""," - " & VLOOKUP(J33,$V$5:$W$12,2,FALSE),""),"") -> Import of Wood Chip - Step 1 | G33: =VLOOKUP(I33,$S$5:$T$10,2,FALSE) -> Import | H33: =B74 -> BIOWCH | I33: =$S$6 -> IMP | J33: =$V$9 -> _S1 | K33: IMP
B34: NUC | C34: Uranium | E34: =I34&H34&J34 -> IMPBIOWCH_S2 | F34: =G34 & " of " & VLOOKUP(H34,$B$5:$C$84,2,FALSE) & IF(J34<>0,IF(VLOOKUP(J34,$V$5:$W$12,2,FALSE)<>""," - " & VLOOKUP(J34,$V$5:$W$12,2,FALSE),""),"") -> Import of Wood Chip - Step 2 | G34: =VLOOKUP(I34,$S$5:$T$10,2,FALSE) -> Import | H34: =B74 -> BIOWCH | I34: =$S$6 -> IMP | J34: =$V$10 -> _S2 | K34: IMP
B35: ELC | C35: Electricity | E35: =I35&H35&J35 -> IMPBIOWCH_S3 | F35: =G35 & " of " & VLOOKUP(H35,$B$5:$C$84,2,FALSE) & IF(J35<>0,IF(VLOOKUP(J35,$V$5:$W$12,2,FALSE)<>""," - " & VLOOKUP(J35,$V$5:$W$12,2,FALSE),""),"") -> Import of Wood Chip - Step 3 | G35: =VLOOKUP(I35,$S$5:$T$10,2,FALSE) -> Import | H35: =B74 -> BIOWCH | I35: =$S$6 -> IMP | J35: =$V$11 -> _S3 | K35: IMP
B36: HET | C36: Heat | E36: =I36&H36&J36 -> IMPBIOWCH_S4 | F36: =G36 & " of " & VLOOKUP(H36,$B$5:$C$84,2,FALSE) & IF(J36<>0,IF(VLOOKUP(J36,$V$5:$W$12,2,FALSE)<>""," - " & VLOOKUP(J36,$V$5:$W$12,2,FALSE),""),"") -> Import of Wood Chip - Step 4 | G36: =VLOOKUP(I36,$S$5:$T$10,2,FALSE) -> Import | H36: =B74 -> BIOWCH | I36: =$S$6 -> IMP | J36: =$V$12 -> _S4 | K36: IMP
B37: WAS | C37: Waste | E37: =I37&H37&J37 -> MINGASNAT_S1 | F37: =G37 & " of " & VLOOKUP(H37,$B$5:$C$84,2,FALSE) & IF(J37<>0,IF(VLOOKUP(J37,$V$5:$W$12,2,FALSE)<>""," - " & VLOOKUP(J37,$V$5:$W$12,2,FALSE),""),"") -> Domestic Potential of Natural Gas - Step 1 | G37: =VLOOKUP(I37,$S$5:$T$10,2,FALSE) -> Domestic Potential | H37: =B53 -> GASNAT | I37: =$S$5 -> MIN | J37: =$V$9 -> _S1 | K37: MIN
B38: COABIT | C38: Bituminous Coal | E38: =I38&H38&J38 -> MINGASNAT_S2 | F38: =G38 & " of " & VLOOKUP(H38,$B$5:$C$84,2,FALSE) & IF(J38<>0,IF(VLOOKUP(J38,$V$5:$W$12,2,FALSE)<>""," - " & VLOOKUP(J38,$V$5:$W$12,2,FALSE),""),"") -> Domestic Potential of Natural Gas - Step 2 | G38: =VLOOKUP(I38,$S$5:$T$10,2,FALSE) -> Domestic Potential | H38: =B53 -> GASNAT | I38: =$S$5 -> MIN | J38: =$V$10 -> _S2 | K38: MIN
B39: COAHAR | C39: Hard Coal / Antracite | E39: =I39&H39&J39 -> MINPEAT_S1 | F39: =G39 & " of " & VLOOKUP(H39,$B$5:$C$84,2,FALSE) & IF(J39<>0,IF(VLOOKUP(J39,$V$5:$W$12,2,FALSE)<>""," - " & VLOOKUP(J39,$V$5:$W$12,2,FALSE),""),"") -> Domestic Potential of Peat - Step 1 | G39: =VLOOKUP(I39,$S$5:$T$10,2,FALSE) -> Domestic Potential | H39: =B42 -> PEAT | I39: =$S$5 -> MIN | J39: =$V$9 -> _S1 | K39: MIN
B40: COACOK | C40: Coke Coal | E40: =I40&H40&J40 -> MINPEAT_S2 | F40: =G40 & " of " & VLOOKUP(H40,$B$5:$C$84,2,FALSE) & IF(J40<>0,IF(VLOOKUP(J40,$V$5:$W$12,2,FALSE)<>""," - " & VLOOKUP(J40,$V$5:$W$12,2,FALSE),""),"") -> Domestic Potential of Peat - Step 2 | G40: =VLOOKUP(I40,$S$5:$T$10,2,FALSE) -> Domestic Potential | H40: =B42 -> PEAT | I40: =$S$5 -> MIN | J40: =$V$10 -> _S2 | K40: MIN
B41: COALIG | C41: Lignite / Brown Coal | E41: =I41&H41&J41 -> MINRENHYD | F41: =G41 & " of " & VLOOKUP(H41,$B$5:$C$84,2,FALSE) & IF(J41<>0,IF(VLOOKUP(J41,$V$5:$W$12,2,FALSE)<>""," - " & VLOOKUP(J41,$V$5:$W$12,2,FALSE),""),"") -> Domestic Potential of Hydro | G41: =VLOOKUP(I41,$S$5:$T$10,2,FALSE) -> Domestic Potential | H41: =B56 -> RENHYD | I41: =$S$5 -> MIN | K41: MIN
B42: PEAT | C42: Peat | E42: =I42&H42&J42 -> MINRENWIN | F42: =G42 & " of " & VLOOKUP(H42,$B$5:$C$84,2,FALSE) & IF(J42<>0,IF(VLOOKUP(J42,$V$5:$W$12,2,FALSE)<>""," - " & VLOOKUP(J42,$V$5:$W$12,2,FALSE),""),"") -> Domestic Potential of Wind | G42: =VLOOKUP(I42,$S$5:$T$10,2,FALSE) -> Domestic Potential | H42: =B57 -> RENWIN | I42: =$S$5 -> MIN | K42: MIN
B43: OILCRD | C43: Crude Oil | E43: =I43&H43&J43 -> MINRENSOL | F43: =G43 & " of " & VLOOKUP(H43,$B$5:$C$84,2,FALSE) & IF(J43<>0,IF(VLOOKUP(J43,$V$5:$W$12,2,FALSE)<>""," - " & VLOOKUP(J43,$V$5:$W$12,2,FALSE),""),"") -> Domestic Potential of Solar | G43: =VLOOKUP(I43,$S$5:$T$10,2,FALSE) -> Domestic Potential | H43: =B58 -> RENSOL | I43: =$S$5 -> MIN | K43: MIN
B44: OILRFG | C44: Refinery Gas | E44: =I44&H44&J44 -> MINMSWAS | F44: =G44 & " of " & VLOOKUP(H44,$B$5:$C$84,2,FALSE) & IF(J44<>0,IF(VLOOKUP(J44,$V$5:$W$12,2,FALSE)<>""," - " & VLOOKUP(J44,$V$5:$W$12,2,FALSE),""),"") -> Domestic Potential of Municipal Solid Waste | G44: =VLOOKUP(I44,$S$5:$T$10,2,FALSE) -> Domestic Potential | H44: =B59 -> MSWAS | I44: =$S$5 -> MIN | K44: MIN
B45: OILKER | C45: Kerosene | E45: =I45&H45&J45 -> MINRENOCE | F45: =G45 & " of " & VLOOKUP(H45,$B$5:$C$84,2,FALSE) & IF(J45<>0,IF(VLOOKUP(J45,$V$5:$W$12,2,FALSE)<>""," - " & VLOOKUP(J45,$V$5:$W$12,2,FALSE),""),"") -> Domestic Potential of Ocean | G45: =VLOOKUP(I45,$S$5:$T$10,2,FALSE) -> Domestic Potential | H45: =B60 -> RENOCE | I45: =$S$5 -> MIN | K45: MIN
B46: OILHFO | C46: Heavy Fuel Oil | E46: =I46&H46&J46 -> MINRENAHT | F46: =G46 & " of " & VLOOKUP(H46,$B$5:$C$84,2,FALSE) & IF(J46<>0,IF(VLOOKUP(J46,$V$5:$W$12,2,FALSE)<>""," - " & VLOOKUP(J46,$V$5:$W$12,2,FALSE),""),"") -> Domestic Potential of Ambient Heat | G46: =VLOOKUP(I46,$S$5:$T$10,2,FALSE) -> Domestic Potential | H46: =B61 -> RENAHT | I46: =$S$5 -> MIN | K46: MIN
B47: OILDST | C47: Diesel Oil | E47: =I47&H47&J47 -> MINBIOWOO1_S1 | F47: =G47 & " of " & VLOOKUP(H47,$B$5:$C$84,2,FALSE) & IF(J47<>0,IF(VLOOKUP(J47,$V$5:$W$12,2,FALSE)<>""," - " & VLOOKUP(J47,$V$5:$W$12,2,FALSE),""),"") -> Domestic Potential of Sawmill residues - Step 1 | G47: =VLOOKUP(I47,$S$5:$T$10,2,FALSE) -> Domestic Potential | H47: =$B$70 -> BIOWOO1 | I47: =$S$5 -> MIN | J47: =$V$9 -> _S1 | K47: MIN
B48: OILLPG | C48: Liquified Petroleum Gas | E48: =I48&H48&J48 -> MINBIOWOO1_S2 | F48: =G48 & " of " & VLOOKUP(H48,$B$5:$C$84,2,FALSE) & IF(J48<>0,IF(VLOOKUP(J48,$V$5:$W$12,2,FALSE)<>""," - " & VLOOKUP(J48,$V$5:$W$12,2,FALSE),""),"") -> Domestic Potential of Sawmill residues - Step 2 | G48: =VLOOKUP(I48,$S$5:$T$10,2,FALSE) -> Domestic Potential | H48: =$B$70 -> BIOWOO1 | I48: =$S$5 -> MIN | J48: =$V$10 -> _S2 | K48: MIN
B49: OILGSL | C49: Gasoline | E49: =I49&H49&J49 -> MINBIOWOO1_S3 | F49: =G49 & " of " & VLOOKUP(H49,$B$5:$C$84,2,FALSE) & IF(J49<>0,IF(VLOOKUP(J49,$V$5:$W$12,2,FALSE)<>""," - " & VLOOKUP(J49,$V$5:$W$12,2,FALSE),""),"") -> Domestic Potential of Sawmill residues - Step 3 | G49: =VLOOKUP(I49,$S$5:$T$10,2,FALSE) -> Domestic Potential | H49: =$B$70 -> BIOWOO1 | I49: =$S$5 -> MIN | J49: =$V$11 -> _S3 | K49: MIN
B50: OILCOK | C50: Petroleum Coke | E50: =I50&H50&J50 -> MINBIOWOO2_S1 | F50: =G50 & " of " & VLOOKUP(H50,$B$5:$C$84,2,FALSE) & IF(J50<>0,IF(VLOOKUP(J50,$V$5:$W$12,2,FALSE)<>""," - " & VLOOKUP(J50,$V$5:$W$12,2,FALSE),""),"") -> Domestic Potential of Post-Consumer Recycled Wood - Step 1 | G50: =VLOOKUP(I50,$S$5:$T$10,2,FALSE) -> Domestic Potential | H50: =$B$71 -> BIOWOO2 | I50: =$S$5 -> MIN | J50: =$V$9 -> _S1 | K50: MIN
B51: OILNAP | C51: Naphta | E51: =I51&H51&J51 -> MINBIOWOO2_S2 | F51: =G51 & " of " & VLOOKUP(H51,$B$5:$C$84,2,FALSE) & IF(J51<>0,IF(VLOOKUP(J51,$V$5:$W$12,2,FALSE)<>""," - " & VLOOKUP(J51,$V$5:$W$12,2,FALSE),""),"") -> Domestic Potential of Post-Consumer Recycled Wood - Step 2 | G51: =VLOOKUP(I51,$S$5:$T$10,2,FALSE) -> Domestic Potential | H51: =$B$71 -> BIOWOO2 | I51: =$S$5 -> MIN | J51: =$V$10 -> _S2 | K51: MIN
B52: OILNEU | C52: Oil for Non-Energy uses | E52: =I52&H52&J52 -> MINBIOWOO2_S3 | F52: =G52 & " of " & VLOOKUP(H52,$B$5:$C$84,2,FALSE) & IF(J52<>0,IF(VLOOKUP(J52,$V$5:$W$12,2,FALSE)<>""," - " & VLOOKUP(J52,$V$5:$W$12,2,FALSE),""),"") -> Domestic Potential of Post-Consumer Recycled Wood - Step 3 | G52: =VLOOKUP(I52,$S$5:$T$10,2,FALSE) -> Domestic Potential | H52: =$B$71 -> BIOWOO2 | I52: =$S$5 -> MIN | J52: =$V$11 -> _S3 | K52: MIN
B53: GASNAT | C53: Natural Gas | E53: =I53&H53&J53 -> MINBIOWOO3_S1 | F53: =G53 & " of " & VLOOKUP(H53,$B$5:$C$84,2,FALSE) & IF(J53<>0,IF(VLOOKUP(J53,$V$5:$W$12,2,FALSE)<>""," - " & VLOOKUP(J53,$V$5:$W$12,2,FALSE),""),"") -> Domestic Potential of Straw - Step 1 | G53: =VLOOKUP(I53,$S$5:$T$10,2,FALSE) -> Domestic Potential | H53: =$B$72 -> BIOWOO3 | I53: =$S$5 -> MIN | J53: =$V$9 -> _S1 | K53: MIN
B54: GASLNG | C54: Liquified Natural Gas | E54: =I54&H54&J54 -> MINBIOWOO3_S2 | F54: =G54 & " of " & VLOOKUP(H54,$B$5:$C$84,2,FALSE) & IF(J54<>0,IF(VLOOKUP(J54,$V$5:$W$12,2,FALSE)<>""," - " & VLOOKUP(J54,$V$5:$W$12,2,FALSE),""),"") -> Domestic Potential of Straw - Step 2 | G54: =VLOOKUP(I54,$S$5:$T$10,2,FALSE) -> Domestic Potential | H54: =$B$72 -> BIOWOO3 | I54: =$S$5 -> MIN | J54: =$V$10 -> _S2 | K54: MIN
B55: NUCURM | C55: Uranium | E55: =I55&H55&J55 -> MINBIOWOO3_S3 | F55: =G55 & " of " & VLOOKUP(H55,$B$5:$C$84,2,FALSE) & IF(J55<>0,IF(VLOOKUP(J55,$V$5:$W$12,2,FALSE)<>""," - " & VLOOKUP(J55,$V$5:$W$12,2,FALSE),""),"") -> Domestic Potential of Straw - Step 3 | G55: =VLOOKUP(I55,$S$5:$T$10,2,FALSE) -> Domestic Potential | H55: =$B$72 -> BIOWOO3 | I55: =$S$5 -> MIN | J55: =$V$11 -> _S3 | K55: MIN
B56: RENHYD | C56: Hydro | E56: =I56&H56&J56 -> MINBIOMSW1_S1 | F56: =G56 & " of " & VLOOKUP(H56,$B$5:$C$84,2,FALSE) & IF(J56<>0,IF(VLOOKUP(J56,$V$5:$W$12,2,FALSE)<>""," - " & VLOOKUP(J56,$V$5:$W$12,2,FALSE),""),"") -> Domestic Potential of Biodegradable Municipal Solid Waste potential - Solid - Step 1 | G56: =VLOOKUP(I56,$S$5:$T$10,2,FALSE) -> Domestic Potential | H56: =$B$75 -> BIOMSW1 | I56: =$S$5 -> MIN | J56: =$V$9 -> _S1 | K56: MIN
B57: RENWIN | C57: Wind | E57: =I57&H57&J57 -> MINBIOMSW1_S2 | F57: =G57 & " of " & VLOOKUP(H57,$B$5:$C$84,2,FALSE) & IF(J57<>0,IF(VLOOKUP(J57,$V$5:$W$12,2,FALSE)<>""," - " & VLOOKUP(J57,$V$5:$W$12,2,FALSE),""),"") -> Domestic Potential of Biodegradable Municipal Solid Waste potential - Solid - Step 2 | G57: =VLOOKUP(I57,$S$5:$T$10,2,FALSE) -> Domestic Potential | H57: =$B$75 -> BIOMSW1 | I57: =$S$5 -> MIN | J57: =$V$10 -> _S2 | K57: MIN
B58: RENSOL | C58: Solar | E58: =I58&H58&J58 -> MINBIOMSW1_S3 | F58: =G58 & " of " & VLOOKUP(H58,$B$5:$C$84,2,FALSE) & IF(J58<>0,IF(VLOOKUP(J58,$V$5:$W$12,2,FALSE)<>""," - " & VLOOKUP(J58,$V$5:$W$12,2,FALSE),""),"") -> Domestic Potential of Biodegradable Municipal Solid Waste potential - Solid - Step 3 | G58: =VLOOKUP(I58,$S$5:$T$10,2,FALSE) -> Domestic Potential | H58: =$B$75 -> BIOMSW1 | I58: =$S$5 -> MIN | J58: =$V$11 -> _S3 | K58: MIN
B59: MSWAS | C59: Municipal Solid Waste | E59: =I59&H59&J59 -> MINBIOMSW2_S1 | F59: =G59 & " of " & VLOOKUP(H59,$B$5:$C$84,2,FALSE) & IF(J59<>0,IF(VLOOKUP(J59,$V$5:$W$12,2,FALSE)<>""," - " & VLOOKUP(J59,$V$5:$W$12,2,FALSE),""),"") -> Domestic Potential of Biodegradable Municipal Solid Waste - Step 1 | G59: =VLOOKUP(I59,$S$5:$T$10,2,FALSE) -> Domestic Potential | H59: =$B$76 -> BIOMSW2 | I59: =$S$5 -> MIN | J59: =$V$9 -> _S1 | K59: MIN
B60: RENOCE | C60: Ocean | E60: =I60&H60&J60 -> MINBIOMSW2_S2 | F60: =G60 & " of " & VLOOKUP(H60,$B$5:$C$84,2,FALSE) & IF(J60<>0,IF(VLOOKUP(J60,$V$5:$W$12,2,FALSE)<>""," - " & VLOOKUP(J60,$V$5:$W$12,2,FALSE),""),"") -> Domestic Potential of Biodegradable Municipal Solid Waste - Step 2 | G60: =VLOOKUP(I60,$S$5:$T$10,2,FALSE) -> Domestic Potential | H60: =$B$76 -> BIOMSW2 | I60: =$S$5 -> MIN | J60: =$V$10 -> _S2 | K60: MIN
B61: RENAHT | C61: Ambient Heat | E61: =I61&H61&J61 -> MINBIOMSW2_S3 | F61: =G61 & " of " & VLOOKUP(H61,$B$5:$C$84,2,FALSE) & IF(J61<>0,IF(VLOOKUP(J61,$V$5:$W$12,2,FALSE)<>""," - " & VLOOKUP(J61,$V$5:$W$12,2,FALSE),""),"") -> Domestic Potential of Biodegradable Municipal Solid Waste - Step 3 | G61: =VLOOKUP(I61,$S$5:$T$10,2,FALSE) -> Domestic Potential | H61: =$B$76 -> BIOMSW2 | I61: =$S$5 -> MIN | J61: =$V$11 -> _S3 | K61: MIN
B62: BIOETH1G | C62: Ethanol 1st generation | E62: =I62&H62&J62 -> MINBIOTLW_S1 | F62: =G62 & " of " & VLOOKUP(H62,$B$5:$C$84,2,FALSE) & IF(J62<>0,IF(VLOOKUP(J62,$V$5:$W$12,2,FALSE)<>""," - " & VLOOKUP(J62,$V$5:$W$12,2,FALSE),""),"") -> Domestic Potential of Tallow - Step 1 | G62: =VLOOKUP(I62,$S$5:$T$10,2,FALSE) -> Domestic Potential | H62: =$B$77 -> BIOTLW | I62: =$S$5 -> MIN | J62: =$V$9 -> _S1 | K62: MIN
B63: BIOETH2G | C63: Ethanol 2nd generation | E63: =I63&H63&J63 -> MINBIOTLW_S2 | F63: =G63 & " of " & VLOOKUP(H63,$B$5:$C$84,2,FALSE) & IF(J63<>0,IF(VLOOKUP(J63,$V$5:$W$12,2,FALSE)<>""," - " & VLOOKUP(J63,$V$5:$W$12,2,FALSE),""),"") -> Domestic Potential of Tallow - Step 2 | G63: =VLOOKUP(I63,$S$5:$T$10,2,FALSE) -> Domestic Potential | H63: =$B$77 -> BIOTLW | I63: =$S$5 -> MIN | J63: =$V$10 -> _S2 | K63: MIN
B64: BIODST1G | C64: Biodiesel 1st generation | E64: =I64&H64&J64 -> MINBIOTLW_S3 | F64: =G64 & " of " & VLOOKUP(H64,$B$5:$C$84,2,FALSE) & IF(J64<>0,IF(VLOOKUP(J64,$V$5:$W$12,2,FALSE)<>""," - " & VLOOKUP(J64,$V$5:$W$12,2,FALSE),""),"") -> Domestic Potential of Tallow - Step 3 | G64: =VLOOKUP(I64,$S$5:$T$10,2,FALSE) -> Domestic Potential | H64: =$B$77 -> BIOTLW | I64: =$S$5 -> MIN | J64: =$V$11 -> _S3 | K64: MIN
B65: BIODST2G | C65: Biodiesel 2nd generation | E65: =I65&H65&J65 -> MINBIORVO_S1 | F65: =G65 & " of " & VLOOKUP(H65,$B$5:$C$84,2,FALSE) & IF(J65<>0,IF(VLOOKUP(J65,$V$5:$W$12,2,FALSE)<>""," - " & VLOOKUP(J65,$V$5:$W$12,2,FALSE),""),"") -> Domestic Potential of Recovered Vegetable Oil - Step 1 | G65: =VLOOKUP(I65,$S$5:$T$10,2,FALSE) -> Domestic Potential | H65: =$B$78 -> BIORVO | I65: =$S$5 -> MIN | J65: =$V$9 -> _S1 | K65: MIN
B66: BIOGAS1G | C66: Biogas 1st generation | E66: =I66&H66&J66 -> MINBIORVO_S2 | F66: =G66 & " of " & VLOOKUP(H66,$B$5:$C$84,2,FALSE) & IF(J66<>0,IF(VLOOKUP(J66,$V$5:$W$12,2,FALSE)<>""," - " & VLOOKUP(J66,$V$5:$W$12,2,FALSE),""),"") -> Domestic Potential of Recovered Vegetable Oil - Step 2 | G66: =VLOOKUP(I66,$S$5:$T$10,2,FALSE) -> Domestic Potential | H66: =$B$78 -> BIORVO | I66: =$S$5 -> MIN | J66: =$V$10 -> _S2 | K66: MIN
B67: BIOGAS2G | C67: Biogas 2nd generation | E67: =I67&H67&J67 -> MINBIORVO_S3 | F67: =G67 & " of " & VLOOKUP(H67,$B$5:$C$84,2,FALSE) & IF(J67<>0,IF(VLOOKUP(J67,$V$5:$W$12,2,FALSE)<>""," - " & VLOOKUP(J67,$V$5:$W$12,2,FALSE),""),"") -> Domestic Potential of Recovered Vegetable Oil - Step 3 | G67: =VLOOKUP(I67,$S$5:$T$10,2,FALSE) -> Domestic Potential | H67: =$B$78 -> BIORVO | I67: =$S$5 -> MIN | J67: =$V$11 -> _S3 | K67: MIN
B68: BIOJKR | C68: Bio Jet Kerosene | E68: =I68&H68&J68 -> MINBIOCATW_S1 | F68: =G68 & " of " & VLOOKUP(H68,$B$5:$C$84,2,FALSE) & IF(J68<>0,IF(VLOOKUP(J68,$V$5:$W$12,2,FALSE)<>""," - " & VLOOKUP(J68,$V$5:$W$12,2,FALSE),""),"") -> Domestic Potential of Cattle Waste - Step 1 | G68: =VLOOKUP(I68,$S$5:$T$10,2,FALSE) -> Domestic Potential | H68: =$B$79 -> BIOCATW | I68: =$S$5 -> MIN | J68: =$V$9 -> _S1 | K68: MIN
B69: BIOWOO | C69: Biomass - generic | E69: =I69&H69&J69 -> MINBIOCATW_S2 | F69: =G69 & " of " & VLOOKUP(H69,$B$5:$C$84,2,FALSE) & IF(J69<>0,IF(VLOOKUP(J69,$V$5:$W$12,2,FALSE)<>""," - " & VLOOKUP(J69,$V$5:$W$12,2,FALSE),""),"") -> Domestic Potential of Cattle Waste - Step 2 | G69: =VLOOKUP(I69,$S$5:$T$10,2,FALSE) -> Domestic Potential | H69: =$B$79 -> BIOCATW | I69: =$S$5 -> MIN | J69: =$V$10 -> _S2 | K69: MIN
B70: BIOWOO1 | C70: Sawmill residues | E70: =I70&H70&J70 -> MINBIOCATW_S3 | F70: =G70 & " of " & VLOOKUP(H70,$B$5:$C$84,2,FALSE) & IF(J70<>0,IF(VLOOKUP(J70,$V$5:$W$12,2,FALSE)<>""," - " & VLOOKUP(J70,$V$5:$W$12,2,FALSE),""),"") -> Domestic Potential of Cattle Waste - Step 3 | G70: =VLOOKUP(I70,$S$5:$T$10,2,FALSE) -> Domestic Potential | H70: =$B$79 -> BIOCATW | I70: =$S$5 -> MIN | J70: =$V$11 -> _S3 | K70: MIN
B71: BIOWOO2 | C71: Post-Consumer Recycled Wood | E71: =I71&H71&J71 -> MINBIOPIGW_S1 | F71: =G71 & " of " & VLOOKUP(H71,$B$5:$C$84,2,FALSE) & IF(J71<>0,IF(VLOOKUP(J71,$V$5:$W$12,2,FALSE)<>""," - " & VLOOKUP(J71,$V$5:$W$12,2,FALSE),""),"") -> Domestic Potential of Pig Waste - Step 1 | G71: =VLOOKUP(I71,$S$5:$T$10,2,FALSE) -> Domestic Potential | H71: =$B$80 -> BIOPIGW | I71: =$S$5 -> MIN | J71: =$V$9 -> _S1 | K71: MIN
B72: BIOWOO3 | C72: Straw | E72: =I72&H72&J72 -> MINBIOPIGW_S2 | F72: =G72 & " of " & VLOOKUP(H72,$B$5:$C$84,2,FALSE) & IF(J72<>0,IF(VLOOKUP(J72,$V$5:$W$12,2,FALSE)<>""," - " & VLOOKUP(J72,$V$5:$W$12,2,FALSE),""),"") -> Domestic Potential of Pig Waste - Step 2 | G72: =VLOOKUP(I72,$S$5:$T$10,2,FALSE) -> Domestic Potential | H72: =$B$80 -> BIOPIGW | I72: =$S$5 -> MIN | J72: =$V$10 -> _S2 | K72: MIN
B73: BIOWPE | C73: Wood Pellets | E73: =I73&H73&J73 -> MINBIOPIGW_S3 | F73: =G73 & " of " & VLOOKUP(H73,$B$5:$C$84,2,FALSE) & IF(J73<>0,IF(VLOOKUP(J73,$V$5:$W$12,2,FALSE)<>""," - " & VLOOKUP(J73,$V$5:$W$12,2,FALSE),""),"") -> Domestic Potential of Pig Waste - Step 3 | G73: =VLOOKUP(I73,$S$5:$T$10,2,FALSE) -> Domestic Potential | H73: =$B$80 -> BIOPIGW | I73: =$S$5 -> MIN | J73: =$V$11 -> _S3 | K73: MIN
B74: BIOWCH | C74: Wood Chip | E74: =I74&H74&J74 -> MINBIOINDF_S1 | F74: =G74 & " of " & VLOOKUP(H74,$B$5:$C$84,2,FALSE) & IF(J74<>0,IF(VLOOKUP(J74,$V$5:$W$12,2,FALSE)<>""," - " & VLOOKUP(J74,$V$5:$W$12,2,FALSE),""),"") -> Domestic Potential of Industrial Food Waste - Step 1 | G74: =VLOOKUP(I74,$S$5:$T$10,2,FALSE) -> Domestic Potential | H74: =$B$81 -> BIOINDF | I74: =$S$5 -> MIN | J74: =$V$9 -> _S1 | K74: MIN
B75: BIOMSW1 | C75: Biodegradable Municipal Solid Waste potential - Solid | E75: =I75&H75&J75 -> MINBIOINDF_S2 | F75: =G75 & " of " & VLOOKUP(H75,$B$5:$C$84,2,FALSE) & IF(J75<>0,IF(VLOOKUP(J75,$V$5:$W$12,2,FALSE)<>""," - " & VLOOKUP(J75,$V$5:$W$12,2,FALSE),""),"") -> Domestic Potential of Industrial Food Waste - Step 2 | G75: =VLOOKUP(I75,$S$5:$T$10,2,FALSE) -> Domestic Potential | H75: =$B$81 -> BIOINDF | I75: =$S$5 -> MIN | J75: =$V$10 -> _S2 | K75: MIN
B76: BIOMSW2 | C76: Biodegradable Municipal Solid Waste | E76: =I76&H76&J76 -> MINBIOINDF_S3 | F76: =G76 & " of " & VLOOKUP(H76,$B$5:$C$84,2,FALSE) & IF(J76<>0,IF(VLOOKUP(J76,$V$5:$W$12,2,FALSE)<>""," - " & VLOOKUP(J76,$V$5:$W$12,2,FALSE),""),"") -> Domestic Potential of Industrial Food Waste - Step 3 | G76: =VLOOKUP(I76,$S$5:$T$10,2,FALSE) -> Domestic Potential | H76: =$B$81 -> BIOINDF | I76: =$S$5 -> MIN | J76: =$V$11 -> _S3 | K76: MIN
B77: BIOTLW | C77: Tallow | E77: =I77&H77&J77 -> MINCYC | F77: =G77 & " of " & VLOOKUP(H77,$B$5:$C$84,2,FALSE) & IF(J77<>0,IF(VLOOKUP(J77,$V$5:$W$12,2,FALSE)<>""," - " & VLOOKUP(J77,$V$5:$W$12,2,FALSE),""),"") -> Domestic Potential of Cycling | G77: =VLOOKUP(I77,$S$5:$T$10,2,FALSE) -> Domestic Potential | H77: =$B$83 -> CYC | I77: =$S$5 -> MIN | K77: MIN
B78: BIORVO | C78: Recovered Vegetable Oil | E78: =I78&H78&J78 -> MINWLK | F78: =G78 & " of " & VLOOKUP(H78,$B$5:$C$84,2,FALSE) & IF(J78<>0,IF(VLOOKUP(J78,$V$5:$W$12,2,FALSE)<>""," - " & VLOOKUP(J78,$V$5:$W$12,2,FALSE),""),"") -> Domestic Potential of Walking | G78: =VLOOKUP(I78,$S$5:$T$10,2,FALSE) -> Domestic Potential | H78: =$B$84 -> WLK | I78: =$S$5 -> MIN | K78: MIN
B79: BIOCATW | C79: Cattle Waste | E79: =I79&H79&J79 -> IMPELC_UK-EWIC | F79: =G79 & " of " & VLOOKUP(H79,$B$5:$C$84,2,FALSE) & IF(J79<>0,IF(VLOOKUP(J79,$V$5:$W$12,2,FALSE)<>""," - " & VLOOKUP(J79,$V$5:$W$12,2,FALSE),""),"") -> Import of Electricity - UK East-West Interconnector | G79: =VLOOKUP(I79,$S$5:$T$10,2,FALSE) -> Import | H79: =$B$35 -> ELC | I79: =$S$6 -> IMP | J79: =$V$6 -> _UK-EWIC | K79: IMP
B80: BIOPIGW | C80: Pig Waste | E80: =I80&H80&J80 -> EXPELC_UK-EWIC | F80: =G80 & " of " & VLOOKUP(H80,$B$5:$C$83,2,FALSE) & IF(J80<>0,IF(VLOOKUP(J80,$V$5:$W$12,2,FALSE)<>""," - " & VLOOKUP(J80,$V$5:$W$12,2,FALSE),""),"") -> Export of Electricity - UK East-West Interconnector | G80: =VLOOKUP(I80,$S$5:$T$10,2,FALSE) -> Export | H80: =$B$35 -> ELC | I80: =$S$7 -> EXP | J80: =$V$6 -> _UK-EWIC | K80: EXP
B81: BIOINDF | C81: Industrial Food Waste | E81: =LEFT(P5,1)&I81&H81&J81 -> SREFOILCRD_Whitegate | F81: =G81 & " of " & VLOOKUP(H81,$B$5:$C$83,2,FALSE) & IF(J81<>0,IF(VLOOKUP(J81,$V$5:$W$12,2,FALSE)<>""," - " & VLOOKUP(J81,$V$5:$W$12,2,FALSE),""),"") -> Refinery of Crude Oil - Whitegate | G81: =VLOOKUP(I81,$S$5:$T$10,2,FALSE) -> Refinery | H81: =B43 -> OILCRD | I81: =$S$8 -> REF | J81: =V8 -> _Whitegate | K81: PRE
B82: H2 | C82: Hydrogen | E82: =I82&$P$5&H82&J82 -> FT-SUPNGA | F82: =G82 & " - " & VLOOKUP(H82,$B$5:$C$84,2,FALSE) & IF(J82<>0,IF(VLOOKUP(J82,$V$5:$W$12,2,FALSE)<>""," - " & VLOOKUP(J82,$V$5:$W$12,2,FALSE),""),"") & " (" & $P$5 & ")" -> Fuel Tech - Natural Gas (SUP) | G82: =VLOOKUP(I82,$S$5:$T$10,2,FALSE) -> Fuel Tech | H82: =B12 -> NGA | I82: =$S$9 -> FT- | K82: PRE
B83: CYC | C83: Cycling | E83: =I83&$P$5&H83&J83 -> FT-SUPCOA | F83: =G83 & " - " & VLOOKUP(H83,$B$5:$C$84,2,FALSE) & IF(J83<>0,IF(VLOOKUP(J83,$V$5:$W$12,2,FALSE)<>""," - " & VLOOKUP(J83,$V$5:$W$12,2,FALSE),""),"") & " (" & $P$5 & ")" -> Fuel Tech - Coal (SUP) | G83: =VLOOKUP(I83,$S$5:$T$10,2,FALSE) -> Fuel Tech | H83: =B5 -> COA | I83: =$S$9 -> FT- | K83: PRE
B84: WLK | C84: Walking | E84: =I84&$P$5&H84&J84 -> FT-SUPWAS | F84: =G84 & " - " & VLOOKUP(H84,$B$5:$C$84,2,FALSE) & IF(J84<>0,IF(VLOOKUP(J84,$V$5:$W$12,2,FALSE)<>""," - " & VLOOKUP(J84,$V$5:$W$12,2,FALSE),""),"") & " (" & $P$5 & ")" -> Fuel Tech - Waste (SUP) | G84: =VLOOKUP(I84,$S$5:$T$10,2,FALSE) -> Fuel Tech | H84: =B37 -> WAS | I84: =$S$9 -> FT- | K84: PRE
E85: =I85&$P$5&H85&J85 -> FT-SUPBIO | F85: =G85 & " - " & VLOOKUP(H85,$B$5:$C$84,2,FALSE) & IF(J85<>0,IF(VLOOKUP(J85,$V$5:$W$12,2,FALSE)<>""," - " & VLOOKUP(J85,$V$5:$W$12,2,FALSE),""),"") & " (" & $P$5 & ")" -> Fuel Tech - Biomass (SUP) | G85: =VLOOKUP(I85,$S$5:$T$10,2,FALSE) -> Fuel Tech | H85: =B13 -> BIO | I85: =$S$9 -> FT- | K85: PRE
E86: =I86&$P$5&H86&J86 -> FT-SUPELC | F86: =G86 & " - " & VLOOKUP(H86,$B$5:$C$84,2,FALSE) & IF(J86<>0,IF(VLOOKUP(J86,$V$5:$W$12,2,FALSE)<>""," - " & VLOOKUP(J86,$V$5:$W$12,2,FALSE),""),"") & " (" & $P$5 & ")" -> Fuel Tech - Electricity (SUP) | G86: =VLOOKUP(I86,$S$5:$T$10,2,FALSE) -> Fuel Tech | H86: =B35 -> ELC | I86: =$S$9 -> FT- | K86: PRE

Sheet Commodities
B2: ~FI_Comm
B3: Csets | C3: CommName | D3: CommDesc | E3: Unit | F3: LimType | G3: CTSLvl | H3: PeakTS | I3: Ctype
B4: \I: Commodity set | C4: Commodity name | D4: Description
B5: \I: Energy Commodities
B6: NRG | C6: =CONVENTIONS!B38 -> COABIT | D6: =CONVENTIONS!C38 -> Bituminous Coal | E6: PJ
B7: NRG | C7: =CONVENTIONS!B39 -> COAHAR | D7: =CONVENTIONS!C39 -> Hard Coal / Antracite | E7: PJ
B8: NRG | C8: =CONVENTIONS!B40 -> COACOK | D8: =CONVENTIONS!C40 -> Coke Coal | E8: PJ
B9: NRG | C9: =CONVENTIONS!B41 -> COALIG | D9: =CONVENTIONS!C41 -> Lignite / Brown Coal | E9: PJ
B10: NRG | C10: =CONVENTIONS!B42 -> PEAT | D10: =CONVENTIONS!C42 -> Peat | E10: PJ
B11: NRG | C11: =CONVENTIONS!B43 -> OILCRD | D11: =CONVENTIONS!C43 -> Crude Oil | E11: PJ
B12: NRG | C12: =CONVENTIONS!B44 -> OILRFG | D12: =CONVENTIONS!C44 -> Refinery Gas | E12: PJ
B13: NRG | C13: =CONVENTIONS!B45 -> OILKER | D13: =CONVENTIONS!C45 -> Kerosene | E13: PJ
B14: NRG | C14: =CONVENTIONS!B46 -> OILHFO | D14: =CONVENTIONS!C46 -> Heavy Fuel Oil | E14: PJ
B15: NRG | C15: =CONVENTIONS!B47 -> OILDST | D15: =CONVENTIONS!C47 -> Diesel Oil | E15: PJ
B16: NRG | C16: =CONVENTIONS!B48 -> OILLPG | D16: =CONVENTIONS!C48 -> Liquified Petroleum Gas | E16: PJ
B17: NRG | C17: =CONVENTIONS!B49 -> OILGSL | D17: =CONVENTIONS!C49 -> Gasoline | E17: PJ
... B20: NRG | C20: =CONVENTIONS!B52 -> OILNEU | D20: =CONVENTIONS!C52 -> Oil for Non-Energy uses | E20: PJ
B21: NRG | C21: =CONVENTIONS!B53 -> GASNAT | D21: =CONVENTIONS!C53 -> Natural Gas | E21: PJ | G21: SEASON
B22: NRG | C22: =CONVENTIONS!B54 -> GASLNG | D22: =CONVENTIONS!C54 -> Liquified Natural Gas | E22: PJ | G22: SEASON
B23: NRG | C23: =CONVENTIONS!B55 -> NUCURM | D23: =CONVENTIONS!C55 -> Uranium | E23: PJ
B24: NRG | C24: =CONVENTIONS!B56 -> RENHYD | D24: =CONVENTIONS!C56 -> Hydro | E24: PJ
B25: NRG | C25: =CONVENTIONS!B57 -> RENWIN | D25: =CONVENTIONS!C57 -> Wind | E25: PJ
B26: NRG | C26: =CONVENTIONS!B58 -> RENSOL | D26: =CONVENTIONS!C58 -> Solar | E26: PJ
B27: NRG | C27: =CONVENTIONS!B59 -> MSWAS | D27: =CONVENTIONS!C59 -> Municipal Solid Waste | E27: PJ
B28: NRG | C28: =CONVENTIONS!B60 -> RENOCE | D28: =CONVENTIONS!C60 -> Ocean | E28: PJ
B29: NRG | C29: =CONVENTIONS!B61 -> RENAHT | D29: =CONVENTIONS!C61 -> Ambient Heat | E29: PJ
B30: NRG | C30: =CONVENTIONS!B62 -> BIOETH1G | D30: =CONVENTIONS!C62 -> Ethanol 1st generation | E30: PJ
B31: NRG | C31: =CONVENTIONS!B63 -> BIOETH2G | D31: =CONVENTIONS!C63 -> Ethanol 2nd generation | E31: PJ
B32: NRG | C32: =CONVENTIONS!B64 -> BIODST1G | D32: =CONVENTIONS!C64 -> Biodiesel 1st generation | E32: PJ
B33: NRG | C33: =CONVENTIONS!B65 -> BIODST2G | D33: =CONVENTIONS!C65 -> Biodiesel 2nd generation | E33: PJ
B34: NRG | C34: =CONVENTIONS!B66 -> BIOGAS1G | D34: =CONVENTIONS!C66 -> Biogas 1st generation | E34: PJ
B35: NRG | C35: =CONVENTIONS!B67 -> BIOGAS2G | D35: =CONVENTIONS!C67 -> Biogas 2nd generation | E35: PJ
B36: NRG | C36: =CONVENTIONS!B68 -> BIOJKR | D36: Bio Jet Kerosene | E36: PJ
B37: NRG | C37: PtLKER | D37: Power to Liquid - Syn. kerosene for aviation | E37: PJ
B38: NRG | C38: =CONVENTIONS!B69 -> BIOWOO | D38: =CONVENTIONS!C69 -> Biomass - generic | E38: PJ
B39: NRG | C39: =CONVENTIONS!B70 -> BIOWOO1 | D39: =CONVENTIONS!C70 -> Sawmill residues | E39: PJ
B40: NRG | C40: =CONVENTIONS!B71 -> BIOWOO2 | D40: =CONVENTIONS!C71 -> Post-Consumer Recycled Wood | E40: PJ
B41: NRG | C41: =CONVENTIONS!B72 -> BIOWOO3 | D41: =CONVENTIONS!C72 -> Straw | E41: PJ
B42: NRG | C42: =CONVENTIONS!B73 -> BIOWPE | D42: =CONVENTIONS!C73 -> Wood Pellets | E42: PJ
B43: NRG | C43: =CONVENTIONS!B74 -> BIOWCH | D43: =CONVENTIONS!C74 -> Wood Chip | E43: PJ
B44: NRG | C44: =CONVENTIONS!B75 -> BIOMSW1 | D44: =CONVENTIONS!C75 -> Biodegradable Municipal Solid Waste potential - Solid | E44: PJ
B45: NRG | C45: =CONVENTIONS!B76 -> BIOMSW2 | D45: =CONVENTIONS!C76 -> Biodegradable Municipal Solid Waste | E45: PJ
B46: NRG | C46: =CONVENTIONS!B77 -> BIOTLW | D46: =CONVENTIONS!C77 -> Tallow | E46: PJ
B47: NRG | C47: =CONVENTIONS!B78 -> BIORVO | D47: =CONVENTIONS!C78 -> Recovered Vegetable Oil | E47: PJ
B48: NRG | C48: =CONVENTIONS!B79 -> BIOCATW | D48: =CONVENTIONS!C79 -> Cattle Waste | E48: PJ
B49: NRG | C49: =CONVENTIONS!B80 -> BIOPIGW | D49: =CONVENTIONS!C80 -> Pig Waste | E49: PJ
B50: NRG | C50: =CONVENTIONS!B81 -> BIOINDF | D50: =CONVENTIONS!C81 -> Industrial Food Waste | E50: PJ
B51: NRG | C51: =CONVENTIONS!B83 -> CYC | D51: =CONVENTIONS!C83 -> Cycling | E51: PJ
B52: NRG | C52: =CONVENTIONS!B84 -> WLK | D52: =CONVENTIONS!C84 -> Walking | E52: PJ
B53: NRG | C53: =CONVENTIONS!$P$5&CONVENTIONS!B5 -> SUPCOA | D53: =CONVENTIONS!C5 & " (" & CONVENTIONS!$P$5 & ")" -> Coal (SUP) | E53: PJ
B54: NRG | C54: =CONVENTIONS!$P$5&CONVENTIONS!B12 -> SUPNGA | D54: =CONVENTIONS!C12 & " (" & CONVENTIONS!$P$5 & ")" -> Natural Gas (SUP) | E54: PJ
B55: NRG | C55: =CONVENTIONS!$P$5&CONVENTIONS!B13 -> SUPBIO | D55: =CONVENTIONS!C13 & " (" & CONVENTIONS!$P$5 & ")" -> Biomass (SUP) | E55: PJ
B56: NRG | C56: =CONVENTIONS!$P$5&CONVENTIONS!B35 -> SUPELC | D56: =CONVENTIONS!C35 & " (" & CONVENTIONS!$P$5 & ")" -> Electricity (SUP) | E56: PJ | G56: DAYNITE
B57: NRG | C57: =CONVENTIONS!$P$5&CONVENTIONS!B37 -> SUPWAS | D57: =CONVENTIONS!C37 & " (" & CONVENTIONS!$P$5 & ")" -> Waste (SUP) | E57: PJ
B58: NRG | C58: =CONVENTIONS!$B$35&CONVENTIONS!AB5 -> ELCC | D58: =CONVENTIONS!$C$35 & " - " & CONVENTIONS!AC5 -> Electricity - centralised | E58: PJ | G58: DAYNITE | I58: ELC
B59: NRG | C59: =CONVENTIONS!$B$35&CONVENTIONS!AB6 -> ELCD | D59: =CONVENTIONS!$C$35 & " - " & CONVENTIONS!AC6 -> Electricity - decentralised | E59: PJ | G59: DAYNITE
B60: NRG | C60: =CONVENTIONS!$P$5&CONVENTIONS!$B$82&CONVENTIONS!Y5&CONVENTIONS!AB5 -> SUPH2GC | D60: =CONVENTIONS!$C$82 & " " & CONVENTIONS!Z5 & " - " & CONVENTIONS!AC5& " (" & CONVENTIONS!$P$5 & ")" -> Hydrogen gaseous - centralised (SUP) | E60: PJ | G60: SEASON
B61: NRG | C61: =CONVENTIONS!$P$5&CONVENTIONS!$B$82&CONVENTIONS!Y6&CONVENTIONS!AB5 -> SUPH2LC | D61: =CONVENTIONS!$C$82 & " " & CONVENTIONS!Z6 & " - " & CONVENTIONS!AC5& " (" & CONVENTIONS!$P$5 & ")" -> Hydrogen liquid - centralised (SUP) | E61: PJ | G61: SEASON
B62: NRG | C62: =CONVENTIONS!$P$5&CONVENTIONS!$B$82&CONVENTIONS!Y5&CONVENTIONS!AB6 -> SUPH2GD | D62: =CONVENTIONS!$C$82 & " " & CONVENTIONS!Z5 & " - " & CONVENTIONS!AC6 & " (" & CONVENTIONS!$P$5 & ")" -> Hydrogen gaseous - decentralised (SUP) | E62: PJ | G62: SEASON
B63: NRG | C63: =CONVENTIONS!$P$5&CONVENTIONS!$B$82&CONVENTIONS!Y6&CONVENTIONS!AB6 -> SUPH2LD | D63: =CONVENTIONS!$C$82 & " " & CONVENTIONS!Z6 & " - " & CONVENTIONS!AC6 & " (" & CONVENTIONS!$P$5 & ")" -> Hydrogen liquid - decentralised (SUP) | E63: PJ | G63: SEASON
B64: \I: Emissions commodities
B65: ENV | C65: =CONVENTIONS!$P$5&CONVENTIONS!M5 -> SUPCH4N | D65: =CONVENTIONS!N5 & " (" & CONVENTIONS!$P$5 & ")" -> Methane - eNergy Emissions (SUP) | E65: kt
B66: ENV | C66: =CONVENTIONS!$P$5&CONVENTIONS!M6 -> SUPCH4P | D66: =CONVENTIONS!N6 & " (" & CONVENTIONS!$P$5 & ")" -> Methane Emissions - Process Emissions (SUP) | E66: kt
B67: ENV | C67: =CONVENTIONS!$P$5&CONVENTIONS!M7 -> SUPN2ON | D67: =CONVENTIONS!N7 & " (" & CONVENTIONS!$P$5 & ")" -> N2O Emissions - eNergy Emissions (SUP) | E67: kt
B68: ENV | C68: =CONVENTIONS!$P$5&CONVENTIONS!M8 -> SUPSO2N | D68: =CONVENTIONS!N8 & " (" & CONVENTIONS!$P$5 & ")" -> Sulfur dioxide - eNergy Emissions (SUP) | E68: kt
B69: ENV | C69: =CONVENTIONS!$P$5&CONVENTIONS!M9 -> SUPCO2N | D69: =CONVENTIONS!N9 & " (" & CONVENTIONS!$P$5 & ")" -> Carbon Dioxide - eNergy Emissions (SUP) | E69: kt
B70: ENV | C70: =CONVENTIONS!$P$5&CONVENTIONS!M10 -> SUPCO2P | D70: =CONVENTIONS!N10 & " (" & CONVENTIONS!$P$5 & ")" -> Carbon Dioxide - Process Emissions (SUP) | E70: kt
B71: ENV | C71: =CONVENTIONS!$P$5&CONVENTIONS!M11 -> SUPCO2S | D71: =CONVENTIONS!N11 & " (" & CONVENTIONS!$P$5 & ")" -> Carbon Dioxide - Sequestered (SUP) | E71: kt
B72: ENV | C72: =CONVENTIONS!$P$5&CONVENTIONS!M12 -> SUPNOXN | D72: =CONVENTIONS!N12 & " (" & CONVENTIONS!$P$5 & ")" -> Nitrogen Oxide - eNergy Emissions (SUP) | E72: kt
B73: ENV | C73: =CONVENTIONS!$P$5&CONVENTIONS!M13 -> SUPPM10 | D73: =CONVENTIONS!N13 & " (" & CONVENTIONS!$P$5 & ")" -> Particulate Matter <10 µm (SUP) | E73: kt
B74: ENV | C74: =CONVENTIONS!$P$5&CONVENTIONS!M14 -> SUPPM25 | D74: =CONVENTIONS!N14 & " (" & CONVENTIONS!$P$5 & ")" -> Particulate Matter <2.5 µm (SUP) | E74: kt
B75: \I: Emissions commodities aggregator
B76: ENV | C76: TOTCO2 | D76: Total CO2 Emmissions | E76: kt | F76: LO
B77: ENV | C77: TOTCO2INT | D77: Total CO2 Emmissions including international | E77: kt | F77: LO
B78: NRG | C78: BIOMUN | D78: Biodegradable Municipal Solid Waste | E78: PJ

Sheet Processes
B1: Processes definition
B3: ~FI_Process
B4: Sets | C4: Region | D4: TechName | E4: TechDesc | F4: Tact | G4: Tcap | H4: Tslvl | I4: PrimaryCG | J4: Vintage
B5: \I: Process Set Membership | D5: Technology name | E5: Description | F5: Activity unit | G5: Capacity unit | H5: TimeSlice level of Process Activity | I5: Primary Commodity Group | J5: Vintage Tracking
B6: \I: Fossil Import Processes
B7: =CONVENTIONS!K5 -> IMP | C7: =_xlfn.TEXTJOIN(",",TRUE,IF(LEFT(Regions!$C$3,1)<>"*",Regions!$C$3,""),IF(LEFT(Regions!$D$3,1)<>"*",Regions!$D$3,"")) -> IE,National | D7: =CONVENTIONS!E5 -> IMPCOABIT | E7: =CONVENTIONS!F5 -> Import of Bituminous Coal | F7: PJ | G7: PJa
B8: =CONVENTIONS!K6 -> IMP | C8: =_xlfn.TEXTJOIN(",",TRUE,IF(LEFT(Regions!$C$3,1)<>"*",Regions!$C$3,""),IF(LEFT(Regions!$D$3,1)<>"*",Regions!$D$3,"")) -> IE,National | D8: =CONVENTIONS!E6 -> IMPCOAHAR | E8: =CONVENTIONS!F6 -> Import of Hard Coal / Antracite | F8: PJ | G8: PJa
B9: =CONVENTIONS!K7 -> IMP | C9: =_xlfn.TEXTJOIN(",",TRUE,IF(LEFT(Regions!$C$3,1)<>"*",Regions!$C$3,""),IF(LEFT(Regions!$D$3,1)<>"*",Regions!$D$3,"")) -> IE,National | D9: =CONVENTIONS!E7 -> IMPCOACOK | E9: =CONVENTIONS!F7 -> Import of Coke Coal | F9: PJ | G9: PJa
B10: =CONVENTIONS!K8 -> IMP | C10: =_xlfn.TEXTJOIN(",",TRUE,IF(LEFT(Regions!$C$3,1)<>"*",Regions!$C$3,""),IF(LEFT(Regions!$D$3,1)<>"*",Regions!$D$3,"")) -> IE,National | D10: =CONVENTIONS!E8 -> IMPCOALIG | E10: =CONVENTIONS!F8 -> Import of Lignite / Brown Coal | F10: PJ | G10: PJa
B11: =CONVENTIONS!K9 -> IMP | C11: =_xlfn.TEXTJOIN(",",TRUE,IF(LEFT(Regions!$C$3,1)<>"*",Regions!$C$3,""),IF(LEFT(Regions!$D$3,1)<>"*",Regions!$D$3,"")) -> IE,National | D11: =CONVENTIONS!E9 -> IMPOILCRD | E11: =CONVENTIONS!F9 -> Import of Crude Oil | F11: PJ | G11: PJa
B12: =CONVENTIONS!K10 -> IMP | C12: =_xlfn.TEXTJOIN(",",TRUE,IF(LEFT(Regions!$C$3,1)<>"*",Regions!$C$3,""),IF(LEFT(Regions!$D$3,1)<>"*",Regions!$D$3,"")) -> IE,National | D12: =CONVENTIONS!E10 -> IMPOILKER | E12: =CONVENTIONS!F10 -> Import of Kerosene | F12: PJ | G12: PJa
B13: =CONVENTIONS!K11 -> IMP | C13: =_xlfn.TEXTJOIN(",",TRUE,IF(LEFT(Regions!$C$3,1)<>"*",Regions!$C$3,""),IF(LEFT(Regions!$D$3,1)<>"*",Regions!$D$3,"")) -> IE,National | D13: =CONVENTIONS!E11 -> IMPOILHFO | E13: =CONVENTIONS!F11 -> Import of Heavy Fuel Oil | F13: PJ | G13: PJa
B14: =CONVENTIONS!K12 -> IMP | C14: =_xlfn.TEXTJOIN(",",TRUE,IF(LEFT(Regions!$C$3,1)<>"*",Regions!$C$3,""),IF(LEFT(Regions!$D$3,1)<>"*",Regions!$D$3,"")) -> IE,National | D14: =CONVENTIONS!E12 -> IMPOILDST | E14: =CONVENTIONS!F12 -> Import of Diesel Oil | F14: PJ | G14: PJa
B15: =CONVENTIONS!K13 -> IMP | C15: =_xlfn.TEXTJOIN(",",TRUE,IF(LEFT(Regions!$C$3,1)<>"*",Regions!$C$3,""),IF(LEFT(Regions!$D$3,1)<>"*",Regions!$D$3,"")) -> IE,National | D15: =CONVENTIONS!E13 -> IMPOILLPG | E15: =CONVENTIONS!F13 -> Import of Liquified Petroleum Gas | F15: PJ | G15: PJa
B16: =CONVENTIONS!K14 -> IMP | C16: =_xlfn.TEXTJOIN(",",TRUE,IF(LEFT(Regions!$C$3,1)<>"*",Regions!$C$3,""),IF(LEFT(Regions!$D$3,1)<>"*",Regions!$D$3,"")) -> IE,National | D16: =CONVENTIONS!E14 -> IMPOILGSL | E16: =CONVENTIONS!F14 -> Import of Gasoline | F16: PJ | G16: PJa
B17: =CONVENTIONS!K15 -> IMP | C17: =_xlfn.TEXTJOIN(",",TRUE,IF(LEFT(Regions!$C$3,1)<>"*",Regions!$C$3,""),IF(LEFT(Regions!$D$3,1)<>"*",Regions!$D$3,"")) -> IE,National | D17: =CONVENTIONS!E15 -> IMPOILCOK | E17: =CONVENTIONS!F15 -> Import of Petroleum Coke | F17: PJ | G17: PJa
B18: =CONVENTIONS!K16 -> IMP | C18: =_xlfn.TEXTJOIN(",",TRUE,IF(LEFT(Regions!$C$3,1)<>"*",Regions!$C$3,""),IF(LEFT(Regions!$D$3,1)<>"*",Regions!$D$3,"")) -> IE,National | D18: =CONVENTIONS!E16 -> IMPOILNEU | E18: =CONVENTIONS!F16 -> Import of Oil for Non-Energy uses | F18: PJ | G18: PJa
... B21: =CONVENTIONS!K19 -> IMP | C21: =_xlfn.TEXTJOIN(",",TRUE,IF(LEFT(Regions!$C$3,1)<>"*",Regions!$C$3,""),IF(LEFT(Regions!$D$3,1)<>"*",Regions!$D$3,"")) -> IE,National | D21: =CONVENTIONS!E19 -> IMPNUCURM | E21: =CONVENTIONS!F19 -> Import of Uranium | F21: PJ | G21: PJa
B22: \I:Bio Import Processes
B23: =CONVENTIONS!K20 -> IMP | C23: =_xlfn.TEXTJOIN(",",TRUE,IF(LEFT(Regions!$C$3,1)<>"*",Regions!$C$3,""),IF(LEFT(Regions!$D$3,1)<>"*",Regions!$D$3,"")) -> IE,National | D23: =CONVENTIONS!E20 -> IMPBIOETH1G_S1 | E23: =CONVENTIONS!F20 -> Import of Ethanol 1st generation - Step 1 | F23: PJ | G23: PJa
B24: =CONVENTIONS!K21 -> IMP | C24: =_xlfn.TEXTJOIN(",",TRUE,IF(LEFT(Regions!$C$3,1)<>"*",Regions!$C$3,""),IF(LEFT(Regions!$D$3,1)<>"*",Regions!$D$3,"")) -> IE,National | D24: =CONVENTIONS!E21 -> IMPBIOETH1G_S2 | E24: =CONVENTIONS!F21 -> Import of Ethanol 1st generation - Step 2 | F24: PJ | G24: PJa
B25: =CONVENTIONS!K22 -> IMP | C25: =_xlfn.TEXTJOIN(",",TRUE,IF(LEFT(Regions!$C$3,1)<>"*",Regions!$C$3,""),IF(LEFT(Regions!$D$3,1)<>"*",Regions!$D$3,"")) -> IE,National | D25: =CONVENTIONS!E22 -> IMPBIOETH1G_S3 | E25: =CONVENTIONS!F22 -> Import of Ethanol 1st generation - Step 3 | F25: PJ | G25: PJa
B26: =CONVENTIONS!K23 -> IMP | C26: =_xlfn.TEXTJOIN(",",TRUE,IF(LEFT(Regions!$C$3,1)<>"*",Regions!$C$3,""),IF(LEFT(Regions!$D$3,1)<>"*",Regions!$D$3,"")) -> IE,National | D26: =CONVENTIONS!E23 -> IMPBIOETH1G_S4 | E26: =CONVENTIONS!F23 -> Import of Ethanol 1st generation - Step 4 | F26: PJ | G26: PJa
B27: =CONVENTIONS!K24 -> IMP | C27: =_xlfn.TEXTJOIN(",",TRUE,IF(LEFT(Regions!$C$3,1)<>"*",Regions!$C$3,""),IF(LEFT(Regions!$D$3,1)<>"*",Regions!$D$3,"")) -> IE,National | D27: =CONVENTIONS!E24 -> IMPBIODST1G_S1 | E27: =CONVENTIONS!F24 -> Import of Biodiesel 1st generation - Step 1 | F27: PJ | G27: PJa
B28: =CONVENTIONS!K25 -> IMP | C28: =_xlfn.TEXTJOIN(",",TRUE,IF(LEFT(Regions!$C$3,1)<>"*",Regions!$C$3,""),IF(LEFT(Regions!$D$3,1)<>"*",Regions!$D$3,"")) -> IE,National | D28: =CONVENTIONS!E25 -> IMPBIODST1G_S2 | E28: =CONVENTIONS!F25 -> Import of Biodiesel 1st generation - Step 2 | F28: PJ | G28: PJa
B29: =CONVENTIONS!K26 -> IMP | C29: =_xlfn.TEXTJOIN(",",TRUE,IF(LEFT(Regions!$C$3,1)<>"*",Regions!$C$3,""),IF(LEFT(Regions!$D$3,1)<>"*",Regions!$D$3,"")) -> IE,National | D29: =CONVENTIONS!E26 -> IMPBIODST1G_S3 | E29: =CONVENTIONS!F26 -> Import of Biodiesel 1st generation - Step 3 | F29: PJ | G29: PJa
B30: =CONVENTIONS!K27 -> IMP | C30: =_xlfn.TEXTJOIN(",",TRUE,IF(LEFT(Regions!$C$3,1)<>"*",Regions!$C$3,""),IF(LEFT(Regions!$D$3,1)<>"*",Regions!$D$3,"")) -> IE,National | D30: =CONVENTIONS!E27 -> IMPBIODST1G_S4 | E30: =CONVENTIONS!F27 -> Import of Biodiesel 1st generation - Step 4 | F30: PJ | G30: PJa
B31: =CONVENTIONS!K29 -> IMP | C31: =_xlfn.TEXTJOIN(",",TRUE,IF(LEFT(Regions!$C$3,1)<>"*",Regions!$C$3,""),IF(LEFT(Regions!$D$3,1)<>"*",Regions!$D$3,"")) -> IE,National | D31: =CONVENTIONS!E28 -> IMPBIOJKR_S1 | E31: =CONVENTIONS!F28 -> Import of Bio Jet Kerosene - Step 1 | F31: PJ | G31: PJa
B32: =B31 -> IMP | C32: =C31 -> IE,National | D32: IMPPtLKER | E32: Import of PtL Synthetic Kerosene for Aviation | F32: PJ | G32: PJa
B33: =CONVENTIONS!K29 -> IMP | C33: =_xlfn.TEXTJOIN(",",TRUE,IF(LEFT(Regions!$C$3,1)<>"*",Regions!$C$3,""),IF(LEFT(Regions!$D$3,1)<>"*",Regions!$D$3,"")) -> IE,National | D33: =CONVENTIONS!E29 -> IMPBIOWPE_S1 | E33: =CONVENTIONS!F29 -> Import of Wood Pellets - Step 1 | F33: PJ | G33: PJa
B34: =CONVENTIONS!K30 -> IMP | C34: =_xlfn.TEXTJOIN(",",TRUE,IF(LEFT(Regions!$C$3,1)<>"*",Regions!$C$3,""),IF(LEFT(Regions!$D$3,1)<>"*",Regions!$D$3,"")) -> IE,National | D34: =CONVENTIONS!E30 -> IMPBIOWPE_S2 | E34: =CONVENTIONS!F30 -> Import of Wood Pellets - Step 2 | F34: PJ | G34: PJa
B35: =CONVENTIONS!K31 -> IMP | C35: =_xlfn.TEXTJOIN(",",TRUE,IF(LEFT(Regions!$C$3,1)<>"*",Regions!$C$3,""),IF(LEFT(Regions!$D$3,1)<>"*",Regions!$D$3,"")) -> IE,National | D35: =CONVENTIONS!E31 -> IMPBIOWPE_S3 | E35: =CONVENTIONS!F31 -> Import of Wood Pellets - Step 3 | F35: PJ | G35: PJa
B36: =CONVENTIONS!K32 -> IMP | C36: =_xlfn.TEXTJOIN(",",TRUE,IF(LEFT(Regions!$C$3,1)<>"*",Regions!$C$3,""),IF(LEFT(Regions!$D$3,1)<>"*",Regions!$D$3,"")) -> IE,National | D36: =CONVENTIONS!E32 -> IMPBIOWPE_S4 | E36: =CONVENTIONS!F32 -> Import of Wood Pellets - Step 4 | F36: PJ | G36: PJa
B37: =CONVENTIONS!K33 -> IMP | C37: =_xlfn.TEXTJOIN(",",TRUE,IF(LEFT(Regions!$C$3,1)<>"*",Regions!$C$3,""),IF(LEFT(Regions!$D$3,1)<>"*",Regions!$D$3,"")) -> IE,National | D37: =CONVENTIONS!E33 -> IMPBIOWCH_S1 | E37: =CONVENTIONS!F33 -> Import of Wood Chip - Step 1 | F37: PJ | G37: PJa
B38: =CONVENTIONS!K34 -> IMP | C38: =_xlfn.TEXTJOIN(",",TRUE,IF(LEFT(Regions!$C$3,1)<>"*",Regions!$C$3,""),IF(LEFT(Regions!$D$3,1)<>"*",Regions!$D$3,"")) -> IE,National | D38: =CONVENTIONS!E34 -> IMPBIOWCH_S2 | E38: =CONVENTIONS!F34 -> Import of Wood Chip - Step 2 | F38: PJ | G38: PJa
B39: =CONVENTIONS!K35 -> IMP | C39: =_xlfn.TEXTJOIN(",",TRUE,IF(LEFT(Regions!$C$3,1)<>"*",Regions!$C$3,""),IF(LEFT(Regions!$D$3,1)<>"*",Regions!$D$3,"")) -> IE,National | D39: =CONVENTIONS!E35 -> IMPBIOWCH_S3 | E39: =CONVENTIONS!F35 -> Import of Wood Chip - Step 3 | F39: PJ | G39: PJa
B40: =CONVENTIONS!K36 -> IMP | C40: =_xlfn.TEXTJOIN(",",TRUE,IF(LEFT(Regions!$C$3,1)<>"*",Regions!$C$3,""),IF(LEFT(Regions!$D$3,1)<>"*",Regions!$D$3,"")) -> IE,National | D40: =CONVENTIONS!E36 -> IMPBIOWCH_S4 | E40: =CONVENTIONS!F36 -> Import of Wood Chip - Step 4 | F40: PJ | G40: PJa
B41: \I:Domestic potentials
B42: =CONVENTIONS!K37 -> MIN | C42: =_xlfn.TEXTJOIN(",",TRUE,IF(LEFT(Regions!$C$3,1)<>"*",Regions!$C$3,""),IF(LEFT(Regions!$D$3,1)<>"*",Regions!$D$3,"")) -> IE,National | D42: =CONVENTIONS!E37 -> MINGASNAT_S1 | E42: =CONVENTIONS!F37 -> Domestic Potential of Natural Gas - Step 1 | F42: PJ | G42: PJa
B43: =CONVENTIONS!K38 -> MIN | C43: =_xlfn.TEXTJOIN(",",TRUE,IF(LEFT(Regions!$C$3,1)<>"*",Regions!$C$3,""),IF(LEFT(Regions!$D$3,1)<>"*",Regions!$D$3,"")) -> IE,National | D43: =CONVENTIONS!E38 -> MINGASNAT_S2 | E43: =CONVENTIONS!F38 -> Domestic Potential of Natural Gas - Step 2 | F43: PJ | G43: PJa
B44: =CONVENTIONS!K39 -> MIN | C44: =_xlfn.TEXTJOIN(",",TRUE,IF(LEFT(Regions!$C$3,1)<>"*",Regions!$C$3,""),IF(LEFT(Regions!$D$3,1)<>"*",Regions!$D$3,"")) -> IE,National | D44: =CONVENTIONS!E39 -> MINPEAT_S1 | E44: =CONVENTIONS!F39 -> Domestic Potential of Peat - Step 1 | F44: PJ | G44: PJa
B45: =CONVENTIONS!K40 -> MIN | C45: =_xlfn.TEXTJOIN(",",TRUE,IF(LEFT(Regions!$C$3,1)<>"*",Regions!$C$3,""),IF(LEFT(Regions!$D$3,1)<>"*",Regions!$D$3,"")) -> IE,National | D45: =CONVENTIONS!E40 -> MINPEAT_S2 | E45: =CONVENTIONS!F40 -> Domestic Potential of Peat - Step 2 | F45: PJ | G45: PJa
B46: =CONVENTIONS!K41 -> MIN | C46: =_xlfn.TEXTJOIN(",",TRUE,IF(LEFT(Regions!$C$3,1)<>"*",Regions!$C$3,""),IF(LEFT(Regions!$D$3,1)<>"*",Regions!$D$3,"")) -> IE,National | D46: =CONVENTIONS!E41 -> MINRENHYD | E46: =CONVENTIONS!F41 -> Domestic Potential of Hydro | F46: PJ | G46: PJa
B47: =CONVENTIONS!K42 -> MIN | C47: =_xlfn.TEXTJOIN(",",TRUE,IF(LEFT(Regions!$C$3,1)<>"*",Regions!$C$3,""),IF(LEFT(Regions!$D$3,1)<>"*",Regions!$D$3,"")) -> IE,National | D47: =CONVENTIONS!E42 -> MINRENWIN | E47: =CONVENTIONS!F42 -> Domestic Potential of Wind | F47: PJ | G47: PJa
B48: =CONVENTIONS!K43 -> MIN | C48: =_xlfn.TEXTJOIN(",",TRUE,IF(LEFT(Regions!$C$3,1)<>"*",Regions!$C$3,""),IF(LEFT(Regions!$D$3,1)<>"*",Regions!$D$3,"")) -> IE,National | D48: =CONVENTIONS!E43 -> MINRENSOL | E48: =CONVENTIONS!F43 -> Domestic Potential of Solar | F48: PJ | G48: PJa
B49: =CONVENTIONS!K44 -> MIN | C49: =_xlfn.TEXTJOIN(",",TRUE,IF(LEFT(Regions!$C$3,1)<>"*",Regions!$C$3,""),IF(LEFT(Regions!$D$3,1)<>"*",Regions!$D$3,"")) -> IE,National | D49: =CONVENTIONS!E44 -> MINMSWAS | E49: =CONVENTIONS!F44 -> Domestic Potential of Municipal Solid Waste | F49: PJ | G49: PJa
B50: =CONVENTIONS!K45 -> MIN | C50: =_xlfn.TEXTJOIN(",",TRUE,IF(LEFT(Regions!$C$3,1)<>"*",Regions!$C$3,""),IF(LEFT(Regions!$D$3,1)<>"*",Regions!$D$3,"")) -> IE,National | D50: =CONVENTIONS!E45 -> MINRENOCE | E50: =CONVENTIONS!F45 -> Domestic Potential of Ocean | F50: PJ | G50: PJa
B51: =CONVENTIONS!K46 -> MIN | C51: =_xlfn.TEXTJOIN(",",TRUE,IF(LEFT(Regions!$C$3,1)<>"*",Regions!$C$3,""),IF(LEFT(Regions!$D$3,1)<>"*",Regions!$D$3,"")) -> IE,National | D51: =CONVENTIONS!E46 -> MINRENAHT | E51: =CONVENTIONS!F46 -> Domestic Potential of Ambient Heat | F51: PJ | G51: PJa
B52: =CONVENTIONS!K47 -> MIN | C52: =_xlfn.TEXTJOIN(",",TRUE,IF(LEFT(Regions!$C$3,1)<>"*",Regions!$C$3,""),IF(LEFT(Regions!$D$3,1)<>"*",Regions!$D$3,"")) -> IE,National | D52: =CONVENTIONS!E47 -> MINBIOWOO1_S1 | E52: =CONVENTIONS!F47 -> Domestic Potential of Sawmill residues - Step 1 | F52: PJ | G52: PJa
B53: =CONVENTIONS!K48 -> MIN | C53: =_xlfn.TEXTJOIN(",",TRUE,IF(LEFT(Regions!$C$3,1)<>"*",Regions!$C$3,""),IF(LEFT(Regions!$D$3,1)<>"*",Regions!$D$3,"")) -> IE,National | D53: =CONVENTIONS!E48 -> MINBIOWOO1_S2 | E53: =CONVENTIONS!F48 -> Domestic Potential of Sawmill residues - Step 2 | F53: PJ | G53: PJa
... B81: =CONVENTIONS!K76 -> MIN | C81: =_xlfn.TEXTJOIN(",",TRUE,IF(LEFT(Regions!$C$3,1)<>"*",Regions!$C$3,""),IF(LEFT(Regions!$D$3,1)<>"*",Regions!$D$3,"")) -> IE,National | D81: =CONVENTIONS!E76 -> MINBIOINDF_S3 | E81: =CONVENTIONS!F76 -> Domestic Potential of Industrial Food Waste - Step 3 | F81: PJ | G81: PJa
B82: =CONVENTIONS!K77 -> MIN | D82: =CONVENTIONS!E77 -> MINCYC | E82: =CONVENTIONS!F77 -> Domestic Potential of Cycling | F82: PJ | G82: PJa
B83: =CONVENTIONS!K78 -> MIN | D83: =CONVENTIONS!E78 -> MINWLK | E83: =CONVENTIONS!F78 -> Domestic Potential of Walking | F83: PJ | G83: PJa
B84: =CONVENTIONS!K79 -> IMP | C84: =_xlfn.TEXTJOIN(",",TRUE,IF(LEFT(Regions!$C$3,1)<>"*",Regions!$C$3,""),IF(LEFT(Regions!$D$3,1)<>"*",Regions!$D$3,"")) -> IE,National | D84: =CONVENTIONS!E79 -> IMPELC_UK-EWIC | E84: =CONVENTIONS!F79 -> Import of Electricity - UK East-West Interconnector | F84: PJ | G84: GW | H84: DAYNITE
B85: =CONVENTIONS!K80 -> EXP | C85: =_xlfn.TEXTJOIN(",",TRUE,IF(LEFT(Regions!$C$3,1)<>"*",Regions!$C$3,""),IF(LEFT(Regions!$D$3,1)<>"*",Regions!$D$3,"")) -> IE,National | D85: =CONVENTIONS!E80 -> EXPELC_UK-EWIC | E85: =CONVENTIONS!F80 -> Export of Electricity - UK East-West Interconnector | F85: PJ | G85: GW | H85: DAYNITE
B86: =CONVENTIONS!K81 -> PRE | C86: =_xlfn.TEXTJOIN(",",TRUE,IF(LEFT(Regions!$C$3,1)<>"*",Regions!$C$3,""),IF(LEFT(Regions!$D$3,1)<>"*",Regions!$D$3,"")) -> IE,National | D86: =CONVENTIONS!E81 -> SREFOILCRD_Whitegate | E86: =CONVENTIONS!F81 -> Refinery of Crude Oil - Whitegate | F86: PJ | G86: PJa | I86: =Commodities!C11 -> OILCRD
B87: \I: Fuel Technologies
B88: =CONVENTIONS!K82 -> PRE | C88: =_xlfn.TEXTJOIN(",",TRUE,IF(LEFT(Regions!$C$3,1)<>"*",Regions!$C$3,""),IF(LEFT(Regions!$D$3,1)<>"*",Regions!$D$3,"")) -> IE,National | D88: =CONVENTIONS!E82 -> FT-SUPNGA | E88: =CONVENTIONS!F82 -> Fuel Tech - Natural Gas (SUP) | F88: PJ | G88: PJa
B89: =CONVENTIONS!K83 -> PRE | C89: =_xlfn.TEXTJOIN(",",TRUE,IF(LEFT(Regions!$C$3,1)<>"*",Regions!$C$3,""),IF(LEFT(Regions!$D$3,1)<>"*",Regions!$D$3,"")) -> IE,National | D89: =CONVENTIONS!E83 -> FT-SUPCOA | E89: =CONVENTIONS!F83 -> Fuel Tech - Coal (SUP) | F89: PJ | G89: PJa
B90: =CONVENTIONS!K84 -> PRE | C90: =_xlfn.TEXTJOIN(",",TRUE,IF(LEFT(Regions!$C$3,1)<>"*",Regions!$C$3,""),IF(LEFT(Regions!$D$3,1)<>"*",Regions!$D$3,"")) -> IE,National | D90: =CONVENTIONS!E84 -> FT-SUPWAS | E90: =CONVENTIONS!F84 -> Fuel Tech - Waste (SUP) | F90: PJ | G90: PJa
B91: =CONVENTIONS!K85 -> PRE | C91: =_xlfn.TEXTJOIN(",",TRUE,IF(LEFT(Regions!$C$3,1)<>"*",Regions!$C$3,""),IF(LEFT(Regions!$D$3,1)<>"*",Regions!$D$3,"")) -> IE,National | D91: =CONVENTIONS!E85 -> FT-SUPBIO | E91: =CONVENTIONS!F85 -> Fuel Tech - Biomass (SUP) | F91: PJ | G91: PJa
B92: =CONVENTIONS!K86 -> PRE | C92: =_xlfn.TEXTJOIN(",",TRUE,IF(LEFT(Regions!$C$3,1)<>"*",Regions!$C$3,""),IF(LEFT(Regions!$D$3,1)<>"*",Regions!$D$3,"")) -> IE,National | D92: =CONVENTIONS!E86 -> FT-SUPELC | E92: =CONVENTIONS!F86 -> Fuel Tech - Electricity (SUP) | F92: PJ | G92: PJa | H92: DAYNITE

Sheet SUP_FuelTech
B1: Fuel Techs - Sectoral infrastructure
E3: ~FI_T
B4: Region | C4: TechName | D4: Comm-IN | E4: Comm-OUT | F4: EFF | G4: Life | H4: Share-I | I4: Pasti | J4: INVCOST | K4: NCAP_BND~UP~0
B5: * | I5: PJa | J5: €/GJa | K5: Interpolation
B6: =Processes!C88 -> IE,National | C6: =Processes!D88 -> FT-SUPNGA | D6: =Commodities!C21 -> GASNAT | E6: =Commodities!C54 -> SUPNGA | F6: 1
B7: =Processes!C89 -> IE,National | C7: =Processes!D89 -> FT-SUPCOA | D7: =Commodities!C7 -> COAHAR | E7: =Commodities!C53 -> SUPCOA | F7: 1
B8: =Processes!C90 -> IE,National | C8: =Processes!D90 -> FT-SUPWAS | D8: =Commodities!C27 -> MSWAS | E8: =Commodities!C57 -> SUPWAS | F8: 1
B9: =Processes!C91 -> IE,National | C9: =Processes!D91 -> FT-SUPBIO | D9: =_xlfn.TEXTJOIN(", ",TRUE,Commodities!C38,Commodities!C42,Commodities!C43) -> BIOWOO, BIOWPE, BIOWCH | E9: =Commodities!C55 -> SUPBIO | F9: 1
B10: =Processes!C92 -> IE,National | C10: =Processes!D92 -> FT-SUPELC | D10: ELCC | E10: =Commodities!C56 -> SUPELC | F10: 1

Sheet Imports_Fossil
B1: Fossil Fuels Import Prices
G3: ~FI_T: IRE_PRICE
C4: Region | D4: TechName | E4: *TechDesc | F4: Other_Indexes | G4: Comm-OUT | H4: 2018~MEUR2018 | I4: 2019~MEUR2019 | J4: 2025~MEUR2019 | K4: 2030~MEUR2019 | L4: 2035~MEUR2019 | M4: 2040~MEUR2019 | N4: *Source/Ratio
C5: *Region Name | D5: *Technology Name | E5: Technology Description | F5: import/Export | G5: Output Commodity | I5: €/GJ | J5: €/GJ | K5: €/GJ | L5: €/GJ | M5: €/GJ
C6: =Processes!C11 -> IE,National | D6: =Processes!D11 -> IMPOILCRD | E6: =Processes!E11 -> Import of Crude Oil | F6: IMP | G6: =Commodities!C11 -> OILCRD | H6: =F55 -> 10.080858 | I6: =Imports_Fossil!F37 -> 9.8525376 | J6: =Imports_Fossil!G37 -> 11.103653 | K6: =Imports_Fossil!H37 -> 11.885601 | L6: =Imports_Fossil!I37 -> 12.667548 | M6: =Imports_Fossil!J37 -> 13.293106 | N6: WEO2019, WEO2020
C7: =Processes!C19 -> IE,National | D7: =Processes!D19 -> IMPGASNAT_UK | E7: =Processes!E19 -> Import of Natural Gas - UK | F7: IMP | G7: =Commodities!C21 -> GASNAT | H7: =F56 -> 6.0993956 | I7: =Imports_Fossil!F38 -> 5.6724016 | J7: =Imports_Fossil!G38 -> 6.1803779 | K7: =Imports_Fossil!H38 -> 9.3975609 | L7: =Imports_Fossil!I38 -> 11.006152 | M7: =Imports_Fossil!J38 -> 12.890088 | N7: WEO2019, WEO2020 | R7: Coal prices | T7: https://www.eia.gov/energyexplained/coal/prices-and-outlook.php
C8: =Processes!C8 -> IE,National | D8: =Processes!D8 -> IMPCOAHAR | E8: =Processes!E8 -> Import of Hard Coal / Antracite | F8: IMP | G8: =Commodities!C7 -> COAHAR | H8: =F57 -> 1.8606832 | I8: =Imports_Fossil!F39 -> 1.3014677 | J8: =Imports_Fossil!G39 -> 1.3868099 | K8: =Imports_Fossil!H39 -> 1.7068429 | L8: =Imports_Fossil!I39 -> 1.8775272 | M8: =Imports_Fossil!J39 -> 2.06528 | N8: WEO2019, WEO2020
C9: =Processes!C7 -> IE,National | D9: =Processes!D7 -> IMPCOABIT | E9: =Processes!E7 -> Import of Bituminous Coal | F9: IMP | G9: =Commodities!C6 -> COABIT | H9: =H$8*$N$9 -> 1.7676491 | I9: =I$8*$N$9 -> 1.2363944 | J9: =J$8*$N$9 -> 1.3174694 | K9: =K$8*$N$9 -> 1.6215008 | L9: =L$8*$N$9 -> 1.7836509 | M9: =M$8*$N$9 -> 1.962016 | N9: 0.95 | R9: Type | S9: USD2019/short ton
C10: =Processes!C9 -> IE,National | D10: =Processes!D9 -> IMPCOACOK | E10: =Processes!E9 -> Import of Coke Coal | F10: IMP | G10: =Commodities!C8 -> COACOK | H10: =H$8*$N10 -> 2.3630677 | I10: =I$8*$N10 -> 1.652864 | J10: =J$8*$N10 -> 1.7612486 | K10: =K$8*$N10 -> 2.1676905 | L10: =L$8*$N10 -> 2.3844596 | M10: =M$8*$N10 -> 2.6229056 | N10: 1.27 | R10: Bituminous | S10: 58.93
C11: =Processes!C10 -> IE,National | D11: =Processes!D10 -> IMPCOALIG | E11: =Processes!E10 -> Import of Lignite / Brown Coal | F11: IMP | G11: =Commodities!C9 -> COALIG | H11: =H$8*$N11 -> 1.6291696 | I11: =I$8*$N11 -> 1.139534 | J11: =J$8*$N11 -> 1.2142575 | K11: =K$8*$N11 -> 1.4944708 | L11: =L$8*$N11 -> 1.6439179 | M11: =M$8*$N11 -> 1.8083096 | N11: 0.87557604 | R11: lignite | S11: 19.86
C12: =Processes!C20 -> IE,National | D12: =Processes!D20 -> IMPGASLNG_GLOBAL | E12: =Processes!E20 -> Import of Liquified Natural Gas | F12: IMP | G12: =Commodities!C22 -> GASLNG | H12: =H$7*$N12 -> 6.507802 | I12: =I$7*$N12 -> 6.0522172 | J12: =J$7*$N12 -> 6.5942068 | K12: =K$7*$N12 -> 10.026808 | L12: =L$7*$N12 -> 11.743108 | M12: =M$7*$N12 -> 13.753189 | N12: 1.0669585 | R12: anthracite | S12: 102.22
C13: =Processes!C14 -> IE,National | D13: =Processes!D14 -> IMPOILDST | E13: =Processes!E14 -> Import of Diesel Oil | F13: IMP | G13: =Commodities!C15 -> OILDST | H13: =H$6*$N13 -> 15.417783 | I13: =I$6*$N13 -> 15.068587 | J13: =J$6*$N13 -> 16.982058 | K13: =K$6*$N13 -> 18.177978 | L13: =L$6*$N13 -> 19.373897 | M13: =M$6*$N13 -> 20.330633 | N13: 1.5294118
C14: =Processes!C16 -> IE,National | D14: =Processes!D16 -> IMPOILGSL | E14: =Processes!E16 -> Import of Gasoline | F14: IMP | G14: =Commodities!C17 -> OILGSL | H14: =H$6*$N14 -> 16.603766 | I14: =I$6*$N14 -> 16.227709 | J14: =J$6*$N14 -> 18.28837 | K14: =K$6*$N14 -> 19.576284 | L14: =L$6*$N14 -> 20.864197 | M14: =M$6*$N14 -> 21.894528 | N14: 1.6470588
C15: =Processes!C13 -> IE,National | D15: =Processes!D13 -> IMPOILHFO | E15: =Processes!E13 -> Import of Heavy Fuel Oil | F15: IMP | G15: =Commodities!C14 -> OILHFO | H15: =H$6*$N15 -> 8.1654951 | I15: =I$6*$N15 -> 7.9805554 | J15: =J$6*$N15 -> 8.9939593 | K15: =K$6*$N15 -> 9.6273367 | L15: =L$6*$N15 -> 10.260714 | M15: =M$6*$N15 -> 10.767416 | N15: 0.81
C16: =Processes!C12 -> IE,National | D16: =Processes!D12 -> IMPOILKER | E16: =Processes!E12 -> Import of Kerosene | F16: IMP | G16: =Commodities!C13 -> OILKER | H16: =H$6*$N16 -> 16.603766 | I16: =I$6*$N16 -> 16.227709 | J16: =J$6*$N16 -> 18.28837 | K16: =K$6*$N16 -> 19.576284 | L16: =L$6*$N16 -> 20.864197 | M16: =M$6*$N16 -> 21.894528 | N16: 1.6470588
C17: =Processes!C15 -> IE,National | D17: =Processes!D15 -> IMPOILLPG | E17: =Processes!E15 -> Import of Liquified Petroleum Gas | F17: IMP | G17: =Commodities!C16 -> OILLPG | H17: =H$6*$N17 -> 13.045816 | I17: =I$6*$N17 -> 12.750343 | J17: =J$6*$N17 -> 14.369434 | K17: =K$6*$N17 -> 15.381366 | L17: =L$6*$N17 -> 16.393298 | M17: =M$6*$N17 -> 17.202843 | N17: 1.2941176
C18: =Processes!C17 -> IE,National | D18: =Processes!D17 -> IMPOILCOK | E18: =Processes!E17 -> Import of Petroleum Coke | F18: IMP | G18: =Commodities!C18 -> OILCOK | H18: =H$6*$N18 -> 16.603766 | I18: =I$6*$N18 -> 16.227709 | J18: =J$6*$N18 -> 18.28837 | K18: =K$6*$N18 -> 19.576284 | L18: =L$6*$N18 -> 20.864197 | M18: =M$6*$N18 -> 21.894528 | N18: 1.6470588
C19: =Processes!C21 -> IE,National | D19: =Processes!D21 -> IMPNUCURM | E19: =Processes!E21 -> Import of Uranium | F19: IMP | G19: =Commodities!C23 -> NUCURM
C20: =Processes!C18 -> IE,National | D20: =Processes!D18 -> IMPOILNEU | E20: =Processes!E18 -> Import of Oil for Non-Energy uses | F20: IMP | G20: =Commodities!C20 -> OILNEU | H20: =H6 -> 10.080858 | I20: =I6 -> 9.8525376 | J20: =J6 -> 11.103653 | K20: =K6 -> 11.885601 | L20: =L6 -> 12.667548 | M20: =M6 -> 13.293106
C24: Fossil fuels import prices | G24: Stated Policies | K24: Sustainable Development | M24: Delayed Recovery
C25: Real Terms (2019 Prices) | D25: unit | E25: 2010 | F25: 2019 | G25: 2025 | H25: 2030 | I25: 2035 | J25: 2040 | K25: 2025 | L25: 2040 | M25: 2025 | N25: 2040
C26: IEA crude oil | D26: $2019/barrel | E26: 91 | F26: 63 | G26: 71 | H26: 76 | I26: 81 | J26: 85 | K26: 57 | L26: 53 | M26: 59 | N26: 71
C27: Natural Gas - EU | D27: $2019/MBtu | E27: 8.7 | F27: 6.7 | G27: 7.3 | H27: 11.1 | I27: 13 | J27: =I27*(1+(I27/H27-1)) -> 15.225225 | K27: 4.8 | L27: 4.9 | M27: 6.3 | N27: 7.6
C28: Steam coal - EU | D28: $2019/tonne | E28: 108 | F28: 61 | G28: 65 | H28: 80 | I28: 88 | J28: =I28*(1+(I28/H28-1)) -> 96.8 | K28: 57 | L28: 55 | M28: 60 | N28: 64
C29: Source: Table 2.2 - Fossil fuel prices by scenario - WEO 2020, IEA
C31: Conversion to from USD to EUR | E31: =E25 -> 2010 | F31: =F25 -> 2019 | G31: =G25 -> 2025 | H31: =H25 -> 2030 | I31: =I25 -> 2035 | J31: =J25 -> 2040 | K31: =K25 -> 2025 | L31: =L25 -> 2040 | ... N31: =N25 -> 2040
C32: =C26 -> IEA crude oil | D32: €2019/barrel | E32: =E26/Conversions!$C$10 -> 81.288139 | F32: =F26/Conversions!$C$10 -> 56.276404 | G32: =G26/Conversions!$C$10 -> 63.422614 | H32: =H26/Conversions!$C$10 -> 67.888996 | I32: =I26/Conversions!$C$10 -> 72.355377 | J32: =J26/Conversions!$C$10 -> 75.928482 | K32: =K26/Conversions!$C$10 -> 50.916747 | L32: =L26/Conversions!$C$10 -> 47.343642 | ... N32: =N26/Conversions!$C$10 -> 63.422614
C33: =C27 -> Natural Gas - EU | D33: €2019/MBtu | E33: =E27/Conversions!$C$10 -> 7.7715034 | F33: =F27/Conversions!$C$10 -> 5.9849509 | G33: =G27/Conversions!$C$10 -> 6.5209167 | H33: =H27/Conversions!$C$10 -> 9.9153665 | I33: =I27/Conversions!$C$10 -> 11.612591 | J33: =J27/Conversions!$C$10 -> 13.600332 | K33: =K27/Conversions!$C$10 -> 4.287726 | L33: =L27/Conversions!$C$10 -> 4.3770537 | ... N33: =N27/Conversions!$C$10 -> 6.7888996
C34: =C28 -> Steam coal - EU | D34: €2019/tonne | E34: =E28/Conversions!$C$10 -> 96.473836 | F34: =F28/Conversions!$C$10 -> 54.489852 | G34: =G28/Conversions!$C$10 -> 58.062957 | H34: =H28/Conversions!$C$10 -> 71.462101 | I34: =I28/Conversions!$C$10 -> 78.608311 | J34: =J28/Conversions!$C$10 -> 86.469142 | K34: =K28/Conversions!$C$10 -> 50.916747 | L34: =L28/Conversions!$C$10 -> 49.130194 | ... N34: =N28/Conversions!$C$10 -> 57.16968
C36: Conversion to EUR/GJ | E36: =E25 -> 2010 | F36: =F25 -> 2019 | G36: =G25 -> 2025 | H36: =H25 -> 2030 | I36: =I25 -> 2035 | J36: =J25 -> 2040 | K36: =K25 -> 2025 | L36: =L25 -> 2040 | ... N36: =N25 -> 2040
C37: =C26 -> IEA crude oil | D37: €2019/GJ | E37: =E32/Conversions!$C$5 -> 14.231443 | F37: =F32/Conversions!$C$5 -> 9.8525376 | G37: =G32/Conversions!$C$5 -> 11.103653 | H37: =H32/Conversions!$C$5 -> 11.885601 | I37: =I32/Conversions!$C$5 -> 12.667548 | J37: =J32/Conversions!$C$5 -> 13.293106 | K37: =K32/Conversions!$C$5 -> 8.9142007 | L37: =L32/Conversions!$C$5 -> 8.2886427 | ... N37: =N32/Conversions!$C$5 -> 11.103653
C38: =C27 -> Natural Gas - EU | D38: €2019/GJ | E38: =E33/Conversions!$C$3 -> 7.3656558 | F38: =F33/Conversions!$C$3 -> 5.6724016 | G38: =G33/Conversions!$C$3 -> 6.1803779 | H38: =H33/Conversions!$C$3 -> 9.3975609 | I38: =I33/Conversions!$C$3 -> 11.006152 | J38: =J33/Conversions!$C$3 -> 12.890088 | K38: =K33/Conversions!$C$3 -> 4.0638101 | L38: =L33/Conversions!$C$3 -> 4.1484728 | ... N38: =N33/Conversions!$C$3 -> 6.434366
C39: =C28 -> Steam coal - EU | D39: €2019/GJ | E39: =E34/(Conversions!$C$2*1000) -> 2.304238 | F39: =F34/(Conversions!$C$2*1000) -> 1.3014677 | G39: =G34/(Conversions!$C$2*1000) -> 1.3868099 | H39: =H34/(Conversions!$C$2*1000) -> 1.7068429 | I39: =I34/(Conversions!$C$2*1000) -> 1.8775272 | J39: =J34/(Conversions!$C$2*1000) -> 2.06528 | K39: =K34/(Conversions!$C$2*1000) -> 1.2161256 | L39: =L34/(Conversions!$C$2*1000) -> 1.1734545 | ... N39: =N34/(Conversions!$C$2*1000) -> 1.3654744
C42: Fossil fuels import prices | G42: Stated Policies | K42: Sustainable Development | M42: Current Policies
C43: Real Terms (2018 Prices) | D43: unit | E43: 2010 | F43: 2018 | G43: 2025 | H43: 2030 | I43: 2035 | J43: 2040 | K43: 2025 | L43: 2040 | M43: 2025 | N43: 2040
C44: IEA crude oil | D44: $2018/barrel | E44: 90 | F44: 68 | G44: 81 | H44: 88 | I44: 96 | J44: 103 | K44: 62 | L44: 59 | M44: 111 | N44: 134
C45: Natural Gas - EU | D45: $2018/MBtu | E45: 8.6 | F45: 7.6 | G45: 8 | H45: 8 | I45: 8.4 | J45: 8.9 | K45: 7.5 | L45: 7.5 | M45: 8.9 | N45: 9.9
C46: Steam coal - EU | D46: $2018/tonne | E46: 106 | F46: 92 | G46: 75 | H46: 76 | I46: 78 | J46: 78 | K46: 58 | L46: 60 | M46: 83 | N46: 90
C47: Source: Table B.4 - Fossil fuel prices by scenario - WEO 2019, IEA
C49: Conversion to from USD to EUR | E49: =E43 -> 2010 | F49: =F43 -> 2018 | G49: =G43 -> 2025 | H49: =H43 -> 2030 | I49: =I43 -> 2035 | J49: =J43 -> 2040 | K49: =K43 -> 2025 | L49: =L43 -> 2040 | ... N49: =N43 -> 2040
C50: =C44 -> IEA crude oil | D50: €2018/barrel | E50: =E44/Conversions!$C$11 -> 76.20954 | F50: =F44/Conversions!$C$11 -> 57.580541 | G50: =G44/Conversions!$C$11 -> 68.588586 | H50: =H44/Conversions!$C$11 -> 74.515995 | I50: =I44/Conversions!$C$11 -> 81.290176 | J50: =J44/Conversions!$C$11 -> 87.217585 | K50: =K44/Conversions!$C$11 -> 52.499905 | L50: =L44/Conversions!$C$11 -> 49.959587 | ... N50: =N44/Conversions!$C$11 -> 113.46754
C51: =C45 -> Natural Gas - EU | D51: €2018/MBtu | E51: =E45/Conversions!$C$11 -> 7.2822449 | F51: =F45/Conversions!$C$11 -> 6.4354723 | G51: =G45/Conversions!$C$11 -> 6.7741813 | H51: =H45/Conversions!$C$11 -> 6.7741813 | I51: =I45/Conversions!$C$11 -> 7.1128904 | J51: =J45/Conversions!$C$11 -> 7.5362767 | K51: =K45/Conversions!$C$11 -> 6.350795 | L51: =L45/Conversions!$C$11 -> 6.350795 | ... N51: =N45/Conversions!$C$11 -> 8.3830494
C52: =C46 -> Steam coal - EU | D52: €2018/tonne | E52: =E46/Conversions!$C$11 -> 89.757903 | F52: =F46/Conversions!$C$11 -> 77.903085 | G52: =G46/Conversions!$C$11 -> 63.50795 | H52: =H46/Conversions!$C$11 -> 64.354723 | I52: =I46/Conversions!$C$11 -> 66.048268 | J52: =J46/Conversions!$C$11 -> 66.048268 | K52: =K46/Conversions!$C$11 -> 49.112815 | L52: =L46/Conversions!$C$11 -> 50.80636 | ... N52: =N46/Conversions!$C$11 -> 76.20954
C54: Conversion to EUR/GJ | E54: =E43 -> 2010 | F54: =F43 -> 2018 | G54: =G43 -> 2025 | H54: =H43 -> 2030 | I54: =I43 -> 2035 | J54: =J43 -> 2040 | K54: =K43 -> 2025 | L54: =L43 -> 2040 | ... N54: =N43 -> 2040
C55: =C44 -> IEA crude oil | D55: €2018/GJ | E55: =E50/Conversions!$C$5 -> 13.342312 | F55: =F50/Conversions!$C$5 -> 10.080858 | G55: =G50/Conversions!$C$5 -> 12.008081 | H55: =H50/Conversions!$C$5 -> 13.045816 | I55: =I50/Conversions!$C$5 -> 14.2318 | J55: =J50/Conversions!$C$5 -> 15.269535 | K55: =K50/Conversions!$C$5 -> 9.1913706 | L55: =L50/Conversions!$C$5 -> 8.7466269 | ... N55: =N50/Conversions!$C$5 -> 19.86522
C56: =C45 -> Natural Gas - EU | D56: €2018/GJ | E56: =E51/Conversions!$C$3 -> 6.9019476 | F56: =F51/Conversions!$C$3 -> 6.0993956 | G56: =G51/Conversions!$C$3 -> 6.4204164 | H56: =H51/Conversions!$C$3 -> 6.4204164 | I56: =I51/Conversions!$C$3 -> 6.7414372 | J56: =J51/Conversions!$C$3 -> 7.1427132 | K56: =K51/Conversions!$C$3 -> 6.0191404 | L56: =L51/Conversions!$C$3 -> 6.0191404 | ... N56: =N51/Conversions!$C$3 -> 7.9452653
C57: =C46 -> Steam coal - EU | D57: €2018/GJ | E57: =E52/(Conversions!$C$2*1000) -> 2.1438307 | F57: =F52/(Conversions!$C$2*1000) -> 1.8606832 | G57: =G52/(Conversions!$C$2*1000) -> 1.5168613 | H57: =H52/(Conversions!$C$2*1000) -> 1.5370861 | I57: =I52/(Conversions!$C$2*1000) -> 1.5775358 | J57: =J52/(Conversions!$C$2*1000) -> 1.5775358 | K57: =K52/(Conversions!$C$2*1000) -> 1.1730394 | L57: =L52/(Conversions!$C$2*1000) -> 1.2134891 | ... N57: =N52/(Conversions!$C$2*1000) -> 1.8202336
B64: Source | C64: ICCT (2022), Current and future cost of e-kerosene in the United States and Europe | F64: https://theicct.org/wp-content/uploads/2022/02/fuels-us-europe-current-future-cost-ekerosene-us-europe-mar22.pdf
C100: e-kerosene price in EU
D101: Average PtL (€/GJ) | E101: Max PtL (€/GJ) | F101: Average SAF (€/GJ) | G101: Max SAF (€/GJ)
C102: 2020 | D102: =H111*$E$120*1000 -> 84.28 | E102: =K111*$E$120*1000/$E$121 -> 114.81235 | F102: =1000*F157*E120/32 -> 29.83125 | G102: =1000*E157*E120/32 -> 35.475
C103: 2025 | D103: =H112*$E$120*1000 -> 73.96 | E103: =K112*$E$120*1000/$E$121 -> 97.840679
C104: 2030 | D104: =H113*$E$120*1000 -> 62.78 | E104: =K113*$E$120*1000/$E$121 -> 87.022083 | F104: =1000*F158*E120/32 -> 27.4125 | G104: =1000*E158*E120/32 -> 32.7875
C105: 2035 | D105: =H114*$E$120*1000 -> 57.62 | E105: =K114*$E$120*1000/$E$121 -> 81.545169
C106: 2040 | D106: =H115*$E$120*1000 -> 53.32 | E106: =K115*$E$120*1000/$E$121 -> 76.879649
C107: 2045 | D107: =H116*$E$120*1000 -> 49.02 | E107: =K116*$E$120*1000/$E$121 -> 69.915178
C108: 2050 | D108: =H117*$E$120*1000 -> 45.58 | E108: =K117*$E$120*1000/$E$121 -> 63.085939
C110: Year | D110: U.S. average (USD per MJ) | E110: U.S. average (USD per gallon) | F110: U.S. min (USD per gallon) | G110: U.S. max (USD per gallon) | H110: EU average (USD per MJ) | I110: EU average (USD per gallon) | J110: EU min (USD per gallon) | K110: EU max (USD per gallon)
C111: 2020 | D111: 0.069 | E111: 8.776 | F111: 6.53 | G111: 11.91 | H111: 0.098 | I111: 12.437 | J111: 8.73 | K111: 16.98
C112: 2025 | D112: 0.061 | E112: 7.754 | F112: 5.52 | G112: 10.67 | H112: 0.086 | I112: 10.817 | J112: 7.71 | K112: 14.47
C113: 2030 | D113: 0.054 | E113: 6.779 | F113: 4.7 | G113: 9.39 | H113: 0.073 | I113: 9.284 | J113: 6.23 | K113: 12.87
C114: 2035 | D114: 0.047 | E114: 5.993 | F114: 4.04 | G114: 8.7 | H114: 0.067 | I114: 8.525 | J114: 5.56 | K114: 12.06
C115: 2040 | D115: 0.042 | E115: 5.267 | F115: 3.46 | G115: 8.04 | H115: 0.062 | I115: 7.878 | J115: 4.96 | K115: 11.37
C116: 2045 | D116: 0.037 | E116: 4.614 | F116: 2.95 | G116: 7.41 | H116: 0.057 | I116: 7.264 | J116: 4.37 | K116: 10.34
C117: 2050 | D117: 0.032 | E117: 4.025 | F117: 2.5 | G117: 6.78 | H117: 0.053 | I117: 6.721 | J117: 3.85 | K117: 9.33
D120: USD to EUR | E120: 0.86
D121: MJ/gal | E121: =E111/D111 -> 127.18841
C127: IEA | D127: https://www.iea.org/articles/are-conditions-right-for-biojet-to-take-flight-over-the-next-five-years
C154: Fuel Type / Year | D154: Min (USD/litre) | E154: Max (USD/litre) | F154: Average (USD/litre)
C155: Fossil jet range (2010–2020) | D155: 0.3 | E155: 0.82 | F155: 0.55
C156: Fossil jet range with CO₂ price | D156: 0.42 | E156: 0.95 | F156: —
C157: HEFA production range (2021) | D157: 0.92 | E157: 1.32 | F157: 1.11
C158: HEFA production range (2030) | D158: 0.85 | E158: 1.22 | F158: 1.02

Sheet Import CO2
B2: ~FI_Process
B3: Sets | C3: Region | D3: TechName | E3: TechDesc | F3: Tact | G3: Tcap | H3: Tslvl | I3: PrimaryCG | J3: Vintage
B4: \I: Process Set Membership | D4: Technology name | E4: Description | F4: Activity unit | G4: Capacity unit | H4: TimeSlice level of Process Activity | I4: Primary Commodity Group | J4: Vintage Tracking
B5: MIN | C5: =_xlfn.TEXTJOIN(",",TRUE,IF(LEFT(Regions!$C$3,1)<>"*",Regions!$C$3,""),IF(LEFT(Regions!$D$3,1)<>"*",Regions!$D$3,"")) -> IE,National | D5: MINCO2-CAL | E5: Domestic CO2 calibration | F5: PJ | G5: Pja
E9: ~FI_T
B10: Region | C10: TechName | D10: TechDesc | E10: Comm-OUT | F10: CUM | G10: COST~2018 | H10: ACT_BND~2023 | I10: ACT_BND~0
B11: *Region Name | C11: *Technology Name | D11: Technology Description | F11: PJ | G11: Euro/GJ
B12: =Processes!C61 -> IE,National | C12: =D5 -> MINCO2-CAL | D12: Domestic CO2 calibration | E12: AGRCO2N | F12: 1000000 | G12: 0.0001 | H12: 0 | I12: 5
E13: INDCO2N
E14: INDCO2P
E15: PWRCO2N
E16: RSDCO2
E17: SRVCO2N
E18: TRACO2N

Sheet Imports_Bio
B2: Imported Bioenergy costs (€/GJ) | E2: ~FI_T: MEUR2010
B3: Region | C3: TechName | D3: *TechDesc | E3: Comm-OUT | F3: COST~2015 | G3: COST~2020 | H3: COST~2025 | I3: COST~2030 | J3: COST~2040 | K3: COST~2050 | L3: *Notes
B4: \I:Region Name | C4: \I:Technology Name | D4: Technology Description | E4: Output Commodity | F4: €/GJ | G4: €/GJ | H4: €/GJ | I4: €/GJ | J4: €/GJ | K4: €/GJ
B5: =Processes!C23 -> IE,National | C5: =Processes!D23 -> IMPBIOETH1G_S1 | D5: =Processes!E23 -> Import of Ethanol 1st generation - Step 1 | E5: =Commodities!$C$30 -> BIOETH1G | F5: ='SEAI-AEA_BioData'!K$23 -> 18.176173 | G5: ='SEAI-AEA_BioData'!L$23 -> 17.579058 | H5: ='SEAI-AEA_BioData'!M$23 -> 16.59979 | I5: ='SEAI-AEA_BioData'!N$23 -> 15.883252
B6: =Processes!C24 -> IE,National | C6: =Processes!D24 -> IMPBIOETH1G_S2 | D6: =Processes!E24 -> Import of Ethanol 1st generation - Step 2 | E6: =Commodities!$C$30 -> BIOETH1G | F6: ='SEAI-AEA_BioData'!K$33 -> 18.916595 | G6: ='SEAI-AEA_BioData'!L$33 -> 19.083787 | H6: ='SEAI-AEA_BioData'!M$33 -> 18.916595 | I6: ='SEAI-AEA_BioData'!N$33 -> 19.131556 | J6: =I6*Imports_Fossil!$I$37/Imports_Fossil!$H$37 -> 20.390211 | K6: =I6*Imports_Fossil!$J$37/Imports_Fossil!$H$37 -> 21.397135
B7: =Processes!C25 -> IE,National | C7: =Processes!D25 -> IMPBIOETH1G_S3 | D7: =Processes!E25 -> Import of Ethanol 1st generation - Step 3 | E7: =Commodities!$C$30 -> BIOETH1G | F7: ='SEAI-AEA_BioData'!K$44 -> 19.680902 | G7: ='SEAI-AEA_BioData'!L$44 -> 20.684055 | H7: ='SEAI-AEA_BioData'!M$44 -> 21.758861 | I7: ='SEAI-AEA_BioData'!N$44 -> 23.550205 | J7: =I7*Imports_Fossil!$I$37/Imports_Fossil!$H$37 -> 25.099561 | K7: =I7*Imports_Fossil!$J$37/Imports_Fossil!$H$37 -> 26.339046
B8: =Processes!C26 -> IE,National | C8: =Processes!D26 -> IMPBIOETH1G_S4 | D8: =Processes!E26 -> Import of Ethanol 1st generation - Step 4 | E8: =Commodities!$C$30 -> BIOETH1G | F8: ='SEAI-AEA_BioData'!K$55 -> 20.636285 | G8: ='SEAI-AEA_BioData'!L$55 -> 22.714245 | H8: ='SEAI-AEA_BioData'!M$55 -> 25.174358 | I8: ='SEAI-AEA_BioData'!N$55 -> 28.757046 | J8: =I8*Imports_Fossil!$I$37/Imports_Fossil!$H$37 -> 30.648957 | K8: =I8*Imports_Fossil!$J$37/Imports_Fossil!$H$37 -> 32.162486
B9: =Processes!C27 -> IE,National | C9: =Processes!D27 -> IMPBIODST1G_S1 | D9: =Processes!E27 -> Import of Biodiesel 1st generation - Step 1 | E9: =Commodities!$C$32 -> BIODST1G | F9: ='SEAI-AEA_BioData'!K$25 -> 31.360466 | G9: ='SEAI-AEA_BioData'!L$25 -> 33.175695 | H9: ='SEAI-AEA_BioData'!M$25 -> 31.862043 | I9: ='SEAI-AEA_BioData'!N$25 -> 31.336582
B10: =Processes!C28 -> IE,National | C10: =Processes!D28 -> IMPBIODST1G_S2 | D10: =Processes!E28 -> Import of Biodiesel 1st generation - Step 2 | E10: =Commodities!$C$32 -> BIODST1G | F10: ='SEAI-AEA_BioData'!K$35 -> 32.650234 | G10: ='SEAI-AEA_BioData'!L$35 -> 35.826884 | H10: ='SEAI-AEA_BioData'!M$35 -> 35.970192 | I10: ='SEAI-AEA_BioData'!N$35 -> 37.021114 | J10: =I10*Imports_Fossil!$I$37/Imports_Fossil!$H$37 -> 39.456714 | K10: =I10*Imports_Fossil!$J$37/Imports_Fossil!$H$37 -> 41.405193
B11: =Processes!C29 -> IE,National | C11: =Processes!D29 -> IMPBIODST1G_S3 | D11: =Processes!E29 -> Import of Biodiesel 1st generation - Step 3 | E11: =Commodities!$C$32 -> BIODST1G | F11: ='SEAI-AEA_BioData'!K$46 -> 33.916117 | G11: ='SEAI-AEA_BioData'!L$46 -> 38.334766 | H11: ='SEAI-AEA_BioData'!M$46 -> 40.460495 | I11: ='SEAI-AEA_BioData'!N$46 -> 43.756568 | J11: =I11*Imports_Fossil!$I$37/Imports_Fossil!$H$37 -> 46.63529 | K11: =I11*Imports_Fossil!$J$37/Imports_Fossil!$H$37 -> 48.938267
B12: =Processes!C30 -> IE,National | C12: =Processes!D30 -> IMPBIODST1G_S4 | D12: =Processes!E30 -> Import of Biodiesel 1st generation - Step 4 | E12: =Commodities!$C$32 -> BIODST1G | F12: ='SEAI-AEA_BioData'!K$57 -> 35.540269 | G12: ='SEAI-AEA_BioData'!L$57 -> 41.917455 | H12: ='SEAI-AEA_BioData'!M$57 -> 46.527181 | I12: ='SEAI-AEA_BioData'!N$57 -> 52.832712 | J12: =I12*Imports_Fossil!$I$37/Imports_Fossil!$H$37 -> 56.308549 | K12: =I12*Imports_Fossil!$J$37/Imports_Fossil!$H$37 -> 59.089218
B13: =Processes!C33 -> IE,National | C13: =Processes!D33 -> IMPBIOWPE_S1 | D13: =Processes!E33 -> Import of Wood Pellets - Step 1 | E13: =Commodities!$C$42 -> BIOWPE | F13: =$F$68 -> 9.6388889 | G13: =$F$68 -> 9.6388889 | H13: =$F$68 -> 9.6388889 | I13: =$F$68 -> 9.6388889 | J13: =$F$68 -> 9.6388889 | K13: =$F$68 -> 9.6388889
B14: =Processes!C34 -> IE,National | C14: =Processes!D34 -> IMPBIOWPE_S2 | D14: =Processes!E34 -> Import of Wood Pellets - Step 2 | E14: =Commodities!$C$42 -> BIOWPE | F14: =$F$69 -> 9.6388889 | G14: =$F$69 -> 9.6388889 | H14: =$F$69 -> 9.6388889 | I14: =$F$69 -> 9.6388889 | J14: =$F$69 -> 9.6388889 | K14: =$F$69 -> 9.6388889
B15: =Processes!C35 -> IE,National | C15: =Processes!D35 -> IMPBIOWPE_S3 | D15: =Processes!E35 -> Import of Wood Pellets - Step 3 | E15: =Commodities!$C$42 -> BIOWPE | F15: =$F$70 -> 10.166667 | G15: =$F$70 -> 10.166667 | H15: =$F$70 -> 10.166667 | I15: =$F$70 -> 10.166667 | J15: =$F$70 -> 10.166667 | K15: =$F$70 -> 10.166667
B16: =Processes!C36 -> IE,National | C16: =Processes!D36 -> IMPBIOWPE_S4 | D16: =Processes!E36 -> Import of Wood Pellets - Step 4 | E16: =Commodities!$C$42 -> BIOWPE | F16: =$F$71 -> 11.194444 | G16: =$F$71 -> 11.194444 | H16: =$F$71 -> 11.194444 | I16: =$F$71 -> 11.194444 | J16: =$F$71 -> 11.194444 | K16: =$F$71 -> 11.194444
B17: =Processes!C37 -> IE,National | C17: =Processes!D37 -> IMPBIOWCH_S1 | D17: =Processes!E37 -> Import of Wood Chip - Step 1 | E17: =Commodities!$C$43 -> BIOWCH | F17: ='SEAI-AEA_BioData'!K$19 -> 5.2068405 | G17: ='SEAI-AEA_BioData'!L$19 -> 4.1559186 | H17: ='SEAI-AEA_BioData'!M$19 -> 3.5588039 | I17: ='SEAI-AEA_BioData'!N$19 -> 3.3916117
B18: =Processes!C38 -> IE,National | C18: =Processes!D38 -> IMPBIOWCH_S2 | D18: =Processes!E38 -> Import of Wood Chip - Step 2 | E18: =Commodities!$C$43 -> BIOWCH | F18: ='SEAI-AEA_BioData'!K$40 -> 5.3979173 | G18: ='SEAI-AEA_BioData'!L$40 -> 4.4186491 | H18: ='SEAI-AEA_BioData'!M$40 -> 3.9409573 | I18: ='SEAI-AEA_BioData'!N$40 -> 3.8693035
B19: =Processes!C39 -> IE,National | C19: =Processes!D39 -> IMPBIOWCH_S3 | D19: =Processes!E39 -> Import of Wood Chip - Step 3 | E19: =Commodities!$C$43 -> BIOWCH | F19: ='SEAI-AEA_BioData'!K$29 -> 6.1383395 | G19: ='SEAI-AEA_BioData'!L$29 -> 5.0396484 | H19: ='SEAI-AEA_BioData'!M$29 -> 4.4664183 | I19: ='SEAI-AEA_BioData'!N$29 -> 4.3708799
B20: =Processes!C40 -> IE,National | C20: =Processes!D40 -> IMPBIOWCH_S4 | D20: =Processes!E40 -> Import of Wood Chip - Step 4 | E20: =Commodities!$C$43 -> BIOWCH | F20: ='SEAI-AEA_BioData'!K$51 -> 6.3771854 | G20: ='SEAI-AEA_BioData'!L$51 -> 5.3979173 | H20: ='SEAI-AEA_BioData'!M$51 -> 4.9918792 | I20: ='SEAI-AEA_BioData'!N$51 -> 5.0396484
B22: Imported Bioenergy costs (€/GJ) | F22: =Imports_Fossil!G3 -> ~FI_T: IRE_PRICE
B23: Region | C23: TechName | D23: *TechDesc | E23: Other_Indexes | F23: Comm-OUT | G23: =Imports_Fossil!H4 -> 2018~MEUR2018 | H23: =Imports_Fossil!I4 -> 2019~MEUR2019 | I23: =Imports_Fossil!J4 -> 2025~MEUR2019 | J23: =Imports_Fossil!K4 -> 2030~MEUR2019 | K23: =Imports_Fossil!L4 -> 2035~MEUR2019 | L23: =Imports_Fossil!M4 -> 2040~MEUR2019 | M23: 2050~MEUR2019 | N23: START | O23: *Notes
B24: \I:Region Name | C24: \I:Technology Name | D24: Technology Description | E24: Import/Export | F24: Output Commodity | G24: €/GJ | H24: €/GJ | I24: €/GJ | J24: €/GJ | K24: €/GJ | L24: €/GJ | M24: €/GJ | N24: Year
B25: =Processes!C31 -> IE,National | C25: =Processes!D31 -> IMPBIOJKR_S1 | D25: =Processes!E31 -> Import of Bio Jet Kerosene - Step 1 | E25: IMP | F25: =Commodities!C36 -> BIOJKR | G25: =Imports_Fossil!G102 -> 35.475 | I25: =Imports_Fossil!G104 -> 32.7875 | N25: 2025 | O25: From IEA Assumptions
B26: =B25 -> IE,National | C26: =Processes!D32 -> IMPPtLKER | D26: Import of PtL, Synthetic Kerosene | E26: IMP | F26: =Commodities!C37 -> PtLKER | G26: =Imports_Fossil!E102 -> 114.81235 | I26: =Imports_Fossil!E103 -> 97.840679 | J26: 63.6 | L26: 47 | M26: 42 | N26: 2030 | O26: From ICCT Working Paper, and updated from https://www.sciencedirect.com/science/article/pii/S2352484725008947
B28: Imported Bioenergy delivery costs (€/GJ) | E28: ~FI_T: MEUR2011 | N28: Energy crops - Delivery Cost
B29: Region | C29: TechName | D29: *TechDesc | E29: Comm-OUT | F29: DELIV~2012 | G29: DELIV~2020 | H29: DELIV~2030 | I29: DELIV~2040 | J29: DELIV~2050 | K29: *Notes | N29: Source: Clancy et al., The economic viability of biomass crops versus conventional agricultural systems and its potential impact on farm incomes in Ireland, Energy Policy 2012
B30: \I:Region Name | C30: \I:Technology Name | D30: Technology Description | E30: Output Commodity | F30: €/GJ | G30: €/GJ | H30: €/GJ | I30: €/GJ | J30: €/GJ | P30: Transport and Processing | R30: Full Adder
B31: =B13 -> IE,National | C31: =C13 -> IMPBIOWPE_S1 | D31: =D13 -> Import of Wood Pellets - Step 1 | E31: =Commodities!$C$42 -> BIOWPE | F31: =SUM($P$31:$R$31) -> 4.85 | G31: =SUM($P$31:$Q$31)+$R$31*(Imports_Fossil!G$37/Imports_Fossil!$E$37) -> 4.3203297 | H31: =SUM($P$31:$Q$31)+$R$31*(Imports_Fossil!H$37/Imports_Fossil!$E$37) -> 4.4527473 | I31: =SUM($P$31:$Q$31)+$R$31*(Imports_Fossil!I$37/Imports_Fossil!$E$37) -> 4.5851648 | J31: =SUM($P$31:$Q$31)+$R$31*(Imports_Fossil!J$37/Imports_Fossil!$E$37) -> 4.6910989 | K31: Based on Clancy et al., The economic viability of biomass crops versus conventional agricultural systems and its potential impact on farm incomes in Ireland, Energy Policy 2012 Transport, p[rocessing and fuel adder | N31: Miscanthus/Willow | O31: €(11)/GJ | P31: 0.53 | Q31: 1.91 | R31: 2.41
B32: =B14 -> IE,National | C32: =C14 -> IMPBIOWPE_S2 | D32: =D14 -> Import of Wood Pellets - Step 2 | E32: =Commodities!$C$42 -> BIOWPE | F32: =SUM($P$31:$R$31) -> 4.85 | G32: =SUM($P$31:$Q$31)+$R$31*(Imports_Fossil!G$37/Imports_Fossil!$E$37) -> 4.3203297 | H32: =SUM($P$31:$Q$31)+$R$31*(Imports_Fossil!H$37/Imports_Fossil!$E$37) -> 4.4527473 | I32: =SUM($P$31:$Q$31)+$R$31*(Imports_Fossil!I$37/Imports_Fossil!$E$37) -> 4.5851648 | J32: =SUM($P$31:$Q$31)+$R$31*(Imports_Fossil!J$37/Imports_Fossil!$E$37) -> 4.6910989
B33: =B15 -> IE,National | C33: =C15 -> IMPBIOWPE_S3 | D33: =D15 -> Import of Wood Pellets - Step 3 | E33: =Commodities!$C$42 -> BIOWPE | F33: =SUM($P$31:$R$31) -> 4.85 | G33: =SUM($P$31:$Q$31)+$R$31*(Imports_Fossil!G$37/Imports_Fossil!$E$37) -> 4.3203297 | H33: =SUM($P$31:$Q$31)+$R$31*(Imports_Fossil!H$37/Imports_Fossil!$E$37) -> 4.4527473 | I33: =SUM($P$31:$Q$31)+$R$31*(Imports_Fossil!I$37/Imports_Fossil!$E$37) -> 4.5851648 | J33: =SUM($P$31:$Q$31)+$R$31*(Imports_Fossil!J$37/Imports_Fossil!$E$37) -> 4.6910989
B34: =B16 -> IE,National | C34: =C16 -> IMPBIOWPE_S4 | D34: =D16 -> Import of Wood Pellets - Step 4 | E34: =Commodities!$C$42 -> BIOWPE | F34: =SUM($P$31:$R$31) -> 4.85 | G34: =SUM($P$31:$Q$31)+$R$31*(Imports_Fossil!G$37/Imports_Fossil!$E$37) -> 4.3203297 | H34: =SUM($P$31:$Q$31)+$R$31*(Imports_Fossil!H$37/Imports_Fossil!$E$37) -> 4.4527473 | I34: =SUM($P$31:$Q$31)+$R$31*(Imports_Fossil!I$37/Imports_Fossil!$E$37) -> 4.5851648 | J34: =SUM($P$31:$Q$31)+$R$31*(Imports_Fossil!J$37/Imports_Fossil!$E$37) -> 4.6910989
B35: =B17 -> IE,National | C35: =C17 -> IMPBIOWCH_S1 | D35: =D17 -> Import of Wood Chip - Step 1 | E35: =Commodities!$C$43 -> BIOWCH | F35: =SUM($P$31:$R$31) -> 4.85 | G35: =SUM($P$31:$Q$31)+$R$31*(Imports_Fossil!G$37/Imports_Fossil!$E$37) -> 4.3203297 | H35: =SUM($P$31:$Q$31)+$R$31*(Imports_Fossil!H$37/Imports_Fossil!$E$37) -> 4.4527473 | I35: =SUM($P$31:$Q$31)+$R$31*(Imports_Fossil!I$37/Imports_Fossil!$E$37) -> 4.5851648 | J35: =SUM($P$31:$Q$31)+$R$31*(Imports_Fossil!J$37/Imports_Fossil!$E$37) -> 4.6910989
B36: =B18 -> IE,National | C36: =C18 -> IMPBIOWCH_S2 | D36: =D18 -> Import of Wood Chip - Step 2 | E36: =Commodities!$C$43 -> BIOWCH | F36: =SUM($P$31:$R$31) -> 4.85 | G36: =SUM($P$31:$Q$31)+$R$31*(Imports_Fossil!G$37/Imports_Fossil!$E$37) -> 4.3203297 | H36: =SUM($P$31:$Q$31)+$R$31*(Imports_Fossil!H$37/Imports_Fossil!$E$37) -> 4.4527473 | I36: =SUM($P$31:$Q$31)+$R$31*(Imports_Fossil!I$37/Imports_Fossil!$E$37) -> 4.5851648 | J36: =SUM($P$31:$Q$31)+$R$31*(Imports_Fossil!J$37/Imports_Fossil!$E$37) -> 4.6910989
B37: =B19 -> IE,National | C37: =C19 -> IMPBIOWCH_S3 | D37: =D19 -> Import of Wood Chip - Step 3 | E37: =Commodities!$C$43 -> BIOWCH | F37: =SUM($P$31:$R$31) -> 4.85 | G37: =SUM($P$31:$Q$31)+$R$31*(Imports_Fossil!G$37/Imports_Fossil!$E$37) -> 4.3203297 | H37: =SUM($P$31:$Q$31)+$R$31*(Imports_Fossil!H$37/Imports_Fossil!$E$37) -> 4.4527473 | I37: =SUM($P$31:$Q$31)+$R$31*(Imports_Fossil!I$37/Imports_Fossil!$E$37) -> 4.5851648 | J37: =SUM($P$31:$Q$31)+$R$31*(Imports_Fossil!J$37/Imports_Fossil!$E$37) -> 4.6910989
B38: =B20 -> IE,National | C38: =C20 -> IMPBIOWCH_S4 | D38: =D20 -> Import of Wood Chip - Step 4 | E38: =Commodities!$C$43 -> BIOWCH | F38: =SUM($P$31:$R$31) -> 4.85 | G38: =SUM($P$31:$Q$31)+$R$31*(Imports_Fossil!G$37/Imports_Fossil!$E$37) -> 4.3203297 | H38: =SUM($P$31:$Q$31)+$R$31*(Imports_Fossil!H$37/Imports_Fossil!$E$37) -> 4.4527473 | I38: =SUM($P$31:$Q$31)+$R$31*(Imports_Fossil!I$37/Imports_Fossil!$E$37) -> 4.5851648 | J38: =SUM($P$31:$Q$31)+$R$31*(Imports_Fossil!J$37/Imports_Fossil!$E$37) -> 4.6910989
B41: Imported Bioenergy potentials (PJ) | E41: ~FI_T: ACT_BND~UP
B42: Region | C42: TechName | D42: *TechDesc | E42: Comm-OUT | F42: 2018 | G42: 2020 | H42: 2025 | I42: 2030 | J42: 2035 | K42: 2040 | L42: 2045 | M42: 2050 | N42: 0 | O42: *Notes
B43: \I:Region Name | C43: \I:Technology Name | D43: Technology Description | E43: Output Commodity | F43: PJ | G43: PJ | H43: PJ | I43: PJ | J43: PJ | K43: PJ | L43: PJ | M43: PJ | N43: I/E rule
B44: =Imports_Bio!B5 -> IE,National | C44: =Imports_Bio!C5 -> IMPBIOETH1G_S1 | D44: =Imports_Bio!D5 -> Import of Ethanol 1st generation - Step 1 | E44: =Commodities!$C$30 -> BIOETH1G | F44: ='EB2018'!AJ3*Conversions!$C$2 -> 0.95614079 | G44: =F44 -> 0.95614079 | H44: =G44 -> 0.95614079 | I44: =H44 -> 0.95614079 | J44: =I44 -> 0.95614079 | K44: =J44 -> 0.95614079 | L44: =K44 -> 0.95614079 | M44: =L44 -> 0.95614079 | N44: 5 | O44: Consumption in 2018
B45: =Imports_Bio!B6 -> IE,National | C45: =Imports_Bio!C6 -> IMPBIOETH1G_S2 | D45: =Imports_Bio!D6 -> Import of Ethanol 1st generation - Step 2 | E45: =Commodities!$C$30 -> BIOETH1G | F45: 0 | G45: =G44*2 -> 1.9122816 | H45: =H44*2 -> 1.9122816 | I45: =I44*2 -> 1.9122816 | J45: =J44*2 -> 1.9122816 | K45: =K44*2 -> 1.9122816 | L45: =L44*2 -> 1.9122816 | M45: =M44*2 -> 1.9122816 | N45: 5 | O45: Doubling Step I
B46: =Imports_Bio!B7 -> IE,National | C46: =Imports_Bio!C7 -> IMPBIOETH1G_S3 | D46: =Imports_Bio!D7 -> Import of Ethanol 1st generation - Step 3 | E46: =Commodities!$C$30 -> BIOETH1G | F46: 0 | G46: =G45*2 -> 3.8245632 | H46: =H45*2 -> 3.8245632 | I46: =I45*2 -> 3.8245632 | J46: =J45*2 -> 3.8245632 | K46: =K45*2 -> 3.8245632 | L46: =L45*2 -> 3.8245632 | M46: =M45*2 -> 3.8245632 | N46: 5 | O46: Doubling Step II
B47: ="*"&Imports_Bio!B8 -> *IE,National | C47: ="*"&Imports_Bio!C8 -> *IMPBIOETH1G_S4 | D47: =Imports_Bio!D8 -> Import of Ethanol 1st generation - Step 4 | E47: =Commodities!$C$30 -> BIOETH1G | F47: 0 | G47: 0 | H47: 0 | I47: 0 | J47: 0 | K47: 0 | L47: 0 | M47: 0 | N47: 5 | O47: Bound not set
B48: *Total | G48: =H48 -> 59.810866 | H48: =I48 -> 59.810866 | I48: ='SEAI-AEA_BioData'!G54*Conversions!$C$2/1000 -> 59.810866 | J48: =I48 -> 59.810866 | K48: =J48 -> 59.810866 | L48: =K48 -> 59.810866 | M48: =L48 -> 59.810866 | O48: Max 2030 potential (Amb Supply, High Dem scenario)
B49: =Imports_Bio!B9 -> IE,National | C49: =Imports_Bio!C9 -> IMPBIODST1G_S1 | D49: =Imports_Bio!D9 -> Import of Biodiesel 1st generation - Step 1 | E49: =Commodities!$C$32 -> BIODST1G | F49: ='EB2018'!AI3*Conversions!$C$2 -> 4.3883698 | G49: =F49 -> 4.3883698 | H49: =G49 -> 4.3883698 | I49: =H49 -> 4.3883698 | J49: =I49 -> 4.3883698 | K49: =J49 -> 4.3883698 | L49: =K49 -> 4.3883698 | M49: =L49 -> 4.3883698 | N49: 5 | O49: Consumption in 2018
B50: =Imports_Bio!B10 -> IE,National | C50: =Imports_Bio!C10 -> IMPBIODST1G_S2 | D50: =Imports_Bio!D10 -> Import of Biodiesel 1st generation - Step 2 | E50: =Commodities!$C$32 -> BIODST1G | F50: 0 | G50: =G49*2 -> 8.7767396 | H50: =H49*2 -> 8.7767396 | I50: =I49*2 -> 8.7767396 | J50: =J49*2 -> 8.7767396 | K50: =K49*2 -> 8.7767396 | L50: =L49*2 -> 8.7767396 | M50: =M49*2 -> 8.7767396 | N50: 5 | O50: Doubling Step I
B51: =Imports_Bio!B11 -> IE,National | C51: =Imports_Bio!C11 -> IMPBIODST1G_S3 | D51: =Imports_Bio!D11 -> Import of Biodiesel 1st generation - Step 3 | E51: =Commodities!$C$32 -> BIODST1G | F51: 0 | G51: =G50*2 -> 17.553479 | H51: =H50*2 -> 17.553479 | I51: =I50*2 -> 17.553479 | J51: =J50*2 -> 17.553479 | K51: =K50*2 -> 17.553479 | L51: =L50*2 -> 17.553479 | M51: =M50*2 -> 17.553479 | N51: 5 | O51: Doubling Step II
B52: ="*"&Imports_Bio!B12 -> *IE,National | C52: ="*"&Imports_Bio!C12 -> *IMPBIODST1G_S4 | D52: =Imports_Bio!D12 -> Import of Biodiesel 1st generation - Step 4 | E52: =Commodities!$C$32 -> BIODST1G | F52: 0 | G52: 0 | H52: 0 | I52: 0 | J52: 0 | K52: 0 | L52: 0 | M52: 0 | N52: 5 | O52: Bound not set
B53: *Total | G53: =H53 -> 102.75859 | H53: =I53 -> 102.75859 | I53: =2727.05194883825*Conversions!$C$2*0.9 -> 102.75859 | J53: =I53 -> 102.75859 | K53: =J53 -> 102.75859 | L53: =K53 -> 102.75859 | M53: =L53 -> 102.75859 | O53: 2015 Transport Diesel Consumption
B54: =Imports_Bio!B13 -> IE,National | C54: =Imports_Bio!C13 -> IMPBIOWPE_S1 | D54: =Imports_Bio!D13 -> Import of Wood Pellets - Step 1 | E54: =Commodities!$C$42 -> BIOWPE | F54: ='EB2018'!AE3*Conversions!$C$2*Imports_Bio!$R$54 -> 0.71165055 | G54: =G68 -> 1.8 | H54: =H68 -> 1.8 | I54: =I68 -> 1.8 | J54: =J68 -> 1.8 | K54: =K68 -> 3.6 | L54: =L68 -> 7.2 | M54: =M68 -> 7.2 | N54: 5 | O54: Max past consumption | R54: 0.7
B55: =Imports_Bio!B14 -> IE,National | C55: =Imports_Bio!C14 -> IMPBIOWPE_S2 | D55: =Imports_Bio!D14 -> Import of Wood Pellets - Step 2 | E55: =Commodities!$C$42 -> BIOWPE | F55: 0 | G55: =G69 -> 0 | H55: =H69 -> 3.6 | I55: =I69 -> 18 | J55: =J69 -> 36 | K55: =K69 -> 54 | L55: =L69 -> 61.2 | M55: =M69 -> 61.2 | N55: 5 | O55: From SEAI Heat Study
B56: =Imports_Bio!B15 -> IE,National | C56: =Imports_Bio!C15 -> IMPBIOWPE_S3 | D56: =Imports_Bio!D15 -> Import of Wood Pellets - Step 3 | E56: =Commodities!$C$42 -> BIOWPE | F56: 0 | G56: 0 | H56: 0 | I56: 0 | J56: 0 | K56: 0 | L56: 0 | M56: 0 | N56: 5 | O56: From SEAI Heat Study
B57: =B56 -> IE,National | C57: =Imports_Bio!C16 -> IMPBIOWPE_S4 | D57: =Imports_Bio!D16 -> Import of Wood Pellets - Step 4 | E57: =Commodities!$C$42 -> BIOWPE | F57: 0 | G57: 0 | H57: 0 | I57: 0 | J57: 0 | K57: 0 | L57: 0 | M57: 0 | N57: 5 | O57: From SEAI Heat Study
B58: *Total | G58: =SUM(G54:G57) -> 1.8 | H58: =SUM(H54:H57) -> 5.4 | I58: =SUM(I54:I57) -> 19.8 | J58: =SUM(J54:J57) -> 37.8 | K58: =SUM(K54:K57) -> 57.6 | L58: =SUM(L54:L57) -> 68.4 | M58: =SUM(M54:M57) -> 68.4 | O58: Max 2030 potential (Amb Supply, High Dem scenario)
B59: =Imports_Bio!B17 -> IE,National | C59: =Imports_Bio!C17 -> IMPBIOWCH_S1 | D59: =Imports_Bio!D17 -> Import of Wood Chip - Step 1 | E59: =Commodities!$C$43 -> BIOWCH | F59: ='EB2018'!AE3*Conversions!$C$2*Imports_Bio!$R$59 -> 0.30499309 | G59: =MAX(F59:F59) -> 0.30499309 | H59: =G59 -> 0.30499309 | I59: =H59 -> 0.30499309 | J59: =I59 -> 0.30499309 | K59: =J59 -> 0.30499309 | L59: =K59 -> 0.30499309 | M59: =L59 -> 0.30499309 | N59: 5 | O59: Max past consumption | R59: =1-R54 -> 0.3
B60: ="*"&Imports_Bio!B18 -> *IE,National | C60: =Imports_Bio!C18 -> IMPBIOWCH_S2 | D60: =Imports_Bio!D18 -> Import of Wood Chip - Step 2 | E60: =Commodities!$C$43 -> BIOWCH | F60: 0 | G60: =G59*2 -> 0.60998619 | H60: =H59*2 -> 0.60998619 | I60: =I59*2 -> 0.60998619 | J60: =J59*2 -> 0.60998619 | K60: =K59*2 -> 0.60998619 | L60: =L59*2 -> 0.60998619 | M60: =M59*2 -> 0.60998619 | N60: 5 | O60: Doubling Step I
B61: ="*"&Imports_Bio!B19 -> *IE,National | C61: =Imports_Bio!C19 -> IMPBIOWCH_S3 | D61: =Imports_Bio!D19 -> Import of Wood Chip - Step 3 | E61: =Commodities!$C$43 -> BIOWCH | F61: 0 | G61: =G60*2 -> 1.2199724 | H61: =H60*2 -> 1.2199724 | I61: =I60*2 -> 1.2199724 | J61: =J60*2 -> 1.2199724 | K61: =K60*2 -> 1.2199724 | L61: =L60*2 -> 1.2199724 | M61: =M60*2 -> 1.2199724 | N61: 5 | O61: Doubling Step II
B62: ="*"&Imports_Bio!B20 -> *IE,National | C62: ="*"&Imports_Bio!C20 -> *IMPBIOWCH_S4 | D62: =Imports_Bio!D20 -> Import of Wood Chip - Step 4 | E62: =Commodities!$C$43 -> BIOWCH | F62: 0 | G62: =G63-SUM(G59:G61) -> 34.580521 | H62: =H63-SUM(H59:H61) -> 34.580521 | I62: =I63-SUM(I59:I61) -> 34.580521 | J62: =J63-SUM(J59:J61) -> 34.580521 | K62: =K63-SUM(K59:K61) -> 34.580521 | L62: =L63-SUM(L59:L61) -> 34.580521 | M62: =M63-SUM(M59:M61) -> 34.580521 | N62: 5 | O62: Bound not set
B63: *Total | G63: =H63 -> 36.715473 | H63: =I63 -> 36.715473 | I63: ='SEAI-AEA_BioData'!G50*Conversions!$C$2/1000 -> 36.715473 | J63: =I63 -> 36.715473 | K63: =J63 -> 36.715473 | L63: =K63 -> 36.715473 | M63: =L63 -> 36.715473 | O63: Max 2030 potential (Amb Supply, High Dem scenario)
G66: Potential quantities of wood pellets available for import to Ireland (PJ)
D67: SEAI Heat Study | E67: Cost (€/MWh) | F67: Cost (€/GJ) | G67: 2020 | H67: 2025 | I67: 2030 | J67: 2035 | K67: 2040 | L67: 2045 | M67: 2050
D68: Import of Wood Pellets - Step 1 | E68: =34.7 -> 34.7 | F68: =E68/3.6 -> 9.6388889 | G68: =500*3.6/1000 -> 1.8 | H68: =500*3.6/1000 -> 1.8 | I68: =500*3.6/1000 -> 1.8 | J68: =500*3.6/1000 -> 1.8 | K68: =1000*3.6/1000 -> 3.6 | L68: =2000*3.6/1000 -> 7.2 | M68: =2000*3.6/1000 -> 7.2
D69: Import of Wood Pellets - Step 2 | E69: =34.7 -> 34.7 | F69: =E69/3.6 -> 9.6388889 | G69: 0 | H69: =1000*3.6/1000 -> 3.6 | I69: =5000*3.6/1000 -> 18 | J69: =10000*3.6/1000 -> 36 | K69: =15000*3.6/1000 -> 54 | L69: =17000*3.6/1000 -> 61.2 | M69: =17000*3.6/1000 -> 61.2
D70: Import of Wood Pellets - Step 3 | E70: =36.6 -> 36.6 | F70: =E70/3.6 -> 10.166667 | G70: 0 | H70: 0 | I70: =15000*3.6/1000 -> 54 | J70: =I70 -> 54 | K70: =J70 -> 54 | L70: =K70 -> 54 | M70: =L70 -> 54
D71: Import of Wood Pellets - Step 4 | E71: =40.3 -> 40.3 | F71: =E71/3.6 -> 11.194444 | G71: 0 | H71: 0 | I71: 0 | J71: =1000*3.6/1000 -> 3.6 | K71: =10000*3.6/1000 -> 36 | L71: =K71 -> 36 | M71: =L71 -> 36
F72: Totoal (PJ) | G72: =SUM(G68:G71) -> 1.8 | H72: =SUM(H68:H71) -> 5.4 | I72: =SUM(I68:I71) -> 73.8 | J72: =SUM(J68:J71) -> 95.4 | K72: =SUM(K68:K71) -> 147.6 | L72: =SUM(L68:L71) -> 158.4 | M72: =SUM(M68:M71) -> 158.4
D73: Reference | E73: SEAI, 2022. Sustainable bioenergy for heat, National Heat study, Spatial Assessment of Resources and Evaluation of Costs and GHG Emissions

Sheet Domestic
B2: Domestic fossil fuels reserves | E2: ~FI_T: MEUR2000
B3: Region | C3: TechName | D3: TechDesc | E3: Comm-OUT | F3: CUM | G3: COST~2012 | H3: COST~2050 | I3: ACT_BND~2018 | J3: ACT_BND~2020 | K3: ACT_BND~2025 | L3: ACT_BND~2050 | M3: ACT_BND~0
B4: *Region Name | C4: *Technology Name | D4: Technology Description | F4: PJ | G4: Euro/GJ | H4: Euro/GJ | I4: PJ | J4: PJ | K4: PJ | L4: PJ
B5: =Processes!C42 -> IE,National | C5: =Processes!D42 -> MINGASNAT_S1 | D5: =Processes!E42 -> Domestic Potential of Natural Gas - Step 1 | E5: =Commodities!$C$21 -> GASNAT | F5: 742.128 | G5: 0.90792312 | H5: 1.1929101 | I5: ='EB2018'!AA2*Conversions!C2 -> 115.21735 | J5: =C31*Conversions!C2 -> 82.47996 | K5: =C32*Conversions!C2 -> 33.4944 | L5: =C33*Conversions!C2 -> 25.1208 | M5: 5
B6: =Processes!C43 -> IE,National | C6: =Processes!D43 -> MINGASNAT_S2 | D6: =Processes!E43 -> Domestic Potential of Natural Gas - Step 2 | E6: =Commodities!$C$21 -> GASNAT | F6: 88.74465 | G6: 1.8 | H6: 1.9434992 | I6: 0 | M6: 5
B7: =Processes!C44 -> IE,National | C7: =Processes!D44 -> MINPEAT_S1 | D7: =Processes!E44 -> Domestic Potential of Peat - Step 1 | E7: =Commodities!$C$10 -> PEAT | F7: 1960 | G7: 0.994 | H7: 1.2 | I7: ='EB2018'!H2*Conversions!C2 -> 34.161121 | J7: =I7 -> 34.161121 | K7: =J7 -> 34.161121 | L7: =MAX(I7:I7) -> 34.161121 | M7: 5
B8: =Processes!C45 -> IE,National | C8: =Processes!D45 -> MINPEAT_S2 | D8: =Processes!E45 -> Domestic Potential of Peat - Step 2 | E8: =Commodities!$C$10 -> PEAT | F8: 2400 | G8: 0.994 | H8: 1.2 | I8: 0 | M8: 5
B9: *Notes | F9: Old PET values (source: WEC) | I9: Calibrated against Energy Balance | J9: Energy Security Report | K9: Energy Security Report | L9: Assumption
B13: Renewable potentials | E13: ~FI_T
B14: Region | C14: TechName | D14: TechDesc | E14: Comm-OUT | F14: COST | G14: BNDACT~UP | H14: BNDACT~UP~2050
B15: *Region Name | C15: *Technology Name | D15: Technology Description | F15: Euro/GJ | G15: PJ | H15: PJ
B16: =Processes!C46 -> IE,National | C16: =Processes!D46 -> MINRENHYD | D16: =Processes!E46 -> Domestic Potential of Hydro | E16: =Commodities!C24 -> RENHYD
B17: =Processes!C47 -> IE,National | C17: =Processes!D47 -> MINRENWIN | D17: =Processes!E47 -> Domestic Potential of Wind | E17: =Commodities!C25 -> RENWIN
B18: =Processes!C48 -> IE,National | C18: =Processes!D48 -> MINRENSOL | D18: =Processes!E48 -> Domestic Potential of Solar | E18: =Commodities!C26 -> RENSOL
B19: =Processes!C49 -> IE,National | C19: =Processes!D49 -> MINMSWAS | D19: =Processes!E49 -> Domestic Potential of Municipal Solid Waste | E19: =Commodities!C27 -> MSWAS
B20: =Processes!C50 -> IE,National | C20: =Processes!D50 -> MINRENOCE | D20: =Processes!E50 -> Domestic Potential of Ocean | E20: =Commodities!C28 -> RENOCE
B21: =Processes!C51 -> IE,National | C21: =Processes!D51 -> MINRENAHT | D21: =Processes!E51 -> Domestic Potential of Ambient Heat | E21: =Commodities!C29 -> RENAHT
C22: =Processes!D82 -> MINCYC | D22: =Processes!E82 -> Domestic Potential of Cycling | E22: =Commodities!C51 -> CYC
C23: =Processes!D83 -> MINWLK | D23: =Processes!E83 -> Domestic Potential of Walking | E23: =Commodities!C52 -> WLK
B28: Projected indigenous natural gas production
B29: year | C29: ktoe
B30: 2019 | C30: 2500
B31: 2020 | C31: 1970
B32: 2025 | C32: 800
B33: 2027 | C33: 600
B34: Source: SEAI, ENERGY SECURITY IN IRELAND, 2020.
B35: https://www.seai.ie/publications/Energy-Security-in-Ireland-2020-.pdf

Sheet Domestic_Bio
B2: Domestic Bioenergy | E2: ~FI_T
B3: Region | C3: TechName | D3: TechDesc | E3: Comm-OUT | F3: COST~2012 | G3: *Notes
B4: \I:Region Name | C4: \I:Technology Name | D4: Technology Description | E4: Output Commodity | F4: €/GJ
B5: =Processes!C52 -> IE,National | C5: =Processes!D52 -> MINBIOWOO1_S1 | D5: =Processes!E52 -> Domestic Potential of Sawmill residues - Step 1 | E5: =Commodities!$C$39 -> BIOWOO1 | F5: 10 | G5: Crop-based feedstocks are modelled within the AGR BY Template. Potentials and costs controlled by scenario files.
B6: =Processes!C55 -> IE,National | C6: =Processes!D55 -> MINBIOWOO2_S1 | D6: =Processes!E55 -> Domestic Potential of Post-Consumer Recycled Wood - Step 1 | E6: =Commodities!$C$40 -> BIOWOO2 | F6: 10
B7: =Processes!C61 -> IE,National | C7: =Processes!D61 -> MINBIOMSW1_S1 | D7: =Processes!E61 -> Domestic Potential of Biodegradable Municipal Solid Waste potential - Solid - Step 1 | E7: =Commodities!$C$44 -> BIOMSW1 | F7: 10
B8: =Processes!C67 -> IE,National | C8: =Processes!D67 -> MINBIOTLW_S1 | D8: =Processes!E67 -> Domestic Potential of Tallow - Step 1 | E8: =Commodities!$C$46 -> BIOTLW | F8: 10
B9: =Processes!C70 -> IE,National | C9: =Processes!D70 -> MINBIORVO_S1 | D9: =Processes!E70 -> Domestic Potential of Recovered Vegetable Oil - Step 1 | E9: =Commodities!$C$47 -> BIORVO | F9: 10
B10: =Processes!C58 -> IE,National | C10: =Processes!D58 -> MINBIOWOO3_S1 | D10: =Processes!E58 -> Domestic Potential of Straw - Step 1 | E10: =Commodities!$C$41 -> BIOWOO3 | F10: 10
B11: =Processes!C73 -> IE,National | C11: =Processes!D73 -> MINBIOCATW_S1 | D11: =Processes!E73 -> Domestic Potential of Cattle Waste - Step 1 | E11: =Commodities!$C$48 -> BIOCATW | F11: 10
B12: =Processes!C76 -> IE,National | C12: =Processes!D76 -> MINBIOPIGW_S1 | D12: =Processes!E76 -> Domestic Potential of Pig Waste - Step 1 | E12: =Commodities!$C$49 -> BIOPIGW | F12: 10
B13: =Processes!C64 -> IE,National | C13: =Processes!D64 -> MINBIOMSW2_S1 | D13: =Processes!E64 -> Domestic Potential of Biodegradable Municipal Solid Waste - Step 1 | E13: =Commodities!$C$45&",BIOMUN" -> BIOMSW2,BIOMUN | F13: 10
B14: =Processes!C79 -> IE,National | C14: =Processes!D79 -> MINBIOINDF_S1 | D14: =Processes!E79 -> Domestic Potential of Industrial Food Waste - Step 1 | E14: =Commodities!$C$50 -> BIOINDF | F14: 10
B15: =Processes!C53 -> IE,National | C15: =Processes!D53 -> MINBIOWOO1_S2 | D15: =Processes!E53 -> Domestic Potential of Sawmill residues - Step 2 | E15: =Commodities!$C$39 -> BIOWOO1 | F15: 10
B16: =Processes!C56 -> IE,National | C16: =Processes!D56 -> MINBIOWOO2_S2 | D16: =Processes!E56 -> Domestic Potential of Post-Consumer Recycled Wood - Step 2 | E16: =Commodities!$C$40 -> BIOWOO2 | F16: 10
B17: =Processes!C62 -> IE,National | C17: =Processes!D62 -> MINBIOMSW1_S2 | D17: =Processes!E62 -> Domestic Potential of Biodegradable Municipal Solid Waste potential - Solid - Step 2 | E17: =Commodities!$C$44 -> BIOMSW1 | F17: 10
B18: =Processes!C68 -> IE,National | C18: =Processes!D68 -> MINBIOTLW_S2 | D18: =Processes!E68 -> Domestic Potential of Tallow - Step 2 | E18: =Commodities!$C$46 -> BIOTLW | F18: 10
B19: =Processes!C71 -> IE,National | C19: =Processes!D71 -> MINBIORVO_S2 | D19: =Processes!E71 -> Domestic Potential of Recovered Vegetable Oil - Step 2 | E19: =Commodities!$C$47 -> BIORVO | F19: 10
B20: =Processes!C59 -> IE,National | C20: =Processes!D59 -> MINBIOWOO3_S2 | D20: =Processes!E59 -> Domestic Potential of Straw - Step 2 | E20: =Commodities!$C$41 -> BIOWOO3 | F20: 10
B21: =Processes!C74 -> IE,National | C21: =Processes!D74 -> MINBIOCATW_S2 | D21: =Processes!E74 -> Domestic Potential of Cattle Waste - Step 2 | E21: =Commodities!$C$48 -> BIOCATW | F21: 10
B22: =Processes!C77 -> IE,National | C22: =Processes!D77 -> MINBIOPIGW_S2 | D22: =Processes!E77 -> Domestic Potential of Pig Waste - Step 2 | E22: =Commodities!$C$49 -> BIOPIGW | F22: 10
B23: =Processes!C65 -> IE,National | C23: =Processes!D65 -> MINBIOMSW2_S2 | D23: =Processes!E65 -> Domestic Potential of Biodegradable Municipal Solid Waste - Step 2 | E23: =Commodities!$C$45&",BIOMUN" -> BIOMSW2,BIOMUN | F23: 10
B24: =Processes!C80 -> IE,National | C24: =Processes!D80 -> MINBIOINDF_S2 | D24: =Processes!E80 -> Domestic Potential of Industrial Food Waste - Step 2 | E24: =Commodities!$C$50 -> BIOINDF | F24: 10
B25: =Processes!C54 -> IE,National | C25: =Processes!D54 -> MINBIOWOO1_S3 | D25: =Processes!E54 -> Domestic Potential of Sawmill residues - Step 3 | E25: =Commodities!$C$39 -> BIOWOO1 | F25: 10
B26: =Processes!C57 -> IE,National | C26: =Processes!D57 -> MINBIOWOO2_S3 | D26: =Processes!E57 -> Domestic Potential of Post-Consumer Recycled Wood - Step 3 | E26: =Commodities!$C$40 -> BIOWOO2 | F26: 10
B27: =Processes!C63 -> IE,National | C27: =Processes!D63 -> MINBIOMSW1_S3 | D27: =Processes!E63 -> Domestic Potential of Biodegradable Municipal Solid Waste potential - Solid - Step 3 | E27: =Commodities!$C$44 -> BIOMSW1 | F27: 10
B28: =Processes!C69 -> IE,National | C28: =Processes!D69 -> MINBIOTLW_S3 | D28: =Processes!E69 -> Domestic Potential of Tallow - Step 3 | E28: =Commodities!$C$46 -> BIOTLW | F28: 10
B29: =Processes!C72 -> IE,National | C29: =Processes!D72 -> MINBIORVO_S3 | D29: =Processes!E72 -> Domestic Potential of Recovered Vegetable Oil - Step 3 | E29: =Commodities!$C$47 -> BIORVO | F29: 10
B30: =Processes!C60 -> IE,National | C30: =Processes!D60 -> MINBIOWOO3_S3 | D30: =Processes!E60 -> Domestic Potential of Straw - Step 3 | E30: =Commodities!$C$41 -> BIOWOO3 | F30: 10
B31: =Processes!C75 -> IE,National | C31: =Processes!D75 -> MINBIOCATW_S3 | D31: =Processes!E75 -> Domestic Potential of Cattle Waste - Step 3 | E31: =Commodities!$C$48 -> BIOCATW | F31: 10
B32: =Processes!C78 -> IE,National | C32: =Processes!D78 -> MINBIOPIGW_S3 | D32: =Processes!E78 -> Domestic Potential of Pig Waste - Step 3 | E32: =Commodities!$C$49 -> BIOPIGW | F32: 10
B33: =Processes!C66 -> IE,National | C33: =Processes!D66 -> MINBIOMSW2_S3 | D33: =Processes!E66 -> Domestic Potential of Biodegradable Municipal Solid Waste - Step 3 | E33: =Commodities!$C$45&",BIOMUN" -> BIOMSW2,BIOMUN | F33: 10
B34: =Processes!C81 -> IE,National | C34: =Processes!D81 -> MINBIOINDF_S3 | D34: =Processes!E81 -> Domestic Potential of Industrial Food Waste - Step 3 | E34: =Commodities!$C$50 -> BIOINDF | F34: 10

Sheet Refinery
B2: Base-year Flexible Refinery | F2: ~FI_T: MEUR2000
B3: Region | C3: TechName | D3: TechDesc | E3: Comm-IN | F3: Comm-OUT | G3: Share~UP~2018 | H3: Share~UP~2050 | I3: Share~UP~0 | J3: EFF~2018 | K3: ACT_BND~2018 | L3: ACT_BND~2050 | M3: ACT_BND~0 | N3: Life | O3: FIXOM | P3: FLO_COST~2012 | Q3: *Notes
B4: \I: Unit | G4: Net production shares | N4: Years | O4: Euro/kW | P4: Euro/GJ
B5: =Processes!C86 -> IE,National | C5: =Processes!D86 -> SREFOILCRD_Whitegate | D5: =Processes!E86 -> Refinery of Crude Oil - Whitegate | E5: =Commodities!C11 -> OILCRD | J5: =(SUM('EB2018'!O20:Z20)-SUM('EB2018'!O25:Z25))/'EB2018'!M14 -> 0.99233426 | K5: =('EB2018'!L14)*Conversions!$C$2 -> 131.08837 | L5: =MAX(K5:K5) -> 131.08837 | M5: 5 | N5: 50 | Q5: Used BY costs from Irish TIMES 1.0
F6: =Commodities!C12 -> OILRFG | G6: =ROUNDUP(E24*$D$22,4) -> 0 | H6: =MAX(G6)*1.1 -> 0 | I6: 5 | Q6: Refinery Gas
F7: OILGSL | G7: =ROUNDUP(E25*$D$22,4) -> 0.2084 | H7: =MAX(G7)*1.1 -> 0.22924 | I7: 5 | P7: 1.7 | Q7: Gasoline
F8: =Commodities!C13 -> OILKER | G8: =ROUNDUP(E26*$D$22,4) -> 0.0738 | H8: =MAX(G8)*1.1 -> 0.08118 | I8: 5 | P8: 1.7 | Q8: Kerosene
C9: * | F9: * | G9: =ROUNDUP(E27*$D$22,4) -> 0 | I9: 5 | Q9: Jet Kerosene
F10: =Commodities!C14 -> OILHFO | G10: =ROUNDUP(E28*$D$22,4) -> 0.3127 | H10: =MAX(G10)*1.1 -> 0.34397 | I10: 5 | P10: 0.83603571 | Q10: Fueloil
F11: =Commodities!C16 -> OILLPG | G11: =ROUNDUP(E29*$D$22,4) -> 0.0211 | I11: 5 | P11: 1.3357143 | Q11: LPG
F12: =Commodities!C15 -> OILDST | G12: =ROUNDUP(E30*$D$22,4) -> 0.3722 | H12: =MAX(G12)*1.1 -> 0.40942 | I12: 5 | P12: 1.5785714 | Q12: Gasoil / Diesel /DERV
F13: =Commodities!C18 -> OILCOK | G13: =ROUNDUP(E31*$D$22,4) -> 0 | I13: 5 | Q13: Petroleum Coke
F14: =Commodities!C19 -> OILNAP | G14: =ROUNDUP(E32*$D$22,4) -> 0.012 | I14: 5 | P14: 1.2142857 | Q14: Naphta
C15: * | F15: * | G15: =ROUNDUP(E33*$D$22,4) -> 0 | I15: 5 | Q15: Bitumen
C16: * | F16: * | G16: =ROUNDUP(E34*$D$22,4) -> 0 | I16: 5 | Q16: White Spirit
C17: * | F17: * | G17: =ROUNDUP(E35*$D$22,4) -> 0 | I17: 5 | Q17: Lubricants
C22: correction: | D22: =1/SUM(E24:E35) -> 0.99828981
C24: =Commodities!C12 -> OILRFG | D24: =('EB2018'!O$20-'EB2018'!O$25)/(SUM('EB2018'!$O$20:$Z$20)-SUM('EB2018'!$O$25:$Z$25)) -> -0.0017131191 | E24: =IF(D24<0,0,D24) -> 0
C25: OILGSL | D25: =('EB2018'!P$20-'EB2018'!P$25)/(SUM('EB2018'!$O$20:$Z$20)-SUM('EB2018'!$O$25:$Z$25)) -> 0.20874582 | E25: =IF(D25<0,0,D25) -> 0.20874582
C26: =Commodities!C13 -> OILKER | D26: =('EB2018'!Q$20-'EB2018'!Q$25)/(SUM('EB2018'!$O$20:$Z$20)-SUM('EB2018'!$O$25:$Z$25)) -> 0.073904025 | E26: =IF(D26<0,0,D26) -> 0.073904025
C27: * | D27: =('EB2018'!R$20-'EB2018'!R$25)/(SUM('EB2018'!$O$20:$Z$20)-SUM('EB2018'!$O$25:$Z$25)) -> 0 | E27: =IF(D27<0,0,D27) -> 0
C28: =Commodities!C14 -> OILHFO | D28: =('EB2018'!S$20-'EB2018'!S$25)/(SUM('EB2018'!$O$20:$Z$20)-SUM('EB2018'!$O$25:$Z$25)) -> 0.31316598 | E28: =IF(D28<0,0,D28) -> 0.31316598
C29: =Commodities!C16 -> OILLPG | D29: =('EB2018'!T$20-'EB2018'!T$25)/(SUM('EB2018'!$O$20:$Z$20)-SUM('EB2018'!$O$25:$Z$25)) -> 0.021115616 | E29: =IF(D29<0,0,D29) -> 0.021115616
C30: =Commodities!C15 -> OILDST | D30: =('EB2018'!U$20-'EB2018'!U$25)/(SUM('EB2018'!$O$20:$Z$20)-SUM('EB2018'!$O$25:$Z$25)) -> 0.37280233 | E30: =IF(D30<0,0,D30) -> 0.37280233
C31: =Commodities!C18 -> OILCOK | D31: =('EB2018'!V$20-'EB2018'!V$25)/(SUM('EB2018'!$O$20:$Z$20)-SUM('EB2018'!$O$25:$Z$25)) -> 0 | E31: =IF(D31<0,0,D31) -> 0
C32: =Commodities!C19 -> OILNAP | D32: =('EB2018'!W$20-'EB2018'!W$25)/(SUM('EB2018'!$O$20:$Z$20)-SUM('EB2018'!$O$25:$Z$25)) -> 0.011979348 | E32: =IF(D32<0,0,D32) -> 0.011979348
C33: * | D33: =('EB2018'!X$20-'EB2018'!X$25)/(SUM('EB2018'!$O$20:$Z$20)-SUM('EB2018'!$O$25:$Z$25)) -> 0 | E33: =IF(D33<0,0,D33) -> 0
C34: * | D34: =('EB2018'!Y$20-'EB2018'!Y$25)/(SUM('EB2018'!$O$20:$Z$20)-SUM('EB2018'!$O$25:$Z$25)) -> 0 | E34: =IF(D34<0,0,D34) -> 0
C35: * | D35: =('EB2018'!Z$20-'EB2018'!Z$25)/(SUM('EB2018'!$O$20:$Z$20)-SUM('EB2018'!$O$25:$Z$25)) -> 0 | E35: =IF(D35<0,0,D35) -> 0

Sheet Interconnector
B2: Electricity Interconnector | G2: ~FI_T: MEUR2014
B3: Region | C3: TechName | D3: TechDesc | E3: Comm-IN | F3: Comm-OUT | G3: Year | H3: NCAP_PASTI | I3: NCAP_TLIFE | J3: PRC_CAPACT | K3: COST~2015 | L3: COST~2020 | M3: COST~2030 | N3: COST~2040 | O3: COST~2050 | P3: NCAP_BND | Q3: NCAP_BND~0
B4: *Region Name | C4: *Technology Name | D4: Technology Description | K4: Euro/GJ | L4: Euro/GJ | M4: Euro/GJ | N4: Euro/GJ | O4: Euro/GJ
B5: =Processes!C84 -> IE,National | C5: =Processes!D84 -> IMPELC_UK-EWIC | D5: =Processes!E84 -> Import of Electricity - UK East-West Interconnector | F5: =Commodities!C58 -> ELCC | G5: 2013 | H5: 0.5 | I5: 100 | J5: =8760*3.6/1000 -> 31.536 | K5: =G22 -> 12.775231 | L5: =H22 -> 13.844655 | M5: =I22 -> 20.699647 | N5: =J22 -> 24.100187 | O5: =K22 -> 27.970361 | P5: 0 | Q5: 2
B6: =Processes!C85 -> IE,National | C6: =Processes!D85 -> EXPELC_UK-EWIC | D6: =Processes!E85 -> Export of Electricity - UK East-West Interconnector | E6: =Commodities!C58 -> ELCC | G6: 2013 | H6: 0.5 | I6: 100 | J6: =8760*3.6/1000 -> 31.536 | K6: =K5*0.7 -> 8.942662 | L6: =L5*0.7 -> 9.6912586 | M6: =M5*0.7 -> 14.489753 | N6: =N5*0.7 -> 16.870131 | O6: =O5*0.7 -> 19.579253 | P6: 0 | Q6: 2
B7: *Notes | G7: Based on a Dummy Gas generator in UK and WEO2016 Gas prices | L7: Calibrated against SEAI Energy Balance | N7: Own Assumption
M11: =H5*8760*3.6 -> 15768
E12: PLEXOS | G12: TIMES
E13: Dummy Gas Generator | G13: 2015 | H13: 2020 | I13: 2030 | J13: 2040 | K13: 2050
C14: Generator CAP [MW] | E14: 1800
C15: EFF | E15: 0.475 | G15: =G19/$E$15 -> 59.752421 | H15: =H19/$E$15 -> 59.752421 | I15: 60 | J15: 60 | K15: =K19/$E$15 -> 59.752421 | M15: PJ | N15: "Fuel Consumption"
C17: Gas Price [Euro/GJ] | G17: =Imports_Fossil!I7 -> 5.6724016 | H17: =Imports_Fossil!J7 -> 6.1803779 | I17: =Imports_Fossil!K7 -> 9.3975609 | J17: =Imports_Fossil!L7 -> 11.006152 | K17: =Imports_Fossil!M7 -> 12.890088 | M17: =Imports_Fossil!N7 -> WEO2019, WEO2020
G18: =G17*G15/G19 -> 11.941898 | H18: =H17*H15/H19 -> 13.011322 | I18: =I17*I15/I19 -> 19.866313 | J18: =J17*J15/J19 -> 23.266853 | K18: =K17*K15/K19 -> 27.137028 | M18: Meuro/PJo
C19: Interconnector CAP [MW] | E19: 900 | G19: =$E$19*8760*3.6*10^-6 -> 28.3824 | H19: =$E$19*8760*3.6*10^-6 -> 28.3824 | I19: =$E$19*8760*3.6*10^-6 -> 28.3824 | J19: =$E$19*8760*3.6*10^-6 -> 28.3824 | K19: =$E$19*8760*3.6*10^-6 -> 28.3824 | M19: PJ | N19: "Max Output"
C20: Charge for power sent over (or back) [Euro/MWh] | E20: 3 | G20: =$E$20/3.6 -> 0.83333333 | H20: =$E$20/3.6 -> 0.83333333 | I20: =$E$20/3.6 -> 0.83333333 | J20: =$E$20/3.6 -> 0.83333333 | K20: =$E$20/3.6 -> 0.83333333 | M20: [Euro/GJo] | N20: Cost in output
G22: =G18+G20 -> 12.775231 | H22: =H18+H20 -> 13.844655 | I22: =I18+I20 -> 20.699647 | J22: =J18+J20 -> 24.100187 | K22: =K18+K20 -> 27.970361 | M22: Meuro/Pjo | N22: TIMES Cost in output | P22: o=output

Sheet Emi
A1: Emission - Dynamic coefficients
B4: ~COMEMI
B5: CommName | C5: =Commodities!C54 -> SUPNGA | D5: =Commodities!C53 -> SUPCOA | E5: =Commodities!C57 -> SUPWAS | F5: *Unit
B6: =Commodities!C69 -> SUPCO2N | C6: 56.1 | D6: 96.1 | E6: 75.3 | F6: kt/PJ
B7: =Commodities!C65 -> SUPCH4N
B8: =Commodities!C68 -> SUPSO2N
B9: =Commodities!C72 -> SUPNOXN
B10: =Commodities!C73 -> SUPPM10
B11: =Commodities!C74 -> SUPPM25
B16: ~COMAGG_R1C2 | F16: ~COMAGG_R1C2
B17: CommName | C17: TOTCO2 | F17: CommName | G17: TOTCO2INT
B18: AGRCO2N | C18: 1 | F18: TRACO2INT | G18: 1
B19: INDCO2N | C19: 1 | F19: TOTCO2 | G19: 1
B20: INDCO2P | C20: 1
B21: PWRCO2N | C21: 1
B22: RSDCO2 | C22: 1
B23: SRVCO2N | C23: 1
B24: TRACO2N | C24: 1
B25: SUPCO2N | C25: 1

Sheet SEAI-AEA_BioData
A1: Source: | B1: SEAI-AEA, Bioenergy Supply Curves for Ireland 2010 – 2030. October 2012, version 1.0 | J1: Conversion | P1: Consumer Price Index (CPI) - CSO
J2: 1 toe | K2: 41.868 | L2: GJ | P2: Base=100 | Q2: 2010
A3: Appendix 3 Potential Imports of Bioenergy | J3: 1 ktoe | K3: 0.041868 | L3: PJ | P3: 36861 | Q3: 127.61665
A4: The following tables refer to potential import scenarios for bioenergy to Ireland, as described in Section11. | P4: Source: http://www.cso.ie/px/pxeirestat/Statire/SelectVarVal/Define.asp?maintable=CPA04&PLanguage=0
A5: Table A. 3: Restricted supply/reference demand | I5: €2010
B6: Unit | C6: 2010 | D6: 2015 | E6: 2020 | F6: 2025 | G6: 2030 | I6: Unit | J6: 2010 | K6: 2015 | L6: 2020 | M6: 2025 | N6: 2030 | P6: Table A. 3: Restricted supply/reference demand
A7: Wood chips | B7: toe | C7: 9358 | D7: 0 | E7: 24163 | F7: 139233 | G7: 470124 | I7: PJ | J7: =C7*$K$3/1000 -> 0.39180074 | K7: =D7*$K$3/1000 -> 0 | L7: =E7*$K$3/1000 -> 1.0116565 | M7: =F7*$K$3/1000 -> 5.8294072 | N7: =G7*$K$3/1000 -> 19.683152 | P7: Table A. 4: Medium supply/reference demand
A8: Wood chips | B8: €/toe | C8: 288 | D8: 162 | E8: 126 | F8: 106 | G8: 98 | I8: €/GJ | J8: =C8/$K$2 -> 6.8787618 | K8: =D8/$K$2 -> 3.8693035 | L8: =E8/$K$2 -> 3.0094583 | M8: =F8/$K$2 -> 2.5317665 | N8: =G8/$K$2 -> 2.3406898 | P8: Table A. 5: Ambitious supply/reference demand
A9: Wood pellets | B9: toe | C9: 28075 | D9: 0 | E9: 72490 | F9: 417699 | G9: 1410371 | I9: PJ | J9: =C9*$K$3/1000 -> 1.1754441 | K9: =D9*$K$3/1000 -> 0 | L9: =E9*$K$3/1000 -> 3.0350113 | M9: =F9*$K$3/1000 -> 17.488222 | N9: =G9*$K$3/1000 -> 59.049413 | P9: Table A. 6: Medium supply/high demand
A10: Wood pellets | B10: €/toe | C10: 590 | D10: 385 | E10: 300 | F10: 251 | G10: 232 | I10: €/GJ | J10: =C10/$K$2 -> 14.091908 | K10: =D10/$K$2 -> 9.195567 | L10: =E10/$K$2 -> 7.1653769 | M10: =F10/$K$2 -> 5.995032 | N10: =G10/$K$2 -> 5.5412248 | P10: Table A. 7: Ambitious supply/high demand
A11: Bioethanol | B11: toe | C11: 535616 | D11: 310101 | E11: 6531 | F11: 43493 | G11: 130927 | I11: PJ | J11: =C11*$K$3/1000 -> 22.425171 | K11: =D11*$K$3/1000 -> 12.983309 | L11: =E11*$K$3/1000 -> 0.27343991 | M11: =F11*$K$3/1000 -> 1.8209649 | N11: =G11*$K$3/1000 -> 5.4816516
A12: Bioethanol | B12: €/toe | C12: 779 | D12: 740 | E12: 693 | F12: 630 | G12: 577 | I12: €/GJ | J12: =C12/$K$2 -> 18.606095 | K12: =D12/$K$2 -> 17.674596 | L12: =E12/$K$2 -> 16.552021 | M12: =F12/$K$2 -> 15.047291 | N12: =G12/$K$2 -> 13.781408
A13: Biodiesel | B13: toe | C13: 106129 | D13: 75725 | E13: 0 | F13: 0 | G13: 0 | I13: PJ | J13: =C13*$K$3/1000 -> 4.443409 | K13: =D13*$K$3/1000 -> 3.1704543 | L13: =E13*$K$3/1000 -> 0 | M13: =F13*$K$3/1000 -> 0 | N13: =G13*$K$3/1000 -> 0
A14: Biodiesel | B14: €/toe | C14: 1209 | D14: 1276 | E14: 1312 | F14: 1218 | G14: 1156 | I14: €/GJ | J14: =C14/$K$2 -> 28.876469 | K14: =D14/$K$2 -> 30.476736 | L14: =E14/$K$2 -> 31.336582 | M14: =F14/$K$2 -> 29.09143 | N14: =G14/$K$2 -> 27.610586
A16: Table A. 4: Medium supply/reference demand | I16: €2010 | P16: Index | V16: €2000
B17: Unit | C17: 2010 | D17: 2015 | E17: 2020 | F17: 2025 | G17: 2030 | I17: Unit | J17: 2010 | K17: 2015 | L17: 2020 | M17: 2025 | N17: 2030 | P17: 2010 | Q17: 2015 | R17: 2020 | S17: 2025 | T17: 2030 | V17: 2010 | W17: 2015 | X17: 2020 | Y17: 2025 | Z17: 2030
A18: Wood chips | B18: toe | C18: 7640 | D18: 7551 | E18: 141276 | F18: 452161 | G18: 1150679 | I18: PJ | J18: =C18*$K$3/1000 -> 0.31987152 | K18: =D18*$K$3/1000 -> 0.31614527 | L18: =E18*$K$3/1000 -> 5.9149436 | M18: =F18*$K$3/1000 -> 18.931077 | N18: =G18*$K$3/1000 -> 48.176628
A19: Wood chips | B19: €/toe | C19: 288 | D19: 218 | E19: 174 | F19: 149 | G19: 142 | I19: €/GJ | J19: =C19/$K$2 -> 6.8787618 | K19: =D19/$K$2 -> 5.2068405 | L19: =E19/$K$2 -> 4.1559186 | M19: =F19/$K$2 -> 3.5588039 | N19: =G19/$K$2 -> 3.3916117 | P19: =J19/$J19 -> 1 | Q19: =K19/$J19 -> 0.75694444 | R19: =L19/$J19 -> 0.60416667 | S19: =M19/$J19 -> 0.51736111 | T19: =N19/$J19 -> 0.49305556 | V19: =J19*100/$Q$3 -> 5.390176 | W19: =K19*100/$Q$3 -> 4.0800638 | X19: =L19*100/$Q$3 -> 3.2565647 | Y19: =M19*100/$Q$3 -> 2.7886675 | Z19: =N19*100/$Q$3 -> 2.6576562
A20: Wood pellets | B20: toe | C20: 22921 | D20: 22653 | E20: 423827 | F20: 1356482 | G20: 3452038 | I20: PJ | J20: =C20*$K$3/1000 -> 0.95965643 | K20: =D20*$K$3/1000 -> 0.9484358 | L20: =E20*$K$3/1000 -> 17.744789 | M20: =F20*$K$3/1000 -> 56.793188 | N20: =G20*$K$3/1000 -> 144.52993
A21: Wood pellets | B21: €/toe | C21: 590 | D21: 446 | E21: 356 | F21: 305 | G21: 291 | I21: €/GJ | J21: =C21/$K$2 -> 14.091908 | K21: =D21/$K$2 -> 10.652527 | L21: =E21/$K$2 -> 8.5029139 | M21: =F21/$K$2 -> 7.2847998 | N21: =G21/$K$2 -> 6.9504156 | P21: =J21/$J21 -> 1 | Q21: =K21/$J21 -> 0.7559322 | R21: =L21/$J21 -> 0.60338983 | S21: =M21/$J21 -> 0.51694915 | T21: =N21/$J21 -> 0.49322034 | V21: =J21*100/$Q$3 -> 11.042374 | W21: =K21*100/$Q$3 -> 8.3472865 | X21: =L21*100/$Q$3 -> 6.6628565 | Y21: =M21*100/$Q$3 -> 5.7083461 | Z21: =N21*100/$Q$3 -> 5.4463237
A22: Bioethanol | B22: toe | C22: 781304 | D22: 791507 | E22: 441100 | F22: 807242 | G22: 1351788 | I22: PJ | J22: =C22*$K$3/1000 -> 32.711636 | K22: =D22*$K$3/1000 -> 33.138815 | L22: =E22*$K$3/1000 -> 18.467975 | M22: =F22*$K$3/1000 -> 33.797608 | N22: =G22*$K$3/1000 -> 56.59666
A23: Bioethanol | B23: €/toe | C23: 779 | D23: 761 | E23: 736 | F23: 695 | G23: 665 | I23: €/GJ | J23: =C23/$K$2 -> 18.606095 | K23: =D23/$K$2 -> 18.176173 | L23: =E23/$K$2 -> 17.579058 | M23: =F23/$K$2 -> 16.59979 | N23: =G23/$K$2 -> 15.883252 | P23: =J23/$J23 -> 1 | Q23: =K23/$J23 -> 0.97689345 | R23: =L23/$J23 -> 0.94480103 | S23: =M23/$J23 -> 0.89216945 | T23: =N23/$J23 -> 0.85365854 | V23: =J23*100/$Q$3 -> 14.579677 | W23: =K23*100/$Q$3 -> 14.242791 | X23: =L23*100/$Q$3 -> 13.774894 | Y23: =M23*100/$Q$3 -> 13.007543 | Z23: =N23*100/$Q$3 -> 12.446066
A24: Biodiesel | B24: toe | C24: 101544 | D24: 112421 | E24: 0 | F24: 0 | G24: 92339 | I24: PJ | J24: =C24*$K$3/1000 -> 4.2514442 | K24: =D24*$K$3/1000 -> 4.7068424 | L24: =E24*$K$3/1000 -> 0 | M24: =F24*$K$3/1000 -> 0 | N24: =G24*$K$3/1000 -> 3.8660493
A25: Biodiesel | B25: €/toe | C25: 1209 | D25: 1313 | E25: 1389 | F25: 1334 | G25: 1312 | I25: €/GJ | J25: =C25/$K$2 -> 28.876469 | K25: =D25/$K$2 -> 31.360466 | L25: =E25/$K$2 -> 33.175695 | M25: =F25/$K$2 -> 31.862043 | N25: =G25/$K$2 -> 31.336582 | P25: =J25/$J25 -> 1 | Q25: =K25/$J25 -> 1.0860215 | R25: =L25/$J25 -> 1.1488834 | S25: =M25/$J25 -> 1.1033912 | T25: =N25/$J25 -> 1.0851944 | V25: =J25*100/$Q$3 -> 22.62751 | W25: =K25*100/$Q$3 -> 24.573962 | X25: =L25*100/$Q$3 -> 25.99637 | Y25: =M25*100/$Q$3 -> 24.966996 | Z25: =N25*100/$Q$3 -> 24.555246
A26: Table A. 5: Ambitious supply/reference demand | I26: €2010 | P26: Index
B27: Unit | C27: 2010 | D27: 2015 | E27: 2020 | F27: 2025 | G27: 2030 | I27: Unit | J27: 2010 | K27: 2015 | L27: 2020 | M27: 2025 | N27: 2030 | P27: 2010 | Q27: 2015 | R27: 2020 | S27: 2025 | T27: 2030 | V27: 2010 | W27: 2015 | X27: 2020 | Y27: 2025 | Z27: 2030
A28: Wood chips | B28: toe | C28: 6382 | D28: 29323 | E28: 214410 | F28: 666226 | G28: 1885232 | I28: PJ | J28: =C28*$K$3/1000 -> 0.26720158 | K28: =D28*$K$3/1000 -> 1.2276954 | L28: =E28*$K$3/1000 -> 8.9769179 | M28: =F28*$K$3/1000 -> 27.89355 | N28: =G28*$K$3/1000 -> 78.930893
A29: Wood chips | B29: €/toe | C29: 288 | D29: 257 | E29: 211 | F29: 187 | G29: 183 | I29: €/GJ | J29: =C29/$K$2 -> 6.8787618 | K29: =D29/$K$2 -> 6.1383395 | L29: =E29/$K$2 -> 5.0396484 | M29: =F29/$K$2 -> 4.4664183 | N29: =G29/$K$2 -> 4.3708799 | P29: =J29/$J29 -> 1 | Q29: =K29/$J29 -> 0.89236111 | R29: =L29/$J29 -> 0.73263889 | S29: =M29/$J29 -> 0.64930556 | T29: =N29/$J29 -> 0.63541667 | V29: =J29*100/$Q$3 -> 5.390176 | W29: =K29*100/$Q$3 -> 4.8099835 | X29: =L29*100/$Q$3 -> 3.9490526 | Y29: =M29*100/$Q$3 -> 3.4998712 | Z29: =N29*100/$Q$3 -> 3.4250077
A30: Wood pellets | B30: toe | C30: 191,47 | D30: 87968 | E30: 643231 | F30: 1998677 | G30: 5655695 | I30: PJ | J30: =C30*$K$3/1000 -> #VALUE! | K30: =D30*$K$3/1000 -> 3.6830442 | L30: =E30*$K$3/1000 -> 26.930796 | M30: =F30*$K$3/1000 -> 83.680609 | N30: =G30*$K$3/1000 -> 236.79264
A31: Wood pellets | B31: €/toe | C31: 590 | D31: 514 | E31: 423 | F31: 374 | G31: 367 | I31: €/GJ | J31: =C31/$K$2 -> 14.091908 | K31: =D31/$K$2 -> 12.276679 | L31: =E31/$K$2 -> 10.103181 | M31: =F31/$K$2 -> 8.9328365 | N31: =G31/$K$2 -> 8.7656444 | P31: =J31/$J31 -> 1 | Q31: =K31/$J31 -> 0.87118644 | R31: =L31/$J31 -> 0.71694915 | S31: =M31/$J31 -> 0.63389831 | T31: =N31/$J31 -> 0.6220339 | V31: =J31*100/$Q$3 -> 11.042374 | W31: =K31*100/$Q$3 -> 9.6199669 | X31: =L31*100/$Q$3 -> 7.916821 | Y31: =M31*100/$Q$3 -> 6.9997425 | Z31: =N31*100/$Q$3 -> 6.8687312
A32: Bioethanol | B32: toe | C32: 779549 | D32: 795568 | E32: 452796 | F32: 823157 | G32: 1376225 | I32: PJ | J32: =C32*$K$3/1000 -> 32.638158 | K32: =D32*$K$3/1000 -> 33.308841 | L32: =E32*$K$3/1000 -> 18.957663 | M32: =F32*$K$3/1000 -> 34.463937 | N32: =G32*$K$3/1000 -> 57.619788
A33: Bioethanol | B33: €/toe | C33: 779 | D33: 792 | E33: 799 | F33: 792 | G33: 801 | I33: €/GJ | J33: =C33/$K$2 -> 18.606095 | K33: =D33/$K$2 -> 18.916595 | L33: =E33/$K$2 -> 19.083787 | M33: =F33/$K$2 -> 18.916595 | N33: =G33/$K$2 -> 19.131556 | P33: =J33/$J33 -> 1 | Q33: =K33/$J33 -> 1.0166881 | R33: =L33/$J33 -> 1.0256739 | S33: =M33/$J33 -> 1.0166881 | T33: =N33/$J33 -> 1.0282413 | V33: =J33*100/$Q$3 -> 14.579677 | W33: =K33*100/$Q$3 -> 14.822984 | X33: =L33*100/$Q$3 -> 14.953995 | Y33: =M33*100/$Q$3 -> 14.822984 | Z33: =N33*100/$Q$3 -> 14.991427
A34: Biodiesel | B34: toe | C34: 101448 | D34: 117598 | E34: 0 | F34: 0 | G34: 104602 | I34: PJ | J34: =C34*$K$3/1000 -> 4.2474249 | K34: =D34*$K$3/1000 -> 4.9235931 | L34: =E34*$K$3/1000 -> 0 | M34: =F34*$K$3/1000 -> 0 | N34: =G34*$K$3/1000 -> 4.3794765
A35: Biodiesel | B35: €/toe | C35: 1209 | D35: 1367 | E35: 1500 | F35: 1506 | G35: 1550 | I35: €/GJ | J35: =C35/$K$2 -> 28.876469 | K35: =D35/$K$2 -> 32.650234 | L35: =E35/$K$2 -> 35.826884 | M35: =F35/$K$2 -> 35.970192 | N35: =G35/$K$2 -> 37.021114 | P35: =J35/$J35 -> 1 | Q35: =K35/$J35 -> 1.1306865 | R35: =L35/$J35 -> 1.2406948 | S35: =M35/$J35 -> 1.2456576 | T35: =N35/$J35 -> 1.2820513 | V35: =J35*100/$Q$3 -> 22.62751 | W35: =K35*100/$Q$3 -> 25.58462 | X35: =L35*100/$Q$3 -> 28.073833 | Y35: =M35*100/$Q$3 -> 28.186129 | Z35: =N35*100/$Q$3 -> 29.009628
A37: Table A. 6: Medium supply/high demand | I37: €2010 | P37: Index | V37: €2000
B38: Unit | C38: 2010 | D38: 2015 | E38: 2020 | F38: 2025 | G38: 2030 | I38: Unit | J38: 2010 | K38: 2015 | L38: 2020 | M38: 2025 | N38: 2030 | P38: 2010 | Q38: 2015 | R38: 2020 | S38: 2025 | T38: 2030 | V38: 2010 | W38: 2015 | X38: 2020 | Y38: 2025 | Z38: 2030
A39: Wood chips | B39: toe | C39: 7640 | D39: 0 | E39: 0 | F39: 0 | G39: 142382 | I39: PJ | J39: =C39*$K$3/1000 -> 0.31987152 | K39: =D39*$K$3/1000 -> 0 | L39: =E39*$K$3/1000 -> 0 | M39: =F39*$K$3/1000 -> 0 | N39: =G39*$K$3/1000 -> 5.9612496
A40: Wood chips | B40: €/toe | C40: 288 | D40: 226 | E40: 185 | F40: 165 | G40: 162 | I40: €/GJ | J40: =C40/$K$2 -> 6.8787618 | K40: =D40/$K$2 -> 5.3979173 | L40: =E40/$K$2 -> 4.4186491 | M40: =F40/$K$2 -> 3.9409573 | N40: =G40/$K$2 -> 3.8693035 | P40: =J40/$J40 -> 1 | Q40: =K40/$J40 -> 0.78472222 | R40: =L40/$J40 -> 0.64236111 | S40: =M40/$J40 -> 0.57291667 | T40: =N40/$J40 -> 0.5625 | V40: =J40*100/$Q$3 -> 5.390176 | W40: =K40*100/$Q$3 -> 4.2297909 | X40: =L40*100/$Q$3 -> 3.4624395 | Y40: =M40*100/$Q$3 -> 3.0881217 | Z40: =N40*100/$Q$3 -> 3.031974
A41: Wood pellets | B41: toe | C41: 22921 | D41: 0 | E41: 0 | F41: 0 | G41: 427146 | I41: PJ | J41: =C41*$K$3/1000 -> 0.95965643 | K41: =D41*$K$3/1000 -> 0 | L41: =E41*$K$3/1000 -> 0 | M41: =F41*$K$3/1000 -> 0 | N41: =G41*$K$3/1000 -> 17.883749
A42: Wood pellets | B42: €/toe | C42: 590 | D42: 462 | E42: 379 | F42: 338 | G42: 331 | I42: €/GJ | J42: =C42/$K$2 -> 14.091908 | K42: =D42/$K$2 -> 11.03468 | L42: =E42/$K$2 -> 9.0522595 | M42: =F42/$K$2 -> 8.0729913 | N42: =G42/$K$2 -> 7.9057992 | P42: =J42/$J42 -> 1 | Q42: =K42/$J42 -> 0.78305085 | R42: =L42/$J42 -> 0.64237288 | S42: =M42/$J42 -> 0.57288136 | T42: =N42/$J42 -> 0.56101695 | V42: =J42*100/$Q$3 -> 11.042374 | W42: =K42*100/$Q$3 -> 8.6467407 | X42: =L42*100/$Q$3 -> 7.0933219 | Y42: =M42*100/$Q$3 -> 6.3259705 | Z42: =N42*100/$Q$3 -> 6.1949592
A43: Bioethanol | B43: toe | C43: 781304 | D43: 788018 | E43: 409398 | F43: 734123 | G43: 1404121 | I43: PJ | J43: =C43*$K$3/1000 -> 32.711636 | K43: =D43*$K$3/1000 -> 32.992738 | L43: =E43*$K$3/1000 -> 17.140675 | M43: =F43*$K$3/1000 -> 30.736262 | N43: =G43*$K$3/1000 -> 58.787738
A44: Bioethanol | B44: €/toe | C44: 779 | D44: 824 | E44: 866 | F44: 911 | G44: 986 | I44: €/GJ | J44: =C44/$K$2 -> 18.606095 | K44: =D44/$K$2 -> 19.680902 | L44: =E44/$K$2 -> 20.684055 | M44: =F44/$K$2 -> 21.758861 | N44: =G44/$K$2 -> 23.550205 | P44: =J44/$J44 -> 1 | Q44: =K44/$J44 -> 1.0577664 | R44: =L44/$J44 -> 1.1116816 | S44: =M44/$J44 -> 1.169448 | T44: =N44/$J44 -> 1.2657253 | V44: =J44*100/$Q$3 -> 14.579677 | W44: =K44*100/$Q$3 -> 15.421892 | X44: =L44*100/$Q$3 -> 16.20796 | Y44: =M44*100/$Q$3 -> 17.050175 | Z44: =N44*100/$Q$3 -> 18.453866
A45: Biodiesel | B45: toe | C45: 101544 | D45: 112987 | E45: 0 | F45: 0 | G45: 109936 | I45: PJ | J45: =C45*$K$3/1000 -> 4.2514442 | K45: =D45*$K$3/1000 -> 4.7305397 | L45: =E45*$K$3/1000 -> 0 | M45: =F45*$K$3/1000 -> 0 | N45: =G45*$K$3/1000 -> 4.6028004
A46: Biodiesel | B46: €/toe | C46: 1209 | D46: 1420 | E46: 1605 | F46: 1694 | G46: 1832 | I46: €/GJ | J46: =C46/$K$2 -> 28.876469 | K46: =D46/$K$2 -> 33.916117 | L46: =E46/$K$2 -> 38.334766 | M46: =F46/$K$2 -> 40.460495 | N46: =G46/$K$2 -> 43.756568 | P46: =J46/$J46 -> 1 | Q46: =K46/$J46 -> 1.1745244 | R46: =L46/$J46 -> 1.3275434 | S46: =M46/$J46 -> 1.401158 | T46: =N46/$J46 -> 1.5153019 | V46: =J46*100/$Q$3 -> 22.62751 | W46: =K46*100/$Q$3 -> 26.576562 | X46: =L46*100/$Q$3 -> 30.039002 | Y46: =M46*100/$Q$3 -> 31.704716 | Z46: =N46*100/$Q$3 -> 34.287509
A48: Table A. 7: Ambitious supply/high demand | I48: €2010 | P48: Index | V48: €2000
B49: Unit | C49: 2010 | D49: 2015 | E49: 2020 | F49: 2025 | G49: 2030 | I49: Unit | J49: 2010 | K49: 2015 | L49: 2020 | M49: 2025 | N49: 2030 | P49: 2010 | Q49: 2015 | R49: 2020 | S49: 2025 | T49: 2030 | V49: 2010 | W49: 2015 | X49: 2020 | Y49: 2025 | Z49: 2030
A50: Wood chips | B50: toe | C50: 6382 | D50: 0 | E50: 69709 | F50: 192223 | G50: 876934 | I50: PJ | J50: =C50*$K$3/1000 -> 0.26720158 | K50: =AVERAGE(J50,L50) -> 1.592889 | L50: =E50*$K$3/1000 -> 2.9185764 | M50: =F50*$K$3/1000 -> 8.0479926 | N50: =G50*$K$3/1000 -> 36.715473
A51: Wood chips | B51: €/toe | C51: 288 | D51: 267 | E51: 226 | F51: 209 | G51: 211 | I51: €/GJ | J51: =C51/$K$2 -> 6.8787618 | K51: =D51/$K$2 -> 6.3771854 | L51: =E51/$K$2 -> 5.3979173 | M51: =F51/$K$2 -> 4.9918792 | N51: =G51/$K$2 -> 5.0396484 | P51: =J51/$J51 -> 1 | Q51: =K51/$J51 -> 0.92708333 | R51: =L51/$J51 -> 0.78472222 | S51: =M51/$J51 -> 0.72569444 | T51: =N51/$J51 -> 0.73263889 | V51: =J51*100/$Q$3 -> 5.390176 | W51: =K51*100/$Q$3 -> 4.9971423 | X51: =L51*100/$Q$3 -> 4.2297909 | Y51: =M51*100/$Q$3 -> 3.9116208 | Z51: =N51*100/$Q$3 -> 3.9490526
A52: Wood pellets | B52: toe | C52: 191470 | D52: 0 | E52: 209128 | F52: 576669 | G52: 2630803 | I52: PJ | J52: =C52*$K$3/1000 -> 8.016466 | K52: =AVERAGE(J52,L52) -> 8.3861185 | L52: =E52*$K$3/1000 -> 8.7557711 | M52: =F52*$K$3/1000 -> 24.143978 | N52: =G52*$K$3/1000 -> 110.14646
A53: Wood pellets | B53: €/toe | C53: 590 | D53: 535 | E53: 452 | F53: 418 | G53: 421 | I53: €/GJ | J53: =C53/$K$2 -> 14.091908 | K53: =D53/$K$2 -> 12.778255 | L53: =E53/$K$2 -> 10.795835 | M53: =F53/$K$2 -> 9.9837585 | N53: =G53/$K$2 -> 10.055412 | P53: =J53/$J53 -> 1 | Q53: =K53/$J53 -> 0.90677966 | R53: =L53/$J53 -> 0.76610169 | S53: =M53/$J53 -> 0.70847458 | T53: =N53/$J53 -> 0.71355932 | V53: =J53*100/$Q$3 -> 11.042374 | W53: =K53*100/$Q$3 -> 10.013001 | X53: =L53*100/$Q$3 -> 8.4595818 | Y53: =M53*100/$Q$3 -> 7.8232416 | Z53: =N53*100/$Q$3 -> 7.8793892
A54: Bioethanol | B54: toe | C54: 779549 | D54: 792079 | E54: 421094 | F54: 750039 | G54: 1428558 | I54: PJ | J54: =C54*$K$3/1000 -> 32.638158 | K54: =D54*$K$3/1000 -> 33.162764 | L54: =E54*$K$3/1000 -> 17.630364 | M54: =F54*$K$3/1000 -> 31.402633 | N54: =G54*$K$3/1000 -> 59.810866
A55: Bioethanol | B55: €/toe | C55: 779 | D55: 864 | E55: 951 | F55: 1054 | G55: 1204 | I55: €/GJ | J55: =C55/$K$2 -> 18.606095 | K55: =D55/$K$2 -> 20.636285 | L55: =E55/$K$2 -> 22.714245 | M55: =F55/$K$2 -> 25.174358 | N55: =G55/$K$2 -> 28.757046 | P55: =J55/$J55 -> 1 | Q55: =K55/$J55 -> 1.1091142 | R55: =L55/$J55 -> 1.2207959 | S55: =M55/$J55 -> 1.3530167 | T55: =N55/$J55 -> 1.5455712 | V55: =J55*100/$Q$3 -> 14.579677 | W55: =K55*100/$Q$3 -> 16.170528 | X55: =L55*100/$Q$3 -> 17.79881 | Y55: =M55*100/$Q$3 -> 19.726547 | Z55: =N55*100/$Q$3 -> 22.53393
A56: Biodiesel | B56: toe | C56: 101448 | D56: 118165 | E56: 0 | F56: 0 | G56: 122199 | I56: PJ | J56: =C56*$K$3/1000 -> 4.2474249 | K56: =D56*$K$3/1000 -> 4.9473322 | L56: =E56*$K$3/1000 -> 0 | M56: =F56*$K$3/1000 -> 0 | N56: =G56*$K$3/1000 -> 5.1162277
A57: Biodiesel | B57: €/toe | C57: 1209 | D57: 1488 | E57: 1755 | F57: 1948 | G57: 2212 | I57: €/GJ | J57: =C57/$K$2 -> 28.876469 | K57: =D57/$K$2 -> 35.540269 | L57: =E57/$K$2 -> 41.917455 | M57: =F57/$K$2 -> 46.527181 | N57: =G57/$K$2 -> 52.832712 | P57: =J57/$J57 -> 1 | Q57: =K57/$J57 -> 1.2307692 | R57: =L57/$J57 -> 1.4516129 | S57: =M57/$J57 -> 1.611249 | T57: =N57/$J57 -> 1.8296112 | V57: =J57*100/$Q$3 -> 22.62751 | W57: =K57*100/$Q$3 -> 27.849243 | X57: =L57*100/$Q$3 -> 32.846385 | Y57: =M57*100/$Q$3 -> 36.458552 | Z57: =N57*100/$Q$3 -> 41.399546

Sheet Conversions
A1: Conversion factors - Energy
A2: 1 ktoe | B2: = | C2: 0.041868 | D2: PJ
A3: 1 MBtu | B3: = | C3: 1.0551 | D3: GJ
A4: 1 toe | B4: = | C4: 7.33 | D4: boe
A5: 1 boe | B5: = | C5: =C2/C4*1000 -> 5.711869 | D5: GJ
A9: Conversion factors - Other
A10: 1 EUR19 | B10: = | C10: 1.1194745 | D10: USD19
A11: 1 EUR18 | B11: = | C11: 1.1809545 | D11: USD18
