Workbook

Sheet Cover
A16: TIMES-Ireland Model
A19: Document type: | B19: New Technologies
A20: Sector(s): | B20: Transport sector (TRA)
A21: Purpose: | B21: Techno-economic data for new vehicles
A23: Original developer(s): | B23: Vahid Aryanpur (UCC, vahid.aryanpur@ucc.ie)
A26: Current maintainer(s): | B26: Vahid Aryanpur (UCC, vahid.aryanpur@ucc.ie)
A29: Part of TIM version: | B29: 1
A30: Model repository: | B30: https://github.com/MaREI-EPMG/TIMES-Ireland-model
A31: Licence: | B31: CC BY-NC-SA 4.0 (unless specified otherwise)
B32: https://creativecommons.org/licenses/by-nc-sa/4.0/

Sheet Commodities
A1: Commodities
A4: Csets | B4: CommName | C4: CommDesc | D4: Unit | E4: LimType | F4: CTSLvl | G4: PeakTS | H4: Ctype
A5: *Commodity Set Membership | B5: Commodity Name | C5: Commodity Description | D5: Unit | E5: Balance equation | F5: Timeslice Level | G5: Peak Monitoring | H5: Electricity Indicator
A6: NRG | B6: TRAWLK | C6: Walking (TRA) | D6: PJ
B7: TRACYC | C7: Cycling (TRA) | D7: PJ
B8: TRAGSL | C8: Gasoline (TRA) | D8: PJ
B9: TRADST | C9: Diesel (TRA) | D9: PJ
B10: TRAETH | C10: BioEthanol (TRA) | D10: PJ
B11: TRABDL | C11: BioDiesel (TRA) | D11: PJ
B12: TRABJK | C12: Bio Jet Kerosene (TRA)_SAF | D12: PJ
B13: TRACNG | C13: CNG (TRA) | D13: PJ
B14: TRAPtLKER | C14: Power to Liquid, pure synthetic kerosene (TRA) | D14: PJ
B15: TRABNG | C15: BioCNG (TRA) | D15: PJ
B16: TRAELC | C16: Electricity (TRA) | D16: PJ | F16: DAYNITE | H16: ELC
B17: TRALNG | C17: LNG (TRA) | D17: PJ
B18: TRAH2 | C18: Hydrogen (TRA) | D18: PJ
B19: TRAKER | C19: Kerosene (TRA) | D19: PJ
A20: DEM | B20: TRAPS | C20: Transport Demand: Short-range passenger travels | D20: Bpkm
B21: TRAPM | C21: Transport Demand: Medium-range passenger travels | D21: Bpkm
B22: TRAPL | C22: Transport Demand: Long-range passenger travels | D22: Bpkm
B23: TRAF | C23: Transport Demand: Goods vehicle for freight | D23: Btkm
B24: TTURS | C24: Transport Demand: Turism fuel | D24: PJ
B25: TNAV | C25: Transport Demand: Navigation fuel | D25: PJ
B26: TOTH | C26: Transport Demand: Unspecified fuel | D26: PJ
B27: TAVIDOM | C27: Transport Demand: Aviation domestic | D27: PJ
B28: TAVIINT | C28: Transport Demand: Aviation international | D28: PJ
A29: ENV | B29: TRACO2N | C29: Carbon Dioxide - Combustion (TRA) | D29: kt
B30: TRACH4N | C30: Methane (TRA) | D30: kt
B31: TRASO2N | C31: Sulphur Oxides (TRA) | D31: kt
B32: TRANOXN | C32: Nitrogen Oxide (TRA) | D32: kt
B33: TRAPM10 | C33: Particulate Matter <10 µm (TRA) | D33: kt
B34: TRAPM25 | C34: Particulate Matter <2.5 µm (TRA) | D34: kt
B35: AVIKER | C35: Kerosene for Aviation
B36: AVIBJK | C36: Biojet kerosene or SAF for Aviation
B37: AVIELC | C37: Electricity for Aviation
B38: AVIH2 | C38: Hydrogen for Aviation
B39: AVIPtL | C39: Syntethic fuel for Aviation
B47: Vehicle type (New technologies)
B48: End-use technologies | C48: Description
B49: Passenger
B50: Two-wheelers
B51: T-MOT-ICE_GSL01 | C51: TRA Motorcycles: Gasoline ICEs - New
B52: T-MOT-EV_ELC01 | C52: TRA Motorcycles: Electric - New
B53: Private cars
B54: T-CAR-ICE_GSL21 | C54: TRA Cars: Gasoline ICEs - New
B55: T-CAR-ICE_DST21 | C55: TRA Cars: Diesel ICEs - New
B56: T-CAR-ICE_DF21 | C56: TRA Cars: Dual fuel ICEs (CNG/BCNG & Gasoline) - New
B57: T-CAR-ICE_NGB21 | C57: TRA Cars: BioCNG and CNG ICEs - New
B58: T-CAR-ICE_E8521 | C58: TRA Cars: Flex fuel ICEs - New
B59: T-CAR-ICE_B10021 | C59: TRA Cars: Biodiesel ICEs - New
B60: T-CAR-HEV_GSL21 | C60: TRA Cars: Gasoline HEVs - New
B61: T-CAR-HEV_DST21 | C61: TRA Cars: Diesel HEVs - New
B62: T-CAR-PHEV10_GSL21 | C62: TRA Cars: Gasoline PHEV, 10-mile all-electric range - New
B63: T-CAR-PHEV20_GSL21 | C63: TRA Cars: Gasoline PHEV, 20-mile all-electric range - New
B64: T-CAR-PHEV40_GSL21 | C64: TRA Cars: Gasoline PHEV, 40-mile all-electric range - New
B65: T-CAR-PHEV10_DST21 | C65: TRA Cars: Diesel PHEV, 10-mile all-electric range - New
... B72: T-CAR-FCV_HYD21 | C72: TRA Cars: Fuel cell vehicles - New
B73: Taxis
B74: T-TAX-ICE_GSL31 | C74: TRA Taxis: Gasoline ICEs - New
B75: T-TAX-ICE_DST31 | C75: TRA Taxis: Diesel ICEs - New
B76: T-TAX-ICE_DF31 | C76: TRA Taxis: Dual fuel ICEs (CNG/BCNG & Gasoline) - New
B77: T-TAX-ICE_NGB31 | C77: TRA Taxis: BioCNG and CNG ICEs - New
B78: T-TAX-ICE_E8531 | C78: TRA Taxis: Flex fuel ICEs - New
B79: T-TAX-ICE_B10031 | C79: TRA Taxis: Biodiesel ICEs - New
B80: T-TAX-HEV_GSL31 | C80: TRA Taxis: Gasoline HEVs - New
B81: T-TAX-HEV_DST31 | C81: TRA Taxis: Diesel HEV - New
B82: T-TAX-PHEV10_GSL31 | C82: TRA Taxis: Gasoline PHEV, 10-mile all-electric range - New
B83: T-TAX-PHEV20_GSL31 | C83: TRA Taxis: Gasoline PHEV, 20-mile all-electric range - New
B84: T-TAX-PHEV40_GSL31 | C84: TRA Taxis: Gasoline PHEV, 40-mile all-electric range - New
B85: T-TAX-PHEV10_DST31 | C85: TRA Taxis: Diesel PHEV, 10-mile all-electric range - New
... B92: T-TAX-FCV_HYD31 | C92: TRA Taxis: Fuel cell vehicles - New
B93: Buses
B94: T-BUS-ICE_DST41 | C94: TRA BUS: Diesel ICEs - New
B95: T-BUS-ICE_B10041 | C95: TRA BUS: Biodiesel ICEs - New
B96: T-BUS-ICE_NGB41 | C96: TRA BUS: BioCNG and CNG ICEs - New
B97: T-BUS-BEV_ELC41 | C97: TRA BUS: BEV - New
B98: T-BUS-FCV_HYD41 | C98: TRA BUS: Fuel Cell Vehicles - New
B99: Passenger Train
B100: T-LPT-BEV_ELC51 | C100: TRA Light Passenger Train: Electric - New
B101: T-HPT-BEV_ELC51 | C101: TRA Heavy Passenger Train: Electric - New
B102: T-HPT-ICE_DST51 | C102: TRA Heavy Passenger Train: Diesel - New
B103: Freights
B104: Light Goods Trucks
B105: T-LGT-ICE_DST61 | C105: TRA Light Goods Truck: Diesel ICE - New
B106: T-LGT-HEV_DST61 | C106: TRA Light Goods Truck: Diesel HEV - New
B107: T-LGT-PHEV_DST61 | C107: TRA Light Goods Truck: Diesel Plug in Hybrid - New
B108: T-LGT-ICE_NGB61 | C108: TRA Light Goods Truck: BioCNG and CNG ICE - New
B109: T-LGT-PHEV_NGB61 | C109: TRA Light Goods Truck: BioCNG and CNG PHEV - New
B110: T-LGT-FCV_HYD61 | C110: TRA Light Goods Truck: Fuel Cell Vehicle - New
B111: T-LGT-BEV_ELC61 | C111: TRA Light Goods Truck: Battery Electric Vehicle - New
B112: Medium Goods Trucks
B113: T-MGT-ICE_DST71 | C113: TRA Medium Goods Truck: Diesel ICE - New
B114: T-MGT-HEV_DST71 | C114: TRA Medium Goods Truck: Diesel HEV - New
B115: T-MGT-FCV_HYD71 | C115: TRA Medium Goods Truck: Hydrogen FCV - New
B116: T-MGT-ICE_NGB71 | C116: TRA Medium Goods Truck: BioCNG and CNG ICE - New
B117: T-MGT-HEV_NGB71 | C117: TRA Medium Goods Truck: BioCNG and CNG HEV - New
B118: T-MGT-ICE_LNG71 | C118: TRA Medium Goods Truck: LNG ICE - New
B119: T-MGT-BEV_ELC71 | C119: TRA Medium Goods Truck: Battery Electric Vehicle - New
B120: Heavy Goods Trucks
B121: T-HGT-ICE_DST81 | C121: TRA Heavy Goods Truck: Diesel ICE - New
...

Sheet TRA
B3: ~FI_Process
B4: Sets | C4: Region | D4: TechName | E4: TechDesc | F4: Tact | G4: Tcap | H4: Tslvl | I4: PrimaryCG | J4: Vintage
B5: *Process Set Membership | C5: Region Name | D5: Technology Name | E5: Technology Description | F5: Activity Unit | G5: Capacity Unit | H5: TimeSlice level of Process Activity | I5: Primary Commodity Group | J5: Vintage Tracking
B6: *Two-wheelers
B7: DMD | D7: =Commodities!B51 -> T-MOT-ICE_GSL01 | E7: =Commodities!C51 -> TRA Motorcycles: Gasoline ICEs - New | F7: Bpkm | G7: 000_Units
B8: DMD | D8: =Commodities!B52 -> T-MOT-EV_ELC01 | E8: =Commodities!C52 -> TRA Motorcycles: Electric - New | F8: Bpkm | G8: 000_Units
B9: *Private cars
B10: DMD | D10: =Commodities!B54 -> T-CAR-ICE_GSL21 | E10: =Commodities!C54 -> TRA Cars: Gasoline ICEs - New | F10: Bpkm | G10: 000_Units
B11: DMD | D11: =Commodities!B55 -> T-CAR-ICE_DST21 | E11: =Commodities!C55 -> TRA Cars: Diesel ICEs - New | F11: Bpkm | G11: 000_Units
B12: DMD | D12: =Commodities!B56 -> T-CAR-ICE_DF21 | E12: =Commodities!C56 -> TRA Cars: Dual fuel ICEs (CNG/BCNG & Gasoline) - New | F12: Bpkm | G12: 000_Units
B13: DMD | D13: =Commodities!B57 -> T-CAR-ICE_NGB21 | E13: =Commodities!C57 -> TRA Cars: BioCNG and CNG ICEs - New | F13: Bpkm | G13: 000_Units
B14: DMD | D14: =Commodities!B58 -> T-CAR-ICE_E8521 | E14: =Commodities!C58 -> TRA Cars: Flex fuel ICEs - New | F14: Bpkm | G14: 000_Units
B15: DMD | D15: =Commodities!B59 -> T-CAR-ICE_B10021 | E15: =Commodities!C59 -> TRA Cars: Biodiesel ICEs - New | F15: Bpkm | G15: 000_Units
B16: DMD | D16: =Commodities!B60 -> T-CAR-HEV_GSL21 | E16: =Commodities!C60 -> TRA Cars: Gasoline HEVs - New | F16: Bpkm | G16: 000_Units
B17: DMD | D17: =Commodities!B61 -> T-CAR-HEV_DST21 | E17: =Commodities!C61 -> TRA Cars: Diesel HEVs - New | F17: Bpkm | G17: 000_Units
B18: DMD | D18: =Commodities!B62 -> T-CAR-PHEV10_GSL21 | E18: =Commodities!C62 -> TRA Cars: Gasoline PHEV, 10-mile all-electric range - New | F18: Bpkm | G18: 000_Units
B19: DMD | D19: =Commodities!B63 -> T-CAR-PHEV20_GSL21 | E19: =Commodities!C63 -> TRA Cars: Gasoline PHEV, 20-mile all-electric range - New | F19: Bpkm | G19: 000_Units
B20: DMD | D20: =Commodities!B64 -> T-CAR-PHEV40_GSL21 | E20: =Commodities!C64 -> TRA Cars: Gasoline PHEV, 40-mile all-electric range - New | F20: Bpkm | G20: 000_Units
B21: DMD | D21: =Commodities!B65 -> T-CAR-PHEV10_DST21 | E21: =Commodities!C65 -> TRA Cars: Diesel PHEV, 10-mile all-electric range - New | F21: Bpkm | G21: 000_Units
... B28: DMD | D28: =Commodities!B72 -> T-CAR-FCV_HYD21 | E28: =Commodities!C72 -> TRA Cars: Fuel cell vehicles - New | F28: Bpkm | G28: 000_Units
B29: *Taxis
B30: DMD | D30: =Commodities!B74 -> T-TAX-ICE_GSL31 | E30: =Commodities!C74 -> TRA Taxis: Gasoline ICEs - New | F30: Bpkm | G30: 000_Units
B31: DMD | D31: =Commodities!B75 -> T-TAX-ICE_DST31 | E31: =Commodities!C75 -> TRA Taxis: Diesel ICEs - New | F31: Bpkm | G31: 000_Units
B32: DMD | D32: =Commodities!B76 -> T-TAX-ICE_DF31 | E32: =Commodities!C76 -> TRA Taxis: Dual fuel ICEs (CNG/BCNG & Gasoline) - New | F32: Bpkm | G32: 000_Units
B33: DMD | D33: =Commodities!B77 -> T-TAX-ICE_NGB31 | E33: =Commodities!C77 -> TRA Taxis: BioCNG and CNG ICEs - New | F33: Bpkm | G33: 000_Units
B34: DMD | D34: =Commodities!B78 -> T-TAX-ICE_E8531 | E34: =Commodities!C78 -> TRA Taxis: Flex fuel ICEs - New | F34: Bpkm | G34: 000_Units
B35: DMD | D35: =Commodities!B79 -> T-TAX-ICE_B10031 | E35: =Commodities!C79 -> TRA Taxis: Biodiesel ICEs - New | F35: Bpkm | G35: 000_Units
B36: DMD | D36: =Commodities!B80 -> T-TAX-HEV_GSL31 | E36: =Commodities!C80 -> TRA Taxis: Gasoline HEVs - New | F36: Bpkm | G36: 000_Units
B37: DMD | D37: =Commodities!B81 -> T-TAX-HEV_DST31 | E37: =Commodities!C81 -> TRA Taxis: Diesel HEV - New | F37: Bpkm | G37: 000_Units
B38: DMD | D38: =Commodities!B82 -> T-TAX-PHEV10_GSL31 | E38: =Commodities!C82 -> TRA Taxis: Gasoline PHEV, 10-mile all-electric range - New | F38: Bpkm | G38: 000_Units
B39: DMD | D39: =Commodities!B83 -> T-TAX-PHEV20_GSL31 | E39: =Commodities!C83 -> TRA Taxis: Gasoline PHEV, 20-mile all-electric range - New | F39: Bpkm | G39: 000_Units
B40: DMD | D40: =Commodities!B84 -> T-TAX-PHEV40_GSL31 | E40: =Commodities!C84 -> TRA Taxis: Gasoline PHEV, 40-mile all-electric range - New | F40: Bpkm | G40: 000_Units
B41: DMD | D41: =Commodities!B85 -> T-TAX-PHEV10_DST31 | E41: =Commodities!C85 -> TRA Taxis: Diesel PHEV, 10-mile all-electric range - New | F41: Bpkm | G41: 000_Units
... B48: DMD | D48: =Commodities!B92 -> T-TAX-FCV_HYD31 | E48: =Commodities!C92 -> TRA Taxis: Fuel cell vehicles - New | F48: Bpkm | G48: 000_Units
B49: *Buses
B50: DMD | D50: =Commodities!B94 -> T-BUS-ICE_DST41 | E50: =Commodities!C94 -> TRA BUS: Diesel ICEs - New | F50: Bpkm | G50: 000_Units
B51: DMD | D51: =Commodities!B95 -> T-BUS-ICE_B10041 | E51: =Commodities!C95 -> TRA BUS: Biodiesel ICEs - New | F51: Bpkm | G51: 000_Units
B52: DMD | D52: =Commodities!B96 -> T-BUS-ICE_NGB41 | E52: =Commodities!C96 -> TRA BUS: BioCNG and CNG ICEs - New | F52: Bpkm | G52: 000_Units
B53: DMD | D53: =Commodities!B97 -> T-BUS-BEV_ELC41 | E53: =Commodities!C97 -> TRA BUS: BEV - New | F53: Bpkm | G53: 000_Units
B54: DMD | D54: =Commodities!B98 -> T-BUS-FCV_HYD41 | E54: =Commodities!C98 -> TRA BUS: Fuel Cell Vehicles - New | F54: Bpkm | G54: 000_Units
B55: *Train
B56: DMD | D56: =Commodities!B100 -> T-LPT-BEV_ELC51 | E56: =Commodities!C100 -> TRA Light Passenger Train: Electric - New | F56: Bpkm | G56: 000_Units
B57: DMD | D57: =Commodities!B101 -> T-HPT-BEV_ELC51 | E57: =Commodities!C101 -> TRA Heavy Passenger Train: Electric - New | F57: Bpkm | G57: 000_Units
B58: DMD | D58: =Commodities!B102 -> T-HPT-ICE_DST51 | E58: =Commodities!C102 -> TRA Heavy Passenger Train: Diesel - New | F58: Bpkm | G58: 000_Units
B59: *Light trucks
B60: DMD | D60: =Commodities!B105 -> T-LGT-ICE_DST61 | E60: =Commodities!C105 -> TRA Light Goods Truck: Diesel ICE - New | F60: Btkm | G60: 000_Units
B61: DMD | D61: =Commodities!B106 -> T-LGT-HEV_DST61 | E61: =Commodities!C106 -> TRA Light Goods Truck: Diesel HEV - New | F61: Btkm | G61: 000_Units
B62: DMD | D62: =Commodities!B107 -> T-LGT-PHEV_DST61 | E62: =Commodities!C107 -> TRA Light Goods Truck: Diesel Plug in Hybrid - New | F62: Btkm | G62: 000_Units
B63: DMD | D63: =Commodities!B108 -> T-LGT-ICE_NGB61 | E63: =Commodities!C108 -> TRA Light Goods Truck: BioCNG and CNG ICE - New | F63: Btkm | G63: 000_Units
B64: DMD | D64: =Commodities!B109 -> T-LGT-PHEV_NGB61 | E64: =Commodities!C109 -> TRA Light Goods Truck: BioCNG and CNG PHEV - New | F64: Btkm | G64: 000_Units
B65: DMD | D65: =Commodities!B110 -> T-LGT-FCV_HYD61 | E65: =Commodities!C110 -> TRA Light Goods Truck: Fuel Cell Vehicle - New | F65: Btkm | G65: 000_Units
B66: DMD | D66: =Commodities!B111 -> T-LGT-BEV_ELC61 | E66: =Commodities!C111 -> TRA Light Goods Truck: Battery Electric Vehicle - New | F66: Btkm | G66: 000_Units
B67: *Medium trucks
B68: DMD | D68: =Commodities!B113 -> T-MGT-ICE_DST71 | E68: =Commodities!C113 -> TRA Medium Goods Truck: Diesel ICE - New | F68: Btkm | G68: 000_Units
B69: DMD | D69: =Commodities!B114 -> T-MGT-HEV_DST71 | E69: =Commodities!C114 -> TRA Medium Goods Truck: Diesel HEV - New | F69: Btkm | G69: 000_Units
B70: DMD | D70: =Commodities!B115 -> T-MGT-FCV_HYD71 | E70: =Commodities!C115 -> TRA Medium Goods Truck: Hydrogen FCV - New | F70: Btkm | G70: 000_Units
B71: DMD | D71: =Commodities!B116 -> T-MGT-ICE_NGB71 | E71: =Commodities!C116 -> TRA Medium Goods Truck: BioCNG and CNG ICE - New | F71: Btkm | G71: 000_Units
B72: DMD | D72: =Commodities!B117 -> T-MGT-HEV_NGB71 | E72: =Commodities!C117 -> TRA Medium Goods Truck: BioCNG and CNG HEV - New | F72: Btkm | G72: 000_Units
B73: DMD | D73: =Commodities!B118 -> T-MGT-ICE_LNG71 | E73: =Commodities!C118 -> TRA Medium Goods Truck: LNG ICE - New | F73: Btkm | G73: 000_Units
B74: DMD | D74: =Commodities!B119 -> T-MGT-BEV_ELC71 | E74: =Commodities!C119 -> TRA Medium Goods Truck: Battery Electric Vehicle - New | F74: Btkm | G74: 000_Units
B75: *Heavy trucks
B76: DMD | D76: =Commodities!B121 -> T-HGT-ICE_DST81 | E76: =Commodities!C121 -> TRA Heavy Goods Truck: Diesel ICE - New | F76: Btkm | G76: 000_Units
B77: DMD | D77: =Commodities!B122 -> T-HGT-HEV_DST81 | E77: =Commodities!C122 -> TRA Heavy Goods Truck: Diesel HEV - New | F77: Btkm | G77: 000_Units
B78: DMD | D78: =Commodities!B123 -> T-HGT-FCV_HYD81 | E78: =Commodities!C123 -> TRA Heavy Goods Truck: Hydrogen FCV - New | F78: Btkm | G78: 000_Units
B79: DMD | D79: =Commodities!B124 -> T-HGT-ICE_NGB81 | E79: =Commodities!C124 -> TRA Heavy Goods Truck: BioCNG and CNG ICE - New | F79: Btkm | G79: 000_Units
B80: DMD | D80: =Commodities!B125 -> T-HGT-HEV_NGB81 | E80: =Commodities!C125 -> TRA Heavy Goods Truck: BioCNG and CNG HEV - New | F80: Btkm | G80: 000_Units
B81: DMD | D81: =Commodities!B126 -> T-HGT-ICE_LNG81 | E81: =Commodities!C126 -> TRA Heavy Goods Truck: LNG ICE - New | F81: Btkm | G81: 000_Units
B82: DMD | D82: =Commodities!B127 -> T-HGT-BEV_ELC81 | E82: =Commodities!C127 -> TRA Heavy Goods Truck: Battery Electric Vehicle - New | F82: Btkm | G82: 000_Units
B83: *Rail trucks
B84: DMD | D84: =Commodities!B129 -> T-GTR-ICE_DST91 | E84: =Commodities!C129 -> TRA Goods Train: ICE Diesel Train - New | F84: Btkm | G84: 000_Units
B85: DMD | D85: =Commodities!B130 -> T-GTR-BEV_ELC91 | E85: =Commodities!C130 -> TRA Goods Train: Electric Train - New | F85: Btkm | G85: 000_Units
B86: DMD | D86: =Commodities!B131 -> T-GTR-FCV_HYD91 | E86: =Commodities!C131 -> TRA Goods Train: Hydrogen Fuel Cell Train - New | F86: Btkm | G86: 000_Units
B87: *Turism, Navigation & Others
B88: DMD | D88: =Commodities!B134 -> T-TUR_NEW | E88: =Commodities!C134 -> TRA Tourism: Advanced Tourism Vehicles - New | F88: PJ | G88: PJa
B89: DMD | D89: =Commodities!B135 -> T-NAV_NEW | E89: =Commodities!C135 -> TRA Navigation: Advanced Navigation Vehicles - New | F89: PJ | G89: PJa
B90: DMD | D90: =Commodities!B136 -> T-OTH_NEW | E90: =Commodities!C136 -> TRA Unspecified: Advanced Unspecified Vehicles - New | F90: PJ | G90: PJa
B91: *Aviation
B92: DMD | D92: =Commodities!B138 -> T-AVI_DOM_NEW | E92: =Commodities!C138 -> Aviation domestic - New | F92: PJ | G92: PJa
B93: DMD | D93: =Commodities!B139 -> T-AVI_INT_NEW | E93: =Commodities!C139 -> Aviation international - New | F93: PJ | G93: PJa
B94: DMD | D94: =Commodities!B140 -> T-SAVI_INT_JETK_NEW | E94: =Commodities!C140 -> Aviation international - Fossil Jet Kerosene - Small Aircraft - New | F94: Bpkm | G94: 000_Units
B95: DMD | D95: =Commodities!B141 -> T-MAVI_INT_JETK_NEW | E95: =Commodities!C141 -> Aviation international - Fossil Jet Kerosene - Medium Aircraft - New | F95: Bpkm | G95: 000_Units
B96: DMD | D96: =Commodities!B142 -> T-LAVI_INT_JETK_NEW | E96: =Commodities!C142 -> Aviation international - Fossil Jet Kerosene - Large Aircraft - New | F96: Bpkm | G96: 000_Units
B97: DMD | D97: =Commodities!B143 -> T-SAVI_INT_SAF_NEW | E97: =Commodities!C143 -> Aviation international - SAF - Small Aircraft - New | F97: Bpkm | G97: 000_Units
B98: DMD | D98: =Commodities!B144 -> T-MAVI_INT_SAF_NEW | E98: =Commodities!C144 -> Aviation international - SAF - Medium Aircraft - New | F98: Bpkm | G98: 000_Units | M98: 2
B99: DMD | D99: =Commodities!B145 -> T-LAVI_INT_SAF_NEW | E99: =Commodities!C145 -> Aviation international - SAF - Large Aircraft - New | F99: Bpkm | G99: 000_Units
B100: DMD | D100: =Commodities!B146 -> T-SAVI_INT_SYN-FUEL_NEW | E100: =Commodities!C146 -> Aviation international - Synthetic Fuel - Small Aircraft - New | F100: Bpkm | G100: 000_Units
B101: DMD | D101: =Commodities!B147 -> T-MAVI_INT_SYN-FUEL_NEW | E101: =Commodities!C147 -> Aviation international - Synthetic Fuel - Medium Aircraft - New | F101: Bpkm | G101: 000_Units
B102: DMD | D102: =Commodities!B148 -> T-LAVI_INT_SYN-FUEL_NEW | E102: =Commodities!C148 -> Aviation international - Synthetic Fuel - Large Aircraft - New | F102: Bpkm | G102: 000_Units
B103: DMD | D103: =Commodities!B149 -> T-SAVI_INT_ELC_NEW | E103: =Commodities!C149 -> Aviation international - Electric - Small Aircraft - New | F103: Bpkm | G103: 000_Units
B104: DMD | D104: =Commodities!B150 -> T-MAVI_INT_ELC_NEW | E104: =Commodities!C150 -> Aviation international - Electric - Medium Aircraft - New | F104: Bpkm | G104: 000_Units
B105: DMD | D105: =Commodities!B151 -> T-SAVI_INT_H2_NEW | E105: =Commodities!C151 -> Aviation international - Hydrogen - Small Aircraft - New | F105: Bpkm | G105: 000_Units
B106: DMD | D106: =Commodities!B152 -> T-MAVI_INT_H2_NEW | E106: =Commodities!C152 -> Aviation international - Hydrogen - Medium Aircraft - New | F106: Bpkm | G106: 000_Units
B107: DMD | D107: =Commodities!B153 -> T-LAVI_INT_H2_NEW | E107: =Commodities!C153 -> Aviation international - Hydrogen - Large Aircraft - New | F107: Bpkm | G107: 000_Units
D118: ~FI_T
B119: TechName | C119: Comm-IN | D119: Comm-OUT | E119: START | F119: EFF~2018 | G119: EFF~2030 | H119: EFF~2050 | I119: EFF~2070 | J119: INVCOST~2018 | K119: INVCOST~2025 | L119: INVCOST~2030 | M119: INVCOST~2035 | N119: INVCOST~2050 | O119: FIXOM~2018 | P119: FIXOM~2030 | Q119: FIXOM~2050 | R119: AFA~2018 | S119: AFA~2021 | T119: AFA~2022 | U119: AFA~2027 | V119: AFA~0 | W119: ACTFLO~DEMO | X119: LIFE | Y119: CAP2ACT | Z119: RCAP_BND~0
B120: *Technology Name | C120: Input Commodity | D120: Output Commodity | F120: Efficiency | G120: Efficiency | H120: Efficiency | I120: Efficiency | J120: Purchase price | K120: Purchase price | L120: Purchase price | M120: Purchase price | N120: Purchase price | O120: Fixed O&M cost | P120: Fixed O&M cost | Q120: Fixed O&M cost | R120: Utilisation Factor | S120: Utilisation Factor | T120: Utilisation Factor | U120: Utilisation Factor | V120: Utilisation Factor | W120: Activity to Flo | X120: Lifetime | Y120: Capacity to Activity Factor
B121: *Units | F121: BV*km/PJ | G121: BV*km/PJ | H121: BV*km/PJ | I121: BV*km/PJ | J121: M€2018/000_units | K121: M€2018/000_units | L121: M€2018/000_units | M121: M€2018/000_units | N121: M€2018/000_units | O121: M€2018/000_units/a | P121: M€2018/000_units/a | Q121: M€2018/000_units/a | R121: '000 km | S121: '000 km | T121: '000 km | U121: '000 km | V121: '000 km | W121: Passenger or tonnage/Vehicle | X121: Years | Y121: bvkm/mvkm
B122: *Two-wheelers
B123: =D7 -> T-MOT-ICE_GSL01 | C123: =Commodities!B8&","&Commodities!B10 -> TRAGSL,TRAETH | D123: =Commodities!B20&","&Commodities!B21 -> TRAPS,TRAPM | E123: 2019 | F123: 0.9259 | G123: 0.9567 | H123: 0.9567 | J123: 3.4222951 | K123: 3.4222951 | L123: 3.4222951 | M123: =L123-((L123-N123)/4) -> 3.4222951 | N123: 3.4222951 | O123: 0.34222939 | P123: 0.34222939 | Q123: 0.34222939 | R123: 2.731 | S123: =R123 -> 2.731 | T123: =S123 -> 2.731 | U123: =T123 -> 2.731 | V123: 5 | W123: 1 | X123: 15 | Y123: 0.001
B124: =D8 -> T-MOT-EV_ELC01 | C124: =Commodities!B16 -> TRAELC | D124: =Commodities!B20&","&Commodities!B21 -> TRAPS,TRAPM | E124: 2019 | F124: 8.1396 | G124: 8.4863 | H124: 9.2248 | J124: 4.6090791 | K124: 4.6090791 | L124: 4.3665433 | M124: =L124-((L124-N124)/4) -> 4.3691261 | N124: 4.3768742 | O124: 0.44354153 | P124: 0.44354153 | Q124: 0.44354153 | R124: 2.731 | S124: =R124 -> 2.731 | T124: =S124 -> 2.731 | U124: =T124 -> 2.731 | V124: 5 | W124: 1 | X124: 15 | Y124: 0.001
...

Sheet Purchase price
A1: New Private Cars (Number) by Car Make and Engine Capacity cc in 2018
B2: All capacities | C2: Up to 900 cc | D2: 901-1000 cc | E2: 1001-1300 cc | F2: 1301-1400 cc | G2: 1401-1500 cc | H2: 1501-1600 cc | I2: 1601-2000 cc | J2: 2001-2400 cc | K2: >2400 cc
A3: All makes | B3: 121157 | C3: 2439 | D3: 20545 | E3: 13872 | F3: 7002 | G3: 20335 | H3: 20414 | I3: 30556 | J3: 3420 | K3: 2574
A4: All other makes | B4: 49 | C4: 13 | D4: 0 | E4: 6 | F4: 10 | G4: 1 | H4: 0 | I4: 8 | J4: 0 | K4: 11 | L4: =B4/$B$3 -> 0.00040443392
A5: Alfa Romeo | B5: 86 | C5: 1 | D5: 0 | E5: 2 | F5: 16 | G5: 0 | H5: 11 | I5: 22 | J5: 29 | K5: 5 | L5: =B5/$B$3 -> 0.00070982279
A6: Audi | B6: 4806 | C6: 0 | D6: 483 | E6: 0 | F6: 197 | G6: 114 | H6: 810 | I6: 2776 | J6: 0 | K6: 426 | L6: =B6/$B$3 -> 0.039667539
A7: BMW | B7: 4128 | C7: 76 | D7: 0 | E7: 0 | F7: 0 | G7: 556 | H7: 0 | I7: 3210 | J7: 0 | K7: 286 | L7: =B7/$B$3 -> 0.034071494
A8: Chevrolet | B8: 0 | C8: 0 | D8: 0 | E8: 0 | F8: 0 | G8: 0 | H8: 0 | I8: 0 | J8: 0 | K8: 0 | L8: =B8/$B$3 -> 0
A9: Chrysler Jeep | B9: 0 | C9: 0 | D9: 0 | E9: 0 | F9: 0 | G9: 0 | H9: 0 | I9: 0 | J9: 0 | K9: 0 | L9: =B9/$B$3 -> 0
A10: Chrysler | B10: 0 | C10: 0 | D10: 0 | E10: 0 | F10: 0 | G10: 0 | H10: 0 | I10: 0 | J10: 0 | K10: 0 | L10: =B10/$B$3 -> 0
A11: Citroen | B11: 1186 | C11: 1 | D11: 20 | E11: 401 | F11: 0 | G11: 0 | H11: 742 | I11: 22 | J11: 0 | K11: 0 | L11: =B11/$B$3 -> 0.0097889515
A12: Dacia | B12: 3411 | C12: 274 | D12: 683 | E12: 1 | F12: 0 | G12: 2451 | H12: 2 | I12: 0 | J12: 0 | K12: 0 | L12: =B12/$B$3 -> 0.028153553
A13: Fiat | B13: 698 | C13: 3 | D13: 1 | E13: 489 | F13: 56 | G13: 0 | H13: 147 | I13: 0 | J13: 2 | K13: 0 | L13: =B13/$B$3 -> 0.0057611199
A14: Ford | B14: 10746 | C14: 0 | D14: 1293 | E14: 2645 | F14: 0 | G14: 5833 | H14: 1 | I14: 928 | J14: 44 | K14: 2 | L14: =B14/$B$3 -> 0.088694834
A15: Honda | B15: 1260 | C15: 2 | D15: 328 | E15: 0 | F15: 237 | G15: 232 | H15: 456 | I15: 5 | J15: 0 | K15: 0 | L15: =B15/$B$3 -> 0.010399729
... A44: Volvo | B44: 1690 | C44: 0 | D44: 0 | E44: 0 | F44: 0 | G44: 58 | H44: 0 | I44: 1631 | J44: 1 | K44: 0 | L44: =B44/$B$3 -> 0.013948843
A45: Source: CSO, Table: TEA29
A50: Purchase price in 2018 (Euro/vehicle)
B51: All capacities | C51: Up to 900 cc | D51: 901-1000 cc | E51: 1001-1300 cc | F51: 1301-1400 cc | G51: 1401-1500 cc | H51: 1501-1600 cc | I51: 1601-2000 cc | J51: 2001-2400 cc | K51: >2400 cc
A52: Ford | C52: 16650 | D52: 19600 | E52: 19600 | F52: 20835 | G52: 20835 | H52: 20835 | I52: 27990 | J52: 53175 | K52: 61500
A53: Hyundai | C53: 11995 | D53: 12995 | E53: 13995 | F53: 17495 | G53: 18995 | H53: 20495 | I53: 25495 | J53: 35995 | K53: 43995
A54: Kia | C54: 11685 | D54: 12810 | E54: 15550 | F54: 18190 | G54: 19035 | H54: 20280 | I54: 26025 | J54: 38625 | K54: 41670
A55: Nissan | C55: 15895 | D55: 15895 | E55: 16395 | F55: 18545 | G55: 19195 | H55: 19995 | I55: 27520 | J55: 30520 | K55: 37720
A56: Renault | C56: 12990 | D56: 13590 | E56: 16390 | F56: 18090 | G56: 19990 | H56: 22390 | I56: 28490 | J56: 31990 | K56: 37990
A57: Skoda | C57: 11095 | D57: 12155 | E57: 15600 | F57: 18285 | G57: 27485 | H57: 27250 | I57: 33065 | J57: 39725 | K57: 42025
A58: Toyota | C58: 13360 | D58: 14580 | E58: 23500 | F58: 23500 | G58: 26000 | H58: 26790 | I58: 31630 | J58: 36500 | K58: 40395
A59: Volkswagen | C59: 13770 | D59: 13770 | E59: 17928 | F59: 21445 | G59: 28265 | H59: 24662 | I59: 31420 | J59: 38700 | K59: 73975
A60: Source: SIMI (Society of the Irish Motor Industry), https://www.simi.ie/en/motorstats/recommended-price-guide
A63: New Private Cars (Number) by Car Make and Engine Capacity cc in 2018
B64: All capacities | C64: Up to 900 cc | D64: 901-1000 cc | E64: 1001-1300 cc | F64: 1301-1400 cc | G64: 1401-1500 cc | H64: 1501-1600 cc | I64: 1601-2000 cc | J64: 2001-2400 cc | K64: >2400 cc
A65: Ford | B65: =B14 -> 10746 | C65: =C14 -> 0 | D65: =D14 -> 1293 | E65: =E14 -> 2645 | F65: =F14 -> 0 | G65: =G14 -> 5833 | H65: =H14 -> 1 | I65: =I14 -> 928 | ... K65: =K14 -> 2
A66: Hyundai | B66: =B16 -> 10950 | C66: =C16 -> 92 | D66: =D16 -> 3571 | E66: =E16 -> 1027 | F66: =F16 -> 806 | G66: =G16 -> 0 | H66: =H16 -> 1171 | I66: =I16 -> 3853 | ... K66: =K16 -> 1
A67: Kia | B67: =B20 -> 7005 | C67: =C20 -> 0 | D67: =D20 -> 613 | E67: =E20 -> 506 | F67: =F20 -> 1090 | G67: =G20 -> 0 | H67: =H20 -> 947 | I67: =I20 -> 3245 | ... K67: =K20 -> 2
A68: Nissan | B68: =B28 -> 9277 | C68: =C28 -> 985 | D68: =D28 -> 1885 | E68: =E28 -> 3043 | F68: =F28 -> 0 | G68: =G28 -> 2224 | H68: =H28 -> 1102 | I68: =I28 -> 17 | ... K68: =K28 -> 0
A69: Renault | B69: =B32 -> 7075 | C69: =C32 -> 794 | D69: =D32 -> 2 | E69: =E32 -> 1441 | F69: =F32 -> 0 | G69: =G32 -> 4248 | H69: =H32 -> 450 | I69: =I32 -> 95 | ... K69: =K32 -> 0
A70: Skoda | B70: =B35 -> 8668 | C70: =C35 -> 0 | D70: =D35 -> 3027 | E70: =E35 -> 238 | F70: =F35 -> 266 | G70: =G35 -> 266 | H70: =H35 -> 2962 | I70: =I35 -> 1909 | ... K70: =K35 -> 0
A71: Toyota | B71: =B41 -> 11484 | C71: =C41 -> 0 | D71: =D41 -> 1636 | E71: =E41 -> 794 | F71: =F41 -> 2107 | G71: =G41 -> 1448 | H71: =H41 -> 229 | I71: =I41 -> 4391 | ... K71: =K41 -> 866
A72: Volkswagen | B72: =B43 -> 13496 | C72: =C43 -> 75 | D72: =D43 -> 4558 | E72: =E43 -> 168 | F72: =F43 -> 356 | G72: =G43 -> 407 | H72: =H43 -> 3563 | I72: =I43 -> 4309 | ... K72: =K43 -> 60
A73: Total | B73: =SUM(B65:B72) -> 78701 | C73: =SUM(C65:C72) -> 1946 | D73: =SUM(D65:D72) -> 16585 | E73: =SUM(E65:E72) -> 9862 | F73: =SUM(F65:F72) -> 4625 | G73: =SUM(G65:G72) -> 14426 | H73: =SUM(H65:H72) -> 10425 | I73: =SUM(I65:I72) -> 18747 | ... K73: =SUM(K65:K72) -> 931
A77: New Private Cars (share) by Car Make and Engine Capacity cc in 2018
B78: All capacities | C78: Up to 900 cc | D78: 901-1000 cc | E78: 1001-1300 cc | F78: 1301-1400 cc | G78: 1401-1500 cc | H78: 1501-1600 cc | I78: 1601-2000 cc | J78: 2001-2400 cc | K78: >2400 cc
A79: Ford | B79: =B65/$B$73 -> 0.1365421 | C79: =C65/$B$73 -> 0 | D79: =D65/$B$73 -> 0.01642927 | E79: =E65/$B$73 -> 0.033608213 | F79: =F65/$B$73 -> 0 | G79: =G65/$B$73 -> 0.074115958 | H79: =H65/$B$73 -> 1.2706319e-05 | I79: =I65/$B$73 -> 0.011791464 | ... K79: =K65/$B$73 -> 2.5412638e-05
A80: Hyundai | B80: =B66/$B$73 -> 0.13913419 | C80: =C66/$B$73 -> 0.0011689813 | D80: =D66/$B$73 -> 0.045374265 | E80: =E66/$B$73 -> 0.013049389 | F80: =F66/$B$73 -> 0.010241293 | G80: =G66/$B$73 -> 0 | H80: =H66/$B$73 -> 0.014879099 | I80: =I66/$B$73 -> 0.048957447 | ... K80: =K66/$B$73 -> 1.2706319e-05
A81: Kia | B81: =B67/$B$73 -> 0.089007764 | C81: =C67/$B$73 -> 0 | D81: =D67/$B$73 -> 0.0077889735 | E81: =E67/$B$73 -> 0.0064293973 | F81: =F67/$B$73 -> 0.013849888 | G81: =G67/$B$73 -> 0 | H81: =H67/$B$73 -> 0.012032884 | I81: =I67/$B$73 -> 0.041232005 | ... K81: =K67/$B$73 -> 2.5412638e-05
A82: Nissan | B82: =B68/$B$73 -> 0.11787652 | C82: =C68/$B$73 -> 0.012515724 | D82: =D68/$B$73 -> 0.023951411 | E82: =E68/$B$73 -> 0.038665328 | F82: =F68/$B$73 -> 0 | G82: =G68/$B$73 -> 0.028258853 | H82: =H68/$B$73 -> 0.014002363 | I82: =I68/$B$73 -> 0.00021600742 | ... K82: =K68/$B$73 -> 0
A83: Renault | B83: =B69/$B$73 -> 0.089897206 | C83: =C69/$B$73 -> 0.010088817 | D83: =D69/$B$73 -> 2.5412638e-05 | E83: =E69/$B$73 -> 0.018309805 | F83: =F69/$B$73 -> 0 | G83: =G69/$B$73 -> 0.053976442 | H83: =H69/$B$73 -> 0.0057178435 | I83: =I69/$B$73 -> 0.0012071003 | ... K83: =K69/$B$73 -> 0
A84: Skoda | B84: =B70/$B$73 -> 0.11013837 | C84: =C70/$B$73 -> 0 | D84: =D70/$B$73 -> 0.038462027 | E84: =E70/$B$73 -> 0.0030241039 | F84: =F70/$B$73 -> 0.0033798808 | G84: =G70/$B$73 -> 0.0033798808 | H84: =H70/$B$73 -> 0.037636116 | I84: =I70/$B$73 -> 0.024256363 | ... K84: =K70/$B$73 -> 0
A85: Toyota | B85: =B71/$B$73 -> 0.14591937 | C85: =C71/$B$73 -> 0 | D85: =D71/$B$73 -> 0.020787538 | E85: =E71/$B$73 -> 0.010088817 | F85: =F71/$B$73 -> 0.026772214 | G85: =G71/$B$73 -> 0.01839875 | H85: =H71/$B$73 -> 0.002909747 | I85: =I71/$B$73 -> 0.055793446 | ... K85: =K71/$B$73 -> 0.011003672
A86: Volkswagen | B86: =B72/$B$73 -> 0.17148448 | C86: =C72/$B$73 -> 0.00095297391 | D86: =D72/$B$73 -> 0.057915401 | E86: =E72/$B$73 -> 0.0021346616 | F86: =F72/$B$73 -> 0.0045234495 | G86: =G72/$B$73 -> 0.0051714718 | H86: =H72/$B$73 -> 0.045272614 | I86: =I72/$B$73 -> 0.054751528 | ... K86: =K72/$B$73 -> 0.00076237913
A87: Total | B87: =SUM(B79:B86) -> 1 | C87: =SUM(C79:C86) -> 0.024726496 | D87: =SUM(D79:D86) -> 0.2107343 | E87: =SUM(E79:E86) -> 0.12530972 | F87: =SUM(F79:F86) -> 0.058766725 | G87: =SUM(G79:G86) -> 0.18330136 | H87: =SUM(H79:H86) -> 0.13246337 | I87: =SUM(I79:I86) -> 0.23820536 | ... K87: =SUM(K79:K86) -> 0.011829583
A90: Diesel | B90: =SUMPRODUCT(C79:K86,C52:K59) -> 21831.587
A91: Petrol | B91: =B90/1.07597 -> 20290.145
A94: Helgeson B, Peter J. The role of electricity in decarbonizing European road transport–Development and assessment of an integrated multi-sectoral model. Applied Energy. 2020 Mar 15;262:114365.
A141: AIM Model
A142: AircraftID | B142: Size class | C142: Size_Name | D142: RepACName | E142: DiscountedListPrice_USD2015 | F142: Avg_Seats | G142: Seat_cat_lower_limit | H142: Seat_cat_upper_limit | I142: OpCostFinance_2015dollarperyear | J142: OpCostMaint_AirframeEngine_2015dollarperhr | K142: OpCostMaint_Labour_2015dollarperhr | L142: OpCostMaint_HeavyComponent_2015dollarpercycle | M142: OpCostPilots_2015dollarperhr | N142: OpCostCabinCrew_2015dollarperhr | O142: Equip_Utilisation
A143: 0 | B143: 1 | C143: SmallRJ | D143: CRJ700 | E143: 28980000 | F143: 56 | G143: 30 | H143: 69 | I143: 1250000 | J143: 581.5 | K143: 120.5 | L143: 153 | M143: 304.1 | N143: 141.49 | O143: 0.26498
A144: 1 | B144: 2 | C144: LargeRJ | D144: Embraer190 | E144: 32340000 | F144: 93 | G144: 70 | H144: 109 | I144: 1400000 | J144: 581.5 | K144: 123 | L144: 111 | M144: 535.8 | N144: 206.91 | O144: 0.28518
A145: 2 | B145: 3 | C145: SmallSA | D145: A319 | E145: 63300000 | F145: 132 | G145: 110 | H145: 129 | I145: 2130000 | J145: 620.1 | K145: 247 | L145: 171 | M145: 616.9 | N145: 268.57 | O145: 0.33089
A146: 3 | B146: 4 | C146: MediumSA | D146: A320 | E146: 69300000 | F146: 158 | G146: 130 | H146: 159 | I146: 2830000 | J146: 644.5 | K146: 260 | L146: 180 | M146: 610.6 | N146: 319.35 | O146: 0.4432
A147: 4 | B147: 5 | C147: LargeSA | D147: B737-800 | E147: 81410000 | F147: 186 | G147: 160 | H147: 199 | I147: 2810000 | J147: 737.7 | K147: 130 | L147: 254 | M147: 709.8 | N147: 325.2 | O147: 0.38019
A148: 5 | B148: 6 | C148: SmallTA | D148: B787-800 | E148: 157220000 | F148: 248 | G148: 200 | H148: 249 | I148: 8760000 | J148: 470.9 | K148: 187 | L148: 377 | M148: 1265.7 | N148: 465.02 | O148: 0.47918
A149: 6 | B149: 7 | C149: MediumTA | D149: A330-300 | E149: 181300000 | F149: 263 | G149: 250 | H149: 299 | I149: 6020000 | J149: 869 | K149: 204 | L149: 612 | M149: 1178.2 | N149: 612.37 | O149: 0.46943
A150: 7 | B150: 8 | C150: LargeTA | D150: 777-300ER | E150: 224140000 | F150: 326 | G150: 300 | H150: 399 | I150: 9960000 | J150: 1034.2 | K150: 212 | L150: 913 | M150: 1731 | N150: 649.7 | O150: 0.50285
A151: 8 | B151: 9 | C151: VLA | D151: A380-800 | E151: 305830000 | F151: 414 | G151: 400 | H151: 999 | I151: 14760000 | J151: 916 | K151: 308 | L151: 972 | M151: 1256 | N151: 865.26 | O151: 0.53568
A156: Average passenger per flight
B157: 2013 | C157: 2014 | D157: 2015 | E157: 2016 | F157: 2017 | G157: 2018 | H157: 2019 | I157: 2020 | J157: 2021 | K157: 2022 | L157: 2023
A158: Regional Flights (<500km) | B158: 94.797688 | C158: 95.706522 | D158: 104.96416 | E158: 106.72204 | F158: 110.39049 | G158: 111.03025 | H158: 112.0384 | I158: 76.202899 | J158: 84.853659 | K158: 115.43833 | L158: 117.34854
A159: Intracontinental Flights (>500km and <3000km) | B159: 138.40793 | C159: 139.75785 | D159: 145.77479 | E159: 149.39885 | F159: 148.693 | G159: 149.10588 | H159: 148.55102 | I159: 91.681416 | J159: 101.80899 | K159: 140.79248 | L159: 149.65089
A160: Intercontinental Flights (>3000km) | B160: 211.2 | C160: 200.9759 | D160: 201.24468 | E160: 205.9899 | F160: 201.82906 | G160: 203.4 | H160: 220.26446 | I160: 118.08333 | J160: 118.02941 | K160: 205.70093 | L160: 220.27434
A165: Calibration of average fuel cunsumption
B166: Bpkm/PJ | C166: Seat | D166: Load factor | E166: MVkm/PJ | F166: PJ/Bpkm | G166: PJ
A167: Regional Flights (<500km) | B167: 0.34978252 | C167: 159 | D167: 0.8 | E167: 2.7498626 | F167: 2.8589193 | G167: 8.4381815
A168: Intracontinental Flights (>500km and <3000km) | B168: 0.75598158 | C168: 199 | D168: 0.8 | E168: 4.748628 | F168: 1.3227836 | G168: 17.561905
A169: Intercontinental Flights (>3000km) | B169: 0.69956504 | C169: 299 | D169: 0.8 | E169: 2.924603 | F169: 1.4294596 | G169: 20.20177
A173: Question: How many miles does an airplane like a 777 fly over the course of its lifetime?
A174: 3,500 hours a year as an average
A175: An average speed of 500 miles per hour
A177: Avergae (km/yr) | B177: =3500*500*1.6 -> 2800000
A182: Share of SAF and PtL in ReFuelEU Aviation Regulation
B183: 2020 | C183: 2021 | D183: 2022 | E183: 2023 | F183: 2024 | G183: 2025 | H183: 2026 | I183: 2027 | J183: 2028 | K183: 2029 | L183: 2030 | M183: 2031 | N183: 2032 | O183: 2033 | P183: 2034 | Q183: 2035 | R183: 2036 | S183: 2037 | T183: 2038 | U183: 2039 | V183: 2040 | W183: 2041 | X183: 2042 | Y183: 2043 | Z183: 2044 | AA183: 2045 | AB183: 2046 | AC183: 2047 | AD183: 2048 | AE183: 2049 | AF183: 2050
A184: SAF | B184: 0 | C184: 0 | D184: 0 | E184: 0 | F184: 0 | G184: =G186-G185 -> 0.02 | H184: =H186-H185 -> 0.0472 | I184: =I186-I185 -> 0.0744 | J184: =J186-J185 -> 0.1016 | K184: =K186-K185 -> 0.1288 | L184: =L186-L185 -> 0.144 | M184: =M186-M185 -> 0.1543 | N184: =N186-N185 -> 0.1646 | ... AF184: =AF186-AF185 -> 0.35
A185: PtL | B185: 0 | C185: 0 | D185: 0 | E185: 0 | F185: 0 | G185: 0 | H185: 0 | I185: 0 | J185: 0 | K185: 0 | L185: 0.012 | M185: =L185+1.69% -> 0.0289 | N185: =M185+1.69% -> 0.0458 | O185: =N185+1.69% -> 0.0627 | P185: =O185+1.69% -> 0.0796 | Q185: =P185+1.69% -> 0.0965 | R185: =Q185+1.69% -> 0.1134 | S185: =R185+1.69% -> 0.1303 | T185: =S185+1.69% -> 0.1472 | ... AE185: =AD185+1.69% -> 0.3331 | AF185: 0.35
A186: Total | B186: 0 | C186: 0 | D186: 0 | E186: 0 | F186: 0 | G186: 0.02 | H186: =G186+2.72% -> 0.0472 | I186: =H186+2.72% -> 0.0744 | J186: =I186+2.72% -> 0.1016 | K186: =J186+2.72% -> 0.1288 | L186: =K186+2.72% -> 0.156 | M186: =L186+2.72% -> 0.1832 | N186: =M186+2.72% -> 0.2104 | O186: =N186+2.72% -> 0.2376 | ... AE186: =AD186+2.72% -> 0.6728 | AF186: 0.7 | AG186: https://transport.ec.europa.eu/transport-modes/air/environment/refueleu-aviation_en
B196: SEC
A197: Technology | B197: toe/MVkm | C197: MVkm/toe | D197: MVkm/PJ
A198: Conventional | B198: 3736.1888 | C198: 0.00026765243 | D198: 6.4031681
A199: Modified Conventional 1 | B199: 3644.6724 | C199: 0.00027437308 | D199: 6.5639493
A200: Modified Conventional 2 | B200: 3383.1392 | C200: 0.00029558346 | D200: 7.0713747
A201: Modified Conventional 3 | B201: 3121.606 | C201: 0.00032034793 | D201: 7.663826
A202: Modified Conventional 4 | B202: 2897.4346 | C202: 0.00034513289 | D202: 8.2567678
A203: Modified Conventional 5 | B203: 2710.6252 | C203: 0.00036891858 | D203: 8.8258033
A204: Modified Conventional 6 | B204: 2523.8158 | C204: 0.00039622543 | D204: 9.4790774
A205: Modified Conventional 7 | B205: 2262.2825 | C205: 0.00044203143 | D205: 10.574915
A206: Hybrid Aircrafts | B206: 2431.5117 | C206: 0.00041126679 | D206: 9.8389184
A207: All Electric Aircrafts | B207: 2146.1737 | C207: 0.00046594551 | D207: 11.147022
A208: Hydrogen Fuel Cell | B208: 2303.611 | C208: 0.00043410107 | D208: 10.385193
A209: Hybrid Fuel Cell & H2 propulsion | B209: 2781.5373 | C209: 0.00035951343 | D209: 8.6007997
A210: Hydrogen Turbine | B210: 4114.3572 | C210: 0.00024305133 | D210: 5.8146252
